Workbook
Name _Ref352134769: 'TABELA DE TARIFAS ANTIGAS'!$A$91
Name _Ref352134769: 'TABELA DE TARIFAS NOVAS'!$A$93

Sheet TABELA DE TARIFAS ANTIGAS
A1: TABELA 1 – TARIFAS DE APLICAÇÃO E BASE ECONÔMICA PARA O GRUPO A.
A2: SUBGRUPO | B2: MODALIDADE | C2: UC | D2: POSTO | E2: TARIFAS DE APLICAÇÃO | J2: BASE ECONÔMICA | N2: Reajuste | O2: Dia | P2: Mês | Q2: Ano
E3: TUSD | G3: TE | J3: TUSD | L3: TE | N3: De | O3: 07 | P3: 08 | Q3: 2025
E4: R$/kW | F4: R$/MWh | G4: BVD – R$/MWh | H4: BAM – R$/MWh | I4: BVM – R$/MWh | J4: R$/kW | K4: R$/MWh | L4: R$/MWh | N4: Até | O4: 06 | P4: 08 | Q4: 2026
B5: AZUL | C5: NA | D5: P
A6: A1 (230 kV ou mais) | D6: FP
B7: AZUL APE | C7: NA | D7: P
D8: FP
A9: A2 (88 a 138kV) | B9: AZUL | C9: NA | D9: P
D10: FP
B11: AZUL APE | C11: NA | D11: P
D12: FP
B13: DISTRIBUIÇÃO | C13: ELFSM | D13: P
D14: FP
D15: NA
B16: GERAÇÃO | C16: UTE LASA | D16: NA
C17: UTE ALCON | D17: NA
C18: UTE SOL | D18: NA
C19: UHE MASCARENHAS - ENERGEST | D19: NA
C20: UHE SUICA | D20: NA
C21: PCH SAO JOAQUIM | D21: NA
C22: PCH SAO SIMAO | D22: NA
C23: PCH FRANCISCO GROSS | D23: NA
C24: PCH SAO PEDRO | D24: NA
C25: UTE LINHARES | D25: NA
C26: UTE ARCEL | D26: NA
C27: NOVO GERADOR | D27: NA
A28: A3 (69kV) | B28: AZUL | C28: NA | D28: P
D29: FP
B30: AZUL APE | C30: NA | D30: P
D31: FP
B32: DISTRIBUIÇÃO | D32: P
D33: FP
D34: NA
B35: GERAÇÃO | C35: NA | D35: NA
A36: A3a (30 a 44kV) | B36: AZUL | C36: NA | D36: P
D37: FP
B38: AZUL APE | C38: NA | D38: P
D39: FP
B40: VERDE | C40: NA | D40: NA
D41: P
D42: FP
B43: VERDE APE | C43: NA | D43: NA
D44: P
D45: FP
B46: CONVENCIONAL | C46: NA | D46: NA
B47: GERAÇÃO | C47: NA | D47: NA
A48: A4 (2,3 a 25kV) | B48: AZUL | C48: NA | D48: P
D49: FP
B50: AZUL APE | C50: NA | D50: P
D51: FP
B52: VERDE | C52: NA | D52: NA
D53: P
D54: FP
B55: VERDE APE | C55: NA | D55: NA
D56: P
D57: FP
B58: CONVENCIONAL | C58: NA | D58: NA
B59: DISTRIBUIÇÃO | C59: COELBA | D59: P
D60: FP
D61: NA
B62: GERAÇÃO | C62: NA | D62: NA
A64: TABELA 2 – TARIFAS DE APLICAÇÃO E BASE ECONÔMICA PARA O GRUPO B.
A65: SUBGRUPO | B65: MODALIDADE | C65: CLASSE | D65: SUBCLASSE | E65: POSTO | F65: TARIFAS DE APLICAÇÃO | K65: TARIFAS BASE ECONÔMICA
F66: TUSD | H66: TE | K66: TUSD | M66: TE
F67: R$/kW | G67: R$/MWh | H67: BVD – R$/MWh | I67: BAM – R$/MWh | J67: BVM – R$/MWh | K67: R$/kW | L67: R$/MWh | M67: R$/MWh
A68: B1 | B68: BRANCA | C68: RESIDENCIAL | D68: RESIDENCIAL | E68: P | F68: 0 | G68: 937.61 | H68: 484.48 | K68: 0 | L68: 918.51 | M68: 492.47
E69: INT | F69: 0 | G69: 651.29 | H69: 305.79 | K69: 0 | L69: 634.94 | M69: 316.46
E70: FP | F70: 0 | G70: 364.96 | H70: 305.79 | K70: 0 | L70: 351.38 | M70: 316.46
B71: CONVENCIONAL | C71: RESIDENCIAL | D71: RESIDENCIAL | E71: NA | F71: 0 | G71: 468.63 | H71: 320.68 | K71: 0 | L71: 454.05 | M71: 331.12
D72: BAIXA RENDA(1) | E72: NA | F72: 0 | G72: 325.43 | H72: 282.45 | K72: 0
D73: DESCONTO SOCIAL | E73: NA | G73: 340.19 | H73: 296.66
A74: B2 | B74: BRANCA | C74: RURAL | D74: NA | E74: P | F74: 0 | G74: 1061.03 | H74: 484.48 | K74: 0 | L74: 1040.73 | M74: 492.47
E75: INT | F75: 0 | G75: 725.34 | H75: 305.79 | K75: 0 | L75: 708.28 | M75: 316.46
E76: FP | F76: 0 | G76: 389.65 | H76: 305.79 | K76: 0 | L76: 375.82 | M76: 316.46
B77: CONVENCIONAL | C77: RURAL | D77: NA | E77: NA | F77: 0 | G77: 468.63 | H77: 320.68 | K77: 0 | L77: 454.05 | M77: 331.12
B78: BRANCA | C78: RURAL | D78: COOPERATIVA DE ELETRIFICAÇÃO RURAL | E78: P | F78: 0 | G78: 1061.03 | H78: 484.48 | K78: 0 | L78: 1040.73 | M78: 492.47
E79: INT | F79: 0 | G79: 725.34 | H79: 305.79 | K79: 0 | L79: 708.28 | M79: 316.46
E80: FP | F80: 0 | G80: 389.65 | H80: 305.79 | K80: 0 | L80: 375.82 | M80: 316.46
B81: CONVENCIONAL | C81: RURAL | D81: COOPERATIVA DE ELETRIFICAÇÃO RURAL | E81: NA | F81: 0 | G81: 468.63 | H81: 320.68 | K81: 0 | L81: 454.05 | M81: 331.12
B82: BRANCA | C82: RURAL | D82: SERVIÇO PÚBLICO DE IRRIGAÇÃO RURAL | E82: P | F82: 0 | G82: 1061.03 | H82: 484.48 | K82: 0 | L82: 1040.73 | M82: 492.47
E83: INT | F83: 0 | G83: 725.34 | H83: 305.79 | K83: 0 | L83: 708.28 | M83: 316.46
E84: FP | F84: 0 | G84: 389.65 | H84: 305.79 | K84: 0 | L84: 375.82 | M84: 316.46
B85: CONVENCIONAL | C85: RURAL | D85: SERVIÇO PÚBLICO DE IRRIGAÇÃO RURAL | E85: NA | F85: 0 | G85: 468.63 | H85: 320.68 | K85: 0 | L85: 454.05 | M85: 331.12
A86: B3 | B86: BRANCA | C86: NA | D86: NA | E86: P | F86: 0 | G86: 1061.03 | H86: 484.48 | K86: 0 | L86: 1040.73 | M86: 492.47
E87: INT | F87: 0 | G87: 725.34 | H87: 305.79 | K87: 0 | L87: 708.28 | M87: 316.46
E88: FP | F88: 0 | G88: 389.65 | H88: 305.79 | K88: 0 | L88: 375.82 | M88: 316.46
B89: CONVENCIONAL | C89: NA | D89: NA | E89: NA | F89: 0 | G89: 468.63 | H89: 320.68 | K89: 0 | L89: 454.05 | M89: 331.12
A90: B4 | B90: CONVENCIONAL | C90: ILUMINAÇÃO PÚBLICA | D90: B4a – REDE DE DISTRIBUIÇÃO | E90: NA | F90: 0 | G90: 257.75 | H90: 176.38 | K90: 0 | L90: 249.73 | M90: 182.12
D91: B4b – BULBO DE LÂMPADA | E91: NA | F91: 0 | G91: 281.18 | H91: 192.41 | K91: 0 | L91: 272.43 | M91: 198.67

Sheet TABELA DE TARIFAS NOVAS
A1: TABELA 1 – TARIFAS DE APLICAÇÃO E BASE ECONÔMICA PARA O GRUPO A.
A2: SUBGRUPO | B2: MODALIDADE | C2: UC | D2: POSTO | E2: TARIFAS DE APLICAÇÃO | J2: BASE ECONÔMICA | N2: Reajuste | O2: Dia | P2: Mês | Q2: Ano
E3: TUSD | G3: TE | J3: TUSD | L3: TE | N3: De | O3: 07 | P3: 08 | Q3: 2026
E4: R$/kW | F4: R$/MWh | G4: BVD – R$/MWh | H4: BAM – R$/MWh | I4: BVM – R$/MWh | J4: R$/kW | K4: R$/MWh | L4: R$/MWh | N4: Até | O4: 31 | P4: 12 | Q4: 9999
B5: AZUL | C5: NA | D5: P
A6: A1 (230 kV ou mais) | D6: FP
B7: AZUL APE | C7: NA | D7: P
D8: FP
A9: A2 (88 a 138kV) | B9: AZUL | C9: NA | D9: P
D10: FP
B11: AZUL APE | C11: NA | D11: P
D12: FP
B13: DISTRIBUIÇÃO | C13: ELFSM | D13: P
D14: FP
D15: NA
B16: GERAÇÃO | C16: UTE LASA | D16: NA
C17: UTE ALCON | D17: NA
C18: UTE SOL | D18: NA
C19: UHE MASCARENHAS - ENERGEST | D19: NA
C20: UHE SUICA | D20: NA
C21: PCH SAO JOAQUIM | D21: NA
C22: PCH SAO SIMAO | D22: NA
C23: PCH FRANCISCO GROSS | D23: NA
C24: PCH SAO PEDRO | D24: NA
C25: UTE LINHARES | D25: NA
C26: UTE POVOACAO 1 | D26: NA
C27: UTE ARCEL | D27: NA
C28: UTE BIANCOGRES | D28: NA
C29: NOVO GERADOR | D29: NA
A30: A3 (69kV) | B30: AZUL | C30: NA | D30: P
D31: FP
B32: AZUL APE | C32: NA | D32: P
D33: FP
B34: DISTRIBUIÇÃO | D34: P
D35: FP
D36: NA
B37: GERAÇÃO | C37: NA | D37: NA
A38: A3a (30 a 44kV) | B38: AZUL | C38: NA | D38: P
D39: FP
B40: AZUL APE | C40: NA | D40: P
D41: FP
B42: VERDE | C42: NA | D42: NA
D43: P
D44: FP
B45: VERDE APE | C45: NA | D45: NA
D46: P
D47: FP
B48: CONVENCIONAL | C48: NA | D48: NA
B49: GERAÇÃO | C49: NA | D49: NA
A50: A4 (2,3 a 25kV) | B50: AZUL | C50: NA | D50: P
D51: FP
B52: AZUL APE | C52: NA | D52: P
D53: FP
B54: VERDE | C54: NA | D54: NA
D55: P
D56: FP
B57: VERDE APE | C57: NA | D57: NA
D58: P
D59: FP
B60: CONVENCIONAL | C60: NA | D60: NA
B61: DISTRIBUIÇÃO | C61: COELBA | D61: P
D62: FP
D63: NA
B64: GERAÇÃO | C64: NA | D64: NA
A66: TABELA 2 – TARIFAS DE APLICAÇÃO E BASE ECONÔMICA PARA O GRUPO B.
A67: SUBGRUPO | B67: MODALIDADE | C67: CLASSE | D67: SUBCLASSE | E67: POSTO | F67: TARIFAS DE APLICAÇÃO | K67: TARIFAS BASE ECONÔMICA
F68: TUSD | H68: TE | K68: TUSD | M68: TE
F69: R$/kW | G69: R$/MWh | H69: BVD – R$/MWh | I69: BAM – R$/MWh | J69: BVM – R$/MWh | K69: R$/kW | L69: R$/MWh | M69: R$/MWh
A70: B1 | B70: BRANCA | C70: RESIDENCIAL | D70: RESIDENCIAL | E70: P | F70: 0 | G70: 999.02 | H70: 516.91 | K70: 0 | L70: 956.95 | M70: 478.38
E71: INT | F71: 0 | G71: 698.21 | H71: 321.07 | K71: 0 | L71: 662.46 | M71: 299.92
E72: FP | F72: 0 | G72: 397.41 | H72: 321.07 | K72: 0 | L72: 367.97 | M72: 299.92
B73: CONVENCIONAL | C73: RESIDENCIAL | D73: RESIDENCIAL | E73: NA | F73: 0 | G73: 506.32 | H73: 337.39 | K73: 0 | L73: 474.59 | M73: 314.79
D74: BAIXA RENDA(1) | E74: NA | F74: 0 | G74: 348.95 | H74: 325.32 | K74: 0 | L74: 334.57 | M74: 303.57
D75: DESCONTO SOCIAL | E75: NA | F75: 0 | G75: 356.42 | H75: 337.59 | L75: 343.39 | M75: 314.79
A76: B2 | B76: BRANCA | C76: RURAL | D76: NA | E76: P | F76: 0 | G76: 1128.67 | H76: 516.91 | K76: 0 | L76: 1083.88 | M76: 478.38
E77: INT | F77: 0 | G77: 776.01 | H77: 321.07 | K77: 0 | L77: 738.62 | M77: 299.92
E78: FP | F78: 0 | G78: 423.34 | H78: 321.07 | K78: 0 | L78: 393.35 | M78: 299.92
B79: CONVENCIONAL | C79: RURAL | D79: NA | E79: NA | F79: 0 | G79: 506.32 | H79: 337.39 | K79: 0 | L79: 474.59 | M79: 314.79
B80: BRANCA | C80: RURAL | D80: COOPERATIVA DE ELETRIFICAÇÃO RURAL | E80: P | F80: 0 | G80: 1128.67 | H80: 516.91 | K80: 0 | L80: 1083.88 | M80: 478.38
E81: INT | F81: 0 | G81: 776.01 | H81: 321.07 | K81: 0 | L81: 738.62 | M81: 299.92
E82: FP | F82: 0 | G82: 423.34 | H82: 321.07 | K82: 0 | L82: 393.35 | M82: 299.92
B83: CONVENCIONAL | C83: RURAL | D83: COOPERATIVA DE ELETRIFICAÇÃO RURAL | E83: NA | F83: 0 | G83: 506.32 | H83: 337.39 | K83: 0 | L83: 474.59 | M83: 314.79
B84: BRANCA | C84: RURAL | D84: SERVIÇO PÚBLICO DE IRRIGAÇÃO RURAL | E84: P | F84: 0 | G84: 1128.67 | H84: 516.91 | K84: 0 | L84: 1083.88 | M84: 478.38
E85: INT | F85: 0 | G85: 776.01 | H85: 321.07 | K85: 0 | L85: 738.62 | M85: 299.92
E86: FP | F86: 0 | G86: 423.34 | H86: 321.07 | K86: 0 | L86: 393.35 | M86: 299.92
B87: CONVENCIONAL | C87: RURAL | D87: SERVIÇO PÚBLICO DE IRRIGAÇÃO RURAL | E87: NA | F87: 0 | G87: 506.32 | H87: 337.39 | K87: 0 | L87: 474.59 | M87: 314.79
A88: B3 | B88: BRANCA | C88: NA | D88: NA | E88: P | F88: 0 | G88: 1128.67 | H88: 516.91 | K88: 0 | L88: 1083.88 | M88: 478.38
E89: INT | F89: 0 | G89: 776.01 | H89: 321.07 | K89: 0 | L89: 738.62 | M89: 299.92
E90: FP | F90: 0 | G90: 423.34 | H90: 321.07 | K90: 0 | L90: 393.35 | M90: 299.92
B91: CONVENCIONAL | C91: NA | D91: NA | E91: NA | F91: 0 | G91: 506.32 | H91: 337.39 | K91: 0 | L91: 474.59 | M91: 314.79
A92: B4 | B92: CONVENCIONAL | C92: ILUMINAÇÃO PÚBLICA | D92: B4a – REDE DE DISTRIBUIÇÃO | E92: NA | F92: 0 | G92: 278.48 | H92: 185.56 | K92: 0 | L92: 261.03 | M92: 173.13
D93: B4b – BULBO DE LÂMPADA | E93: NA | F93: 0 | G93: 303.79 | H93: 202.43 | K93: 0 | L93: 284.76 | M93: 188.87

Sheet B1 (Res) Branca OK
B2: B1 Res | E2: Vigência das Tarifas: | F2: 46241 | H2: TARIFA BRANCA | M2: Bandeira | N2: R$/kWh | Q2: TUSD FIO B
M3: VERDE | N3: 0
B4: TARIFA | C4: TARIFA ANTIGA - REH 3370/2024 | F4: TARIFA NOVA - REH xxxx/2025 | I4: Tarifas Proporcionalizadas | M4: BAM | N4: 0.01885 | Q4: TARIFA | R4: =C4 -> TARIFA ANTIGA - REH 3370/2024 | U4: =F4 -> TARIFA NOVA - REH xxxx/2025 | X4: Tarifas Proporcionalizadas
C5: Tusd | D5: TE | E5: TUSD + TE | F5: Tusd | G5: TE | H5: TUSD + TE | I5: Tusd | J5: TE | K5: TUSD + TE | M5: BVM1 | N5: 0.04463 | R5: Tusd (R$/kWh) | U5: Tusd (R$/kWh) | X5: Tusd (R$/kWh)
B6: B1 Ponta | C6: ='TABELA DE TARIFAS ANTIGAS'!G68/1000 -> 0.93761 | D6: ='TABELA DE TARIFAS ANTIGAS'!H68/1000 -> 0.48448 | E6: =C6+D6 -> 1.42209 | F6: ='TABELA DE TARIFAS NOVAS'!G70/1000 -> 0.99902 | G6: ='TABELA DE TARIFAS NOVAS'!H70/1000 -> 0.51691 | H6: =F6+G6 -> 1.51593 | I6: =((C6*$C$15)+(F6*$D$15))/($D$15+$C$15) -> 0.966268 | J6: =((D6*$C$15)+(G6*$D$15))/($D$15+$C$15) -> 0.499614 | K6: =I6+J6 -> 1.465882 | M6: BVM2 | N6: 0.07877 | Q6: =B6 -> B1 Ponta | R6: ='FIO B'!H7/1000 -> 0.59110909 | U6: ='FIO B'!K7/1000 -> 0.60653962 | X6: =((R6*$C$15)+(U6*$D$15))/($D$15+$C$15) -> 0.59831
B7: B1 Fora Ponta | C7: ='TABELA DE TARIFAS ANTIGAS'!G70/1000 -> 0.36496 | D7: ='TABELA DE TARIFAS ANTIGAS'!H70/1000 -> 0.30579 | E7: =C7+D7 -> 0.67075 | F7: ='TABELA DE TARIFAS NOVAS'!G72/1000 -> 0.39741 | G7: ='TABELA DE TARIFAS NOVAS'!H72/1000 -> 0.32107 | H7: =F7+G7 -> 0.71848 | I7: =((C7*$C$15)+(F7*$D$15))/($D$15+$C$15) -> 0.38010333 | J7: =((D7*$C$15)+(G7*$D$15))/($D$15+$C$15) -> 0.31292067 | K7: =I7+J7 -> 0.693024 | M7: Escassez Hídrica | N7: 0.142 | Q7: =B7 -> B1 Fora Ponta | R7: ='FIO B'!H9/1000 -> 0.1182218 | U7: ='FIO B'!K9/1000 -> 0.1213079 | X7: =((R7*$C$15)+(U7*$D$15))/($D$15+$C$15) -> 0.11966198
B8: B1 Interm. | C8: ='TABELA DE TARIFAS ANTIGAS'!G69/1000 -> 0.65129 | D8: ='TABELA DE TARIFAS ANTIGAS'!H69/1000 -> 0.30579 | E8: =C8+D8 -> 0.95708 | F8: ='TABELA DE TARIFAS NOVAS'!G71/1000 -> 0.69821 | G8: ='TABELA DE TARIFAS NOVAS'!H71/1000 -> 0.32107 | H8: =F8+G8 -> 1.01928 | I8: =((C8*$C$15)+(F8*$D$15))/($D$15+$C$15) -> 0.673186 | J8: =((D8*$C$15)+(G8*$D$15))/($D$15+$C$15) -> 0.31292067 | K8: =I8+J8 -> 0.98610667 | Q8: =B8 -> B1 Interm. | R8: ='FIO B'!H8/1000 -> 0.3546655 | U8: ='FIO B'!K8/1000 -> 0.36392381 | X8: =((R8*$C$15)+(U8*$D$15))/($D$15+$C$15) -> 0.35898604
B9: CDE Escassez Hídrica | C9: 0.00018774721 | D9: -0.0044031307 | E9: 0.0036054084 | F9: =T13 -> 0.00018418923 | G9: =U13 -> -0.00053182975 | H9: =F9+G9 -> -0.00034764052 | I9: =((C9*$C$15)+(F9*$D$15))/($D$15+$C$15) -> 0.00018608682 | J9: =((D9*$C$15)+(G9*$D$15))/($D$15+$C$15) -> -0.0025965236 | K9: =I9+J9 -> -0.0024104368
P10: CUSTO | R10: Part. TUSD (%) | S10: Part. TE (%) | T10: Tusd (R$/kWh) | U10: TE (R$/kWh)
H11: Fatura | L11: Vigência das Tarifas (troca Bandeira): | M11: =EOMONTH(B15,0)+1 -> 46235 | P11: CDE CONTAS
B12: INSTALAÇÃO | C12: 99019 | H12: =E15 -> 46254 | K12: Altere a bandeira na célula abaixo | P12: CDE COVID | U12: 0
K13: BAM | L13: BAM | P13: CDE ESCASSEZ HÍDRICA | T13: =0.184189231569235/1000 -> 0.00018418923 | U13: =-0.531829748712515/1000 -> -0.00053182975
B14: Leitura Anterior | C14: Nº de dias tarifa Anterior | D14: Nº de dias tarifa Nova | E14: Leitura Atual | J14: Leitura Anterior | K14: Nº de dias tarifa Anterior | L14: Nº de dias tarifa Nova | M14: Leitura Atual
B15: 46224 | C15: =IF((F2-B15-1)<0,0,(F2-B15-1)) -> 16 | D15: =E15-F2+1 -> 14 | E15: 46254 | J15: =B15 -> 46224 | K15: =IF((M11-J15-1)<0,0,(M11-J15-1)) -> 10 | L15: =M15-M11+1 -> 20 | M15: =E15 -> 46254 | O15: Documento impressão: | Q15: 1025310387
B17: Descrição | C17: Unidade | D17: Quantidade | E17: Preço Unit (R$) com tributos | F17: Valor Total (R$) | G17: PIS/COFINS (R$) | H17: Base de Cálculo ICMS (R$) | I17: Alíquota ICMS (%) | J17: ICMS (R$) | K17: Preço Unit (R$) | L17: Tributos | M17: Base de Cálc (R$) | N17: Alíquota (%) | O17: Valor (R$)
B19: TUSD - Consumo Ponta | C19: kWh | D19: 15 | E19: =IFERROR((ROUND(D19*K19,2)+ROUND(G19,2)+ROUND(J19,2))/ROUND(D19,4),0) -> 1.24 | F19: =ROUND(D19*E19,2) -> 18.6 | G19: =((D19*K19)/(1-$N$19-$N$20))*($N$19+$N$20) -> 0.95308647 | H19: =ROUND((D19*K19)/(1-$N$19-$N$20)/(1-$I$19),8) -> 18.610972 | I19: 0.17 | J19: =H19*$I$19 -> 3.1638652 | K19: =IF(AND($B$15<$F$2,$E$15<$F$2),C6,IF($B$15<$F$2,I6,F6)) -> 0.966268 | L19: PIS | M19: =D61 -> 173.59054 | N19: 0.011 | O19: =ROUND(M19*N19,2) -> 1.91
B20: TUSD - Consumo Intermediário | C20: kWh | D20: 11 | E20: =IFERROR((ROUND(D20*K20,2)+ROUND(G20,2)+ROUND(J20,2))/ROUND(D20,4),0) -> 0.86545455 | F20: =ROUND(D20*E20,2) -> 9.52 | G20: =((D20*K20)/(1-$N$19-$N$20))*($N$19+$N$20) -> 0.48693524 | H20: =ROUND((D20*K20)/(1-$N$19-$N$20)/(1-$I$19),8) -> 9.5084111 | I20: =I19 -> 0.17 | J20: =H20*$I$19 -> 1.6164299 | K20: =IF(AND($B$15<$F$2,$E$15<$F$2),C8,IF($B$15<$F$2,I8,F8)) -> 0.673186 | L20: COFINS | M20: =M19 -> 173.59054 | N20: 0.0507 | O20: =ROUND(M20*N20,2) -> 8.8
B21: TUSD - Consumo Fora Ponta | C21: kWh | D21: 182 | E21: =IFERROR((ROUND(D21*K21,2)+ROUND(G21,2)+ROUND(J21,2))/ROUND(D21,4),0) -> 0.48807692 | F21: =ROUND(D21*E21,2) -> 88.83 | G21: =((D21*K21)/(1-$N$19-$N$20))*($N$19+$N$20) -> 4.549006 | H21: =ROUND((D21*K21)/(1-$N$19-$N$20)/(1-$I$19),8) -> 88.82869 | I21: =I19 -> 0.17 | J21: =H21*$I$19 -> 15.100877 | K21: =IF(AND($B$15<$F$2,$E$15<$F$2),C7,IF($B$15<$F$2,I7,F7)) -> 0.38010333
B22: TE - Consumo Ponta | C22: kWh | D22: =D19 -> 15 | E22: =IFERROR((ROUND(D22*K22,2)+ROUND(G22,2)+ROUND(J22,2))/ROUND(D22,4),0) -> 0.64133333 | F22: =ROUND(D22*E22,2) -> 9.62 | G22: =((D22*K22)/(1-$N$19-$N$20))*($N$19+$N$20) -> 0.49279842 | H22: =(D22*K22)/(1-$N$19-$N$20)/(1-$I$19) -> 9.6229017 | J22: =H22*$I$19 -> 1.6358933 | K22: =IF(AND($B$15<$F$2,$E$15<$F$2),D6,IF($B$15<$F$2,J6,G6)) -> 0.499614 | R22: TUSD Fio B | S22: Receita Fio B
B23: TE - Consumo Intermediário | C23: kWh | D23: =D20 -> 11 | E23: =IFERROR((ROUND(D23*K23,2)+ROUND(G23,2)+ROUND(J23,2))/ROUND(D23,4),0) -> 0.40181818 | F23: =ROUND(D23*E23,2) -> 4.42 | G23: =((D23*K23)/(1-$N$19-$N$20))*($N$19+$N$20) -> 0.22634473 | H23: =(D23*K23)/(1-$N$19-$N$20)/(1-$I$19) -> 4.4198459 | J23: =H23*$I$19 -> 0.7513738 | K23: =IF(AND($B$15<$F$2,$E$15<$F$2),D8,IF($B$15<$F$2,J8,G8)) -> 0.31292067 | R23: =IF(AND($B$15<$F$2,$E$15<$F$2),R6,IF($B$15<$F$2,X6,U6)) -> 0.59831 | S23: =D47*R23 -> 8.9746501
B24: TE - Consumo Fora Ponta | C24: kWh | D24: =D21 -> 182 | E24: =IFERROR((ROUND(D24*K24,2)+ROUND(G24,2)+ROUND(J24,2))/ROUND(D24,4),0) -> 0.40175824 | F24: =ROUND(D24*E24,2) -> 73.12 | G24: =((D24*K24)/(1-$N$19-$N$20))*($N$19+$N$20) -> 3.7449764 | H24: =(D24*K24)/(1-$N$19-$N$20)/(1-$I$19) -> 73.128359 | J24: =H24*$I$19 -> 12.431821 | K24: =IF(AND($B$15<$F$2,$E$15<$F$2),D7,IF($B$15<$F$2,J7,G7)) -> 0.31292067 | R24: =IF(AND($B$15<$F$2,$E$15<$F$2),R7,IF($B$15<$F$2,X7,U7)) -> 0.11966198 | S24: =D48*R24 -> 21.77848
B25: Adicional BAM | C25: kWh | D25: =IF($K$13=M4,(($D$19+$D$20+$D$21)*($K$15)/($K$15+$L$15)),0)+IF($L$13=M4,(($D$19+$D$20+$D$21)*($L$15)/($K$15+$L$15)),0) -> 208 | E25: =IFERROR( (ROUND(D25*K25,2)+ROUND(G25,2)+ROUND(J25,2))/ROUND(D25,4), N4) -> 0.024230769 | F25: =ROUND(D25*E25,2) -> 5.04 | G25: =((D25*K25)/(1-$N$19-$N$20))*($N$19+$N$20) -> 0.25782091 | H25: =(D25*K25)/(1-$N$19-$N$20)/(1-$I$19) -> 5.034483 | J25: =H25*$I$19 -> 0.85586211 | K25: =N4 -> 0.01885 | R25: =IF(AND($B$15<$F$2,$E$15<$F$2),R8,IF($B$15<$F$2,X8,U8)) -> 0.35898604 | S25: =D49*R25 -> 3.9488465
B26: Adicional BVM 1 | C26: kWh | D26: =IF($K$13=M5,(($D$19+$D$20+$D$21)*($K$15)/($K$15+$L$15)),0)+IF($L$13=M5,(($D$19+$D$20+$D$21)*($L$15)/($K$15+$L$15)),0) -> 0 | E26: =K26/(1-$N$19-$N$20)/(1-$I$19) -> 0.057306921 | F26: =ROUND(D26*E26,2) -> 0 | G26: =((D26*K26)/(1-$N$19-$N$20))*($N$19+$N$20) -> 0 | H26: =(D26*K26)/(1-$N$19-$N$20)/(1-$I$19) -> 0 | J26: =H26*$I$19 -> 0 | K26: =N5 -> 0.04463 | S26: =SUM(S23:S25) -> 34.701977
B27: Adicional BVM 2 | C27: kWh | D27: =IF($K$13=M6,(($D$19+$D$20+$D$21)*($K$15)/($K$15+$L$15)),0)+IF($L$13=M6,(($D$19+$D$20+$D$21)*($L$15)/($K$15+$L$15)),0) -> 0 | E27: =K27/(1-$N$19-$N$20)/(1-$I$19) -> 0.10114421 | F27: =ROUND(D27*E27,2) -> 0 | G27: =((D27*K27)/(1-$N$19-$N$20))*($N$19+$N$20) -> 0 | H27: =(D27*K27)/(1-$N$19-$N$20)/(1-$I$19) -> 0 | J27: =H27*$I$19 -> 0 | K27: =N6 -> 0.07877
B28: Adicional Escassez | C28: kWh | D28: =IF($K$13=M7,(($D$19+$D$20+$D$21)*($K$15)/($K$15+$L$15)),0)+IF($L$13=M7,(($D$19+$D$20+$D$21)*($L$15)/($K$15+$L$15)),0) -> 0 | E28: =K28/(1-$N$19-$N$20)/(1-$I$19) -> 0.18233437 | F28: =ROUND(D28*E28,2) -> 0 | G28: =((D28*K28)/(1-$N$19-$N$20))*($N$19+$N$20) -> 0 | H28: =(D28*K28)/(1-$N$19-$N$20)/(1-$I$19) -> 0 | J28: =H28*$I$19 -> 0 | K28: =N7 -> 0.142
B29: Multas | F29: 4.54
B30: Juros | F30: 0.49
B31: Bônus/Descontos | F31: 3.38
B32: Doações | F32: 0.31
B33: CIP | F33: 45.66
B36: TOTAL | F36: =SUM(F19:F35) -> 263.53 | G36: =SUM(G19:G35) -> 10.710968 | H36: =SUM(H19:H35) -> 209.15366 | J36: =SUM(J19:J35) -> 35.556123
B38: Informativo Escassez | C38: =D19+D20+D21 -> 208 | D38: =IF(AND($B$15<$F$2,$E$15<$F$2),C9,IF($B$15<$F$2,I9,F9)) -> 0.00018608682 | E38: =IF(AND($B$15<$F$2,$E$15<$F$2),D9,IF($B$15<$F$2,J9,G9)) -> -0.0025965236 | F38: =C38*(D38+E38) -> -0.50137085
B43: Fatura B1 Residencial TB
D44: Qtde | E44: TUSD | F44: TE | G44: TUSD + TE | H44: R$ | J44: Documento impressão: | L44: =Q15 -> 1025310387
B45: Fornecimento de Energia Elétrica | H45: =SUM(H47:H55)+SUM(H61:H63) -> 209.14522
B47: Consumo Ponta | D47: =D19 -> 15 | E47: =IF(AND($B$15<$F$2,$E$15<$F$2),C6,IF($B$15<$F$2,I6,F6)) -> 0.966268 | F47: =IF(AND($B$15<$F$2,$E$15<$F$2),D6,IF($B$15<$F$2,J6,G6)) -> 0.499614 | G47: =E47+F47 -> 1.465882 | H47: =ROUND((D47*E47),2)+ROUND((D47*F47),2) -> 21.98 | U47: =D47*E47 -> 14.49402
B48: Consumo Fora Ponta | D48: =D21 -> 182 | E48: =IF(AND($B$15<$F$2,$E$15<$F$2),C7,IF($B$15<$F$2,I7,F7)) -> 0.38010333 | F48: =IF(AND($B$15<$F$2,$E$15<$F$2),D7,IF($B$15<$F$2,J7,G7)) -> 0.31292067 | G48: =E48+F48 -> 0.693024 | H48: =ROUND((D48*E48),2)+ROUND((D48*F48),2) -> 126.13 | U48: =D48*E48 -> 69.178807
B49: Consumo Intemediário | D49: =D20 -> 11 | E49: =IF(AND($B$15<$F$2,$E$15<$F$2),C8,IF($B$15<$F$2,I8,F8)) -> 0.673186 | F49: =IF(AND($B$15<$F$2,$E$15<$F$2),D8,IF($B$15<$F$2,J8,G8)) -> 0.31292067 | G49: =E49+F49 -> 0.98610667 | H49: =ROUND((D49*E49),2)+ROUND((D49*F49),2) -> 10.85 | U49: =D49*E49 -> 7.405046
U50: =SUM(U47:U49) -> 91.077873
B52: Adicional BAM | D52: =IF($K$13=M4,((D47+D48+D49)*(K15)/(K15+L15)),0)+IF($L$13=M4,((D47+D48+D49)*(L15)/(K15+L15)),0) -> 208 | F52: =N4 -> 0.01885 | H52: =ROUND(D52*(E52+F52),2) -> 3.92
B53: Adicional BVM 1 | D53: =IF($K$13=M5,((D47+D48+D49)*(K15)/(K15+L15)),0)+IF($L$13=M5,((D47+D48+D49)*(L15)/(K15+L15)),0) -> 0 | F53: =N5 -> 0.04463 | H53: =ROUND(D53*(E53+F53),2) -> 0
B54: Adicional BVM 2 | D54: =IF($K$13=M6,((D47+D48+D49)*(K15)/(K15+L15)),0)+IF($L$13=M6,((D47+D48+D49)*(L15)/(K15+L15)),0) -> 0 | F54: =N6 -> 0.07877 | H54: =ROUND(D54*(E54+F54),2) -> 0
B55: Adicional Escassez Hídrica | D55: =IF($K$13=M7,((D47+D48+D49)*(K15)/(K15+L15)),0)+IF($L$13=M7,((D47+D48+D49)*(L15)/(K15+L15)),0) -> 0 | F55: =N7 -> 0.142 | H55: =ROUND(D55*(E55+F55),2) -> 0
D60: Base de Cálculo
B61: PIS | D61: =(SUM(H47:H55)/(1-E61-E62)) -> 173.59054 | E61: =N19 -> 0.011 | H61: =D61*E61 -> 1.9094959
B62: COFINS | D62: =D61 -> 173.59054 | E62: =N20 -> 0.0507 | H62: =D62*E62 -> 8.8010402
B63: ICMS | D63: =D61/(1-E63) -> 209.14522 | E63: 0.17 | H63: =D63*E63 -> 35.554688
B65: Informativo Escassez Hídrica | D65: =SUM(D47:D49) -> 208 | E65: =IF(AND($B$15<$F$2,$E$15<$F$2),C9,IF($B$15<$F$2,I9,F9)) -> 0.00018608682 | F65: =IF(AND($B$15<$F$2,$E$15<$F$2),D9,IF($B$15<$F$2,J9,G9)) -> -0.0025965236 | H65: =D65*(E65+F65) -> -0.50137085
B67: Participação
C68: R$
B69: Energia | C69: =(SUM(H47:H55)*IF($B$15<$F$2,D107,D79)) -> 72.562224
B70: Distribuição | C70: =(SUM(H47:H55)*IF($B$15<$F$2,F107,F79)) -> 42.868719
B71: Transmissão | C71: =(SUM(H47:H55)*IF($B$15<$F$2,E107,E79)) -> 13.674282
B72: Encargos Setoriais | C72: =(SUM(H47:H55)*IF($B$15<$F$2,G107,G79)) -> 33.775619
B73: Impostos / Tributos | C73: =H61+H62+H63 -> 46.265224
B74: Total | C74: =SUM(C69:C73) -> 209.14607
B76: 2024 | D76: Energia | E76: Transmissão | F76: Distribuição | G76: Setoriais
B77: Grupo B | D77: % | E77: % | F77: % | G77: %
B79: B1 - Residencial | D79: 0.45246417 | E79: 0.073959411 | F79: 0.27500913 | G79: 0.19856729
B80: B1 - Residencial Baixa Renda | D80: 0.53149576 | E80: 0.086877849 | F80: 0.32304478 | G80: 0.058581612
B81: B2 - Rural | D81: 0.45246417 | E81: 0.073959411 | F81: 0.27500913 | G81: 0.19856729
B82: B2 - Cooperativa Eletrificação Rural | D82: 0.45246417 | E82: 0.073959411 | F82: 0.27500913 | G82: 0.19856729
B83: B2 - Serviço de Irrigação | D83: 0.45246417 | E83: 0.073959411 | F83: 0.27500913 | G83: 0.19856729
B84: B3 - Demais Classes | D84: 0.45246417 | E84: 0.073959411 | F84: 0.27500913 | G84: 0.19856729
B85: B4 - Iluminação Pública | D85: 0.45246417 | E85: 0.073959411 | F85: 0.27500913 | G85: 0.19856729
B86: B4a - Rede de Distribuição | D86: 0.45246417 | E86: 0.073959411 | F86: 0.27500913 | G86: 0.19856729
B87: B4b - Bulbo de Lâmpada | D87: 0.45246417 | E87: 0.073959411 | F87: 0.27500913 | G87: 0.19856729
B90: 2023 | D90: Energia | E90: Transmissão | F90: Distribuição | G90: Setoriais
B91: Grupo B | D91: % | E91: % | F91: % | G91: %
B93: B1 - Residencial | D93: 0.43939696 | E93: 0.092697586 | F93: 0.25285208 | G93: 0.21506308
B94: B1 - Residencial Baixa Renda | D94: 0.5269162 | E94: 0.11116112 | F94: 0.30321524 | G94: 0.058707433
B95: B2 - Rural | D95: 0.439393 | E95: 0.092696751 | F95: 0.2528498 | G95: 0.21506045
B96: B2 - Cooperativa Eletrificação Rural | D96: 0.439393 | E96: 0.092696751 | F96: 0.2528498 | G96: 0.21506045
B97: B2 - Serviço de Irrigação | D97: 0.439393 | E97: 0.092696751 | F97: 0.2528498 | G97: 0.21506045
B98: B3 - Demais Classes | D98: 0.439393 | E98: 0.092696751 | F98: 0.2528498 | G98: 0.21506045
B99: B4 - Iluminação Pública | D99: 0 | E99: 0 | F99: 0 | G99: 0
B100: B4a - Rede de Distribuição | D100: 0.43938946 | E100: 0.092697337 | F100: 0.2528514 | G100: 0.21506181
B101: B4b - Bulbo de Lâmpada | D101: 0.43938946 | E101: 0.092697337 | F101: 0.2528514 | G101: 0.21506181
B103: proporcional
D104: Energia | E104: Transmissão | F104: Distribuição | G104: Setoriais
B105: Grupo B | D105: % | E105: % | F105: % | G105: %
B107: B1 - Residencial | D107: =((D93*$C$15)+(D79*$D$15))/($C$15+$D$15) -> 0.44549499 | E107: =((E93*$C$15)+(E79*$D$15))/($C$15+$D$15) -> 0.083953104 | F107: =((F93*$C$15)+(F79*$D$15))/($C$15+$D$15) -> 0.26319204 | G107: =((G93*$C$15)+(G79*$D$15))/($C$15+$D$15) -> 0.20736505
B108: B1 - Residencial Baixa Renda | D108: =((D94*$C$15)+(D80*$D$15))/($C$15+$D$15) -> 0.52905333 | E108: =((E94*$C$15)+(E80*$D$15))/($C$15+$D$15) -> 0.099828928 | F108: =((F94*$C$15)+(F80*$D$15))/($C$15+$D$15) -> 0.31246903 | G108: =((G94*$C$15)+(G80*$D$15))/($C$15+$D$15) -> 0.058648717
B109: B2 - Rural | D109: =((D95*$C$15)+(D81*$D$15))/($C$15+$D$15) -> 0.44549288 | E109: =((E95*$C$15)+(E81*$D$15))/($C$15+$D$15) -> 0.083952659 | F109: =((F95*$C$15)+(F81*$D$15))/($C$15+$D$15) -> 0.26319082 | G109: =((G95*$C$15)+(G81*$D$15))/($C$15+$D$15) -> 0.20736364
B110: B2 - Cooperativa Eletrificação Rural | D110: =((D96*$C$15)+(D82*$D$15))/($C$15+$D$15) -> 0.44549288 | E110: =((E96*$C$15)+(E82*$D$15))/($C$15+$D$15) -> 0.083952659 | F110: =((F96*$C$15)+(F82*$D$15))/($C$15+$D$15) -> 0.26319082 | G110: =((G96*$C$15)+(G82*$D$15))/($C$15+$D$15) -> 0.20736364
B111: B2 - Serviço de Irrigação | D111: =((D97*$C$15)+(D83*$D$15))/($C$15+$D$15) -> 0.44549288 | E111: =((E97*$C$15)+(E83*$D$15))/($C$15+$D$15) -> 0.083952659 | F111: =((F97*$C$15)+(F83*$D$15))/($C$15+$D$15) -> 0.26319082 | G111: =((G97*$C$15)+(G83*$D$15))/($C$15+$D$15) -> 0.20736364
B112: B3 - Demais Classes | D112: =((D98*$C$15)+(D84*$D$15))/($C$15+$D$15) -> 0.44549288 | E112: =((E98*$C$15)+(E84*$D$15))/($C$15+$D$15) -> 0.083952659 | F112: =((F98*$C$15)+(F84*$D$15))/($C$15+$D$15) -> 0.26319082 | G112: =((G98*$C$15)+(G84*$D$15))/($C$15+$D$15) -> 0.20736364
B113: B4 - Iluminação Pública | D113: =((D99*$C$15)+(D85*$D$15))/($C$15+$D$15) -> 0.21114994 | E113: =((E99*$C$15)+(E85*$D$15))/($C$15+$D$15) -> 0.034514392 | F113: =((F99*$C$15)+(F85*$D$15))/($C$15+$D$15) -> 0.1283376 | G113: =((G99*$C$15)+(G85*$D$15))/($C$15+$D$15) -> 0.092664735
B114: B4a - Rede de Distribuição | D114: =((D100*$C$15)+(D86*$D$15))/($C$15+$D$15) -> 0.44549099 | E114: =((E100*$C$15)+(E86*$D$15))/($C$15+$D$15) -> 0.083952971 | F114: =((F100*$C$15)+(F86*$D$15))/($C$15+$D$15) -> 0.26319168 | G114: =((G100*$C$15)+(G86*$D$15))/($C$15+$D$15) -> 0.20736437
B115: B4b - Bulbo de Lâmpada | D115: =((D101*$C$15)+(D87*$D$15))/($C$15+$D$15) -> 0.44549099 | E115: =((E101*$C$15)+(E87*$D$15))/($C$15+$D$15) -> 0.083952971 | F115: =((F101*$C$15)+(F87*$D$15))/($C$15+$D$15) -> 0.26319168 | G115: =((G101*$C$15)+(G87*$D$15))/($C$15+$D$15) -> 0.20736437

Sheet B2 (Rural) Branca OK
B2: B2 Rural | E2: Vigência das Tarifas: | F2: ='B1 (Res) Branca OK'!F2 -> 46241 | H2: TARIFA BRANCA | M2: Bandeira | N2: R$/kWh | Q2: TUSD FIO B
M3: VERDE | N3: ='B1 (Res) Branca OK'!N3 -> 0
B4: TARIFA | C4: ='B1 (Res) Branca OK'!C4 -> TARIFA ANTIGA - REH 3370/2024 | F4: ='B1 (Res) Branca OK'!F4 -> TARIFA NOVA - REH xxxx/2025 | I4: Tarifas Proporcionalizadas | M4: BAM | N4: ='B1 (Res) Branca OK'!N4 -> 0.01885 | Q4: TARIFA | R4: =C4 -> TARIFA ANTIGA - REH 3370/2024 | U4: =F4 -> TARIFA NOVA - REH xxxx/2025
C5: Tusd | D5: TE | E5: TUSD + TE | F5: Tusd | G5: TE | H5: TUSD + TE | I5: Tusd | J5: TE | K5: TUSD + TE | M5: BVM1 | N5: ='B1 (Res) Branca OK'!N5 -> 0.04463 | R5: Tusd (R$/kWh) | U5: Tusd (R$/kWh) | X5: Tusd (R$/kWh)
B6: B2 Ponta | C6: ='TABELA DE TARIFAS ANTIGAS'!G74/1000 -> 1.06103 | D6: ='TABELA DE TARIFAS ANTIGAS'!H74/1000 -> 0.48448 | E6: =C6+D6 -> 1.54551 | F6: ='TABELA DE TARIFAS NOVAS'!G76/1000 -> 1.12867 | G6: ='TABELA DE TARIFAS NOVAS'!H76/1000 -> 0.51691 | H6: =F6+G6 -> 1.64558 | I6: =((C6*$C$15)+(F6*$D$15))/($D$15+$C$15) -> 1.1061233 | J6: =((D6*$C$15)+(G6*$D$15))/($D$15+$C$15) -> 0.5061 | K6: =I6+J6 -> 1.6122233 | M6: BVM2 | N6: ='B1 (Res) Branca OK'!N6 -> 0.07877 | Q6: =B6 -> B2 Ponta | R6: ='FIO B'!H16/1000 -> 0.69302445 | U6: ='FIO B'!K16/1000 -> 0.71111541 | X6: =((R6*$C$15)+(U6*$D$15))/($D$15+$C$15) -> 0.70508509
B7: B2 Fora Ponta | C7: ='TABELA DE TARIFAS ANTIGAS'!G76/1000 -> 0.38965 | D7: ='TABELA DE TARIFAS ANTIGAS'!H76/1000 -> 0.30579 | E7: =C7+D7 -> 0.69544 | F7: ='TABELA DE TARIFAS NOVAS'!G78/1000 -> 0.42334 | G7: ='TABELA DE TARIFAS NOVAS'!H78/1000 -> 0.32107 | H7: =F7+G7 -> 0.74441 | I7: =((C7*$C$15)+(F7*$D$15))/($D$15+$C$15) -> 0.41211 | J7: =((D7*$C$15)+(G7*$D$15))/($D$15+$C$15) -> 0.31597667 | K7: =I7+J7 -> 0.72808667 | M7: Escassez Hídrica | N7: ='B1 (Res) Branca OK'!N7 -> 0.142 | Q7: =B7 -> B2 Fora Ponta | R7: ='FIO B'!H18/1000 -> 0.13860487 | U7: ='FIO B'!K18/1000 -> 0.14222306 | X7: =((R7*$C$15)+(U7*$D$15))/($D$15+$C$15) -> 0.141017
B8: B2 Interm. | C8: ='TABELA DE TARIFAS ANTIGAS'!G75/1000 -> 0.72534 | D8: ='TABELA DE TARIFAS ANTIGAS'!H75/1000 -> 0.30579 | E8: =C8+D8 -> 1.03113 | F8: ='TABELA DE TARIFAS NOVAS'!G77/1000 -> 0.77601 | G8: ='TABELA DE TARIFAS NOVAS'!H77/1000 -> 0.32107 | H8: =F8+G8 -> 1.09708 | I8: =((C8*$C$15)+(F8*$D$15))/($D$15+$C$15) -> 0.75912 | J8: =((D8*$C$15)+(G8*$D$15))/($D$15+$C$15) -> 0.31597667 | K8: =I8+J8 -> 1.0750967 | Q8: =B8 -> B2 Interm. | R8: ='FIO B'!H17/1000 -> 0.41581471 | U8: ='FIO B'!K17/1000 -> 0.42666929 | X8: =((R8*$C$15)+(U8*$D$15))/($D$15+$C$15) -> 0.4230511
B9: CDE Escassez Hídrica | C9: ='B1 (Res) Branca OK'!C9 -> 0.00018774721 | D9: ='B1 (Res) Branca OK'!D9 -> -0.0044031307 | E9: =SUM(C9+D9) -> -0.0042153835 | F9: =T13 -> 0.00018418923 | G9: =U13 -> -0.00053182975 | H9: =F9+G9 -> -0.00034764052 | I9: =((C9*$C$15)+(F9*$D$15))/($D$15+$C$15) -> 0.00018537523 | J9: =((D9*$C$15)+(G9*$D$15))/($D$15+$C$15) -> -0.0018222634 | K9: =I9+J9 -> -0.0016368882
P10: CUSTO | R10: Part. TUSD (%) | S10: Part. TE (%) | T10: Tusd (R$/kWh) | U10: TE (R$/kWh)
H11: Fatura | L11: Vigência das Tarifas (troca Bandeira): | M11: =EOMONTH(B15,0)+1 -> 46235 | P11: CDE CONTAS
B12: INSTALAÇÃO | C12: 160451628 | H12: =E15 -> 46260 | K12: Altere a bandeira na célula abaixo | P12: CDE COVID | U12: 0
K13: BAM | L13: ='B1 (Res) Branca OK'!L13 -> BAM | P13: CDE ESCASSEZ HÍDRICA | T13: ='B1 (Res) Branca OK'!T13 -> 0.00018418923 | U13: ='B1 (Res) Branca OK'!U13 -> -0.00053182975
B14: Leitura Anterior | C14: Nº de dias tarifa Anterior | D14: Nº de dias tarifa Nova | E14: Leitura Atual | J14: Leitura Anterior | K14: Nº de dias tarifa Anterior | L14: Nº de dias tarifa Nova | M14: Leitura Atual
B15: 46230 | C15: =IF((F2-B15-1)<0,0,(F2-B15-1)) -> 10 | D15: =E15-F2+1 -> 20 | E15: 46260 | J15: =B15 -> 46230 | K15: =IF((M11-J15-1)<0,0,(M11-J15-1)) -> 4 | L15: =M15-M11+1 -> 26 | M15: =E15 -> 46260 | O15: Documento impressão: | Q15: 1025310389
B17: Descrição | C17: Unidade | D17: Quantidade | E17: Preço Unit (R$) com tributos | F17: Valor Total (R$) | G17: PIS/COFINS (R$) | H17: Base de Cálculo ICMS (R$) | I17: Alíquota ICMS (%) | J17: ICMS (R$) | K17: Preço Unit (R$) | L17: Tributos | M17: Base de Cálc (R$) | N17: Alíquota (%) | O17: Valor (R$)
B19: TUSD - Consumo Ponta | C19: kWh | D19: 27 | E19: =IFERROR((ROUND(D19*K19,2)+ROUND(G19,2)+ROUND(J19,2))/ROUND(D19,4), 0) -> 1.4203704 | F19: =ROUND(D19*E19,2) -> 38.35 | G19: =((D19*K19)/(1-$N$19-$N$20))*($N$19+$N$20) -> 1.9638611 | H19: =(IF($I$19=12%,(D19*K19)/(1-$N$19-$N$20)/(1-$C$72)/$F$72*$C$72,(D19*K19)/(1-$N$19-$N$20)/(1-$I$19))) -> 38.348423 | I19: 0.17 | J19: =H19*$I$19 -> 6.5192319 | K19: =IF(AND($B$15<$F$2,$E$15<$F$2),C6,IF($B$15<$F$2,I6,F6)) -> 1.1061233 | L19: PIS | M19: =D60 -> 209.55984 | N19: ='B1 (Res) Branca OK'!N19 -> 0.011 | O19: =ROUND(M19*N19,2) -> 2.31 | Q19: TUSD Fio B | R19: Receita Fio B
B20: TUSD - Consumo Intermediário | C20: kWh | D20: 20 | E20: =IFERROR((ROUND(D20*K20,2)+ROUND(G20,2)+ROUND(J20,2))/ROUND(D20,4), 0) -> 0.9745 | F20: =ROUND(D20*E20,2) -> 19.49 | G20: =((D20*K20)/(1-$N$19-$N$20))*($N$19+$N$20) -> 0.99835242 | H20: =(IF($I$19=12%,(D20*K20)/(1-$N$19-$N$20)/(1-$C$72)/$F$72*$C$72,(D20*K20)/(1-$N$19-$N$20)/(1-$I$19))) -> 19.494882 | I20: =I19 -> 0.17 | J20: =H20*$I$19 -> 3.31413 | K20: =IF(AND($B$15<$F$2,$E$15<$F$2),C8,IF($B$15<$F$2,I8,F8)) -> 0.75912 | L20: COFINS | M20: =D61 -> 209.55984 | N20: ='B1 (Res) Branca OK'!N20 -> 0.0507 | O20: =ROUND(M20*N20,2) -> 10.62 | Q20: =IF(AND($B$15<$F$2,$E$15<$F$2),R6,IF($B$15<$F$2,X6,U6)) -> 0.70508509 | R20: =D46*Q20 -> 19.037298
B21: TUSD - Consumo Fora Ponta | C21: kWh | D21: 175 | E21: =IFERROR((ROUND(D21*K21,2)+ROUND(G21,2)+ROUND(J21,2))/ROUND(D21,4), 0) -> 0.52914286 | F21: =ROUND(D21*E21,2) -> 92.6 | G21: =((D21*K21)/(1-$N$19-$N$20))*($N$19+$N$20) -> 4.7423614 | H21: =(IF($I$19=12%,(D21*K21)/(1-$N$19-$N$20)/(1-$C$72)/$F$72*$C$72,(D21*K21)/(1-$N$19-$N$20)/(1-$I$19))) -> 92.604351 | I21: =I19 -> 0.17 | J21: =H21*$I$19 -> 15.74274 | K21: =IF(AND($B$15<$F$2,$E$15<$F$2),C7,IF($B$15<$F$2,I7,F7)) -> 0.41211 | Q21: =IF(AND($B$15<$F$2,$E$15<$F$2),R7,IF($B$15<$F$2,X7,U7)) -> 0.141017 | R21: =D47*Q21 -> 24.677975
B22: TE - Consumo Ponta | C22: kWh | D22: =D19 -> 27 | E22: =IFERROR((ROUND(D22*K22,2)+ROUND(G22,2)+ROUND(J22,2))/ROUND(D22,4), 0) -> 0.64962963 | F22: =ROUND(D22*E22,2) -> 17.54 | G22: =((D22*K22)/(1-$N$19-$N$20))*($N$19+$N$20) -> 0.89855269 | H22: =(IF($I$19=12%,(D22*K22)/(1-$N$19-$N$20)/(1-$C$72)/$F$72*$C$72,(D22*K22)/(1-$N$19-$N$20)/(1-$I$19))) -> 17.546088 | J22: =H22*$I$19 -> 2.9828349 | K22: =IF(AND($B$15<$F$2,$E$15<$F$2),D6,IF($B$15<$F$2,J6,G6)) -> 0.5061 | Q22: =IF(AND($B$15<$F$2,$E$15<$F$2),R8,IF($B$15<$F$2,X8,U8)) -> 0.4230511 | R22: =D48*Q22 -> 8.4610219
B23: TE - Consumo Intermediário | C23: kWh | D23: =D20 -> 20 | E23: =IFERROR((ROUND(D23*K23,2)+ROUND(G23,2)+ROUND(J23,2))/ROUND(D23,4), 0) -> 0.406 | F23: =ROUND(D23*E23,2) -> 8.12 | G23: =((D23*K23)/(1-$N$19-$N$20))*($N$19+$N$20) -> 0.41555495 | H23: =(IF($I$19=12%,(D23*K23)/(1-$N$19-$N$20)/(1-$C$72)/$F$72*$C$72,(D23*K23)/(1-$N$19-$N$20)/(1-$I$19))) -> 8.1145642 | J23: =H23*$I$19 -> 1.3794759 | K23: =IF(AND($B$15<$F$2,$E$15<$F$2),D8,IF($B$15<$F$2,J8,G8)) -> 0.31597667 | R23: =SUM(R20:R22) -> 52.176294
B24: TE - Consumo Fora Ponta | C24: kWh | D24: =D21 -> 175 | E24: =IFERROR((ROUND(D24*K24,2)+ROUND(G24,2)+ROUND(J24,2))/ROUND(D24,4), 0) -> 0.40577143 | F24: =ROUND(D24*E24,2) -> 71.01 | G24: =((D24*K24)/(1-$N$19-$N$20))*($N$19+$N$20) -> 3.6361058 | H24: =(IF($I$19=12%,(D24*K24)/(1-$N$19-$N$20)/(1-$C$72)/$F$72*$C$72,(D24*K24)/(1-$N$19-$N$20)/(1-$I$19))) -> 71.002437 | J24: =H24*$I$19 -> 12.070414 | K24: =IF(AND($B$15<$F$2,$E$15<$F$2),D7,IF($B$15<$F$2,J7,G7)) -> 0.31597667
B25: Adicional BAM | C25: kWh | D25: =IF($K$13=M4,(($D$19+$D$20+$D$21)*($K$15)/($K$15+$L$15)),0)+IF($L$13=M4,(($D$19+$D$20+$D$21)*($L$15)/($K$15+$L$15)),0) -> 222 | E25: =IFERROR((ROUND(D25*K25,2)+ROUND(G25,2)+ROUND(J25,2))/ROUND(D25,4), 0) -> 0.024189189 | F25: =ROUND(D25*E25,2) -> 5.37 | G25: =((D25*K25)/(1-$N$19-$N$20))*($N$19+$N$20) -> 0.27517424 | H25: =(IF($I$19=12%,(D25*K25)/(1-$N$19-$N$20)/(1-$C$72)/$F$72*$C$72,(D25*K25)/(1-$N$19-$N$20)/(1-$I$19))) -> 5.3733425 | J25: =H25*$I$19 -> 0.91346822 | K25: =N4 -> 0.01885
B26: Adicional BVM 1 | C26: kWh | D26: =IF($K$13=M5,(($D$19+$D$20+$D$21)*($K$15)/($K$15+$L$15)),0)+IF($L$13=M5,(($D$19+$D$20+$D$21)*($L$15)/($K$15+$L$15)),0) -> 0 | E26: =IFERROR((ROUND(D26*K26,2)+ROUND(G26,2)+ROUND(J26,2))/ROUND(D26,4), 0) -> 0 | F26: =ROUND(D26*E26,2) -> 0 | G26: =((D26*K26)/(1-$N$19-$N$20))*($N$19+$N$20) -> 0 | H26: =(IF($I$19=12%,(D26*K26)/(1-$N$19-$N$20)/(1-$C$72)/$F$72*$C$72,(D26*K26)/(1-$N$19-$N$20)/(1-$I$19))) -> 0 | J26: =H26*$I$19 -> 0 | K26: =N5 -> 0.04463
B27: Adicional BVM 2 | C27: kWh | D27: =IF($K$13=M6,(($D$19+$D$20+$D$21)*($K$15)/($K$15+$L$15)),0)+IF($L$13=M6,(($D$19+$D$20+$D$21)*($L$15)/($K$15+$L$15)),0) -> 0 | E27: =IFERROR((ROUND(D27*K27,2)+ROUND(G27,2)+ROUND(J27,2))/ROUND(D27,4), 0) -> 0 | F27: =ROUND(D27*E27,2) -> 0 | G27: =((D27*K27)/(1-$N$19-$N$20))*($N$19+$N$20) -> 0 | H27: =(IF($I$19=12%,(D27*K27)/(1-$N$19-$N$20)/(1-$C$72)/$F$72*$C$72,(D27*K27)/(1-$N$19-$N$20)/(1-$I$19))) -> 0 | J27: =H27*$I$19 -> 0 | K27: =N6 -> 0.07877
B28: Adicional Escassez | C28: kWh | D28: =IF($K$13=M7,(($D$19+$D$20+$D$21)*($K$15)/($K$15+$L$15)),0)+IF($L$13=M7,(($D$19+$D$20+$D$21)*($L$15)/($K$15+$L$15)),0) -> 0 | E28: =IFERROR((ROUND(D28*K28,2)+ROUND(G28,2)+ROUND(J28,2))/ROUND(D28,4), 0) -> 0 | F28: =ROUND(D28*E28,2) -> 0 | G28: =((D28*K28)/(1-$N$19-$N$20))*($N$19+$N$20) -> 0 | H28: =(IF($I$19=12%,(D28*K28)/(1-$N$19-$N$20)/(1-$C$72)/$F$72*$C$72,(D28*K28)/(1-$N$19-$N$20)/(1-$I$19))) -> 0 | J28: =H28*$I$19 -> 0 | K28: =N7 -> 0.142
B29: Multas
B30: Juros | Q30: 200
B31: Doações | F31: -6.91 | Q31: 18700
B32: CIP | Q32: 600
B35: TOTAL | F35: =SUM(F19:F34) -> 245.57 | G35: =SUM(G19:G34) -> 12.929963 | H35: =SUM(H19:H34) -> 252.48409 | J35: =SUM(J19:J34) -> 42.922295
B37: Informativo Escassez | C37: =D19+D20+D21 -> 222 | D37: =IF(AND($B$15<$F$2,$E$15<$F$2),C9,IF($B$15<$F$2,I9,F9)) -> 0.00018537523 | E37: =IF(AND($B$15<$F$2,$E$15<$F$2),D9,IF($B$15<$F$2,J9,G9)) -> -0.0018222634 | F37: =C37*(D37+E37) -> -0.36338918
B42: Fatura B2 Rural TB
D43: Qtde | E43: TUSD | F43: TE | G43: TUSD + TE | H43: R$
B44: Fornecimento de Energia Elétrica | H44: =SUM(H46:H54)+SUM(H60:H62) -> 218.2915 | J44: B1 Residencial | L44: Diferença
J45: TUSD + TE | K45: R$
B46: Consumo Ponta | D46: =D19 -> 27 | E46: =IF(AND($B$15<$F$2,$E$15<$F$2),C6,IF($B$15<$F$2,I6,F6)) -> 1.1061233 | F46: =IF(AND($B$15<$F$2,$E$15<$F$2),D6,IF($B$15<$F$2,J6,G6)) -> 0.5061 | G46: =E46+F46 -> 1.6122233 | H46: =ROUND((D46*E46),2)+ROUND((D46*F46),2) -> 43.53 | J46: =IF(AND($B$15<$F$2,$E$15<$F$2),E132,IF($B$15<$F$2,K132,H132)) -> 1.465882 | K46: =D46*J46 -> 39.578814 | L46: =K46-H46 -> -3.951186
B47: Consumo Fora Ponta | D47: =D21 -> 175 | E47: =IF(AND($B$15<$F$2,$E$15<$F$2),C7,IF($B$15<$F$2,I7,F7)) -> 0.41211 | F47: =IF(AND($B$15<$F$2,$E$15<$F$2),D7,IF($B$15<$F$2,J7,G7)) -> 0.31597667 | G47: =E47+F47 -> 0.72808667 | H47: =ROUND((D47*E47),2)+ROUND((D47*F47),2) -> 127.42 | J47: =IF(AND($B$15<$F$2,$E$15<$F$2),E133,IF($B$15<$F$2,K133,H133)) -> 0.693024 | K47: =D47*J47 -> 121.2792 | L47: =K47-H47 -> -6.1408
B48: Consumo Intemediário | D48: =D20 -> 20 | E48: =IF(AND($B$15<$F$2,$E$15<$F$2),C8,IF($B$15<$F$2,I8,F8)) -> 0.75912 | F48: =IF(AND($B$15<$F$2,$E$15<$F$2),D8,IF($B$15<$F$2,J8,G8)) -> 0.31597667 | G48: =E48+F48 -> 1.0750967 | H48: =ROUND((D48*E48),2)+ROUND((D48*F48),2) -> 21.5 | J48: =IF(AND($B$15<$F$2,$E$15<$F$2),E134,IF($B$15<$F$2,K134,H134)) -> 0.98610667 | K48: =D48*J48 -> 19.722133 | L48: =K48-H48 -> -1.7778667
L50: =SUM(L46:L48) -> -11.869853
B51: Adicional BAM | D51: =IF($K$13=M4,((D46+D47+D48)*(K15)/(K15+L15)),0)+IF($L$13=M4,((D46+D47+D48)*(L15)/(K15+L15)),0) -> 222 | F51: =N4 -> 0.01885 | H51: =ROUND(D51*(E51+F51),2) -> 4.18
B52: Adicional BVM 1 | D52: =IF($K$13=M5,((D46+D47+D48)*(K15)/(K15+L15)),0)+IF($L$13=M5,((D46+D47+D48)*(L15)/(K15+L15)),0) -> 0 | F52: =N5 -> 0.04463 | H52: =ROUND(D52*(E52+F52),2) -> 0
B53: Adicional BVM 2 | D53: =IF($K$13=M6,((D46+D47+D48)*(K15)/(K15+L15)),0)+IF($L$13=M6,((D46+D47+D48)*(L15)/(K15+L15)),0) -> 0 | F53: =N6 -> 0.07877 | H53: =ROUND(D53*(E53+F53),2) -> 0
B54: Adicional Escassez Hídrica | D54: =IF($K$13=M7,((D46+D47+D48)*(K15)/(K15+L15)),0)+IF($L$13=M7,((D46+D47+D48)*(L15)/(K15+L15)),0) -> 0 | F54: =N7 -> 0.142 | H54: =ROUND(D54*(E54+F54),2) -> 0
D59: Base de Cálculo
B60: PIS | D60: =(SUM(H46:H54)/(1-E60-E61)) -> 209.55984 | E60: =N19 -> 0.011 | H60: =D60*E60 -> 2.3051583
B61: COFINS | D61: =D60 -> 209.55984 | E61: =N20 -> 0.0507 | H61: =D61*E61 -> 10.624684
B62: ICMS | D62: =IF((E62=17%),(D60)/(1-E62),D72) -> 72.763834 | E62: 0.12 | H62: =D62*E62 -> 8.7316601
B64: Informativo Escassez Hídrica | D64: =SUM(D46:D48) -> 222 | E64: =IF(AND($B$15<$F$2,$E$15<$F$2),C9,IF($B$15<$F$2,I9,F9)) -> 0.00018537523 | F64: =IF(AND($B$15<$F$2,$E$15<$F$2),D9,IF($B$15<$F$2,J9,G9)) -> -0.0018222634 | H64: =D64*(E64+F64) -> -0.36338918
B65: Benefício Rural (em relação ao B1 residencial) | H65: =L50 -> -11.869853 | I65: (mensagem na fatura)
B68: Se for base reduzida: (célula E37 = 12%)
D69: Com tributos
B70: PIS | C70: =E60 -> 0.011 | D70: =SUM(H48:H54)/(1-C70-C71) -> 27.368645 | E70: x | F70: =C70 -> 0.011 | G70: =D70*F70 -> 0.3010551
B71: COFINS | C71: =E61 -> 0.0507 | D71: =D70 -> 27.368645 | E71: x | F71: =C71 -> 0.0507 | G71: =D71*F71 -> 1.3875903
A72: Rural c/ incrição | B72: ICMS | C72: 0.04 | D72: =H72/F72*C72 -> 72.763834 | E72: x | F72: 0.12 | G72: =D72*F72 -> 8.7316601 | H72: =(H46+H47+H48+H51+H52+H53+H54)/(1-E60-E61)/(1-C72) -> 218.2915 | I72: =H72*C72 -> 8.7316601
E73: =(O62)/(1-C70-C71-C72) -> 0
D75: Base de cálculo reduzida = | E75: Importe | G75: = | H75: =H72/F72*C72 -> 72.763834
E76: 12% x 4%
B79: Participação
C80: R$
B81: Energia | C81: =(SUM(H46:H54)*IF($B$15<$F$2,D119,D91)) -> 88.111561
B82: Distribuição | C82: =(SUM(H46:H54)*IF($B$15<$F$2,F119,F91)) -> 52.622799
B83: Transmissão | C83: =(SUM(H46:H54)*IF($B$15<$F$2,E119,E91)) -> 15.770801
B84: Encargos Setoriais | C84: =(SUM(H46:H54)*IF($B$15<$F$2,G119,G91)) -> 40.125475
B85: Impostos / Tributos | C85: =H60+H61+H62 -> 21.661502
B86: Total | C86: =SUM(C81:C85) -> 218.29214
B88: ='B1 (Res) Branca OK'!B76 -> 2024 | D88: Energia | E88: Transmissão | F88: Distribuição | G88: Setoriais
B89: Grupo B | D89: % | E89: % | F89: % | G89: %
B91: B1 - Residencial | D91: ='B1 (Res) Branca OK'!D79 -> 0.45246417 | E91: ='B1 (Res) Branca OK'!E79 -> 0.073959411 | F91: ='B1 (Res) Branca OK'!F79 -> 0.27500913 | G91: ='B1 (Res) Branca OK'!G79 -> 0.19856729
B92: B1 - Residencial Baixa Renda | D92: ='B1 (Res) Branca OK'!D80 -> 0.53149576 | E92: ='B1 (Res) Branca OK'!E80 -> 0.086877849 | F92: ='B1 (Res) Branca OK'!F80 -> 0.32304478 | G92: ='B1 (Res) Branca OK'!G80 -> 0.058581612
B93: B2 - Rural | D93: ='B1 (Res) Branca OK'!D81 -> 0.45246417 | E93: ='B1 (Res) Branca OK'!E81 -> 0.073959411 | F93: ='B1 (Res) Branca OK'!F81 -> 0.27500913 | G93: ='B1 (Res) Branca OK'!G81 -> 0.19856729
B94: B2 - Cooperativa Eletrificação Rural | D94: ='B1 (Res) Branca OK'!D82 -> 0.45246417 | E94: ='B1 (Res) Branca OK'!E82 -> 0.073959411 | F94: ='B1 (Res) Branca OK'!F82 -> 0.27500913 | G94: ='B1 (Res) Branca OK'!G82 -> 0.19856729
B95: B2 - Serviço de Irrigação | D95: ='B1 (Res) Branca OK'!D83 -> 0.45246417 | E95: ='B1 (Res) Branca OK'!E83 -> 0.073959411 | F95: ='B1 (Res) Branca OK'!F83 -> 0.27500913 | G95: ='B1 (Res) Branca OK'!G83 -> 0.19856729
B96: B3 - Demais Classes | D96: ='B1 (Res) Branca OK'!D84 -> 0.45246417 | E96: ='B1 (Res) Branca OK'!E84 -> 0.073959411 | F96: ='B1 (Res) Branca OK'!F84 -> 0.27500913 | G96: ='B1 (Res) Branca OK'!G84 -> 0.19856729
B97: B4 - Iluminação Pública | D97: ='B1 (Res) Branca OK'!D85 -> 0.45246417 | E97: ='B1 (Res) Branca OK'!E85 -> 0.073959411 | F97: ='B1 (Res) Branca OK'!F85 -> 0.27500913 | G97: ='B1 (Res) Branca OK'!G85 -> 0.19856729
B98: B4a - Rede de Distribuição | D98: ='B1 (Res) Branca OK'!D86 -> 0.45246417 | E98: ='B1 (Res) Branca OK'!E86 -> 0.073959411 | F98: ='B1 (Res) Branca OK'!F86 -> 0.27500913 | G98: ='B1 (Res) Branca OK'!G86 -> 0.19856729
B99: B4b - Bulbo de Lâmpada | D99: ='B1 (Res) Branca OK'!D87 -> 0.45246417 | E99: ='B1 (Res) Branca OK'!E87 -> 0.073959411 | F99: ='B1 (Res) Branca OK'!F87 -> 0.27500913 | G99: ='B1 (Res) Branca OK'!G87 -> 0.19856729
B102: ='B1 (Res) Branca OK'!B90 -> 2023 | D102: Energia | E102: Transmissão | F102: Distribuição | G102: Setoriais
B103: Grupo B | D103: % | E103: % | F103: % | G103: %
B105: B1 - Residencial | D105: ='B1 (Res) Branca OK'!D93 -> 0.43939696 | E105: ='B1 (Res) Branca OK'!E93 -> 0.092697586 | F105: ='B1 (Res) Branca OK'!F93 -> 0.25285208 | G105: ='B1 (Res) Branca OK'!G93 -> 0.21506308
B106: B1 - Residencial Baixa Renda | D106: ='B1 (Res) Branca OK'!D94 -> 0.5269162 | E106: ='B1 (Res) Branca OK'!E94 -> 0.11116112 | F106: ='B1 (Res) Branca OK'!F94 -> 0.30321524 | G106: ='B1 (Res) Branca OK'!G94 -> 0.058707433
B107: B2 - Rural | D107: ='B1 (Res) Branca OK'!D95 -> 0.439393 | E107: ='B1 (Res) Branca OK'!E95 -> 0.092696751 | F107: ='B1 (Res) Branca OK'!F95 -> 0.2528498 | G107: ='B1 (Res) Branca OK'!G95 -> 0.21506045
B108: B2 - Cooperativa Eletrificação Rural | D108: ='B1 (Res) Branca OK'!D96 -> 0.439393 | E108: ='B1 (Res) Branca OK'!E96 -> 0.092696751 | F108: ='B1 (Res) Branca OK'!F96 -> 0.2528498 | G108: ='B1 (Res) Branca OK'!G96 -> 0.21506045
B109: B2 - Serviço de Irrigação | D109: ='B1 (Res) Branca OK'!D97 -> 0.439393 | E109: ='B1 (Res) Branca OK'!E97 -> 0.092696751 | F109: ='B1 (Res) Branca OK'!F97 -> 0.2528498 | G109: ='B1 (Res) Branca OK'!G97 -> 0.21506045
B110: B3 - Demais Classes | D110: ='B1 (Res) Branca OK'!D98 -> 0.439393 | E110: ='B1 (Res) Branca OK'!E98 -> 0.092696751 | F110: ='B1 (Res) Branca OK'!F98 -> 0.2528498 | G110: ='B1 (Res) Branca OK'!G98 -> 0.21506045
B111: B4 - Iluminação Pública | D111: ='B1 (Res) Branca OK'!D99 -> 0 | E111: ='B1 (Res) Branca OK'!E99 -> 0 | F111: ='B1 (Res) Branca OK'!F99 -> 0 | G111: ='B1 (Res) Branca OK'!G99 -> 0
B112: B4a - Rede de Distribuição | D112: ='B1 (Res) Branca OK'!D100 -> 0.43938946 | E112: ='B1 (Res) Branca OK'!E100 -> 0.092697337 | F112: ='B1 (Res) Branca OK'!F100 -> 0.2528514 | G112: ='B1 (Res) Branca OK'!G100 -> 0.21506181
B113: B4b - Bulbo de Lâmpada | D113: ='B1 (Res) Branca OK'!D101 -> 0.43938946 | E113: ='B1 (Res) Branca OK'!E101 -> 0.092697337 | F113: ='B1 (Res) Branca OK'!F101 -> 0.2528514 | G113: ='B1 (Res) Branca OK'!G101 -> 0.21506181
B115: proporcional
D116: Energia | E116: Transmissão | F116: Distribuição | G116: Setoriais
B117: Grupo B | D117: % | E117: % | F117: % | G117: %
B119: B1 - Residencial | D119: =((D105*$C$15)+(D91*$D$15))/($C$15+$D$15) -> 0.44810843 | E119: =((E105*$C$15)+(E91*$D$15))/($C$15+$D$15) -> 0.080205469 | F119: =((F105*$C$15)+(F91*$D$15))/($C$15+$D$15) -> 0.26762345 | G119: =((G105*$C$15)+(G91*$D$15))/($C$15+$D$15) -> 0.20406589
B120: B1 - Residencial Baixa Renda | D120: =((D106*$C$15)+(D92*$D$15))/($C$15+$D$15) -> 0.52996924 | E120: =((E106*$C$15)+(E92*$D$15))/($C$15+$D$15) -> 0.094972273 | F120: =((F106*$C$15)+(F92*$D$15))/($C$15+$D$15) -> 0.31643494 | G120: =((G106*$C$15)+(G92*$D$15))/($C$15+$D$15) -> 0.058623552
B121: B2 - Rural | D121: =((D107*$C$15)+(D93*$D$15))/($C$15+$D$15) -> 0.44810711 | E121: =((E107*$C$15)+(E93*$D$15))/($C$15+$D$15) -> 0.080205191 | F121: =((F107*$C$15)+(F93*$D$15))/($C$15+$D$15) -> 0.26762269 | G121: =((G107*$C$15)+(G93*$D$15))/($C$15+$D$15) -> 0.20406501
B122: B2 - Cooperativa Eletrificação Rural | D122: =((D108*$C$15)+(D94*$D$15))/($C$15+$D$15) -> 0.44810711 | E122: =((E108*$C$15)+(E94*$D$15))/($C$15+$D$15) -> 0.080205191 | F122: =((F108*$C$15)+(F94*$D$15))/($C$15+$D$15) -> 0.26762269 | G122: =((G108*$C$15)+(G94*$D$15))/($C$15+$D$15) -> 0.20406501
B123: B2 - Serviço de Irrigação | D123: =((D109*$C$15)+(D95*$D$15))/($C$15+$D$15) -> 0.44810711 | E123: =((E109*$C$15)+(E95*$D$15))/($C$15+$D$15) -> 0.080205191 | F123: =((F109*$C$15)+(F95*$D$15))/($C$15+$D$15) -> 0.26762269 | G123: =((G109*$C$15)+(G95*$D$15))/($C$15+$D$15) -> 0.20406501
B124: B3 - Demais Classes | D124: =((D110*$C$15)+(D96*$D$15))/($C$15+$D$15) -> 0.44810711 | E124: =((E110*$C$15)+(E96*$D$15))/($C$15+$D$15) -> 0.080205191 | F124: =((F110*$C$15)+(F96*$D$15))/($C$15+$D$15) -> 0.26762269 | G124: =((G110*$C$15)+(G96*$D$15))/($C$15+$D$15) -> 0.20406501
B125: B4 - Iluminação Pública | D125: =((D111*$C$15)+(D97*$D$15))/($C$15+$D$15) -> 0.30164278 | E125: =((E111*$C$15)+(E97*$D$15))/($C$15+$D$15) -> 0.049306274 | F125: =((F111*$C$15)+(F97*$D$15))/($C$15+$D$15) -> 0.18333942 | G125: =((G111*$C$15)+(G97*$D$15))/($C$15+$D$15) -> 0.13237819
B126: B4a - Rede de Distribuição | D126: =((D112*$C$15)+(D98*$D$15))/($C$15+$D$15) -> 0.44810593 | E126: =((E112*$C$15)+(E98*$D$15))/($C$15+$D$15) -> 0.080205386 | F126: =((F112*$C$15)+(F98*$D$15))/($C$15+$D$15) -> 0.26762322 | G126: =((G112*$C$15)+(G98*$D$15))/($C$15+$D$15) -> 0.20406546
B127: B4b - Bulbo de Lâmpada | D127: =((D113*$C$15)+(D99*$D$15))/($C$15+$D$15) -> 0.44810593 | E127: =((E113*$C$15)+(E99*$D$15))/($C$15+$D$15) -> 0.080205386 | F127: =((F113*$C$15)+(F99*$D$15))/($C$15+$D$15) -> 0.26762322 | G127: =((G113*$C$15)+(G99*$D$15))/($C$15+$D$15) -> 0.20406546
B132: B1 Ponta | C132: ='B1 (Res) Branca OK'!C6 -> 0.93761 | D132: ='B1 (Res) Branca OK'!D6 -> 0.48448 | E132: ='B1 (Res) Branca OK'!E6 -> 1.42209 | F132: ='B1 (Res) Branca OK'!F6 -> 0.99902 | G132: ='B1 (Res) Branca OK'!G6 -> 0.51691 | H132: ='B1 (Res) Branca OK'!H6 -> 1.51593 | I132: ='B1 (Res) Branca OK'!I6 -> 0.966268 | J132: ='B1 (Res) Branca OK'!J6 -> 0.499614 | K132: =I132+J132 -> 1.465882
...

Sheet FIO B
B2: TUSD FIO B
B4: SUBGRUPO | C4: MODALIDADE | D4: CLASSE | E4: SUBCLASSE | F4: POSTO | G4: TARIFAS DE APLICAÇÃO
G5: TUSD FIO B (RTP 2025) | J5: TUSD FIO B (RTA 2026)
G6: R$/kW | H6: R$/MWh | J6: R$/kW | K6: R$/MWh
B7: B1 | C7: BRANCA | D7: RESIDENCIAL | E7: RESIDENCIAL | F7: P | G7: 0 | H7: 591.10909 | J7: 0 | K7: 606.53962
B8: B1 | C8: BRANCA | D8: RESIDENCIAL | E8: RESIDENCIAL | F8: INT | G8: 0 | H8: 354.6655 | J8: 0 | K8: 363.92381
B9: B1 | C9: BRANCA | D9: RESIDENCIAL | E9: RESIDENCIAL | F9: FP | G9: 0 | H9: 118.2218 | J9: 0 | K9: 121.3079
B10: B1 | C10: PRÉ-PAGAMENTO | D10: RESIDENCIAL | E10: RESIDENCIAL | F10: NA | G10: 0 | H10: 203.83072 | J10: 0 | K10: 209.15159
B11: B1 | C11: CONVENCIONAL | D11: RESIDENCIAL | E11: RESIDENCIAL | F11: NA | G11: 0 | H11: 203.83072 | J11: 0 | K11: 209.15159
B12: B1 | C12: PRÉ-PAGAMENTO | D12: RESIDENCIAL | E12: BAIXA RENDA | F12: NA | G12: 0 | H12: 203.83072 | J12: 0 | K12: 209.15159
B13: B1 | C13: CONVENCIONAL | D13: RESIDENCIAL | E13: BAIXA RENDA | F13: NA | G13: 0 | H13: 203.83072 | J13: 0 | K13: 209.15159
B14: B1 | C14: PRÉ-PAGAMENTO | D14: RESIDENCIAL | E14: RESIDENCIAL DESCONTO SOCIAL | F14: NA | G14: 0 | H14: 203.83072 | J14: 0 | K14: 209.15159
B15: B1 | C15: CONVENCIONAL | D15: RESIDENCIAL | E15: RESIDENCIAL DESCONTO SOCIAL | F15: NA | G15: 0 | H15: 203.83072 | J15: 0 | K15: 209.15159
B16: B2 | C16: BRANCA | D16: RURAL | E16: NÃO SE APLICA | F16: P | G16: 0 | H16: 693.02445 | J16: 0 | K16: 711.11541
B17: B2 | C17: BRANCA | D17: RURAL | E17: NÃO SE APLICA | F17: INT | G17: 0 | H17: 415.81471 | J17: 0 | K17: 426.66929
B18: B2 | C18: BRANCA | D18: RURAL | E18: NÃO SE APLICA | F18: FP | G18: 0 | H18: 138.60487 | J18: 0 | K18: 142.22306
... B39: B | C39: GERAÇÃO | D39: TIPO 02 | E39: NA | F39: NA | G39: 0 | H39: 11.690957 | J39: 0 | K39: 11.996142

Sheet B2 (Rural Irrig) Branca OK
B2: B2 Rural | E2: Vigência das Tarifas: | F2: ='B1 (Res) Branca OK'!F2 -> 46241 | H2: TARIFA BRANCA | M2: Bandeira | N2: R$/kWh | Q2: TUSD FIO B
M3: VERDE | N3: ='B1 (Res) Branca OK'!N3 -> 0
B4: TARIFA | C4: ='B1 (Res) Branca OK'!C4 -> TARIFA ANTIGA - REH 3370/2024 | F4: ='B1 (Res) Branca OK'!F4 -> TARIFA NOVA - REH xxxx/2025 | I4: Tarifas Proporcionalizadas | M4: BAM | N4: ='B1 (Res) Branca OK'!N4 -> 0.01885 | Q4: TARIFA | R4: =C4 -> TARIFA ANTIGA - REH 3370/2024 | U4: =F4 -> TARIFA NOVA - REH xxxx/2025
C5: Tusd | D5: TE | E5: TUSD + TE | F5: Tusd | G5: TE | H5: TUSD + TE | I5: Tusd | J5: TE | K5: TUSD + TE | M5: BVM1 | N5: ='B1 (Res) Branca OK'!N5 -> 0.04463 | R5: Tusd (R$/kWh) | U5: Tusd (R$/kWh) | X5: Tusd (R$/kWh)
B6: B2 Ponta | C6: ='TABELA DE TARIFAS ANTIGAS'!G74/1000 -> 1.06103 | D6: ='TABELA DE TARIFAS ANTIGAS'!H74/1000 -> 0.48448 | E6: =C6+D6 -> 1.54551 | F6: ='TABELA DE TARIFAS NOVAS'!G76/1000 -> 1.12867 | G6: ='TABELA DE TARIFAS NOVAS'!H76/1000 -> 0.51691 | H6: =F6+G6 -> 1.64558 | I6: =((C6*$C$15)+(F6*$D$15))/($D$15+$C$15) -> 1.0903407 | J6: =((D6*$C$15)+(G6*$D$15))/($D$15+$C$15) -> 0.498533 | K6: =I6+J6 -> 1.5888737 | M6: BVM2 | N6: ='B1 (Res) Branca OK'!N6 -> 0.07877 | Q6: =B6 -> B2 Ponta | R6: ='FIO B'!H16/1000 -> 0.69302445 | U6: ='FIO B'!K16/1000 -> 0.71111541 | X6: =((R6*$C$15)+(U6*$D$15))/($D$15+$C$15) -> 0.70086387
B7: B2 Fora Ponta | C7: ='TABELA DE TARIFAS ANTIGAS'!G76/1000 -> 0.38965 | D7: ='TABELA DE TARIFAS ANTIGAS'!H76/1000 -> 0.30579 | E7: =C7+D7 -> 0.69544 | F7: ='TABELA DE TARIFAS NOVAS'!G78/1000 -> 0.42334 | G7: ='TABELA DE TARIFAS NOVAS'!H78/1000 -> 0.32107 | H7: =F7+G7 -> 0.74441 | I7: =((C7*$C$15)+(F7*$D$15))/($D$15+$C$15) -> 0.404249 | J7: =((D7*$C$15)+(G7*$D$15))/($D$15+$C$15) -> 0.31241133 | K7: =I7+J7 -> 0.71666033 | M7: Escassez Hídrica | N7: ='B1 (Res) Branca OK'!N7 -> 0.142 | Q7: =B7 -> B2 Fora Ponta | R7: ='FIO B'!H18/1000 -> 0.13860487 | U7: ='FIO B'!K18/1000 -> 0.14222306 | X7: =((R7*$C$15)+(U7*$D$15))/($D$15+$C$15) -> 0.14017275
B8: B2 Interm. | C8: ='TABELA DE TARIFAS ANTIGAS'!G75/1000 -> 0.72534 | D8: ='TABELA DE TARIFAS ANTIGAS'!H75/1000 -> 0.30579 | E8: =C8+D8 -> 1.03113 | F8: ='TABELA DE TARIFAS NOVAS'!G77/1000 -> 0.77601 | G8: ='TABELA DE TARIFAS NOVAS'!H77/1000 -> 0.32107 | H8: =F8+G8 -> 1.09708 | I8: =((C8*$C$15)+(F8*$D$15))/($D$15+$C$15) -> 0.747297 | J8: =((D8*$C$15)+(G8*$D$15))/($D$15+$C$15) -> 0.31241133 | K8: =I8+J8 -> 1.0597083 | Q8: =B8 -> B2 Interm. | R8: ='FIO B'!H17/1000 -> 0.41581471 | U8: ='FIO B'!K17/1000 -> 0.42666929 | X8: =((R8*$C$15)+(U8*$D$15))/($D$15+$C$15) -> 0.42051836
B9: CDE Escassez Hídrica | C9: ='B1 (Res) Branca OK'!C9 -> 0.00018774721 | D9: ='B1 (Res) Branca OK'!D9 -> -0.0044031307 | E9: =SUM(C9+D9) -> -0.0042153835 | F9: =T13 -> 0.00018418923 | G9: =U13 -> -0.00053182975 | H9: =F9+G9 -> -0.00034764052 | I9: =((C9*$C$15)+(F9*$D$15))/($D$15+$C$15) -> 0.00018620542 | J9: =((D9*$C$15)+(G9*$D$15))/($D$15+$C$15) -> -0.002725567 | K9: =I9+J9 -> -0.0025393616
P10: CUSTO | R10: Part. TUSD (%) | S10: Part. TE (%) | T10: Tusd (R$/kWh) | U10: TE (R$/kWh)
H11: Fatura | L11: Vigência das Tarifas (troca Bandeira): | M11: 45968 | P11: CDE CONTAS
B12: INSTALAÇÃO | C12: 1831902 | H12: =E15 -> 46253 | K12: Altere a bandeira na célula abaixo | P12: CDE COVID | U12: 0
K13: ='B1 (Res) Branca OK'!K13 -> BAM | L13: ='B1 (Res) Branca OK'!L13 -> BAM | P13: CDE ESCASSEZ HÍDRICA | T13: ='B1 (Res) Branca OK'!T13 -> 0.00018418923 | U13: ='B1 (Res) Branca OK'!U13 -> -0.00053182975
B14: Leitura Anterior | C14: Nº de dias tarifa Anterior | D14: Nº de dias tarifa Nova | E14: Leitura Atual | J14: Leitura Anterior | K14: Nº de dias tarifa Anterior | L14: Nº de dias tarifa Nova | M14: Leitura Atual
B15: 46223 | C15: =IF((F2-B15-1)<0,0,(F2-B15-1)) -> 17 | D15: =E15-F2+1 -> 13 | E15: 46253 | J15: =B15 -> 46223 | K15: =IF((M11-J15-1)<0,0,(M11-J15-1)) -> 0 | L15: =M15-M11+1 -> 286 | M15: =E15 -> 46253 | O15: Documento impressão: | Q15: 1025310390
B17: Descrição | C17: Unidade | D17: Quantidade | E17: Preço Unit (R$) com tributos | F17: Valor Total (R$) | G17: PIS/COFINS (R$) | H17: Base de Cálculo ICMS (R$) | I17: Alíquota ICMS (%) | J17: ICMS (R$) | K17: Preço Unit (R$) | L17: Tributos | M17: Base de Cálc (R$) | N17: Alíquota (%) | O17: Valor (R$)
B19: TUSD - Consumo Ponta | C19: kWh | D19: 0 | E19: =IFERROR((ROUND(D19*K19,2)+ROUND(G19,2)+ROUND(J19,2))/ROUND(D19,4), 0) -> 0 | F19: =ROUND(D19*E19,2) -> 0 | G19: =((D19*K19)/(1-$N$19-$N$20))*($N$19+$N$20) -> 0 | H19: =(IF($I$19=12%,(D19*K19)/(1-$N$19-$N$20)/(1-$C$85)/$F$85*$C$85,(D19*K19)/(1-$N$19-$N$20)/(1-$I$19))) -> 0 | I19: 0.12 | J19: =H19*$I$19 -> 0 | K19: =IF(AND($B$15<$F$2,$E$15<$F$2),C6,IF($B$15<$F$2,I6,F6)) -> 1.0903407 | L19: PIS | M19: =D52 -> 265 | N19: ='B1 (Res) Branca OK'!N19 -> 0.011 | O19: =ROUND(M19*N19,2) -> 2.92
B20: TUSD - Consumo Intermediário | C20: kWh | D20: 2 | E20: =IFERROR((ROUND(D20*K20,2)+ROUND(G20,2)+ROUND(J20,2))/ROUND(D20,4), 0) -> 0.83 | F20: =ROUND(D20*E20,2) -> 1.66 | G20: =((D20*K20)/(1-$N$19-$N$20))*($N$19+$N$20) -> 0.098280347 | H20: =(IF($I$19=12%,(D20*K20)/(1-$N$19-$N$20)/(1-$C$85)/$F$85*$C$85,(D20*K20)/(1-$N$19-$N$20)/(1-$I$19))) -> 0.55308137 | I20: =I19 -> 0.12 | J20: =H20*$I$19 -> 0.066369764 | K20: =IF(AND($B$15<$F$2,$E$15<$F$2),C8,IF($B$15<$F$2,I8,F8)) -> 0.747297 | L20: COFINS | M20: =M19 -> 265 | N20: ='B1 (Res) Branca OK'!N20 -> 0.0507 | O20: =ROUND(M20*N20,2) -> 13.44 | Q20: TUSD Fio B | R20: Receita Fio B
B21: TUSD - Consumo Fora Ponta | C21: kWh | D21: 265 | E21: =IFERROR((ROUND(D21*K21,2)+ROUND(G21,2)+ROUND(J21,2))/ROUND(D21,4), 0) -> 0.44879245 | F21: =ROUND(D21*E21,2) -> 118.93 | G21: =((D21*K21)/(1-$N$19-$N$20))*($N$19+$N$20) -> 7.044307 | H21: =(IF($I$19=12%,(D21*K21)/(1-$N$19-$N$20)/(1-$C$85)/$F$85*$C$85,(D21*K21)/(1-$N$19-$N$20)/(1-$I$19))) -> 39.642463 | I21: =I19 -> 0.12 | J21: =H21*$I$19 -> 4.7570955 | K21: =IF(AND($B$15<$F$2,$E$15<$F$2),C7,IF($B$15<$F$2,I7,F7)) -> 0.404249 | Q21: =IF(AND($B$15<$F$2,$E$15<$F$2),R6,IF($B$15<$F$2,X6,U6)) -> 0.70086387 | R21: =D51*Q21 -> 0
B22: TUSD - Consumo Reservado | C22: kWh | D22: 586 | E22: =IFERROR((ROUND(D22*K22,2)+ROUND(G22,2)+ROUND(J22,2))/ROUND(D22,4), 0) -> 0.17952218 | F22: =ROUND(D22*E22,2) -> 105.2 | G22: =((D22*K22)/(1-$N$19-$N$20))*($N$19+$N$20) -> 6.2308889 | H22: =(IF($I$19=12%,(D22*K22)/(1-$N$19-$N$20)/(1-$C$85)/$F$85*$C$85,(D22*K22)/(1-$N$19-$N$20)/(1-$I$19))) -> 35.06488 | I22: =I20 -> 0.12 | J22: =H22*$I$19 -> 4.2077856 | K22: =ROUND(K21+(K21*(-$H$46)),8) -> 0.1616996 | Q22: =IF(AND($B$15<$F$2,$E$15<$F$2),R7,IF($B$15<$F$2,X7,U7)) -> 0.14017275 | R22: =D52*Q22 -> 37.14578
Q23: =IF(AND($B$15<$F$2,$E$15<$F$2),R8,IF($B$15<$F$2,X8,U8)) -> 0.42051836 | R23: =D53*Q23 -> 0.84103673
B24: TE - Consumo Ponta | C24: kWh | D24: =D19 -> 0 | E24: =IFERROR((ROUND(D24*K24,2)+ROUND(G24,2)+ROUND(J24,2))/ROUND(D24,4), 0) -> 0 | F24: =ROUND(D24*E24,2) -> 0 | G24: =((D24*K24)/(1-$N$19-$N$20))*($N$19+$N$20) -> 0 | H24: =(IF($I$19=12%,(D24*K24)/(1-$N$19-$N$20)/(1-$C$85)/$F$85*$C$85,(D24*K24)/(1-$N$19-$N$20)/(1-$I$19))) -> 0 | J24: =H24*$I$19 -> 0 | K24: =IF(AND($B$15<$F$2,$E$15<$F$2),D6,IF($B$15<$F$2,J6,G6)) -> 0.498533 | Q24: =IF(AND($B$15<$F$2,$E$15<$F$2),R7,IF($B$15<$F$2,(X7-(X7*H46)),U7)) -> 0.056069101 | R24: =D54*Q24 -> 32.856493
B25: TE - Consumo Intermediário | C25: kWh | D25: =D20 -> 2 | E25: =IFERROR((ROUND(D25*K25,2)+ROUND(G25,2)+ROUND(J25,2))/ROUND(D25,4), 0) -> 0.345 | F25: =ROUND(D25*E25,2) -> 0.69 | G25: =((D25*K25)/(1-$N$19-$N$20))*($N$19+$N$20) -> 0.041086602 | H25: =(IF($I$19=12%,(D25*K25)/(1-$N$19-$N$20)/(1-$C$85)/$F$85*$C$85,(D25*K25)/(1-$N$19-$N$20)/(1-$I$19))) -> 0.2312185 | J25: =H25*$I$19 -> 0.02774622 | K25: =IF(AND($B$15<$F$2,$E$15<$F$2),D8,IF($B$15<$F$2,J8,G8)) -> 0.31241133 | R25: =-R24*H46 -> -19.713896 | S25: Não esta considerando o desconto do reservado.
B26: TE - Consumo Fora Ponta | C26: kWh | D26: =D21 -> 265 | E26: =IFERROR((ROUND(D26*K26,2)+ROUND(G26,2)+ROUND(J26,2))/ROUND(D26,4), 0) -> 0.34683019 | F26: =ROUND(D26*E26,2) -> 91.91 | G26: =((D26*K26)/(1-$N$19-$N$20))*($N$19+$N$20) -> 5.4439747 | H26: =(IF($I$19=12%,(D26*K26)/(1-$N$19-$N$20)/(1-$C$85)/$F$85*$C$85,(D26*K26)/(1-$N$19-$N$20)/(1-$I$19))) -> 30.636451 | J26: =H26*$I$19 -> 3.6763741 | K26: =IF(AND($B$15<$F$2,$E$15<$F$2),D7,IF($B$15<$F$2,J7,G7)) -> 0.31241133 | R26: =SUM(R21:R25) -> 51.129414
B27: TE - Consumo Reservado | C27: kWh | D27: =D22 -> 586 | E27: =IFERROR((ROUND(D27*K27,2)+ROUND(G27,2)+ROUND(J27,2))/ROUND(D27,4), 0) -> 0.1387372 | F27: =ROUND(D27*E27,2) -> 81.3 | G27: =((D27*K27)/(1-$N$19-$N$20))*($N$19+$N$20) -> 4.8153496 | H27: =(IF($I$19=12%,(D27*K27)/(1-$N$19-$N$20)/(1-$C$85)/$F$85*$C$85,(D27*K27)/(1-$N$19-$N$20)/(1-$I$19))) -> 27.098807 | J27: =H27*$I$19 -> 3.2518568 | K27: =ROUND(K26+(K26*(-$H$46)),8) -> 0.12496453
B29: Adicional BAM | C29: kWh | D29: =IF($K$13=M4,(($D$19+$D$20+$D$21+$D$22)*($K$15)/($K$15+$L$15)),0)+IF($L$13=M4,(($D$19+$D$20+$D$21+$D$22)*($L$15)/($K$15+$L$15)),0) -> 853 | E29: =IFERROR((ROUND(D29*K29,2)+ROUND(G29,2)+ROUND(J29,2))/ROUND(D29,4), 0) -> 0.012297773 | F29: =ROUND(D29*E29,2) -> 10.49 | G29: =((D29*K29)/(1-$N$19-$N$20))*($N$19+$N$20) -> 0.62149714 | H29: =(IF($I$19=12%,(D29*K29)/(1-$N$19-$N$20)/(1-$C$85)/$F$85*$C$85,(D29*K29)/(1-$N$19-$N$20)/(1-$I$19))) -> 3.4975303 | J29: =H29*$I$19 -> 0.41970363 | K29: =J62 -> 0.011080176
B30: Adicional BVM 1 | C30: kWh | D30: =IF($K$13=M5,(($D$19+$D$20+$D$21+$D$22)*($K$15)/($K$15+$L$15)),0)+IF($L$13=M5,(($D$19+$D$20+$D$21+$D$22)*($L$15)/($K$15+$L$15)),0) -> 0 | E30: =IFERROR((ROUND(D30*K30,2)+ROUND(G30,2)+ROUND(J30,2))/ROUND(D30,4), 0) -> 0 | F30: =ROUND(D30*E30,2) -> 0 | G30: =((D30*K30)/(1-$N$19-$N$20))*($N$19+$N$20) -> 0 | H30: =(IF($I$19=12%,(D30*K30)/(1-$N$19-$N$20)/(1-$C$85)/$F$85*$C$85,(D30*K30)/(1-$N$19-$N$20)/(1-$I$19))) -> 0 | J30: =H30*$I$19 -> 0 | K30: =J63 -> 0.04463
B31: Adicional BVM 2 | C31: kWh | D31: =IF($K$13=M6,(($D$19+$D$20+$D$21+$D$22)*($K$15)/($K$15+$L$15)),0)+IF($L$13=M6,(($D$19+$D$20+$D$21+$D$22)*($L$15)/($K$15+$L$15)),0) -> 0 | E31: =IFERROR((ROUND(D31*K31,2)+ROUND(G31,2)+ROUND(J31,2))/ROUND(D31,4), 0) -> 0 | F31: =ROUND(D31*E31,2) -> 0 | G31: =((D31*K31)/(1-$N$19-$N$20))*($N$19+$N$20) -> 0 | H31: =(IF($I$19=12%,(D31*K31)/(1-$N$19-$N$20)/(1-$C$85)/$F$85*$C$85,(D31*K31)/(1-$N$19-$N$20)/(1-$I$19))) -> 0 | J31: =H31*$I$19 -> 0 | K31: =J64 -> 0.07877 | AG31: =(D22*K30)/(1-$N$19-$N$20)/(1-$I$19) -> 31.673796
B32: Adicional Escassez | C32: kWh | D32: =IF($K$13=M7,(($D$19+$D$20+$D$21+$D$22)*($K$15)/($K$15+$L$15)),0)+IF($L$13=M7,(($D$19+$D$20+$D$21+$D$22)*($L$15)/($K$15+$L$15)),0) -> 0 | E32: =IFERROR((ROUND(D32*K32,2)+ROUND(G32,2)+ROUND(J32,2))/ROUND(D32,4), 0) -> 0 | F32: =ROUND(D32*E32,2) -> 0 | G32: =((D32*K32)/(1-$N$19-$N$20))*($N$19+$N$20) -> 0 | H32: =(IF($I$19=12%,(D32*K32)/(1-$N$19-$N$20)/(1-$C$85)/$F$85*$C$85,(D32*K32)/(1-$N$19-$N$20)/(1-$I$19))) -> 0 | J32: =H32*$I$19 -> 0 | K32: =J65 -> 0.142
B34: Multas
B35: Juros
B36: Doações
B37: CIP
B40: TOTAL | F40: =SUM(F19:F39) -> 410.18 | G40: =SUM(G19:G39) -> 24.295384 | H40: =SUM(H19:H39) -> 136.72443 | J40: =SUM(J19:J39) -> 16.406932
B42: Informativo Escassez | C42: =D19+D20+D21+D22 -> 853 | D42: =IF(AND($B$15<$F$2,$E$15<$F$2),C9,IF($B$15<$F$2,I9,F9)) -> 0.00018620542 | E42: =IF(AND($B$15<$F$2,$E$15<$F$2),D9,IF($B$15<$F$2,J9,G9)) -> -0.002725567 | F42: =C42*(D42+E42)+((D22*(D42+E42))*(-$H$46)) -> -1.2732359
B44: Desconto Rural Irrigante | F44: =SUM(H55+H68+H69+H70+H71) -> -258.606
G46: desconto: | H46: 0.6
B47: Fatura B2 Rural TB
D48: Qtde | E48: TUSD | F48: TE | G48: TUSD + TE | H48: R$
B49: Fornecimento de Energia Elétrica | H49: =SUM(H51:H60)+SUM(H73:H75) -> 469.98834
B51: Consumo Ponta | D51: =D19 -> 0 | E51: =IF(AND($B$15<$F$2,$E$15<$F$2),C6,IF($B$15<$F$2,I6,F6)) -> 1.0903407 | F51: =IF(AND($B$15<$F$2,$E$15<$F$2),D6,IF($B$15<$F$2,J6,G6)) -> 0.498533 | G51: =E51+F51 -> 1.5888737 | H51: =ROUND((D51*E51),2)+ROUND((D51*F51),2) -> 0
B52: Consumo Fora Ponta | D52: =D21 -> 265 | E52: =IF(AND($B$15<$F$2,$E$15<$F$2),C7,IF($B$15<$F$2,I7,F7)) -> 0.404249 | F52: =IF(AND($B$15<$F$2,$E$15<$F$2),D7,IF($B$15<$F$2,J7,G7)) -> 0.31241133 | G52: =E52+F52 -> 0.71666033 | H52: =ROUND((D52*E52),2)+ROUND((D52*F52),2) -> 189.92
B53: Consumo Intemediário | D53: =D20 -> 2 | E53: =IF(AND($B$15<$F$2,$E$15<$F$2),C8,IF($B$15<$F$2,I8,F8)) -> 0.747297 | F53: =IF(AND($B$15<$F$2,$E$15<$F$2),D8,IF($B$15<$F$2,J8,G8)) -> 0.31241133 | G53: =E53+F53 -> 1.0597083 | H53: =ROUND((D53*E53),2)+ROUND((D53*F53),2) -> 2.11
B54: Consumo reservado | D54: =D22 -> 586 | E54: =E52 -> 0.404249 | F54: =F52 -> 0.31241133 | G54: =E54+F54 -> 0.71666033 | H54: =ROUND((D54*E54),2)+ROUND((D54*F54),2) -> 419.96
B55: Desc reservado | H55: =-H54*$H$46 -> -251.976 | I55: =((D54*E54)-(D54*E54*H46))/D54 -> 0.1616996
B57: Adicional BAM | D57: =IF($K$13=M4,((D51+D52+D53)*(K15)/(K15+L15)),0)+IF($L$13=M4,((D51+D52+D53)*(L15)/(K15+L15)),0) -> 267 | F57: =N4 -> 0.01885 | H57: =ROUND(D57*(E57+F57),2) -> 5.03
B58: Adicional BVM 1 | D58: =IF($K$13=M5,((D51+D52+D53)*(K15)/(K15+L15)),0)+IF($L$13=M5,((D51+D52+D53)*(L15)/(K15+L15)),0) -> 0 | F58: =N5 -> 0.04463 | H58: =ROUND(D58*(E58+F58),2) -> 0
B59: Adicional BVM 2 | D59: =IF($K$13=M6,((D51+D52+D53)*(K15)/(K15+L15)),0)+IF($L$13=M6,((D51+D52+D53)*(L15)/(K15+L15)),0) -> 0 | F59: =N6 -> 0.07877 | H59: =ROUND(D59*(E59+F59),2) -> 0
B60: Adicional Escassez Hídrica | D60: =IF($K$13=M7,((D51+D52+D53)*(K15)/(K15+L15)),0)+IF($L$13=M7,((D51+D52+D53)*(L15)/(K15+L15)),0) -> 0 | F60: =N7 -> 0.142 | H60: =ROUND(D60*(E60+F60),2) -> 0
J61: Tarifa reservada bandeira com desconto
J62: =IFERROR((((D57*F57)+(D63*F63))-(D63*F63*$H$46))/(D57+D63), N4) -> 0.011080176
B63: Adicional BAM PT Reservado | D63: =IF($K$13=M4,(($D$54)*($K$15)/($K$15+$L$15)),0)+IF($L$13=M4,(($D$54)*($L$15)/($K$15+$L$15)),0) -> 586 | F63: =F57 -> 0.01885 | H63: =ROUND(D63*(E63+F63),2) -> 11.05 | J63: =IFERROR((((D58*F58)+(D64*F64))-(D64*F64*$H$46))/(D58+D64), N5) -> 0.04463
B64: Adicional BVM 1 PT Reservado | D64: =IF($K$13=M5,(($D$54)*($K$15)/($K$15+$L$15)),0)+IF($L$13=M5,(($D$54)*($L$15)/($K$15+$L$15)),0) -> 0 | F64: =F58 -> 0.04463 | H64: =ROUND(D64*(E64+F64),2) -> 0 | J64: =IFERROR((((D59*F59)+(D65*F65))-(D65*F65*$H$46))/(D59+D65), N6) -> 0.07877
B65: Adicional BVM 2 PT Reservado | D65: =IF($K$13=M6,(($D$54)*($K$15)/($K$15+$L$15)),0)+IF($L$13=M6,(($D$54)*($L$15)/($K$15+$L$15)),0) -> 0 | F65: =F59 -> 0.07877 | H65: =ROUND(D65*(E65+F65),2) -> 0 | J65: =IFERROR((((D60*F60)+(D66*F66))-(D66*F66*$H$46))/(D60+D66), N7) -> 0.142
B66: Adicional Esc. Hídrica Reserv | D66: =IF($K$13=M7,(($D$54)*($K$15)/($K$15+$L$15)),0)+IF($L$13=M7,(($D$54)*($L$15)/($K$15+$L$15)),0) -> 0 | F66: =F60 -> 0.142 | H66: =ROUND(D66*(E66+F66),2) -> 0
B68: Desc Adicional BAM | H68: =-H63*$H$46 -> -6.63
B69: Desc Adicional BVM 1 | H69: =-H64*$H$46 -> 0
B70: Desc Adicional BVM 2 | H70: =-H65*$H$46 -> 0
B71: Desc Adicional Escassez Hídrica | H71: =-H66*$H$49 -> 0
D72: Base de Cálculo
B73: PIS | D73: =(SUM(H51:H68)/(1-E73-E74)) -> 393.75893 | E73: =N19 -> 0.011 | H73: =D73*E73 -> 4.3313482
B74: COFINS | D74: =D73 -> 393.75893 | E74: =N20 -> 0.0507 | H74: =D74*E74 -> 19.963578
B75: ICMS | D75: =IF((E75=17%),(D73)/(1-E75),D85) -> 474.40834 | E75: 0.17 | H75: =D75*E75 -> 80.649419
B77: Informativo Escassez Hídrica | D77: =SUM(D51:D54) -> 853 | E77: =IF(AND($B$15<$F$2,$E$15<$F$2),C9,IF($B$15<$F$2,I9,F9)) -> 0.00018620542 | F77: =IF(AND($B$15<$F$2,$E$15<$F$2),D9,IF($B$15<$F$2,J9,G9)) -> -0.002725567 | H77: =D77*(E77+F77)+(D54*(E77+F77))*(-H46) -> -1.2732359
B78: Desconto Rural Irrigante | H78: =SUM(H55+H68+H69+H70+H71) -> -258.606 | I78: (mensagem na fatura)
B81: Se for base reduzida: (célula E37 = 12%)
D82: Com tributos
B83: PIS | C83: =E73 -> 0.011 | D83: =SUM(H53:H60)/(1-C83-C84) -> 186.63967 | E83: x | F83: =C83 -> 0.011 | G83: =D83*F83 -> 2.0530363
B84: COFINS | C84: =E74 -> 0.0507 | D84: =D83 -> 186.63967 | E84: x | F84: =C84 -> 0.0507 | G84: =D84*F84 -> 9.4626311
A85: Rural c/ incrição | B85: ICMS | C85: 0.04 | D85: =H85/F85*C85 -> 72.922958 | E85: x | F85: 0.12 | G85: =D85*F85 -> 8.7507549 | H85: =(H51+H52+H53+H57+H58+H59+H60)/(1-E73-E74)/(1-C85) -> 218.76887 | I85: =H85*C85 -> 8.7507549
E86: =(O75)/(1-C83-C84-C85) -> 0
D88: Base de cálculo reduzida = | E88: Importe | G88: = | H88: =H85/F85*C85 -> 72.922958
E89: 12% x 4%
B92: Participação
C93: R$
B94: Energia | C94: =(SUM(H51:H60)*IF($B$15<$F$2,D132,D104)) -> 162.46627
B95: Distribuição | C95: =(SUM(H51:H60)*IF($B$15<$F$2,F132,F104)) -> 95.807064
B96: Transmissão | C96: =(SUM(H51:H60)*IF($B$15<$F$2,E132,E104)) -> 30.874586
B97: Encargos Setoriais | C97: =(SUM(H51:H60)*IF($B$15<$F$2,G132,G104)) -> 75.898089
B98: Impostos / Tributos | C98: =H73+H74+H75 -> 104.94434
B99: Total | C99: =SUM(C94:C98) -> 469.99035
B101: ='B1 (Res) Branca OK'!B76 -> 2024 | D101: Energia | E101: Transmissão | F101: Distribuição | G101: Setoriais
B102: Grupo B | D102: % | E102: % | F102: % | G102: %
B104: B1 - Residencial | D104: ='B1 (Res) Branca OK'!D79 -> 0.45246417 | E104: ='B1 (Res) Branca OK'!E79 -> 0.073959411 | F104: ='B1 (Res) Branca OK'!F79 -> 0.27500913 | G104: ='B1 (Res) Branca OK'!G79 -> 0.19856729
B105: B1 - Residencial Baixa Renda | D105: ='B1 (Res) Branca OK'!D80 -> 0.53149576 | E105: ='B1 (Res) Branca OK'!E80 -> 0.086877849 | F105: ='B1 (Res) Branca OK'!F80 -> 0.32304478 | G105: ='B1 (Res) Branca OK'!G80 -> 0.058581612
B106: B2 - Rural | D106: ='B1 (Res) Branca OK'!D81 -> 0.45246417 | E106: ='B1 (Res) Branca OK'!E81 -> 0.073959411 | F106: ='B1 (Res) Branca OK'!F81 -> 0.27500913 | G106: ='B1 (Res) Branca OK'!G81 -> 0.19856729
B107: B2 - Cooperativa Eletrificação Rural | D107: ='B1 (Res) Branca OK'!D82 -> 0.45246417 | E107: ='B1 (Res) Branca OK'!E82 -> 0.073959411 | F107: ='B1 (Res) Branca OK'!F82 -> 0.27500913 | G107: ='B1 (Res) Branca OK'!G82 -> 0.19856729
B108: B2 - Serviço de Irrigação | D108: ='B1 (Res) Branca OK'!D83 -> 0.45246417 | E108: ='B1 (Res) Branca OK'!E83 -> 0.073959411 | F108: ='B1 (Res) Branca OK'!F83 -> 0.27500913 | G108: ='B1 (Res) Branca OK'!G83 -> 0.19856729
B109: B3 - Demais Classes | D109: ='B1 (Res) Branca OK'!D84 -> 0.45246417 | E109: ='B1 (Res) Branca OK'!E84 -> 0.073959411 | F109: ='B1 (Res) Branca OK'!F84 -> 0.27500913 | G109: ='B1 (Res) Branca OK'!G84 -> 0.19856729
B110: B4 - Iluminação Pública | D110: ='B1 (Res) Branca OK'!D85 -> 0.45246417 | E110: ='B1 (Res) Branca OK'!E85 -> 0.073959411 | F110: ='B1 (Res) Branca OK'!F85 -> 0.27500913 | G110: ='B1 (Res) Branca OK'!G85 -> 0.19856729
B111: B4a - Rede de Distribuição | D111: ='B1 (Res) Branca OK'!D86 -> 0.45246417 | E111: ='B1 (Res) Branca OK'!E86 -> 0.073959411 | F111: ='B1 (Res) Branca OK'!F86 -> 0.27500913 | G111: ='B1 (Res) Branca OK'!G86 -> 0.19856729
B112: B4b - Bulbo de Lâmpada | D112: ='B1 (Res) Branca OK'!D87 -> 0.45246417 | E112: ='B1 (Res) Branca OK'!E87 -> 0.073959411 | F112: ='B1 (Res) Branca OK'!F87 -> 0.27500913 | G112: ='B1 (Res) Branca OK'!G87 -> 0.19856729
B115: ='B1 (Res) Branca OK'!B90 -> 2023 | D115: Energia | E115: Transmissão | F115: Distribuição | G115: Setoriais
B116: Grupo B | D116: % | E116: % | F116: % | G116: %
B118: B1 - Residencial | D118: ='B1 (Res) Branca OK'!D93 -> 0.43939696 | E118: ='B1 (Res) Branca OK'!E93 -> 0.092697586 | F118: ='B1 (Res) Branca OK'!F93 -> 0.25285208 | G118: ='B1 (Res) Branca OK'!G93 -> 0.21506308
B119: B1 - Residencial Baixa Renda | D119: ='B1 (Res) Branca OK'!D94 -> 0.5269162 | E119: ='B1 (Res) Branca OK'!E94 -> 0.11116112 | F119: ='B1 (Res) Branca OK'!F94 -> 0.30321524 | G119: ='B1 (Res) Branca OK'!G94 -> 0.058707433
B120: B2 - Rural | D120: ='B1 (Res) Branca OK'!D95 -> 0.439393 | E120: ='B1 (Res) Branca OK'!E95 -> 0.092696751 | F120: ='B1 (Res) Branca OK'!F95 -> 0.2528498 | G120: ='B1 (Res) Branca OK'!G95 -> 0.21506045
B121: B2 - Cooperativa Eletrificação Rural | D121: ='B1 (Res) Branca OK'!D96 -> 0.439393 | E121: ='B1 (Res) Branca OK'!E96 -> 0.092696751 | F121: ='B1 (Res) Branca OK'!F96 -> 0.2528498 | G121: ='B1 (Res) Branca OK'!G96 -> 0.21506045
B122: B2 - Serviço de Irrigação | D122: ='B1 (Res) Branca OK'!D97 -> 0.439393 | E122: ='B1 (Res) Branca OK'!E97 -> 0.092696751 | F122: ='B1 (Res) Branca OK'!F97 -> 0.2528498 | G122: ='B1 (Res) Branca OK'!G97 -> 0.21506045
B123: B3 - Demais Classes | D123: ='B1 (Res) Branca OK'!D98 -> 0.439393 | E123: ='B1 (Res) Branca OK'!E98 -> 0.092696751 | F123: ='B1 (Res) Branca OK'!F98 -> 0.2528498 | G123: ='B1 (Res) Branca OK'!G98 -> 0.21506045
B124: B4 - Iluminação Pública | D124: ='B1 (Res) Branca OK'!D99 -> 0 | E124: ='B1 (Res) Branca OK'!E99 -> 0 | F124: ='B1 (Res) Branca OK'!F99 -> 0 | G124: ='B1 (Res) Branca OK'!G99 -> 0
...

Sheet B3 Branca OK
B2: B3 | E2: Vigência das Tarifas: | F2: ='B1 (Res) Branca OK'!F2 -> 46241 | H2: TARIFA BRANCA | M2: Bandeira | N2: R$/kWh | Q2: TUSD FIO B
M3: VERDE | N3: ='B1 (Res) Branca OK'!N3 -> 0
B4: TARIFA | C4: ='B1 (Res) Branca OK'!C4 -> TARIFA ANTIGA - REH 3370/2024 | F4: ='B1 (Res) Branca OK'!F4 -> TARIFA NOVA - REH xxxx/2025 | I4: Tarifas Proporcionalizadas | M4: BAM | N4: ='B1 (Res) Branca OK'!N4 -> 0.01885 | Q4: TARIFA | R4: =C4 -> TARIFA ANTIGA - REH 3370/2024 | U4: =F4 -> TARIFA NOVA - REH xxxx/2025 | X4: Tarifas Proporcionalizadas
C5: Tusd | D5: TE | E5: TUSD + TE | F5: Tusd | G5: TE | H5: TUSD + TE | I5: Tusd | J5: TE | K5: TUSD + TE | M5: BVM1 | N5: ='B1 (Res) Branca OK'!N5 -> 0.04463 | R5: Tusd (R$/kWh) | U5: Tusd (R$/kWh) | X5: Tusd (R$/kWh)
B6: B3 Ponta | C6: ='TABELA DE TARIFAS ANTIGAS'!G86/1000 -> 1.06103 | D6: ='TABELA DE TARIFAS ANTIGAS'!H86/1000 -> 0.48448 | E6: =C6+D6 -> 1.54551 | F6: ='TABELA DE TARIFAS NOVAS'!G88/1000 -> 1.12867 | G6: ='TABELA DE TARIFAS NOVAS'!H88/1000 -> 0.51691 | H6: =F6+G6 -> 1.64558 | I6: =((C6*$C$15)+(F6*$D$15))/($D$15+$C$15) -> 1.0925953 | J6: =((D6*$C$15)+(G6*$D$15))/($D$15+$C$15) -> 0.499614 | K6: =I6+J6 -> 1.5922093 | M6: BVM2 | N6: ='B1 (Res) Branca OK'!N6 -> 0.07877 | Q6: =B6 -> B3 Ponta | R6: ='FIO B'!H31/1000 -> 0.69302445 | U6: ='FIO B'!K31/1000 -> 0.71111541 | X6: =((R6*$C$46)+(U6*$D$46))/($D$46+$C$46) -> 0.7014669
B7: B3 Fora Ponta | C7: ='TABELA DE TARIFAS ANTIGAS'!G88/1000 -> 0.38965 | D7: ='TABELA DE TARIFAS ANTIGAS'!H88/1000 -> 0.30579 | E7: =C7+D7 -> 0.69544 | F7: ='TABELA DE TARIFAS NOVAS'!G90/1000 -> 0.42334 | G7: ='TABELA DE TARIFAS NOVAS'!H90/1000 -> 0.32107 | H7: =F7+G7 -> 0.74441 | I7: =((C7*$C$15)+(F7*$D$15))/($D$15+$C$15) -> 0.405372 | J7: =((D7*$C$15)+(G7*$D$15))/($D$15+$C$15) -> 0.31292067 | K7: =I7+J7 -> 0.71829267 | M7: Escassez Hídrica | N7: ='B1 (Res) Branca OK'!N7 -> 0.142 | Q7: =B7 -> B3 Fora Ponta | R7: ='FIO B'!H33/1000 -> 0.13860487 | U7: ='FIO B'!K33/1000 -> 0.14222306 | X7: =((R7*$C$46)+(U7*$D$46))/($D$46+$C$46) -> 0.14029336
B8: B3 Interm. | C8: ='TABELA DE TARIFAS ANTIGAS'!G87/1000 -> 0.72534 | D8: ='TABELA DE TARIFAS ANTIGAS'!H87/1000 -> 0.30579 | E8: =C8+D8 -> 1.03113 | F8: ='TABELA DE TARIFAS NOVAS'!G89/1000 -> 0.77601 | G8: ='TABELA DE TARIFAS NOVAS'!H89/1000 -> 0.32107 | H8: =F8+G8 -> 1.09708 | I8: =((C8*$C$15)+(F8*$D$15))/($D$15+$C$15) -> 0.748986 | J8: =((D8*$C$15)+(G8*$D$15))/($D$15+$C$15) -> 0.31292067 | K8: =I8+J8 -> 1.0619067 | Q8: =B8 -> B3 Interm. | R8: ='FIO B'!H32/1000 -> 0.41581471 | U8: ='FIO B'!K32/1000 -> 0.42666929 | X8: =((R8*$C$46)+(U8*$D$46))/($D$46+$C$46) -> 0.42088018
B9: CDE Escassez Hídrica | C9: ='B1 (Res) Branca OK'!C9 -> 0.00018774721 | D9: ='B1 (Res) Branca OK'!D9 -> -0.0044031307 | E9: =SUM(C9+D9) -> -0.0042153835 | F9: =T13 -> 0.00018418923 | G9: =U13 -> -0.00053182975 | H9: =F9+G9 -> -0.00034764052 | I9: =((C9*$C$15)+(F9*$D$15))/($D$15+$C$15) -> 0.00018608682 | J9: =((D9*$C$15)+(G9*$D$15))/($D$15+$C$15) -> -0.0025965236 | K9: =I9+J9 -> -0.0024104368
P10: CUSTO | R10: Part. TUSD (%) | S10: Part. TE (%) | T10: Tusd (R$/kWh) | U10: TE (R$/kWh)
H11: Fatura | L11: Vigência das Tarifas (troca Bandeira): | M11: =EOMONTH(B15,0)+1 -> 46235 | P11: CDE CONTAS
B12: INSTALAÇÃO | C12: 160008463 | H12: =E15 -> 46254 | K12: Altere a bandeira na célula abaixo | P12: CDE COVID | U12: 0
K13: ='B1 (Res) Branca OK'!K13 -> BAM | L13: ='B1 (Res) Branca OK'!L13 -> BAM | P13: CDE ESCASSEZ HÍDRICA | T13: ='B1 (Res) Branca OK'!T13 -> 0.00018418923 | U13: ='B1 (Res) Branca OK'!U13 -> -0.00053182975
B14: Leitura Anterior | C14: Nº de dias tarifa Anterior | D14: Nº de dias tarifa Nova | E14: Leitura Atual | J14: Leitura Anterior | K14: Nº de dias tarifa Anterior | L14: Nº de dias tarifa Nova | M14: Leitura Atual
B15: 46224 | C15: =IF((F2-B15-1)<0,0,(F2-B15-1)) -> 16 | D15: =E15-F2+1 -> 14 | E15: 46254 | J15: =B15 -> 46224 | K15: =IF((M11-J15-1)<0,0,(M11-J15-1)) -> 10 | L15: =M15-M11+1 -> 20 | M15: =E15 -> 46254 | O15: Documento impressão: | Q15: 1025310394
B17: Descrição | C17: Unidade | D17: Quantidade | E17: Preço Unit (R$) com tributos | F17: Valor Total (R$) | G17: PIS/COFINS (R$) | H17: Base de Cálculo ICMS (R$) | I17: Alíquota ICMS (%) | J17: ICMS (R$) | K17: Preço Unit (R$) | L17: Tributos | M17: Base de Cálc (R$) | N17: Alíquota (%) | O17: Valor (R$)
B19: TUSD - Consumo Ponta | C19: kWh | D19: 19 | E19: =IFERROR((ROUND(D19*K19,2)+ROUND(G19,2)+ROUND(J19,2))/ROUND(D19,4), 0) -> 1.4031579 | F19: =ROUND(D19*E19,2) -> 26.66 | G19: =((D19*K19)/(1-$N$19-$N$20))*($N$19+$N$20) -> 1.3650746 | H19: =ROUND((D19*K19)/(1-$N$19-$N$20)/(1-$I$19),8) -> 26.655887 | I19: 0.17 | J19: =H19*$I$19 -> 4.5315007 | K19: =IF(AND($B$15<$F$2,$E$15<$F$2),C6,IF($B$15<$F$2,I6,F6)) -> 1.0925953 | L19: PIS | M19: =D66 -> 289.87531 | N19: ='B1 (Res) Branca OK'!N19 -> 0.011 | O19: =ROUND(M19*N19,2) -> 3.19 | R19: TUSD Fio B | S19: Receita Fio B
B20: TUSD - Consumo Intermediário | C20: kWh | D20: 16 | E20: =IFERROR((ROUND(D20*K20,2)+ROUND(G20,2)+ROUND(J20,2))/ROUND(D20,4), 0) -> 0.961875 | F20: =ROUND(D20*E20,2) -> 15.39 | G20: =((D20*K20)/(1-$N$19-$N$20))*($N$19+$N$20) -> 0.7880198 | H20: =ROUND((D20*K20)/(1-$N$19-$N$20)/(1-$I$19),8) -> 15.387706 | I20: =I19 -> 0.17 | J20: =H20*$I$19 -> 2.61591 | K20: =IF(AND($B$15<$F$2,$E$15<$F$2),C8,IF($B$15<$F$2,I8,F8)) -> 0.748986 | L20: COFINS | M20: =M19 -> 289.87531 | N20: ='B1 (Res) Branca OK'!N20 -> 0.0507 | O20: =ROUND(M20*N20,2) -> 14.7 | R20: =IF(AND($B$46<$F$2,$E$46<$F$2),R6,IF($B$46<$F$2,X6,U6)) -> 0.7014669 | S20: =D52*R20 -> 13.327871
B21: TUSD - Consumo Fora Ponta | C21: kWh | D21: 304 | E21: =IFERROR((ROUND(D21*K21,2)+ROUND(G21,2)+ROUND(J21,2))/ROUND(D21,4), 0) -> 0.52049342 | F21: =ROUND(D21*E21,2) -> 158.23 | G21: =((D21*K21)/(1-$N$19-$N$20))*($N$19+$N$20) -> 8.1034653 | H21: =ROUND((D21*K21)/(1-$N$19-$N$20)/(1-$I$19),8) -> 158.23681 | I21: =I19 -> 0.17 | J21: =H21*$I$19 -> 26.900258 | K21: =IF(AND($B$15<$F$2,$E$15<$F$2),C7,IF($B$15<$F$2,I7,F7)) -> 0.405372 | R21: =IF(AND($B$46<$F$2,$E$46<$F$2),R7,IF($B$46<$F$2,X7,U7)) -> 0.14029336 | S21: =D53*R21 -> 42.649181
B22: TE - Consumo Ponta | C22: kWh | D22: =D19 -> 19 | E22: =IFERROR((ROUND(D22*K22,2)+ROUND(G22,2)+ROUND(J22,2))/ROUND(D22,4), 0) -> 0.64105263 | F22: =ROUND(D22*E22,2) -> 12.18 | G22: =((D22*K22)/(1-$N$19-$N$20))*($N$19+$N$20) -> 0.62421133 | H22: =(D22*K22)/(1-$N$19-$N$20)/(1-$I$19) -> 12.189009 | J22: =H22*$I$19 -> 2.0721315 | K22: =IF(AND($B$15<$F$2,$E$15<$F$2),D6,IF($B$15<$F$2,J6,G6)) -> 0.499614 | R22: =IF(AND($B$46<$F$2,$E$46<$F$2),R8,IF($B$46<$F$2,X8,U8)) -> 0.42088018 | S22: =D54*R22 -> 6.7340829
B23: TE - Consumo Intermediário | C23: kWh | D23: =D20 -> 16 | E23: =IFERROR((ROUND(D23*K23,2)+ROUND(G23,2)+ROUND(J23,2))/ROUND(D23,4), 0) -> 0.401875 | F23: =ROUND(D23*E23,2) -> 6.43 | G23: =((D23*K23)/(1-$N$19-$N$20))*($N$19+$N$20) -> 0.32922869 | H23: =(D23*K23)/(1-$N$19-$N$20)/(1-$I$19) -> 6.4288667 | J23: =H23*$I$19 -> 1.0929073 | K23: =IF(AND($B$15<$F$2,$E$15<$F$2),D8,IF($B$15<$F$2,J8,G8)) -> 0.31292067 | S23: =SUM(S20:S22) -> 62.711136
B24: TE - Consumo Fora Ponta | C24: kWh | D24: =D21 -> 304 | E24: =IFERROR((ROUND(D24*K24,2)+ROUND(G24,2)+ROUND(J24,2))/ROUND(D24,4), 0) -> 0.40184211 | F24: =ROUND(D24*E24,2) -> 122.16 | G24: =((D24*K24)/(1-$N$19-$N$20))*($N$19+$N$20) -> 6.2553452 | H24: =(D24*K24)/(1-$N$19-$N$20)/(1-$I$19) -> 122.14847 | J24: =H24*$I$19 -> 20.765239 | K24: =IF(AND($B$15<$F$2,$E$15<$F$2),D7,IF($B$15<$F$2,J7,G7)) -> 0.31292067
B25: Adicional BAM | C25: kWh | D25: =IF($K$13=M4,(($D$19+$D$20+$D$21)*($K$15)/($K$15+$L$15)),0)+IF($L$13=M4,(($D$19+$D$20+$D$21)*($L$15)/($K$15+$L$15)),0) -> 339 | E25: =IFERROR((ROUND(D25*K25,2)+ROUND(G25,2)+ROUND(J25,2))/ROUND(D25,4), 0) -> 0.024188791 | F25: =ROUND(D25*E25,2) -> 8.2 | G25: =((D25*K25)/(1-$N$19-$N$20))*($N$19+$N$20) -> 0.4201985 | H25: =(D25*K25)/(1-$N$19-$N$20)/(1-$I$19) -> 8.2052392 | J25: =H25*$I$19 -> 1.3948907 | K25: =N4 -> 0.01885
B26: Adicional BVM 1 | C26: kWh | D26: =IF($K$13=M5,(($D$19+$D$20+$D$21)*($K$15)/($K$15+$L$15)),0)+IF($L$13=M5,(($D$19+$D$20+$D$21)*($L$15)/($K$15+$L$15)),0) -> 0 | E26: =K26/(1-$N$19-$N$20)/(1-$I$19) -> 0.057306921 | F26: =ROUND(D26*E26,2) -> 0 | G26: =((D26*K26)/(1-$N$19-$N$20))*($N$19+$N$20) -> 0 | H26: =(D26*K26)/(1-$N$19-$N$20)/(1-$I$19) -> 0 | J26: =H26*$I$19 -> 0 | K26: =N5 -> 0.04463
B27: Adicional BVM 2 | C27: kWh | D27: =IF($K$13=M6,(($D$19+$D$20+$D$21)*($K$15)/($K$15+$L$15)),0)+IF($L$13=M6,(($D$19+$D$20+$D$21)*($L$15)/($K$15+$L$15)),0) -> 0 | E27: =K27/(1-$N$19-$N$20)/(1-$I$19) -> 0.10114421 | F27: =ROUND(D27*E27,2) -> 0 | G27: =((D27*K27)/(1-$N$19-$N$20))*($N$19+$N$20) -> 0 | H27: =(D27*K27)/(1-$N$19-$N$20)/(1-$I$19) -> 0 | J27: =H27*$I$19 -> 0 | K27: =N6 -> 0.07877
B28: Adicional Escassez | C28: kWh | D28: =IF($K$13=M7,(($D$19+$D$20+$D$21)*($K$15)/($K$15+$L$15)),0)+IF($L$13=M7,(($D$19+$D$20+$D$21)*($L$15)/($K$15+$L$15)),0) -> 0 | E28: =K28/(1-$N$19-$N$20)/(1-$I$19) -> 0.18233437 | F28: =ROUND(D28*E28,2) -> 0 | G28: =((D28*K28)/(1-$N$19-$N$20))*($N$19+$N$20) -> 0 | H28: =(D28*K28)/(1-$N$19-$N$20)/(1-$I$19) -> 0 | J28: =H28*$I$19 -> 0 | K28: =N7 -> 0.142
B29: Multas
B30: Juros
B31: Doações
B32: CIP | F32: 61.03
B35: TOTAL | F35: =SUM(F19:F34) -> 410.28 | G35: =SUM(G19:G34) -> 17.885543 | H35: =SUM(H19:H34) -> 349.25199 | J35: =SUM(J19:J34) -> 59.372838
B37: Informativo Escassez | C37: =D19+D20+D21 -> 339 | D37: =IF(AND($B$15<$F$2,$E$15<$F$2),C9,IF($B$15<$F$2,I9,F9)) -> 0.00018608682 | E37: =IF(AND($B$15<$F$2,$E$15<$F$2),D9,IF($B$15<$F$2,J9,G9)) -> -0.0025965236 | F37: =C37*(D37+E37) -> -0.81713807
H42: Fatura | L42: Vigência das Tarifas (troca Bandeira): | M42: =EOMONTH(B46,0)+1 -> 46235
B43: INSTALAÇÃO | C43: =C12 -> 160008463 | H43: =E46 -> 46254 | K43: Altere a bandeira na célula abaixo
K44: =K13 -> BAM | L44: =L13 -> BAM
B45: Leitura Anterior | C45: Nº de dias tarifa Anterior | D45: Nº de dias tarifa Nova | E45: Leitura Atual | J45: Leitura Anterior | K45: Nº de dias tarifa Anterior | L45: Nº de dias tarifa Nova | M45: Leitura Atual
B46: =B15 -> 46224 | C46: =IF((F2-B46-1)<0,0,(F2-B46-1)) -> 16 | D46: =E46-F2+1 -> 14 | E46: =E15 -> 46254 | J46: =B46 -> 46224 | K46: =IF((M42-J46-1)<0,0,(M42-J46-1)) -> 10 | L46: =M46-M42+1 -> 20 | M46: =E46 -> 46254
B48: Fatura B3 - TB
D49: Qtde | E49: TUSD | F49: TE | G49: TUSD + TE | H49: R$
B50: Fornecimento de Energia Elétrica | H50: =SUM(H52:H60)+SUM(H66:H68) -> 349.24736
B52: Consumo Ponta | D52: =D19 -> 19 | E52: =IF(AND($B$46<$F$2,$E$46<$F$2),C6,IF($B$46<$F$2,I6,F6)) -> 1.0925953 | F52: =IF(AND($B$46<$F$2,$E$46<$F$2),D6,IF($B$46<$F$2,J6,G6)) -> 0.499614 | G52: 1.325 | H52: =ROUND((D52*E52),2)+ROUND((D52*F52),2) -> 30.25
B53: Consumo Fora Ponta | D53: =D21 -> 304 | E53: =IF(AND($B$46<$F$2,$E$46<$F$2),C7,IF($B$46<$F$2,I7,F7)) -> 0.405372 | F53: =IF(AND($B$46<$F$2,$E$46<$F$2),D7,IF($B$46<$F$2,J7,G7)) -> 0.31292067 | G53: 0.5328 | H53: =ROUND((D53*E53),2)+ROUND((D53*F53),2) -> 218.36
B54: Consumo Intemediário | D54: =D20 -> 16 | E54: =IF(AND($B$46<$F$2,$E$46<$F$2),C8,IF($B$46<$F$2,I8,F8)) -> 0.748986 | F54: =IF(AND($B$46<$F$2,$E$46<$F$2),D8,IF($B$46<$F$2,J8,G8)) -> 0.31292067 | G54: 0.84406 | H54: =ROUND((D54*E54),2)+ROUND((D54*F54),2) -> 16.99
B57: Adicional BAM | D57: =IF($K$44=M4,((D52+D53+D54)*(K46)/(K46+L46)),0)+IF($L$44=M4,((D52+D53+D54)*(L46)/(K46+L46)),0) -> 339 | F57: =N4 -> 0.01885 | H57: =ROUND(D57*(E57+F57),2) -> 6.39
B58: Adicional BVM 1 | D58: =IF($K$44=M5,((D52+D53+D54)*(K46)/(K46+L46)),0)+IF($L$44=M5,((D52+D53+D54)*(L46)/(K46+L46)),0) -> 0 | F58: =N5 -> 0.04463 | H58: =ROUND(D58*(E58+F58),2) -> 0
B59: Adicional BVM 2 | D59: =IF($K$44=M6,((D52+D53+D54)*(K46)/(K46+L46)),0)+IF($L$44=M6,((D52+D53+D54)*(L46)/(K46+L46)),0) -> 0 | F59: =N6 -> 0.07877 | H59: =ROUND(D59*(E59+F59),2) -> 0
B60: Adicional Escassez Hídrica | D60: =IF($K$44=M7,((D52+D53+D54)*(K46)/(K46+L46)),0)+IF($L$44=M7,((D52+D53+D54)*(L46)/(K46+L46)),0) -> 0 | F60: =N7 -> 0.142 | H60: =ROUND(D60*(E60+F60),2) -> 0
D65: Base de Cálculo
B66: PIS | D66: =(SUM(H52:H63)/(1-E66-E67)) -> 289.87531 | E66: =N19 -> 0.011 | H66: =D66*E66 -> 3.1886284
B67: COFINS | D67: =D66 -> 289.87531 | E67: =N20 -> 0.0507 | H67: =D67*E67 -> 14.696678
B68: ICMS | D68: =D66/(1-E68) -> 349.24736 | E68: =I19 -> 0.17 | H68: =D68*E68 -> 59.372051
B70: Informativo Escassez Hídrica | D70: =SUM(D52:D54) -> 339 | E70: =IF(AND($B$46<$F$2,$E$46<$F$2),C9,IF($B$46<$F$2,I9,F9)) -> 0.00018608682 | F70: =IF(AND($B$46<$F$2,$E$46<$F$2),D9,IF($B$46<$F$2,J9,G9)) -> -0.0025965236 | H70: =D70*(E70+F70) -> -0.81713807
B72: Participação
C73: R$
B74: Energia | C74: =(SUM(H52:H63)*IF($B$46<$F$2,D112,D84)) -> 121.17018
B75: Distribuição | C75: =(SUM(H52:H63)*IF($B$46<$F$2,F112,F84)) -> 71.585602
B76: Transmissão | C76: =(SUM(H52:H63)*IF($B$46<$F$2,E112,E84)) -> 22.834405
B77: Encargos Setoriais | C77: =(SUM(H52:H63)*IF($B$46<$F$2,G112,G84)) -> 56.401219
B78: Impostos / Tributos | C78: =H66+H67+H68 -> 77.257357
B79: Total | C79: =SUM(C74:C78) -> 349.24877
B81: ='B1 (Res) Branca OK'!B76 -> 2024 | D81: Energia | E81: Transmissão | F81: Distribuição | G81: Setoriais
B82: Grupo B | D82: % | E82: % | F82: % | G82: %
B84: B1 - Residencial | D84: ='B1 (Res) Branca OK'!D79 -> 0.45246417 | E84: ='B1 (Res) Branca OK'!E79 -> 0.073959411 | F84: ='B1 (Res) Branca OK'!F79 -> 0.27500913 | G84: ='B1 (Res) Branca OK'!G79 -> 0.19856729
B85: B1 - Residencial Baixa Renda | D85: ='B1 (Res) Branca OK'!D80 -> 0.53149576 | E85: ='B1 (Res) Branca OK'!E80 -> 0.086877849 | F85: ='B1 (Res) Branca OK'!F80 -> 0.32304478 | G85: ='B1 (Res) Branca OK'!G80 -> 0.058581612
B86: B2 - Rural | D86: ='B1 (Res) Branca OK'!D81 -> 0.45246417 | E86: ='B1 (Res) Branca OK'!E81 -> 0.073959411 | F86: ='B1 (Res) Branca OK'!F81 -> 0.27500913 | G86: ='B1 (Res) Branca OK'!G81 -> 0.19856729
B87: B2 - Cooperativa Eletrificação Rural | D87: ='B1 (Res) Branca OK'!D82 -> 0.45246417 | E87: ='B1 (Res) Branca OK'!E82 -> 0.073959411 | F87: ='B1 (Res) Branca OK'!F82 -> 0.27500913 | G87: ='B1 (Res) Branca OK'!G82 -> 0.19856729
B88: B2 - Serviço de Irrigação | D88: ='B1 (Res) Branca OK'!D83 -> 0.45246417 | E88: ='B1 (Res) Branca OK'!E83 -> 0.073959411 | F88: ='B1 (Res) Branca OK'!F83 -> 0.27500913 | G88: ='B1 (Res) Branca OK'!G83 -> 0.19856729
B89: B3 - Demais Classes | D89: ='B1 (Res) Branca OK'!D84 -> 0.45246417 | E89: ='B1 (Res) Branca OK'!E84 -> 0.073959411 | F89: ='B1 (Res) Branca OK'!F84 -> 0.27500913 | G89: ='B1 (Res) Branca OK'!G84 -> 0.19856729
B90: B4 - Iluminação Pública | D90: ='B1 (Res) Branca OK'!D85 -> 0.45246417 | E90: ='B1 (Res) Branca OK'!E85 -> 0.073959411 | F90: ='B1 (Res) Branca OK'!F85 -> 0.27500913 | G90: ='B1 (Res) Branca OK'!G85 -> 0.19856729
B91: B4a - Rede de Distribuição | D91: ='B1 (Res) Branca OK'!D86 -> 0.45246417 | E91: ='B1 (Res) Branca OK'!E86 -> 0.073959411 | F91: ='B1 (Res) Branca OK'!F86 -> 0.27500913 | G91: ='B1 (Res) Branca OK'!G86 -> 0.19856729
B92: B4b - Bulbo de Lâmpada | D92: ='B1 (Res) Branca OK'!D87 -> 0.45246417 | E92: ='B1 (Res) Branca OK'!E87 -> 0.073959411 | F92: ='B1 (Res) Branca OK'!F87 -> 0.27500913 | G92: ='B1 (Res) Branca OK'!G87 -> 0.19856729
B95: ='B1 (Res) Branca OK'!B90 -> 2023 | D95: Energia | E95: Transmissão | F95: Distribuição | G95: Setoriais
B96: Grupo B | D96: % | E96: % | F96: % | G96: %
B98: B1 - Residencial | D98: ='B1 (Res) Branca OK'!D93 -> 0.43939696 | E98: ='B1 (Res) Branca OK'!E93 -> 0.092697586 | F98: ='B1 (Res) Branca OK'!F93 -> 0.25285208 | G98: ='B1 (Res) Branca OK'!G93 -> 0.21506308
B99: B1 - Residencial Baixa Renda | D99: ='B1 (Res) Branca OK'!D94 -> 0.5269162 | E99: ='B1 (Res) Branca OK'!E94 -> 0.11116112 | F99: ='B1 (Res) Branca OK'!F94 -> 0.30321524 | G99: ='B1 (Res) Branca OK'!G94 -> 0.058707433
B100: B2 - Rural | D100: ='B1 (Res) Branca OK'!D95 -> 0.439393 | E100: ='B1 (Res) Branca OK'!E95 -> 0.092696751 | F100: ='B1 (Res) Branca OK'!F95 -> 0.2528498 | G100: ='B1 (Res) Branca OK'!G95 -> 0.21506045
B101: B2 - Cooperativa Eletrificação Rural | D101: ='B1 (Res) Branca OK'!D96 -> 0.439393 | E101: ='B1 (Res) Branca OK'!E96 -> 0.092696751 | F101: ='B1 (Res) Branca OK'!F96 -> 0.2528498 | G101: ='B1 (Res) Branca OK'!G96 -> 0.21506045
B102: B2 - Serviço de Irrigação | D102: ='B1 (Res) Branca OK'!D97 -> 0.439393 | E102: ='B1 (Res) Branca OK'!E97 -> 0.092696751 | F102: ='B1 (Res) Branca OK'!F97 -> 0.2528498 | G102: ='B1 (Res) Branca OK'!G97 -> 0.21506045
B103: B3 - Demais Classes | D103: ='B1 (Res) Branca OK'!D98 -> 0.439393 | E103: ='B1 (Res) Branca OK'!E98 -> 0.092696751 | F103: ='B1 (Res) Branca OK'!F98 -> 0.2528498 | G103: ='B1 (Res) Branca OK'!G98 -> 0.21506045
B104: B4 - Iluminação Pública | D104: ='B1 (Res) Branca OK'!D99 -> 0 | E104: ='B1 (Res) Branca OK'!E99 -> 0 | F104: ='B1 (Res) Branca OK'!F99 -> 0 | G104: ='B1 (Res) Branca OK'!G99 -> 0
B105: B4a - Rede de Distribuição | D105: ='B1 (Res) Branca OK'!D100 -> 0.43938946 | E105: ='B1 (Res) Branca OK'!E100 -> 0.092697337 | F105: ='B1 (Res) Branca OK'!F100 -> 0.2528514 | G105: ='B1 (Res) Branca OK'!G100 -> 0.21506181
B106: B4b - Bulbo de Lâmpada | D106: ='B1 (Res) Branca OK'!D101 -> 0.43938946 | E106: ='B1 (Res) Branca OK'!E101 -> 0.092697337 | F106: ='B1 (Res) Branca OK'!F101 -> 0.2528514 | G106: ='B1 (Res) Branca OK'!G101 -> 0.21506181
B108: proporcional
D109: Energia | E109: Transmissão | F109: Distribuição | G109: Setoriais
B110: Grupo B | D110: % | E110: % | F110: % | G110: %
B112: B1 - Residencial | D112: =((D98*$C$46)+(D84*$D$46))/($C$46+$D$46) -> 0.44549499 | E112: =((E98*$C$46)+(E84*$D$46))/($C$46+$D$46) -> 0.083953104 | F112: =((F98*$C$46)+(F84*$D$46))/($C$46+$D$46) -> 0.26319204 | G112: =((G98*$C$46)+(G84*$D$46))/($C$46+$D$46) -> 0.20736505
B113: B1 - Residencial Baixa Renda | D113: =((D99*$C$46)+(D85*$D$46))/($C$46+$D$46) -> 0.52905333 | E113: =((E99*$C$46)+(E85*$D$46))/($C$46+$D$46) -> 0.099828928 | F113: =((F99*$C$46)+(F85*$D$46))/($C$46+$D$46) -> 0.31246903 | G113: =((G99*$C$46)+(G85*$D$46))/($C$46+$D$46) -> 0.058648717
B114: B2 - Rural | D114: =((D100*$C$46)+(D86*$D$46))/($C$46+$D$46) -> 0.44549288 | E114: =((E100*$C$46)+(E86*$D$46))/($C$46+$D$46) -> 0.083952659 | F114: =((F100*$C$46)+(F86*$D$46))/($C$46+$D$46) -> 0.26319082 | G114: =((G100*$C$46)+(G86*$D$46))/($C$46+$D$46) -> 0.20736364
B115: B2 - Cooperativa Eletrificação Rural | D115: =((D101*$C$46)+(D87*$D$46))/($C$46+$D$46) -> 0.44549288 | E115: =((E101*$C$46)+(E87*$D$46))/($C$46+$D$46) -> 0.083952659 | F115: =((F101*$C$46)+(F87*$D$46))/($C$46+$D$46) -> 0.26319082 | G115: =((G101*$C$46)+(G87*$D$46))/($C$46+$D$46) -> 0.20736364
B116: B2 - Serviço de Irrigação | D116: =((D102*$C$46)+(D88*$D$46))/($C$46+$D$46) -> 0.44549288 | E116: =((E102*$C$46)+(E88*$D$46))/($C$46+$D$46) -> 0.083952659 | F116: =((F102*$C$46)+(F88*$D$46))/($C$46+$D$46) -> 0.26319082 | G116: =((G102*$C$46)+(G88*$D$46))/($C$46+$D$46) -> 0.20736364
B117: B3 - Demais Classes | D117: =((D103*$C$46)+(D89*$D$46))/($C$46+$D$46) -> 0.44549288 | E117: =((E103*$C$46)+(E89*$D$46))/($C$46+$D$46) -> 0.083952659 | F117: =((F103*$C$46)+(F89*$D$46))/($C$46+$D$46) -> 0.26319082 | G117: =((G103*$C$46)+(G89*$D$46))/($C$46+$D$46) -> 0.20736364
B118: B4 - Iluminação Pública | D118: =((D104*$C$46)+(D90*$D$46))/($C$46+$D$46) -> 0.21114994 | E118: =((E104*$C$46)+(E90*$D$46))/($C$46+$D$46) -> 0.034514392 | F118: =((F104*$C$46)+(F90*$D$46))/($C$46+$D$46) -> 0.1283376 | G118: =((G104*$C$46)+(G90*$D$46))/($C$46+$D$46) -> 0.092664735
B119: B4a - Rede de Distribuição | D119: =((D105*$C$46)+(D91*$D$46))/($C$46+$D$46) -> 0.44549099 | E119: =((E105*$C$46)+(E91*$D$46))/($C$46+$D$46) -> 0.083952971 | F119: =((F105*$C$46)+(F91*$D$46))/($C$46+$D$46) -> 0.26319168 | G119: =((G105*$C$46)+(G91*$D$46))/($C$46+$D$46) -> 0.20736437
B120: B4b - Bulbo de Lâmpada | D120: =((D106*$C$46)+(D92*$D$46))/($C$46+$D$46) -> 0.44549099 | E120: =((E106*$C$46)+(E92*$D$46))/($C$46+$D$46) -> 0.083952971 | F120: =((F106*$C$46)+(F92*$D$46))/($C$46+$D$46) -> 0.26319168 | G120: =((G106*$C$46)+(G92*$D$46))/($C$46+$D$46) -> 0.20736437

Sheet B3 PPF Branca OK
B2: B3 | E2: Vigência das Tarifas: | F2: ='B1 (Res) Branca OK'!F2 -> 46241 | H2: TARIFA BRANCA | M2: Bandeira | N2: R$/kWh | Q2: TUSD FIO B
M3: VERDE | N3: ='B1 (Res) Branca OK'!N3 -> 0
B4: TARIFA | C4: ='B1 (Res) Branca OK'!C4 -> TARIFA ANTIGA - REH 3370/2024 | F4: ='B1 (Res) Branca OK'!F4 -> TARIFA NOVA - REH xxxx/2025 | I4: Tarifas Proporcionalizadas | M4: BAM | N4: ='B1 (Res) Branca OK'!N4 -> 0.01885 | Q4: TARIFA | R4: =C4 -> TARIFA ANTIGA - REH 3370/2024 | U4: =F4 -> TARIFA NOVA - REH xxxx/2025 | X4: Tarifas Proporcionalizadas
C5: Tusd | D5: TE | E5: TUSD + TE | F5: Tusd | G5: TE | H5: TUSD + TE | I5: Tusd | J5: TE | K5: TUSD + TE | M5: BVM1 | N5: ='B1 (Res) Branca OK'!N5 -> 0.04463 | R5: Tusd (R$/kWh) | U5: Tusd (R$/kWh) | X5: Tusd (R$/kWh)
B6: B3 Ponta | C6: ='TABELA DE TARIFAS ANTIGAS'!G86/1000 -> 1.06103 | D6: ='TABELA DE TARIFAS ANTIGAS'!H86/1000 -> 0.48448 | E6: =C6+D6 -> 1.54551 | F6: ='TABELA DE TARIFAS NOVAS'!G88/1000 -> 1.12867 | G6: ='TABELA DE TARIFAS NOVAS'!H88/1000 -> 0.51691 | H6: =F6+G6 -> 1.64558 | I6: =((C6*$C$50)+(F6*$D$50))/($D$50+$C$50) -> 1.0903407 | J6: =((D6*$C$50)+(G6*$D$50))/($D$50+$C$50) -> 0.498533 | K6: =I6+J6 -> 1.5888737 | M6: BVM2 | N6: ='B1 (Res) Branca OK'!N6 -> 0.07877 | Q6: =B6 -> B3 Ponta | R6: ='FIO B'!H31/1000 -> 0.69302445 | U6: ='FIO B'!K31/1000 -> 0.71111541 | X6: =((R6*$C$50)+(U6*$D$50))/($D$50+$C$50) -> 0.70086387
B7: B3 Fora Ponta | C7: ='TABELA DE TARIFAS ANTIGAS'!G88/1000 -> 0.38965 | D7: ='TABELA DE TARIFAS ANTIGAS'!H88/1000 -> 0.30579 | E7: =C7+D7 -> 0.69544 | F7: ='TABELA DE TARIFAS NOVAS'!G90/1000 -> 0.42334 | G7: ='TABELA DE TARIFAS NOVAS'!H90/1000 -> 0.32107 | H7: =F7+G7 -> 0.74441 | I7: =((C7*$C$50)+(F7*$D$50))/($D$50+$C$50) -> 0.404249 | J7: =((D7*$C$50)+(G7*$D$50))/($D$50+$C$50) -> 0.31241133 | K7: =I7+J7 -> 0.71666033 | M7: Escassez Hídrica | N7: ='B1 (Res) Branca OK'!N7 -> 0.142 | Q7: =B7 -> B3 Fora Ponta | R7: ='FIO B'!H33/1000 -> 0.13860487 | U7: ='FIO B'!K33/1000 -> 0.14222306 | X7: =((R7*$C$50)+(U7*$D$50))/($D$50+$C$50) -> 0.14017275
B8: B3 Interm. | C8: ='TABELA DE TARIFAS ANTIGAS'!G87/1000 -> 0.72534 | D8: ='TABELA DE TARIFAS ANTIGAS'!H87/1000 -> 0.30579 | E8: =C8+D8 -> 1.03113 | F8: ='TABELA DE TARIFAS NOVAS'!G89/1000 -> 0.77601 | G8: ='TABELA DE TARIFAS NOVAS'!H89/1000 -> 0.32107 | H8: =F8+G8 -> 1.09708 | I8: =((C8*$C$50)+(F8*$D$50))/($D$50+$C$50) -> 0.747297 | J8: =((D8*$C$50)+(G8*$D$50))/($D$50+$C$50) -> 0.31241133 | K8: =I8+J8 -> 1.0597083 | Q8: =B8 -> B3 Interm. | R8: ='FIO B'!H32/1000 -> 0.41581471 | U8: ='FIO B'!K32/1000 -> 0.42666929 | X8: =((R8*$C$50)+(U8*$D$50))/($D$50+$C$50) -> 0.42051836
B9: CDE Escassez Hídrica | C9: ='B1 (Res) Branca OK'!C9 -> 0.00018774721 | D9: ='B1 (Res) Branca OK'!D9 -> -0.0044031307 | E9: =SUM(C9+D9) -> -0.0042153835 | F9: =T13 -> 0.00018418923 | G9: =U13 -> -0.00053182975 | H9: =F9+G9 -> -0.00034764052 | I9: =((C9*$C$50)+(F9*$D$50))/($D$50+$C$50) -> 0.00018620542 | J9: =((D9*$C$50)+(G9*$D$50))/($D$50+$C$50) -> -0.002725567 | K9: =I9+J9 -> -0.0025393616
P10: CUSTO | R10: Part. TUSD (%) | S10: Part. TE (%) | T10: Tusd (R$/kWh) | U10: TE (R$/kWh)
H11: Fatura | L11: Vigência das Tarifas (troca Bandeira): | M11: =EOMONTH(B15,0)+1 -> 46235 | P11: CDE CONTAS
B12: INSTALAÇÃO | C12: 475728 | H12: =E15 -> 46253 | K12: Altere a bandeira na célula abaixo | P12: CDE COVID | U12: 0
K13: ='B2 (Rural) Branca OK'!K13 -> BAM | L13: ='B1 (Res) Branca OK'!L13 -> BAM | P13: CDE ESCASSEZ HÍDRICA | T13: ='B1 (Res) Branca OK'!T13 -> 0.00018418923 | U13: ='B1 (Res) Branca OK'!U13 -> -0.00053182975
B14: Leitura Anterior | C14: Nº de dias tarifa Anterior | D14: Nº de dias tarifa Nova | E14: Leitura Atual | J14: Leitura Anterior | K14: Nº de dias tarifa Anterior | L14: Nº de dias tarifa Nova | M14: Leitura Atual
B15: 46223 | C15: =IF((F2-B15-1)<0,0,(F2-B15-1)) -> 17 | D15: =E15-F2+1 -> 13 | E15: 46253 | J15: =B15 -> 46223 | K15: =IF((M11-J15-1)<0,0,(M11-J15-1)) -> 11 | L15: =M15-M11+1 -> 19 | M15: =E15 -> 46253
P16: Documento simulado: | R16: 1025310395
B17: Descrição | C17: Unidade | D17: Quantidade | E17: Preço Unit (R$) com tributos | F17: Valor Total (R$) | G17: PIS/COFINS (R$) | H17: Base de Cálculo ICMS (R$) | I17: Alíquota ICMS (%) | J17: ICMS (R$) | K17: Preço Unit (R$) | L17: Tributos | M17: Base de Cálc (R$) | N17: Alíquota (%) | O17: Valor (R$)
B19: TUSD - Consumo Ponta | C19: kWh | D19: 33 | E19: =IFERROR((ROUND(D19*K19,2)+ROUND(G19,2)+ROUND(J19,2))/ROUND(D19,4), 0) -> 1.4 | F19: =ROUND(D19*E19,2) -> 46.2 | G19: =((D19*K19)/(1-$N$19-$N$20))*($N$19+$N$20) -> 2.3660265 | H19: =ROUND((D19*K19)/(1-$N$19-$N$20)/(1-$I$19),8) -> 46.201528 | I19: 0.17 | J19: =H19*$I$19 -> 7.8542598 | K19: =IF(AND($B$15<$F$2,$E$15<$F$2),C6,IF($B$15<$F$2,I6,F6)) -> 1.0903407 | L19: PIS | M19: =D70 -> 228.62624 | N19: ='B1 (Res) Branca OK'!N19 -> 0.011 | O19: =ROUND(M19*N19,2) -> 2.51 | R19: TUSD Fio B | S19: Receita Fio B
B20: TUSD - Consumo Intermediário | C20: kWh | D20: 14 | E20: =IFERROR((ROUND(D20*K20,2)+ROUND(G20,2)+ROUND(J20,2))/ROUND(D20,4), 0) -> 0.95928571 | F20: =ROUND(D20*E20,2) -> 13.43 | G20: =((D20*K20)/(1-$N$19-$N$20))*($N$19+$N$20) -> 0.68796243 | H20: =ROUND((D20*K20)/(1-$N$19-$N$20)/(1-$I$19),8) -> 13.43388 | I20: =I19 -> 0.17 | J20: =H20*$I$19 -> 2.2837596 | K20: =IF(AND($B$15<$F$2,$E$15<$F$2),C8,IF($B$15<$F$2,I8,F8)) -> 0.747297 | L20: COFINS | M20: =M19 -> 228.62624 | N20: ='B1 (Res) Branca OK'!N20 -> 0.0507 | O20: =ROUND(M20*N20,2) -> 11.59 | R20: =IF(AND($B$50<$F$2,$E$50<$F$2),R6,IF($B$50<$F$2,X6,U6)) -> 0.70086387 | S20: =D56*R20 -> 23.128508
B21: TUSD - Consumo Fora Ponta | C21: kWh | D21: 199 | E21: =IFERROR((ROUND(D21*K21,2)+ROUND(G21,2)+ROUND(J21,2))/ROUND(D21,4), 0) -> 0.51909548 | F21: =ROUND(D21*E21,2) -> 103.3 | G21: =((D21*K21)/(1-$N$19-$N$20))*($N$19+$N$20) -> 5.2898758 | H21: =ROUND((D21*K21)/(1-$N$19-$N$20)/(1-$I$19),8) -> 103.29569 | I21: =I19 -> 0.17 | J21: =H21*$I$19 -> 17.560268 | K21: =IF(AND($B$15<$F$2,$E$15<$F$2),C7,IF($B$15<$F$2,I7,F7)) -> 0.404249 | R21: =IF(AND($B$50<$F$2,$E$50<$F$2),R7,IF($B$50<$F$2,X7,U7)) -> 0.14017275 | S21: =D57*R21 -> 27.894378
B22: TE - Consumo Ponta | C22: kWh | D22: =D19 -> 33 | E22: =IFERROR((ROUND(D22*K22,2)+ROUND(G22,2)+ROUND(J22,2))/ROUND(D22,4), 0) -> 0.64 | F22: =ROUND(D22*E22,2) -> 21.12 | G22: =((D22*K22)/(1-$N$19-$N$20))*($N$19+$N$20) -> 1.0818108 | H22: =(D22*K22)/(1-$N$19-$N$20)/(1-$I$19) -> 21.124578 | J22: =H22*$I$19 -> 3.5911783 | K22: =IF(AND($B$15<$F$2,$E$15<$F$2),D6,IF($B$15<$F$2,J6,G6)) -> 0.498533 | R22: =IF(AND($B$50<$F$2,$E$50<$F$2),R8,IF($B$50<$F$2,X8,U8)) -> 0.42051836 | S22: =D58*R22 -> 5.8872571
B23: TE - Consumo Intermediário | C23: kWh | D23: =D20 -> 14 | E23: =IFERROR((ROUND(D23*K23,2)+ROUND(G23,2)+ROUND(J23,2))/ROUND(D23,4), 0) -> 0.40071429 | F23: =ROUND(D23*E23,2) -> 5.61 | G23: =((D23*K23)/(1-$N$19-$N$20))*($N$19+$N$20) -> 0.28760621 | H23: =(D23*K23)/(1-$N$19-$N$20)/(1-$I$19) -> 5.6161023 | J23: =H23*$I$19 -> 0.95473739 | K23: =IF(AND($B$15<$F$2,$E$15<$F$2),D8,IF($B$15<$F$2,J8,G8)) -> 0.31241133 | S23: =SUM(S20:S22) -> 56.910143
B24: TE - Consumo Fora Ponta | C24: kWh | D24: =D21 -> 199 | E24: =IFERROR((ROUND(D24*K24,2)+ROUND(G24,2)+ROUND(J24,2))/ROUND(D24,4), 0) -> 0.40115578 | F24: =ROUND(D24*E24,2) -> 79.83 | G24: =((D24*K24)/(1-$N$19-$N$20))*($N$19+$N$20) -> 4.0881169 | H24: =(D24*K24)/(1-$N$19-$N$20)/(1-$I$19) -> 79.828882 | J24: =H24*$I$19 -> 13.57091 | K24: =IF(AND($B$15<$F$2,$E$15<$F$2),D7,IF($B$15<$F$2,J7,G7)) -> 0.31241133
B25: Adicional BAM | C25: kWh | D25: =IF($K$13=M4,(($D$19+$D$20+$D$21)*($K$15)/($K$15+$L$15)),0)+IF($L$13=M4,(($D$19+$D$20+$D$21)*($L$15)/($K$15+$L$15)),0) -> 246 | E25: =IFERROR((ROUND(D25*K25,2)+ROUND(G25,2)+ROUND(J25,2))/ROUND(D25,4), 0) -> 0.024186992 | F25: =ROUND(D25*E25,2) -> 5.95 | G25: =((D25*K25)/(1-$N$19-$N$20))*($N$19+$N$20) -> 0.30492281 | H25: =(D25*K25)/(1-$N$19-$N$20)/(1-$I$19) -> 5.9542443 | J25: =H25*$I$19 -> 1.0122215 | K25: =N4 -> 0.01885
B26: Adicional BVM 1 | C26: kWh | D26: =IF($K$13=M5,(($D$19+$D$20+$D$21)*($K$15)/($K$15+$L$15)),0)+IF($L$13=M5,(($D$19+$D$20+$D$21)*($L$15)/($K$15+$L$15)),0) -> 0 | E26: =K26/(1-$N$19-$N$20)/(1-$I$19) -> 0.057306921 | F26: =ROUND(D26*E26,2) -> 0 | G26: =((D26*K26)/(1-$N$19-$N$20))*($N$19+$N$20) -> 0 | H26: =(D26*K26)/(1-$N$19-$N$20)/(1-$I$19) -> 0 | J26: =H26*$I$19 -> 0 | K26: =N5 -> 0.04463
B27: Adicional BVM 2 | C27: kWh | D27: =IF($K$13=M6,(($D$19+$D$20+$D$21)*($K$15)/($K$15+$L$15)),0)+IF($L$13=M6,(($D$19+$D$20+$D$21)*($L$15)/($K$15+$L$15)),0) -> 0 | E27: =K27/(1-$N$19-$N$20)/(1-$I$19) -> 0.10114421 | F27: =ROUND(D27*E27,2) -> 0 | G27: =((D27*K27)/(1-$N$19-$N$20))*($N$19+$N$20) -> 0 | H27: =(D27*K27)/(1-$N$19-$N$20)/(1-$I$19) -> 0 | J27: =H27*$I$19 -> 0 | K27: =N6 -> 0.07877
B28: Adicional Escassez | C28: kWh | D28: =IF($K$13=M7,(($D$19+$D$20+$D$21)*($K$15)/($K$15+$L$15)),0)+IF($L$13=M7,(($D$19+$D$20+$D$21)*($L$15)/($K$15+$L$15)),0) -> 0 | E28: =K28/(1-$N$19-$N$20)/(1-$I$19) -> 0.18233437 | F28: =ROUND(D28*E28,2) -> 0 | G28: =((D28*K28)/(1-$N$19-$N$20))*($N$19+$N$20) -> 0 | H28: =(D28*K28)/(1-$N$19-$N$20)/(1-$I$19) -> 0 | J28: =H28*$I$19 -> 0 | K28: =N7 -> 0.142
B29: Multas
B30: Juros
B31: Retenção PIS/PASEP | F31: -1.79
B32: Retenção CSLL | F32: -2.75
B33: Retenção IR | F33: -3.31
B34: Retenção COFINS | F34: -8.26
B35: Descontos
B36: CIP | F36: 64.32
B39: TOTAL | F39: =SUM(F19:F38) -> 323.65 | G39: =SUM(G19:G38) -> 14.106321 | H39: =SUM(H19:H38) -> 275.45491 | J39: =SUM(J19:J38) -> 46.827335
B41: Informativo Escassez | C41: =D19+D20+D21 -> 246 | D41: =IF(AND($B$15<$F$2,$E$15<$F$2),C9,IF($B$15<$F$2,I9,F9)) -> 0.00018620542 | E41: =IF(AND($B$15<$F$2,$E$15<$F$2),D9,IF($B$15<$F$2,J9,G9)) -> -0.002725567 | F41: =C41*(D41+E41) -> -0.62468294
H46: Fatura | L46: Vigência das Tarifas (troca Bandeira): | M46: =EOMONTH(B50,0)+1 -> 46235
B47: INSTALAÇÃO | C47: =C12 -> 475728 | H47: =E50 -> 46253 | K47: Altere a bandeira na célula abaixo
K48: =K13 -> BAM | L48: =L13 -> BAM
B49: Leitura Anterior | C49: Nº de dias tarifa Anterior | D49: Nº de dias tarifa Nova | E49: Leitura Atual | J49: Leitura Anterior | K49: Nº de dias tarifa Anterior | L49: Nº de dias tarifa Nova | M49: Leitura Atual
B50: =B15 -> 46223 | C50: =IF((F2-B50-1)<0,0,(F2-B50-1)) -> 17 | D50: =E50-F2+1 -> 13 | E50: =E15 -> 46253 | J50: =B50 -> 46223 | K50: =IF((M46-J50-1)<0,0,(M46-J50-1)) -> 11 | L50: =M50-M46+1 -> 19 | M50: =E50 -> 46253
B52: Fatura B3 - TB
D53: Qtde | E53: TUSD | F53: TE | G53: TUSD + TE | H53: R$ | J53: Documento simulado:
B54: Fornecimento de Energia Elétrica | H54: =SUM(H56:H64)+SUM(H70:H72) -> 275.4533
B56: Consumo Ponta | D56: =D19 -> 33 | E56: =IF(AND($B$50<$F$2,$E$50<$F$2),C6,IF($B$50<$F$2,I6,F6)) -> 1.0903407 | F56: =IF(AND($B$50<$F$2,$E$50<$F$2),D6,IF($B$50<$F$2,J6,G6)) -> 0.498533 | G56: 1.325 | H56: =ROUND((D56*E56),2)+ROUND((D56*F56),2) -> 52.43
B57: Consumo Fora Ponta | D57: =D21 -> 199 | E57: =IF(AND($B$50<$F$2,$E$50<$F$2),C7,IF($B$50<$F$2,I7,F7)) -> 0.404249 | F57: =IF(AND($B$50<$F$2,$E$50<$F$2),D7,IF($B$50<$F$2,J7,G7)) -> 0.31241133 | G57: 0.5328 | H57: =ROUND((D57*E57),2)+ROUND((D57*F57),2) -> 142.62
B58: Consumo Intemediário | D58: =D20 -> 14 | E58: =IF(AND($B$50<$F$2,$E$50<$F$2),C8,IF($B$50<$F$2,I8,F8)) -> 0.747297 | F58: =IF(AND($B$50<$F$2,$E$50<$F$2),D8,IF($B$50<$F$2,J8,G8)) -> 0.31241133 | G58: 0.84406 | H58: =ROUND((D58*E58),2)+ROUND((D58*F58),2) -> 14.83
B61: Adicional BAM | D61: =IF($K$48=M4,((D56+D57+D58)*(K50)/(K50+L50)),0)+IF($L$48=M4,((D56+D57+D58)*(L50)/(K50+L50)),0) -> 246 | F61: =N4 -> 0.01885 | H61: =ROUND(D61*(E61+F61),2) -> 4.64
B62: Adicional BVM 1 | D62: =IF($K$48=M5,((D56+D57+D58)*(K50)/(K50+L50)),0)+IF($L$48=M5,((D56+D57+D58)*(L50)/(K50+L50)),0) -> 0 | F62: =N5 -> 0.04463 | H62: =ROUND(D62*(E62+F62),2) -> 0
B63: Adicional BVM 2 | D63: =IF($K$48=M6,((D56+D57+D58)*(K50)/(K50+L50)),0)+IF($L$48=M6,((D56+D57+D58)*(L50)/(K50+L50)),0) -> 0 | F63: =N6 -> 0.07877 | H63: =ROUND(D63*(E63+F63),2) -> 0
B64: Adicional Escassez Hídrica | D64: =IF($K$48=M7,((D56+D57+D58)*(K50)/(K50+L50)),0)+IF($L$48=M7,((D56+D57+D58)*(L50)/(K50+L50)),0) -> 0 | F64: =N7 -> 0.142 | H64: =ROUND(D64*(E64+F64),2) -> 0
D69: Base de Cálculo
B70: PIS | D70: =(SUM(H56:H67)/(1-E70-E71)) -> 228.62624 | E70: =N19 -> 0.011 | H70: =D70*E70 -> 2.5148886
B71: COFINS | D71: =D70 -> 228.62624 | E71: =N20 -> 0.0507 | H71: =D71*E71 -> 11.59135
B72: ICMS | D72: =D70/(1-E72) -> 275.4533 | E72: =I19 -> 0.17 | H72: =D72*E72 -> 46.827061
B74: Informativo Escassez Hídrica | D74: =SUM(D56:D58) -> 246 | E74: =IF(AND($B$50<$F$2,$E$50<$F$2),C9,IF($B$50<$F$2,I9,F9)) -> 0.00018620542 | F74: =IF(AND($B$50<$F$2,$E$50<$F$2),D9,IF($B$50<$F$2,J9,G9)) -> -0.002725567 | H74: =D74*(E74+F74) -> -0.62468294
B76: Participação
C77: R$
B78: Energia | C78: =(SUM(H56:H67)*IF($B$50<$F$2,D116,D88)) -> 95.474146
B79: Distribuição | C79: =(SUM(H56:H67)*IF($B$50<$F$2,F116,F88)) -> 56.301518
B80: Transmissão | C80: =(SUM(H56:H67)*IF($B$50<$F$2,E116,E88)) -> 18.14361
B81: Encargos Setoriais | C81: =(SUM(H56:H67)*IF($B$50<$F$2,G116,G88)) -> 44.601906
B82: Impostos / Tributos | C82: =H70+H71+H72 -> 60.9333
B83: Total | C83: =SUM(C78:C82) -> 275.45448
B85: ='B1 (Res) Branca OK'!B76 -> 2024 | D85: Energia | E85: Transmissão | F85: Distribuição | G85: Setoriais
B86: Grupo B | D86: % | E86: % | F86: % | G86: %
B88: B1 - Residencial | D88: ='B1 (Res) Branca OK'!D79 -> 0.45246417 | E88: ='B1 (Res) Branca OK'!E79 -> 0.073959411 | F88: ='B1 (Res) Branca OK'!F79 -> 0.27500913 | G88: ='B1 (Res) Branca OK'!G79 -> 0.19856729
B89: B1 - Residencial Baixa Renda | D89: ='B1 (Res) Branca OK'!D80 -> 0.53149576 | E89: ='B1 (Res) Branca OK'!E80 -> 0.086877849 | F89: ='B1 (Res) Branca OK'!F80 -> 0.32304478 | G89: ='B1 (Res) Branca OK'!G80 -> 0.058581612
B90: B2 - Rural | D90: ='B1 (Res) Branca OK'!D81 -> 0.45246417 | E90: ='B1 (Res) Branca OK'!E81 -> 0.073959411 | F90: ='B1 (Res) Branca OK'!F81 -> 0.27500913 | G90: ='B1 (Res) Branca OK'!G81 -> 0.19856729
B91: B2 - Cooperativa Eletrificação Rural | D91: ='B1 (Res) Branca OK'!D82 -> 0.45246417 | E91: ='B1 (Res) Branca OK'!E82 -> 0.073959411 | F91: ='B1 (Res) Branca OK'!F82 -> 0.27500913 | G91: ='B1 (Res) Branca OK'!G82 -> 0.19856729
B92: B2 - Serviço de Irrigação | D92: ='B1 (Res) Branca OK'!D83 -> 0.45246417 | E92: ='B1 (Res) Branca OK'!E83 -> 0.073959411 | F92: ='B1 (Res) Branca OK'!F83 -> 0.27500913 | G92: ='B1 (Res) Branca OK'!G83 -> 0.19856729
B93: B3 - Demais Classes | D93: ='B1 (Res) Branca OK'!D84 -> 0.45246417 | E93: ='B1 (Res) Branca OK'!E84 -> 0.073959411 | F93: ='B1 (Res) Branca OK'!F84 -> 0.27500913 | G93: ='B1 (Res) Branca OK'!G84 -> 0.19856729
B94: B4 - Iluminação Pública | D94: ='B1 (Res) Branca OK'!D85 -> 0.45246417 | E94: ='B1 (Res) Branca OK'!E85 -> 0.073959411 | F94: ='B1 (Res) Branca OK'!F85 -> 0.27500913 | G94: ='B1 (Res) Branca OK'!G85 -> 0.19856729
B95: B4a - Rede de Distribuição | D95: ='B1 (Res) Branca OK'!D86 -> 0.45246417 | E95: ='B1 (Res) Branca OK'!E86 -> 0.073959411 | F95: ='B1 (Res) Branca OK'!F86 -> 0.27500913 | G95: ='B1 (Res) Branca OK'!G86 -> 0.19856729
B96: B4b - Bulbo de Lâmpada | D96: ='B1 (Res) Branca OK'!D87 -> 0.45246417 | E96: ='B1 (Res) Branca OK'!E87 -> 0.073959411 | F96: ='B1 (Res) Branca OK'!F87 -> 0.27500913 | G96: ='B1 (Res) Branca OK'!G87 -> 0.19856729
B99: ='B1 (Res) Branca OK'!B90 -> 2023 | D99: Energia | E99: Transmissão | F99: Distribuição | G99: Setoriais
B100: Grupo B | D100: % | E100: % | F100: % | G100: %
B102: B1 - Residencial | D102: ='B1 (Res) Branca OK'!D93 -> 0.43939696 | E102: ='B1 (Res) Branca OK'!E93 -> 0.092697586 | F102: ='B1 (Res) Branca OK'!F93 -> 0.25285208 | G102: ='B1 (Res) Branca OK'!G93 -> 0.21506308
B103: B1 - Residencial Baixa Renda | D103: ='B1 (Res) Branca OK'!D94 -> 0.5269162 | E103: ='B1 (Res) Branca OK'!E94 -> 0.11116112 | F103: ='B1 (Res) Branca OK'!F94 -> 0.30321524 | G103: ='B1 (Res) Branca OK'!G94 -> 0.058707433
B104: B2 - Rural | D104: ='B1 (Res) Branca OK'!D95 -> 0.439393 | E104: ='B1 (Res) Branca OK'!E95 -> 0.092696751 | F104: ='B1 (Res) Branca OK'!F95 -> 0.2528498 | G104: ='B1 (Res) Branca OK'!G95 -> 0.21506045
B105: B2 - Cooperativa Eletrificação Rural | D105: ='B1 (Res) Branca OK'!D96 -> 0.439393 | E105: ='B1 (Res) Branca OK'!E96 -> 0.092696751 | F105: ='B1 (Res) Branca OK'!F96 -> 0.2528498 | G105: ='B1 (Res) Branca OK'!G96 -> 0.21506045
B106: B2 - Serviço de Irrigação | D106: ='B1 (Res) Branca OK'!D97 -> 0.439393 | E106: ='B1 (Res) Branca OK'!E97 -> 0.092696751 | F106: ='B1 (Res) Branca OK'!F97 -> 0.2528498 | G106: ='B1 (Res) Branca OK'!G97 -> 0.21506045
B107: B3 - Demais Classes | D107: ='B1 (Res) Branca OK'!D98 -> 0.439393 | E107: ='B1 (Res) Branca OK'!E98 -> 0.092696751 | F107: ='B1 (Res) Branca OK'!F98 -> 0.2528498 | G107: ='B1 (Res) Branca OK'!G98 -> 0.21506045
B108: B4 - Iluminação Pública | D108: ='B1 (Res) Branca OK'!D99 -> 0 | E108: ='B1 (Res) Branca OK'!E99 -> 0 | F108: ='B1 (Res) Branca OK'!F99 -> 0 | G108: ='B1 (Res) Branca OK'!G99 -> 0
B109: B4a - Rede de Distribuição | D109: ='B1 (Res) Branca OK'!D100 -> 0.43938946 | E109: ='B1 (Res) Branca OK'!E100 -> 0.092697337 | F109: ='B1 (Res) Branca OK'!F100 -> 0.2528514 | G109: ='B1 (Res) Branca OK'!G100 -> 0.21506181
B110: B4b - Bulbo de Lâmpada | D110: ='B1 (Res) Branca OK'!D101 -> 0.43938946 | E110: ='B1 (Res) Branca OK'!E101 -> 0.092697337 | F110: ='B1 (Res) Branca OK'!F101 -> 0.2528514 | G110: ='B1 (Res) Branca OK'!G101 -> 0.21506181
B112: proporcional
D113: Energia | E113: Transmissão | F113: Distribuição | G113: Setoriais
B114: Grupo B | D114: % | E114: % | F114: % | G114: %
B116: B1 - Residencial | D116: =((D102*$C$50)+(D88*$D$50))/($C$50+$D$50) -> 0.44505942 | E116: =((E102*$C$50)+(E88*$D$50))/($C$50+$D$50) -> 0.08457771 | F116: =((F102*$C$50)+(F88*$D$50))/($C$50+$D$50) -> 0.26245347 | G116: =((G102*$C$50)+(G88*$D$50))/($C$50+$D$50) -> 0.20791491
B117: B1 - Residencial Baixa Renda | D117: =((D103*$C$50)+(D89*$D$50))/($C$50+$D$50) -> 0.52890068 | E117: =((E103*$C$50)+(E89*$D$50))/($C$50+$D$50) -> 0.10063837 | F117: =((F103*$C$50)+(F89*$D$50))/($C$50+$D$50) -> 0.31180804 | G117: =((G103*$C$50)+(G89*$D$50))/($C$50+$D$50) -> 0.058652911
B118: B2 - Rural | D118: =((D104*$C$50)+(D90*$D$50))/($C$50+$D$50) -> 0.44505717 | E118: =((E104*$C$50)+(E90*$D$50))/($C$50+$D$50) -> 0.084577237 | F118: =((F104*$C$50)+(F90*$D$50))/($C$50+$D$50) -> 0.26245218 | G118: =((G104*$C$50)+(G90*$D$50))/($C$50+$D$50) -> 0.20791341
B119: B2 - Cooperativa Eletrificação Rural | D119: =((D105*$C$50)+(D91*$D$50))/($C$50+$D$50) -> 0.44505717 | E119: =((E105*$C$50)+(E91*$D$50))/($C$50+$D$50) -> 0.084577237 | F119: =((F105*$C$50)+(F91*$D$50))/($C$50+$D$50) -> 0.26245218 | G119: =((G105*$C$50)+(G91*$D$50))/($C$50+$D$50) -> 0.20791341
B120: B2 - Serviço de Irrigação | D120: =((D106*$C$50)+(D92*$D$50))/($C$50+$D$50) -> 0.44505717 | E120: =((E106*$C$50)+(E92*$D$50))/($C$50+$D$50) -> 0.084577237 | F120: =((F106*$C$50)+(F92*$D$50))/($C$50+$D$50) -> 0.26245218 | G120: =((G106*$C$50)+(G92*$D$50))/($C$50+$D$50) -> 0.20791341
B121: B3 - Demais Classes | D121: =((D107*$C$50)+(D93*$D$50))/($C$50+$D$50) -> 0.44505717 | E121: =((E107*$C$50)+(E93*$D$50))/($C$50+$D$50) -> 0.084577237 | F121: =((F107*$C$50)+(F93*$D$50))/($C$50+$D$50) -> 0.26245218 | G121: =((G107*$C$50)+(G93*$D$50))/($C$50+$D$50) -> 0.20791341
B122: B4 - Iluminação Pública | D122: =((D108*$C$50)+(D94*$D$50))/($C$50+$D$50) -> 0.19606781 | E122: =((E108*$C$50)+(E94*$D$50))/($C$50+$D$50) -> 0.032049078 | F122: =((F108*$C$50)+(F94*$D$50))/($C$50+$D$50) -> 0.11917062 | G122: =((G108*$C$50)+(G94*$D$50))/($C$50+$D$50) -> 0.086045826
B123: B4a - Rede de Distribuição | D123: =((D109*$C$50)+(D95*$D$50))/($C$50+$D$50) -> 0.44505516 | E123: =((E109*$C$50)+(E95*$D$50))/($C$50+$D$50) -> 0.084577569 | F123: =((F109*$C$50)+(F95*$D$50))/($C$50+$D$50) -> 0.26245308 | G123: =((G109*$C$50)+(G95*$D$50))/($C$50+$D$50) -> 0.20791418
B124: B4b - Bulbo de Lâmpada | D124: =((D110*$C$50)+(D96*$D$50))/($C$50+$D$50) -> 0.44505516 | E124: =((E110*$C$50)+(E96*$D$50))/($C$50+$D$50) -> 0.084577569 | F124: =((F110*$C$50)+(F96*$D$50))/($C$50+$D$50) -> 0.26245308 | G124: =((G110*$C$50)+(G96*$D$50))/($C$50+$D$50) -> 0.20791418

Sheet B3CP Branca OK
B2: B3 | E2: Vigência das Tarifas: | F2: ='B1 (Res) Branca OK'!F2 -> 46241 | H2: TARIFA BRANCA | M2: Bandeira | N2: R$/kWh | Q2: TUSD FIO B
M3: VERDE | N3: ='B1 (Res) Branca OK'!N3 -> 0
B4: TARIFA | C4: ='B1 (Res) Branca OK'!C4 -> TARIFA ANTIGA - REH 3370/2024 | F4: ='B1 (Res) Branca OK'!F4 -> TARIFA NOVA - REH xxxx/2025 | I4: Tarifas Proporcionalizadas | M4: BAM | N4: ='B1 (Res) Branca OK'!N4 -> 0.01885 | Q4: TARIFA | R4: =C4 -> TARIFA ANTIGA - REH 3370/2024 | U4: =F4 -> TARIFA NOVA - REH xxxx/2025 | X4: Tarifas Proporcionalizadas
C5: Tusd | D5: TE | E5: TUSD + TE | F5: Tusd | G5: TE | H5: TUSD + TE | I5: Tusd | J5: TE | K5: TUSD + TE | M5: BVM1 | N5: ='B1 (Res) Branca OK'!N5 -> 0.04463 | R5: Tusd (R$/kWh) | U5: Tusd (R$/kWh) | X5: Tusd (R$/kWh)
B6: B3 Ponta | C6: ='TABELA DE TARIFAS ANTIGAS'!G86/1000 -> 1.06103 | D6: ='TABELA DE TARIFAS ANTIGAS'!H86/1000 -> 0.48448 | E6: =C6+D6 -> 1.54551 | F6: ='TABELA DE TARIFAS NOVAS'!G88/1000 -> 1.12867 | G6: ='TABELA DE TARIFAS NOVAS'!H88/1000 -> 0.51691 | H6: =F6+G6 -> 1.64558 | I6: =((C6*$C$46)+(F6*$D$46))/($D$46+$C$46) -> 1.0925953 | J6: =((D6*$C$46)+(G6*$D$46))/($D$46+$C$46) -> 0.499614 | K6: =I6+J6 -> 1.5922093 | M6: BVM2 | N6: ='B1 (Res) Branca OK'!N6 -> 0.07877 | Q6: =B6 -> B3 Ponta | R6: ='FIO B'!H31/1000 -> 0.69302445 | U6: ='FIO B'!K31/1000 -> 0.71111541 | X6: =((R6*$C$46)+(U6*$D$46))/($D$46+$C$46) -> 0.7014669
B7: B3 Fora Ponta | C7: ='TABELA DE TARIFAS ANTIGAS'!G88/1000 -> 0.38965 | D7: ='TABELA DE TARIFAS ANTIGAS'!H88/1000 -> 0.30579 | E7: =C7+D7 -> 0.69544 | F7: ='TABELA DE TARIFAS NOVAS'!G90/1000 -> 0.42334 | G7: ='TABELA DE TARIFAS NOVAS'!H90/1000 -> 0.32107 | H7: =F7+G7 -> 0.74441 | I7: =((C7*$C$46)+(F7*$D$46))/($D$46+$C$46) -> 0.405372 | J7: =((D7*$C$46)+(G7*$D$46))/($D$46+$C$46) -> 0.31292067 | K7: =I7+J7 -> 0.71829267 | M7: Escassez Hídrica | N7: ='B1 (Res) Branca OK'!N7 -> 0.142 | Q7: =B7 -> B3 Fora Ponta | R7: ='FIO B'!H33/1000 -> 0.13860487 | U7: ='FIO B'!K33/1000 -> 0.14222306 | X7: =((R7*$C$46)+(U7*$D$46))/($D$46+$C$46) -> 0.14029336
B8: B3 Interm. | C8: ='TABELA DE TARIFAS ANTIGAS'!G87/1000 -> 0.72534 | D8: ='TABELA DE TARIFAS ANTIGAS'!H87/1000 -> 0.30579 | E8: =C8+D8 -> 1.03113 | F8: ='TABELA DE TARIFAS NOVAS'!G89/1000 -> 0.77601 | G8: ='TABELA DE TARIFAS NOVAS'!H89/1000 -> 0.32107 | H8: =F8+G8 -> 1.09708 | I8: =((C8*$C$46)+(F8*$D$46))/($D$46+$C$46) -> 0.748986 | J8: =((D8*$C$46)+(G8*$D$46))/($D$46+$C$46) -> 0.31292067 | K8: =I8+J8 -> 1.0619067 | Q8: =B8 -> B3 Interm. | R8: ='FIO B'!H32/1000 -> 0.41581471 | U8: ='FIO B'!K32/1000 -> 0.42666929 | X8: =((R8*$C$46)+(U8*$D$46))/($D$46+$C$46) -> 0.42088018
B9: CDE Escassez Hídrica | C9: ='B1 (Res) Branca OK'!C9 -> 0.00018774721 | D9: ='B1 (Res) Branca OK'!D9 -> -0.0044031307 | E9: =SUM(C9+D9) -> -0.0042153835 | F9: =T13 -> 0.00018418923 | G9: =U13 -> -0.00053182975 | H9: =F9+G9 -> -0.00034764052 | I9: =((C9*$C$46)+(F9*$D$46))/($D$46+$C$46) -> 0.00018608682 | J9: =((D9*$C$46)+(G9*$D$46))/($D$46+$C$46) -> -0.0025965236 | K9: =I9+J9 -> -0.0024104368
P10: CUSTO | R10: Part. TUSD (%) | S10: Part. TE (%) | T10: Tusd (R$/kWh) | U10: TE (R$/kWh)
H11: Fatura | L11: Vigência das Tarifas (troca Bandeira): | M11: =EOMONTH(B15,0)+1 -> 46235 | P11: CDE CONTAS
B12: INSTALAÇÃO | C12: 160247791 | H12: =E15 -> 46254 | K12: Altere a bandeira na célula abaixo | P12: CDE COVID | U12: 0
K13: ='B1 (Res) Branca OK'!K13 -> BAM | L13: ='B1 (Res) Branca OK'!L13 -> BAM | P13: CDE ESCASSEZ HÍDRICA | T13: ='B1 (Res) Branca OK'!T13 -> 0.00018418923 | U13: ='B1 (Res) Branca OK'!U13 -> -0.00053182975
B14: Leitura Anterior | C14: Nº de dias tarifa Anterior | D14: Nº de dias tarifa Nova | E14: Leitura Atual | J14: Leitura Anterior | K14: Nº de dias tarifa Anterior | L14: Nº de dias tarifa Nova | M14: Leitura Atual
B15: 46224 | C15: =IF((F2-B15-1)<0,0,(F2-B15-1)) -> 16 | D15: =E15-F2+1 -> 14 | E15: 46254 | J15: =B15 -> 46224 | K15: =IF((M11-J15-1)<0,0,(M11-J15-1)) -> 10 | L15: =M15-M11+1 -> 20 | M15: =E15 -> 46254
P16: Documento simulado: | R16: 1025310396
B17: Descrição | C17: Unidade | D17: Quantidade | E17: Preço Unit (R$) com tributos | F17: Valor Total (R$) | G17: PIS/COFINS (R$) | H17: Base de Cálculo ICMS (R$) | I17: Alíquota ICMS (%) | J17: ICMS (R$) | K17: Preço Unit (R$) | L17: Tributos | M17: Base de Cálc (R$) | N17: Alíquota (%) | O17: Valor (R$)
R18: TUSD Fio B | S18: Receita Fio B
B19: TUSD - Consumo Ponta | C19: kWh | D19: 92 | E19: =IFERROR((ROUND(D19*K19,2)+ROUND(G19,2)+ROUND(J19,2))/ROUND(D19,4), 0) -> 1.1644565 | F19: =ROUND(D19*E19,2) -> 107.13 | G19: =((D19*K19)/(1-$N$19-$N$20))*($N$19+$N$20) -> 6.609835 | H19: =IF(I19=0%,0,(D19*K19)/(1-$N$19-$N$20)/(1-$I$19)) -> 0 | I19: 0 | J19: =H19*$I$19 -> 0 | K19: =IF(AND($B$15<$F$2,$E$15<$F$2),C6,IF($B$15<$F$2,I6,F6)) -> 1.0925953 | L19: PIS | M19: =D66 -> 1422.0825 | N19: ='B1 (Res) Branca OK'!N19 -> 0.011 | O19: =ROUND(M19*N19,2) -> 15.64 | R19: =IF(AND($B$46<$F$2,$E$46<$F$2),R6,IF($B$46<$F$2,X6,U6)) -> 0.7014669 | S19: =D52*R19 -> 64.534955
B20: TUSD - Consumo Intermediário | C20: kWh | D20: 101 | E20: =IFERROR((ROUND(D20*K20,2)+ROUND(G20,2)+ROUND(J20,2))/ROUND(D20,4), 0) -> 0.79821782 | F20: =ROUND(D20*E20,2) -> 80.62 | G20: =((D20*K20)/(1-$N$19-$N$20))*($N$19+$N$20) -> 4.974375 | H20: =IF(I20=0%,0,(D20*K20)/(1-$N$19-$N$20)/(1-$I$19)) -> 0 | I20: =I19 -> 0 | J20: =H20*$I$19 -> 0 | K20: =IF(AND($B$15<$F$2,$E$15<$F$2),C8,IF($B$15<$F$2,I8,F8)) -> 0.748986 | L20: COFINS | M20: =M19 -> 1422.0825 | N20: ='B1 (Res) Branca OK'!N20 -> 0.0507 | O20: =ROUND(M20*N20,2) -> 72.1 | R20: =IF(AND($B$46<$F$2,$E$46<$F$2),R7,IF($B$46<$F$2,X7,U7)) -> 0.14029336 | S20: =D53*R20 -> 204.9686
B21: TUSD - Consumo Fora Ponta | C21: kWh | D21: 1461 | E21: =IFERROR((ROUND(D21*K21,2)+ROUND(G21,2)+ROUND(J21,2))/ROUND(D21,4), 0) -> 0.43202601 | F21: =ROUND(D21*E21,2) -> 631.19 | G21: =((D21*K21)/(1-$N$19-$N$20))*($N$19+$N$20) -> 38.944615 | H21: =IF(I21=0%,0,(D21*K21)/(1-$N$19-$N$20)/(1-$I$19)) -> 0 | I21: =I19 -> 0 | J21: =H21*$I$19 -> 0 | K21: =IF(AND($B$15<$F$2,$E$15<$F$2),C7,IF($B$15<$F$2,I7,F7)) -> 0.405372 | R21: =IF(AND($B$46<$F$2,$E$46<$F$2),R8,IF($B$46<$F$2,X8,U8)) -> 0.42088018 | S21: =D54*R21 -> 42.508898
B22: TE - Consumo Ponta | C22: kWh | D22: =D19 -> 92 | E22: =IFERROR((ROUND(D22*K22,2)+ROUND(G22,2)+ROUND(J22,2))/ROUND(D22,4), 0) -> 0.5323913 | F22: =ROUND(D22*E22,2) -> 48.98 | G22: =((D22*K22)/(1-$N$19-$N$20))*($N$19+$N$20) -> 3.022497 | H22: =IF(I22=0%,0,(D22*K22)/(1-$N$19-$N$20)/(1-$I$19)) -> 0 | J22: =H22*$I$19 -> 0 | K22: =IF(AND($B$15<$F$2,$E$15<$F$2),D6,IF($B$15<$F$2,J6,G6)) -> 0.499614 | S22: =SUM(S19:S21) -> 312.01245
B23: TE - Consumo Intermediário | C23: kWh | D23: =D20 -> 101 | E23: =IFERROR((ROUND(D23*K23,2)+ROUND(G23,2)+ROUND(J23,2))/ROUND(D23,4), 0) -> 0.33346535 | F23: =ROUND(D23*E23,2) -> 33.68 | G23: =((D23*K23)/(1-$N$19-$N$20))*($N$19+$N$20) -> 2.0782561 | H23: =IF(I23=0%,0,(D23*K23)/(1-$N$19-$N$20)/(1-$I$19)) -> 0 | J23: =H23*$I$19 -> 0 | K23: =IF(AND($B$15<$F$2,$E$15<$F$2),D8,IF($B$15<$F$2,J8,G8)) -> 0.31292067
B24: TE - Consumo Fora Ponta | C24: kWh | D24: =D21 -> 1461 | E24: =IFERROR((ROUND(D24*K24,2)+ROUND(G24,2)+ROUND(J24,2))/ROUND(D24,4), 0) -> 0.3334976 | F24: =ROUND(D24*E24,2) -> 487.24 | G24: =((D24*K24)/(1-$N$19-$N$20))*($N$19+$N$20) -> 30.062695 | H24: =IF(I24=0%,0,(D24*K24)/(1-$N$19-$N$20)/(1-$I$19)) -> 0 | J24: =H24*$I$19 -> 0 | K24: =IF(AND($B$15<$F$2,$E$15<$F$2),D7,IF($B$15<$F$2,J7,G7)) -> 0.31292067
B25: Adicional BAM | C25: kWh | D25: =IF($K$13=M4,(($D$19+$D$20+$D$21)*($K$15)/($K$15+$L$15)),0)+IF($L$13=M4,(($D$19+$D$20+$D$21)*($L$15)/($K$15+$L$15)),0) -> 1654 | E25: =IFERROR((ROUND(D25*K25,2)+ROUND(G25,2)+ROUND(J25,2))/ROUND(D25,4), 0) -> 0.020090689 | F25: =ROUND(D25*E25,2) -> 33.23 | G25: =((D25*K25)/(1-$N$19-$N$20))*($N$19+$N$20) -> 2.050172 | H25: =IF(I25=0%,0,(D25*K25)/(1-$N$19-$N$20)/(1-$I$19)) -> 0 | J25: =H25*$I$19 -> 0 | K25: =N4 -> 0.01885
B26: Adicional BVM 1 | C26: kWh | D26: =IF($K$13=M5,(($D$19+$D$20+$D$21)*($K$15)/($K$15+$L$15)),0)+IF($L$13=M5,(($D$19+$D$20+$D$21)*($L$15)/($K$15+$L$15)),0) -> 0 | E26: =K26/(1-$N$19-$N$20)/(1-$I$19) -> 0.047564745 | F26: =ROUND(D26*E26,2) -> 0 | G26: =((D26*K26)/(1-$N$19-$N$20))*($N$19+$N$20) -> 0 | H26: =IF(I26=0%,0,(D26*K26)/(1-$N$19-$N$20)/(1-$I$19)) -> 0 | J26: =H26*$I$19 -> 0 | K26: =N5 -> 0.04463
B27: Adicional BVM 2 | C27: kWh | D27: =IF($K$13=M6,(($D$19+$D$20+$D$21)*($K$15)/($K$15+$L$15)),0)+IF($L$13=M6,(($D$19+$D$20+$D$21)*($L$15)/($K$15+$L$15)),0) -> 0 | E27: =K27/(1-$N$19-$N$20)/(1-$I$19) -> 0.083949696 | F27: =ROUND(D27*E27,2) -> 0 | G27: =((D27*K27)/(1-$N$19-$N$20))*($N$19+$N$20) -> 0 | H27: =IF(I27=0%,0,(D27*K27)/(1-$N$19-$N$20)/(1-$I$19)) -> 0 | J27: =H27*$I$19 -> 0 | K27: =N6 -> 0.07877
B28: Adicional Escassez | C28: kWh | D28: =IF($K$13=M7,(($D$19+$D$20+$D$21)*($K$15)/($K$15+$L$15)),0)+IF($L$13=M7,(($D$19+$D$20+$D$21)*($L$15)/($K$15+$L$15)),0) -> 0 | E28: =K28/(1-$N$19-$N$20)/(1-$I$19) -> 0.15133753 | F28: =ROUND(D28*E28,2) -> 0 | G28: =((D28*K28)/(1-$N$19-$N$20))*($N$19+$N$20) -> 0 | H28: =IF(I28=0%,0,(D28*K28)/(1-$N$19-$N$20)/(1-$I$19)) -> 0 | J28: =H28*$I$19 -> 0 | K28: =N7 -> 0.142
B29: Multas
B30: Juros
B31: Doações
B32: CIP
B35: TOTAL | F35: =SUM(F19:F34) -> 1422.07 | G35: =SUM(G19:G34) -> 87.742445 | H35: =SUM(H19:H34) -> 0 | J35: =SUM(J19:J34) -> 0
B37: Informativo Escassez | C37: =D19+D20+D21 -> 1654 | D37: =IF(AND($B$15<$F$2,$E$15<$F$2),C9,IF($B$15<$F$2,I9,F9)) -> 0.00018608682 | E37: =IF(AND($B$15<$F$2,$E$15<$F$2),D9,IF($B$15<$F$2,J9,G9)) -> -0.0025965236 | F37: =C37*(D37+E37) -> -3.9868624
H42: Fatura | L42: Vigência das Tarifas (troca Bandeira): | M42: =EOMONTH(B46,0)+1 -> 46235
B43: INSTALAÇÃO | C43: =C12 -> 160247791 | H43: =E46 -> 46254 | K43: Altere a bandeira na célula abaixo
K44: =K13 -> BAM | L44: =L13 -> BAM
B45: Leitura Anterior | C45: Nº de dias tarifa Anterior | D45: Nº de dias tarifa Nova | E45: Leitura Atual | J45: Leitura Anterior | K45: Nº de dias tarifa Anterior | L45: Nº de dias tarifa Nova | M45: Leitura Atual
B46: =B15 -> 46224 | C46: =IF((F2-B46-1)<0,0,(F2-B46-1)) -> 16 | D46: =E46-F2+1 -> 14 | E46: =E15 -> 46254 | J46: =B46 -> 46224 | K46: =IF((M42-J46-1)<0,0,(M42-J46-1)) -> 10 | L46: =M46-M42+1 -> 20 | M46: =E46 -> 46254
B48: Fatura B3 - TB
D49: Qtde | E49: TUSD | F49: TE | G49: TUSD + TE | H49: R$ | J49: Documento simulado:
B50: Fornecimento de Energia Elétrica | H50: =SUM(H52:H60)+SUM(H66:H68) -> 1422.0825
B52: Consumo Ponta | D52: =D19 -> 92 | E52: =IF(AND($B$46<$F$2,$E$46<$F$2),C6,IF($B$46<$F$2,I6,F6)) -> 1.0925953 | F52: =IF(AND($B$46<$F$2,$E$46<$F$2),D6,IF($B$46<$F$2,J6,G6)) -> 0.499614 | G52: 1.325 | H52: =ROUND((D52*E52),2)+ROUND((D52*F52),2) -> 146.48
B53: Consumo Fora Ponta | D53: =D21 -> 1461 | E53: =IF(AND($B$46<$F$2,$E$46<$F$2),C7,IF($B$46<$F$2,I7,F7)) -> 0.405372 | F53: =IF(AND($B$46<$F$2,$E$46<$F$2),D7,IF($B$46<$F$2,J7,G7)) -> 0.31292067 | G53: 0.5328 | H53: =ROUND((D53*E53),2)+ROUND((D53*F53),2) -> 1049.43
B54: Consumo Intemediário | D54: =D20 -> 101 | E54: =IF(AND($B$46<$F$2,$E$46<$F$2),C8,IF($B$46<$F$2,I8,F8)) -> 0.748986 | F54: =IF(AND($B$46<$F$2,$E$46<$F$2),D8,IF($B$46<$F$2,J8,G8)) -> 0.31292067 | G54: 0.84406 | H54: =ROUND((D54*E54),2)+ROUND((D54*F54),2) -> 107.25
B57: Adicional BAM | D57: =IF($K$44=M4,((D52+D53+D54)*(K46)/(K46+L46)),0)+IF($L$44=M4,((D52+D53+D54)*(L46)/(K46+L46)),0) -> 1654 | F57: =N4 -> 0.01885 | H57: =ROUND(D57*(E57+F57),2) -> 31.18
B58: Adicional BVM 1 | D58: =IF($K$44=M5,((D52+D53+D54)*(K46)/(K46+L46)),0)+IF($L$44=M5,((D52+D53+D54)*(L46)/(K46+L46)),0) -> 0 | F58: =N5 -> 0.04463 | H58: =ROUND(D58*(E58+F58),2) -> 0
B59: Adicional BVM 2 | D59: =IF($K$44=M6,((D52+D53+D54)*(K46)/(K46+L46)),0)+IF($L$44=M6,((D52+D53+D54)*(L46)/(K46+L46)),0) -> 0 | F59: =N6 -> 0.07877 | H59: =ROUND(D59*(E59+F59),2) -> 0
B60: Adicional Escassez Hídrica | D60: =IF($K$44=M7,((D52+D53+D54)*(K46)/(K46+L46)),0)+IF($L$44=M7,((D52+D53+D54)*(L46)/(K46+L46)),0) -> 0 | F60: =N7 -> 0.142 | H60: =ROUND(D60*(E60+F60),2) -> 0
D65: Base de Cálculo
B66: PIS | D66: =(SUM(H52:H63)/(1-E66-E67)) -> 1422.0825 | E66: =N19 -> 0.011 | H66: =D66*E66 -> 15.642907
B67: COFINS | D67: =D66 -> 1422.0825 | E67: =N20 -> 0.0507 | H67: =D67*E67 -> 72.099582
B68: ICMS | D68: =D66/(1-E68) -> 1422.0825 | E68: =I19 -> 0 | H68: =D68*E68 -> 0
B70: Informativo Escassez Hídrica | D70: =SUM(D52:D54) -> 1654 | E70: =IF(AND($B$46<$F$2,$E$46<$F$2),C9,IF($B$46<$F$2,I9,F9)) -> 0.00018608682 | F70: =IF(AND($B$46<$F$2,$E$46<$F$2),D9,IF($B$46<$F$2,J9,G9)) -> -0.0025965236 | H70: =D70*(E70+F70) -> -3.9868624
B72: Participação
C73: R$
B74: Energia | C74: =(SUM(H52:H63)*IF($B$46<$F$2,D112,D84)) -> 594.44179
B75: Distribuição | C75: =(SUM(H52:H63)*IF($B$46<$F$2,F112,F84)) -> 351.18766
B76: Transmissão | C76: =(SUM(H52:H63)*IF($B$46<$F$2,E112,E84)) -> 112.02199
B77: Encargos Setoriais | C77: =(SUM(H52:H63)*IF($B$46<$F$2,G112,G84)) -> 276.69548
B78: Impostos / Tributos | C78: =H66+H67+H68 -> 87.74249
B79: Total | C79: =SUM(C74:C78) -> 1422.0894
B81: ='B1 (Res) Branca OK'!B76 -> 2024 | D81: Energia | E81: Transmissão | F81: Distribuição | G81: Setoriais
B82: Grupo B | D82: % | E82: % | F82: % | G82: %
B84: B1 - Residencial | D84: ='B1 (Res) Branca OK'!D79 -> 0.45246417 | E84: ='B1 (Res) Branca OK'!E79 -> 0.073959411 | F84: ='B1 (Res) Branca OK'!F79 -> 0.27500913 | G84: ='B1 (Res) Branca OK'!G79 -> 0.19856729
B85: B1 - Residencial Baixa Renda | D85: ='B1 (Res) Branca OK'!D80 -> 0.53149576 | E85: ='B1 (Res) Branca OK'!E80 -> 0.086877849 | F85: ='B1 (Res) Branca OK'!F80 -> 0.32304478 | G85: ='B1 (Res) Branca OK'!G80 -> 0.058581612
B86: B2 - Rural | D86: ='B1 (Res) Branca OK'!D81 -> 0.45246417 | E86: ='B1 (Res) Branca OK'!E81 -> 0.073959411 | F86: ='B1 (Res) Branca OK'!F81 -> 0.27500913 | G86: ='B1 (Res) Branca OK'!G81 -> 0.19856729
B87: B2 - Cooperativa Eletrificação Rural | D87: ='B1 (Res) Branca OK'!D82 -> 0.45246417 | E87: ='B1 (Res) Branca OK'!E82 -> 0.073959411 | F87: ='B1 (Res) Branca OK'!F82 -> 0.27500913 | G87: ='B1 (Res) Branca OK'!G82 -> 0.19856729
B88: B2 - Serviço de Irrigação | D88: ='B1 (Res) Branca OK'!D83 -> 0.45246417 | E88: ='B1 (Res) Branca OK'!E83 -> 0.073959411 | F88: ='B1 (Res) Branca OK'!F83 -> 0.27500913 | G88: ='B1 (Res) Branca OK'!G83 -> 0.19856729
B89: B3 - Demais Classes | D89: ='B1 (Res) Branca OK'!D84 -> 0.45246417 | E89: ='B1 (Res) Branca OK'!E84 -> 0.073959411 | F89: ='B1 (Res) Branca OK'!F84 -> 0.27500913 | G89: ='B1 (Res) Branca OK'!G84 -> 0.19856729
B90: B4 - Iluminação Pública | D90: ='B1 (Res) Branca OK'!D85 -> 0.45246417 | E90: ='B1 (Res) Branca OK'!E85 -> 0.073959411 | F90: ='B1 (Res) Branca OK'!F85 -> 0.27500913 | G90: ='B1 (Res) Branca OK'!G85 -> 0.19856729
B91: B4a - Rede de Distribuição | D91: ='B1 (Res) Branca OK'!D86 -> 0.45246417 | E91: ='B1 (Res) Branca OK'!E86 -> 0.073959411 | F91: ='B1 (Res) Branca OK'!F86 -> 0.27500913 | G91: ='B1 (Res) Branca OK'!G86 -> 0.19856729
B92: B4b - Bulbo de Lâmpada | D92: ='B1 (Res) Branca OK'!D87 -> 0.45246417 | E92: ='B1 (Res) Branca OK'!E87 -> 0.073959411 | F92: ='B1 (Res) Branca OK'!F87 -> 0.27500913 | G92: ='B1 (Res) Branca OK'!G87 -> 0.19856729
B95: ='B1 (Res) Branca OK'!B90 -> 2023 | D95: Energia | E95: Transmissão | F95: Distribuição | G95: Setoriais
B96: Grupo B | D96: % | E96: % | F96: % | G96: %
B98: B1 - Residencial | D98: ='B1 (Res) Branca OK'!D93 -> 0.43939696 | E98: ='B1 (Res) Branca OK'!E93 -> 0.092697586 | F98: ='B1 (Res) Branca OK'!F93 -> 0.25285208 | G98: ='B1 (Res) Branca OK'!G93 -> 0.21506308
B99: B1 - Residencial Baixa Renda | D99: ='B1 (Res) Branca OK'!D94 -> 0.5269162 | E99: ='B1 (Res) Branca OK'!E94 -> 0.11116112 | F99: ='B1 (Res) Branca OK'!F94 -> 0.30321524 | G99: ='B1 (Res) Branca OK'!G94 -> 0.058707433
B100: B2 - Rural | D100: ='B1 (Res) Branca OK'!D95 -> 0.439393 | E100: ='B1 (Res) Branca OK'!E95 -> 0.092696751 | F100: ='B1 (Res) Branca OK'!F95 -> 0.2528498 | G100: ='B1 (Res) Branca OK'!G95 -> 0.21506045
B101: B2 - Cooperativa Eletrificação Rural | D101: ='B1 (Res) Branca OK'!D96 -> 0.439393 | E101: ='B1 (Res) Branca OK'!E96 -> 0.092696751 | F101: ='B1 (Res) Branca OK'!F96 -> 0.2528498 | G101: ='B1 (Res) Branca OK'!G96 -> 0.21506045
B102: B2 - Serviço de Irrigação | D102: ='B1 (Res) Branca OK'!D97 -> 0.439393 | E102: ='B1 (Res) Branca OK'!E97 -> 0.092696751 | F102: ='B1 (Res) Branca OK'!F97 -> 0.2528498 | G102: ='B1 (Res) Branca OK'!G97 -> 0.21506045
B103: B3 - Demais Classes | D103: ='B1 (Res) Branca OK'!D98 -> 0.439393 | E103: ='B1 (Res) Branca OK'!E98 -> 0.092696751 | F103: ='B1 (Res) Branca OK'!F98 -> 0.2528498 | G103: ='B1 (Res) Branca OK'!G98 -> 0.21506045
B104: B4 - Iluminação Pública | D104: ='B1 (Res) Branca OK'!D99 -> 0 | E104: ='B1 (Res) Branca OK'!E99 -> 0 | F104: ='B1 (Res) Branca OK'!F99 -> 0 | G104: ='B1 (Res) Branca OK'!G99 -> 0
B105: B4a - Rede de Distribuição | D105: ='B1 (Res) Branca OK'!D100 -> 0.43938946 | E105: ='B1 (Res) Branca OK'!E100 -> 0.092697337 | F105: ='B1 (Res) Branca OK'!F100 -> 0.2528514 | G105: ='B1 (Res) Branca OK'!G100 -> 0.21506181
B106: B4b - Bulbo de Lâmpada | D106: ='B1 (Res) Branca OK'!D101 -> 0.43938946 | E106: ='B1 (Res) Branca OK'!E101 -> 0.092697337 | F106: ='B1 (Res) Branca OK'!F101 -> 0.2528514 | G106: ='B1 (Res) Branca OK'!G101 -> 0.21506181
B108: proporcional
D109: Energia | E109: Transmissão | F109: Distribuição | G109: Setoriais
B110: Grupo B | D110: % | E110: % | F110: % | G110: %
B112: B1 - Residencial | D112: =((D98*$C$46)+(D84*$D$46))/($C$46+$D$46) -> 0.44549499 | E112: =((E98*$C$46)+(E84*$D$46))/($C$46+$D$46) -> 0.083953104 | F112: =((F98*$C$46)+(F84*$D$46))/($C$46+$D$46) -> 0.26319204 | G112: =((G98*$C$46)+(G84*$D$46))/($C$46+$D$46) -> 0.20736505
B113: B1 - Residencial Baixa Renda | D113: =((D99*$C$46)+(D85*$D$46))/($C$46+$D$46) -> 0.52905333 | E113: =((E99*$C$46)+(E85*$D$46))/($C$46+$D$46) -> 0.099828928 | F113: =((F99*$C$46)+(F85*$D$46))/($C$46+$D$46) -> 0.31246903 | G113: =((G99*$C$46)+(G85*$D$46))/($C$46+$D$46) -> 0.058648717
B114: B2 - Rural | D114: =((D100*$C$46)+(D86*$D$46))/($C$46+$D$46) -> 0.44549288 | E114: =((E100*$C$46)+(E86*$D$46))/($C$46+$D$46) -> 0.083952659 | F114: =((F100*$C$46)+(F86*$D$46))/($C$46+$D$46) -> 0.26319082 | G114: =((G100*$C$46)+(G86*$D$46))/($C$46+$D$46) -> 0.20736364
B115: B2 - Cooperativa Eletrificação Rural | D115: =((D101*$C$46)+(D87*$D$46))/($C$46+$D$46) -> 0.44549288 | E115: =((E101*$C$46)+(E87*$D$46))/($C$46+$D$46) -> 0.083952659 | F115: =((F101*$C$46)+(F87*$D$46))/($C$46+$D$46) -> 0.26319082 | G115: =((G101*$C$46)+(G87*$D$46))/($C$46+$D$46) -> 0.20736364
B116: B2 - Serviço de Irrigação | D116: =((D102*$C$46)+(D88*$D$46))/($C$46+$D$46) -> 0.44549288 | E116: =((E102*$C$46)+(E88*$D$46))/($C$46+$D$46) -> 0.083952659 | F116: =((F102*$C$46)+(F88*$D$46))/($C$46+$D$46) -> 0.26319082 | G116: =((G102*$C$46)+(G88*$D$46))/($C$46+$D$46) -> 0.20736364
B117: B3 - Demais Classes | D117: =((D103*$C$46)+(D89*$D$46))/($C$46+$D$46) -> 0.44549288 | E117: =((E103*$C$46)+(E89*$D$46))/($C$46+$D$46) -> 0.083952659 | F117: =((F103*$C$46)+(F89*$D$46))/($C$46+$D$46) -> 0.26319082 | G117: =((G103*$C$46)+(G89*$D$46))/($C$46+$D$46) -> 0.20736364
B118: B4 - Iluminação Pública | D118: =((D104*$C$46)+(D90*$D$46))/($C$46+$D$46) -> 0.21114994 | E118: =((E104*$C$46)+(E90*$D$46))/($C$46+$D$46) -> 0.034514392 | F118: =((F104*$C$46)+(F90*$D$46))/($C$46+$D$46) -> 0.1283376 | G118: =((G104*$C$46)+(G90*$D$46))/($C$46+$D$46) -> 0.092664735
B119: B4a - Rede de Distribuição | D119: =((D105*$C$46)+(D91*$D$46))/($C$46+$D$46) -> 0.44549099 | E119: =((E105*$C$46)+(E91*$D$46))/($C$46+$D$46) -> 0.083952971 | F119: =((F105*$C$46)+(F91*$D$46))/($C$46+$D$46) -> 0.26319168 | G119: =((G105*$C$46)+(G91*$D$46))/($C$46+$D$46) -> 0.20736437
B120: B4b - Bulbo de Lâmpada | D120: =((D106*$C$46)+(D92*$D$46))/($C$46+$D$46) -> 0.44549099 | E120: =((E106*$C$46)+(E92*$D$46))/($C$46+$D$46) -> 0.083952971 | F120: =((F106*$C$46)+(F92*$D$46))/($C$46+$D$46) -> 0.26319168 | G120: =((G106*$C$46)+(G92*$D$46))/($C$46+$D$46) -> 0.20736437

Sheet O3 Branca
B2: OPTANTE | E2: Vigência das Tarifas: | F2: ='B1 (Res) Branca OK'!F2 -> 46241 | H2: TARIFA BRANCA | M2: Bandeira | N2: R$/kWh | Q2: TUSD FIO B
M3: VERDE | N3: ='B1 (Res) Branca OK'!N3 -> 0
B4: TARIFA | C4: ='B1 (Res) Branca OK'!C4 -> TARIFA ANTIGA - REH 3370/2024 | F4: ='B1 (Res) Branca OK'!F4 -> TARIFA NOVA - REH xxxx/2025 | I4: Tarifas Proporcionalizadas | M4: BAM | N4: ='B1 (Res) Branca OK'!N4 -> 0.01885 | Q4: TARIFA | R4: =C4 -> TARIFA ANTIGA - REH 3370/2024 | U4: =F4 -> TARIFA NOVA - REH xxxx/2025 | X4: Tarifas Proporcionalizadas
C5: Tusd | D5: TE | E5: TUSD + TE | F5: Tusd | G5: TE | H5: TUSD + TE | I5: Tusd | J5: TE | K5: TUSD + TE | M5: BVM1 | N5: ='B1 (Res) Branca OK'!N5 -> 0.04463 | R5: Tusd (R$/kWh) | U5: Tusd (R$/kWh) | X5: Tusd (R$/kWh)
B6: B3 Ponta | C6: ='TABELA DE TARIFAS ANTIGAS'!G85/1000 -> 0.46863 | D6: ='TABELA DE TARIFAS ANTIGAS'!H85/1000 -> 0.32068 | E6: =C6+D6 -> 0.78931 | F6: ='TABELA DE TARIFAS NOVAS'!G87/1000 -> 0.50632 | G6: ='TABELA DE TARIFAS NOVAS'!H87/1000 -> 0.33739 | H6: =F6+G6 -> 0.84371 | I6: =((C6*$C$15)+(F6*$D$15))/($D$15+$C$15) -> -0.57453194 | J6: =((D6*$C$15)+(G6*$D$15))/($D$15+$C$15) -> -0.14180968 | K6: =I6+J6 -> -0.71634161 | M6: BVM2 | N6: ='B1 (Res) Branca OK'!N6 -> 0.07877 | Q6: =B6 -> B3 Ponta | R6: ='FIO B'!H29/1000 -> 0.20383072 | U6: ='FIO B'!K29/1000 -> 0.20915159 | X6: =((R6*$C$15)+(U6*$D$15))/($D$15+$C$15) -> 0.056562764
B7: B3 Fora Ponta | C7: ='TABELA DE TARIFAS ANTIGAS'!G87/1000 -> 0.72534 | D7: ='TABELA DE TARIFAS ANTIGAS'!H87/1000 -> 0.30579 | E7: =C7+D7 -> 1.03113 | F7: ='TABELA DE TARIFAS NOVAS'!G89/1000 -> 0.77601 | G7: ='TABELA DE TARIFAS NOVAS'!H89/1000 -> 0.32107 | H7: =F7+G7 -> 1.09708 | I7: =((C7*$C$15)+(F7*$D$15))/($D$15+$C$15) -> -0.67707484 | J7: =((D7*$C$15)+(G7*$D$15))/($D$15+$C$15) -> -0.11712097 | K7: =I7+J7 -> -0.79419581 | M7: Escassez Hídrica | N7: ='B1 (Res) Branca OK'!N7 -> 0.142 | Q7: =B7 -> B3 Fora Ponta | R7: ='FIO B'!H31/1000 -> 0.69302445 | U7: ='FIO B'!K31/1000 -> 0.71111541 | X7: =((R7*$C$15)+(U7*$D$15))/($D$15+$C$15) -> 0.1923134
B8: B3 Interm. | C8: ='TABELA DE TARIFAS ANTIGAS'!G86/1000 -> 1.06103 | D8: ='TABELA DE TARIFAS ANTIGAS'!H86/1000 -> 0.48448 | E8: =C8+D8 -> 1.54551 | F8: ='TABELA DE TARIFAS NOVAS'!G88/1000 -> 1.12867 | G8: ='TABELA DE TARIFAS NOVAS'!H88/1000 -> 0.51691 | H8: =F8+G8 -> 1.64558 | I8: =((C8*$C$15)+(F8*$D$15))/($D$15+$C$15) -> -0.81107065 | J8: =((D8*$C$15)+(G8*$D$15))/($D$15+$C$15) -> -0.41309871 | K8: =I8+J8 -> -1.2241694 | Q8: =B8 -> B3 Interm. | R8: ='FIO B'!H30/1000 -> 0.20383072 | U8: ='FIO B'!K30/1000 -> 0.20915159 | X8: =((R8*$C$15)+(U8*$D$15))/($D$15+$C$15) -> 0.056562764
B9: B1 | C9: ='TABELA DE TARIFAS ANTIGAS'!G71/1000 -> 0.46863 | D9: ='TABELA DE TARIFAS ANTIGAS'!H71/1000 -> 0.32068 | E9: =C9+D9 -> 0.78931 | F9: ='TABELA DE TARIFAS NOVAS'!G73/1000 -> 0.50632 | G9: ='TABELA DE TARIFAS NOVAS'!H73/1000 -> 0.33739 | H9: =F9+G9 -> 0.84371 | I9: =((C9*$C$15)+(F9*$D$15))/($D$15+$C$15) -> -0.57453194 | J9: =((D9*$C$15)+(G9*$D$15))/($D$15+$C$15) -> -0.14180968 | K9: =I9+J9 -> -0.71634161
B10: CDE Escassez Hídrica | C10: ='B1 (Res) Branca OK'!C9 -> 0.00018774721 | D10: ='B1 (Res) Branca OK'!D9 -> -0.0044031307 | E10: =SUM(C10+D10) -> -0.0042153835 | F10: =T13 -> 0.00017567286 | G10: =U13 -> 0.0034297355 | H10: =F10+G10 -> 0.0036054084 | I10: =((C10*$C$15)+(F10*$D$15))/($D$15+$C$15) -> 0.0005219342 | J10: =((D10*$C$15)+(G10*$D$15))/($D$15+$C$15) -> -0.22119666 | K10: =I10+J10 -> -0.22067472 | P10: CUSTO | R10: Part. TUSD (%) | S10: Part. TE (%) | T10: Tusd (R$/kWh) | U10: TE (R$/kWh)
H11: Fatura | L11: Vigência das Tarifas (troca Bandeira): | M11: 45352 | P11: CDE CONTAS
B12: INSTALAÇÃO | C12: 1787048 | H12: =E15 -> 45382 | K12: Altere a bandeira na célula abaixo | P12: CDE COVID | U12: =5.61/1000 -> 0.00561
K13: VERDE | L13: VERDE | P13: CDE ESCASSEZ HÍDRICA | T13: =0.175672859965349/1000 -> 0.00017567286 | U13: =3.42973552660492/1000 -> 0.0034297355
B14: Leitura Anterior | C14: Nº de dias tarifa Anterior | D14: Nº de dias tarifa Nova | E14: Leitura Atual | J14: Leitura Anterior | K14: Nº de dias tarifa Anterior | L14: Nº de dias tarifa Nova | M14: Leitura Atual
B15: 45351 | C15: =IF((F2-B15-1)<0,0,(F2-B15-1)) -> 889 | D15: =E15-F2+1 -> -858 | E15: 45382 | J15: =B15 -> 45351 | K15: =IF((M11-J15-1)<0,0,(M11-J15-1)) -> 0 | L15: =M15-M11+1 -> 31 | M15: =E15 -> 45382
B17: Descrição | C17: Unidade | D17: Quantidade | E17: Preço Unit (R$) com tributos | F17: Valor Total (R$) | G17: PIS/COFINS (R$) | H17: Base de Cálculo ICMS (R$) | I17: Alíquota ICMS (%) | J17: ICMS (R$) | K17: Preço Unit (R$) | L17: Tributos | M17: Base de Cálc (R$) | N17: Alíquota (%) | O17: Valor (R$)
B19: TUSD - Consumo Ponta | C19: kWh | D19: 23.94 | E19: =(ROUND(D19*K19,2)+ROUND(G19,2)+ROUND(J19,2))/ROUND(D19,4) -> 0.59314954 | F19: =ROUND(D19*E19,2) -> 14.2 | G19: =((D19*K19)/(1-$N$19-$N$20))*($N$19+$N$20) -> 0.56566398 | H19: =ROUND((D19*K19)/(1-$N$19-$N$20)/(1-$I$19),8) -> 14.198393 | I19: 0.17 | J19: =H19*$I$19 -> 2.4137268 | K19: =IF(AND($B$15<$F$2,$E$15<$F$2),C6,IF($B$15<$F$2,I6,F6)) -> 0.46863 | L19: PIS | M19: =D60 -> 5453.855 | N19: 0.0085 | O19: =ROUND(M19*N19,2) -> 46.36
B20: TUSD - Consumo Intermediário | C20: kWh | D20: 20.3 | E20: =(ROUND(D20*K20,2)+ROUND(G20,2)+ROUND(J20,2))/ROUND(D20,4) -> 1.3428571 | F20: =ROUND(D20*E20,2) -> 27.26 | G20: =((D20*K20)/(1-$N$19-$N$20))*($N$19+$N$20) -> 1.0859954 | H20: =ROUND((D20*K20)/(1-$N$19-$N$20)/(1-$I$19),8) -> 27.258921 | I20: =I19 -> 0.17 | J20: =H20*$I$19 -> 4.6340166 | K20: =IF(AND($B$15<$F$2,$E$15<$F$2),C8,IF($B$15<$F$2,I8,F8)) -> 1.06103 | L20: COFINS | M20: =M19 -> 5453.855 | N20: 0.0395 | O20: =ROUND(M20*N20,2) -> 215.43
B21: TUSD - Consumo Fora Ponta | C21: kWh | D21: 4981.9 | E21: =(ROUND(D21*K21,2)+ROUND(G21,2)+ROUND(J21,2))/ROUND(D21,4) -> 0.91796704 | F21: =ROUND(D21*E21,2) -> 4573.22 | G21: =((D21*K21)/(1-$N$19-$N$20))*($N$19+$N$20) -> 182.19687 | H21: =ROUND((D21*K21)/(1-$N$19-$N$20)/(1-$I$19),8) -> 4573.2147 | I21: =I19 -> 0.17 | J21: =H21*$I$19 -> 777.4465 | K21: =IF(AND($B$15<$F$2,$E$15<$F$2),C7,IF($B$15<$F$2,I7,F7)) -> 0.72534
B22: TE - Consumo Ponta | C22: kWh | D22: =D19 -> 23.94 | E22: =(ROUND(D22*K22,2)+ROUND(G22,2)+ROUND(J22,2))/ROUND(D22,4) -> 0.40601504 | F22: =ROUND(D22*E22,2) -> 9.72 | G22: =((D22*K22)/(1-$N$19-$N$20))*($N$19+$N$20) -> 0.38707962 | H22: =(D22*K22)/(1-$N$19-$N$20)/(1-$I$19) -> 9.715854 | J22: =H22*$I$19 -> 1.6516952 | K22: =IF(AND($B$15<$F$2,$E$15<$F$2),D6,IF($B$15<$F$2,J6,G6)) -> 0.32068
B23: TE - Consumo Intermediário | C23: kWh | D23: =D20 -> 20.3 | E23: =(ROUND(D23*K23,2)+ROUND(G23,2)+ROUND(J23,2))/ROUND(D23,4) -> 0.61330049 | F23: =ROUND(D23*E23,2) -> 12.45 | G23: =((D23*K23)/(1-$N$19-$N$20))*($N$19+$N$20) -> 0.49587953 | H23: =(D23*K23)/(1-$N$19-$N$20)/(1-$I$19) -> 12.446775 | J23: =H23*$I$19 -> 2.1159518 | K23: =IF(AND($B$15<$F$2,$E$15<$F$2),D8,IF($B$15<$F$2,J8,G8)) -> 0.48448
B24: TE - Consumo Fora Ponta | C24: kWh | D24: =D21 -> 4981.9 | E24: =(ROUND(D24*K24,2)+ROUND(G24,2)+ROUND(J24,2))/ROUND(D24,4) -> 0.38699894 | F24: =ROUND(D24*E24,2) -> 1927.99 | G24: =((D24*K24)/(1-$N$19-$N$20))*($N$19+$N$20) -> 76.81085 | H24: =(D24*K24)/(1-$N$19-$N$20)/(1-$I$19) -> 1927.9832 | J24: =H24*$I$19 -> 327.75714 | K24: =IF(AND($B$15<$F$2,$E$15<$F$2),D7,IF($B$15<$F$2,J7,G7)) -> 0.30579
B25: Adicional BAM | C25: kWh | D25: =IF($K$13=M4,((D19+D20+D21)*(K15)/(K15+L15)),0)+IF($L$13=M4,((D19+D20+D21)*(L15)/(K15+L15)),0) -> 0 | E25: 0 | F25: =ROUND(D25*E25,2) -> 0 | G25: =((D25*K25)/(1-$N$19-$N$20))*($N$19+$N$20) -> 0 | H25: =(D25*K25)/(1-$N$19-$N$20)/(1-$I$19) -> 0 | J25: =H25*$I$19 -> 0 | K25: =N4 -> 0.01885
B26: Adicional BVM 1 | C26: kWh | D26: =IF($K$11=M5,(D19*(K13)/(K13+L13)),0)+IF($L$11=M5,(D19*(L13)/(K13+L13)),0) -> 0 | E26: =K26/(1-$N$19-$N$20)/(1-$I$19) -> 0.056482231 | F26: =ROUND(D26*E26,2) -> 0 | G26: =((D26*K26)/(1-$N$19-$N$20))*($N$19+$N$20) -> 0 | H26: =(D26*K26)/(1-$N$19-$N$20)/(1-$I$19) -> 0 | J26: =H26*$I$19 -> 0 | K26: =N5 -> 0.04463
B27: Adicional BVM 2 | C27: kWh | D27: =IF($K$11=M6,(D19*(K13)/(K13+L13)),0)+IF($L$11=M6,(D19*(L13)/(K13+L13)),0) -> 0 | E27: =K27/(1-$N$19-$N$20)/(1-$I$19) -> 0.099688671 | F27: =ROUND(D27*E27,2) -> 0 | G27: =((D27*K27)/(1-$N$19-$N$20))*($N$19+$N$20) -> 0 | H27: =(D27*K27)/(1-$N$19-$N$20)/(1-$I$19) -> 0 | J27: =H27*$I$19 -> 0 | K27: =N6 -> 0.07877
B28: Adicional Escassez | C28: kWh | D28: =IF($K$11=M7,(D19*(K13)/(K13+L13)),0)+IF($L$11=M7,(D19*(L13)/(K13+L13)),0) -> 0 | E28: =K28/(1-$N$19-$N$20)/(1-$I$19) -> 0.17971044 | F28: =ROUND(D28*E28,2) -> 0 | G28: =((D28*K28)/(1-$N$19-$N$20))*($N$19+$N$20) -> 0 | H28: =(D28*K28)/(1-$N$19-$N$20)/(1-$I$19) -> 0 | J28: =H28*$I$19 -> 0 | K28: =N7 -> 0.142
B29: Juros
B30: Multas
B31: CIP | F31: 84.97
B32: ERE - Ponta | D32: 1.16 | E32: =(ROUND(D32*K32,2)+ROUND(G32,2)+ROUND(J32,2))/ROUND(D32,4) -> 0.40517241 | F32: =ROUND(D32*E32,2) -> 0.47 | G32: =((D32*K32)/(1-$N$19-$N$20))*($N$19+$N$20) -> 0.018755738 | H32: =(D32*K32)/(1-$N$19-$N$20)/(1-$I$19) -> 0.47077655 | J32: =H32*$I$19 -> 0.080032014 | K32: =IF(AND($B$15<$F$2,$E$15<$F$2),D9,IF($B$15<$F$2,J9,G9)) -> 0.32068
B33: ERE - Fora Ponta | D33: 1.18 | E33: =(ROUND(D33*K33,2)+ROUND(G33,2)+ROUND(J33,2))/ROUND(D33,4) -> 0.40677966 | F33: =ROUND(D33*E33,2) -> 0.48 | G33: =((D33*K33)/(1-$N$19-$N$20))*($N$19+$N$20) -> 0.019079113 | H33: =(D33*K33)/(1-$N$19-$N$20)/(1-$I$19) -> 0.47889339 | J33: =H33*$I$19 -> 0.081411876 | K33: =IF(AND($B$15<$F$2,$E$15<$F$2),D9,IF($B$15<$F$2,J9,G9)) -> 0.32068
B35: TOTAL | F35: =SUM(F19:F34) -> 6650.76 | G35: =SUM(G19:G34) -> 261.58018 | H35: =SUM(H19:H34) -> 6565.7675 | J35: =SUM(J19:J34) -> 1116.1805
B37: Informativo Escassez | C37: =D19+D20+D21 -> 5026.14 | D37: =IF(AND($B$15<$F$2,$E$15<$F$2),C10,IF($B$15<$F$2,I10,F10)) -> 0.00018774721 | E37: =IF(AND($B$15<$F$2,$E$15<$F$2),D10,IF($B$15<$F$2,J10,G10)) -> -0.0044031307 | F37: =C37*(D37+E37) -> -21.187108
B42: Fatura B3 - TB
D43: Qtde | E43: TUSD | F43: TE | G43: TUSD + TE | H43: R$ | J43: Documento simulado: | L43: 30005965989
B44: Fornecimento de Energia Elétrica | H44: =SUM(H46:H54)+SUM(H60:H62) -> 6566.0997
R45: TUSD Fio B | S45: Receita Fio B
B46: Consumo Ponta | D46: =D19 -> 23.94 | E46: =IF(AND($B$15<$F$2,$E$15<$F$2),C6,IF($B$15<$F$2,I6,F6)) -> 0.46863 | F46: =IF(AND($B$15<$F$2,$E$15<$F$2),D6,IF($B$15<$F$2,J6,G6)) -> 0.32068 | G46: 1.325 | H46: =ROUND((D46*E46),2)+ROUND((D46*F46),2) -> 18.9 | R46: =IF(AND($B$15<$F$2,$E$15<$F$2),R6,IF($B$15<$F$2,X6,U6)) -> 0.20383072 | S46: =D46*R46 -> 4.8797075
B47: Consumo Fora Ponta | D47: =D21 -> 4981.9 | E47: =IF(AND($B$15<$F$2,$E$15<$F$2),C7,IF($B$15<$F$2,I7,F7)) -> 0.72534 | F47: =IF(AND($B$15<$F$2,$E$15<$F$2),D7,IF($B$15<$F$2,J7,G7)) -> 0.30579 | G47: 0.5328 | H47: =ROUND((D47*E47),2)+ROUND((D47*F47),2) -> 5136.99 | R47: =IF(AND($B$15<$F$2,$E$15<$F$2),R7,IF($B$15<$F$2,X7,U7)) -> 0.69302445 | S47: =D47*R47 -> 3452.5785
B48: Consumo Intemediário | D48: =D20 -> 20.3 | E48: =IF(AND($B$15<$F$2,$E$15<$F$2),C8,IF($B$15<$F$2,I8,F8)) -> 1.06103 | F48: =IF(AND($B$15<$F$2,$E$15<$F$2),D8,IF($B$15<$F$2,J8,G8)) -> 0.48448 | G48: 0.84406 | H48: =ROUND((D48*E48),2)+ROUND((D48*F48),2) -> 31.37 | R48: =IF(AND($B$15<$F$2,$E$15<$F$2),R8,IF($B$15<$F$2,X8,U8)) -> 0.20383072 | S48: =D48*R48 -> 4.1377637
S49: =SUM(S46:S48) -> 3461.596
B51: Adicional BAM | D51: =IF($K$13=M4,((D46+D47+D48)*(K15)/(K15+L15)),0)+IF($L$13=M4,((D46+D47+D48)*(L15)/(K15+L15)),0) -> 0 | F51: =N4 -> 0.01885 | H51: =ROUND(D51*(E51+F51),2) -> 0
B52: Adicional BVM 1 | D52: =IF($K$13=M5,((D46+D47+D48)*(K15)/(K15+L15)),0)+IF($L$13=M5,((D46+D47+D48)*(L15)/(K15+L15)),0) -> 0 | F52: =N5 -> 0.04463 | H52: =ROUND(D52*(E52+F52),2) -> 0
B53: Adicional BVM 2 | D53: =IF($K$13=M6,((D46+D47+D48)*(K15)/(K15+L15)),0)+IF($L$13=M6,((D46+D47+D48)*(L15)/(K15+L15)),0) -> 0 | F53: =N6 -> 0.07877 | H53: =ROUND(D53*(E53+F53),2) -> 0
B54: Adicional Escassez Hídrica | D54: =IF($K$13=M7,((D46+D47+D48)*(K15)/(K15+L15)),0)+IF($L$13=M7,((D46+D47+D48)*(L15)/(K15+L15)),0) -> 0 | F54: =N7 -> 0.142 | H54: =ROUND(D54*(E54+F54),2) -> 0
B56: ERE | D56: 15 | F56: =IF(AND($B$15<$F$2,$E$15<$F$2),D9,IF($B$15<$F$2,J9,G9)) -> 0.32068 | G56: 0.84406 | H56: =ROUND((D56*E56),2)+ROUND((D56*F56),2) -> 4.81
D59: Base de Cálculo
B60: PIS | D60: =(SUM(H46:H57)/(1-E60-E61)) -> 5453.855 | E60: =N19 -> 0.0085 | H60: =D60*E60 -> 46.357768
B61: COFINS | D61: =D60 -> 5453.855 | E61: =N20 -> 0.0395 | H61: =D61*E61 -> 215.42727
B62: ICMS | D62: =D60/(1-E62) -> 6570.9097 | E62: 0.17 | H62: =D62*E62 -> 1117.0546
B64: Informativo Escassez Hídrica | D64: =SUM(D46:D48) -> 5026.14 | E64: =IF(AND($B$15<$F$2,$E$15<$F$2),C10,IF($B$15<$F$2,I10,F10)) -> 0.00018774721 | F64: =IF(AND($B$15<$F$2,$E$15<$F$2),D10,IF($B$15<$F$2,J10,G10)) -> -0.0044031307 | H64: =D64*(E64+F64) -> -21.187108
B66: Participação
C67: R$
B68: Energia | C68: =(SUM(H46:H57)*IF($B$15<$F$2,D106,D78)) -> 403.58184
B69: Distribuição | C69: =(SUM(H46:H57)*IF($B$15<$F$2,F106,F78)) -> -1871.2116
B70: Transmissão | C70: =(SUM(H46:H57)*IF($B$15<$F$2,E106,E78)) -> 3174.0261
B71: Encargos Setoriais | C71: =(SUM(H46:H57)*IF($B$15<$F$2,G106,G78)) -> 3487.1191
B72: Impostos / Tributos | C72: =H60+H61+H62 -> 1378.8397
B73: Total | C73: =SUM(C68:C72) -> 6572.3551
B75: ='B1 (Res) Branca OK'!B76 -> 2024 | D75: Energia | E75: Transmissão | F75: Distribuição | G75: Setoriais
B76: Grupo B | D76: % | E76: % | F76: % | G76: %
B78: B1 - Residencial | D78: ='B1 (Res) Branca OK'!D79 -> 0.45246417 | E78: ='B1 (Res) Branca OK'!E79 -> 0.073959411 | F78: ='B1 (Res) Branca OK'!F79 -> 0.27500913 | G78: ='B1 (Res) Branca OK'!G79 -> 0.19856729
B79: B1 - Residencial Baixa Renda | D79: ='B1 (Res) Branca OK'!D80 -> 0.53149576 | E79: ='B1 (Res) Branca OK'!E80 -> 0.086877849 | F79: ='B1 (Res) Branca OK'!F80 -> 0.32304478 | G79: ='B1 (Res) Branca OK'!G80 -> 0.058581612
B80: B2 - Rural | D80: ='B1 (Res) Branca OK'!D81 -> 0.45246417 | E80: ='B1 (Res) Branca OK'!E81 -> 0.073959411 | F80: ='B1 (Res) Branca OK'!F81 -> 0.27500913 | G80: ='B1 (Res) Branca OK'!G81 -> 0.19856729
B81: B2 - Cooperativa Eletrificação Rural | D81: ='B1 (Res) Branca OK'!D82 -> 0.45246417 | E81: ='B1 (Res) Branca OK'!E82 -> 0.073959411 | F81: ='B1 (Res) Branca OK'!F82 -> 0.27500913 | G81: ='B1 (Res) Branca OK'!G82 -> 0.19856729
B82: B2 - Serviço de Irrigação | D82: ='B1 (Res) Branca OK'!D83 -> 0.45246417 | E82: ='B1 (Res) Branca OK'!E83 -> 0.073959411 | F82: ='B1 (Res) Branca OK'!F83 -> 0.27500913 | G82: ='B1 (Res) Branca OK'!G83 -> 0.19856729
B83: B3 - Demais Classes | D83: ='B1 (Res) Branca OK'!D84 -> 0.45246417 | E83: ='B1 (Res) Branca OK'!E84 -> 0.073959411 | F83: ='B1 (Res) Branca OK'!F84 -> 0.27500913 | G83: ='B1 (Res) Branca OK'!G84 -> 0.19856729
B84: B4 - Iluminação Pública | D84: ='B1 (Res) Branca OK'!D85 -> 0.45246417 | E84: ='B1 (Res) Branca OK'!E85 -> 0.073959411 | F84: ='B1 (Res) Branca OK'!F85 -> 0.27500913 | G84: ='B1 (Res) Branca OK'!G85 -> 0.19856729
B85: B4a - Rede de Distribuição | D85: ='B1 (Res) Branca OK'!D86 -> 0.45246417 | E85: ='B1 (Res) Branca OK'!E86 -> 0.073959411 | F85: ='B1 (Res) Branca OK'!F86 -> 0.27500913 | G85: ='B1 (Res) Branca OK'!G86 -> 0.19856729
B86: B4b - Bulbo de Lâmpada | D86: ='B1 (Res) Branca OK'!D87 -> 0.45246417 | E86: ='B1 (Res) Branca OK'!E87 -> 0.073959411 | F86: ='B1 (Res) Branca OK'!F87 -> 0.27500913 | G86: ='B1 (Res) Branca OK'!G87 -> 0.19856729
B89: ='B1 (Res) Branca OK'!B90 -> 2023 | D89: Energia | E89: Transmissão | F89: Distribuição | G89: Setoriais
B90: Grupo B | D90: % | E90: % | F90: % | G90: %
B92: B1 - Residencial | D92: ='B1 (Res) Branca OK'!D93 -> 0.43939696 | E92: ='B1 (Res) Branca OK'!E93 -> 0.092697586 | F92: ='B1 (Res) Branca OK'!F93 -> 0.25285208 | G92: ='B1 (Res) Branca OK'!G93 -> 0.21506308
B93: B1 - Residencial Baixa Renda | D93: ='B1 (Res) Branca OK'!D94 -> 0.5269162 | E93: ='B1 (Res) Branca OK'!E94 -> 0.11116112 | F93: ='B1 (Res) Branca OK'!F94 -> 0.30321524 | G93: ='B1 (Res) Branca OK'!G94 -> 0.058707433
B94: B2 - Rural | D94: ='B1 (Res) Branca OK'!D95 -> 0.439393 | E94: ='B1 (Res) Branca OK'!E95 -> 0.092696751 | F94: ='B1 (Res) Branca OK'!F95 -> 0.2528498 | G94: ='B1 (Res) Branca OK'!G95 -> 0.21506045
B95: B2 - Cooperativa Eletrificação Rural | D95: ='B1 (Res) Branca OK'!D96 -> 0.439393 | E95: ='B1 (Res) Branca OK'!E96 -> 0.092696751 | F95: ='B1 (Res) Branca OK'!F96 -> 0.2528498 | G95: ='B1 (Res) Branca OK'!G96 -> 0.21506045
B96: B2 - Serviço de Irrigação | D96: ='B1 (Res) Branca OK'!D97 -> 0.439393 | E96: ='B1 (Res) Branca OK'!E97 -> 0.092696751 | F96: ='B1 (Res) Branca OK'!F97 -> 0.2528498 | G96: ='B1 (Res) Branca OK'!G97 -> 0.21506045
B97: B3 - Demais Classes | D97: ='B1 (Res) Branca OK'!D98 -> 0.439393 | E97: ='B1 (Res) Branca OK'!E98 -> 0.092696751 | F97: ='B1 (Res) Branca OK'!F98 -> 0.2528498 | G97: ='B1 (Res) Branca OK'!G98 -> 0.21506045
B98: B4 - Iluminação Pública | D98: ='B1 (Res) Branca OK'!D99 -> 0 | E98: ='B1 (Res) Branca OK'!E99 -> 0 | F98: ='B1 (Res) Branca OK'!F99 -> 0 | G98: ='B1 (Res) Branca OK'!G99 -> 0
B99: B4a - Rede de Distribuição | D99: ='B1 (Res) Branca OK'!D100 -> 0.43938946 | E99: ='B1 (Res) Branca OK'!E100 -> 0.092697337 | F99: ='B1 (Res) Branca OK'!F100 -> 0.2528514 | G99: ='B1 (Res) Branca OK'!G100 -> 0.21506181
B100: B4b - Bulbo de Lâmpada | D100: ='B1 (Res) Branca OK'!D101 -> 0.43938946 | E100: ='B1 (Res) Branca OK'!E101 -> 0.092697337 | F100: ='B1 (Res) Branca OK'!F101 -> 0.2528514 | G100: ='B1 (Res) Branca OK'!G101 -> 0.21506181
B102: proporcional
D103: Energia | E103: Transmissão | F103: Distribuição | G103: Setoriais
B104: Grupo B | D104: % | E104: % | F104: % | G104: %
B106: B1 - Residencial | D106: =((D92*$C$15)+(D78*$D$15))/($C$15+$D$15) -> 0.077730431 | E106: =((E92*$C$15)+(E78*$D$15))/($C$15+$D$15) -> 0.6113219 | F106: =((F92*$C$15)+(F78*$D$15))/($C$15+$D$15) -> -0.36039799 | G106: =((G92*$C$15)+(G78*$D$15))/($C$15+$D$15) -> 0.67162405
B107: B1 - Residencial Baixa Renda | D107: =((D93*$C$15)+(D79*$D$15))/($C$15+$D$15) -> 0.40016583 | E107: =((E93*$C$15)+(E79*$D$15))/($C$15+$D$15) -> 0.78325949 | F107: =((F93*$C$15)+(F79*$D$15))/($C$15+$D$15) -> -0.24561518 | G107: =((G93*$C$15)+(G79*$D$15))/($C$15+$D$15) -> 0.062189852
B108: B2 - Rural | D108: =((D94*$C$15)+(D80*$D$15))/($C$15+$D$15) -> 0.077616917 | E108: =((E94*$C$15)+(E80*$D$15))/($C$15+$D$15) -> 0.61129795 | F108: =((F94*$C$15)+(F80*$D$15))/($C$15+$D$15) -> -0.36046331 | G108: =((G94*$C$15)+(G80*$D$15))/($C$15+$D$15) -> 0.67154844
B109: B2 - Cooperativa Eletrificação Rural | D109: =((D95*$C$15)+(D81*$D$15))/($C$15+$D$15) -> 0.077616917 | E109: =((E95*$C$15)+(E81*$D$15))/($C$15+$D$15) -> 0.61129795 | F109: =((F95*$C$15)+(F81*$D$15))/($C$15+$D$15) -> -0.36046331 | G109: =((G95*$C$15)+(G81*$D$15))/($C$15+$D$15) -> 0.67154844
B110: B2 - Serviço de Irrigação | D110: =((D96*$C$15)+(D82*$D$15))/($C$15+$D$15) -> 0.077616917 | E110: =((E96*$C$15)+(E82*$D$15))/($C$15+$D$15) -> 0.61129795 | F110: =((F96*$C$15)+(F82*$D$15))/($C$15+$D$15) -> -0.36046331 | G110: =((G96*$C$15)+(G82*$D$15))/($C$15+$D$15) -> 0.67154844
B111: B3 - Demais Classes | D111: =((D97*$C$15)+(D83*$D$15))/($C$15+$D$15) -> 0.077616917 | E111: =((E97*$C$15)+(E83*$D$15))/($C$15+$D$15) -> 0.61129795 | F111: =((F97*$C$15)+(F83*$D$15))/($C$15+$D$15) -> -0.36046331 | G111: =((G97*$C$15)+(G83*$D$15))/($C$15+$D$15) -> 0.67154844
B112: B4 - Iluminação Pública | D112: =((D98*$C$15)+(D84*$D$15))/($C$15+$D$15) -> -12.52304 | E112: =((E98*$C$15)+(E84*$D$15))/($C$15+$D$15) -> -2.0470056 | F112: =((F98*$C$15)+(F84*$D$15))/($C$15+$D$15) -> -7.6115431 | G112: =((G98*$C$15)+(G84*$D$15))/($C$15+$D$15) -> -5.4958302
B113: B4a - Rede de Distribuição | D113: =((D99*$C$15)+(D85*$D$15))/($C$15+$D$15) -> 0.077515251 | E113: =((E99*$C$15)+(E85*$D$15))/($C$15+$D$15) -> 0.61131476 | F113: =((F99*$C$15)+(F85*$D$15))/($C$15+$D$15) -> -0.36041746 | G113: =((G99*$C$15)+(G85*$D$15))/($C$15+$D$15) -> 0.67158744
B114: B4b - Bulbo de Lâmpada | D114: =((D100*$C$15)+(D86*$D$15))/($C$15+$D$15) -> 0.077515251 | E114: =((E100*$C$15)+(E86*$D$15))/($C$15+$D$15) -> 0.61131476 | F114: =((F100*$C$15)+(F86*$D$15))/($C$15+$D$15) -> -0.36041746 | G114: =((G100*$C$15)+(G86*$D$15))/($C$15+$D$15) -> 0.67158744

Sheet B3 Branca (AES) NÃO
B2: B3 AES | E2: Vigência das Tarifas: | F2: ='B1 (Res) Branca OK'!F2 -> 46241 | H2: TARIFA BRANCA | M2: Bandeira | N2: R$/kWh | Q2: TUSD FIO B
M3: VERDE | N3: ='B1 (Res) Branca OK'!N3 -> 0
B4: TARIFA | C4: ='B1 (Res) Branca OK'!C4 -> TARIFA ANTIGA - REH 3370/2024 | F4: ='B1 (Res) Branca OK'!F4 -> TARIFA NOVA - REH xxxx/2025 | I4: Tarifas Proporcionalizadas | M4: BAM | N4: ='B1 (Res) Branca OK'!N4 -> 0.01885 | Q4: TARIFA | R4: =C4 -> TARIFA ANTIGA - REH 3370/2024 | U4: =F4 -> TARIFA NOVA - REH xxxx/2025 | X4: Tarifas Proporcionalizadas
C5: Tusd | D5: TE | E5: TUSD + TE | F5: Tusd | G5: TE | H5: TUSD + TE | I5: Tusd | J5: TE | K5: TUSD + TE | M5: BVM1 | N5: ='B1 (Res) Branca OK'!N5 -> 0.04463 | R5: Tusd (R$/kWh) | U5: Tusd (R$/kWh) | X5: Tusd (R$/kWh)
B6: B3 Ponta | C6: ='TABELA DE TARIFAS ANTIGAS'!G85/1000 -> 0.46863 | D6: ='TABELA DE TARIFAS ANTIGAS'!H85/1000 -> 0.32068 | E6: =C6+D6 -> 0.78931 | F6: ='TABELA DE TARIFAS NOVAS'!G87/1000 -> 0.50632 | G6: ='TABELA DE TARIFAS NOVAS'!H87/1000 -> 0.33739 | H6: =F6+G6 -> 0.84371 | I6: =((C6*$C$15)+(F6*$D$15))/($D$15+$C$15) -> -0.84687258 | J6: =((D6*$C$15)+(G6*$D$15))/($D$15+$C$15) -> -0.2625529 | K6: =I6+J6 -> -1.1094255 | M6: BVM2 | N6: ='B1 (Res) Branca OK'!N6 -> 0.07877 | Q6: =B6 -> B3 Ponta | R6: ='FIO B'!H29/1000 -> 0.20383072 | U6: ='FIO B'!K29/1000 -> 0.20915159 | X6: =((R6*$C$15)+(U6*$D$15))/($D$15+$C$15) -> 0.018115186
B7: B3 Fora Ponta | C7: ='TABELA DE TARIFAS ANTIGAS'!G87/1000 -> 0.72534 | D7: ='TABELA DE TARIFAS ANTIGAS'!H87/1000 -> 0.30579 | E7: =C7+D7 -> 1.03113 | F7: ='TABELA DE TARIFAS NOVAS'!G89/1000 -> 0.77601 | G7: ='TABELA DE TARIFAS NOVAS'!H89/1000 -> 0.32107 | H7: =F7+G7 -> 1.09708 | I7: =((C7*$C$15)+(F7*$D$15))/($D$15+$C$15) -> -1.0432065 | J7: =((D7*$C$15)+(G7*$D$15))/($D$15+$C$15) -> -0.22753129 | K7: =I7+J7 -> -1.2707377 | M7: Escassez Hídrica | N7: ='B1 (Res) Branca OK'!N7 -> 0.142 | Q7: =B7 -> B3 Fora Ponta | R7: ='FIO B'!H31/1000 -> 0.69302445 | U7: ='FIO B'!K31/1000 -> 0.71111541 | X7: =((R7*$C$15)+(U7*$D$15))/($D$15+$C$15) -> 0.061591631
B8: B3 Interm. | C8: ='TABELA DE TARIFAS ANTIGAS'!G86/1000 -> 1.06103 | D8: ='TABELA DE TARIFAS ANTIGAS'!H86/1000 -> 0.48448 | E8: =C8+D8 -> 1.54551 | F8: ='TABELA DE TARIFAS NOVAS'!G88/1000 -> 1.12867 | G8: ='TABELA DE TARIFAS NOVAS'!H88/1000 -> 0.51691 | H8: =F8+G8 -> 1.64558 | I8: =((C8*$C$15)+(F8*$D$15))/($D$15+$C$15) -> -1.2998242 | J8: =((D8*$C$15)+(G8*$D$15))/($D$15+$C$15) -> -0.64743161 | K8: =I8+J8 -> -1.9472558 | Q8: =B8 -> B3 Interm. | R8: ='FIO B'!H30/1000 -> 0.20383072 | U8: ='FIO B'!K30/1000 -> 0.20915159 | X8: =((R8*$C$15)+(U8*$D$15))/($D$15+$C$15) -> 0.018115186
B9: CDE Escassez Hídrica | C9: ='B1 (Res) Branca OK'!C9 -> 0.00018774721 | D9: ='B1 (Res) Branca OK'!D9 -> -0.0044031307 | E9: =SUM(C9+D9) -> -0.0042153835 | F9: =T13 -> 0.00017567286 | G9: =U13 -> 0.0034297355 | H9: =F9+G9 -> 0.0036054084 | I9: =((C9*$C$15)+(F9*$D$15))/($D$15+$C$15) -> 0.00060918115 | J9: =((D9*$C$15)+(G9*$D$15))/($D$15+$C$15) -> -0.27779543 | K9: =I9+J9 -> -0.27718625
P10: CUSTO | R10: Part. TUSD (%) | S10: Part. TE (%) | T10: Tusd (R$/kWh) | U10: TE (R$/kWh)
H11: Fatura | L11: Vigência das Tarifas (troca Bandeira): | M11: =EOMONTH(B15,0)+1 -> 45139 | P11: CDE CONTAS
B12: INSTALAÇÃO | H12: =E15 -> 45158 | K12: Altere a bandeira na célula abaixo | P12: CDE COVID | U12: =5.61/1000 -> 0.00561
K13: VERDE | L13: VERDE | P13: CDE ESCASSEZ HÍDRICA | T13: =0.175672859965349/1000 -> 0.00017567286 | U13: =3.42973552660492/1000 -> 0.0034297355
B14: Leitura Anterior | C14: Nº de dias tarifa Anterior | D14: Nº de dias tarifa Nova | E14: Leitura Atual | J14: Leitura Anterior | K14: Nº de dias tarifa Anterior | L14: Nº de dias tarifa Nova | M14: Leitura Atual
B15: 45127 | C15: =IF((F2-B15-1)<0,0,(F2-B15-1)) -> 1113 | D15: =E15-F2+1 -> -1082 | E15: 45158 | J15: =B15 -> 45127 | K15: =IF((M11-J15-1)<0,0,(M11-J15-1)) -> 11 | L15: =M15-M11+1 -> 20 | M15: =E15 -> 45158
F16: desconto: | G16: 0.03 | H16: 0.03
B17: Descrição | C17: Unidade | D17: Quantidade | E17: Preço Unit (R$) com tributos | F17: Valor Total (R$) | G17: PIS/COFINS (R$) | H17: Base de Cálculo ICMS (R$) | I17: Alíquota ICMS (%) | J17: ICMS (R$) | K17: Preço Unit (R$) | L17: Tributos | M17: Base de Cálc (R$) | N17: Alíquota (%) | O17: Valor (R$)
B19: TUSD - Consumo Ponta | C19: kWh | D19: 200 | E19: =(ROUND(D19*K19,2)+ROUND(G19,2)+ROUND(J19,2))/ROUND(D19,4) -> 0.5931 | F19: =ROUND(D19*E19,2) -> 118.62 | G19: =((D19*K19)/(1-$N$19-$N$20))*($N$19+$N$20) -> 4.7256807 | H19: =ROUND((D19*K19)/(1-$N$19-$N$20)/(1-$I$19),8) -> 118.61648 | I19: 0.17 | J19: =H19*$I$19 -> 20.164802 | K19: =IF(AND($B$15<$F$2,$E$15<$F$2),C6,IF($B$15<$F$2,I6,F6)) -> 0.46863 | L19: PIS | M19: =D62 -> 14256.086 | N19: 0.0085 | O19: =ROUND(M19*N19,2) -> 121.18
B20: TUSD - Consumo Intermediário | C20: kWh | D20: 200 | E20: =(ROUND(D20*K20,2)+ROUND(G20,2)+ROUND(J20,2))/ROUND(D20,4) -> 1.34285 | F20: =ROUND(D20*E20,2) -> 268.57 | G20: =((D20*K20)/(1-$N$19-$N$20))*($N$19+$N$20) -> 10.699462 | H20: =ROUND((D20*K20)/(1-$N$19-$N$20)/(1-$I$19),8) -> 268.5608 | I20: =I19 -> 0.17 | J20: =H20*$I$19 -> 45.655336 | K20: =IF(AND($B$15<$F$2,$E$15<$F$2),C8,IF($B$15<$F$2,I8,F8)) -> 1.06103 | L20: COFINS | M20: =M19 -> 14256.086 | N20: 0.0395 | O20: =ROUND(M20*N20,2) -> 563.12
B21: TUSD - Consumo Fora Ponta | C21: kWh | D21: 200 | E21: =(ROUND(D21*K21,2)+ROUND(G21,2)+ROUND(J21,2))/ROUND(D21,4) -> 0.91795 | F21: =ROUND(D21*E21,2) -> 183.59 | G21: =((D21*K21)/(1-$N$19-$N$20))*($N$19+$N$20) -> 7.3143529 | H21: =ROUND((D21*K21)/(1-$N$19-$N$20)/(1-$I$19),8) -> 183.5932 | I21: =I19 -> 0.17 | J21: =H21*$I$19 -> 31.210843 | K21: =IF(AND($B$15<$F$2,$E$15<$F$2),C7,IF($B$15<$F$2,I7,F7)) -> 0.72534
B22: TE - Consumo Ponta | C22: kWh | D22: =D19 -> 200 | E22: =(ROUND(D22*K22,2)+ROUND(G22,2)+ROUND(J22,2))/ROUND(D22,4) -> 0.40585 | F22: =ROUND(D22*E22,2) -> 81.17 | G22: =((D22*K22)/(1-$N$19-$N$20))*($N$19+$N$20) -> 3.2337479 | H22: =(D22*K22)/(1-$N$19-$N$20)/(1-$I$19) -> 81.168371 | J22: =H22*$I$19 -> 13.798623 | K22: =IF(AND($B$15<$F$2,$E$15<$F$2),D6,IF($B$15<$F$2,J6,G6)) -> 0.32068
B23: TE - Consumo Intermediário | C23: kWh | D23: =D20 -> 200 | E23: =(ROUND(D23*K23,2)+ROUND(G23,2)+ROUND(J23,2))/ROUND(D23,4) -> 0.6132 | F23: =ROUND(D23*E23,2) -> 122.64 | G23: =((D23*K23)/(1-$N$19-$N$20))*($N$19+$N$20) -> 4.8855126 | H23: =(D23*K23)/(1-$N$19-$N$20)/(1-$I$19) -> 122.62833 | J23: =H23*$I$19 -> 20.846816 | K23: =IF(AND($B$15<$F$2,$E$15<$F$2),D8,IF($B$15<$F$2,J8,G8)) -> 0.48448
B24: TE - Consumo Fora Ponta | C24: kWh | D24: =D21 -> 200 | E24: =(ROUND(D24*K24,2)+ROUND(G24,2)+ROUND(J24,2))/ROUND(D24,4) -> 0.387 | F24: =ROUND(D24*E24,2) -> 77.4 | G24: =((D24*K24)/(1-$N$19-$N$20))*($N$19+$N$20) -> 3.0835966 | H24: =(D24*K24)/(1-$N$19-$N$20)/(1-$I$19) -> 77.399514 | J24: =H24*$I$19 -> 13.157917 | K24: =IF(AND($B$15<$F$2,$E$15<$F$2),D7,IF($B$15<$F$2,J7,G7)) -> 0.30579
B25: Adicional BAM | C25: kWh | D25: =IF($K$13=N4,((D19+D20+D21)*(K15)/(K15+L15)),0)+IF($L$13=N4,((D19+D20+D21)*(L15)/(K15+L15)),0) -> 0 | E25: =(ROUND(D25*K25,2)+ROUND(G25,2)+ROUND(J25,2))/ROUND(D25,4) -> #DIV/0! | F25: =ROUND(D25*E25,2) -> #DIV/0! | G25: =((D25*K25)/(1-$N$19-$N$20))*($N$19+$N$20) -> 0 | H25: =(D25*K25)/(1-$N$19-$N$20)/(1-$I$19) -> 0 | J25: =H25*$I$19 -> 0 | K25: =N4 -> 0.01885
B26: Adicional BVM 1 | C26: kWh | D26: =IF($K$11=M5,(D19*(K13)/(K13+L13)),0)+IF($L$11=M5,(D19*(L13)/(K13+L13)),0) -> 0 | E26: =K26/(1-$N$19-$N$20)/(1-$I$19) -> 0.056482231 | F26: =ROUND(D26*E26,2) -> 0 | G26: =((D26*K26)/(1-$N$19-$N$20))*($N$19+$N$20) -> 0 | H26: =(D26*K26)/(1-$N$19-$N$20)/(1-$I$19) -> 0 | J26: =H26*$I$19 -> 0 | K26: =N5 -> 0.04463
B27: Adicional BVM 2 | C27: kWh | D27: =IF($K$11=M6,(D19*(K13)/(K13+L13)),0)+IF($L$11=M6,(D19*(L13)/(K13+L13)),0) -> 0 | E27: =K27/(1-$N$19-$N$20)/(1-$I$19) -> 0.099688671 | F27: =ROUND(D27*E27,2) -> 0 | G27: =((D27*K27)/(1-$N$19-$N$20))*($N$19+$N$20) -> 0 | H27: =(D27*K27)/(1-$N$19-$N$20)/(1-$I$19) -> 0 | J27: =H27*$I$19 -> 0 | K27: =N6 -> 0.07877
B28: Adicional Escassez | C28: kWh | D28: =IF($K$11=M7,(D19*(K13)/(K13+L13)),0)+IF($L$11=M7,(D19*(L13)/(K13+L13)),0) -> 0 | E28: =K28/(1-$N$19-$N$20)/(1-$I$19) -> 0.17971044 | F28: =ROUND(D28*E28,2) -> 0 | G28: =((D28*K28)/(1-$N$19-$N$20))*($N$19+$N$20) -> 0 | H28: =(D28*K28)/(1-$N$19-$N$20)/(1-$I$19) -> 0 | J28: =H28*$I$19 -> 0 | K28: =N7 -> 0.142
B29: Juros
B30: Multas
B31: CIP
B35: TOTAL | F35: =SUM(F19:F34) -> #DIV/0! | G35: =SUM(G19:G34) -> 33.942353 | H35: =SUM(H19:H34) -> 851.96669 | J35: =SUM(J19:J34) -> 144.83434
B37: Informativo Escassez | C37: =D19+D20+D21 -> 600 | D37: =IF(AND($B$15<$F$2,$E$15<$F$2),C9,IF($B$15<$F$2,I9,F9)) -> 0.00018774721 | E37: =IF(AND($B$15<$F$2,$E$15<$F$2),D9,IF($B$15<$F$2,J9,G9)) -> -0.0044031307 | F37: =C37*(D37+E37) -> -2.5292301
B42: Fatura B3 - AES TB
D43: Qtde | E43: TUSD | F43: TE | G43: TUSD + TE | H43: R$ | J43: Documento simulado:
B44: Fornecimento de Energia Elétrica | H44: =SUM(H46:H56)+SUM(H62:H64) -> 17176.007
R45: TUSD Fio B | S45: Receita Fio B
B46: Consumo Ponta | D46: 16 | E46: =IF(AND($B$15<$F$2,$E$15<$F$2),C6,IF($B$15<$F$2,I6,F6)) -> 0.46863 | F46: =IF(AND($B$15<$F$2,$E$15<$F$2),D6,IF($B$15<$F$2,J6,G6)) -> 0.32068 | G46: 1.325 | H46: =ROUND((D46*E46),2)+ROUND((D46*F46),2) -> 12.63 | R46: =IF(AND($B$15<$F$2,$E$15<$F$2),R6,IF($B$15<$F$2,X6,U6)) -> 0.20383072 | S46: =D46*R46 -> 3.2612916
B47: Consumo Fora Ponta | D47: 13580 | E47: =IF(AND($B$15<$F$2,$E$15<$F$2),C7,IF($B$15<$F$2,I7,F7)) -> 0.72534 | F47: =IF(AND($B$15<$F$2,$E$15<$F$2),D7,IF($B$15<$F$2,J7,G7)) -> 0.30579 | G47: 0.5328 | H47: =ROUND((D47*E47),2)+ROUND((D47*F47),2) -> 14002.75 | R47: =IF(AND($B$15<$F$2,$E$15<$F$2),R7,IF($B$15<$F$2,X7,U7)) -> 0.69302445 | S47: =D47*R47 -> 9411.2721
B48: Consumo Intemediário | D48: 15 | E48: =IF(AND($B$15<$F$2,$E$15<$F$2),C8,IF($B$15<$F$2,I8,F8)) -> 1.06103 | F48: =IF(AND($B$15<$F$2,$E$15<$F$2),D8,IF($B$15<$F$2,J8,G8)) -> 0.48448 | G48: 0.84406 | H48: =ROUND((D48*E48),2)+ROUND((D48*F48),2) -> 23.19 | R48: =IF(AND($B$15<$F$2,$E$15<$F$2),R8,IF($B$15<$F$2,X8,U8)) -> 0.20383072 | S48: =D48*R48 -> 3.0574608
B49: Desc Consumo Ponta | H49: =IF(AND($B$15<$F$2,$E$15<$F$2),-H46*$G$16,-IF($B$15<$F$2,((((E6)*$G$16*$C$15)+((H6)*$H$16*$D$15))/($C$15+$D$15))*D46,H46*$H$16)) -> -0.3789 | I49: =H49/H46 -> -0.03 | S49: =SUM(S46:S48) -> 9417.5908
B50: Desc Consumo FPonta | H50: =IF(AND($B$15<$F$2,$E$15<$F$2),-H47*$G$16,-IF($B$15<$F$2,((((E7)*$G$16*$C$15)+((H7)*$H$16*$D$15))/($C$15+$D$15))*D47,H47*$H$16)) -> -420.0825 | I50: =H50/H47 -> -0.03
B51: Desc Consumo Intermed | H51: =IF(AND($B$15<$F$2,$E$15<$F$2),-H48*$G$16,-IF($B$15<$F$2,((((E8)*$G$16*$C$15)+((H8)*$H$16*$D$15))/($C$15+$D$15))*D48,H48*$H$16)) -> -0.6957 | I51: =H51/H48 -> -0.03
B53: Adicional BAM | D53: =IF($K$13=M4,((D46+D47+D48)*(K15)/(K15+L15)),0)+IF($L$13=M4,((D46+D47+D48)*(L15)/(K15+L15)),0) -> 0 | F53: =N4 -> 0.01885 | H53: =ROUND(D53*(E53+F53),2) -> 0
B54: Adicional BVM 1 | D54: =IF($K$13=M5,((D46+D47+D48)*(K15)/(K15+L15)),0)+IF($L$13=M5,((D46+D47+D48)*(L15)/(K15+L15)),0) -> 0 | F54: =N5 -> 0.04463 | H54: =ROUND(D54*(E54+F54),2) -> 0
B55: Adicional BVM 2 | D55: =IF($K$13=M6,((D46+D47+D48)*(K15)/(K15+L15)),0)+IF($L$13=M6,((D46+D47+D48)*(L15)/(K15+L15)),0) -> 0 | F55: =N6 -> 0.07877 | H55: =ROUND(D55*(E55+F55),2) -> 0
B56: Adicional Escassez Hídrica | D56: =IF($K$13=M7,((D46+D47+D48)*(K15)/(K15+L15)),0)+IF($L$13=M7,((D46+D47+D48)*(L15)/(K15+L15)),0) -> 0 | F56: =N7 -> 0.142 | H56: =ROUND(D56*(E56+F56),2) -> 0
D61: Base de Cálculo
B62: PIS | D62: =(SUM(H46:H59)/(1-E62-E63)) -> 14256.086 | E62: 0.008 | H62: =D62*E62 -> 114.04868
B63: COFINS | D63: =D62 -> 14256.086 | E63: 0.0368 | H63: =D63*E63 -> 524.62395
B64: ICMS | D64: =D62/(1-E64) -> 17176.007 | E64: 0.17 | H64: =D64*E64 -> 2919.9211
B66: Informativo Escassez Hídrica | D66: =SUM(D46:D48) -> 13611 | E66: =IF(AND($B$15<$F$2,$E$15<$F$2),C9,IF($B$15<$F$2,I9,F9)) -> 0.00018774721 | F66: =IF(AND($B$15<$F$2,$E$15<$F$2),D9,IF($B$15<$F$2,J9,G9)) -> -0.0044031307 | H66: =D66*(E66+F66) -> -57.375585
B68: Participação
C69: R$
B70: Energia | C70: =(SUM(H46:H59)*IF($B$15<$F$2,D108,D80)) -> -227.28371
B71: Distribuição | C71: =(SUM(H46:H59)*IF($B$15<$F$2,F108,F80)) -> -7087.8712
B72: Transmissão | C72: =(SUM(H46:H59)*IF($B$15<$F$2,E108,E80)) -> 10168.399
B73: Encargos Setoriais | C73: =(SUM(H46:H59)*IF($B$15<$F$2,G108,G80)) -> 10768.915
B74: Impostos / Tributos | C74: =H62+H63+H64 -> 3558.5938
B75: Total | C75: =SUM(C70:C74) -> 17180.753
B77: ='B3 Branca OK'!B81 -> 2024 | D77: Energia | E77: Transmissão | F77: Distribuição | G77: Setoriais
B78: Grupo B | D78: % | E78: % | F78: % | G78: %
B80: B1 - Residencial | D80: ='B3 Branca OK'!D84 -> 0.45246417 | E80: ='B3 Branca OK'!E84 -> 0.073959411 | F80: ='B3 Branca OK'!F84 -> 0.27500913 | G80: ='B3 Branca OK'!G84 -> 0.19856729
B81: B1 - Residencial Baixa Renda | D81: ='B3 Branca OK'!D85 -> 0.53149576 | E81: ='B3 Branca OK'!E85 -> 0.086877849 | F81: ='B3 Branca OK'!F85 -> 0.32304478 | G81: ='B3 Branca OK'!G85 -> 0.058581612
B82: B2 - Rural | D82: ='B3 Branca OK'!D86 -> 0.45246417 | E82: ='B3 Branca OK'!E86 -> 0.073959411 | F82: ='B3 Branca OK'!F86 -> 0.27500913 | G82: ='B3 Branca OK'!G86 -> 0.19856729
B83: B2 - Cooperativa Eletrificação Rural | D83: ='B3 Branca OK'!D87 -> 0.45246417 | E83: ='B3 Branca OK'!E87 -> 0.073959411 | F83: ='B3 Branca OK'!F87 -> 0.27500913 | G83: ='B3 Branca OK'!G87 -> 0.19856729
B84: B2 - Serviço de Irrigação | D84: ='B3 Branca OK'!D88 -> 0.45246417 | E84: ='B3 Branca OK'!E88 -> 0.073959411 | F84: ='B3 Branca OK'!F88 -> 0.27500913 | G84: ='B3 Branca OK'!G88 -> 0.19856729
B85: B3 - Demais Classes | D85: ='B3 Branca OK'!D89 -> 0.45246417 | E85: ='B3 Branca OK'!E89 -> 0.073959411 | F85: ='B3 Branca OK'!F89 -> 0.27500913 | G85: ='B3 Branca OK'!G89 -> 0.19856729
B86: B4 - Iluminação Pública | D86: ='B3 Branca OK'!D90 -> 0.45246417 | E86: ='B3 Branca OK'!E90 -> 0.073959411 | F86: ='B3 Branca OK'!F90 -> 0.27500913 | G86: ='B3 Branca OK'!G90 -> 0.19856729
B87: B4a - Rede de Distribuição | D87: ='B3 Branca OK'!D91 -> 0.45246417 | E87: ='B3 Branca OK'!E91 -> 0.073959411 | F87: ='B3 Branca OK'!F91 -> 0.27500913 | G87: ='B3 Branca OK'!G91 -> 0.19856729
B88: B4b - Bulbo de Lâmpada | D88: ='B3 Branca OK'!D92 -> 0.45246417 | E88: ='B3 Branca OK'!E92 -> 0.073959411 | F88: ='B3 Branca OK'!F92 -> 0.27500913 | G88: ='B3 Branca OK'!G92 -> 0.19856729
B91: ='B3 Branca OK'!B95 -> 2023 | D91: Energia | E91: Transmissão | F91: Distribuição | G91: Setoriais
B92: Grupo B | D92: % | E92: % | F92: % | G92: %
B94: B1 - Residencial | D94: ='B3 Branca OK'!D98 -> 0.43939696 | E94: ='B3 Branca OK'!E98 -> 0.092697586 | F94: ='B3 Branca OK'!F98 -> 0.25285208 | G94: ='B3 Branca OK'!G98 -> 0.21506308
B95: B1 - Residencial Baixa Renda | D95: ='B3 Branca OK'!D99 -> 0.5269162 | E95: ='B3 Branca OK'!E99 -> 0.11116112 | F95: ='B3 Branca OK'!F99 -> 0.30321524 | G95: ='B3 Branca OK'!G99 -> 0.058707433
B96: B2 - Rural | D96: ='B3 Branca OK'!D100 -> 0.439393 | E96: ='B3 Branca OK'!E100 -> 0.092696751 | F96: ='B3 Branca OK'!F100 -> 0.2528498 | G96: ='B3 Branca OK'!G100 -> 0.21506045
B97: B2 - Cooperativa Eletrificação Rural | D97: ='B3 Branca OK'!D101 -> 0.439393 | E97: ='B3 Branca OK'!E101 -> 0.092696751 | F97: ='B3 Branca OK'!F101 -> 0.2528498 | G97: ='B3 Branca OK'!G101 -> 0.21506045
B98: B2 - Serviço de Irrigação | D98: ='B3 Branca OK'!D102 -> 0.439393 | E98: ='B3 Branca OK'!E102 -> 0.092696751 | F98: ='B3 Branca OK'!F102 -> 0.2528498 | G98: ='B3 Branca OK'!G102 -> 0.21506045
B99: B3 - Demais Classes | D99: ='B3 Branca OK'!D103 -> 0.439393 | E99: ='B3 Branca OK'!E103 -> 0.092696751 | F99: ='B3 Branca OK'!F103 -> 0.2528498 | G99: ='B3 Branca OK'!G103 -> 0.21506045
B100: B4 - Iluminação Pública | D100: ='B3 Branca OK'!D104 -> 0 | E100: ='B3 Branca OK'!E104 -> 0 | F100: ='B3 Branca OK'!F104 -> 0 | G100: ='B3 Branca OK'!G104 -> 0
B101: B4a - Rede de Distribuição | D101: ='B3 Branca OK'!D105 -> 0.43938946 | E101: ='B3 Branca OK'!E105 -> 0.092697337 | F101: ='B3 Branca OK'!F105 -> 0.2528514 | G101: ='B3 Branca OK'!G105 -> 0.21506181
B102: B4b - Bulbo de Lâmpada | D102: ='B3 Branca OK'!D106 -> 0.43938946 | E102: ='B3 Branca OK'!E106 -> 0.092697337 | F102: ='B3 Branca OK'!F106 -> 0.2528514 | G102: ='B3 Branca OK'!G106 -> 0.21506181
B104: proporcional
D105: Energia | E105: Transmissão | F105: Distribuição | G105: Setoriais
B106: Grupo B | D106: % | E106: % | F106: % | G106: %
B108: B1 - Residencial | D108: =((D94*$C$15)+(D80*$D$15))/($C$15+$D$15) -> -0.016690667 | E108: =((E94*$C$15)+(E80*$D$15))/($C$15+$D$15) -> 0.74672032 | F108: =((F94*$C$15)+(F80*$D$15))/($C$15+$D$15) -> -0.52050057 | G108: =((G94*$C$15)+(G80*$D$15))/($C$15+$D$15) -> 0.79081946
B109: B1 - Residencial Baixa Renda | D109: =((D95*$C$15)+(D81*$D$15))/($C$15+$D$15) -> 0.36707483 | E109: =((E95*$C$15)+(E81*$D$15))/($C$15+$D$15) -> 0.95872573 | F109: =((F95*$C$15)+(F81*$D$15))/($C$15+$D$15) -> -0.38889957 | G109: =((G95*$C$15)+(G81*$D$15))/($C$15+$D$15) -> 0.063099015
B110: B2 - Rural | D110: =((D96*$C$15)+(D82*$D$15))/($C$15+$D$15) -> -0.016832784 | E110: =((E96*$C$15)+(E82*$D$15))/($C$15+$D$15) -> 0.74669034 | F110: =((F96*$C$15)+(F82*$D$15))/($C$15+$D$15) -> -0.52058235 | G110: =((G96*$C$15)+(G82*$D$15))/($C$15+$D$15) -> 0.79072479
B111: B2 - Cooperativa Eletrificação Rural | D111: =((D97*$C$15)+(D83*$D$15))/($C$15+$D$15) -> -0.016832784 | E111: =((E97*$C$15)+(E83*$D$15))/($C$15+$D$15) -> 0.74669034 | F111: =((F97*$C$15)+(F83*$D$15))/($C$15+$D$15) -> -0.52058235 | G111: =((G97*$C$15)+(G83*$D$15))/($C$15+$D$15) -> 0.79072479
B112: B2 - Serviço de Irrigação | D112: =((D98*$C$15)+(D84*$D$15))/($C$15+$D$15) -> -0.016832784 | E112: =((E98*$C$15)+(E84*$D$15))/($C$15+$D$15) -> 0.74669034 | F112: =((F98*$C$15)+(F84*$D$15))/($C$15+$D$15) -> -0.52058235 | G112: =((G98*$C$15)+(G84*$D$15))/($C$15+$D$15) -> 0.79072479
B113: B3 - Demais Classes | D113: =((D99*$C$15)+(D85*$D$15))/($C$15+$D$15) -> -0.016832784 | E113: =((E99*$C$15)+(E85*$D$15))/($C$15+$D$15) -> 0.74669034 | F113: =((F99*$C$15)+(F85*$D$15))/($C$15+$D$15) -> -0.52058235 | G113: =((G99*$C$15)+(G85*$D$15))/($C$15+$D$15) -> 0.79072479
B114: B4 - Iluminação Pública | D114: =((D100*$C$15)+(D86*$D$15))/($C$15+$D$15) -> -15.792459 | E114: =((E100*$C$15)+(E86*$D$15))/($C$15+$D$15) -> -2.581422 | F114: =((F100*$C$15)+(F86*$D$15))/($C$15+$D$15) -> -9.5987059 | G114: =((G100*$C$15)+(G86*$D$15))/($C$15+$D$15) -> -6.930639
B115: B4a - Rede de Distribuição | D115: =((D101*$C$15)+(D87*$D$15))/($C$15+$D$15) -> -0.016960067 | E115: =((E101*$C$15)+(E87*$D$15))/($C$15+$D$15) -> 0.74671139 | F115: =((F101*$C$15)+(F87*$D$15))/($C$15+$D$15) -> -0.52052494 | G115: =((G101*$C$15)+(G87*$D$15))/($C$15+$D$15) -> 0.79077362
B116: B4b - Bulbo de Lâmpada | D116: =((D102*$C$15)+(D88*$D$15))/($C$15+$D$15) -> -0.016960067 | E116: =((E102*$C$15)+(E88*$D$15))/($C$15+$D$15) -> 0.74671139 | F116: =((F102*$C$15)+(F88*$D$15))/($C$15+$D$15) -> -0.52052494 | G116: =((G102*$C$15)+(G88*$D$15))/($C$15+$D$15) -> 0.79077362
