Workbook
Name _Ref352134769: 'TABELA DE TARIFAS NOVAS'!$A$93

Sheet FIO B
B2: TUSD FIO B
B4: SUBGRUPO | C4: MODALIDADE | D4: CLASSE | E4: SUBCLASSE | F4: POSTO | G4: TARIFAS DE APLICAÇÃO
G5: TUSD FIO B (RTP 2025) | J5: TUSD FIO B (RTA 2026)
G6: R$/kW | H6: R$/MWh | J6: R$/kW | K6: R$/MWh
B7: B1 | C7: BRANCA | D7: RESIDENCIAL | E7: RESIDENCIAL | F7: P | G7: 0 | H7: 591.10909 | J7: 0 | K7: 606.53962
B8: B1 | C8: BRANCA | D8: RESIDENCIAL | E8: RESIDENCIAL | F8: INT | G8: 0 | H8: 354.6655 | J8: 0 | K8: 363.92381
B9: B1 | C9: BRANCA | D9: RESIDENCIAL | E9: RESIDENCIAL | F9: FP | G9: 0 | H9: 118.2218 | J9: 0 | K9: 121.3079
B10: B1 | C10: PRÉ-PAGAMENTO | D10: RESIDENCIAL | E10: RESIDENCIAL | F10: NA | G10: 0 | H10: 203.83072 | J10: 0 | K10: 209.15159
B11: B1 | C11: CONVENCIONAL | D11: RESIDENCIAL | E11: RESIDENCIAL | F11: NA | G11: 0 | H11: 203.83072 | J11: 0 | K11: 209.15159
B12: B1 | C12: PRÉ-PAGAMENTO | D12: RESIDENCIAL | E12: BAIXA RENDA | F12: NA | G12: 0 | H12: 203.83072 | J12: 0 | K12: 209.15159
B13: B1 | C13: CONVENCIONAL | D13: RESIDENCIAL | E13: BAIXA RENDA | F13: NA | G13: 0 | H13: 203.83072 | J13: 0 | K13: 209.15159
B14: B1 | C14: PRÉ-PAGAMENTO | D14: RESIDENCIAL | E14: RESIDENCIAL DESCONTO SOCIAL | F14: NA | G14: 0 | H14: 203.83072 | J14: 0 | K14: 209.15159
B15: B1 | C15: CONVENCIONAL | D15: RESIDENCIAL | E15: RESIDENCIAL DESCONTO SOCIAL | F15: NA | G15: 0 | H15: 203.83072 | J15: 0 | K15: 209.15159
B16: B2 | C16: BRANCA | D16: RURAL | E16: NÃO SE APLICA | F16: P | G16: 0 | H16: 693.02445 | J16: 0 | K16: 711.11541
B17: B2 | C17: BRANCA | D17: RURAL | E17: NÃO SE APLICA | F17: INT | G17: 0 | H17: 415.81471 | J17: 0 | K17: 426.66929
B18: B2 | C18: BRANCA | D18: RURAL | E18: NÃO SE APLICA | F18: FP | G18: 0 | H18: 138.60487 | J18: 0 | K18: 142.22306
... B39: B | C39: GERAÇÃO | D39: TIPO 02 | E39: NA | F39: NA | G39: 0 | H39: 11.690957 | J39: 0 | K39: 11.996142

Sheet TABELA DE TARIFAS ANTIGAS
A1: TABELA 1 – TARIFAS DE APLICAÇÃO E BASE ECONÔMICA PARA O GRUPO A.
A2: SUBGRUPO | B2: MODALIDADE | C2: UC | D2: POSTO | E2: TARIFAS DE APLICAÇÃO | J2: BASE ECONÔMICA | N2: Reajuste | O2: Dia | P2: Mês | Q2: Ano
E3: TUSD | G3: TE | J3: TUSD | L3: TE | N3: De | O3: 07 | P3: 08 | Q3: 2025
E4: R$/kW | F4: R$/MWh | G4: BVD – R$/MWh | H4: BAM – R$/MWh | I4: BVM – R$/MWh | J4: R$/kW | K4: R$/MWh | L4: R$/MWh | N4: Até | O4: 06 | P4: 08 | Q4: 2026
B5: AZUL | C5: NA | D5: P
A6: A1 (230 kV ou mais) | D6: FP
B7: AZUL APE | C7: NA | D7: P
D8: FP
A9: A2 (88 a 138kV) | B9: AZUL | C9: NA | D9: P
D10: FP
B11: AZUL APE | C11: NA | D11: P
D12: FP
B13: DISTRIBUIÇÃO | C13: ELFSM | D13: P
D14: FP
D15: NA
B16: GERAÇÃO | C16: UTE LASA | D16: NA
C17: UTE ALCON | D17: NA
C18: UTE SOL | D18: NA
C19: UHE MASCARENHAS - ENERGEST | D19: NA
C20: UHE SUICA | D20: NA
C21: PCH SAO JOAQUIM | D21: NA
C22: PCH SAO SIMAO | D22: NA
C23: PCH FRANCISCO GROSS | D23: NA
C24: PCH SAO PEDRO | D24: NA
C25: UTE LINHARES | D25: NA
C26: UTE ARCEL | D26: NA
C27: NOVO GERADOR | D27: NA
A28: A3 (69kV) | B28: AZUL | C28: NA | D28: P
D29: FP
B30: AZUL APE | C30: NA | D30: P
D31: FP
B32: DISTRIBUIÇÃO | D32: P
D33: FP
D34: NA
B35: GERAÇÃO | C35: NA | D35: NA
A36: A3a (30 a 44kV) | B36: AZUL | C36: NA | D36: P
D37: FP
B38: AZUL APE | C38: NA | D38: P
D39: FP
B40: VERDE | C40: NA | D40: NA
D41: P
D42: FP
B43: VERDE APE | C43: NA | D43: NA
D44: P
D45: FP
B46: CONVENCIONAL | C46: NA | D46: NA
B47: GERAÇÃO | C47: NA | D47: NA
A48: A4 (2,3 a 25kV) | B48: AZUL | C48: NA | D48: P
D49: FP
B50: AZUL APE | C50: NA | D50: P
D51: FP
B52: VERDE | C52: NA | D52: NA
D53: P
D54: FP
B55: VERDE APE | C55: NA | D55: NA
D56: P
D57: FP
B58: CONVENCIONAL | C58: NA | D58: NA
B59: DISTRIBUIÇÃO | C59: COELBA | D59: P
D60: FP
D61: NA
B62: GERAÇÃO | C62: NA | D62: NA
A64: TABELA 2 – TARIFAS DE APLICAÇÃO E BASE ECONÔMICA PARA O GRUPO B.
A65: SUBGRUPO | B65: MODALIDADE | C65: CLASSE | D65: SUBCLASSE | E65: POSTO | F65: TARIFAS DE APLICAÇÃO | K65: TARIFAS BASE ECONÔMICA
F66: TUSD | H66: TE | K66: TUSD | M66: TE
F67: R$/kW | G67: R$/MWh | H67: BVD – R$/MWh | I67: BAM – R$/MWh | J67: BVM – R$/MWh | K67: R$/kW | L67: R$/MWh | M67: R$/MWh
A68: B1 | B68: BRANCA | C68: RESIDENCIAL | D68: RESIDENCIAL | E68: P | F68: 0 | G68: 937.61 | H68: 484.48 | K68: 0 | L68: 918.51 | M68: 492.47
E69: INT | F69: 0 | G69: 651.29 | H69: 305.79 | K69: 0 | L69: 634.94 | M69: 316.46
E70: FP | F70: 0 | G70: 364.96 | H70: 305.79 | K70: 0 | L70: 351.38 | M70: 316.46
B71: CONVENCIONAL | C71: RESIDENCIAL | D71: RESIDENCIAL | E71: NA | F71: 0 | G71: 468.63 | H71: 320.68 | K71: 0 | L71: 454.05 | M71: 331.12
D72: BAIXA RENDA(1) | E72: NA | F72: 0 | G72: 325.43 | H72: 282.45 | K72: 0
D73: DESCONTO SOCIAL | E73: NA | G73: 340.19 | H73: 296.66
A74: B2 | B74: BRANCA | C74: RURAL | D74: NA | E74: P | F74: 0 | G74: 1061.03 | H74: 484.48 | K74: 0 | L74: 1040.73 | M74: 492.47
E75: INT | F75: 0 | G75: 725.34 | H75: 305.79 | K75: 0 | L75: 708.28 | M75: 316.46
E76: FP | F76: 0 | G76: 389.65 | H76: 305.79 | K76: 0 | L76: 375.82 | M76: 316.46
B77: CONVENCIONAL | C77: RURAL | D77: NA | E77: NA | F77: 0 | G77: 468.63 | H77: 320.68 | K77: 0 | L77: 454.05 | M77: 331.12
B78: BRANCA | C78: RURAL | D78: COOPERATIVA DE ELETRIFICAÇÃO RURAL | E78: P | F78: 0 | G78: 1061.03 | H78: 484.48 | K78: 0 | L78: 1040.73 | M78: 492.47
E79: INT | F79: 0 | G79: 725.34 | H79: 305.79 | K79: 0 | L79: 708.28 | M79: 316.46
E80: FP | F80: 0 | G80: 389.65 | H80: 305.79 | K80: 0 | L80: 375.82 | M80: 316.46
B81: CONVENCIONAL | C81: RURAL | D81: COOPERATIVA DE ELETRIFICAÇÃO RURAL | E81: NA | F81: 0 | G81: 468.63 | H81: 320.68 | K81: 0 | L81: 454.05 | M81: 331.12
B82: BRANCA | C82: RURAL | D82: SERVIÇO PÚBLICO DE IRRIGAÇÃO RURAL | E82: P | F82: 0 | G82: 1061.03 | H82: 484.48 | K82: 0 | L82: 1040.73 | M82: 492.47
E83: INT | F83: 0 | G83: 725.34 | H83: 305.79 | K83: 0 | L83: 708.28 | M83: 316.46
E84: FP | F84: 0 | G84: 389.65 | H84: 305.79 | K84: 0 | L84: 375.82 | M84: 316.46
B85: CONVENCIONAL | C85: RURAL | D85: SERVIÇO PÚBLICO DE IRRIGAÇÃO RURAL | E85: NA | F85: 0 | G85: 468.63 | H85: 320.68 | K85: 0 | L85: 454.05 | M85: 331.12
A86: B3 | B86: BRANCA | C86: NA | D86: NA | E86: P | F86: 0 | G86: 1061.03 | H86: 484.48 | K86: 0 | L86: 1040.73 | M86: 492.47
E87: INT | F87: 0 | G87: 725.34 | H87: 305.79 | K87: 0 | L87: 708.28 | M87: 316.46
E88: FP | F88: 0 | G88: 389.65 | H88: 305.79 | K88: 0 | L88: 375.82 | M88: 316.46
B89: CONVENCIONAL | C89: NA | D89: NA | E89: NA | F89: 0 | G89: 468.63 | H89: 320.68 | K89: 0 | L89: 454.05 | M89: 331.12
A90: B4 | B90: CONVENCIONAL | C90: ILUMINAÇÃO PÚBLICA | D90: B4a – REDE DE DISTRIBUIÇÃO | E90: NA | F90: 0 | G90: 257.75 | H90: 176.38 | K90: 0 | L90: 249.73 | M90: 182.12
D91: B4b – BULBO DE LÂMPADA | E91: NA | F91: 0 | G91: 281.18 | H91: 192.41 | K91: 0 | L91: 272.43 | M91: 198.67

Sheet TABELA DE TARIFAS NOVAS
A1: TABELA 1 – TARIFAS DE APLICAÇÃO E BASE ECONÔMICA PARA O GRUPO A.
A2: SUBGRUPO | B2: MODALIDADE | C2: UC | D2: POSTO | E2: TARIFAS DE APLICAÇÃO | J2: BASE ECONÔMICA | N2: Reajuste | O2: Dia | P2: Mês | Q2: Ano
E3: TUSD | G3: TE | J3: TUSD | L3: TE | N3: De | O3: 07 | P3: 08 | Q3: 2026
E4: R$/kW | F4: R$/MWh | G4: BVD – R$/MWh | H4: BAM – R$/MWh | I4: BVM – R$/MWh | J4: R$/kW | K4: R$/MWh | L4: R$/MWh | N4: Até | O4: 31 | P4: 12 | Q4: 9999
B5: AZUL | C5: NA | D5: P
A6: A1 (230 kV ou mais) | D6: FP
B7: AZUL APE | C7: NA | D7: P
D8: FP
A9: A2 (88 a 138kV) | B9: AZUL | C9: NA | D9: P
D10: FP
B11: AZUL APE | C11: NA | D11: P
D12: FP
B13: DISTRIBUIÇÃO | C13: ELFSM | D13: P
D14: FP
D15: NA
B16: GERAÇÃO | C16: UTE LASA | D16: NA
C17: UTE ALCON | D17: NA
C18: UTE SOL | D18: NA
C19: UHE MASCARENHAS - ENERGEST | D19: NA
C20: UHE SUICA | D20: NA
C21: PCH SAO JOAQUIM | D21: NA
C22: PCH SAO SIMAO | D22: NA
C23: PCH FRANCISCO GROSS | D23: NA
C24: PCH SAO PEDRO | D24: NA
C25: UTE LINHARES | D25: NA
C26: UTE POVOACAO 1 | D26: NA
C27: UTE ARCEL | D27: NA
C28: UTE BIANCOGRES | D28: NA
C29: NOVO GERADOR | D29: NA
A30: A3 (69kV) | B30: AZUL | C30: NA | D30: P
D31: FP
B32: AZUL APE | C32: NA | D32: P
D33: FP
B34: DISTRIBUIÇÃO | D34: P
D35: FP
D36: NA
B37: GERAÇÃO | C37: NA | D37: NA
A38: A3a (30 a 44kV) | B38: AZUL | C38: NA | D38: P
D39: FP
B40: AZUL APE | C40: NA | D40: P
D41: FP
B42: VERDE | C42: NA | D42: NA
D43: P
D44: FP
B45: VERDE APE | C45: NA | D45: NA
D46: P
D47: FP
B48: CONVENCIONAL | C48: NA | D48: NA
B49: GERAÇÃO | C49: NA | D49: NA
A50: A4 (2,3 a 25kV) | B50: AZUL | C50: NA | D50: P
D51: FP
B52: AZUL APE | C52: NA | D52: P
D53: FP
B54: VERDE | C54: NA | D54: NA
D55: P
D56: FP
B57: VERDE APE | C57: NA | D57: NA
D58: P
D59: FP
B60: CONVENCIONAL | C60: NA | D60: NA
B61: DISTRIBUIÇÃO | C61: COELBA | D61: P
D62: FP
D63: NA
B64: GERAÇÃO | C64: NA | D64: NA
A66: TABELA 2 – TARIFAS DE APLICAÇÃO E BASE ECONÔMICA PARA O GRUPO B.
A67: SUBGRUPO | B67: MODALIDADE | C67: CLASSE | D67: SUBCLASSE | E67: POSTO | F67: TARIFAS DE APLICAÇÃO | K67: TARIFAS BASE ECONÔMICA
F68: TUSD | H68: TE | K68: TUSD | M68: TE
F69: R$/kW | G69: R$/MWh | H69: BVD – R$/MWh | I69: BAM – R$/MWh | J69: BVM – R$/MWh | K69: R$/kW | L69: R$/MWh | M69: R$/MWh
A70: B1 | B70: BRANCA | C70: RESIDENCIAL | D70: RESIDENCIAL | E70: P | F70: 0 | G70: 999.02 | H70: 516.91 | K70: 0 | L70: 956.95 | M70: 478.38
E71: INT | F71: 0 | G71: 698.21 | H71: 321.07 | K71: 0 | L71: 662.46 | M71: 299.92
E72: FP | F72: 0 | G72: 397.41 | H72: 321.07 | K72: 0 | L72: 367.97 | M72: 299.92
B73: CONVENCIONAL | C73: RESIDENCIAL | D73: RESIDENCIAL | E73: NA | F73: 0 | G73: 506.32 | H73: 337.39 | K73: 0 | L73: 474.59 | M73: 314.79
D74: BAIXA RENDA(1) | E74: NA | F74: 0 | G74: 348.95 | H74: 325.32 | K74: 0 | L74: 334.57 | M74: 303.57
D75: DESCONTO SOCIAL | E75: NA | F75: 0 | G75: 356.42 | H75: 337.59 | L75: 343.39 | M75: 314.79
A76: B2 | B76: BRANCA | C76: RURAL | D76: NA | E76: P | F76: 0 | G76: 1128.67 | H76: 516.91 | K76: 0 | L76: 1083.88 | M76: 478.38
E77: INT | F77: 0 | G77: 776.01 | H77: 321.07 | K77: 0 | L77: 738.62 | M77: 299.92
E78: FP | F78: 0 | G78: 423.34 | H78: 321.07 | K78: 0 | L78: 393.35 | M78: 299.92
B79: CONVENCIONAL | C79: RURAL | D79: NA | E79: NA | F79: 0 | G79: 506.32 | H79: 337.39 | K79: 0 | L79: 474.59 | M79: 314.79
B80: BRANCA | C80: RURAL | D80: COOPERATIVA DE ELETRIFICAÇÃO RURAL | E80: P | F80: 0 | G80: 1128.67 | H80: 516.91 | K80: 0 | L80: 1083.88 | M80: 478.38
E81: INT | F81: 0 | G81: 776.01 | H81: 321.07 | K81: 0 | L81: 738.62 | M81: 299.92
E82: FP | F82: 0 | G82: 423.34 | H82: 321.07 | K82: 0 | L82: 393.35 | M82: 299.92
B83: CONVENCIONAL | C83: RURAL | D83: COOPERATIVA DE ELETRIFICAÇÃO RURAL | E83: NA | F83: 0 | G83: 506.32 | H83: 337.39 | K83: 0 | L83: 474.59 | M83: 314.79
B84: BRANCA | C84: RURAL | D84: SERVIÇO PÚBLICO DE IRRIGAÇÃO RURAL | E84: P | F84: 0 | G84: 1128.67 | H84: 516.91 | K84: 0 | L84: 1083.88 | M84: 478.38
E85: INT | F85: 0 | G85: 776.01 | H85: 321.07 | K85: 0 | L85: 738.62 | M85: 299.92
E86: FP | F86: 0 | G86: 423.34 | H86: 321.07 | K86: 0 | L86: 393.35 | M86: 299.92
B87: CONVENCIONAL | C87: RURAL | D87: SERVIÇO PÚBLICO DE IRRIGAÇÃO RURAL | E87: NA | F87: 0 | G87: 506.32 | H87: 337.39 | K87: 0 | L87: 474.59 | M87: 314.79
A88: B3 | B88: BRANCA | C88: NA | D88: NA | E88: P | F88: 0 | G88: 1128.67 | H88: 516.91 | K88: 0 | L88: 1083.88 | M88: 478.38
E89: INT | F89: 0 | G89: 776.01 | H89: 321.07 | K89: 0 | L89: 738.62 | M89: 299.92
E90: FP | F90: 0 | G90: 423.34 | H90: 321.07 | K90: 0 | L90: 393.35 | M90: 299.92
B91: CONVENCIONAL | C91: NA | D91: NA | E91: NA | F91: 0 | G91: 506.32 | H91: 337.39 | K91: 0 | L91: 474.59 | M91: 314.79
A92: B4 | B92: CONVENCIONAL | C92: ILUMINAÇÃO PÚBLICA | D92: B4a – REDE DE DISTRIBUIÇÃO | E92: NA | F92: 0 | G92: 278.48 | H92: 185.56 | K92: 0 | L92: 261.03 | M92: 173.13
D93: B4b – BULBO DE LÂMPADA | E93: NA | F93: 0 | G93: 303.79 | H93: 202.43 | K93: 0 | L93: 284.76 | M93: 188.87

Sheet Fatura B1 (GD) OK
B2: B1 Res | E2: Vigência das Tarifas: | F2: 46241 | M2: Bandeira | N2: R$/kWh | O2: ANEEL em 29/06 | Q2: TUSD FIO B
M3: VERDE | N3: 0
B4: TARIFA | C4: TARIFA ANTIGA - REH 3508/2025 | F4: TARIFA NOVA - REH xxxx/2026 | I4: Tarifas Proporcionalizadas | M4: BAM | N4: =[1]BANDEIRA!$D$5 -> 0.01885 | Q4: TARIFA | R4: =C4 -> TARIFA ANTIGA - REH 3508/2025 | U4: =F4 -> TARIFA NOVA - REH xxxx/2026 | X4: Tarifas Proporcionalizadas
C5: Tusd | D5: TE | E5: TUSD + TE | F5: Tusd | G5: TE | H5: TUSD + TE | I5: Tusd | J5: TE | K5: TUSD + TE | M5: BVM1 | N5: =[1]BANDEIRA!$D$6 -> 0.04463 | R5: Tusd (R$/kWh) | U5: Tusd (R$/kWh) | X5: Tusd (R$/kWh)
B6: B1 | C6: ='TABELA DE TARIFAS ANTIGAS'!G71/1000 -> 0.46863 | D6: ='TABELA DE TARIFAS ANTIGAS'!H71/1000 -> 0.32068 | E6: =C6+D6 -> 0.78931 | F6: ='TABELA DE TARIFAS NOVAS'!G73/1000 -> 0.50632 | G6: ='TABELA DE TARIFAS NOVAS'!H73/1000 -> 0.33739 | H6: =F6+G6 -> 0.84371 | I6: =((C6*$C$14)+(F6*$D$14))/($D$14+$C$14) -> 0.49100844 | J6: =((D6*$C$14)+(G6*$D$14))/($D$14+$C$14) -> 0.33060156 | K6: =I6+J6 -> 0.82161 | M6: BVM2 | N6: =[1]BANDEIRA!$D$7 -> 0.07877 | Q6: =B6 -> B1 | R6: ='FIO B'!H11/1000 -> 0.20383072 | U6: ='FIO B'!K11/1000 -> 0.20915159 | X6: =((R6*$C$14)+(U6*$D$14))/($D$14+$C$14) -> 0.20698999
B7: CDE Escassez Hídrica | C7: 0.00018774721 | D7: -0.0044031307 | E7: 0.0036054084 | F7: =T11 -> 0.00018418923 | G7: =U11 -> -0.00053182975 | H7: =F7+G7 -> -0.00034764052 | I7: =((C7*$C$14)+(F7*$D$14))/($D$14+$C$14) -> 0.00018563466 | J7: =((D7*$C$14)+(G7*$D$14))/($D$14+$C$14) -> -0.0021045458 | K7: =I7+J7 -> -0.0019189111 | M7: Escassez Hídrica | N7: 0.142
B8: TE SCEE | G8: =G6*15% -> 0.0506085 | J8: =((D8*$C$14)+(G8*$D$14))/($D$14+$C$14) -> 0.030048797 | P8: CUSTO | R8: Part. TUSD (%) | S8: Part. TE (%) | T8: Tusd (R$/kWh) | U8: TE (R$/kWh)
P9: CDE CONTAS
H10: Fatura | L10: Vigência das Tarifas (troca Bandeira): | M10: =EOMONTH(B14,0)+1 -> 46235 | P10: CDE COVID | U10: 0
B11: INSTALAÇÃO | C11: 73278 | H11: =E14 -> 46259 | K11: Altere a bandeira na célula abaixo | P11: CDE ESCASSEZ HÍDRICA | T11: =0.184189231569235/1000 -> 0.00018418923 | U11: =-0.531829748712515/1000 -> -0.00053182975
K12: BAM | L12: BAM
B13: Leitura Anterior | C13: Nº de dias tarifa Anterior | D13: Nº de dias tarifa Nova | E13: Leitura Atual | J13: Leitura Anterior | K13: Nº de dias tarifa Anterior | L13: Nº de dias tarifa Nova | M13: Leitura Atual
B14: 46227 | C14: =IF((F2-B14-1)<0,0,(F2-B14-1)) -> 13 | D14: =E14-F2+1 -> 19 | E14: 46259 | J14: =B14 -> 46227 | K14: =IF((M10-J14-1)<0,0,(M10-J14-1)) -> 7 | L14: =M14-M10+1 -> 25 | M14: =E14 -> 46259
B17: Perc. de Redução da Energia Injetada | E17: TUSD | F17: 1 | G17: TE | H17: 1 | M17: Documento Impressão | O17: 1025311173
B19: Descrição | C19: Unidade | D19: Quantidade | E19: Preço Unit (R$) com tributos | F19: Valor Total (R$) | G19: PIS/COFINS (R$) | H19: Base de Cálculo ICMS (R$) | I19: Alíquota ICMS (%) | J19: ICMS (R$) | K19: Preço Unit (R$) | L19: Tributos | M19: Base de Cálc (R$) | N19: Alíquota (%) | O19: Valor (R$)
R20: TUSD Fio B | S20: Receita Fio B
B21: TUSD - Consumo | C21: kWh | D21: 324 | E21: =(ROUND(D21*K21,2)+ROUND(G21,2)+ROUND(J21,2))/ROUND(D21,4) -> 0.63049383 | F21: =ROUND(D21*E21,2) -> 204.28 | G21: =((D21*K21)/(1-$N$21-$N$23))*($N$21+$N$23) -> 10.461101 | H21: =((D21*K21)/(1-$N$21-$N$23)/(1-$I$21)) -> 204.2745 | I21: 0.17 | J21: =(H21*$I$21) -> 34.726665 | K21: =IF(AND($B$14<$F$2,$E$14<$F$2),C6,IF($B$14<$F$2,I6,F6)) -> 0.49100844 | L21: PIS | M21: =D71 -> 290.21635 | N21: 0.011 | O21: =ROUND(M21*N21,2) -> 3.19 | R21: =IF(AND($B$14<$F$2,$E$14<$F$2),R6,IF($B$14<$F$2,X6,U6)) -> 0.20698999 | S21: =D21*R21 -> 67.064756 | T21: não está considerando energia injetada
B22: TE - Consumo | C22: kWh | D22: =D21 -> 324 | E22: =(ROUND(D22*K22,2)+ROUND(G22,2)+ROUND(J22,2))/ROUND(D22,4) -> 0.42447531 | F22: =ROUND(D22*E22,2) -> 137.53 | G22: =((D22*K22)/(1-$N$21-$N$23))*($N$21+$N$23) -> 7.0435785 | H22: =ROUND((D22*K22)/(1-$N$21-$N$23)/(1-$I$21),8) -> 137.54034 | J22: =ROUND(H22*$I$21,2) -> 23.38 | K22: =IF(AND($B$14<$F$2,$E$14<$F$2),D6,IF($B$14<$F$2,J6,G6)) -> 0.33060156 | L22: PIS Inj | M22: =D72 -> -245.42257 | N22: =N21 -> 0.011 | O22: =ROUND(M22*N22,2) -> -2.7
B23: Adicional BAM | C23: kWh | D23: =IF($K$12=M4,($D$21*($K$14)/($L$14+$K$14)),0)+IF($L$12=M4,($D$21*($L$14)/($L$14+$K$14)),0) -> 324 | E23: =IFERROR((ROUND(D23*K23,2)+ROUND(G23,2)+ROUND(J23,2))/ROUND(D23,4), 0) -> 0.024197531 | F23: =ROUND(D23*E23,2) -> 7.84 | G23: =((D23*K23)/(1-$N$21-$N$23))*($N$21+$N$23) -> 0.40160565 | H23: =ROUND((D23*K23)/(1-$N$21-$N$23)/(1-$I$21),8) -> 7.8421755 | J23: =ROUND(H23*$I$21,2) -> 1.33 | K23: =N4 -> 0.01885 | L23: COFINS | M23: =M21 -> 290.21635 | N23: 0.0507 | O23: =ROUND(M23*N23,2) -> 14.71
B24: Adicional BVM1 | C24: kWh | D24: =IF($K$12=M5,($D$21*($K$14)/($L$14+$K$14)),0)+IF($L$12=M5,($D$21*($L$14)/($L$14+$K$14)),0) -> 0 | E24: =IFERROR((ROUND(D24*K24,2)+ROUND(G24,2)+ROUND(J24,2))/ROUND(D24,4), 0) -> 0 | F24: =ROUND(D24*E24,2) -> 0 | G24: =((D24*K24)/(1-$N$21-$N$23))*($N$21+$N$23) -> 0 | H24: =ROUND((D24*K24)/(1-$N$21-$N$23)/(1-$I$21),8) -> 0 | J24: =ROUND(H24*$I$21,2) -> 0 | K24: =N5 -> 0.04463 | L24: COFINS Inj | M24: =M22 -> -245.42257 | N24: =N23 -> 0.0507 | O24: =ROUND(M24*N24,2) -> -12.44
B25: Adicional BVM2 | C25: kWh | D25: =IF($K$12=M6,($D$21*($K$14)/($L$14+$K$14)),0)+IF($L$12=M6,($D$21*($L$14)/($L$14+$K$14)),0) -> 0 | E25: =IFERROR((ROUND(D25*K25,2)+ROUND(G25,2)+ROUND(J25,2))/ROUND(D25,4), 0) -> 0 | F25: =ROUND(D25*E25,2) -> 0 | G25: =((D25*K25)/(1-$N$21-$N$23))*($N$21+$N$23) -> 0 | H25: =ROUND((D25*K25)/(1-$N$21-$N$23)/(1-$I$21),8) -> 0 | J25: =ROUND(H25*$I$21,2) -> 0 | K25: =N6 -> 0.07877
B26: Adicional EH | C26: kWh | D26: =IF($K$12=M7,($D$21*($K$14)/($L$14+$K$14)),0)+IF($L$12=M7,($D$21*($L$14)/($L$14+$K$14)),0) -> 0 | E26: =IFERROR((ROUND(D26*K26,2)+ROUND(G26,2)+ROUND(J26,2))/ROUND(D26,4), 0) -> 0 | F26: =ROUND(D26*E26,2) -> 0 | G26: =((D26*K26)/(1-$N$21-$N$23))*($N$21+$N$23) -> 0 | H26: =ROUND((D26*K26)/(1-$N$21-$N$23)/(1-$I$21),8) -> 0 | J26: =ROUND(H26*$I$21,2) -> 0 | K26: =N7 -> 0.142
B28: TUSD - Consumo inj | C28: kWh | D28: -274 | E28: =IFERROR((ROUND(D28*K28,2)+ROUND(G28,2)+ROUND(J28,2))/ROUND(D28,4),0) -> 0.52332117 | F28: =ROUND(D28*E28,2) -> -143.39 | G28: =((D28*K28)/(1-$N$22-$N$24))*($N$22+$N$24) -> -8.8467339 | H28: 0 | I28: 0 | J28: =H28*$I$21 -> 0 | K28: =K21 -> 0.49100844
B29: TE - Consumo inj | C29: kWh | D29: =D28 -> -274 | E29: =IFERROR((ROUND(D29*K29,2)+ROUND(G29,2)+ROUND(J29,2))/ROUND(D29,4),0) -> 0.42448905 | F29: =ROUND(D29*E29,2) -> -116.31 | G29: =((D29*K29)/(1-$N$22-$N$24))*($N$22+$N$24) -> -5.9566065 | H29: =ROUND((D29*K29)/(1-$N$22-$N$24)/(1-$I$21),8) -> -116.31498 | I29: =I21 -> 0.17 | J29: =H29*$I$21 -> -19.773547 | K29: =K22 -> 0.33060156
B30: Adicional BAM inj | C30: kWh | D30: =IF($K$12=M4,($D$28*($K$14)/($K$14+$L$14)),0)+IF($L$12=M4,($D$28*($L$14)/($K$14+$L$14)),0) -> -274 | E30: =IFERROR((ROUND(D30*K30,2)+ROUND(G30,2)+ROUND(J30,2))/ROUND(D30,4),0) -> 0.02419708 | F30: =ROUND(D30*E30,2) -> -6.63 | G30: =((D30*K30)/(1-$N$22-$N$24))*($N$22+$N$24) -> -0.33962947 | H30: =(D30*K30)/(1-$N$22-$N$24)/(1-$I$21) -> -6.6319632 | J30: =H30*$I$21 -> -1.1274337 | K30: =N4 -> 0.01885
B31: Adicional BVM1 inj | C31: kWh | D31: =IF($K$12=M5,($D$28*($K$14)/($K$14+$L$14)),0)+IF($L$12=M5,($D$28*($L$14)/($K$14+$L$14)),0) -> 0 | E31: =IFERROR((ROUND(D31*K31,2)+ROUND(G31,2)+ROUND(J31,2))/ROUND(D31,4),0) -> 0 | F31: =ROUND(D31*E31,2) -> 0 | G31: =((D31*K31)/(1-$N$22-$N$24))*($N$22+$N$24) -> 0 | H31: =(D31*K31)/(1-$N$22-$N$24)/(1-$I$21) -> 0 | J31: =H31*$I$21 -> 0 | K31: =N5 -> 0.04463
B32: Adicional BVM2 inj | C32: kWh | D32: =IF($K$12=M6,($D$28*($K$14)/($K$14+$L$14)),0)+IF($L$12=M6,($D$28*($L$14)/($K$14+$L$14)),0) -> 0 | E32: =IFERROR((ROUND(D32*K32,2)+ROUND(G32,2)+ROUND(J32,2))/ROUND(D32,4),0) -> 0 | F32: =ROUND(D32*E32,2) -> 0 | G32: =((D32*K32)/(1-$N$22-$N$24))*($N$22+$N$24) -> 0 | H32: =(D32*K32)/(1-$N$22-$N$24)/(1-$I$21) -> 0 | J32: =H32*$I$21 -> 0 | K32: =N6 -> 0.07877
B33: Adicional EH inj | C33: kWh | D33: =IF($K$12=M7,($D$28*($K$14)/($K$14+$L$14)),0)+IF($L$12=M7,($D$28*($L$14)/($K$14+$L$14)),0) -> 0 | E33: =IFERROR((ROUND(D33*K33,2)+ROUND(G33,2)+ROUND(J33,2))/ROUND(D33,4),0) -> 0 | F33: =ROUND(D33*E33,2) -> 0 | G33: =((D33*K33)/(1-$N$22-$N$24))*($N$22+$N$24) -> 0 | H33: =(D33*K33)/(1-$N$22-$N$24)/(1-$I$21) -> 0 | J33: =H33*$I$21 -> 0 | K33: =N7 -> 0.142
B35: Multas
B36: Juros
B37: Bônus/Descontos
B38: Doações | F38: -8.29
B39: CIP | F39: 46.36
B42: TOTAL | F42: =SUM(F21:F41) -> 121.39 | G42: =SUM(G21:G41) -> 2.7633157 | H42: =SUM(H21:H41) -> 226.71007 | J42: =SUM(J21:J41) -> 38.535684
B44: Informativo Escassez | C44: =(D21+D28) -> 50 | D44: =IF(AND($B$14<$F$2,$E$14<$F$2),C7,IF($B$14<$F$2,I7,F7)) -> 0.00018563466 | E44: =IF(AND($B$14<$F$2,$E$14<$F$2),D7,IF($B$14<$F$2,J7,G7)) -> -0.0021045458 | F44: =C44*(D44+E44) -> -0.095945556
B46: Fatura B1 Residencial
D47: Qtde | E47: TUSD | F47: TE | G47: TUSD + TE | H47: R$
B48: Fornecimento de Energia Elétrica | H48: =SUM(H50:H66)+SUM(H71:H76) -> 83.335768
B50: Energia Fornecida | D50: =D21 -> 324 | E50: =IF(AND($B$14<$F$2,$E$14<$F$2),C6,IF($B$14<$F$2,I6,F6)) -> 0.49100844 | F50: =IF(AND($B$14<$F$2,$E$14<$F$2),D6,IF($B$14<$F$2,J6,G6)) -> 0.33060156 | G50: =E50+F50 -> 0.82161 | H50: =ROUND((D50*E50),2)+ROUND((D50*F50),2) -> 266.2
B52: Adicional BAM | D52: =IF($K$12=M4,(D50*(K14)/(K14+L14)),0)+IF($L$12=M4,(D50*(L14)/(K14+L14)),0) -> 324 | F52: =N4 -> 0.01885 | H52: =ROUND(D52*(E52+F52),2) -> 6.11
B53: Adicional BVM 1 | D53: =IF($K$12=M5,(D50*(K14)/(K14+L14)),0)+IF($L$12=M5,(D50*(L14)/(K14+L14)),0) -> 0 | F53: =N5 -> 0.04463 | H53: =ROUND(D53*(E53+F53),2) -> 0
B54: Adicional BVM 2 | D54: =IF($K$12=M6,(D50*(K14)/(K14+L14)),0)+IF($L$12=M6,(D50*(L14)/(K14+L14)),0) -> 0 | F54: =N6 -> 0.07877 | H54: =ROUND(D54*(E54+F54),2) -> 0
B55: Adicional Escassez Hídrica | D55: =IF($K$12=M8,(D50*(K14)/(K14+L14)),0)+IF($L$12=M8,(D50*(L14)/(K14+L14)),0) -> 0 | F55: =N8 -> 0 | H55: =ROUND(D55*(E55+F55),2) -> 0
B57: Energia Injetada | D57: =D28 -> -274 | E57: =E50*F17 -> 0.49100844 | F57: =F50 -> 0.33060156 | G57: =E57+F57 -> 0.82161 | H57: =ROUND((D57*E57),2)+ROUND((D57*F57),2) -> -225.12
B59: Adicional BAM | D59: =IF($K$12=M4,(D57*(K14)/(K14+L14)),0)+IF($L$12=M4,(D57*(L14)/(K14+L14)),0) -> -274 | F59: =F52 -> 0.01885 | H59: =ROUND(D59*(E59+F59),2) -> -5.16
B60: Adicional BVM 1 | D60: =IF($K$12=M5,(D57*(K14)/(K14+L14)),0)+IF($L$12=M5,(D57*(L14)/(K14+L14)),0) -> 0 | F60: =F53 -> 0.04463 | H60: =ROUND(D60*(E60+F60),2) -> 0
B61: Adicional BVM 2 | D61: =IF($K$12=M6,(D57*(K14)/(K14+L14)),0)+IF($L$12=M6,(D57*(L14)/(K14+L14)),0) -> 0 | F61: =F54 -> 0.07877 | H61: =ROUND(D61*(E61+F61),2) -> 0
B62: Adicional Escassez Hídrica | D62: =IF($K$12=M8,(D57*(K14)/(K14+L14)),0)+IF($L$12=M8,(D57*(L14)/(K14+L14)),0) -> 0 | F62: =F55 -> 0 | H62: =ROUND(D62*(E62+F62),2) -> 0
H68: =SUM(H50:H67) -> 42.03
D70: Base de Cálculo
B71: PIS | D71: =(H50+H52+H53+H54+H55)/(1-E71-E73) -> 290.21635 | E71: =N21 -> 0.011 | H71: =D71*E71 -> 3.1923798
B72: PIS Eneg Inj | D72: =(H57+H59+H60+H61+H62+H64+H66)/(1-E71-E73) -> -245.42257 | E72: =E71 -> 0.011 | H72: =D72*E72 -> -2.6996483
B73: COFINS | D73: =D71 -> 290.21635 | E73: =N23 -> 0.0507 | H73: =D73*E73 -> 14.713969
B74: COFINS Eneg Inj | D74: =D72 -> -245.42257 | E74: =E73 -> 0.0507 | H74: =D74*E74 -> -12.442924
B75: ICMS | D75: =D71/(1-E75) -> 349.65825 | E75: 0.17 | H75: =D75*E75 -> 59.441903
B76: ICMS Eneg Inj | D76: =((D57*F57)+(H59+H60+H61+H62)+(D64*F64)+(D66*F66))/(1-E72-E74)/(1-E76) -> -122.94065 | E76: =E75 -> 0.17 | H76: =D76*E76 -> -20.899911
B78: Informativo Escassez Hídrica | D78: =D50+D57 -> 50 | E78: =IF(AND($B$14<$F$2,$E$14<$F$2),C7,IF($B$14<$F$2,I7,F7)) -> 0.00018563466 | F78: =IF(AND($B$14<$F$2,$E$14<$F$2),D7,IF($B$14<$F$2,J7,G7)) -> -0.0021045458 | H78: =D78*(E78+F78) -> -0.095945556

Sheet Fatura B1 (GD I)
B2: B1 Res | E2: Vigência das Tarifas: | F2: 45145 | I2: GDI | M2: Bandeira | N2: R$/kWh | O2: ANEEL em 29/06 | Q2: TUSD FIO B
M3: VERDE | N3: 0
B4: TARIFA | C4: TARIFA ANTIGA - REH 3091/2022 | F4: TARIFA NOVA - REH XXXX/2023 | I4: Tarifas Proporcionalizadas | M4: BAM | N4: 0.02989 | Q4: TARIFA | R4: =C4 -> TARIFA ANTIGA - REH 3091/2022 | U4: =F4 -> TARIFA NOVA - REH XXXX/2023 | X4: Tarifas Proporcionalizadas
C5: Tusd | D5: TE | E5: TUSD + TE | F5: Tusd | G5: TE | H5: TUSD + TE | I5: Tusd | J5: TE | K5: TUSD + TE | M5: BVM1 | N5: 0.065 | R5: Tusd (R$/kWh) | U5: Tusd (R$/kWh) | X5: Tusd (R$/kWh)
B6: B1 | C6: 0.39681 | D6: 0.27703 | E6: =C6+D6 -> 0.67384 | F6: 0.39681 | G6: 0.27703 | H6: =F6+G6 -> 0.67384 | I6: =((C6*$C$14)+(F6*$D$14))/($D$14+$C$14) -> 0.39681 | J6: =((D6*$C$14)+(G6*$D$14))/($D$14+$C$14) -> 0.27703 | K6: =I6+J6 -> 0.67384 | M6: BVM2 | N6: 0.09795 | Q6: =B6 -> B1 | R6: ='[2]FIO B'!H11/1000 -> 0.19205 | U6: ='[2]FIO B'!K11/1000 -> 0.17652 | X6: =((R6*$C$14)+(U6*$D$14))/($D$14+$C$14) -> 0.18503645
B7: CDE Escassez Hídrica | F7: =T11 -> 0.00020011 | G7: =U11 -> 0.00402681 | H7: =F7+G7 -> 0.00422692 | I7: =((C7*$C$14)+(F7*$D$14))/($D$14+$C$14) -> 9.0372258e-05 | J7: =((D7*$C$14)+(G7*$D$14))/($D$14+$C$14) -> 0.0018185594 | K7: =I7+J7 -> 0.0019089316
B8: TE SCEE | G8: =G6*15% -> 0.0415545 | J8: =((D8*$C$14)+(G8*$D$14))/($D$14+$C$14) -> 0.018766548 | M8: Escassez Hídrica | N8: 0.142 | P8: CUSTO | T8: Tusd (R$/kWh) | U8: TE (R$/kWh)
P9: CDE CONTAS
H10: Fatura | L10: Vigência das Tarifas (troca Bandeira): | M10: =EOMONTH(B14,0)+1 -> 45139 | P10: CDE COVID
B11: INSTALAÇÃO | C11: 1182321 | H11: =E14 -> 45158 | K11: Altere a bandeira na célula abaixo | P11: CDE ESCASSEZ HÍDRICA | T11: 0.00020011 | U11: 0.00402681
K12: BAM | L12: BVM2
B13: Leitura Anterior | C13: Nº de dias tarifa Anterior | D13: Nº de dias tarifa Nova | E13: Leitura Atual | J13: Leitura Anterior | K13: Nº de dias tarifa Anterior | L13: Nº de dias tarifa Nova | M13: Leitura Atual
B14: 45127 | C14: =IF((F2-B14-1)<0,0,(F2-B14-1)) -> 17 | D14: =E14-F2+1 -> 14 | E14: 45158 | J14: =B14 -> 45127 | K14: =IF((M10-J14-1)<0,0,(M10-J14-1)) -> 11 | L14: =M14-M10+1 -> 20 | M14: =E14 -> 45158
B17: Perc. de Redução da Energia Injetada | E17: TUSD | F17: 1 | G17: TE | H17: 1
B19: Fatura B1 Residencial
D20: Qtde | E20: TUSD | F20: TE | G20: TUSD + TE | H20: R$
B21: Fornecimento de Energia Elétrica | H21: =SUM(H23:H39)+SUM(H44:H49) -> 254.92055
B23: Energia Fornecida | D23: 2000 | E23: =IF(AND($B$14<$F$2,$E$14<$F$2),C6,IF($B$14<$F$2,I6,F6)) -> 0.39681 | F23: =IF(AND($B$14<$F$2,$E$14<$F$2),D6,IF($B$14<$F$2,J6,G6)) -> 0.27703 | G23: =E23+F23 -> 0.67384 | H23: =ROUND((D23*E23),2)+ROUND((D23*F23),2) -> 1347.68
B25: Adicional BAM | D25: =IF($K$12=M4,(D23*(K14)/(K14+L14)),0)+IF($L$12=M4,(D23*(L14)/(K14+L14)),0) -> 709.67742 | F25: =N4 -> 0.02989 | H25: =ROUND(D25*(E25+F25),2) -> 21.21
B26: Adicional BVM 1 | D26: =IF($K$12=M5,(D23*(K14)/(K14+L14)),0)+IF($L$12=M5,(D23*(L14)/(K14+L14)),0) -> 0 | F26: =N5 -> 0.065 | H26: =ROUND(D26*(E26+F26),2) -> 0
B27: Adicional BVM 2 | D27: =IF($K$12=M6,(D23*(K14)/(K14+L14)),0)+IF($L$12=M6,(D23*(L14)/(K14+L14)),0) -> 1290.3226 | F27: =N6 -> 0.09795 | H27: =ROUND(D27*(E27+F27),2) -> 126.39
B28: Adicional Escassez Hídrica | D28: =IF($K$12=M8,(D23*(K14)/(K14+L14)),0)+IF($L$12=M8,(D23*(L14)/(K14+L14)),0) -> 0 | F28: =N8 -> 0.142 | H28: =ROUND(D28*(E28+F28),2) -> 0
B30: Energia Injetada | D30: -1900.0009 | E30: =E23*F17 -> 0.39681 | F30: =F23 -> 0.27703 | G30: =E30+F30 -> 0.67384 | H30: =ROUND((D30*E30),2)+ROUND((D30*F30),2) -> -1280.3
B32: Adicional BAM | D32: =IF($K$12=M4,(D30*(K14)/(K14+L14)),0)+IF($L$12=M4,(D30*(L14)/(K14+L14)),0) -> -674.19385 | F32: =F25 -> 0.02989 | H32: =ROUND(D32*(E32+F32),2) -> -20.15
B33: Adicional BVM 1 | D33: =IF($K$12=M5,(D30*(K14)/(K14+L14)),0)+IF($L$12=M5,(D30*(L14)/(K14+L14)),0) -> 0 | F33: =F26 -> 0.065 | H33: =ROUND(D33*(E33+F33),2) -> 0
B34: Adicional BVM 2 | D34: =IF($K$12=M6,(D30*(K14)/(K14+L14)),0)+IF($L$12=M6,(D30*(L14)/(K14+L14)),0) -> -1225.807 | F34: =F27 -> 0.09795 | H34: =ROUND(D34*(E34+F34),2) -> -120.07
B35: Adicional Escassez Hídrica | D35: =IF($K$12=M8,(D30*(K14)/(K14+L14)),0)+IF($L$12=M8,(D30*(L14)/(K14+L14)),0) -> 0 | F35: =F28 -> 0.142 | H35: =ROUND(D35*(E35+F35),2) -> 0
H41: =SUM(H23:H40) -> 74.76
D43: Base de Cálculo
B44: PIS | D44: =(H23+H25+H26+H27+H28)/(1-E44-E46) -> 1559.0449 | E44: 0.0073 | H44: =D44*E44 -> 11.381028
B45: PIS Eneg Inj | D45: =(H30+H32+H33+H34+H35+H37+H39)/(1-E44-E46) -> -1481.0969 | E45: =E44 -> 0.0073 | H45: =D45*E45 -> -10.812007
B46: COFINS | D46: =D44 -> 1559.0449 | E46: 0.0336 | H46: =D46*E46 -> 52.38391
B47: COFINS Eneg Inj | D47: =D45 -> -1481.0969 | E47: =E46 -> 0.0336 | H47: =D47*E47 -> -49.764855
B48: ICMS | D48: =D44/(1-E48) -> 1878.3674 | E48: 0.17 | H48: =D48*E48 -> 319.32246
B49: ICMS Eneg Inj | D49: =((D30*F30)+(H32+H33+H34+H35)+(D37*F37)+(D39*F39))/(1-E45-E47)/(1-E49) -> -837.35284 | E49: =E48 -> 0.17 | H49: =D49*E49 -> -142.34998
B51: Informativo Escassez Hídrica | D51: =D23+D30 -> 99.999137 | E51: =IF(AND($B$13<$F$2,$E$13<$F$2),C7,IF($B$13<$F$2,I7,F7)) -> 0.00020011 | F51: =IF(AND($B$13<$F$2,$E$13<$F$2),D7,IF($B$13<$F$2,J7,G7)) -> 0.00402681 | H51: =D51*(E51+F51) -> 0.42268835

Sheet Fatura B1CDE (GD) OK
B2: B1 Res | E2: Vigência das Tarifas: | F2: ='Fatura B1 (GD) OK'!F2 -> 46241 | M2: Bandeira | N2: R$/kWh | O2: ANEEL em 29/06 | Q2: TUSD FIO B
M3: VERDE | N3: 0
B4: TARIFA | C4: TARIFA ANTIGA - REH 3508/2025 | F4: TARIFA NOVA - REH xxxx/2026 | I4: Tarifas Proporcionalizadas | M4: BAM | N4: =[1]BANDEIRA!$D$5 -> 0.01885 | Q4: TARIFA | R4: =C4 -> TARIFA ANTIGA - REH 3508/2025 | U4: =F4 -> TARIFA NOVA - REH xxxx/2026 | X4: Tarifas Proporcionalizadas
C5: Tusd | D5: TE | E5: TUSD + TE | F5: Tusd | G5: TE | H5: TUSD + TE | I5: Tusd | J5: TE | K5: TUSD + TE | M5: BVM1 | N5: =[1]BANDEIRA!$D$6 -> 0.04463 | R5: Tusd (R$/kWh) | U5: Tusd (R$/kWh) | X5: Tusd (R$/kWh)
B6: B1 | C6: ='TABELA DE TARIFAS ANTIGAS'!G71/1000 -> 0.46863 | D6: ='TABELA DE TARIFAS ANTIGAS'!H71/1000 -> 0.32068 | E6: =C6+D6 -> 0.78931 | F6: ='TABELA DE TARIFAS NOVAS'!G73/1000 -> 0.50632 | G6: ='TABELA DE TARIFAS NOVAS'!H73/1000 -> 0.33739 | H6: =F6+G6 -> 0.84371 | I6: =((C6*$C$16)+(F6*$D$16))/($D$16+$C$16) -> 0.48621867 | J6: =((D6*$C$16)+(G6*$D$16))/($D$16+$C$16) -> 0.328478 | K6: =I6+J6 -> 0.81469667 | M6: BVM2 | N6: =[1]BANDEIRA!$D$7 -> 0.07877 | Q6: =B6 -> B1 | R6: ='FIO B'!H11/1000 -> 0.20383072 | U6: ='FIO B'!K11/1000 -> 0.20915159 | X6: =((R6*$C$16)+(U6*$D$16))/($D$16+$C$16) -> 0.20631379
B7: B1CDE | C7: ='TABELA DE TARIFAS ANTIGAS'!G73/1000 -> 0.34019 | D7: ='TABELA DE TARIFAS ANTIGAS'!H73/1000 -> 0.29666 | E7: =C7+D7 -> 0.63685 | F7: ='TABELA DE TARIFAS NOVAS'!G75/1000 -> 0.35642 | G7: ='TABELA DE TARIFAS NOVAS'!H75/1000 -> 0.33759 | H7: =F7+G7 -> 0.69401 | I7: =((C7*$C$16)+(F7*$D$16))/($D$16+$C$16) -> 0.347764 | J7: =((D7*$C$16)+(G7*$D$16))/($D$16+$C$16) -> 0.31576067 | K7: =I7+J7 -> 0.66352467 | M7: Escassez Hídrica | N7: 0.142
B8: CDE Escassez Hídrica até 120 kWh | C8: 0 | D8: -0.0044 | E8: =C8+D8 -> -0.0044 | F8: =T12 -> 0 | G8: =U12 -> -0.00053182975 | H8: =F8+G8 -> -0.00053182975 | I8: =((C8*$C$16)+(F8*$D$16))/($D$16+$C$16) -> 0 | J8: =((D8*$C$16)+(G8*$D$16))/($D$16+$C$16) -> -0.0025948539 | K8: =I8+J8 -> -0.0025948539
B9: CDE Escassez Hídrica acima 120 kWh | C9: 0.00018774721 | D9: -0.0044031307 | E9: =C9+D9 -> -0.0042153835 | F9: =T13 -> 0.00018418923 | G9: =U13 -> -0.00053182975 | H9: =F9+G9 -> -0.00034764052 | I9: =((C9*$C$16)+(F9*$D$16))/($D$16+$C$16) -> 0.00018608682 | J9: =((D9*$C$16)+(G9*$D$16))/($D$16+$C$16) -> -0.0025965236 | K9: =I9+J9 -> -0.0024104368
B10: TE SCEE | G10: =G6*15% -> 0.0506085 | J10: =((D10*$C$16)+(G10*$D$16))/($D$16+$C$16) -> 0.0236173 | P10: CUSTO | R10: Part. TUSD (%) | S10: Part. TE (%) | T10: Tusd (R$/kWh) | U10: TE (R$/kWh)
P11: CDE CONTAS
H12: Fatura | L12: Vigência das Tarifas (troca Bandeira): | M12: =EOMONTH(B16,0)+1 -> 46235 | P12: CDE ESCASSEZ HÍDRICA | T12: 0 | U12: =-0.531829748712515/1000 -> -0.00053182975
B13: INSTALAÇÃO | C13: 9858 | H13: =E16 -> 46254 | K13: Altere a bandeira na célula abaixo | P13: CDE ESCASSEZ HÍDRICA | T13: ='Fatura B1 (GD) OK'!T11 -> 0.00018418923 | U13: ='Fatura B1 (GD) OK'!U11 -> -0.00053182975
K14: BAM | L14: BAM
B15: Leitura Anterior | C15: Nº de dias tarifa Anterior | D15: Nº de dias tarifa Nova | E15: Leitura Atual | J15: Leitura Anterior | K15: Nº de dias tarifa Anterior | L15: Nº de dias tarifa Nova | M15: Leitura Atual
B16: 46224 | C16: =IF((F2-B16-1)<0,0,(F2-B16-1)) -> 16 | D16: =E16-F2+1 -> 14 | E16: 46254 | J16: =B16 -> 46224 | K16: =IF((M12-J16-1)<0,0,(M12-J16-1)) -> 10 | L16: =M16-M12+1 -> 20 | M16: =E16 -> 46254
B19: Perc. de Redução da Energia Injetada | E19: TUSD | F19: 1 | G19: TE | H19: 1 | M19: Documento Impressão | O19: 1025311174
B21: Descrição | C21: Unidade | D21: Quantidade | E21: Preço Unit (R$) com tributos | F21: Valor Total (R$) | G21: PIS/COFINS (R$) | H21: Base de Cálculo ICMS (R$) | I21: Alíquota ICMS (%) | J21: ICMS (R$) | K21: Preço Unit (R$) | L21: Tributos | M21: Base de Cálc (R$) | N21: Alíquota (%) | O21: Valor (R$)
R22: TUSD Fio B | S22: Receita Fio B
B23: TUSD - Consumo até 120 KWh | C23: kWh | D23: 120 | E23: =(ROUND(D23*K23,2)+ROUND(G23,2)+ROUND(J23,2))/ROUND(D23,4) -> 0.4465 | F23: =ROUND(D23*E23,2) -> 53.58 | G23: =((D23*K23)/(1-$N$23-$N$25))*($N$23+$N$25) -> 2.7441593 | H23: =((D23*K23)/(1-$N$23-$N$25)/(1-$I$23)) -> 53.585349 | I23: 0.17 | J23: =(H23*$I$23) -> 9.1095093 | K23: =IF(AND($B$16<$F$2,$E$16<$F$2),C7,IF($B$16<$F$2,I7,F7)) -> 0.347764 | L23: PIS | M23: =D81 -> 106.60769 | N23: 0.011 | O23: =ROUND(M23*N23,2) -> 1.17 | R23: =IF(AND($B$16<$F$2,$E$16<$F$2),R6,IF($B$16<$F$2,X6,U6)) -> 0.20631379 | S23: =(D23+D24)*R23 -> 149.37119 | T23: não está considerando energia injetada
B24: TUSD - Consumo acima 120 KWh | C24: kWh | D24: 604 | E24: =(ROUND(D24*K24,2)+ROUND(G24,2)+ROUND(J24,2))/ROUND(D24,4) -> 0.62433775 | F24: =ROUND(D24*E24,2) -> 377.1 | G24: =((D24*K24)/(1-$N$23-$N$25))*($N$23+$N$25) -> 19.311322 | H24: =ROUND((D24*K24)/(1-$N$23-$N$25)/(1-$I$23),8) -> 377.09325 | J24: =ROUND(H24*$I$23,2) -> 64.11 | K24: =IF(AND($B$16<$F$2,$E$16<$F$2),C6,IF($B$16<$F$2,I6,F6)) -> 0.48621867 | L24: PIS Inj | M24: =D8280 -> 0 | N24: =N23 -> 0.011 | O24: =ROUND(M24*N24,2) -> 0
B25: TUSD - Consumo inj até 120kwh | C25: kWh | D25: -20 | E25: =(ROUND(D25*K25,2)+ROUND(G25,2)+ROUND(J25,2))/ROUND(D25,4) -> 0.371 | F25: =ROUND(D25*E25,2) -> -7.42 | G25: =((D25*K25)/(1-$N$24-$N$26))*($N$24+$N$26) -> -0.45735988 | H25: =((D25*K25)/(1-$N$23-$N$25)/(1-$I$23))*0 -> 0 | J25: =(H25*$I$23) -> 0 | K25: =K23 -> 0.347764 | L25: COFINS | M25: =M23 -> 106.60769 | N25: 0.0507 | O25: =ROUND(M25*N25,2) -> 5.41
B26: TUSD - Consumo inj acima 120kwh | C26: kWh | D26: -604 | E26: =(ROUND(D26*K26,2)+ROUND(G26,2)+ROUND(J26,2))/ROUND(D26,4) -> 0.51819536 | F26: =ROUND(D26*E26,2) -> -312.99 | G26: =((D26*K26)/(1-$N$24-$N$26))*($N$24+$N$26) -> -19.311322 | H26: =ROUND((D26*K26)/(1-$N$23-$N$25)/(1-$I$23),8)*0 -> 0 | J26: =ROUND(H26*$I$23,2) -> 0 | K26: =K24 -> 0.48621867 | L26: COFINS Inj | M26: =M24 -> 0 | N26: =N25 -> 0.0507 | O26: =ROUND(M26*N26,2) -> 0
B27: Adicional BAM | C27: kWh | D27: =IF($K$14=M4,(($D$23+$D$24)*($K$16)/($L$16+$K$16)),0)+IF($L$14=M4,(($D$23+$D$24)*($L$16)/($L$16+$K$16)),0) -> 724 | E27: =IFERROR((ROUND(D27*K27,2)+ROUND(G27,2)+ROUND(J27,2))/ROUND(D27,4), 0) -> 0.024212707 | F27: =ROUND(D27*E27,2) -> 17.53 | G27: =((D27*K27)/(1-$N$23-$N$25))*($N$23+$N$25) -> 0.89741509 | H27: =ROUND((D27*K27)/(1-$N$23-$N$25)/(1-$I$23),8) -> 17.523874 | J27: =ROUND(H27*$I$23,2) -> 2.98 | K27: =N4 -> 0.01885
B28: Adicional BVM1 | C28: kWh | D28: =IF($K$14=M5,(($D$23+$D$24)*($K$16)/($L$16+$K$16)),0)+IF($L$14=M5,(($D$23+$D$24)*($L$16)/($L$16+$K$16)),0) -> 0 | E28: =IFERROR((ROUND(D28*K28,2)+ROUND(G28,2)+ROUND(J28,2))/ROUND(D28,4), 0) -> 0 | F28: =ROUND(D28*E28,2) -> 0 | G28: =((D28*K28)/(1-$N$23-$N$25))*($N$23+$N$25) -> 0 | H28: =ROUND((D28*K28)/(1-$N$23-$N$25)/(1-$I$23),8) -> 0 | J28: =ROUND(H28*$I$23,2) -> 0 | K28: =N5 -> 0.04463
B29: Adicional BVM2 | C29: kWh | D29: =IF($K$14=M6,(($D$23+$D$24)*($K$16)/($L$16+$K$16)),0)+IF($L$14=M6,(($D$23+$D$24)*($L$16)/($L$16+$K$16)),0) -> 0 | E29: =IFERROR((ROUND(D29*K29,2)+ROUND(G29,2)+ROUND(J29,2))/ROUND(D29,4), 0) -> 0 | F29: =ROUND(D29*E29,2) -> 0 | G29: =((D29*K29)/(1-$N$23-$N$25))*($N$23+$N$25) -> 0 | H29: =ROUND((D29*K29)/(1-$N$23-$N$25)/(1-$I$23),8) -> 0 | J29: =ROUND(H29*$I$23,2) -> 0 | K29: =N6 -> 0.07877
B30: Adicional EH | C30: kWh | D30: =IF($K$14=M7,(($D$23+$D$24)*($K$16)/($L$16+$K$16)),0)+IF($L$14=M7,(($D$23+$D$24)*($L$16)/($L$16+$K$16)),0) -> 0 | E30: =IFERROR((ROUND(D30*K30,2)+ROUND(G30,2)+ROUND(J30,2))/ROUND(D30,4), 0) -> 0 | F30: =ROUND(D30*E30,2) -> 0 | G30: =((D30*K30)/(1-$N$23-$N$25))*($N$23+$N$25) -> 0 | H30: =ROUND((D30*K30)/(1-$N$23-$N$25)/(1-$I$23),8) -> 0 | J30: =ROUND(H30*$I$23,2) -> 0 | K30: =N7 -> 0.142
B32: TE - Consumo até 120 KWh | C32: kWh | D32: =D23 -> 120 | E32: =IFERROR((ROUND(D32*K32,2)+ROUND(G32,2)+ROUND(J32,2))/ROUND(D32,4),0) -> 0.40541667 | F32: =ROUND(D32*E32,2) -> 48.65 | G32: =((D32*K32)/(1-$N$23-$N$25))*($N$23+$N$25) -> 2.4916253 | H32: =((D32*K32)/(1-$N$23-$N$25)/(1-$I$23)) -> 48.654103 | J32: =H32*$I$23 -> 8.2711975 | K32: =IF(AND($B$16<$F$2,$E$16<$F$2),D7,IF($B$16<$F$2,J7,G7)) -> 0.31576067
B33: TE - Consumo acima 120 KWh | C33: kWh | D33: =D24 -> 604 | E33: =IFERROR((ROUND(D33*K33,2)+ROUND(G33,2)+ROUND(J33,2))/ROUND(D33,4),0) -> 0.42178808 | F33: =ROUND(D33*E33,2) -> 254.76 | G33: =((D33*K33)/(1-$N$23-$N$25))*($N$23+$N$25) -> 13.046279 | H33: =ROUND((D33*K33)/(1-$N$24-$N$26)/(1-$I$23),8) -> 254.75541 | J33: =H33*$I$23 -> 43.30842 | K33: =IF(AND($B$16<$F$2,$E$16<$F$2),D6,IF($B$16<$F$2,J6,G6)) -> 0.328478
B34: TE - Consumo inj até 120kwh | C34: kWh | D34: =D25 -> -20 | E34: =IFERROR((ROUND(D34*K34,2)+ROUND(G34,2)+ROUND(J34,2))/ROUND(D34,4),0) -> 0.406 | F34: =ROUND(D34*E34,2) -> -8.12 | G34: =((D34*K34)/(1-$N$24-$N$26))*($N$24+$N$26) -> -0.41527088 | H34: =((D34*K34)/(1-$N$23-$N$26)/(1-$I$23)) -> -8.1090171 | J34: =H34*$I$23 -> -1.3785329 | K34: =K32 -> 0.31576067
B35: TE - Consumo inj acima 120kwh | C35: kWh | D35: =D26 -> -604 | E35: =IFERROR((ROUND(D35*K35,2)+ROUND(G35,2)+ROUND(J35,2))/ROUND(D35,4),0) -> 0.42178808 | F35: =ROUND(D35*E35,2) -> -254.76 | G35: =((D35*K35)/(1-$N$24-$N$26))*($N$24+$N$26) -> -13.046279 | H35: =ROUND((D35*K35)/(1-$N$24-$N$26)/(1-$I$23),8) -> -254.75541 | J35: =H35*$I$23 -> -43.30842 | K35: =K33 -> 0.328478
B36: Adicional BAM inj | C36: kWh | D36: =IF($K$14=M4,(($D$25+$D$26)*($K$16)/($K$16+$L$16)),0)+IF($L$14=M4,(($D$25+$D$26)*($L$16)/($K$16+$L$16)),0) -> -624 | E36: =IFERROR((ROUND(D36*K36,2)+ROUND(G36,2)+ROUND(J36,2))/ROUND(D36,4),0) -> 0.024198718 | F36: =ROUND(D36*E36,2) -> -15.1 | G36: =((D36*K36)/(1-$N$24-$N$26))*($N$24+$N$26) -> -0.77346273 | H36: =(D36*K36)/(1-$N$24-$N$26)/(1-$I$23) -> -15.103449 | J36: =H36*$I$23 -> -2.5675863 | K36: =N4 -> 0.01885
B37: Adicional BVM1 inj | C37: kWh | D37: =IF($K$14=M5,(($D$25+$D$26)*($K$16)/($K$16+$L$16)),0)+IF($L$14=M5,(($D$25+$D$26)*($L$16)/($K$16+$L$16)),0) -> 0 | E37: =IFERROR((ROUND(D37*K37,2)+ROUND(G37,2)+ROUND(J37,2))/ROUND(D37,4),0) -> 0 | F37: =ROUND(D37*E37,2) -> 0 | G37: =((D37*K37)/(1-$N$24-$N$26))*($N$24+$N$26) -> 0 | H37: =(D37*K37)/(1-$N$24-$N$26)/(1-$I$23) -> 0 | J37: =H37*$I$23 -> 0 | K37: =N5 -> 0.04463
B38: Adicional BVM2 inj | C38: kWh | D38: =IF($K$14=M6,(($D$25+$D$26)*($K$16)/($K$16+$L$16)),0)+IF($L$14=M6,(($D$25+$D$26)*($L$16)/($K$16+$L$16)),0) -> 0 | E38: =IFERROR((ROUND(D38*K38,2)+ROUND(G38,2)+ROUND(J38,2))/ROUND(D38,4),0) -> 0 | F38: =ROUND(D38*E38,2) -> 0 | G38: =((D38*K38)/(1-$N$24-$N$26))*($N$24+$N$26) -> 0 | H38: =(D38*K38)/(1-$N$24-$N$26)/(1-$I$23) -> 0 | J38: =H38*$I$23 -> 0 | K38: =N6 -> 0.07877
B39: Adicional EH inj | C39: kWh | D39: =IF($K$14=M7,(($D$25+$D$26)*($K$16)/($K$16+$L$16)),0)+IF($L$14=M7,(($D$25+$D$26)*($L$16)/($K$16+$L$16)),0) -> 0 | E39: =IFERROR((ROUND(D39*K39,2)+ROUND(G39,2)+ROUND(J39,2))/ROUND(D39,4),0) -> 0 | F39: =ROUND(D39*E39,2) -> 0 | G39: =((D39*K39)/(1-$N$24-$N$26))*($N$24+$N$26) -> 0 | H39: =(D39*K39)/(1-$N$24-$N$26)/(1-$I$23) -> 0 | J39: =H39*$I$23 -> 0 | K39: =N7 -> 0.142
B41: Multas | F41: 0
B42: Juros | F42: 0
B43: Bônus/Descontos | F43: -8.97
B44: Doações | F44: 0
B45: CIP | F45: 0
B48: TOTAL | F48: =SUM(F23:F47) -> 144.26 | G48: =SUM(G23:G47) -> 4.4871061 | H48: =SUM(H23:H47) -> 473.64411 | J48: =SUM(J23:J47) -> 80.524587
B50: Informativo Escassez | C50: =(D23) -> 120 | D50: =IF(AND($B$16<$F$2,$E$16<$F$2),C8,IF($B$16<$F$2,I8,F8)) -> 0 | E50: =IF(AND($B$16<$F$2,$E$16<$F$2),D8,IF($B$16<$F$2,J8,G8)) -> -0.0025948539 | F50: =C50*(D50+E50) -> -0.31138247 | G50: não está correto no sistema, está com quantidades superiores e tributando
C51: =(D24) -> 604 | D51: =IF(AND($B$16<$F$2,$E$16<$F$2),C9,IF($B$16<$F$2,I9,F9)) -> 0.00018608682 | E51: =IF(AND($B$16<$F$2,$E$16<$F$2),D9,IF($B$16<$F$2,J9,G9)) -> -0.0025965236 | F51: =C51*(D51+E51) -> -1.4559038
C52: =D25 -> -20 | D52: =D50 -> 0 | E52: =E50 -> -0.0025948539 | F52: =C52*(D52+E52) -> 0.051897078
C53: =D26 -> -604 | D53: =D51 -> 0.00018608682 | E53: =E51 -> -0.0025965236 | F53: =C53*(D53+E53) -> 1.4559038
F54: =SUM(F50:F53) -> -0.25948539
J55: Verifivar base do PIS e COFINS
B56: Fatura B1 Residencial
D57: Qtde | E57: TUSD | F57: TE | G57: TUSD + TE | H57: R$
B58: Fornecimento de Energia Elétrica | H58: =SUM(H60:H76)+SUM(H81:H86) -> 244.14835
B60: Energia Fornecida | D60: =D23 -> 120 | E60: =IF(AND($B$16<$F$2,$E$16<$F$2),C6,IF($B$16<$F$2,I6,F6)) -> 0.48621867 | F60: =IF(AND($B$16<$F$2,$E$16<$F$2),D6,IF($B$16<$F$2,J6,G6)) -> 0.328478 | G60: =E60+F60 -> 0.81469667 | H60: =ROUND((D60*E60),2)+ROUND((D60*F60),2) -> 97.77
B62: Adicional BAM | D62: =IF($K$14=M4,(D60*(K16)/(K16+L16)),0)+IF($L$14=M4,(D60*(L16)/(K16+L16)),0) -> 120 | F62: =N4 -> 0.01885 | H62: =ROUND(D62*(E62+F62),2) -> 2.26
B63: Adicional BVM 1 | D63: =IF($K$14=M5,(D60*(K16)/(K16+L16)),0)+IF($L$14=M5,(D60*(L16)/(K16+L16)),0) -> 0 | F63: =N5 -> 0.04463 | H63: =ROUND(D63*(E63+F63),2) -> 0
B64: Adicional BVM 2 | D64: =IF($K$14=M6,(D60*(K16)/(K16+L16)),0)+IF($L$14=M6,(D60*(L16)/(K16+L16)),0) -> 0 | F64: =N6 -> 0.07877 | H64: =ROUND(D64*(E64+F64),2) -> 0
B65: Adicional Escassez Hídrica | D65: =IF($K$14=M10,(D60*(K16)/(K16+L16)),0)+IF($L$14=M10,(D60*(L16)/(K16+L16)),0) -> 0 | F65: =N10 -> 0 | H65: =ROUND(D65*(E65+F65),2) -> 0
B67: Energia Injetada | D67: =D32 -> 120 | E67: =E60*F19 -> 0.48621867 | F67: =F60 -> 0.328478 | G67: =E67+F67 -> 0.81469667 | H67: =ROUND((D67*E67),2)+ROUND((D67*F67),2) -> 97.77
B69: Adicional BAM | D69: =IF($K$14=M4,(D67*(K16)/(K16+L16)),0)+IF($L$14=M4,(D67*(L16)/(K16+L16)),0) -> 120 | F69: =F62 -> 0.01885 | H69: =ROUND(D69*(E69+F69),2) -> 2.26
B70: Adicional BVM 1 | D70: =IF($K$14=M5,(D67*(K16)/(K16+L16)),0)+IF($L$14=M5,(D67*(L16)/(K16+L16)),0) -> 0 | F70: =F63 -> 0.04463 | H70: =ROUND(D70*(E70+F70),2) -> 0
B71: Adicional BVM 2 | D71: =IF($K$14=M6,(D67*(K16)/(K16+L16)),0)+IF($L$14=M6,(D67*(L16)/(K16+L16)),0) -> 0 | F71: =F64 -> 0.07877 | H71: =ROUND(D71*(E71+F71),2) -> 0
B72: Adicional Escassez Hídrica | D72: =IF($K$14=M10,(D67*(K16)/(K16+L16)),0)+IF($L$14=M10,(D67*(L16)/(K16+L16)),0) -> 0 | F72: =F65 -> 0 | H72: =ROUND(D72*(E72+F72),2) -> 0
H78: =SUM(H60:H77) -> 200.06
D80: Base de Cálculo
B81: PIS | D81: =(H60+H62+H63+H64+H65)/(1-E81-E83) -> 106.60769 | E81: =N23 -> 0.011 | H81: =D81*E81 -> 1.1726846
B82: PIS Eneg Inj | D82: =(H67+H69+H70+H71+H72+H74+H76)/(1-E81-E83) -> 106.60769 | E82: =E81 -> 0.011 | H82: =D82*E82 -> 1.1726846
B83: COFINS | D83: =D81 -> 106.60769 | E83: =N25 -> 0.0507 | H83: =D83*E83 -> 5.4050101
B84: COFINS Eneg Inj | D84: =D82 -> 106.60769 | E84: =E83 -> 0.0507 | H84: =D84*E84 -> 5.4050101
B85: ICMS | D85: =D81/(1-E85) -> 128.44301 | E85: 0.17 | H85: =D85*E85 -> 21.835311
B86: ICMS Eneg Inj | D86: =((D67*F67)+(H69+H70+H71+H72)+(D74*F74)+(D76*F76))/(1-E82-E84)/(1-E86) -> 53.515599 | E86: =E85 -> 0.17 | H86: =D86*E86 -> 9.0976519
B88: Informativo Escassez Hídrica | D88: =D60+D67 -> 240 | E88: =IF(AND($B$16<$F$2,$E$16<$F$2),C8,IF($B$16<$F$2,I8,F8)) -> 0 | F88: =IF(AND($B$16<$F$2,$E$16<$F$2),D8,IF($B$16<$F$2,J8,G8)) -> -0.0025948539 | H88: =D88*(E88+F88) -> -0.62276493
B90: DESCONTO SOCIAL | J90: DESCONTO SOCIAL
D91: Qtde | E91: TUSD | F91: TE | G91: TUSD + TE | H91: R$ | J91: =SUM(H92:H93) -> -15.11
B92: Consumo até 120 KWh | D92: =D23+D25 -> 100 | E92: =IF(AND($B$16<$F$2,$E$16<$F$2),C7,IF($B$16<$F$2,I7,F7)) -> 0.347764 | F92: =IF(AND($B$16<$F$2,$E$16<$F$2),D7,IF($B$16<$F$2,J7,G7)) -> 0.31576067 | G92: =SUM(E92:F92) -> 0.66352467 | H92: =ROUND((D92*E92),2)+ROUND((D92*F92),2) -> 66.36
B93: Consumo acima 120 KWh | D93: =-D92 -> -100 | E93: =IF(AND($B$16<$F$2,$E$16<$F$2),C6,IF($B$16<$F$2,I6,F6)) -> 0.48621867 | F93: =IF(AND($B$16<$F$2,$E$16<$F$2),D6,IF($B$16<$F$2,J6,G6)) -> 0.328478 | G93: =SUM(E93:F93) -> 0.81469667 | H93: =ROUND((D93*E93),2)+ROUND((D93*F93),2) -> -81.47

Sheet Fatura B3 (GD) OK
B2: B3 | E2: Vigência das Tarifas: | F2: ='Fatura B1 (GD) OK'!F2 -> 46241 | M2: Bandeira | N2: R$/kWh | O2: ANEEL em 29/06 | Q2: TUSD FIO B
M3: VERDE | N3: 0
B4: TARIFA | C4: ='Fatura B1 (GD) OK'!C4:E4 -> TARIFA ANTIGA - REH 3508/2025 | F4: ='Fatura B1 (GD) OK'!F4 -> TARIFA NOVA - REH xxxx/2026 | I4: Tarifas Proporcionalizadas | M4: BAM | N4: =[1]BANDEIRA!$D$5 -> 0.01885 | Q4: TARIFA | R4: =C4 -> TARIFA ANTIGA - REH 3508/2025 | U4: =F4 -> TARIFA NOVA - REH xxxx/2026 | X4: Tarifas Proporcionalizadas
C5: Tusd | D5: TE | E5: TUSD + TE | F5: Tusd | G5: TE | H5: TUSD + TE | I5: Tusd | J5: TE | K5: TUSD + TE | M5: BVM1 | N5: =[1]BANDEIRA!$D$6 -> 0.04463 | R5: Tusd (R$/kWh) | U5: Tusd (R$/kWh) | X5: Tusd (R$/kWh)
B6: B3 | C6: ='TABELA DE TARIFAS ANTIGAS'!G89/1000 -> 0.46863 | D6: ='TABELA DE TARIFAS ANTIGAS'!H89/1000 -> 0.32068 | E6: =C6+D6 -> 0.78931 | F6: ='TABELA DE TARIFAS NOVAS'!G91/1000 -> 0.50632 | G6: ='TABELA DE TARIFAS NOVAS'!H91/1000 -> 0.33739 | H6: =F6+G6 -> 0.84371 | I6: =((C6*$C$14)+(F6*$D$14))/($D$14+$C$14) -> 0.502551 | J6: =((D6*$C$14)+(G6*$D$14))/($D$14+$C$14) -> 0.335719 | K6: =I6+J6 -> 0.83827 | M6: BVM2 | N6: =[1]BANDEIRA!$D$7 -> 0.07877 | Q6: =B6 -> B3 | R6: ='FIO B'!H35/1000 -> 0.20383072 | U6: ='FIO B'!K35/1000 -> 0.20915159 | X6: =((R6*$C$14)+(U6*$D$14))/($D$14+$C$14) -> 0.20861951
B7: CDE Escassez Hídrica | C7: 0.00018774721 | D7: -0.0044031307 | E7: 0.0036054084 | F7: =T11 -> 0.00018418923 | G7: =U11 -> -0.00053182975 | H7: =F7+G7 -> -0.00034764052 | I7: =((C7*$C$14)+(F7*$D$14))/($D$14+$C$14) -> 0.00018454503 | J7: =((D7*$C$14)+(G7*$D$14))/($D$14+$C$14) -> -0.00091895985 | K7: =I7+J7 -> -0.00073441482 | M7: Escassez Hídrica | N7: 0.142
B8: TE SCEE | G8: =G6*15% -> 0.0506085 | J8: =((D8*$C$14)+(G8*$D$14))/($D$14+$C$14) -> 0.04554765 | P8: CUSTO | R8: Part. TUSD (%) | S8: Part. TE (%) | T8: Tusd (R$/kWh) | U8: TE (R$/kWh)
P9: CDE CONTAS
H10: Fatura | L10: Vigência das Tarifas (troca Bandeira): | M10: =EOMONTH(B14,0)+1 -> 46266 | P10: CDE COVID | U10: 0
B11: INSTALAÇÃO | C11: 945467 | H11: =E14 -> 46267 | K11: Altere a bandeira na célula abaixo | P11: CDE ESCASSEZ HÍDRICA | T11: ='Fatura B1 (GD) OK'!T11 -> 0.00018418923 | U11: ='Fatura B1 (GD) OK'!U11 -> -0.00053182975
K12: BAM | L12: BAM
B13: Leitura Anterior | C13: Nº de dias tarifa Anterior | D13: Nº de dias tarifa Nova | E13: Leitura Atual | J13: Leitura Anterior | K13: Nº de dias tarifa Anterior | L13: Nº de dias tarifa Nova | M13: Leitura Atual
B14: 46237 | C14: =IF((F2-B14-1)<0,0,(F2-B14-1)) -> 3 | D14: =E14-F2+1 -> 27 | E14: 46267 | J14: =B14 -> 46237 | K14: =IF((M10-J14-1)<0,0,(M10-J14-1)) -> 28 | L14: =M14-M10+1 -> 2 | M14: =E14 -> 46267
B17: Perc. de Redução da Energia Injetada | E17: TUSD | F17: 1 | G17: TE | H17: 1 | M17: Documento Impressão | O17: 1025311205
B19: Descrição | C19: Unidade | D19: Quantidade | E19: Preço Unit (R$) com tributos | F19: Valor Total (R$) | G19: PIS/COFINS (R$) | H19: Base de Cálculo ICMS (R$) | I19: Alíquota ICMS (%) | J19: ICMS (R$) | K19: Preço Unit (R$) | L19: Tributos | M19: Base de Cálc (R$) | N19: Alíquota (%) | O19: Valor (R$)
R20: TUSD Fio B | S20: Receita Fio B
B21: TUSD - Consumo | C21: kWh | D21: 2282 | E21: =(ROUND(D21*K21,2)+ROUND(G21,2)+ROUND(J21,2))/ROUND(D21,4) -> 0.64529798 | F21: =ROUND(D21*E21,2) -> 1472.57 | G21: =((D21*K21)/(1-$N$21-$N$23))*($N$21+$N$23) -> 75.411786 | H21: =((D21*K21)/(1-$N$21-$N$23)/(1-$I$21)) -> 1472.5701 | I21: 0.17 | J21: =(H21*$I$21) -> 250.33691 | K21: =IF(AND($B$14<$F$2,$E$14<$F$2),C6,IF($B$14<$F$2,I6,F6)) -> 0.502551 | L21: PIS | M21: =D70 -> 2084.5678 | N21: 0.011 | O21: =ROUND(M21*N21,2) -> 22.93 | R21: =IF(AND($B$14<$F$2,$E$14<$F$2),R6,IF($B$14<$F$2,X6,U6)) -> 0.20861951 | S21: =D21*R21 -> 476.06971 | T21: não está considerando energia injetada
B22: TE - Consumo | C22: kWh | D22: =D21 -> 2282 | E22: =(ROUND(D22*K22,2)+ROUND(G22,2)+ROUND(J22,2))/ROUND(D22,4) -> 0.431078 | F22: =ROUND(D22*E22,2) -> 983.72 | G22: =((D22*K22)/(1-$N$21-$N$23))*($N$21+$N$23) -> 50.377314 | H22: =ROUND((D22*K22)/(1-$N$21-$N$23)/(1-$I$21),8) -> 983.72057 | J22: =ROUND(H22*$I$21,2) -> 167.23 | K22: =IF(AND($B$14<$F$2,$E$14<$F$2),D6,IF($B$14<$F$2,J6,G6)) -> 0.335719 | L22: PIS Inj | M22: =D71 -> -357.17787 | N22: =N21 -> 0.011 | O22: =ROUND(M22*N22,2) -> -3.93
B23: Adicional BAM | C23: kWh | D23: =IF($K$12=M4,($D$21*($K$14)/($K$14+$L$14)),0)+IF($L$12=M4,($D$21*($L$14)/($K$14+$L$14)),0) -> 2282 | E23: =IFERROR((ROUND(D23*K23,2)+ROUND(G23,2)+ROUND(J23,2))/ROUND(D23,4), 0) -> 0.024206836 | F23: =ROUND(D23*E23,2) -> 55.24 | G23: =((D23*K23)/(1-$N$21-$N$23))*($N$21+$N$23) -> 2.8285929 | H23: =ROUND((D23*K23)/(1-$N$21-$N$23)/(1-$I$21),8) -> 55.234088 | J23: =ROUND(H23*$I$21,2) -> 9.39 | K23: =N4 -> 0.01885 | L23: COFINS | M23: =M21 -> 2084.5678 | N23: 0.0507 | O23: =ROUND(M23*N23,2) -> 105.69
B24: Adicional BVM1 | C24: kWh | D24: =IF($K$12=M5,($D$21*($K$14)/($K$14+$L$14)),0)+IF($L$12=M5,($D$21*($L$14)/($K$14+$L$14)),0) -> 0 | E24: =IFERROR((ROUND(D24*K24,2)+ROUND(G24,2)+ROUND(J24,2))/ROUND(D24,4), 0) -> 0 | F24: =ROUND(D24*E24,2) -> 0 | G24: =((D24*K24)/(1-$N$21-$N$23))*($N$21+$N$23) -> 0 | H24: =ROUND((D24*K24)/(1-$N$21-$N$23)/(1-$I$21),8) -> 0 | J24: =ROUND(H24*$I$21,2) -> 0 | K24: =N5 -> 0.04463 | L24: COFINS Inj | M24: =M22 -> -357.17787 | N24: =N23 -> 0.0507 | O24: =ROUND(M24*N24,2) -> -18.11
B25: Adicional BVM2 | C25: kWh | D25: =IF($K$12=M6,($D$21*($K$14)/($K$14+$L$14)),0)+IF($L$12=M6,($D$21*($L$14)/($K$14+$L$14)),0) -> 0 | E25: =IFERROR((ROUND(D25*K25,2)+ROUND(G25,2)+ROUND(J25,2))/ROUND(D25,4), 0) -> 0 | F25: =ROUND(D25*E25,2) -> 0 | G25: =((D25*K25)/(1-$N$21-$N$23))*($N$21+$N$23) -> 0 | H25: =ROUND((D25*K25)/(1-$N$21-$N$23)/(1-$I$21),8) -> 0 | J25: =ROUND(H25*$I$21,2) -> 0 | K25: =N6 -> 0.07877
B26: Adicional EH | C26: kWh | D26: =IF($K$12=M7,($D$21*($K$14)/($K$14+$L$14)),0)+IF($L$12=M7,($D$21*($L$14)/($K$14+$L$14)),0) -> 0 | E26: =IFERROR((ROUND(D26*K26,2)+ROUND(G26,2)+ROUND(J26,2))/ROUND(D26,4), 0) -> 0 | F26: =ROUND(D26*E26,2) -> 0 | G26: =((D26*K26)/(1-$N$21-$N$23))*($N$21+$N$23) -> 0 | H26: =ROUND((D26*K26)/(1-$N$21-$N$23)/(1-$I$21),8) -> 0 | J26: =ROUND(H26*$I$21,2) -> 0 | K26: =N7 -> 0.142
B28: TUSD - Consumo inj | C28: kWh | D28: -391 | E28: =IFERROR((ROUND(D28*K28,2)+ROUND(G28,2)+ROUND(J28,2))/ROUND(D28,4),0) -> 0.53560102 | F28: =ROUND(D28*E28,2) -> -209.42 | G28: =((D28*K28)/(1-$N$22-$N$24))*($N$22+$N$24) -> -12.921126 | H28: 0 | I28: 0.12 | J28: =H28*$I$21 -> 0 | K28: =K21 -> 0.502551
B29: TE - Consumo inj | C29: kWh | D29: =D28 -> -391 | E29: =IFERROR((ROUND(D29*K29,2)+ROUND(G29,2)+ROUND(J29,2))/ROUND(D29,4),0) -> 0.43107417 | F29: =ROUND(D29*E29,2) -> -168.55 | G29: =((D29*K29)/(1-$N$22-$N$24))*($N$22+$N$24) -> -8.6316958 | H29: =ROUND((D29*K29)/(1-$N$22-$N$24)/(1-$I$21),8) -> -168.5516 | I29: =I21 -> 0.17 | J29: =H29*$I$21 -> -28.653771 | K29: =K22 -> 0.335719
B30: Adicional BAM inj | C30: kWh | D30: =IF($K$12=M4,($D$28*($K$14)/($K$14+$L$14)),0)+IF($L$12=M4,($D$28*($L$14)/($K$14+$L$14)),0) -> -391 | E30: =IFERROR((ROUND(D30*K30,2)+ROUND(G30,2)+ROUND(J30,2))/ROUND(D30,4),0) -> 0.024194373 | F30: =ROUND(D30*E30,2) -> -9.46 | G30: =((D30*K30)/(1-$N$22-$N$24))*($N$22+$N$24) -> -0.48465373 | H30: =(D30*K30)/(1-$N$22-$N$24)/(1-$I$21) -> -9.4638599 | J30: =H30*$I$21 -> -1.6088562 | K30: =N4 -> 0.01885
B31: Adicional BVM1 inj | C31: kWh | D31: =IF($K$12=M5,($D$28*($K$14)/($K$14+$L$14)),0)+IF($L$12=M5,($D$28*($L$14)/($K$14+$L$14)),0) -> 0 | E31: =IFERROR((ROUND(D31*K31,2)+ROUND(G31,2)+ROUND(J31,2))/ROUND(D31,4),0) -> 0 | F31: =ROUND(D31*E31,2) -> 0 | G31: =((D31*K31)/(1-$N$22-$N$24))*($N$22+$N$24) -> 0 | H31: =(D31*K31)/(1-$N$22-$N$24)/(1-$I$21) -> 0 | J31: =H31*$I$21 -> 0 | K31: =N5 -> 0.04463
B32: Adicional BVM2 inj | C32: kWh | D32: =IF($K$12=M6,($D$28*($K$14)/($K$14+$L$14)),0)+IF($L$12=M6,($D$28*($L$14)/($K$14+$L$14)),0) -> 0 | E32: =IFERROR((ROUND(D32*K32,2)+ROUND(G32,2)+ROUND(J32,2))/ROUND(D32,4),0) -> 0 | F32: =ROUND(D32*E32,2) -> 0 | G32: =((D32*K32)/(1-$N$22-$N$24))*($N$22+$N$24) -> 0 | H32: =(D32*K32)/(1-$N$22-$N$24)/(1-$I$21) -> 0 | J32: =H32*$I$21 -> 0 | K32: =N6 -> 0.07877
B33: Adicional EH inj | C33: kWh | D33: =IF($K$12=M7,($D$28*($K$14)/($K$14+$L$14)),0)+IF($L$12=M7,($D$28*($L$14)/($K$14+$L$14)),0) -> 0 | E33: =IFERROR((ROUND(D33*K33,2)+ROUND(G33,2)+ROUND(J33,2))/ROUND(D33,4),0) -> 0 | F33: =ROUND(D33*E33,2) -> 0 | G33: =((D33*K33)/(1-$N$22-$N$24))*($N$22+$N$24) -> 0 | H33: =(D33*K33)/(1-$N$22-$N$24)/(1-$I$21) -> 0 | J33: =H33*$I$21 -> 0 | K33: =N7 -> 0.142
B35: Multas
B36: Juros
B37: Doações
B38: CIP | F38: 61.73
B41: TOTAL | F41: =SUM(F21:F40) -> 2185.83 | G41: =SUM(G21:G40) -> 106.58022 | H41: =SUM(H21:H40) -> 2333.5093 | J41: =SUM(J21:J40) -> 396.69429
B43: Informativo Escassez Hídrica | D43: 50 | E43: 0.00018418923 | F43: -0.00053182975 | H43: -0.017382026
B45: Fatura B1 Residencial
D46: Qtde | E46: TUSD | F46: TE | G46: TUSD + TE | H46: R$
B47: Fornecimento de Energia Elétrica | H47: =SUM(H49:H65)+SUM(H70:H75) -> 2124.0871
B49: Energia Fornecida | D49: =D21 -> 2282 | E49: =IF(AND($B$14<$F$2,$E$14<$F$2),C6,IF($B$14<$F$2,I6,F6)) -> 0.502551 | F49: =IF(AND($B$14<$F$2,$E$14<$F$2),D6,IF($B$14<$F$2,J6,G6)) -> 0.335719 | G49: =E49+F49 -> 0.83827 | H49: =ROUND((D49*E49),2)+ROUND((D49*F49),2) -> 1912.93
B51: Adicional BAM | D51: =IF($K$12=M4,(D49*(K14)/(K14+L14)),0)+IF($L$12=M4,(D49*(L14)/(K14+L14)),0) -> 2282 | F51: =N4 -> 0.01885 | H51: =ROUND(D51*(E51+F51),2) -> 43.02
B52: Adicional BVM 1 | D52: =IF($K$12=M5,(D49*(K14)/(K14+L14)),0)+IF($L$12=M5,(D49*(L14)/(K14+L14)),0) -> 0 | F52: =N5 -> 0.04463 | H52: =ROUND(D52*(E52+F52),2) -> 0
B53: Adicional BVM 2 | D53: =IF($K$12=M6,(D49*(K14)/(K14+L14)),0)+IF($L$12=M6,(D49*(L14)/(K14+L14)),0) -> 0 | F53: =N6 -> 0.07877 | H53: =ROUND(D53*(E53+F53),2) -> 0
B54: Adicional Escassez Hídrica | D54: =IF($K$12=M8,(D49*(K14)/(K14+L14)),0)+IF($L$12=M8,(D49*(L14)/(K14+L14)),0) -> 0 | F54: =N8 -> 0 | H54: =ROUND(D54*(E54+F54),2) -> 0
B56: Energia Injetada | D56: =D28 -> -391 | E56: =E49*F17 -> 0.502551 | F56: =F49 -> 0.335719 | G56: =E56+F56 -> 0.83827 | H56: =ROUND((D56*E56),2)+ROUND((D56*F56),2) -> -327.77
B58: Adicional BAM | D58: =IF($K$12=M4,(D56*(K14)/(K14+L14)),0)+IF($L$12=M4,(D56*(L14)/(K14+L14)),0) -> -391 | F58: =F51 -> 0.01885 | H58: =ROUND(D58*(E58+F58),2) -> -7.37
B59: Adicional BVM 1 | D59: =IF($K$12=M5,(D56*(K14)/(K14+L14)),0)+IF($L$12=M5,(D56*(L14)/(K14+L14)),0) -> 0 | F59: =F52 -> 0.04463 | H59: =ROUND(D59*(E59+F59),2) -> 0
B60: Adicional BVM 2 | D60: =IF($K$12=M6,(D56*(K14)/(K14+L14)),0)+IF($L$12=M6,(D56*(L14)/(K14+L14)),0) -> 0 | F60: =F53 -> 0.07877 | H60: =ROUND(D60*(E60+F60),2) -> 0
B61: Adicional Escassez Hídrica | D61: =IF($K$12=M8,(D56*(K14)/(K14+L14)),0)+IF($L$12=M8,(D56*(L14)/(K14+L14)),0) -> 0 | F61: =F54 -> 0 | H61: =ROUND(D61*(E61+F61),2) -> 0
H67: =SUM(H49:H66) -> 1620.81
D69: Base de Cálculo
B70: PIS | D70: =(H49+H51+H52+H53+H54)/(1-E70-E72) -> 2084.5678 | E70: =N21 -> 0.011 | H70: =D70*E70 -> 22.930246
B71: PIS Eneg Inj | D71: =(H56+H58+H59+H60+H61+H63+H65)/(1-E70-E72) -> -357.17787 | E71: =E70 -> 0.011 | H71: =D71*E71 -> -3.9289566
B72: COFINS | D72: =D70 -> 2084.5678 | E72: =N23 -> 0.0507 | H72: =D72*E72 -> 105.68759
B73: COFINS Eneg Inj | D73: =D71 -> -357.17787 | E73: =E72 -> 0.0507 | H73: =D73*E73 -> -18.108918
B74: ICMS | D74: =D70/(1-E74) -> 2511.5275 | E74: 0.17 | H74: =D74*E74 -> 426.95968
B75: ICMS Eneg Inj | D75: =((D56*F56)+(H58+H59+H60+H61)+(D63*F63)+(D65*F65))/(1-E71-E73)/(1-E75) -> -178.01501 | E75: =E74 -> 0.17 | H75: =D75*E75 -> -30.262551
B77: Informativo Escassez Hídrica | D77: =D49+D56 -> 1891 | E77: =IF(AND($B$14<$F$2,$E$14<$F$2),C7,IF($B$14<$F$2,I7,F7)) -> 0.00018454503 | F77: =IF(AND($B$14<$F$2,$E$14<$F$2),D7,IF($B$14<$F$2,J7,G7)) -> -0.00091895985 | H77: =D77*(E77+F77) -> -1.3887784

Sheet Fatura B2 (GD) OK
B2: B2 | E2: Vigência das Tarifas: | F2: ='Fatura B1 (GD) OK'!F2 -> 46241 | M2: Bandeira | N2: R$/kWh | O2: ANEEL em 29/06 | Q2: TUSD FIO B
M3: VERDE | N3: 0
B4: TARIFA | C4: ='Fatura B1 (GD) OK'!C4:E4 -> TARIFA ANTIGA - REH 3508/2025 | F4: ='Fatura B1 (GD) OK'!F4 -> TARIFA NOVA - REH xxxx/2026 | I4: Tarifas Proporcionalizadas | M4: BAM | N4: ='[3]Fatura B1 (Res) OK'!$N$4 -> 0.01885 | Q4: TARIFA | R4: =C4 -> TARIFA ANTIGA - REH 3508/2025 | U4: =F4 -> TARIFA NOVA - REH xxxx/2026 | X4: Tarifas Proporcionalizadas
C5: Tusd | D5: TE | E5: TUSD + TE | F5: Tusd | G5: TE | H5: TUSD + TE | I5: Tusd | J5: TE | K5: TUSD + TE | M5: BVM1 | N5: ='[3]Fatura B1 (Res) OK'!$N$5 -> 0.04463 | R5: Tusd (R$/kWh) | U5: Tusd (R$/kWh) | X5: Tusd (R$/kWh)
B6: B2 | C6: ='TABELA DE TARIFAS ANTIGAS'!G77/1000 -> 0.46863 | D6: ='TABELA DE TARIFAS ANTIGAS'!H77/1000 -> 0.32068 | E6: =C6+D6 -> 0.78931 | F6: ='TABELA DE TARIFAS NOVAS'!G79/1000 -> 0.50632 | G6: ='TABELA DE TARIFAS NOVAS'!H79/1000 -> 0.33739 | H6: =F6+G6 -> 0.84371 | I6: =((C6*$C$14)+(F6*$D$14))/($D$14+$C$14) -> 0.48621867 | J6: =((D6*$C$14)+(G6*$D$14))/($D$14+$C$14) -> 0.328478 | K6: =I6+J6 -> 0.81469667 | M6: BVM2 | N6: ='[3]Fatura B1 (Res) OK'!$N$6 -> 0.07877 | Q6: =B6 -> B2 | R6: ='FIO B'!H20/1000 -> 0.20383072 | U6: ='FIO B'!K20/1000 -> 0.20915159 | X6: =((R6*$C$14)+(U6*$D$14))/($D$14+$C$14) -> 0.20631379
B7: CDE Escassez Hídrica | C7: 0.00018774721 | D7: -0.0044031307 | E7: 0.0036054084 | F7: =T11 -> 0.00018418923 | G7: =U11 -> -0.00053182975 | H7: =F7+G7 -> -0.00034764052 | I7: =((C7*$C$14)+(F7*$D$14))/($D$14+$C$14) -> 0.00018608682 | J7: =((D7*$C$14)+(G7*$D$14))/($D$14+$C$14) -> -0.0025965236 | K7: =I7+J7 -> -0.0024104368 | M7: Escassez Hídrica | N7: 0.142
B8: TE SCEE | G8: =G6*15% -> 0.0506085 | J8: =((D8*$C$14)+(G8*$D$14))/($D$14+$C$14) -> 0.0236173 | P8: CUSTO | R8: Part. TUSD (%) | S8: Part. TE (%) | T8: Tusd (R$/kWh) | U8: TE (R$/kWh)
P9: CDE CONTAS
H10: Fatura | L10: Vigência das Tarifas (troca Bandeira): | M10: =EOMONTH(B14,0)+1 -> 46235 | P10: CDE COVID | U10: 0
B11: INSTALAÇÃO | C11: 1321770 | H11: =E14 -> 46254 | K11: Altere a bandeira na célula abaixo | P11: CDE ESCASSEZ HÍDRICA | T11: ='Fatura B1 (GD) OK'!T11 -> 0.00018418923 | U11: ='Fatura B1 (GD) OK'!U11 -> -0.00053182975
K12: ='Fatura B1 (GD) OK'!K12 -> BAM | L12: ='Fatura B1 (GD) OK'!L12 -> BAM
B13: Leitura Anterior | C13: Nº de dias tarifa Anterior | D13: Nº de dias tarifa Nova | E13: Leitura Atual | J13: Leitura Anterior | K13: Nº de dias tarifa Anterior | L13: Nº de dias tarifa Nova | M13: Leitura Atual
B14: 46224 | C14: =IF((F2-B14-1)<0,0,(F2-B14-1)) -> 16 | D14: =E14-F2+1 -> 14 | E14: 46254 | J14: =B14 -> 46224 | K14: =IF((M10-J14-1)<0,0,(M10-J14-1)) -> 10 | L14: =M14-M10+1 -> 20 | M14: =E14 -> 46254
B17: Perc. de Redução da Energia Injetada | E17: TUSD | F17: 1 | G17: TE | H17: 1 | M17: Documento Impressão | O17: 1025311193
B19: Descrição | C19: Unidade | D19: Quantidade | E19: Preço Unit (R$) com tributos | F19: Valor Total (R$) | G19: PIS/COFINS (R$) | H19: Base de Cálculo ICMS (R$) | I19: Alíquota ICMS (%) | J19: ICMS (R$) | K19: Preço Unit (R$) | L19: Tributos | M19: Base de Cálc (R$) | N19: Alíquota (%) | O19: Valor (R$)
R20: TUSD Fio B | S20: Receita Fio B
B21: TUSD - Consumo | C21: kWh | D21: 715 | E21: =(ROUND(D21*K21,2)+ROUND(G21,2)+ROUND(J21,2))/ROUND(D21,4) -> 0.62433566 | F21: =ROUND(D21*E21,2) -> 446.4 | G21: =((D21*K21)/(1-$N$21-$N$23))*($N$21+$N$23) -> 22.860257 | H21: =(IF($I$21=12%,(D21*K21)/(1-$N$21-$N$23)/(1-$C$50)/$F$50*$C$50,(D21*K21)/(1-$N$21-$N$23)/(1-$I$21))) -> 446.3935 | I21: 0.17 | J21: =(H21*$I$21) -> 75.886895 | K21: =IF(AND($B$14<$F$2,$E$14<$F$2),C6,IF($B$14<$F$2,I6,F6)) -> 0.48621867 | L21: PIS | M21: =D82 -> 635.18065 | N21: ='Fatura B1 (GD) OK'!N21 -> 0.011 | O21: =ROUND(M21*N21,2) -> 6.99 | R21: =IF(AND($B$14<$F$2,$E$14<$F$2),R6,IF($B$14<$F$2,X6,U6)) -> 0.20631379 | S21: =D21*R21 -> 147.51436 | T21: não está considerando energia injetada
B22: TE - Consumo | C22: kWh | D22: =D21 -> 715 | E22: =(ROUND(D22*K22,2)+ROUND(G22,2)+ROUND(J22,2))/ROUND(D22,4) -> 0.42177622 | F22: =ROUND(D22*E22,2) -> 301.57 | G22: =((D22*K22)/(1-$N$21-$N$23))*($N$21+$N$23) -> 15.443857 | H22: =(IF($I$21=12%,(D22*K22)/(1-$N$21-$N$23)/(1-$C$50)/$F$50*$C$50,(D22*K22)/(1-$N$21-$N$23)/(1-$I$21))) -> 301.57304 | J22: =ROUND(H22*$I$21,2) -> 51.27 | K22: =IF(AND($B$14<$F$2,$E$14<$F$2),D6,IF($B$14<$F$2,J6,G6)) -> 0.328478 | L22: PIS Inj | M22: =D83 -> -162.57061 | N22: =N21 -> 0.011 | O22: =ROUND(M22*N22,2) -> -1.79
B23: Adicional BAM | C23: kWh | D23: =IF($K$12=M4,($D$21*($K$14)/($K$14+$L$14)),0)+IF($L$12=M4,($D$21*($L$14)/($K$14+$L$14)),0) -> 715 | E23: =IFERROR((ROUND(D23*K23,2)+ROUND(G23,2)+ROUND(J23,2))/ROUND(D23,4), 0) -> 0.02420979 | F23: =ROUND(D23*E23,2) -> 17.31 | G23: =((D23*K23)/(1-$N$21-$N$23))*($N$21+$N$23) -> 0.88625938 | H23: =(IF($I$21=12%,(D23*K23)/(1-$N$21-$N$23)/(1-$C$50)/$F$50*$C$50,(D23*K23)/(1-$N$21-$N$23)/(1-$I$21))) -> 17.306035 | J23: =ROUND(H23*$I$21,2) -> 2.94 | K23: =N4 -> 0.01885 | L23: COFINS | M23: =M21 -> 635.18065 | N23: ='Fatura B1 (GD) OK'!N23 -> 0.0507 | O23: =ROUND(M23*N23,2) -> 32.2
B24: Adicional BVM1 | C24: kWh | D24: =IF($K$12=M5,($D$21*($K$14)/($K$14+$L$14)),0)+IF($L$12=M5,($D$21*($L$14)/($K$14+$L$14)),0) -> 0 | E24: =IFERROR((ROUND(D24*K24,2)+ROUND(G24,2)+ROUND(J24,2))/ROUND(D24,4), 0) -> 0 | F24: =ROUND(D24*E24,2) -> 0 | G24: =((D24*K24)/(1-$N$21-$N$23))*($N$21+$N$23) -> 0 | H24: =(IF($I$21=12%,(D24*K24)/(1-$N$21-$N$23)/(1-$C$50)/$F$50*$C$50,(D24*K24)/(1-$N$21-$N$23)/(1-$I$21))) -> 0 | J24: =ROUND(H24*$I$21,2) -> 0 | K24: =N5 -> 0.04463 | L24: COFINS Inj | M24: =M22 -> -162.57061 | N24: =N23 -> 0.0507 | O24: =ROUND(M24*N24,2) -> -8.24
B25: Adicional BVM2 | C25: kWh | D25: =IF($K$12=M6,($D$21*($K$14)/($K$14+$L$14)),0)+IF($L$12=M6,($D$21*($L$14)/($K$14+$L$14)),0) -> 0 | E25: =IFERROR((ROUND(D25*K25,2)+ROUND(G25,2)+ROUND(J25,2))/ROUND(D25,4), 0) -> 0 | F25: =ROUND(D25*E25,2) -> 0 | G25: =((D25*K25)/(1-$N$21-$N$23))*($N$21+$N$23) -> 0 | H25: =(IF($I$21=12%,(D25*K25)/(1-$N$21-$N$23)/(1-$C$50)/$F$50*$C$50,(D25*K25)/(1-$N$21-$N$23)/(1-$I$21))) -> 0 | J25: =ROUND(H25*$I$21,2) -> 0 | K25: =N6 -> 0.07877
B26: Adicional EH | C26: kWh | D26: =IF($K$12=M7,($D$21*($K$14)/($K$14+$L$14)),0)+IF($L$12=M7,($D$21*($L$14)/($K$14+$L$14)),0) -> 0 | E26: =IFERROR((ROUND(D26*K26,2)+ROUND(G26,2)+ROUND(J26,2))/ROUND(D26,4), 0) -> 0 | F26: =ROUND(D26*E26,2) -> 0 | G26: =((D26*K26)/(1-$N$21-$N$23))*($N$21+$N$23) -> 0 | H26: =(IF($I$21=12%,(D26*K26)/(1-$N$21-$N$23)/(1-$C$50)/$F$50*$C$50,(D26*K26)/(1-$N$21-$N$23)/(1-$I$21))) -> 0 | J26: =ROUND(H26*$I$21,2) -> 0 | K26: =N7 -> 0.142
B28: TUSD - Consumo inj | C28: kWh | D28: -183 | E28: =IFERROR((ROUND(D28*K28,2)+ROUND(G28,2)+ROUND(J28,2))/ROUND(D28,4), 0) -> 0.51819672 | F28: =ROUND(D28*E28,2) -> -94.83 | G28: =((D28*K28)/(1-$N$22-$N$24))*($N$22+$N$24) -> -5.850947 | H28: 0 | I28: 0 | J28: =H28*$I$21 -> 0 | K28: =K21 -> 0.48621867
B29: TE - Consumo inj | C29: kWh | D29: =D28 -> -183 | E29: =IFERROR((ROUND(D29*K29,2)+ROUND(G29,2)+ROUND(J29,2))/ROUND(D29,4), 0) -> 0.42174863 | F29: =ROUND(D29*E29,2) -> -77.18 | G29: =((D29*K29)/(1-$N$22-$N$24))*($N$22+$N$24) -> -3.9527635 | H29: =(IF($I$29=12%,(D29*K29)/(1-$N$22-$N$24)/(1-$C$50)/$F$50*$C$50,(D29*K29)/(1-$N$22-$N$24)/(1-$I$29))) -> -77.185828 | I29: =I21 -> 0.17 | J29: =H29*$I$21 -> -13.121591 | K29: =K22 -> 0.328478
B30: Adicional BAM Inj | C30: kWh | D30: =IF($K$12=M4,($D$28*($K$14)/($K$14+$L$14)),0)+IF($L$12=M4,($D$28*($L$14)/($K$14+$L$14)),0) -> -183 | E30: =IFERROR((ROUND(D30*K30,2)+ROUND(G30,2)+ROUND(J30,2))/ROUND(D30,4), 0) -> 0.02420765 | F30: =ROUND(D30*E30,2) -> -4.43 | G30: =((D30*K30)/(1-$N$22-$N$24))*($N$22+$N$24) -> -0.22683282 | H30: =(IF($I$29=12%,(D30*K30)/(1-$N$22-$N$24)/(1-$C$50)/$F$50*$C$50,(D30*K30)/(1-$N$22-$N$24)/(1-$I$29))) -> -4.4293769 | J30: =H30*$I$21 -> -0.75299407 | K30: =N4 -> 0.01885
B31: Adicional BVM1 Inj | C31: kWh | D31: =IF($K$12=M5,($D$28*($K$14)/($K$14+$L$14)),0)+IF($L$12=M5,($D$28*($L$14)/($K$14+$L$14)),0) -> 0 | E31: =IFERROR((ROUND(D31*K31,2)+ROUND(G31,2)+ROUND(J31,2))/ROUND(D31,4), 0) -> 0 | F31: =ROUND(D31*E31,2) -> 0 | G31: =((D31*K31)/(1-$N$22-$N$24))*($N$22+$N$24) -> 0 | H31: =(IF($I$29=12%,(D31*K31)/(1-$N$22-$N$24)/(1-$C$50)/$F$50*$C$50,(D31*K31)/(1-$N$22-$N$24)/(1-$I$29))) -> 0 | J31: =H31*$I$21 -> 0 | K31: =N5 -> 0.04463
B32: Adicional BVM2 Inj | C32: kWh | D32: =IF($K$12=M6,($D$28*($K$14)/($K$14+$L$14)),0)+IF($L$12=M6,($D$28*($L$14)/($K$14+$L$14)),0) -> 0 | E32: =IFERROR((ROUND(D32*K32,2)+ROUND(G32,2)+ROUND(J32,2))/ROUND(D32,4), 0) -> 0 | F32: =ROUND(D32*E32,2) -> 0 | G32: =((D32*K32)/(1-$N$22-$N$24))*($N$22+$N$24) -> 0 | H32: =(IF($I$29=12%,(D32*K32)/(1-$N$22-$N$24)/(1-$C$50)/$F$50*$C$50,(D32*K32)/(1-$N$22-$N$24)/(1-$I$29))) -> 0 | J32: =H32*$I$21 -> 0 | K32: =N6 -> 0.07877
B33: Adicional EH Inj | C33: kWh | D33: =IF($K$12=M7,($D$28*($K$14)/($K$14+$L$14)),0)+IF($L$12=M7,($D$28*($L$14)/($K$14+$L$14)),0) -> 0 | E33: =IFERROR((ROUND(D33*K33,2)+ROUND(G33,2)+ROUND(J33,2))/ROUND(D33,4), 0) -> 0 | F33: =ROUND(D33*E33,2) -> 0 | G33: =((D33*K33)/(1-$N$22-$N$24))*($N$22+$N$24) -> 0 | H33: =(IF($I$29=12%,(D33*K33)/(1-$N$22-$N$24)/(1-$C$50)/$F$50*$C$50,(D33*K33)/(1-$N$22-$N$24)/(1-$I$29))) -> 0 | J33: =H33*$I$21 -> 0 | K33: =N7 -> 0.142
B35: Juros
B36: Multas
B37: Doações | F37: -6.69
B38: CIP
B42: TOTAL | F42: =SUM(F21:F41) -> 582.15 | G42: =SUM(G21:G41) -> 29.159831 | H42: =SUM(H21:H41) -> 683.65737 | J42: =SUM(J21:J41) -> 116.22231
B44: Informativo Escassez | C44: =D21+D28 -> 532 | D44: =IF(AND($B$14<$F$2,$E$14<$F$2),C7,IF($B$14<$F$2,I7,F7)) -> 0.00018608682 | E44: =IF(AND($B$14<$F$2,$E$14<$F$2),D7,IF($B$14<$F$2,J7,G7)) -> -0.0025965236 | F44: =C44*(D44+E44) -> -1.2823524
B46: Se for base reduzida: (célula I18 = 12%)
D47: Com tributos
B48: PIS | C48: =N21 -> 0.011 | D48: =((D21*K21)+(D22*K22)+(D23*K23)+(D24*K24)+(D25*K25)+(D26*K26))/(1-$N$21-$N$23) -> 635.17624 | E48: x | F48: =C48 -> 0.011 | G48: =D48*F48 -> 6.9869386
B49: COFINS | C49: =N23 -> 0.0507 | D49: =D48 -> 635.17624 | E49: x | F49: =C49 -> 0.0507 | G49: =D49*F49 -> 32.203435
A50: Rural c/ incrição | B50: ICMS | C50: 0.04 | D50: =H50/F50*C50 -> 220.54731 | E50: x | F50: 0.12 | G50: =D50*F50 -> 26.465677 | H50: =((D21*K21)+(D22*K22)+(D23*K23)+(D24*K24)+(D25*K25)+(D26*K26))/(1-F48-F49)/(1-(C50)) -> 661.64192
E51: =(O40)/(1-C48-C49-C50) -> 0
C52: Base de cálculo reduzida = | D52: Importe
D53: 12% x 4%
B57: Fatura B2
D58: Qtde | E58: TUSD | F58: TE | G58: TUSD + TE | H58: R$
B59: Fornecimento de Energia Elétrica | H59: =SUM(H61:H77)+SUM(H82:H87) -> 588.8326
B61: Energia Fornecida | D61: =D21 -> 715 | E61: =IF(AND($B$14<$F$2,$E$14<$F$2),C6,IF($B$14<$F$2,I6,F6)) -> 0.48621867 | F61: =IF(AND($B$14<$F$2,$E$14<$F$2),D6,IF($B$14<$F$2,J6,G6)) -> 0.328478 | G61: =E61+F61 -> 0.81469667 | H61: =ROUND((D61*E61),2)+ROUND((D61*F61),2) -> 582.51
B63: Adicional BAM | D63: =IF($K$12=M4,(D61*(K14)/(K14+L14)),0)+IF($L$12=M4,(D61*(L14)/(K14+L14)),0) -> 715 | F63: =N4 -> 0.01885 | H63: =ROUND(D63*(E63+F63),2) -> 13.48
B64: Adicional BVM 1 | D64: =IF($K$12=M5,(D61*(K14)/(K14+L14)),0)+IF($L$12=M5,(D61*(L14)/(K14+L14)),0) -> 0 | F64: =N5 -> 0.04463 | H64: =ROUND(D64*(E64+F64),2) -> 0
B65: Adicional BVM 2 | D65: =IF($K$12=M6,(D61*(K14)/(K14+L14)),0)+IF($L$12=M6,(D61*(L14)/(K14+L14)),0) -> 0 | F65: =N6 -> 0.07877 | H65: =ROUND(D65*(E65+F65),2) -> 0
B66: Adicional Escassez Hídrica | D66: =IF($K$12=M7,(D61*(K14)/(K14+L14)),0)+IF($L$12=M7,(D61*(L14)/(K14+L14)),0) -> 0 | F66: =N7 -> 0.142 | H66: =ROUND(D66*(E66+F66),2) -> 0
B68: Energia Injetada | D68: =D28 -> -183 | E68: =E61*F17 -> 0.48621867 | F68: =F61 -> 0.328478 | G68: =E68+F68 -> 0.81469667 | H68: =ROUND((D68*E68),2)+ROUND((D68*F68),2) -> -149.09
B70: Adicional BAM | D70: =IF($K$12=M4,(D68*(K14)/(K14+L14)),0)+IF($L$12=M4,(D68*(L14)/(K14+L14)),0) -> -183 | F70: =F63 -> 0.01885 | H70: =ROUND(D70*(E70+F70),2) -> -3.45
B71: Adicional BVM 1 | D71: =IF($K$12=M5,(D68*(K14)/(K14+L14)),0)+IF($L$12=M5,(D68*(L14)/(K14+L14)),0) -> 0 | F71: =F64 -> 0.04463 | H71: =ROUND(D71*(E71+F71),2) -> 0
B72: Adicional BVM 2 | D72: =IF($K$12=M6,(D68*(K14)/(K14+L14)),0)+IF($L$12=M6,(D68*(L14)/(K14+L14)),0) -> 0 | F72: =F65 -> 0.07877 | H72: =ROUND(D72*(E72+F72),2) -> 0
B73: Adicional Escassez Hídrica | D73: =IF($K$12=M7,(D68*(K14)/(K14+L14)),0)+IF($L$12=M7,(D68*(L14)/(K14+L14)),0) -> 0 | F73: =F66 -> 0.142 | H73: =ROUND(D73*(E73+F73),2) -> 0
H79: =SUM(H61:H78) -> 443.45
D81: Base de Cálculo
B82: PIS | D82: =(H61+H63+H64+H65+H66)/(1-E82-E84) -> 635.18065 | E82: =N21 -> 0.011 | H82: =D82*E82 -> 6.9869871
B83: PIS Eneg Inj | D83: =(H68+H70+H71+H72+H73+H75+H77)/(1-E82-E84) -> -162.57061 | E83: =E82 -> 0.011 | H83: =D83*E83 -> -1.7882767
B84: COFINS | D84: =D82 -> 635.18065 | E84: =N23 -> 0.0507 | H84: =D84*E84 -> 32.203659
B85: COFINS Eneg Inj | D85: =D83 -> -162.57061 | E85: =E84 -> 0.0507 | H85: =D85*E85 -> -8.2423297
B86: ICMS | D86: =D82/(1-E86) -> 765.27789 | E86: 0.17 | H86: =D86*E86 -> 130.09724
B87: ICMS Eneg Inj | D87: =((D68*F68)+(H70+H71+H72+H73)+(D75*F75)+(D77*F77))/(1-E83-E85)/(1-E87) -> -81.615783 | E87: =E86 -> 0.17 | H87: =D87*E87 -> -13.874683
B89: Informativo Escassez Hídrica | D89: =D61+D68 -> 532 | E89: =IF(AND($B$14<$F$2,$E$14<$F$2),C7,IF($B$14<$F$2,I7,F7)) -> 0.00018608682 | F89: =IF(AND($B$14<$F$2,$E$14<$F$2),D7,IF($B$14<$F$2,J7,G7)) -> -0.0025965236 | H89: =D89*(E89+F89) -> -1.2823524

Sheet Fatura B2 IRRIG (GD) OK
B2: B2 | E2: Vigência das Tarifas: | F2: ='Fatura B1 (GD) OK'!F2 -> 46241 | M2: Bandeira | N2: R$/kWh | O2: ANEEL em 29/06 | Q2: TUSD FIO B
M3: VERDE | N3: 0
B4: TARIFA | C4: ='Fatura B1 (GD) OK'!C4:E4 -> TARIFA ANTIGA - REH 3508/2025 | F4: ='Fatura B1 (GD) OK'!F4 -> TARIFA NOVA - REH xxxx/2026 | I4: Tarifas Proporcionalizadas | M4: BAM | N4: 0.01885 | Q4: TARIFA | R4: =C4 -> TARIFA ANTIGA - REH 3508/2025 | U4: =F4 -> TARIFA NOVA - REH xxxx/2026 | X4: Tarifas Proporcionalizadas
C5: Tusd | D5: TE | E5: TUSD + TE | F5: Tusd | G5: TE | H5: TUSD + TE | I5: Tusd | J5: TE | K5: TUSD + TE | M5: BVM1 | N5: 0.04463 | R5: Tusd (R$/kWh) | U5: Tusd (R$/kWh) | X5: Tusd (R$/kWh)
B6: B2 | C6: ='TABELA DE TARIFAS ANTIGAS'!G77/1000 -> 0.46863 | D6: ='TABELA DE TARIFAS ANTIGAS'!H77/1000 -> 0.32068 | E6: =C6+D6 -> 0.78931 | F6: ='TABELA DE TARIFAS NOVAS'!G79/1000 -> 0.50632 | G6: ='TABELA DE TARIFAS NOVAS'!H79/1000 -> 0.33739 | H6: =F6+G6 -> 0.84371 | I6: =((C6*$C$14)+(F6*$D$14))/($D$14+$C$14) -> 0.50380733 | J6: =((D6*$C$14)+(G6*$D$14))/($D$14+$C$14) -> 0.336276 | K6: =I6+J6 -> 0.84008333 | M6: BVM2 | N6: 0.07877 | Q6: =B6 -> B2 | R6: ='FIO B'!H30/1000 -> 0.20383072 | U6: ='FIO B'!K30/1000 -> 0.20915159 | X6: =((R6*$C$14)+(U6*$D$14))/($D$14+$C$14) -> 0.20879687
B7: CDE Escassez Hídrica | C7: 0.00018774721 | D7: -0.0044031307 | E7: 0.0036054084 | F7: =T11 -> 0.00018418923 | G7: =U11 -> -0.00053182975 | H7: =F7+G7 -> -0.00034764052 | I7: =((C7*$C$14)+(F7*$D$14))/($D$14+$C$14) -> 0.00018442643 | J7: =((D7*$C$14)+(G7*$D$14))/($D$14+$C$14) -> -0.00078991648 | K7: =I7+J7 -> -0.00060549005
B8: TE SCEE | G8: =G6*15% -> 0.0506085 | J8: =((D8*$C$14)+(G8*$D$14))/($D$14+$C$14) -> 0.0472346 | M8: Escassez Hídrica | N8: 0.142 | P8: CUSTO | R8: Part. TUSD (%) | S8: Part. TE (%) | T8: Tusd (R$/kWh) | U8: TE (R$/kWh)
P9: CDE CONTAS
H10: Fatura | L10: Vigência das Tarifas (troca Bandeira): | M10: =EOMONTH(B14,0)+1 -> 46266 | P10: CDE COVID | U10: 0
B11: INSTALAÇÃO | C11: 160489097 | H11: =E14 -> 46268 | K11: Altere a bandeira na célula abaixo | P11: CDE ESCASSEZ HÍDRICA | T11: ='Fatura B1 (GD) OK'!T11 -> 0.00018418923 | U11: ='Fatura B1 (GD) OK'!U11 -> -0.00053182975
K12: BAM | L12: BAM
B13: Leitura Anterior | C13: Nº de dias tarifa Anterior | D13: Nº de dias tarifa Nova | E13: Leitura Atual | J13: Leitura Anterior | K13: Nº de dias tarifa Anterior | L13: Nº de dias tarifa Nova | M13: Leitura Atual
B14: 46238 | C14: =IF((F2-B14-1)<0,0,(F2-B14-1)) -> 2 | D14: =E14-F2+1 -> 28 | E14: 46268 | J14: =B14 -> 46238 | K14: =IF((M10-J14-1)<0,0,(M10-J14-1)) -> 27 | L14: =M14-M10+1 -> 3 | M14: =E14 -> 46268
B17: Perc. de Redução da Energia Injetada | E17: TUSD | F17: 1 | G17: TE | H17: 1 | M17: Documento Impressão | O17: 1025311195
R18: ERRO EM PRD QUANDO O CONSUMO É ABAIXO DO MÍNIMO NA UTILIZAÇÃO DA INJETADA
B19: Descrição | C19: Unidade | D19: Quantidade | E19: Preço Unit (R$) com tributos | F19: Valor Total (R$) | G19: PIS/COFINS (R$) | H19: Base de Cálculo ICMS (R$) | I19: Alíquota ICMS (%) | J19: ICMS (R$) | K19: Preço Unit (R$) | L19: Tributos | M19: Base de Cálc (R$) | N19: Alíquota (%) | O19: Valor (R$)
R20: TUSD Fio B | S20: Receita Fio B | T20: não está considerando energia injetada
B21: TUSD - Ativo | C21: kWh | D21: 1036 | E21: =IFERROR((ROUND(D21*K21,2)+ROUND(G21,2)+ROUND(J21,2))/ROUND(D21,4), 0) -> 0.55930502 | F21: =ROUND(D21*E21,2) -> 579.44 | G21: =((D21*K21)/(1-$N$21-$N$23))*($N$21+$N$23) -> 34.321613 | H21: =(IF($I$21=12%,(D21*K21)/(1-$N$21-$N$23)/(1-$C$122)/$F$122*$C$122,(D21*K21)/(1-$N$21-$N$23)/(1-$I$21))) -> 579.44376 | I21: 0.04 | J21: =(H21*$I$21) -> 23.17775 | K21: =IF(AND($B$14<$F$2,$E$14<$F$2),C6,IF($B$14<$F$2,I6,F6)) -> 0.50380733 | L21: PIS | M21: =D109 -> 948.36406 | N21: ='Fatura B1 (GD) OK'!N21 -> 0.011 | O21: =ROUND(M21*N21,2) -> 10.43 | R21: =IF(AND($B$14<$F$2,$E$14<$F$2),R6,IF($B$14<$F$2,X6,U6)) -> 0.20879687 | S21: =D21*R21 -> 216.31355 | T21: =SUM(S21:S23) -> 216.31355
B22: TUSD - Consumo Reservado | C22: kWh | D22: 0 | E22: =IFERROR((ROUND(D22*K22,2)+ROUND(G22,2)+ROUND(J22,2))/ROUND(D22,4), 0) -> 0 | F22: =ROUND(D22*E22,2) -> 0 | G22: =((D22*K22)/(1-$N$21-$N$23))*($N$21+$N$23) -> 0 | H22: =(IF($I$21=12%,(D22*K22)/(1-$N$21-$N$23)/(1-$C$122)/$F$122*$C$122,(D22*K22)/(1-$N$21-$N$23)/(1-$I$21))) -> 0 | I22: =I21 -> 0.04 | J22: =(H22*$I$21) -> 0 | K22: =(K21+(K21*(-$H$55))) -> 0.20152293 | L22: PIS Inj | M22: =D110 -> -920.8995 | N22: =N21 -> 0.011 | O22: =ROUND(M22*N22,2) -> -10.13 | R22: =IF(AND($B$14<$F$2,$E$14<$F$2),R6,IF($B$14<$F$2,X6,U6)) -> 0.20879687 | S22: =D22*R22 -> 0
B23: TE - Consumo | C23: kWh | D23: =D21 -> 1036 | E23: =IFERROR((ROUND(D23*K23,2)+ROUND(G23,2)+ROUND(J23,2))/ROUND(D23,4), 0) -> 0.37332046 | F23: =ROUND(D23*E23,2) -> 386.76 | G23: =((D23*K23)/(1-$N$21-$N$23))*($N$21+$N$23) -> 22.908628 | H23: =(IF($I$21=12%,(D23*K23)/(1-$N$21-$N$23)/(1-$C$122)/$F$122*$C$122,(D23*K23)/(1-$N$21-$N$23)/(1-$I$21))) -> 386.761 | J23: =ROUND(H23*$I$21,2) -> 15.47 | K23: =IF(AND($B$14<$F$2,$E$14<$F$2),D6,IF($B$14<$F$2,J6,G6)) -> 0.336276 | L23: COFINS | M23: =M21 -> 948.36406 | N23: ='Fatura B1 (GD) OK'!N23 -> 0.0507 | O23: =ROUND(M23*N23,2) -> 48.08 | S23: =-S22*$H$55 -> 0 | T23: NÃO ESTÁ CONSIDERANDO O DESCONTO DO RESERVADO DA CONSUMIDA
B24: TE - Consumo Reservado | C24: kWh | D24: =D22 -> 0 | E24: =IFERROR((ROUND(D24*K24,2)+ROUND(G24,2)+ROUND(J24,2))/ROUND(D24,4), 0) -> 0 | F24: =ROUND(D24*E24,2) -> 0 | G24: =((D24*K24)/(1-$N$21-$N$23))*($N$21+$N$23) -> 0 | H24: =(IF($I$21=12%,(D24*K24)/(1-$N$21-$N$23)/(1-$C$122)/$F$122*$C$122,(D24*K24)/(1-$N$21-$N$23)/(1-$I$21))) -> 0 | J24: =ROUND(H24*$I$21,2) -> 0 | K24: =ROUND(K23+(K23*(-$H$55)),8) -> 0.1345104 | L24: COFINS Inj | M24: =M22 -> -920.8995 | N24: =N23 -> 0.0507 | O24: =ROUND(M24*N24,2) -> -46.69
B25: Adicional BAM | C25: kWh | D25: =IF($K$12=M4,($D$21*($K$14)/($K$14+$L$14)),0)+IF($L$12=M4,($D$21*($L$14)/($K$14+$L$14)),0)+IF($K$12=M4,($D$22*($K$14)/($K$14+$L$14)),0)+IF($L$12=M4,(D22*($L$14)/($K$14+$L$14)),0) -> 1036 | E25: =IFERROR((ROUND(D25*K25,2)+ROUND(G25,2)+ROUND(J25,2))/ROUND(D25,4), 0) -> 0.020926641 | F25: =ROUND(D25*E25,2) -> 21.68 | G25: =((D25*K25)/(1-$N$21-$N$23))*($N$21+$N$23) -> 1.2841465 | H25: =(IF($I$21=12%,(D25*K25)/(1-$N$21-$N$23)/(1-$C$122)/$F$122*$C$122,(D25*K25)/(1-$N$21-$N$23)/(1-$I$21))) -> 21.679944 | J25: =ROUND(H25*$I$21,2) -> 0.87 | K25: =J65 -> 0.01885
B26: Adicional BVM1 | C26: kWh | D26: =IF($K$12=M5,((D21+D22)*($K$14)/($K$14+$L$14)),0)+IF($L$12=M5,((D21+D22)*($L$14)/($K$14+$L$14)),0) -> 0 | E26: =IFERROR((ROUND(D26*K26,2)+ROUND(G26,2)+ROUND(J26,2))/ROUND(D26,4), 0) -> 0 | F26: =ROUND(D26*E26,2) -> 0 | G26: =((D26*K26)/(1-$N$21-$N$23))*($N$21+$N$23) -> 0 | H26: =(IF($I$21=12%,(D26*K26)/(1-$N$21-$N$23)/(1-$C$122)/$F$122*$C$122,(D26*K26)/(1-$N$21-$N$23)/(1-$I$21))) -> 0 | J26: =ROUND(H26*$I$21,2) -> 0 | K26: =J66 -> 0
B27: Adicional BVM2 | C27: kWh | D27: =IF($K$12=M6,((D22+D23)*($K$14)/($K$14+$L$14)),0)+IF($L$12=M6,((D22+D23)*($L$14)/($K$14+$L$14)),0) -> 0 | E27: =IFERROR((ROUND(D27*K27,2)+ROUND(G27,2)+ROUND(J27,2))/ROUND(D27,4), 0) -> 0 | F27: =ROUND(D27*E27,2) -> 0 | G27: =((D27*K27)/(1-$N$21-$N$23))*($N$21+$N$23) -> 0 | H27: =(IF($I$21=12%,(D27*K27)/(1-$N$21-$N$23)/(1-$C$122)/$F$122*$C$122,(D27*K27)/(1-$N$21-$N$23)/(1-$I$21))) -> 0 | J27: =ROUND(H27*$I$21,2) -> 0 | K27: =J67 -> 0
B28: Adicional EH | C28: kWh | D28: =IF($K$12=M7,((D23+D24)*($K$14)/($K$14+$L$14)),0)+IF($L$12=M7,((D23+D24)*($L$14)/($K$14+$L$14)),0) -> 0 | E28: =IFERROR((ROUND(D28*K28,2)+ROUND(G28,2)+ROUND(J28,2))/ROUND(D28,4), 0) -> 0 | F28: =ROUND(D28*E28,2) -> 0 | G28: =((D28*K28)/(1-$N$21-$N$23))*($N$21+$N$23) -> 0 | H28: =(IF($I$21=12%,(D28*K28)/(1-$N$21-$N$23)/(1-$C$122)/$F$122*$C$122,(D28*K28)/(1-$N$21-$N$23)/(1-$I$21))) -> 0 | J28: =ROUND(H28*$I$21,2) -> 0 | K28: =J68 -> 0
B30: TUSD - Consumo inj Reservado | C30: kWh | D30: 0 | E30: =IFERROR((ROUND(D30*K30,2)+ROUND(G30,2)+ROUND(J30,2))/ROUND(D30,4), 0) -> 0 | F30: =ROUND(D30*E30,2) -> 0 | G30: =((D30*K30)/(1-$N$22-$N$24))*($N$22+$N$24) -> 0 | H30: 0 | I30: 0 | J30: =H30*$I$21 -> 0 | K30: =K22 -> 0.20152293
B31: TUSD - Consumo inj | C31: kWh | D31: -1006 | E31: =IFERROR((ROUND(D31*K31,2)+ROUND(G31,2)+ROUND(J31,2))/ROUND(D31,4), 0) -> 0.53693837 | F31: =ROUND(D31*E31,2) -> -540.16 | G31: =((D31*K31)/(1-$N$22-$N$24))*($N$22+$N$24) -> -33.327744 | H31: 0 | I31: 0 | J31: =H31*$I$21 -> 0 | K31: =K21 -> 0.50380733
B32: TUSD - Consumo inj 11/2025 | C32: kWh | D32: 0 | E32: =IFERROR((ROUND(D32*K32,2)+ROUND(G32,2)+ROUND(J32,2))/ROUND(D32,4), 0) -> 0 | F32: =ROUND(D32*E32,2) -> 0 | G32: =((D32*K32)/(1-$N$22-$N$24))*($N$22+$N$24) -> 0 | I32: 0 | J32: =H32*$I$21 -> 0 | K32: =K22 -> 0.20152293
B33: TE - Consumo inj Reservado | C33: kWh | D33: =D30 -> 0 | E33: =IFERROR((ROUND(D33*K33,2)+ROUND(G33,2)+ROUND(J33,2))/ROUND(D33,4), 0) -> 0 | F33: =ROUND(D33*E33,2) -> 0 | G33: =((D33*K33)/(1-$N$22-$N$24))*($N$22+$N$24) -> 0 | H33: =(IF($I$33=12%,(D33*K33)/(1-$N$22-$N$24)/(1-$C$128)/$F$128*$C$128,(D33*K33)/(1-$N$22-$N$24)/(1-$I$33))) -> 0 | I33: =I21 -> 0.04 | J33: =H33*$I$21 -> 0 | K33: =K24 -> 0.1345104
B34: TE - Consumo inj | C34: kWh | D34: =D31 -> -1006 | E34: =IFERROR((ROUND(D34*K34,2)+ROUND(G34,2)+ROUND(J34,2))/ROUND(D34,4), 0) -> 0.37332008 | F34: =ROUND(D34*E34,2) -> -375.56 | G34: =((D34*K34)/(1-$N$22-$N$24))*($N$22+$N$24) -> -22.245251 | H34: =(IF($I$33=12%,(D34*K34)/(1-$N$22-$N$24)/(1-$C$128)/$F$128*$C$128,(D34*K34)/(1-$N$22-$N$24)/(1-$I$33))) -> -375.56136 | I34: =I22 -> 0.04 | J34: =H34*$I$21 -> -15.022454 | K34: =K23 -> 0.336276
B35: TE - Consumo inj 11/2025 | C35: kWh | D35: =D32 -> 0 | E35: =IFERROR((ROUND(D35*K35,2)+ROUND(G35,2)+ROUND(J35,2))/ROUND(D35,4), 0) -> 0 | F35: =ROUND(D35*E35,2) -> 0 | G35: =((D35*K35)/(1-$N$22-$N$24))*($N$22+$N$24) -> 0 | H35: =(IF($I$33=12%,(D35*K35)/(1-$N$22-$N$24)/(1-$C$128)/$F$128*$C$128,(D35*K35)/(1-$N$22-$N$24)/(1-$I$33))) -> 0 | I35: =I23 -> 0 | J35: =H35*$I$21 -> 0 | K35: =K24 -> 0.1345104
B36: Adicional BAM inj | C36: kWh | D36: =IF($K$12=M4,(($D$30+$D$31)*($K$14)/($K$14+$L$14)),0)+IF($L$12=M4,(($D$30+$D$31)*($L$14)/($K$14+$L$14)),0) -> -1006 | E36: =IFERROR((ROUND(D36*K36,2)+ROUND(G36,2)+ROUND(J36,2))/ROUND(D36,4), 0) -> 0.020924453 | F36: =ROUND(D36*E36,2) -> -21.05 | G36: =((D36*K36)/(1-$N$22-$N$24))*($N$22+$N$24) -> -1.2469607 | H36: =(IF($I$33=12%,(D36*K36)/(1-$N$22-$N$24)/(1-$C$128)/$F$128*$C$128,(D36*K36)/(1-$N$22-$N$24)/(1-$I$33))) -> -21.052147 | J36: =H36*$I$21 -> -0.84208586 | K36: =J84 -> 0.01885
B37: Adicional BVM1 inj | C37: kWh | D37: =IF($K$12=M5,(($D$30+$D$31)*($K$14)/($K$14+$L$14)),0)+IF($L$12=M5,(($D$30+$D$31)*($L$14)/($K$14+$L$14)),0) -> 0 | E37: =IFERROR((ROUND(D37*K37,2)+ROUND(G37,2)+ROUND(J37,2))/ROUND(D37,4), 0) -> 0 | F37: =ROUND(D37*E37,2) -> 0 | G37: =((D37*K37)/(1-$N$22-$N$24))*($N$22+$N$24) -> 0 | H37: =(IF($I$33=12%,(D37*K37)/(1-$N$22-$N$24)/(1-$C$128)/$F$128*$C$128,(D37*K37)/(1-$N$22-$N$24)/(1-$I$33))) -> 0 | J37: =H37*$I$21 -> 0 | K37: =J85 -> 0
B38: Adicional BVM2 inj | C38: kWh | D38: =IF($K$12=M6,(($D$30+$D$31)*($K$14)/($K$14+$L$14)),0)+IF($L$12=M6,(($D$30+$D$31)*($L$14)/($K$14+$L$14)),0) -> 0 | E38: =IFERROR((ROUND(D38*K38,2)+ROUND(G38,2)+ROUND(J38,2))/ROUND(D38,4), 0) -> 0 | F38: =ROUND(D38*E38,2) -> 0 | G38: =((D38*K38)/(1-$N$22-$N$24))*($N$22+$N$24) -> 0 | H38: =(IF($I$33=12%,(D38*K38)/(1-$N$22-$N$24)/(1-$C$128)/$F$128*$C$128,(D38*K38)/(1-$N$22-$N$24)/(1-$I$33))) -> 0 | J38: =H38*$I$21 -> 0 | K38: =J86 -> 0
B39: Adicional EH inj | C39: kWh | D39: =IF($K$12=M7,(($D$30+$D$31)*($K$14)/($K$14+$L$14)),0)+IF($L$12=M7,(($D$30+$D$31)*($L$14)/($K$14+$L$14)),0) -> 0 | E39: =IFERROR((ROUND(D39*K39,2)+ROUND(G39,2)+ROUND(J39,2))/ROUND(D39,4), 0) -> 0 | F39: =ROUND(D39*E39,2) -> 0 | G39: =((D39*K39)/(1-$N$22-$N$24))*($N$22+$N$24) -> 0 | H39: =(IF($I$33=12%,(D39*K39)/(1-$N$22-$N$24)/(1-$C$128)/$F$128*$C$128,(D39*K39)/(1-$N$22-$N$24)/(1-$I$33))) -> 0 | J39: =H39*$I$21 -> 0 | K39: =J87 -> 0
B41: Juros
B42: Multas | F42: -211.16
B43: Bônus/Descontos
B44: CIP
B48: TOTAL | F48: =SUM(F21:F47) -> -160.05 | G48: =SUM(G21:G47) -> 1.6944321 | H48: =SUM(H21:H47) -> 591.2712 | J48: =SUM(J21:J47) -> 23.65321
B50: Informativo Escassez Hídrica | D50: =D21+D22 -> 1036 | E50: =IF(AND($B$14<$F$2,$E$14<$F$2),C7,IF($B$14<$F$2,I7,F7)) -> 0.00018442643 | F50: =IF(AND($B$14<$F$2,$E$14<$F$2),D7,IF($B$14<$F$2,J7,G7)) -> -0.00078991648 | H50: =(D50*(E50+F50))+(D61*(E50+F50)*-H55) -> -0.62728769
D51: =D31+D30 -> -1006 | E51: =IF(AND($B$14<$F$2,$E$14<$F$2),C7,IF($B$14<$F$2,I7,F7)) -> 0.00018442643 | F51: =IF(AND($B$14<$F$2,$E$14<$F$2),D7,IF($B$14<$F$2,J7,G7)) -> -0.00078991648 | H51: =(D51*(E51+F51))+(D80*(E51+F51)*-H55) -> 0.60912299
H52: =SUM(H50:H51) -> -0.018164702
B53: Desconto Rural Irrigante | F53: =SUM(H74+H62+H75+H76+H77+H81+H93+H94+H95+H96) -> 0
G55: desconto: | H55: 0.6
B56: Fatura B2 Irrig
D57: Qtde | E57: TUSD | F57: TE | G57: TUSD + TE | H57: R$
B58: Fornecimento de Energia Elétrica | H58: =SUM(H60:H104)+SUM(H109:H114) -> 35.348152
B60: Energia Fornecida | D60: =D21 -> 1036 | E60: =IF(AND($B$14<$F$2,$E$14<$F$2),C6,IF($B$14<$F$2,I6,F6)) -> 0.50380733 | F60: =IF(AND($B$14<$F$2,$E$14<$F$2),D6,IF($B$14<$F$2,J6,G6)) -> 0.336276 | G60: =E60+F60 -> 0.84008333 | H60: =ROUND((D60*E60),2)+ROUND((D60*F60),2) -> 870.32
B61: Energia Fornecida reservado | D61: =D22 -> 0 | E61: =E60 -> 0.50380733 | F61: =F60 -> 0.336276 | G61: =G60 -> 0.84008333 | H61: =ROUND((D61*E61),2)+ROUND((D61*F61),2) -> 0 | J61: =(($D$61*E61)-($D$61*E61*$H$55))/$D$61 -> #DIV/0! | K61: =(($D$61*F61)-($D$61*F61*$H$55))/$D$61 -> #DIV/0!
B62: Desconto reservado | H62: =-H61*$H$55 -> 0
B64: Adicional BAM | D64: =IF($K$12=M4,(D60*(K14)/(K14+L14)),0)+IF($L$12=M4,(D60*(L14)/(K14+L14)),0) -> 1036 | F64: =N4 -> 0.01885 | H64: =ROUND(D64*(E64+F64),2) -> 19.53 | J64: Tarifa reservada bandeira com desconto
B65: Adicional BVM 1 | D65: =IF($K$12=M5,(D60*(K14)/(K14+L14)),0)+IF($L$12=M5,(D60*(L14)/(K14+L14)),0) -> 0 | F65: =N5 -> 0.04463 | H65: =ROUND(D65*(E65+F65),2) -> 0 | J65: =IFERROR((((D64*F64)+(D69*F69))-(D69*F69*$H$55))/(D64+D69), 0) -> 0.01885
B66: Adicional BVM 2 | D66: =IF($K$12=M6,(D60*(K14)/(K14+L14)),0)+IF($L$12=M6,(D60*(L14)/(K14+L14)),0) -> 0 | F66: =N6 -> 0.07877 | H66: =ROUND(D66*(E66+F66),2) -> 0 | J66: =IFERROR((((D65*F65)+(D70*F70))-(D70*F70*$H$55))/(D65+D70), 0) -> 0
B67: Adicional Escassez Hídrica | D67: =IF($K$12=M8,(D60*(K14)/(K14+L14)),0)+IF($L$12=M8,(D60*(L14)/(K14+L14)),0) -> 0 | F67: =N8 -> 0.142 | H67: =ROUND(D67*(E67+F67),2) -> 0 | J67: =IFERROR((((D66*F66)+(D71*F71))-(D71*F71*$H$55))/(D66+D71), 0) -> 0
J68: =IFERROR((((D67*F67)+(D72*F72))-(D72*F72*$H$55))/(D67+D72), 0) -> 0
B69: Adicional BAM PT Reservado | D69: =IF($K$12=M4,((D61)*(K14)/(K14+L14)),0)+IF($L$12=M4,((D61)*(L14)/(K14+L14)),0) -> 0 | F69: =F64 -> 0.01885 | H69: =ROUND(D69*(E69+F69),2) -> 0
B70: Adicional BVM 1 PT Reservado | D70: =IF($K$12=M5,((D61)*(K14)/(K14+L14)),0)+IF($L$12=M5,((D61)*(L14)/(K14+L14)),0) -> 0 | F70: =F65 -> 0.04463 | H70: =ROUND(D70*(E70+F70),2) -> 0
B71: Adicional BVM 2 PT Reservado | D71: =IF($K$12=M6,((D61)*(K14)/(K14+L14)),0)+IF($L$12=M6,((D61)*(L14)/(K14+L14)),0) -> 0 | F71: =F66 -> 0.07877 | H71: =ROUND(D71*(E71+F71),2) -> 0
B72: Adicional Esc. Hídrica Reserv | D72: =IF($K$12=M8,((D61)*(K14)/(K14+L14)),0)+IF($L$12=M8,((D61)*(L14)/(K14+L14)),0) -> 0 | F72: =F67 -> 0.142 | H72: =ROUND(D72*(E72+F72),2) -> 0
M73: 46.34
B74: Desc Adicional BAM | H74: =-H69*$H$55 -> 0
B75: Desc Adicional BVM 1 | H75: =-H70*$H$55 -> 0 | J75: =(K80*D80)/(1-N21-N23)/(1-I21) -> #DIV/0!
B76: Desc Adicional BVM 2 | H76: =-H71*$H$55 -> 0 | J76: =J75*I21 -> #DIV/0!
B77: Desc Adicional Escassez Hídrica | H77: =-H72*$H$55 -> 0
B79: Energia Injetada | D79: =D31 -> -1006 | E79: =E60*F17 -> 0.50380733 | F79: =F60 -> 0.336276 | G79: =E79+F79 -> 0.84008333 | H79: =ROUND((D79*E79),2)+ROUND((D79*F79),2) -> -845.12
B80: Energia Injetada reservado | D80: =D30 -> 0 | E80: =E79 -> 0.50380733 | F80: =F79 -> 0.336276 | G80: =G79 -> 0.84008333 | H80: =ROUND((D80*E80),2)+ROUND((D80*F80),2) -> 0 | J80: =(($D$80*E80)+($D$80*E80*$H$55))/$D$80 -> #DIV/0! | K80: =(($D$80*F80)+($D$80*F80*-$H$55))/$D$80 -> #DIV/0!
B81: Desconto Injetado reservado | H81: =-H80*$H$55 -> 0
B83: Adicional BAM Injet | D83: =IF($K$12=M4,(D79*(K14)/(K14+L14)),0)+IF($L$12=M4,(D79*(L14)/(K14+L14)),0) -> -1006 | F83: =F64 -> 0.01885 | H83: =ROUND(D83*(E83+F83),2) -> -18.96 | J83: Tarifa reservada bandeira com desconto
B84: Adicional BVM 1 Injet | D84: =IF($K$12=M5,(D79*(K14)/(K14+L14)),0)+IF($L$12=M5,(D79*(L14)/(K14+L14)),0) -> 0 | F84: =F65 -> 0.04463 | H84: =ROUND(D84*(E84+F84),2) -> 0 | J84: =IFERROR((((D83*F83)+(D88*F88))-(D88*F88*0.6))/(D83+D88), 0) -> 0.01885
B85: Adicional BVM 2 Injet | D85: =IF($K$12=M6,(D79*(K14)/(K14+L14)),0)+IF($L$12=M6,(D79*(L14)/(K14+L14)),0) -> 0 | F85: =F66 -> 0.07877 | H85: =ROUND(D85*(E85+F85),2) -> 0 | J85: =IFERROR((((D84*F84)+(D89*F89))-(D89*F89*0.6))/(D84+D89), 0) -> 0
B86: Adicional Escassez Hídrica | D86: =IF($K$12=M8,(D79*(K14)/(K14+L14)),0)+IF($L$12=M8,(D79*(L14)/(K14+L14)),0) -> 0 | F86: =F67 -> 0.142 | H86: =ROUND(D86*(E86+F86),2) -> 0 | J86: =IFERROR((((D85*F85)+(D90*F90))-(D90*F90*0.6))/(D85+D90), 0) -> 0
J87: =IFERROR((((D86*F86)+(D91*F91))-(D91*F91*0.6))/(D86+D91), 0) -> 0
B88: Adicional BAM PT Reservado Injet | D88: =IF($K$12=M4,((D80)*(K14)/(K14+L14)),0)+IF($L$12=M4,((D80)*(L14)/(K14+L14)),0) -> 0 | F88: =F83 -> 0.01885 | H88: =ROUND(D88*(E88+F88),2) -> 0
B89: Adicional BVM 1 PT Reservado Injet | D89: =IF($K$12=M5,((D80)*(K14)/(K14+L14)),0)+IF($L$12=M5,((D80)*(L14)/(K14+L14)),0) -> 0 | F89: =F84 -> 0.04463 | H89: =ROUND(D89*(E89+F89),2) -> 0
B90: Adicional BVM 2 PT Reservado Injet | D90: =IF($K$12=M6,((D80)*(K14)/(K14+L14)),0)+IF($L$12=M6,((D80)*(L14)/(K14+L14)),0) -> 0 | F90: =F85 -> 0.07877 | H90: =ROUND(D90*(E90+F90),2) -> 0
B91: Adicional Esc. Hídrica Reserv | D91: =IF($K$12=M8,((D80)*(K14)/(K14+L14)),0)+IF($L$12=M8,((D80)*(L14)/(K14+L14)),0) -> 0 | F91: =F86 -> 0.142 | H91: =ROUND(D91*(E91+F91),2) -> 0
B93: Desc Adicional BAM Injet | H93: =-H88*$H$55 -> 0
B94: Desc Adicional BVM 1 Injet | H94: =-H89*$H$55 -> 0
B95: Desc Adicional BVM 2 Injet | H95: =-H90*$H$55 -> 0
B96: Desc Adicional Escassez Hídrica | H96: =-H91*$H$55 -> 0
I102: =H98+H102 -> 0
H106: =SUM(H60:H105) -> 25.77
D108: Base de Cálculo
B109: PIS | D109: =SUM(H60:H62,H64:H67,H69:H72,H74:H77)/(1-E109-E111) -> 948.36406 | E109: =N21 -> 0.011 | H109: =D109*E109 -> 10.432005
B110: PIS Eneg Inj | D110: =SUM(H79:H81,H83:H86,H88:H91,H93:H96,H98:H100,H102:H104)/(1-E109-E111) -> -920.8995 | E110: =E109 -> 0.011 | H110: =D110*E110 -> -10.129894
B111: COFINS | D111: =D109 -> 948.36406 | E111: =N23 -> 0.0507 | H111: =D111*E111 -> 48.082058
B112: COFINS Eneg Inj | D112: =D110 -> -920.8995 | E112: =E111 -> 0.0507 | H112: =D112*E112 -> -46.689605
B113: ICMS | D113: =IF((E113=17%),(D109/(1-E113)),D122) -> 329.29308 | E113: =I21 -> 0.04 | H113: =D113*E113 -> 13.171723
B114: ICMS Eneg Inj | D114: =IF((E114=17%),(D110/(1-E114)),D128) -> -132.20336 | E114: =E113 -> 0.04 | H114: =D114*E114 -> -5.2881342
B116: Informativo Escassez Hídrica | D116: =D60+D61+D79+D80 -> 30 | E116: =IF(AND($B$14<$F$2,$E$14<$F$2),C7,IF($B$14<$F$2,I7,F7)) -> 0.00018442643 | F116: =IF(AND($B$14<$F$2,$E$14<$F$2),D7,IF($B$14<$F$2,J7,G7)) -> -0.00078991648 | H116: =((D116)*(E116+F116)+D61*(E116+F116)*-H55)+D80*(E116+F116)*-H55 -> -0.018164702
B118: Se for base reduzida: (célula E43 = 12%)
B119: Fornecida | D119: Com tributos
B120: PIS | C120: =E109 -> 0.011 | D120: =SUM(H60:H77)/(1-C120-C121) -> 948.36406 | E120: x | F120: =C120 -> 0.011 | G120: =D120*F120 -> 10.432005
B121: COFINS | C121: =E111 -> 0.0507 | D121: =D120 -> 948.36406 | E121: x | F121: =C121 -> 0.0507 | G121: =D121*F121 -> 48.082058
A122: Rural c/ incrição | B122: ICMS | C122: 0.04 | D122: =H122/F122*C122 -> 329.29308 | E122: x | F122: 0.12 | G122: =D122*F122 -> 39.515169 | H122: =((SUM(H60:H77))/(1-F120-F121)/(1-(C122))) -> 987.87923 | I122: =H122*C122 -> 39.515169
E123: =(O111)/(1-C120-C121-C122) -> 0
B125: Injetada | D125: Com tributos
B126: PIS | C126: =C120 -> 0.011 | D126: =SUM(H79:H104)/(1-C126-C127) -> -920.8995 | E126: x | F126: =C126 -> 0.011 | G126: =D126*F126 -> -10.129894
B127: COFINS | C127: =C121 -> 0.0507 | D127: =D126 -> -920.8995 | E127: x | F127: =C127 -> 0.0507 | G127: =D127*F127 -> -46.689605
...

Sheet Fatura B1 BRe (GD)
B2: B1 Baixa renda | E2: Vigência das Tarifas: | F2: ='[4]Fatura B1 (GD)'!F2 -> 45511 | M2: Bandeira | N2: R$/kWh | O2: ANEEL em 29/06 | Q2: TUSD FIO B
M3: VERDE | N3: 0
B4: TARIFA R$ kWh | C4: TARIFA ANTIGA - REH 3091/2022 | F4: ='[4]Fatura B1 (GD)'!F4 -> TARIFA NOVA - REH xxxx/2024 | I4: Tarifas Proporcionalizadas | M4: BAM | N4: 0.01885 | Q4: TARIFA | R4: =C4 -> TARIFA ANTIGA - REH 3091/2022 | U4: =F4 -> TARIFA NOVA - REH xxxx/2024 | X4: Tarifas Proporcionalizadas
C5: Tusd | D5: TE | E5: TUSD + TE | F5: Tusd | G5: TE | H5: TUSD + TE | I5: Tusd | J5: TE | K5: TUSD + TE | M5: BVM1 | N5: 0.04463 | R5: Tusd (R$/kWh) | U5: Tusd (R$/kWh) | X5: Tusd (R$/kWh)
B6: Baixa renda | C6: 0.28337 | D6: 0.2988 | E6: 0.58217 | F6: 0.28935 | G6: 0.29334 | H6: 0.58269 | I6: =((C6*$C$14)+(F6*$D$14))/($D$14+$C$14) -> 0.28935 | J6: =((D6*$C$14)+(G6*$D$14))/($D$14+$C$14) -> 0.29334 | K6: =I6+J6 -> 0.58269 | M6: BVM2 | N6: 0.07877 | Q6: =B6 -> Baixa renda | R6: 0.17652 | U6: 0.061783268 | X6: 0.061783268
B7: CDE Escassez Hídrica | C7: =0.207830737658616/1000 -> 0.00020783074 | D7: =4.01792/1000 -> 0.00401792 | E7: =C7+D7 -> 0.0042257507 | F7: =T11 -> 0.00020783074 | G7: =U11 -> 0.00402 | H7: =F7+G7 -> 0.0042278307 | I7: =((C7*$C$14)+(F7*$D$14))/($D$14+$C$14) -> 0.00020783074 | J7: =((D7*$C$14)+(G7*$D$14))/($D$14+$C$14) -> 0.00402 | K7: =I7+J7 -> 0.0042278307
B8: TE SCEE | G8: =G6*15% -> 0.044001 | J8: =((D8*$C$14)+(G8*$D$14))/($D$14+$C$14) -> 0.044001 | M8: Escassez Hídrica | N8: 0.142 | P8: CUSTO | R8: Part. TUSD (%) | S8: Part. TE (%) | T8: Tusd (R$/kWh) | U8: TE (R$/kWh)
P9: CDE CONTAS
H10: Fatura | L10: Vigência das Tarifas (troca Bandeira): | M10: =EOMONTH(B14,0)+1 -> 46235 | P10: CDE COVID | U10: =5.61/1000 -> 0.00561
B11: INSTALAÇÃO | C11: 1041172 | H11: =E14 -> 46259 | K11: Altere a bandeira na célula abaixo | P11: CDE ESCASSEZ HÍDRICA | T11: =0.207830737658616/1000 -> 0.00020783074 | U11: =4.02/1000 -> 0.00402 | W11: prop
K12: ='Fatura B1 (GD) OK'!K12 -> BAM | L12: ='Fatura B1 (GD) OK'!L12 -> BAM | P12: 0 - 30 | Q12: 0.65 | U12: =$U$11*(1-Q12) -> 0.001407 | W12: =((T12*$C$14)+(U12*$D$14))/($D$14+$C$14) -> 0.001407
B13: Leitura Anterior | C13: Nº de dias tarifa Anterior | D13: Nº de dias tarifa Nova | E13: Leitura Atual | J13: Leitura Anterior | K13: Nº de dias tarifa Anterior | L13: Nº de dias tarifa Nova | M13: Leitura Atual | P13: 31- 100 | Q13: 0.4 | U13: =$U$11*(1-Q13) -> 0.002412 | W13: =((T13*$C$14)+(U13*$D$14))/($D$14+$C$14) -> 0.002412
B14: ='Fatura B1 (GD) OK'!B14 -> 46227 | C14: =IF((F2-B14-1)<0,0,(F2-B14-1)) -> 0 | D14: =E14-F2+1 -> 749 | E14: ='Fatura B1 (GD) OK'!E14 -> 46259 | J14: =B14 -> 46227 | K14: =IF((M10-J14-1)<0,0,(M10-J14-1)) -> 7 | L14: =M14-M10+1 -> 25 | M14: =E14 -> 46259 | P14: 101 - 220 | Q14: 0.1 | U14: =$U$11*(1-Q14) -> 0.003618 | W14: =((T14*$C$14)+(U14*$D$14))/($D$14+$C$14) -> 0.003618
P15: >220 | Q15: 0 | U15: =$U$11*(1-Q15) -> 0.00402 | W15: =((T15*$C$14)+(U15*$D$14))/($D$14+$C$14) -> 0.00402
B16: CONSUMO | D16: 537
B17: INJEÇÃO | D17: 221
B18: DIFERENÇA | D18: 316
B19: COMPENSAÇÃO | D19: =D16-D18 -> 221 | M19: Documento impressão: | O19: 241002228329
B21: Descrição | C21: Unidade | D21: Quantidade | E21: Preço Unit (R$) com tributos | F21: Valor Total (R$) | G21: PIS/COFINS (R$) | H21: Base de Cálculo ICMS (R$) | I21: Alíquota ICMS (%) | J21: ICMS (R$) | K21: Preço Unit (R$) | L21: Tributos | M21: Base de Cálc (R$) | N21: Alíquota (%) | O21: Valor (R$)
B23: Desconto Bx renda | D23: =-K168 -> -35.786655 | E23: 1 | F23: =D23*E23 -> -35.786655 | G23: 0 | H23: 0 | I23: 0 | K23: 1
B24: Valor Bx Renda | D24: =D23 -> -35.786655 | E24: =K24/(1-$N$25-$N$26)/(1-$I$24) -> 1.2840448 | F24: =-1*(F23-J24) -> 43.598155 | G24: 0 | H24: =ROUND((K168*K24)/(1-$N$25-$N$26)/(1-$I$24),2) -> 45.95 | I24: 0.17 | J24: =H24*$I$24 -> 7.8115 | K24: 1
A25: 0.65 | B25: TUSD - EAF 0 a 30 | C25: kWh | D25: =IF(D19>0,30,0) -> 30 | E25: =K25/(1-$N$25-$N$26)/(1-$I$24) -> 0.13003843 | F25: =ROUND(D25*E25,2) -> 3.9 | G25: =ROUND(((D25*K25)/(1-$N$25-$N$26))*($N$25+$N$26),2) -> 0.2 | H25: =ROUND((D25*K25)/(1-$N$25-$N$26)/(1-$I$24),2) -> 3.9 | J25: =H25*$I$24 -> 0.663 | K25: =K28*(1-A25) -> 0.1012725 | L25: PIS | M25: =D138 -> 267.98465 | N25: ='Fatura B1 (GD) OK'!N21 -> 0.011 | O25: =ROUND(M25*N25,2) -> 2.95
A26: 0.4 | B26: TUSD - EAF 31 a 100 | C26: kWh | D26: =IF(D19>30,IF(D19>100,70,D19-30),0) -> 70 | E26: =K26/(1-$N$25-$N$26)/(1-$I$24) -> 0.22292303 | F26: =ROUND(D26*E26,2) -> 15.6 | G26: =ROUND(((D26*K26)/(1-$N$25-$N$26))*($N$25+$N$26),2) -> 0.8 | H26: =ROUND((D26*K26)/(1-$N$25-$N$26)/(1-$I$24),2) -> 15.6 | J26: =H26*$I$24 -> 2.652 | K26: =K28*(1-A26) -> 0.17361 | L26: COFINS | M26: =M25 -> 267.98465 | N26: ='Fatura B1 (GD) OK'!N23 -> 0.0507 | O26: =ROUND(M26*N26,2) -> 13.59
A27: 0.1 | B27: TUSD - EAF 101 a 220 | C27: kWh | D27: =IF(D19>100,IF(D19>220,220-100,D19-100),0) -> 120 | E27: =K27/(1-$N$25-$N$26)/(1-$I$24) -> 0.33438454 | F27: =ROUND(D27*E27,2) -> 40.13 | G27: =ROUND(((D27*K27)/(1-$N$25-$N$26))*($N$25+$N$26),2) -> 2.05 | H27: =ROUND((D27*K27)/(1-$N$25-$N$26)/(1-$I$24),2) -> 40.13 | J27: =H27*$I$24 -> 6.8221 | K27: =K28*(1-A27) -> 0.260415
A28: 0 | B28: TUSD - EAF > 220 | C28: kWh | D28: =IF(D19>220,D19-220,0) -> 1 | E28: =K28/(1-$N$25-$N$26)/(1-$I$24) -> 0.37153838 | F28: =ROUND(D28*E28,2) -> 0.37 | G28: =ROUND(((D28*K28)/(1-$N$25-$N$26))*($N$25+$N$26),2) -> 0.02 | H28: =ROUND((D28*K28)/(1-$N$25-$N$26)/(1-$I$24),2) -> 0.37 | J28: =H28*$I$24 -> 0.0629 | K28: =IF(AND($B$13<$F$2,$E$13<$F$2),C6,IF($B$13<$F$2,I6,F6)) -> 0.28935
A29: 0.65 | B29: TUSD - EAFdc 0 a 30 | C29: kWh | D29: =IF(D18>0,30,0) -> 30 | E29: =K29/(1-$N$25-$N$26)/(1-$I$24) -> 0.13003843 | F29: =ROUND(D29*E29,2) -> 3.9 | G29: =ROUND(((D29*K29)/(1-$N$25-$N$26))*($N$25+$N$26),2) -> 0.2 | H29: =ROUND((D29*K29)/(1-$N$25-$N$26)/(1-$I$24),2) -> 3.9 | J29: =H29*$I$24 -> 0.663 | K29: =K32*(1-A29) -> 0.1012725
A30: 0.4 | B30: TUSD - EAFdc 31 a 100 | C30: kWh | D30: =IF(D18>30,IF(D18>100,70,D18-30),0) -> 70 | E30: =K30/(1-$N$25-$N$26)/(1-$I$24) -> 0.22292303 | F30: =ROUND(D30*E30,2) -> 15.6 | G30: =ROUND(((D30*K30)/(1-$N$25-$N$26))*($N$25+$N$26),2) -> 0.8 | H30: =ROUND((D30*K30)/(1-$N$25-$N$26)/(1-$I$24),2) -> 15.6 | J30: =H30*$I$24 -> 2.652 | K30: =K32*(1-A30) -> 0.17361
A31: 0.1 | B31: TUSD - EAFdc 101 a 220 | C31: kWh | D31: =IF(D18>100,IF(D18>220,220-100,D18-100),0) -> 120 | E31: =K31/(1-$N$25-$N$26)/(1-$I$24) -> 0.33438454 | F31: =ROUND(D31*E31,2) -> 40.13 | G31: =ROUND(((D31*K31)/(1-$N$25-$N$26))*($N$25+$N$26),2) -> 2.05 | H31: =ROUND((D31*K31)/(1-$N$25-$N$26)/(1-$I$24),2) -> 40.13 | J31: =H31*$I$24 -> 6.8221 | K31: =K32*(1-A31) -> 0.260415
A32: 0 | B32: TUSD - EAFdc > 220 | C32: kWh | D32: =IF(D18>220,D18-220,0) -> 96 | E32: =K32/(1-$N$25-$N$26)/(1-$I$24) -> 0.37153838 | F32: =ROUND(D32*E32,2) -> 35.67 | G32: =ROUND(((D32*K32)/(1-$N$25-$N$26))*($N$25+$N$26),2) -> 1.83 | H32: =ROUND((D32*K32)/(1-$N$25-$N$26)/(1-$I$24),2) -> 35.67 | J32: =H32*$I$24 -> 6.0639 | K32: =IF(AND($B$14<$F$2,$E$14<$F$2),C6,IF($B$14<$F$2,I6,F6)) -> 0.28935
B34: TE - EAF 0 a 30 | C34: kWh | D34: =D25 -> 30 | E34: =K34/(1-$N$25-$N$26)/(1-$I$24) -> 0.1318316 | F34: =ROUND(D34*E34,2) -> 3.95 | G34: =ROUND(((D34*K34)/(1-$N$25-$N$26))*($N$25+$N$26),2) -> 0.2 | H34: =ROUND((D34*K34)/(1-$N$25-$N$26)/(1-$I$24),2) -> 3.95 | J34: =H34*$I$24 -> 0.6715 | K34: =K37*(1-A25) -> 0.102669
B35: TE - EAF 31 a 100 | C35: kWh | D35: =D26 -> 70 | E35: =K35/(1-$N$25-$N$26)/(1-$I$24) -> 0.22599703 | F35: =ROUND(D35*E35,2) -> 15.82 | G35: =ROUND(((D35*K35)/(1-$N$25-$N$26))*($N$25+$N$26),2) -> 0.81 | H35: =ROUND((D35*K35)/(1-$N$25-$N$26)/(1-$I$24),2) -> 15.82 | J35: =H35*$I$24 -> 2.6894 | K35: =K37*(1-A26) -> 0.176004
B36: TE - EAF 101 a 220 | C36: kWh | D36: =D27 -> 120 | E36: =K36/(1-$N$25-$N$26)/(1-$I$24) -> 0.33899554 | F36: =ROUND(D36*E36,2) -> 40.68 | G36: =ROUND(((D36*K36)/(1-$N$25-$N$26))*($N$25+$N$26),2) -> 2.08 | H36: =ROUND((D36*K36)/(1-$N$25-$N$26)/(1-$I$24),2) -> 40.68 | J36: =H36*$I$24 -> 6.9156 | K36: =K37*(1-A27) -> 0.264006
B37: TE - EAF > 220 | C37: kWh | D37: =D28 -> 1 | E37: =K37/(1-$N$25-$N$26)/(1-$I$24) -> 0.37666171 | F37: =ROUND(D37*E37,2) -> 0.38 | G37: =ROUND(((D37*K37)/(1-$N$25-$N$26))*($N$25+$N$26),2) -> 0.02 | H37: =ROUND((D37*K37)/(1-$N$25-$N$26)/(1-$I$24),2) -> 0.38 | J37: =H37*$I$24 -> 0.0646 | K37: =IF(AND($B$14<$F$2,$E$14<$F$2),D6,IF($B$14<$F$2,J6,G6)) -> 0.29334
B38: TE - EAFdc 0 a 30 | C38: kWh | D38: =D29 -> 30 | E38: =K38/(1-$N$25-$N$26)/(1-$I$24) -> 0.1318316 | F38: =ROUND(D38*E38,2) -> 3.95 | G38: =ROUND(((D38*K38)/(1-$N$25-$N$26))*($N$25+$N$26),2) -> 0.2 | H38: =ROUND((D38*K38)/(1-$N$25-$N$26)/(1-$I$24),2) -> 3.95 | J38: =H38*$I$24 -> 0.6715 | K38: =K41*(1-A29) -> 0.102669
B39: TE - EAFdc 31 a 100 | C39: kWh | D39: =D30 -> 70 | E39: =K39/(1-$N$25-$N$26)/(1-$I$24) -> 0.22599703 | F39: =ROUND(D39*E39,2) -> 15.82 | G39: =ROUND(((D39*K39)/(1-$N$25-$N$26))*($N$25+$N$26),2) -> 0.81 | H39: =ROUND((D39*K39)/(1-$N$25-$N$26)/(1-$I$24),2) -> 15.82 | J39: =H39*$I$24 -> 2.6894 | K39: =K41*(1-A30) -> 0.176004
B40: TE - EAFdc 101 a 220 | C40: kWh | D40: =D31 -> 120 | E40: =K40/(1-$N$25-$N$26)/(1-$I$24) -> 0.33899554 | F40: =ROUND(D40*E40,2) -> 40.68 | G40: =ROUND(((D40*K40)/(1-$N$25-$N$26))*($N$25+$N$26),2) -> 2.08 | H40: =ROUND((D40*K40)/(1-$N$25-$N$26)/(1-$I$24),2) -> 40.68 | J40: =H40*$I$24 -> 6.9156 | K40: =K41*(1-A31) -> 0.264006
B41: TE - EAFdc > 220 | C41: kWh | D41: =D32 -> 96 | E41: =K41/(1-$N$25-$N$26)/(1-$I$24) -> 0.37666171 | F41: =ROUND(D41*E41,2) -> 36.16 | G41: =ROUND(((D41*K41)/(1-$N$25-$N$26))*($N$25+$N$26),2) -> 1.85 | H41: =ROUND((D41*K41)/(1-$N$25-$N$26)/(1-$I$24),2) -> 36.16 | J41: =H41*$I$24 -> 6.1472 | K41: =IF(AND($B$14<$F$2,$E$14<$F$2),D6,IF($B$14<$F$2,J6,G6)) -> 0.29334
B43: Adicional BAM | D43: =C175+C212 -> 60 | F43: =(O175+O212)/(1-$N$25-$N$26)/(1-$I$24) -> 0.51361794 | G43: =ROUND(((D43*K43)/(1-$N$25-$N$26))*($N$25+$N$26),2) -> 0.03 | H43: =F43 -> 0.51361794 | J43: =H43*$I$24 -> 0.087315049 | K43: =K175 -> 0.0065975
B44: Adicional BAM | D44: =C176+C213 -> 140 | F44: =(O176+O213)/(1-$N$25-$N$26)/(1-$I$24) -> 2.0287909 | G44: =ROUND(((D44*K44)/(1-$N$25-$N$26))*($N$25+$N$26),2) -> 0.1 | H44: =F44 -> 2.0287909 | J44: =H44*$I$24 -> 0.34489445 | K44: =K176 -> 0.01131
B45: Adicional BAM | D45: =C177+C214 -> 240 | F45: =(O177+O214)/(1-$N$25-$N$26)/(1-$I$24) -> 5.238903 | G45: =ROUND(((D45*K45)/(1-$N$25-$N$26))*($N$25+$N$26),2) -> 0.27 | H45: =F45 -> 5.238903 | J45: =H45*$I$24 -> 0.8906135 | K45: =K177 -> 0.016965
B46: Adicional BAM | D46: =C178+C215 -> 97 | F46: =(O178+O215)/(1-$N$25-$N$26)/(1-$I$24) -> 2.3498021 | G46: =ROUND(((D46*K46)/(1-$N$25-$N$26))*($N$25+$N$26),2) -> 0.12 | H46: =F46 -> 2.3498021 | J46: =H46*$I$24 -> 0.39946635 | K46: =K178 -> 0.01885
B47: Adicional BVM1 | D47: =C184+C221 -> 0 | F47: =(O184+O221)/(1-$N$25-$N$26)/(1-$I$24) -> 0 | G47: =ROUND(((D47*K47)/(1-$N$25-$N$26))*($N$25+$N$26),2) -> 0 | H47: =F47 -> 0 | J47: =H47*$I$24 -> 0 | K47: =K184 -> 0.0156205
B48: Adicional BVM1 | D48: =C185+C222 -> 0 | F48: =(O185+O222)/(1-$N$25-$N$26)/(1-$I$24) -> 0 | G48: =ROUND(((D48*K48)/(1-$N$25-$N$26))*($N$25+$N$26),2) -> 0 | H48: =F48 -> 0 | J48: =H48*$I$24 -> 0 | K48: =K185 -> 0.026778
B49: Adicional BVM1 | D49: =C186+C223 -> 0 | F49: =(O186+O223)/(1-$N$25-$N$26)/(1-$I$24) -> 0 | G49: =ROUND(((D49*K49)/(1-$N$25-$N$26))*($N$25+$N$26),2) -> 0 | H49: =F49 -> 0 | J49: =H49*$I$24 -> 0 | K49: =K186 -> 0.040167
B50: Adicional BVM1 | D50: =C187+C224 -> 0 | F50: =(O187+O224)/(1-$N$25-$N$26)/(1-$I$24) -> 0 | G50: =ROUND(((D50*K50)/(1-$N$25-$N$26))*($N$25+$N$26),2) -> 0 | H50: =F50 -> 0 | J50: =H50*$I$24 -> 0 | K50: =K187 -> 0.04463
B51: Adicional BVM2 | D51: =C193+C230 -> 0 | F51: =(O193+O230)/(1-$N$25-$N$26)/(1-$I$24) -> 0 | G51: =ROUND(((D51*K51)/(1-$N$25-$N$26))*($N$25+$N$26),2) -> 0 | H51: =F51 -> 0 | J51: =H51*$I$24 -> 0 | K51: =K193 -> 0.0275695
B52: Adicional BVM2 | D52: =C194+C231 -> 0 | F52: =(O194+O231)/(1-$N$25-$N$26)/(1-$I$24) -> 0 | G52: =ROUND(((D52*K52)/(1-$N$25-$N$26))*($N$25+$N$26),2) -> 0 | H52: =F52 -> 0 | J52: =H52*$I$24 -> 0 | K52: =K194 -> 0.047262
B53: Adicional BVM2 | D53: =C195+C232 -> 0 | F53: =(O195+O232)/(1-$N$25-$N$26)/(1-$I$24) -> 0 | G53: =ROUND(((D53*K53)/(1-$N$25-$N$26))*($N$25+$N$26),2) -> 0 | H53: =F53 -> 0 | J53: =H53*$I$24 -> 0 | K53: =K195 -> 0.070893
B54: Adicional BVM2 | D54: =C196+C233 -> 0 | F54: =(O196+O233)/(1-$N$25-$N$26)/(1-$I$24) -> 0 | G54: =ROUND(((D54*K54)/(1-$N$25-$N$26))*($N$25+$N$26),2) -> 0 | H54: =F54 -> 0 | J54: =H54*$I$24 -> 0 | K54: =K196 -> 0.07877
B55: Adicional EH | D55: =C202+C239 -> 0 | F55: =(O202+O239)/(1-$N$25-$N$26)/(1-$I$24) -> 0 | G55: =ROUND(((D55*K55)/(1-$N$25-$N$26))*($N$25+$N$26),2) -> 0 | H55: =F55 -> 0 | J55: =H55*$I$24 -> 0 | K55: =K202 -> 0.0497
B56: Adicional EH | D56: =C203+C240 -> 0 | F56: =(O203+O240)/(1-$N$25-$N$26)/(1-$I$24) -> 0 | G56: =ROUND(((D56*K56)/(1-$N$25-$N$26))*($N$25+$N$26),2) -> 0 | H56: =F56 -> 0 | J56: =H56*$I$24 -> 0 | K56: =K203 -> 0.0852
B57: Adicional EH | D57: =C204+C241 -> 0 | F57: =(O204+O241)/(1-$N$25-$N$26)/(1-$I$24) -> 0 | G57: =ROUND(((D57*K57)/(1-$N$25-$N$26))*($N$25+$N$26),2) -> 0 | H57: =F57 -> 0 | J57: =H57*$I$24 -> 0 | K57: =K204 -> 0.1278
B58: Adicional EH | D58: =C205+C242 -> 0 | F58: =(O205+O242)/(1-$N$25-$N$26)/(1-$I$24) -> 0 | G58: =ROUND(((D58*K58)/(1-$N$25-$N$26))*($N$25+$N$26),2) -> 0 | H58: =F58 -> 0 | J58: =H58*$I$24 -> 0 | K58: =K205 -> 0.142
A60: 0.65 | B60: TUSD - EAF Inj | C60: kWh | D60: =-(IF(D17>0,30,0)) -> -30 | E60: =K60/(1-$N$25-$N$26)/(1-$I$60) -> 0.1079319 | F60: =ROUND(D60*E60,2) -> -3.24 | G60: =ROUND(((D60*K60)/(1-$N$25-$N$26))*($N$25+$N$26),2) -> -0.2 | H60: =ROUND((D60*K60)/(1-$N$25-$N$26)/(1-$I$24),2) -> -3.9 | J60: =H60*$I$24 -> -0.663 | K60: =K63*(1-A60) -> 0.1012725 | L60: PIS Inj | M60: =D139 -> -103.53831 | N60: =N25 -> 0.011 | O60: =ROUND(M60*N60,2) -> -1.14
A61: 0.4 | B61: TUSD - EAF Inj | C61: kWh | D61: =-(IF(D17>30,IF(D17>100,70,D17-30),0)) -> -70 | E61: =K61/(1-$N$25-$N$26)/(1-$I$60) -> 0.18502611 | F61: =ROUND(D61*E61,2) -> -12.95 | G61: =ROUND(((D61*K61)/(1-$N$25-$N$26))*($N$25+$N$26),2) -> -0.8 | H61: =ROUND((D61*K61)/(1-$N$25-$N$26)/(1-$I$24),2) -> -15.6 | J61: =H61*$I$24 -> -2.652 | K61: =K63*(1-A61) -> 0.17361 | L61: COFINS Inj | M61: =M60 -> -103.53831 | N61: =N26 -> 0.0507 | O61: =ROUND(M61*N61,2) -> -5.25
A62: 0.1 | B62: TUSD - EAF Inj | C62: kWh | D62: =-(IF(D17>100,IF(D17>220,220-100,D17-100),0)) -> -120 | E62: =K62/(1-$N$25-$N$26)/(1-$I$60) -> 0.27753917 | F62: =ROUND(D62*E62,2) -> -33.3 | G62: =ROUND(((D62*K62)/(1-$N$25-$N$26))*($N$25+$N$26),2) -> -2.05 | H62: =ROUND((D62*K62)/(1-$N$25-$N$26)/(1-$I$24),2) -> -40.13 | J62: =H62*$I$24 -> -6.8221 | K62: =K63*(1-A62) -> 0.260415
A63: 0 | B63: TUSD - EAF Inj | C63: kWh | D63: =-(IF(D17>220,D17-220,0)) -> -1 | E63: =K63/(1-$N$25-$N$26)/(1-$I$60) -> 0.30837685 | F63: =ROUND(D63*E63,2) -> -0.31 | G63: =ROUND(((D63*K63)/(1-$N$25-$N$26))*($N$25+$N$26),2) -> -0.02 | H63: =ROUND((D63*K63)/(1-$N$25-$N$26)/(1-$I$24),2) -> -0.37 | J63: =H63*$I$24 -> -0.0629 | K63: =IF(AND($B$14<$F$2,$E$14<$F$2),C6,IF($B$14<$F$2,I6,F6)) -> 0.28935
B65: TE - EAF Inj | C65: kWh | D65: =D60 -> -30 | E65: =K65/(1-$N$25-$N$26)/(1-$I$24) -> 0.1318316 | F65: =ROUND(D65*E65,2) -> -3.95 | G65: =ROUND(((D65*K65)/(1-$N$25-$N$26))*($N$25+$N$26),2) -> -0.2 | H65: =ROUND((D65*K65)/(1-$N$25-$N$26)/(1-$I$24),2) -> -3.95 | J65: =H65*$I$24 -> -0.6715 | K65: =$K$68*(1-A60) -> 0.102669
B66: TE - EAF Inj | C66: kWh | D66: =D61 -> -70 | E66: =K66/(1-$N$25-$N$26)/(1-$I$24) -> 0.22599703 | F66: =ROUND(D66*E66,2) -> -15.82 | G66: =ROUND(((D66*K66)/(1-$N$25-$N$26))*($N$25+$N$26),2) -> -0.81 | H66: =ROUND((D66*K66)/(1-$N$25-$N$26)/(1-$I$24),2) -> -15.82 | J66: =H66*$I$24 -> -2.6894 | K66: =$K$68*(1-A61) -> 0.176004
B67: TE - EAF Inj | C67: kWh | D67: =D62 -> -120 | E67: =K67/(1-$N$25-$N$26)/(1-$I$24) -> 0.33899554 | F67: =ROUND(D67*E67,2) -> -40.68 | G67: =ROUND(((D67*K67)/(1-$N$25-$N$26))*($N$25+$N$26),2) -> -2.08 | H67: =ROUND((D67*K67)/(1-$N$25-$N$26)/(1-$I$24),2) -> -40.68 | J67: =H67*$I$24 -> -6.9156 | K67: =$K$68*(1-A62) -> 0.264006
B68: TE - EAF Inj | C68: kWh | D68: =D63 -> -1 | E68: =K68/(1-$N$25-$N$26)/(1-$I$24) -> 0.37666171 | F68: =ROUND(D68*E68,2) -> -0.38 | G68: =ROUND(((D68*K68)/(1-$N$25-$N$26))*($N$25+$N$26),2) -> -0.02 | H68: =ROUND((D68*K68)/(1-$N$25-$N$26)/(1-$I$24),2) -> -0.38 | J68: =H68*$I$24 -> -0.0646 | K68: =IF(AND($B$14<$F$2,$E$14<$F$2),D6,IF($B$14<$F$2,J6,G6)) -> 0.29334
B70: Adicional BAM Inj | D70: =C251 -> -30 | F70: =O251/(1-$N$25-$N$26)/(1-$I$24) -> -0.25680897 | G70: =ROUND(((D70*K70)/(1-$N$25-$N$26))*($N$25+$N$26),2) -> -0.01 | H70: =F70 -> -0.25680897 | J70: =H70*$I$24 -> -0.043657525 | K70: =K43 -> 0.0065975
B71: Adicional BAM Inj | D71: =C252 -> -70 | F71: =O252/(1-$N$25-$N$26)/(1-$I$24) -> -1.0143954 | G71: =ROUND(((D71*K71)/(1-$N$25-$N$26))*($N$25+$N$26),2) -> -0.05 | H71: =F71 -> -1.0143954 | J71: =H71*$I$24 -> -0.17244722 | K71: =K44 -> 0.01131
B72: Adicional BAM Inj | D72: =C253 -> -120 | F72: =O253/(1-$N$25-$N$26)/(1-$I$24) -> -2.6194515 | G72: =ROUND(((D72*K72)/(1-$N$25-$N$26))*($N$25+$N$26),2) -> -0.13 | H72: =F72 -> -2.6194515 | J72: =H72*$I$24 -> -0.44530675 | K72: =K45 -> 0.016965
B73: Adicional BAM Inj | D73: =C254 -> -1 | F73: =O254/(1-$N$25-$N$26)/(1-$I$24) -> -0.025680897 | G73: =ROUND(((D73*K73)/(1-$N$25-$N$26))*($N$25+$N$26),2) -> 0 | H73: =F73 -> -0.025680897 | J73: =H73*$I$24 -> -0.0043657525 | K73: =K46 -> 0.01885
B74: Adicional BVM1 Inj | D74: =C260 -> 0 | F74: =O260/(1-$N$25-$N$26)/(1-$I$24) -> 0 | G74: =ROUND(((D74*K74)/(1-$N$25-$N$26))*($N$25+$N$26),2) -> 0 | H74: =F74 -> 0 | J74: =H74*$I$24 -> 0 | K74: =K47 -> 0.0156205
B75: Adicional BVM1 Inj | D75: =C261 -> 0 | F75: =O261/(1-$N$25-$N$26)/(1-$I$24) -> 0 | G75: =ROUND(((D75*K75)/(1-$N$25-$N$26))*($N$25+$N$26),2) -> 0 | H75: =F75 -> 0 | J75: =H75*$I$24 -> 0 | K75: =K48 -> 0.026778
B76: Adicional BVM1 Inj | D76: =C262 -> 0 | F76: =O262/(1-$N$25-$N$26)/(1-$I$24) -> 0 | G76: =ROUND(((D76*K76)/(1-$N$25-$N$26))*($N$25+$N$26),2) -> 0 | H76: =F76 -> 0 | J76: =H76*$I$24 -> 0 | K76: =K49 -> 0.040167
B77: Adicional BVM1 Inj | D77: =C263 -> 0 | F77: =O263/(1-$N$25-$N$26)/(1-$I$24) -> 0 | G77: =ROUND(((D77*K77)/(1-$N$25-$N$26))*($N$25+$N$26),2) -> 0 | H77: =F77 -> 0 | J77: =H77*$I$24 -> 0 | K77: =K50 -> 0.04463
B78: Adicional BVM2 Inj | D78: =C269 -> 0 | F78: =O269/(1-$N$25-$N$26)/(1-$I$24) -> 0 | G78: =ROUND(((D78*K78)/(1-$N$25-$N$26))*($N$25+$N$26),2) -> 0 | H78: =F78 -> 0 | J78: =H78*$I$24 -> 0 | K78: =K51 -> 0.0275695
B79: Adicional BVM2 Inj | D79: =C270 -> 0 | F79: =O270/(1-$N$25-$N$26)/(1-$I$24) -> 0 | G79: =ROUND(((D79*K79)/(1-$N$25-$N$26))*($N$25+$N$26),2) -> 0 | H79: =F79 -> 0 | J79: =H79*$I$24 -> 0 | K79: =K52 -> 0.047262
B80: Adicional BVM2 Inj | D80: =C271 -> 0 | F80: =O271/(1-$N$25-$N$26)/(1-$I$24) -> 0 | G80: =ROUND(((D80*K80)/(1-$N$25-$N$26))*($N$25+$N$26),2) -> 0 | H80: =F80 -> 0 | J80: =H80*$I$24 -> 0 | K80: =K53 -> 0.070893
B81: Adicional BVM2 Inj | D81: =C272 -> 0 | F81: =O272/(1-$N$25-$N$26)/(1-$I$24) -> 0 | G81: =ROUND(((D81*K81)/(1-$N$25-$N$26))*($N$25+$N$26),2) -> 0 | H81: =F81 -> 0 | J81: =H81*$I$24 -> 0 | K81: =K54 -> 0.07877
B82: Adicional EH Inj | D82: =C278 -> 0 | F82: =O278/(1-$N$25-$N$26)/(1-$I$24) -> 0 | G82: =ROUND(((D82*K82)/(1-$N$25-$N$26))*($N$25+$N$26),2) -> 0 | H82: =F82 -> 0 | J82: =H82*$I$24 -> 0 | K82: =K55 -> 0.0497
B83: Adicional EH Inj | D83: =C279 -> 0 | F83: =O279/(1-$N$25-$N$26)/(1-$I$24) -> 0 | G83: =ROUND(((D83*K83)/(1-$N$25-$N$26))*($N$25+$N$26),2) -> 0 | H83: =F83 -> 0 | J83: =H83*$I$24 -> 0 | K83: =K56 -> 0.0852
B84: Adicional EH Inj | D84: =C280 -> 0 | F84: =O280/(1-$N$25-$N$26)/(1-$I$24) -> 0 | G84: =ROUND(((D84*K84)/(1-$N$25-$N$26))*($N$25+$N$26),2) -> 0 | H84: =F84 -> 0 | J84: =H84*$I$24 -> 0 | K84: =K57 -> 0.1278
B85: Adicional EH Inj | D85: =C281 -> 0 | F85: =O281/(1-$N$25-$N$26)/(1-$I$24) -> 0 | G85: =ROUND(((D85*K85)/(1-$N$25-$N$26))*($N$25+$N$26),2) -> 0 | H85: =F85 -> 0 | J85: =H85*$I$24 -> 0 | K85: =K58 -> 0.142
B87: Juros | F87: 0.46
B88: Multas | F88: 4.55
B89: CIP
B93: TOTAL | F93: =SUM(F23:F92) -> 221.14628 | G93: =SUM(G25:G92) -> 10.15 | H93: =SUM(H23:H92) -> 244.07478 | J93: =SUM(J23:J92) -> 41.492712
B95: Informativo Escassez | F95: =(D25*AK12)+(D26*AK13)+(D27*AK14)+(D28*AK15) -> 0
B97: Consumo = | G97: =D16 -> 537 | H97: kWh
B98: Energia Injetada = | G98: =D17 -> 221 | H98: kWh | J98: Doc Impr | K98: =O19 -> 241002228329
G99: =G98 -> 221 | H99: =G97-G99 -> 316
B100: Perc. de Redução da Energia Injetada | E100: TUSD | F100: 1 | G100: TE | H100: 1
B102: Fatura B1 Baixa Renda
D103: Qtde | E103: TUSD | F103: TE | G103: TUSD + TE | H103: R$
B104: Fornecimento de Energia Elétrica | H104: =SUM(H106:H135)+SUM(H138:H143) -> 198.12812
J105: Bx Ren
A106: 0.65 | B106: Consumo 0 - 30 | D106: =D25 -> 30 | E106: =$E$119*(1-A106) -> 0.1012725 | F106: =$F$119*(1-A106) -> 0.102669 | G106: =E106+F106 -> 0.2039415 | H106: =ROUND((D106*E106),2)+ROUND((D106*F106),2) -> 6.12 | J106: =IF(D16>0,30,0) -> 30
A107: 0.4 | B107: Consumo 31 - 100 | D107: =D26 -> 70 | E107: =$E$119*(1-A107) -> 0.17361 | F107: =$F$119*(1-A107) -> 0.176004 | G107: =E107+F107 -> 0.349614 | H107: =ROUND((D107*E107),2)+ROUND((D107*F107),2) -> 24.47 | J107: =IF(D16>30,IF(D16>100,70,D16-30),0) -> 70
A108: 0.1 | B108: Consumo 101 - 220 | D108: =D27 -> 120 | E108: =$E$119*(1-A108) -> 0.260415 | F108: =$F$119*(1-A108) -> 0.264006 | G108: =E108+F108 -> 0.524421 | H108: =ROUND((D108*E108),2)+ROUND((D108*F108),2) -> 62.93 | J108: =IF(D16>100,IF(D16>220,220-100,D16-100),0) -> 120
A109: 0 | B109: Consumo > 220 | D109: =D28 -> 1 | E109: =$E$119*(1-A109) -> 0.28935 | F109: =$F$119*(1-A109) -> 0.29334 | G109: =E109+F109 -> 0.58269 | H109: =ROUND((D109*E109),2)+ROUND((D109*F109),2) -> 0.58 | J109: =IF(D16>220,D16-220,0) -> 317
B111: Adicional BAM | H111: =O179 -> 3.05
B112: Adicional BVM 1 | H112: =O188 -> 0
B113: Adicional BVM 2 | H113: =O197 -> 0
B114: Adicional Escassez Hídrica | H114: =O206 -> 0
A116: 0.65 | B116: Energia Fornecida 0 - 30 | D116: =D29 -> 30 | E116: =$E$119*(1-A116) -> 0.1012725 | F116: =$F$119*(1-A116) -> 0.102669 | G116: =E116+F116 -> 0.2039415 | H116: =ROUND((D116*E116),2)+ROUND((D116*F116),2) -> 6.12
A117: 0.4 | B117: Energia Fornecida 31 - 100 | D117: =D30 -> 70 | E117: =$E$119*(1-A117) -> 0.17361 | F117: =$F$119*(1-A117) -> 0.176004 | G117: =E117+F117 -> 0.349614 | H117: =ROUND((D117*E117),2)+ROUND((D117*F117),2) -> 24.47
...

Sheet Fatura B1 BRe (GD) MP 1300 OK
B2: B1 Baixa renda | E2: Vigência das Tarifas: | F2: ='Fatura B1 (GD) OK'!F2 -> 46241 | M2: Bandeira | N2: R$/kWh | O2: ANEEL em 29/06 | Q2: TUSD FIO B
M3: VERDE | N3: 0
B4: TARIFA R$ kWh | C4: ='Fatura B1 (GD) OK'!C4:E4 -> TARIFA ANTIGA - REH 3508/2025 | F4: ='Fatura B1 (GD) OK'!F4 -> TARIFA NOVA - REH xxxx/2026 | I4: Tarifas Proporcionalizadas | M4: BAM | N4: 0.01885 | Q4: TARIFA | R4: =C4 -> TARIFA ANTIGA - REH 3508/2025 | U4: =F4 -> TARIFA NOVA - REH xxxx/2026 | X4: Tarifas Proporcionalizadas
C5: Tusd | D5: TE | E5: TUSD + TE | F5: Tusd | G5: TE | H5: TUSD + TE | I5: Tusd | J5: TE | K5: TUSD + TE | M5: BVM1 | N5: 0.04463 | R5: Tusd (R$/kWh) | U5: Tusd (R$/kWh) | X5: Tusd (R$/kWh)
B6: Baixa renda | C6: ='TABELA DE TARIFAS ANTIGAS'!G72/1000 -> 0.32543 | D6: ='TABELA DE TARIFAS ANTIGAS'!H72/1000 -> 0.28245 | E6: =C6+D6 -> 0.60788 | F6: ='TABELA DE TARIFAS NOVAS'!G74/1000 -> 0.34895 | G6: ='TABELA DE TARIFAS NOVAS'!H74/1000 -> 0.32532 | H6: =F6+G6 -> 0.67427 | I6: =((C6*$C$14)+(F6*$D$14))/($D$14+$C$14) -> 0.336406 | J6: =((D6*$C$14)+(G6*$D$14))/($D$14+$C$14) -> 0.302456 | K6: =I6+J6 -> 0.638862 | M6: BVM2 | N6: 0.07877 | Q6: =B6 -> Baixa renda | R6: ='FIO B'!H13/1000 -> 0.20383072 | U6: ='FIO B'!K13/1000 -> 0.20915159 | X6: =((R6*$C$14)+(U6*$D$14))/($D$14+$C$14) -> 0.20631379
B7: CDE Escassez Hídrica | C7: 0 | D7: -0.0044031307 | E7: 0.0036054084 | F7: =T11 -> 0 | G7: =U11 -> -0.00053182975 | H7: =F7+G7 -> -0.00053182975 | I7: =((C7*$C$14)+(F7*$D$14))/($D$14+$C$14) -> 0 | J7: =((D7*$C$14)+(G7*$D$14))/($D$14+$C$14) -> -0.0025965236 | K7: =I7+J7 -> -0.0025965236
B8: TE SCEE | G8: =G6*15% -> 0.048798 | J8: =((D8*$C$14)+(G8*$D$14))/($D$14+$C$14) -> 0.0227724 | M8: Escassez Hídrica | N8: 0.142
P9: NOVO | X9: ANTIGO | AF9: PROPORCIONAL
H10: Fatura | L10: Vigência das Tarifas (troca Bandeira): | M10: =EOMONTH(B14,0)+1 -> 46235 | P10: CUSTO | R10: Part. TUSD (%) | S10: Part. TE (%) | T10: Tusd (R$/kWh) | U10: TE (R$/kWh) | X10: CUSTO | Z10: Part. TUSD (%) | AA10: Part. TE (%) | AB10: Tusd (R$/kWh) | AC10: TE (R$/kWh) | AF10: CUSTO | AH10: Part. TUSD (%) | AI10: Part. TE (%) | AJ10: Tusd (R$/kWh) | AK10: TE (R$/kWh)
B11: INSTALAÇÃO | C11: 191127 | H11: =E14 -> 46254 | K11: Altere a bandeira na célula abaixo | P11: CDE ESCASSEZ HÍDRICA | T11: 0 | U11: =-0.531829748712515/1000 -> -0.00053182975 | X11: CDE ESCASSEZ HÍDRICA | AB11: 0 | AC11: 0.00120041 | AF11: CDE ESCASSEZ HÍDRICA | AJ11: =((T11*$C$14)+(AB11*$D$14))/($D$14+$C$14) -> 0 | AK11: =((U11*$D$14)+(AC11*$C$14))/($D$14+$C$14) -> 0.00039203145
K12: BAM | L12: BAM | P12: 0 - 80 | Q12: 1 | U12: =$U$11*(1-Q12) -> 0 | W12: =((T12*$C$14)+(U12*$D$14))/($D$14+$C$14) -> 0 | X12: 0 - 30 | Y12: 0.65 | AC12: =$AC$11*(1-Y12) -> 0.0004201435 | AE12: =((AB12*$C$13)+(AC12*$D$13))/($D$13+$C$13) -> #VALUE! | AF12: 0 - 80 | AG12: 1 | AK12: =$AK$11*(1-AG12) -> 0
B13: Leitura Anterior | C13: Nº de dias tarifa Anterior | D13: Nº de dias tarifa Nova | E13: Leitura Atual | J13: Leitura Anterior | K13: Nº de dias tarifa Anterior | L13: Nº de dias tarifa Nova | M13: Leitura Atual | P13: >80 | Q13: 0 | U13: =$U$11*(1-Q13) -> -0.00053182975 | W13: =((#REF!*$C$14)+(#REF!*$D$14))/($D$14+$C$14) -> #REF! | X13: 31- 100 | Y13: 0.4 | AC13: =$AC$11*(1-Y13) -> 0.000720246 | AE13: =((AB15*$C$13)+(AC15*$D$13))/($D$13+$C$13) -> #VALUE! | AF13: >80 | AG13: 0 | AK13: =$AK$11*(1-AG13) -> 0.00039203145
B14: 46224 | C14: =IF((F2-B14-1)<0,0,(F2-B14-1)) -> 16 | D14: =E14-F2+1 -> 14 | E14: 46254 | J14: =B14 -> 46224 | K14: =IF((M10-J14-1)<0,0,(M10-J14-1)) -> 10 | L14: =M14-M10+1 -> 20 | M14: =E14 -> 46254 | W14: =((#REF!*$C$14)+(#REF!*$D$14))/($D$14+$C$14) -> #REF! | X14: 101 - 220 | Y14: 0.1 | AC14: =$AC$11*(1-Y14) -> 0.001080369
W15: =((T13*$C$13)+(U13*$D$13))/($D$13+$C$13) -> #VALUE! | X15: >220 | Y15: 0 | AC15: =$AC$11*(1-Y15) -> 0.00120041
B16: CONSUMO | D16: 444
B17: INJEÇÃO | D17: 364
M18: Documento impressão: | O18: 1025311206
B20: Descrição | C20: Unidade | D20: Quantidade | E20: Preço Unit (R$) com tributos | F20: Valor Total (R$) | G20: PIS/COFINS (R$) | H20: Base de Cálculo ICMS (R$) | I20: Alíquota ICMS (%) | J20: ICMS (R$) | K20: Preço Unit (R$) | L20: Tributos | M20: Base de Cálc (R$) | N20: Alíquota (%) | O20: Valor (R$) | Q20: TUSD Fio B | R20: Receita Fio B
B22: Desconto Bx renda | D22: =-K109 -> -52.61836 | E22: 1 | F22: =D22*E22 -> -52.61836 | G22: 0 | H22: 0 | I22: 0 | J22: 0 | K22: 1 | L22: PIS | M22: =D82 -> 255.14228 | N22: ='Fatura B1 (GD) OK'!N21 -> 0.011 | O22: =ROUND(M22*N22,2) -> 2.81 | Q22: =IF(AND($B$14<$F$2,$E$14<$F$2),R6,IF($B$14<$F$2,X6,U6)) -> 0.20631379 | R22: =D65*Q22 -> 75.098221 | S22: não está considerando energia injetada
B23: Valor Bx Renda | D23: =D22 -> -52.61836 | E23: =K23/(1-$N$22-$N$23)/(1-$I$23) -> 1.2840448 | F23: =-1*(F22-J23) -> 64.10356 | G23: 0 | H23: =ROUND((K109*K23)/(1-$N$22-$N$23)/(1-$I$23),2) -> 67.56 | I23: 0.17 | J23: =H23*$I$23 -> 11.4852 | K23: 1 | L23: COFINS | M23: =M22 -> 255.14228 | N23: ='Fatura B1 (GD) OK'!N23 -> 0.0507 | O23: =ROUND(M23*N23,2) -> 12.94 | Q23: =IF(AND($B$14<$F$2,$E$14<$F$2),R6,IF($B$14<$F$2,X6,U6))*(1-A65) -> 0.20631379 | R23: =D66*Q23 -> 16.505104
A24: 1 | B24: TUSD - EAF 0 a 80 | C24: kWh | D24: =IF(D16>0,80,0) -> 80 | E24: =K24/(1-$N$22-$N$23)/(1-$I$23) -> 0 | F24: =ROUND(D24*E24,2) -> 0 | G24: =ROUND(((D24*K24)/(1-$N$22-$N$23))*($N$22+$N$23),2) -> 0 | H24: =ROUND((D24*K24)/(1-$N$22-$N$23)/(1-$I$23),2) -> 0 | J24: =H24*$I$23 -> 0 | K24: =K25*(1-A24) -> 0 | R24: =SUM(R22:R23) -> 91.603325
A25: 0 | B25: TUSD - EAF > 80 | C25: kWh | D25: =IF(D16>80,D16-80,0) -> 364 | E25: =K25/(1-$N$22-$N$23)/(1-$I$23) -> 0.43196039 | F25: =ROUND(D25*E25,2) -> 157.23 | G25: =ROUND(((D25*K25)/(1-$N$22-$N$23))*($N$22+$N$23),2) -> 8.05 | H25: =ROUND((D25*K25)/(1-$N$22-$N$23)/(1-$I$23),2) -> 157.23 | J25: =H25*$I$23 -> 26.7291 | K25: =IF(AND($B$14<$F$2,$E$14<$F$2),C6,IF($B$14<$F$2,I6,F6)) -> 0.336406
B26: TE - EAF 0 a 80 | C26: kWh | D26: =D24 -> 80 | E26: =K26/(1-$N$22-$N$23)/(1-$I$23) -> 0 | F26: =ROUND(D26*E26,2) -> 0 | G26: =ROUND(((D26*K26)/(1-$N$22-$N$23))*($N$22+$N$23),2) -> 0 | H26: =ROUND((D26*K26)/(1-$N$22-$N$23)/(1-$I$23),2) -> 0 | J26: =H26*$I$23 -> 0 | K26: =K27*(1-A24) -> 0
B27: TE - EAF > 80 | C27: kWh | D27: =D25 -> 364 | E27: =K27/(1-$N$22-$N$23)/(1-$I$23) -> 0.38836707 | F27: =ROUND(D27*E27,2) -> 141.37 | G27: =ROUND(((D27*K27)/(1-$N$22-$N$23))*($N$22+$N$23),2) -> 7.24 | H27: =ROUND((D27*K27)/(1-$N$22-$N$23)/(1-$I$23),2) -> 141.37 | J27: =H27*$I$23 -> 24.0329 | K27: =IF(AND($B$14<$F$2,$E$14<$F$2),D6,IF($B$14<$F$2,J6,G6)) -> 0.302456
B29: Adicional BAM | D29: =C115 -> 80 | E29: =K29/(1-$N$22-$N$23)/(1-$I$23) -> 0 | F29: =ROUND(D29*E29,2) -> 0 | G29: =ROUND(((D29*K29)/(1-$N$22-$N$23))*($N$22+$N$23),2) -> 0 | H29: =F29 -> 0 | J29: =H29*$I$23 -> 0 | K29: =K115 -> 0
B30: Adicional BAM | D30: =C116 -> 364 | E30: =K30/(1-$N$22-$N$23)/(1-$I$23) -> 0.024204245 | F30: =ROUND(D30*E30,2) -> 8.81 | G30: =ROUND(((D30*K30)/(1-$N$22-$N$23))*($N$22+$N$23),2) -> 0.45 | H30: =F30 -> 8.81 | J30: =H30*$I$23 -> 1.4977 | K30: =K116 -> 0.01885
B31: Adicional BVM1 | D31: =C122 -> 0 | E31: =K31/(1-$N$22-$N$23)/(1-$I$23) -> 0 | F31: =ROUND(D31*E31,2) -> 0 | G31: =ROUND(((D31*K31)/(1-$N$22-$N$23))*($N$22+$N$23),2) -> 0 | H31: =F31 -> 0 | J31: =H31*$I$23 -> 0 | K31: =K122 -> 0
B32: Adicional BVM1 | D32: =C123 -> 0 | E32: =K32/(1-$N$22-$N$23)/(1-$I$23) -> 0.057306921 | F32: =ROUND(D32*E32,2) -> 0 | G32: =ROUND(((D32*K32)/(1-$N$22-$N$23))*($N$22+$N$23),2) -> 0 | H32: =F32 -> 0 | J32: =H32*$I$23 -> 0 | K32: =K123 -> 0.04463
B33: Adicional BVM2 | D33: =C129 -> 0 | E33: =K33/(1-$N$22-$N$23)/(1-$I$23) -> 0 | F33: =ROUND(D33*E33,2) -> 0 | G33: =ROUND(((D33*K33)/(1-$N$22-$N$23))*($N$22+$N$23),2) -> 0 | H33: =F33 -> 0 | J33: =H33*$I$23 -> 0 | K33: =K129 -> 0
B34: Adicional BVM2 | D34: =C130 -> 0 | E34: =K34/(1-$N$22-$N$23)/(1-$I$23) -> 0.10114421 | F34: =ROUND(D34*E34,2) -> 0 | G34: =ROUND(((D34*K34)/(1-$N$22-$N$23))*($N$22+$N$23),2) -> 0 | H34: =F34 -> 0 | J34: =H34*$I$23 -> 0 | K34: =K130 -> 0.07877
B35: Adicional EH | D35: =C136 -> 0 | E35: =K35/(1-$N$22-$N$23)/(1-$I$23) -> 0 | F35: =ROUND(D35*E35,2) -> 0 | G35: =ROUND(((D35*K35)/(1-$N$22-$N$23))*($N$22+$N$23),2) -> 0 | H35: =F35 -> 0 | J35: =H35*$I$23 -> 0 | K35: =K136 -> 0
B36: Adicional EH | D36: =C137 -> 0 | E36: =K36/(1-$N$22-$N$23)/(1-$I$23) -> 0.18233437 | F36: =ROUND(D36*E36,2) -> 0 | G36: =ROUND(((D36*K36)/(1-$N$22-$N$23))*($N$22+$N$23),2) -> 0 | H36: =F36 -> 0 | J36: =H36*$I$23 -> 0 | K36: =K137 -> 0.142
A38: 0 | B38: TUSD - EAF Inj | C38: kWh | D38: =-D17 -> -364 | E38: =K38/(1-$N$22-$N$23)/(1-$I$38) -> 0.35852712 | F38: =ROUND(D38*E38,2) -> -130.5 | G38: =ROUND(((D38*K38)/(1-$N$22-$N$23))*($N$22+$N$23),2) -> -8.05 | H38: =ROUND((D38*K38)/(1-$N$22-$N$23)/(1-$I$38),2)*0 -> 0 | I38: 0 | J38: =H38*$I$23 -> 0 | K38: =IF(AND($B$14<$F$2,$E$14<$F$2),C6,IF($B$14<$F$2,I6,F6)) -> 0.336406 | L38: PIS Inj | M38: =D83 -> -255.14228 | N38: =N22 -> 0.011 | O38: =ROUND(M38*N38,2) -> -2.81
B39: TE - EAF Inj | C39: kWh | D39: =D38 -> -364 | E39: =K39/(1-$N$22-$N$23)/(1-$I$23) -> 0.38836707 | F39: =ROUND(D39*E39,2) -> -141.37 | G39: =ROUND(((D39*K39)/(1-$N$22-$N$23))*($N$22+$N$23),2) -> -7.24 | H39: =ROUND((D39*K39)/(1-$N$22-$N$23)/(1-$I$23),2) -> -141.37 | J39: =H39*$I$23 -> -24.0329 | K39: =IF(AND($B$14<$F$2,$E$14<$F$2),D6,IF($B$14<$F$2,J6,G6)) -> 0.302456 | L39: COFINS Inj | M39: =M38 -> -255.14228 | N39: =N23 -> 0.0507 | O39: =ROUND(M39*N39,2) -> -12.94
B41: Adicional BAM Inj | D41: =C145 -> -364 | E41: =K41/(1-$N$22-$N$23)/(1-$I$23) -> 0.024204245 | F41: =ROUND(D41*E41,2) -> -8.81 | G41: =ROUND(((D41*K41)/(1-$N$22-$N$23))*($N$22+$N$23),2) -> -0.45 | H41: =F41 -> -8.81 | J41: =H41*$I$23 -> -1.4977 | K41: =K30 -> 0.01885
B42: Adicional BVM1 Inj | D42: =C151 -> 0 | E42: =K42/(1-$N$22-$N$23)/(1-$I$23) -> 0.057306921 | F42: =ROUND(D42*E42,2) -> 0 | G42: =ROUND(((D42*K42)/(1-$N$22-$N$23))*($N$22+$N$23),2) -> 0 | H42: =F42 -> 0 | J42: =H42*$I$23 -> 0 | K42: =K32 -> 0.04463
B43: Adicional BVM2 Inj | D43: =C157 -> 0 | E43: =K43/(1-$N$22-$N$23)/(1-$I$23) -> 0.10114421 | F43: =ROUND(D43*E43,2) -> 0 | G43: =ROUND(((D43*K43)/(1-$N$22-$N$23))*($N$22+$N$23),2) -> 0 | H43: =F43 -> 0 | J43: =H43*$I$23 -> 0 | K43: =K34 -> 0.07877
B44: Adicional EH Inj | D44: =C163 -> 0 | E44: =K44/(1-$N$22-$N$23)/(1-$I$23) -> 0.18233437 | F44: =ROUND(D44*E44,2) -> 0 | G44: =ROUND(((D44*K44)/(1-$N$22-$N$23))*($N$22+$N$23),2) -> 0 | H44: =F44 -> 0 | J44: =H44*$I$23 -> 0 | K44: =K36 -> 0.142
B46: Juros
B47: Multas | F47: -5.83
B48: CIP
B52: TOTAL | F52: =SUM(F22:F51) -> 32.3852 | G52: =SUM(G24:G51) -> -7.2164497e-16 | H52: =SUM(H22:H51) -> 224.79 | J52: =SUM(J22:J51) -> 38.2143
B54: Informativo Escassez | F54: =(D24*AK12)+(D25*AK13)+(D38*AK13) -> 0
B56: Consumo = | G56: =D16 -> 444 | H56: kWh
B57: Energia Injetada = | G57: =D17 -> 364 | H57: kWh | J57: Doc Impr | K57: =O18 -> 1025311206
G58: =G57 -> 364 | H58: =G56-G58 -> 80
B59: Perc. de Redução da Energia Injetada | E59: TUSD | F59: 1 | G59: TE | H59: 1 | J59: Bx Ren
J60: =IF(D16>0,80,0) -> 80
B61: Fatura B1 Baixa Renda | J61: =IF(D16>80,D16-80,0) -> 364
D62: Qtde | E62: TUSD | F62: TE | G62: TUSD + TE | H62: R$
B63: Fornecimento de Energia Elétrica | H63: =SUM(H65:H79)+SUM(H82:H87) -> 1.3322676e-14
A65: 0 | B65: Consumo > 80 | D65: =D25 -> 364 | E65: =IF(AND($B$14<$F$2,$E$14<$F$2),C6,IF($B$14<$F$2,I6,F6)) -> 0.336406 | F65: =IF(AND($B$14<$F$2,$E$14<$F$2),D6,IF($B$14<$F$2,J6,G6)) -> 0.302456 | G65: =E65+F65 -> 0.638862 | H65: =ROUND((D65*E65),2)+ROUND((D65*F65),2) -> 232.54
A66: 1 | B66: Consumo <80 | D66: =D24 -> 80 | E66: 0 | F66: 0 | G66: 0 | H66: 0
B68: Adicional BAM | H68: =O117 -> 6.86
B69: Adicional BVM 1 | H69: =O124 -> 0
B70: Adicional BVM 2 | H70: =O131 -> 0
B71: Adicional Escassez Hídrica | H71: =O138 -> 0
A73: 0 | B73: Energia Injetada | D73: =D38 -> -364 | E73: =IF(AND($B$14<$F$2,$E$14<$F$2),C6,IF($B$14<$F$2,I6,F6)) -> 0.336406 | F73: =IF(AND($B$14<$F$2,$E$14<$F$2),D6,IF($B$14<$F$2,J6,G6)) -> 0.302456 | G73: =E73+F73 -> 0.638862 | H73: =ROUND((D73*E73),2)+ROUND((D73*F73),2) -> -232.54
B75: Adicional BAM | H75: =O146 -> -6.86 | J75: =-(IF(D17>0,30,0)) -> -30
B76: Adicional BVM 1 | H76: =O152 -> 0 | J76: =-(IF(D17>30,IF(D17>100,70,D17-30),0)) -> -70
B77: Adicional BVM 2 | H77: =O158 -> 0 | J77: =-(IF(D17>100,IF(D17>220,220-100,D17-100),0)) -> -120
B78: Adicional Escassez Hídrica | H78: =O164 -> 0 | J78: =-(IF(D17>220,D17-220,0)) -> -144
D81: Base de Cálculo
B82: PIS | D82: =SUM(H65:H71)/(1-E82-E84) -> 255.14228 | E82: =N22 -> 0.011 | H82: =D82*E82 -> 2.8065651
B83: PIS Eneg Inj | D83: =SUM(H73:H78)/(1-E82-E84) -> -255.14228 | E83: =E82 -> 0.011 | H83: =D83*E83 -> -2.8065651
B84: COFINS | D84: =D82 -> 255.14228 | E84: =N23 -> 0.0507 | H84: =D84*E84 -> 12.935714
B85: COFINS Eneg Inj | D85: =D83 -> -255.14228 | E85: =E84 -> 0.0507 | H85: =D85*E85 -> -12.935714
B86: ICMS | D86: =D82/(1-E86) -> 307.40034 | E86: 0.17 | H86: =D86*E86 -> 52.258057
B87: ICMS Eneg Inj | D87: =D83/(1-E87) -> -307.40034 | E87: =E86 -> 0.17 | H87: =D87*E87 -> -52.258057
B88: ICMS Desc Tarifa Social | D88: =K109 -> 52.61836 | E88: =E87 -> 0.17 | H88: =D88*E88 -> 8.9451212 | I88: Não está considerando bandeira no cálculo do ICMS
B89: Informativo Escassez Hídrica | D89: =D67+D73+D65+D68 -> 0 | E89: =IF(AND($B$14<$F$2,$E$14<$F$2),#REF!,IF($B$14<$F$2,#REF!,#REF!)) -> #REF! | F89: =IF(AND($B$14<$F$2,$E$14<$F$2),#REF!,IF($B$14<$F$2,#REF!,#REF!)) -> #REF! | H89: =((D89)*(E89+F89)+D34*(E89+F89)*-H28)+D53*(E89+F89)*-H28 -> #REF!
B91: Benefício Tarifa Social | H91: =K108 -> 51.10896 | I91: (mensagem na fatura)
B92: Consumo Bx Renda | C92: BAM | D92: =O117 -> 6.86
C93: BVM1 | D93: =O124 -> 0 | F93: Memória benefício Tarifa Social
C94: BVM2 | D94: =O131 -> 0 | I94: TUSD X | J94: TE
C95: EH | D95: =O138 -> 0 | F95: Consumo B1 | G95: B1 Baixa Renda | H95: =D16 -> 444 | I95: =E65 -> 0.336406 | J95: =F65 -> 0.302456 | K95: =H95*(I95+J95) -> 283.65473
G96: BAM | H96: =IF($K$12=M4,($H$95*($K$14)/($K$14+$L$14)),0)+IF($L$12=M4,($H$95*($L$14)/($K$14+$L$14)),0) -> 444 | J96: =N4 -> 0.01885 | K96: =H96*(I96+J96) -> 8.3694
G97: BVM1 | H97: =IF($K$12=M5,($H$95*($K$14)/($K$14+$L$14)),0)+IF($L$12=M5,($H$95*($L$14)/($K$14+$L$14)),0) -> 0 | J97: =N5 -> 0.04463 | K97: =H97*(I97+J97) -> 0
G98: BVM2 | H98: =IF($K$12=M6,($H$95*($K$14)/($K$14+$L$14)),0)+IF($L$12=M6,($H$95*($L$14)/($K$14+$L$14)),0) -> 0 | J98: =N6 -> 0.07877 | K98: =H98*(I98+J98) -> 0 | N98: Energia Injetada Normal
G99: Escassez Hídrica | H99: =IF($K$12=M8,($H$95*($K$14)/($K$14+$L$14)),0)+IF($L$12=M8,($H$95*($L$14)/($K$14+$L$14)),0) -> 0 | J99: =N8 -> 0.142 | K99: =H99*(I99+J99) -> 0 | N99: =-D17 -> -364 | O99: 0.28935 | P99: 0.29334 | Q99: =N99*(O99+P99) -> -212.09916
K100: =SUM(K95:K99) -> 292.02413 | M100: BAM | N100: =IF($K$12=M4,($N$99*($K$14)/($K$14+$L$14)),0)+IF($L$12=M4,($N$99*($L$14)/($K$14+$L$14)),0) -> -364 | P100: 0.01885 | Q100: =N100*(O100+P100) -> -6.8614
M101: BVM1 | N101: =IF($K$12=M5,($N$99*($K$14)/($K$14+$L$14)),0)+IF($L$12=M5,($N$99*($L$14)/($K$14+$L$14)),0) -> 0 | P101: 0.04463 | Q101: =N101*(O101+P101) -> 0
B102: Energia Injetada | C102: BAM | D102: =O146 -> -6.86 | F102: Consumo BR | G102: 0 | H102: =D25 -> 364 | I102: =E65 -> 0.336406 | J102: =F65 -> 0.302456 | K102: =H102*(I102+J102) -> 232.54577 | M102: BVM2 | N102: =IF($K$12=M6,($N$99*($K$14)/($K$14+$L$14)),0)+IF($L$12=M6,($N$99*($L$14)/($K$14+$L$14)),0) -> 0 | P102: 0.07877 | Q102: =N102*(O102+P102) -> 0
C103: BVM1 | D103: =O152 -> 0 | G103: 1 | H103: =D24 -> 80 | I103: 0 | J103: 0 | K103: =H103*(I103+J103) -> 0 | M103: Escassez Hídrica | N103: =IF($K$12=M7,($N$99*($K$14)/($K$14+$L$14)),0)+IF($L$12=M7,($N$99*($L$14)/($K$14+$L$14)),0) -> 0 | P103: 0.142 | Q103: =N103*(O103+P103) -> 0
C104: BVM2 | D104: =O158 -> 0 | Q104: =SUM(Q99:Q103) -> -218.96056
C105: EH | D105: =O164 -> 0 | K105: =SUM(K102:K104) -> 232.54577 | L105: =K105+SUM(D92:D95) -> 239.40577
G108: PIS | H108: =(K108+K96+K97+K98+K99)/(1-E82-E84) -> 63.389492 | J108: Benefício Tarifa Social | K108: =K95-K105 -> 51.10896 | L108: sem considerar as bandeiras
G109: COFINS | H109: =H108 -> 63.389492 | J109: Com tributos | K109: =K100-L105 -> 52.61836 | L109: considerando as bandeiras no cálculo dos tributos
G110: ICMS | H110: =H108/(1-E86) -> 76.372881
B111: Consumo - Adicional de Bandeira
B112: BAM | K112: =N4 -> 0.01885
C113: Consumo | J113: Tarifas | M113: Receita | O113: Receita Total
C114: KWh | K114: TE | M114: Tusd | N114: TE | O114: Tusd+TE
C115: =IF($K$12=$B$112,(D66/($K$14+$L$14)*($K$14)),0)+IF($L$12=$B$112,(D66/($K$14+$L$14)*($L$14)),0) -> 80 | K115: =$K$112*(1-Q115) -> 0 | N115: =ROUND((C115*K115),2) -> 0 | O115: =M115+N115 -> 0 | Q115: 1
C116: =IF($K$12=$B$112,(D65/($K$14+$L$14)*($K$14)),0)+IF($L$12=$B$112,(D65/($K$14+$L$14)*($L$14)),0) -> 364 | K116: =$K$112*(1-Q116) -> 0.01885 | N116: =ROUND((C116*K116),2) -> 6.86 | O116: =M116+N116 -> 6.86 | Q116: 0
C117: TOTAL | O117: =SUM(O115:O116) -> 6.86
B119: BVM1 | K119: =N5 -> 0.04463
C120: Consumo | J120: Tarifas Proporcionalizadas | M120: Receita | O120: Receita Total
C121: KWh | G121: Tusd | H121: TE | J121: Tusd | K121: TE | M121: Tusd | N121: TE | O121: Tusd+TE
C122: =IF($K$12=$B$119,(D66/($K$14+$L$14)*($K$14)),0)+IF($L$12=$B$119,(D66/($K$14+$L$14)*($L$14)),0) -> 0 | K122: =$K$119*(1-Q122) -> 0 | N122: =ROUND((C122*K122),2) -> 0 | O122: =M122+N122 -> 0 | Q122: 1
...

Sheet V4 MMGD GDII
B2: A4 Verde | C2: MMGD | E2: Vigência das Tarifas: | F2: ='[5]A2 Azul'!F2 -> 45145 | I2: OK | M2: Bandeira | N2: R$/kWh | Q2: TUSD FIO B
M3: VERDE | N3: =[5]BANDEIRA!$D$4 -> 0
B4: TARIFA | C4: ='[5]A2 Azul'!C4:E4 -> TARIFA ANTIGA - REH 3091/2022 | F4: ='[5]A2 Azul'!F4:H4 -> TARIFA NOVA - REH 3241/2023 | I4: Tarifas Proporcionalizadas | M4: BAM | N4: =[5]BANDEIRA!$D$5 -> 0.02989 | Q4: TARIFA | R4: =C4 -> TARIFA ANTIGA - REH 3091/2022 | U4: =F4 -> TARIFA NOVA - REH 3241/2023 | X4: Tarifas Proporcionalizadas
C5: Tusd (R$/kW) | D5: Tusd (R$/kWh) | E5: TE (R$/kWh) | F5: Tusd (R$/kW) | G5: Tusd (R$/kWh) | H5: TE (R$/kWh) | I5: Tusd (R$/kW) | J5: Tusd (R$/kWh) | K5: TE (R$/kWh) | M5: BVM1 | N5: =[5]BANDEIRA!$D$6 -> 0.065 | R5: Tusd (R$/kW) | S5: Tusd (R$/kW) | U5: Tusd (R$/kW) | V5: Tusd (R$/kW) | X5: Tusd (R$/kW) | Y5: Tusd (R$/kW)
B6: A4 Verde P | C6: ='[5]TABELA DE TARIFAS ANTIGAS'!E52 -> 30.44 | D6: ='[5]TABELA DE TARIFAS ANTIGAS'!F53/1000 -> 1.24002 | E6: ='[5]TABELA DE TARIFAS ANTIGAS'!G53/1000 -> 0.4226 | F6: ='[5]TABELA DE TARIFAS NOVAS'!E52 -> 31.53 | G6: ='[5]TABELA DE TARIFAS NOVAS'!F53/1000 -> 1.26783 | H6: ='[5]TABELA DE TARIFAS NOVAS'!G53/1000 -> 0.45803 | I6: =((C6*$C$17)+(F6*$D$17))/($D$17+$C$17) -> 31.319032 | J6: =((D6*$C$17)+(G6*$D$17))/($D$17+$C$17) -> 1.2624474 | K6: =((E6*$C$17)+(H6*$D$17))/($D$17+$C$17) -> 0.45117258 | M6: BVM2 | N6: =[5]BANDEIRA!$D$7 -> 0.09795 | Q6: =B6 -> A4 Verde P | R6: ='[5]Grupo A_FIO B'!F49 -> 26.16 | S6: ='[5]Grupo A_FIO B'!G50/1000 -> 0.93588 | U6: ='[5]Grupo A_FIO B'!I49 -> 24.04 | V6: ='[5]Grupo A_FIO B'!J50/1000 -> 0.86024 | X6: =((R6*$C$17)+(U6*$D$17))/($D$17+$C$17) -> 24.450323 | Y6: =((S6*$C$17)+(V6*$D$17))/($D$17+$C$17) -> 0.87488
B7: A4 Verde FP | D7: ='[5]TABELA DE TARIFAS ANTIGAS'!F54/1000 -> 0.13433 | E7: ='[5]TABELA DE TARIFAS ANTIGAS'!G54/1000 -> 0.2638 | G7: ='[5]TABELA DE TARIFAS NOVAS'!F54/1000 -> 0.12117 | H7: ='[5]TABELA DE TARIFAS NOVAS'!G54/1000 -> 0.29041 | J7: =((D7*$C$17)+(G7*$D$17))/($D$17+$C$17) -> 0.1237171 | K7: =((E7*$C$17)+(H7*$D$17))/($D$17+$C$17) -> 0.28525968 | M7: Escassez Hídrica | N7: =[5]BANDEIRA!$D$8 -> 0.142 | Q7: =B7 -> A4 Verde FP
B8: B1 | D8: ='[5]TABELA DE TARIFAS ANTIGAS'!G71/1000 -> 0.39681 | E8: ='[5]TABELA DE TARIFAS ANTIGAS'!H71/1000 -> 0.27703 | G8: ='[5]TABELA DE TARIFAS NOVAS'!G71/1000 -> 0.39253 | H8: ='[5]TABELA DE TARIFAS NOVAS'!H71/1000 -> 0.3056 | J8: =((D8*$C$17)+(G8*$D$17))/($D$17+$C$17) -> 0.39335839 | K8: =((E8*$C$17)+(H8*$D$17))/($D$17+$C$17) -> 0.30007032
B9: TE SCEE P | H9: =H6*15% -> 0.0687045 | K9: =((D9*$C$17)+(H9*$D$17))/($D$17+$C$17) -> 0.055406855
B10: TE SCEE FP | H10: =H7*15% -> 0.0435615 | K10: =((D10*$C$17)+(H10*$D$17))/($D$17+$C$17) -> 0.035130242
B12: MMGD
H13: Fatura | L13: Vigência das Tarifas (troca Bandeira): | M13: =EOMONTH(B17,0)+1 -> 45139
B14: INSTALAÇÃO | C14: 1175387 | H14: =E17 -> 45169 | K14: Altere a bandeira na célula abaixo
K15: VERDE | L15: VERDE
B16: Leitura Anterior | C16: Nº de dias tarifa Anterior | D16: Nº de dias tarifa Nova | E16: Leitura Atual | J16: Leitura Anterior | K16: Nº de dias tarifa Anterior | L16: Nº de dias tarifa Nova | M16: Leitura Atual
B17: 45138 | C17: =IF((F2-B17-1)<0,0,(F2-B17-1)) -> 6 | D17: =E17-F2+1 -> 25 | E17: 45169 | J17: =B17 -> 45138 | K17: =IF((M13-J17-1)<0,0,(M13-J17-1)) -> 0 | L17: =M17-M13+1 -> 31 | M17: =E17 -> 45169
B19: Perc. de Redução da Energia Injetada | E19: TUSD P | F19: 0.8868 | G19: TE P | H19: 1
E20: TUSD FP | F20: 1 | G20: TE FP | H20: 1
B22: Fatura A4 Verde - MMGD | J22: Documento impressão:
D23: Qtde | E23: TUSD | F23: TE | G23: TUSD + TE | H23: R$
J24: TUSD Fio B | K24: Receita Fio B
B25: Consumo Ponta | D25: 1290.8358 | E25: =IF(AND($B$17<$F$2,$E$17<$F$2),D6,IF($B$17<$F$2,J6,G6)) -> 1.2624474 | F25: =IF(AND($B$17<$F$2,$E$17<$F$2),E6,IF($B$17<$F$2,K6,H6)) -> 0.45117258 | G25: =E25+F25 -> 1.71362 | H25: =ROUND((D25*E25),2)+ROUND((D25*F25),2) -> 2212 | J25: =IF(AND($B$17<$F$2,$E$17<$F$2),S6,IF($B$17<$F$2,Y6,V6)) -> 0.87488 | K25: =D25*J25 -> 1129.3264
B26: Consumo Fora Ponta | D26: 12358.327 | E26: =IF(AND($B$17<$F$2,$E$17<$F$2),D7,IF($B$17<$F$2,J7,G7)) -> 0.1237171 | F26: =IF(AND($B$17<$F$2,$E$17<$F$2),E7,IF($B$17<$F$2,K7,H7)) -> 0.28525968 | G26: =E26+F26 -> 0.40897677 | H26: =ROUND((D26*E26),2)+ROUND((D26*F26),2) -> 5054.27
B28: Adicional BAM | D28: =IF($K$15=$M$4,((D25+D26)*(K17)/(K17+L17)),0)+IF($L$15=$M$4,((D25+D26)*(L17)/(K17+L17)),0) -> 0 | F28: =N4 -> 0.02989 | H28: =ROUND(D28*(E28+F28),2) -> 0
B29: Adicional BVM 1 | D29: =IF($K$15=$M$5,((D25+D26)*(K17)/(K17+L17)),0)+IF($L$15=$M$5,((D25+D26)*(L17)/(K17+L17)),0) -> 0 | F29: =N5 -> 0.065 | H29: =ROUND(D29*(E29+F29),2) -> 0
B30: Adicional BVM 2 | D30: =IF($K$15=$M$6,((D25+D26)*(K17)/(K17+L17)),0)+IF($L$15=$M$6,((D25+D26)*(L17)/(K17+L17)),0) -> 0 | F30: =N6 -> 0.09795 | H30: =ROUND(D30*(E30+F30),2) -> 0
B31: Adic. Escassez Hídrica | D31: =IF($K$15=$M$7,((D25+D26)*(K17)/(K17+L17)),0)+IF($L$15=$M$7,((D25+D26)*(L17)/(K17+L17)),0) -> 0 | F31: =N7 -> 0.142 | H31: =ROUND(D31*(E31+F31),2) -> 0
B33: Energ Injetada Ponta | D33: 0 | E33: =-E25 -> -1.2624474 | F33: =-F25 -> -0.45117258 | H33: =ROUND(D33*(E33+F33),2) -> 0
B34: Energ Injetada Fora Ponta | D34: -1422.72 | E34: =-E26 -> -0.1237171 | F34: =-F26 -> -0.28525968 | H34: =ROUND(D34*(E34+F34),2) -> 581.86
B36: Adicional BAM | D36: =IF($K$15=$M$4,((D33+D34)*(K17)/(K17+L17)),0)+IF($L$15=$M$4,((D33+D34)*(L17)/(K17+L17)),0) -> 0 | F36: =-F28 -> -0.02989 | H36: =ROUND(D36*(E36+F36),2) -> 0
B37: Adicional BVM 1 | D37: =IF($K$15=$M$5,((D33+D34)*(K17)/(K17+L17)),0)+IF($L$15=$M$5,((D33+D34)*(L17)/(K17+L17)),0) -> 0 | F37: =-F29 -> -0.065 | H37: =ROUND(D37*(E37+F37),2) -> 0
B38: Adicional BVM 2 | D38: =IF($K$15=$M$6,((D33+D34)*(K17)/(K17+L17)),0)+IF($L$15=$M$6,((D33+D34)*(L17)/(K17+L17)),0) -> 0 | F38: =-F30 -> -0.09795 | H38: =ROUND(D38*(E38+F38),2) -> 0
B39: Adic. Escassez Hídrica | D39: =IF($K$15=$M$7,((D33+D34)*(K17)/(K17+L17)),0)+IF($L$15=$M$7,((D33+D34)*(L17)/(K17+L17)),0) -> 0 | F39: =-F31 -> -0.142 | H39: =ROUND(D39*(E39+F39),2) -> 0
J40: TUSD Fio B | K40: Receita Fio B | L40: EUSD B
B41: Demanda | D41: 100.86 | E41: =IF(AND($B$17<$F$2,$E$17<$F$2),C6,IF($B$17<$F$2,I6,F6)) -> 31.319032 | H41: =ROUND(D41*(E41+F41),2) -> 3158.84 | J41: =IF(AND($B$17<$F$2,$E$17<$F$2),R6,IF($B$17<$F$2,X6,U6)) -> 24.450323 | K41: =D41*J41 -> 2466.0595 | L41: =K41+K44+K47 -> 2567.2839
B44: Demanda não utilizada | D44: 4.14 | E44: =E41 -> 31.319032 | H44: =ROUND(D44*(E44+F44),2) -> 129.66 | J44: =J41 -> 24.450323 | K44: =D44*J44 -> 101.22434
B47: Ultrap Demanda | D47: 0 | E47: =E41*2 -> 62.638065 | H47: =ROUND(D47*(E47+F47),2) -> 0
B49: Energia Comp. P SCEE | D49: =-D33 -> 0 | E49: =E25 -> 1.2624474 | F49: =IF(AND($B$17<$F$2,$E$17<$F$2),D9,IF($B$17<$F$2,K9,H9)) -> 0.055406855 | G49: =E49+F49 -> 1.3178543 | H49: =ROUND(D49*(E49+F49),2) -> 0
B50: Energia Comp. FP SCEE | D50: =-D34 -> 1422.72 | E50: =E26 -> 0.1237171 | F50: =IF(AND($B$17<$F$2,$E$17<$F$2),D10,IF($B$17<$F$2,K10,H10)) -> 0.035130242 | G50: =E50+F50 -> 0.15884734 | H50: =ROUND(D50*(E50+F50),2) -> 226
B52: Des Energ. Comp. P SCEE | D52: =-D49 -> 0 | E52: =E49*F19 -> 1.1195384 | F52: =F49*H19 -> 0.055406855 | G52: =E52+F52 -> 1.1749452 | H52: =ROUND(D52*(E52+F52),2) -> 0
B53: Des Energ. Comp. FP SCEE | D53: =-D50 -> -1422.72 | E53: =E50*F20 -> 0.1237171 | F53: =F50*H20 -> 0.035130242 | G53: =E53+F53 -> 0.15884734 | H53: =ROUND(D53*(E53+F53),2) -> -226
B55: ERE | D55: 27.675 | F55: =IF(AND($B$17<$F$2,$E$17<$F$2),E8,IF($B$17<$F$2,K8,H8)) -> 0.30007032 | H55: =ROUND(D55*(E55+F55),2) -> 8.3
B56: DRE | D56: 0 | E56: =E42 -> 0 | H56: =ROUND(D56*(E56+F56),2) -> 0
D58: Base de Cálculo
B59: PIS | D59: =(SUM(H25:H31)+H41+H47+H55+H56)/(1-E59-E62) -> 10922.749 | E59: 0.008 | H59: =D59*E59 -> 87.381993
B60: PIS Injetado | D60: =(SUM(H33:H39,H49:H53))/(1-E59-E62) -> 609.14992 | E60: =E59 -> 0.008 | H60: =D60*E60 -> 4.8731993
B61: PIS não utilizada | D61: =(H44)/(1-E61-E64) -> 135.74121 | E61: =E59 -> 0.008 | H61: =D61*E61 -> 1.0859296
B62: COFINS | D62: =D59 -> 10922.749 | E62: 0.0368 | H62: =D62*E62 -> 401.95717
B63: COFINS Injetado | D63: =D60 -> 609.14992 | E63: =E62 -> 0.0368 | H63: =D63*E63 -> 22.416717
B64: COFINS não utilizada | D64: =D61 -> 135.74121 | E64: =E62 -> 0.0368 | H64: =D64*E64 -> 4.9952764
B65: ICMS | D65: =D59/(1-E65) -> 13159.939 | E65: 0.17 | H65: =D65*E65 -> 2237.1896
B66: ICMS Injetado TE | D66: =((D33*F33)+(D34*F34)+SUM(H36:H39)+(D49*F49)+(D50*F50)+(D52*F52)+(D53*F53))/(1-E60-E63)/(1-E66) -> 511.9027 | E66: =E65 -> 0.17 | H66: =D66*E66 -> 87.023458

Sheet A4 MMGD GDII
B2: A4 AZUL | C2: MMGD | E2: Vigência das Tarifas: | F2: ='[5]A2 Azul'!F2 -> 45145 | I2: OK | M2: Bandeira | N2: R$/kWh | Q2: TUSD FIO B
M3: VERDE | N3: =[5]BANDEIRA!$D$4 -> 0
B4: TARIFA | C4: ='[5]A2 Azul'!C4:E4 -> TARIFA ANTIGA - REH 3091/2022 | F4: ='[5]A2 Azul'!F4:H4 -> TARIFA NOVA - REH 3241/2023 | I4: Tarifas Proporcionalizadas | M4: BAM | N4: =[5]BANDEIRA!$D$5 -> 0.02989 | Q4: TARIFA | R4: =C4 -> TARIFA ANTIGA - REH 3091/2022 | U4: =F4 -> TARIFA NOVA - REH 3241/2023 | X4: Tarifas Proporcionalizadas
C5: Tusd (R$/kW) | D5: Tusd (R$/kWh) | E5: TE (R$/kWh) | F5: Tusd (R$/kW) | G5: Tusd (R$/kWh) | H5: TE (R$/kWh) | I5: Tusd (R$/kW) | J5: Tusd (R$/kWh) | K5: TE (R$/kWh) | M5: BVM1 | N5: =[5]BANDEIRA!$D$6 -> 0.065 | R5: Tusd (R$/kW) | S5: Tusd (R$/kW) | U5: Tusd (R$/kW) | V5: Tusd (R$/kW) | X5: Tusd (R$/kW) | Y5: Tusd (R$/kW)
B6: A4 Azul P | C6: ='[5]A4 Azul'!C6 -> 45.59 | D6: ='[5]A4 Azul'!D6 -> 0.13433 | E6: ='[5]A4 Azul'!E6 -> 0.4226 | F6: ='[5]A4 Azul'!F6 -> 47.23 | G6: ='[5]A4 Azul'!G6 -> 0.12117 | H6: ='[5]A4 Azul'!H6 -> 0.45803 | I6: =((C6*$C$17)+(F6*$D$17))/($D$17+$C$17) -> 46.912581 | J6: =((D6*$C$17)+(G6*$D$17))/($D$17+$C$17) -> 0.1237171 | K6: =((E6*$C$17)+(H6*$D$17))/($D$17+$C$17) -> 0.45117258 | M6: BVM2 | N6: =[5]BANDEIRA!$D$7 -> 0.09795 | Q6: =B6 -> A4 Azul P | R6: ='[5]Grupo A_FIO B'!F49 -> 26.16 | S6: ='[5]Grupo A_FIO B'!G50/1000 -> 0.93588 | U6: ='[5]Grupo A_FIO B'!I49 -> 24.04 | V6: ='[5]Grupo A_FIO B'!J50/1000 -> 0.86024 | X6: =((R6*$C$17)+(U6*$D$17))/($D$17+$C$17) -> 24.450323 | Y6: =((S6*$C$17)+(V6*$D$17))/($D$17+$C$17) -> 0.87488
B7: A4 Azul FP | C7: ='[5]A4 Azul'!C7 -> 30.44 | D7: ='[5]A4 Azul'!D7 -> 0.13433 | E7: ='[5]A4 Azul'!E7 -> 0.2638 | F7: ='[5]A4 Azul'!F7 -> 31.53 | G7: ='[5]A4 Azul'!G7 -> 0.12117 | H7: ='[5]A4 Azul'!H7 -> 0.29041 | I7: =((C7*$C$17)+(F7*$D$17))/($D$17+$C$17) -> 31.319032 | J7: =((D7*$C$17)+(G7*$D$17))/($D$17+$C$17) -> 0.1237171 | K7: =((E7*$C$17)+(H7*$D$17))/($D$17+$C$17) -> 0.28525968 | M7: Escassez Hídrica | N7: =[5]BANDEIRA!$D$8 -> 0.142 | Q7: =B7 -> A4 Azul FP
B8: B1 | D8: ='[5]TABELA DE TARIFAS ANTIGAS'!G71/1000 -> 0.39681 | E8: ='[5]TABELA DE TARIFAS ANTIGAS'!H71/1000 -> 0.27703 | G8: ='[5]TABELA DE TARIFAS NOVAS'!G71/1000 -> 0.39253 | H8: ='[5]TABELA DE TARIFAS NOVAS'!H71/1000 -> 0.3056 | J8: =((D8*$C$17)+(G8*$D$17))/($D$17+$C$17) -> 0.39335839 | K8: =((E8*$C$17)+(H8*$D$17))/($D$17+$C$17) -> 0.30007032
B9: TE SCEE P | H9: =H6*15% -> 0.0687045 | K9: =((D9*$C$17)+(H9*$D$17))/($D$17+$C$17) -> 0.055406855
B10: TE SCEE FP | H10: =H7*15% -> 0.0435615 | K10: =((D10*$C$17)+(H10*$D$17))/($D$17+$C$17) -> 0.035130242
B12: MMGD
H13: Fatura | L13: Vigência das Tarifas (troca Bandeira): | M13: =EOMONTH(B17,0)+1 -> 45139
B14: INSTALAÇÃO | H14: =E17 -> 45169 | K14: Altere a bandeira na célula abaixo
K15: VERDE | L15: VERDE
B16: Leitura Anterior | C16: Nº de dias tarifa Anterior | D16: Nº de dias tarifa Nova | E16: Leitura Atual | J16: Leitura Anterior | K16: Nº de dias tarifa Anterior | L16: Nº de dias tarifa Nova | M16: Leitura Atual
B17: 45138 | C17: =IF((F2-B17-1)<0,0,(F2-B17-1)) -> 6 | D17: =E17-F2+1 -> 25 | E17: 45169 | J17: =B17 -> 45138 | K17: =IF((M13-J17-1)<0,0,(M13-J17-1)) -> 0 | L17: =M17-M13+1 -> 31 | M17: =E17 -> 45169
B19: Perc. de Redução da Energia Injetada | E19: TUSD P | F19: 1 | G19: TE P | H19: 1
E20: TUSD FP | F20: 1 | G20: TE FP | H20: 1
B22: Fatura A4 Azul - MMGD | J22: Documento impressão:
D23: Qtde | E23: TUSD | F23: TE | G23: TUSD + TE | H23: R$
J24: TUSD Fio B | K24: Receita Fio B
B25: Consumo Ponta | D25: 1290.8358 | E25: =IF(AND($B$17<$F$2,$E$17<$F$2),D6,IF($B$17<$F$2,J6,G6)) -> 0.1237171 | F25: =IF(AND($B$17<$F$2,$E$17<$F$2),E6,IF($B$17<$F$2,K6,H6)) -> 0.45117258 | G25: =E25+F25 -> 0.57488968 | H25: =ROUND((D25*E25),2)+ROUND((D25*F25),2) -> 742.09 | J25: =IF(AND($B$17<$F$2,$E$17<$F$2),S6,IF($B$17<$F$2,Y6,V6)) -> 0.87488 | K25: =D25*J25 -> 1129.3264
B26: Consumo Fora Ponta | D26: 12358.327 | E26: =IF(AND($B$17<$F$2,$E$17<$F$2),D7,IF($B$17<$F$2,J7,G7)) -> 0.1237171 | F26: =IF(AND($B$17<$F$2,$E$17<$F$2),E7,IF($B$17<$F$2,K7,H7)) -> 0.28525968 | G26: =E26+F26 -> 0.40897677 | H26: =ROUND((D26*E26),2)+ROUND((D26*F26),2) -> 5054.27
B28: Adicional BAM | D28: =IF($K$15=$M$4,((D25+D26)*(K17)/(K17+L17)),0)+IF($L$15=$M$4,((D25+D26)*(L17)/(K17+L17)),0) -> 0 | F28: =N4 -> 0.02989 | H28: =ROUND(D28*(E28+F28),2) -> 0
B29: Adicional BVM 1 | D29: =IF($K$15=$M$5,((D25+D26)*(K17)/(K17+L17)),0)+IF($L$15=$M$5,((D25+D26)*(L17)/(K17+L17)),0) -> 0 | F29: =N5 -> 0.065 | H29: =ROUND(D29*(E29+F29),2) -> 0
B30: Adicional BVM 2 | D30: =IF($K$15=$M$6,((D25+D26)*(K17)/(K17+L17)),0)+IF($L$15=$M$6,((D25+D26)*(L17)/(K17+L17)),0) -> 0 | F30: =N6 -> 0.09795 | H30: =ROUND(D30*(E30+F30),2) -> 0
B31: Adic. Escassez Hídrica | D31: =IF($K$15=$M$7,((D25+D26)*(K17)/(K17+L17)),0)+IF($L$15=$M$7,((D25+D26)*(L17)/(K17+L17)),0) -> 0 | F31: =N7 -> 0.142 | H31: =ROUND(D31*(E31+F31),2) -> 0
B33: Energ Injetada Ponta | D33: 0 | E33: =-E25 -> -0.1237171 | F33: =-F25 -> -0.45117258 | H33: =ROUND(D33*(E33+F33),2) -> 0
B34: Energ Injetada Fora Ponta | D34: 1422.72 | E34: =-E26 -> -0.1237171 | F34: =-F26 -> -0.28525968 | H34: =ROUND(D34*(E34+F34),2) -> -581.86
B36: Adicional BAM | D36: =IF($K$15=$M$4,((D33+D34)*(K17)/(K17+L17)),0)+IF($L$15=$M$4,((D33+D34)*(L17)/(K17+L17)),0) -> 0 | F36: =-F28 -> -0.02989 | H36: =ROUND(D36*(E36+F36),2) -> 0
B37: Adicional BVM 1 | D37: =IF($K$15=$M$5,((D33+D34)*(K17)/(K17+L17)),0)+IF($L$15=$M$5,((D33+D34)*(L17)/(K17+L17)),0) -> 0 | F37: =-F29 -> -0.065 | H37: =ROUND(D37*(E37+F37),2) -> 0
B38: Adicional BVM 2 | D38: =IF($K$15=$M$6,((D33+D34)*(K17)/(K17+L17)),0)+IF($L$15=$M$6,((D33+D34)*(L17)/(K17+L17)),0) -> 0 | F38: =-F30 -> -0.09795 | H38: =ROUND(D38*(E38+F38),2) -> 0
B39: Adic. Escassez Hídrica | D39: =IF($K$15=$M$7,((D33+D34)*(K17)/(K17+L17)),0)+IF($L$15=$M$7,((D33+D34)*(L17)/(K17+L17)),0) -> 0 | F39: =-F31 -> -0.142 | H39: =ROUND(D39*(E39+F39),2) -> 0
J40: TUSD Fio B | K40: Receita Fio B | L40: EUSD B
B41: Demanda Ponta | D41: 100.86 | E41: =IF(AND($B$17<$F$2,$E$17<$F$2),C6,IF($B$17<$F$2,I6,F6)) -> 46.912581 | H41: =ROUND(D41*(E41+F41),2) -> 4731.6 | J41: =IF(AND($B$17<$F$2,$E$17<$F$2),R6,IF($B$17<$F$2,X6,U6)) -> 24.450323 | K41: =D41*J41 -> 2466.0595 | L41: =K41+K44+K47 -> 2567.2839
B42: Demanda Fora Ponta | D42: 100.86 | E42: =IF(AND($B$17<$F$2,$E$17<$F$2),C7,IF($B$17<$F$2,I7,F7)) -> 31.319032 | H42: =ROUND(D42*(E42+F42),2) -> 3158.84
B44: Demanda não utilizada P | D44: 4.14 | E44: =E41 -> 46.912581 | H44: =ROUND(D44*(E44+F44),2) -> 194.22 | J44: =J41 -> 24.450323 | K44: =D44*J44 -> 101.22434
B45: Demanda não utilizada FP | D45: 4.14 | E45: =E42 -> 31.319032 | H45: =ROUND(D45*(E45+F45),2) -> 129.66
B47: Ultrap Demanda P | D47: 0 | E47: =E41*2 -> 93.825161 | H47: =ROUND(D47*(E47+F47),2) -> 0
B48: Ultrap Demanda FP | D48: 0 | E48: =E42*2 -> 62.638065 | H48: =ROUND(D48*(E48+F48),2) -> 0
B50: Energia Comp. P SCEE | D50: =-D33 -> 0 | E50: =E25 -> 0.1237171 | F50: =IF(AND($B$17<$F$2,$E$17<$F$2),D9,IF($B$17<$F$2,K9,H9)) -> 0.055406855 | G50: =E50+F50 -> 0.17912395 | H50: =ROUND(D50*(E50+F50),2) -> 0
B51: Energia Comp. FP SCEE | D51: =-D34 -> -1422.72 | E51: =E26 -> 0.1237171 | F51: =IF(AND($B$17<$F$2,$E$17<$F$2),D10,IF($B$17<$F$2,K10,H10)) -> 0.035130242 | G51: =E51+F51 -> 0.15884734 | H51: =ROUND(D51*(E51+F51),2) -> -226
B53: Des Energ. Comp. P SCEE | D53: =-D50 -> 0 | E53: =E50*F19 -> 0.1237171 | F53: =F50*H19 -> 0.055406855 | G53: =E53+F53 -> 0.17912395 | H53: =ROUND(D53*(E53+F53),2) -> 0
B54: Des Energ. Comp. FP SCEE | D54: =-D51 -> 1422.72 | E54: =E51*F20 -> 0.1237171 | F54: =F51*H20 -> 0.035130242 | G54: =E54+F54 -> 0.15884734 | H54: =ROUND(D54*(E54+F54),2) -> 226
B56: ERE | D56: 27.675 | F56: =IF(AND($B$17<$F$2,$E$17<$F$2),E8,IF($B$17<$F$2,K8,H8)) -> 0.30007032 | H56: =ROUND(D56*(E56+F56),2) -> 8.3
B57: DRE | D57: 0 | E57: =E42 -> 31.319032 | H57: =ROUND(D57*(E57+F57),2) -> 0
D59: Base de Cálculo
B60: PIS | D60: =(SUM(H25:H31)+H41+H42+H47+H48+H56+H57)/(1-E60-E63) -> 14337.416 | E60: 0.008 | H60: =D60*E60 -> 114.69933
B61: PIS Injetado | D61: =(SUM(H33:H39))/(1-E60-E63) -> -609.14992 | E61: =E60 -> 0.008 | H61: =D61*E61 -> -4.8731993
B62: PIS não utilizada | D62: =(H44+H45)/(1-E62-E65) -> 339.07035 | E62: =E60 -> 0.008 | H62: =D62*E62 -> 2.7125628
B63: COFINS | D63: =D60 -> 14337.416 | E63: 0.0368 | H63: =D63*E63 -> 527.61692
B64: COFINS Injetado | D64: =D61 -> -609.14992 | E64: =E63 -> 0.0368 | H64: =D64*E64 -> -22.416717
B65: COFINS não utilizada | D65: =D62 -> 339.07035 | E65: =E63 -> 0.0368 | H65: =D65*E65 -> 12.477789
B66: ICMS | D66: =D60/(1-E66) -> 17273.995 | E66: 0.17 | H66: =D66*E66 -> 2936.5792
B67: ICMS Injetado TE | D67: =((D33*F33)+(D34*F34)+SUM(H36:H39)+(D50*F50)+(D51*F51)+(D53*F53)+(D54*F54))/(1-E61-E64)/(1-E67) -> -511.9027 | E67: =E66 -> 0.17 | H67: =D67*E67 -> -87.023458

Sheet Fatura B1 (GD II) (Baixa Re (2)
B2: B1 Baixa renda | E2: Vigência das Tarifas: | F2: 45145 | I2: GDII | M2: Bandeira | N2: R$/kWh | O2: ANEEL em 29/06 | Q2: TUSD FIO B
M3: VERDE | N3: 0
B4: TARIFA R$ kWh | C4: TARIFA ANTIGA - REH 3091/2022 | F4: TARIFA NOVA - REH XXXX/2023 | I4: Tarifas Proporcionalizadas | M4: BAM | N4: 0.02989 | Q4: TARIFA | R4: =C4 -> TARIFA ANTIGA - REH 3091/2022 | U4: =F4 -> TARIFA NOVA - REH XXXX/2023 | X4: Tarifas Proporcionalizadas
C5: Tusd | D5: TE | E5: TUSD + TE | F5: Tusd | G5: TE | H5: TUSD + TE | I5: Tusd | J5: TE | K5: TUSD + TE | M5: BVM1 | N5: 0.065 | R5: Tusd (R$/kWh) | U5: Tusd (R$/kWh) | X5: Tusd (R$/kWh)
B6: Baixa renda | C6: 0.27266 | D6: 0.27703 | E6: =C6+D6 -> 0.54969 | F6: 0.27266 | G6: 0.27703 | H6: =F6+G6 -> 0.54969 | I6: =((C6*$C$13)+(F6*$D$13))/($D$13+$C$13) -> 0.27266 | J6: =((D6*$C$13)+(G6*$D$13))/($D$13+$C$13) -> 0.27703 | K6: =I6+J6 -> 0.54969 | M6: BVM2 | N6: 0.09795 | Q6: =B6 -> Baixa renda | R6: ='[2]FIO B'!H11/1000 -> 0.19205 | U6: ='[2]FIO B'!K11/1000 -> 0.17652 | X6: =((R6*$C$13)+(U6*$D$13))/($D$13+$C$13) -> 0.18503645
B7: TE SCEE | G7: =G6*15% -> 0.0415545 | J7: =((D7*$C$13)+(G7*$D$13))/($D$13+$C$13) -> 0.018766548 | M7: Escassez Hídrica | N7: 0.142
H9: Fatura | L9: Vigência das Tarifas (troca Bandeira): | M9: =EOMONTH(B13,0)+1 -> 45139
B10: INSTALAÇÃO | C10: 1182321 | H10: =E13 -> 45158 | K10: Altere a bandeira na célula abaixo
K11: VERDE | L11: VERDE
B12: Leitura Anterior | C12: Nº de dias tarifa Anterior | D12: Nº de dias tarifa Nova | E12: Leitura Atual | J12: Leitura Anterior | K12: Nº de dias tarifa Anterior | L12: Nº de dias tarifa Nova | M12: Leitura Atual
B13: 45127 | C13: =IF((F2-B13-1)<0,0,(F2-B13-1)) -> 17 | D13: =E13-F2+1 -> 14 | E13: 45158 | J13: =B13 -> 45127 | K13: =IF((M9-J13-1)<0,0,(M9-J13-1)) -> 11 | L13: =M13-M9+1 -> 20 | M13: =E13 -> 45158
B15: Regra do custo de disponibilidade
A16: monofásico | B16: Cliente | D16: trifásico | G16: =IF(D16="monofásico",30,IF(D16="bifásico",50,100)) -> 100 | H16: kWh
A17: bifásico | B17: TUSD = | G17: =I6 -> 0.27266 | H17: R$/kWh
A18: trifásico | B18: TE = | G18: =J6 -> 0.27703 | H18: R$/kWh | J18: bandeira proporcional
B19: Adicional de Bandeira Amarela | G19: =(IF($K$11=M4,(G16*(K13)/(K13+L13)),0)+IF($L$11=M4,(G16*(L13)/(K13+L13)),0))*N4 -> 0 | H19: R$ | I19: =IF(OR($K$11=M4,$L$11=M4),N4,0) -> 0 | J19: =(IF($K$11=M4,(N4*(K13)/(K13+L13)),0)+IF($L$11=M4,(N4*(L13)/(K13+L13)),0)) -> 0
B20: Adicional de bandeira Vermelha 1 | G20: =(IF($K$11=M5,(G16*(K13)/(K13+L13)),0)+IF($L$11=M5,(G16*(L13)/(K13+L13)),0))*N5 -> 0 | H20: R$ | I20: =IF(OR($K$11=M5,$L$11=M5),N5,0) -> 0 | J20: =(IF($K$11=M5,(N5*(K13)/(K13+L13)),0)+IF($L$11=M5,(N5*(L13)/(K13+L13)),0)) -> 0
B21: Adicional de bandeira Vermelha 2 | G21: =(IF($K$11=M6,(G16*(K13)/(K13+L13)),0)+IF($L$11=M6,(G16*(L13)/(K13+L13)),0))*N6 -> 0 | H21: R$ | I21: =IF(OR($K$11=M6,$L$11=M6),N6,0) -> 0 | J21: =(IF($K$11=M6,(N6*(K13)/(K13+L13)),0)+IF($L$11=M6,(N6*(L13)/(K13+L13)),0)) -> 0
B22: Custo de disponibilidade | G22: =G16*(G17+G18)+G19+G20+G21 -> 54.969 | H22: R$
B24: Consumo = | G24: 1000 | H24: kWh
B25: Energia Injetada = | G25: 600 | H25: kWh | I25: =G25+D53 -> 570
G26: =-IF(G24<G16,0,IF(G25<(((G24*(E46+F46))+H48+H49+H50+H51)-((G16*(G17+G18)+G19+G20+G21)))/(E71+F56+J19+J20+J21),-G25,-(((G24*(E46+F46))+H48+H49+H50+H51)-((G16*(G17+G18)+G19+G20+G21)))/(E71+F56+J19+J20+J21))) -> 600 | H26: =G24-G26 -> 400
B27: Perc. de Redução da Energia Injetada | E27: TUSD | F27: 1 | G27: TE | H27: 1 | K27: =M101+M107 -> 72.880698
B29: Fatura B1 Baixa Renda
D30: Qtde | E30: TUSD | F30: TE | G30: TUSD + TE | H30: R$
B31: Fornecimento de Energia Elétrica | H31: =SUM(H33:H71)+SUM(H76:H81) -> 25.154358
A33: 0.65 | B33: Consumo 0 - 30 | D33: =IF(H26>0,30,0) -> 30 | E33: =$E$46*(1-A33) -> 0.095431 | F33: =$F$46*(1-A33) -> 0.0969605 | G33: =E33+F33 -> 0.1923915 | H33: =ROUND((D33*E33),2)+ROUND((D33*F33),2) -> 5.77
A34: 0.4 | B34: Consumo 31 - 100 | D34: 20 | E34: =$E$46*(1-A34) -> 0.163596 | F34: =$F$46*(1-A34) -> 0.166218 | G34: =E34+F34 -> 0.329814 | H34: =ROUND((D34*E34),2)+ROUND((D34*F34),2) -> 6.59
A35: 0.1 | B35: Consumo 101 - 220 | E35: =$E$46*(1-A35) -> 0.245394 | F35: =$F$46*(1-A35) -> 0.249327 | G35: =E35+F35 -> 0.494721 | H35: =ROUND((D35*E35),2)+ROUND((D35*F35),2) -> 0
A36: 0 | B36: Consumo > 220 | E36: =$E$46*(1-A36) -> 0.27266 | F36: =$F$46*(1-A36) -> 0.27703 | G36: =E36+F36 -> 0.54969 | H36: =ROUND((D36*E36),2)+ROUND((D36*F36),2) -> 0
B38: Adicional BAM | H38: =O124 -> 0
B39: Adicional BVM 1 | H39: =O133 -> 0
B40: Adicional BVM 2 | H40: =O142 -> 0
B41: Adicional Escassez Hídrica | H41: =O151 -> 0
A43: 0.65 | B43: Energia Fornecida 0 - 30 | D43: 30 | E43: =$E$46*(1-A43) -> 0.095431 | F43: =$F$46*(1-A43) -> 0.0969605 | G43: =E43+F43 -> 0.1923915 | H43: =ROUND((D43*E43),2)+ROUND((D43*F43),2) -> 5.77
A44: 0.4 | B44: Energia Fornecida 31 - 100 | D44: 70 | E44: =$E$46*(1-A44) -> 0.163596 | F44: =$F$46*(1-A44) -> 0.166218 | G44: =E44+F44 -> 0.329814 | H44: =ROUND((D44*E44),2)+ROUND((D44*F44),2) -> 23.09
A45: 0.1 | B45: Energia Fornecida 101 - 220 | D45: 120 | E45: =$E$46*(1-A45) -> 0.245394 | F45: =$F$46*(1-A45) -> 0.249327 | G45: =E45+F45 -> 0.494721 | H45: =ROUND((D45*E45),2)+ROUND((D45*F45),2) -> 59.37
A46: 0 | B46: Energia Fornecida > 220 | D46: 9 | E46: =IF(AND($B$13<$F$2,$E$13<$F$2),C6,IF($B$13<$F$2,I6,F6)) -> 0.27266 | F46: =IF(AND($B$13<$F$2,$E$13<$F$2),D6,IF($B$13<$F$2,J6,G6)) -> 0.27703 | G46: =E46+F46 -> 0.54969 | H46: =ROUND((D46*E46),2)+ROUND((D46*F46),2) -> 4.94
B48: Adicional BAM | H48: =O161 -> 0
B49: Adicional BVM 1 | H49: =O170 -> 0
B50: Adicional BVM 2 | H50: =O179 -> 0
B51: Adicional Escassez Hídrica | H51: =O188 -> 0
A53: 0.65 | B53: Energia Inejtada 0 - 30 | D53: -30 | E53: =E43 -> 0.095431 | F53: =F43 -> 0.0969605 | G53: =E53+F53 -> 0.1923915 | H53: =ROUND((D53*E53),2)+ROUND((D53*F53),2) -> -5.77
A54: 0.4 | B54: Energia Injetada 31 - 100 | D54: -70 | E54: =E44 -> 0.163596 | F54: =F44 -> 0.166218 | G54: =E54+F54 -> 0.329814 | H54: =ROUND((D54*E54),2)+ROUND((D54*F54),2) -> -23.09
A55: 0.1 | B55: Energia Injetada 101 - 220 | D55: -120 | E55: =E45 -> 0.245394 | F55: =F45 -> 0.249327 | G55: =E55+F55 -> 0.494721 | H55: =ROUND((D55*E55),2)+ROUND((D55*F55),2) -> -59.37
A56: 0 | B56: Energia Injetada > 220 | D56: -9 | E56: =E46 -> 0.27266 | F56: =F46 -> 0.27703 | G56: =E56+F56 -> 0.54969 | H56: =ROUND((D56*E56),2)+ROUND((D56*F56),2) -> -4.94
B58: Adicional BAM | H58: =O200 -> 0
B59: Adicional BVM 1 | H59: =O209 -> 0
B60: Adicional BVM 2 | H60: =O218 -> 0
B61: Adicional Escassez Hídrica | H61: =O227 -> 0
A63: 0.65 | B63: Energia Compensada SCEE 0 - 30 | D63: =-D53 -> 30 | E63: =$E$66*(1-A63) -> 0.095431 | F63: =$F$66*(1-A63) -> 0.0065682919 | G63: =E63+F63 -> 0.10199929 | H63: =ROUND(D63*(E63+F63),2) -> 3.06
A64: 0.4 | B64: Energia Compensada SCEE 31 - 100 | D64: =-D54 -> 70 | E64: =$E$66*(1-A64) -> 0.163596 | F64: =$F$66*(1-A64) -> 0.011259929 | G64: =E64+F64 -> 0.17485593 | H64: =ROUND(D64*(E64+F64),2) -> 12.24
A65: 0.1 | B65: Energia Compensada SCEE 101 - 220 | D65: =-D55 -> 120 | E65: =$E$66*(1-A65) -> 0.245394 | F65: =$F$66*(1-A65) -> 0.016889894 | G65: =E65+F65 -> 0.26228389 | H65: =ROUND(D65*(E65+F65),2) -> 31.47
A66: 0 | B66: Energia Compensada SCEE > 220 | D66: =-D56 -> 9 | E66: =E46 -> 0.27266 | F66: =IF(AND($B$13<$F$2,$E$13<$F$2),D7,IF($B$13<$F$2,J7,G7)) -> 0.018766548 | G66: =E66+F66 -> 0.29142655 | H66: =ROUND(D66*(E66+F66),2) -> 2.62
B68: Des Energ. Comp. SCEE 0 - 30 | D68: =-D63 -> -30 | E68: =E63*$F$27 -> 0.095431 | F68: =F63*$H$27 -> 0.0065682919 | G68: =E68+F68 -> 0.10199929 | H68: =ROUND(D68*(E68+F68),2) -> -3.06
B69: Des Energ. Comp. SCEE 31 - 100 | D69: =-D64 -> -70 | E69: =E64*$F$27 -> 0.163596 | F69: =F64*$H$27 -> 0.011259929 | G69: =E69+F69 -> 0.17485593 | H69: =ROUND(D69*(E69+F69),2) -> -12.24
B70: Des Energ. Comp. SCEE 101 - 220 | D70: =-D65 -> -120 | E70: =E65*$F$27 -> 0.245394 | F70: =F65*$H$27 -> 0.016889894 | G70: =E70+F70 -> 0.26228389 | H70: =ROUND(D70*(E70+F70),2) -> -31.47
B71: Des Energ. Comp. SCEE > 220 | D71: =-D66 -> -9 | E71: =E66*$F$27 -> 0.27266 | F71: =F66*$H$27 -> 0.018766548 | G71: =E71+F71 -> 0.29142655 | H71: =ROUND(D71*(E71+F71),2) -> -2.62 | I71: =SUM(H63:H71) -> -9.7699626e-15
H73: =SUM(H33:H72) -> 12.36 | J73: =231.75-'Fatura B1 (GD II) (Baixa Re (2)'!H73 -> 219.39
D75: Base de Cálculo
B76: PIS | D76: =SUM(H33:H51)/(1-E76-E78) -> 108.98482 | E76: 0.0056 | H76: =D76*E76 -> 0.61031499
B77: PIS Eneg Inj | D77: =SUM(H53:H71)/(1-E76-E78) -> -96.22018 | E77: =E76 -> 0.0056 | H77: =D77*E77 -> -0.53883301
B78: COFINS | D78: =D76 -> 108.98482 | E78: 0.0261 | H78: =D78*E78 -> 2.8445038
B79: COFINS Eneg Inj | D79: =D77 -> -96.22018 | E79: =E78 -> 0.0261 | H79: =D79*E79 -> -2.5113467
B80: ICMS | D80: =D76/(1-E80) -> 131.30701 | E80: 0.17 | H80: =D80*E80 -> 22.322192
B81: ICMS Eneg Inj | D81: =((D53*F53)+(D54*F54)+(D55*F55)+(D56*F56)+(D64*F64)+(D65*F65)+(D66*F66)+(D69*F69)+(D70*F70)+(D71*F71)+(H58+H59+H60+H61)+(D63*F63)+(D68*F68))/(1-E77-E79)/(1-E81) -> -58.426313 | E81: =E80 -> 0.17 | H81: =D81*E81 -> -9.9324732
B82: ICMS Desc Tarifa Social | D82: =K114 -> 39.007906 | E82: =E81 -> 0.17 | H82: =D82*E82 -> 6.631344
B85: Benefício Tarifa Social | H85: =K113 -> 15.1245 | I85: (mensagem na fatura)
F87: Memória benefício Tarifa Social
I88: TUSD X | J88: TE | M88: Com tributos e bandeiras (base ICMS)
F89: Consumo | G89: B1 Baixa Renda | H89: =SUM(D33:D36,D43:D46) -> 279 | I89: =E36 -> 0.27266 | J89: =F36 -> 0.27703 | K89: =H89*(I89+J89) -> 153.36351 | M89: =SUM(K89:K93)/(1-E76-E78)/(1-E80) -> 190.82445
G90: BAM | H90: =IF($K$11=$B$154,(H89*($K$13)/($K$13+$L$13)),0)+IF($L$11=$B$154,(H89*($L$13)/($K$13+$L$13)),0) -> 0 | J90: =N4 -> 0.02989 | K90: =H90*(I90+J90) -> 0
G91: BVM1 | H91: =IF($K$11=$B$163,(H90*($K$13)/($K$13+$L$13)),0)+IF($L$11=$B$163,(H90*($L$13)/($K$13+$L$13)),0) -> 0 | J91: =N5 -> 0.065 | K91: =H91*(I91+J91) -> 0
G92: BVM2 | H92: =IF($K$11=$B$172,(H91*($K$13)/($K$13+$L$13)),0)+IF($L$11=$B$172,(H91*($L$13)/($K$13+$L$13)),0) -> 0 | J92: =N6 -> 0.09795 | K92: =H92*(I92+J92) -> 0
G93: Escassez Hídrica | H93: =IF($K$11=$B$181,(H92*($K$13)/($K$13+$L$13)),0)+IF($L$11=$B$181,(H92*($L$13)/($K$13+$L$13)),0) -> 0 | J93: =N7 -> 0.142 | K93: =H93*(I93+J93) -> 0
F95: Injetada | G95: B1 Baixa Renda | H95: =SUM(D53:D56) -> -229 | I95: =E71 -> 0.27266 | J95: =J89 -> 0.27703 | K95: =H95*(I95+J95) -> -125.87901 | M95: =((H95*J95)+(K96+K97+K98+K99))/(1-E77-E79)/(1-E81) -> -78.935845
G96: BAM | H96: =IF($K$11=$B$154,(H95*($K$13)/($K$13+$L$13)),0)+IF($L$11=$B$154,(H95*($L$13)/($K$13+$L$13)),0) -> 0 | J96: =J90 -> 0.02989 | K96: =H96*(I96+J96) -> 0
G97: BVM1 | H97: =IF($K$11=$B$163,(H96*($K$13)/($K$13+$L$13)),0)+IF($L$11=$B$163,(H96*($L$13)/($K$13+$L$13)),0) -> 0 | J97: =J91 -> 0.065 | K97: =H97*(I97+J97) -> 0
G98: BVM2 | H98: =IF($K$11=$B$172,(H97*($K$13)/($K$13+$L$13)),0)+IF($L$11=$B$172,(H97*($L$13)/($K$13+$L$13)),0) -> 0 | J98: =J92 -> 0.09795 | K98: =H98*(I98+J98) -> 0
G99: Escassez Hídrica | H99: =IF($K$11=$B$181,(H98*($K$13)/($K$13+$L$13)),0)+IF($L$11=$B$181,(H98*($L$13)/($K$13+$L$13)),0) -> 0 | J99: =J93 -> 0.142 | K99: =H99*(I99+J99) -> 0
F101: Bx Renda Consumo | G101: Baixa Renda | K101: =SUM(H33:H36,H43:H46) -> 105.53 | M101: =SUM(K101:K105)/(1-E76-E78)/(1-E80) -> 131.30701
G102: BAM | K102: =H38+H48 -> 0
G103: BVM1 | K103: =H39+H49 -> 0
G104: BVM2 | K104: =H40+H50 -> 0
G105: Escassez Hídrica | K105: =H41+H51 -> 0
F107: Bx Renda Injetada | G107: Baixa Renda | K107: =SUM(H53:H56,H63:H66,H68:H71) -> -93.17 | M107: =D81 -> -58.426313
G108: BAM | K108: =H58 -> 0
G109: BVM1 | K109: =H59 -> 0
G110: BVM2 | K110: =H60 -> 0
G111: Escassez Hídrica | K111: =H61 -> 0
J113: Benefício Tarifa Social | K113: =(K89+K95)-(K101+K107) -> 15.1245 | L113: sem considerar as bandeiras
J114: Com tributos | K114: =(M89+M95)-(M101+M107) -> 39.007906 | L114: considerando as bandeiras no cálculo dos tributos
B116: Consumo - Adicional de Bandeira
B117: BAM | K117: =N4 -> 0.02989
C118: Consumo | J118: Tarifas | M118: Receita | O118: Receita Total
C119: KWh | K119: TE | M119: Tusd | N119: TE | O119: Tusd+TE
C120: =IF($K$11=$B$117,(D33*($K$13)/($K$13+$L$13)),0)+IF($L$11=$B$117,(D33*($L$13)/($K$13+$L$13)),0) -> 0 | K120: =$K$154*(1-Q120) -> 0.0104615 | N120: =ROUND((C120*K120),2) -> 0 | O120: =M120+N120 -> 0 | Q120: 0.65
C121: =IF($K$11=$B$117,(D34*($K$13)/($K$13+$L$13)),0)+IF($L$11=$B$117,(D34*($L$13)/($K$13+$L$13)),0) -> 0 | K121: =$K$154*(1-Q121) -> 0.017934 | N121: =ROUND((C121*K121),2) -> 0 | O121: =M121+N121 -> 0 | Q121: 0.4
C122: =IF($K$11=$B$117,(D35*($K$13)/($K$13+$L$13)),0)+IF($L$11=$B$117,(D35*($L$13)/($K$13+$L$13)),0) -> 0 | K122: =$K$154*(1-Q122) -> 0.026901 | N122: =ROUND((C122*K122),2) -> 0 | O122: =M122+N122 -> 0 | Q122: 0.1
C123: =IF($K$11=$B$117,(D36*($K$13)/($K$13+$L$13)),0)+IF($L$11=$B$117,(D36*($L$13)/($K$13+$L$13)),0) -> 0 | K123: =$K$154*(1-Q123) -> 0.02989 | N123: =ROUND((C123*K123),2) -> 0 | O123: =M123+N123 -> 0 | Q123: 0
...
