Workbook
Name _Ref352134769: 'TABELA DE TARIFAS NOVAS'!$A$93

Sheet FIO B
B2: TUSD FIO B
B4: SUBGRUPO | C4: MODALIDADE | D4: CLASSE | E4: SUBCLASSE | F4: POSTO | G4: TARIFAS DE APLICAÇÃO
G5: TUSD FIO B (RTP 2025) | J5: TUSD FIO B (RTA 2026)
G6: R$/kW | H6: R$/MWh | J6: R$/kW | K6: R$/MWh
B7: B1 | C7: BRANCA | D7: RESIDENCIAL | E7: RESIDENCIAL | F7: P | G7: 0 | H7: 591.10909 | J7: 0 | K7: 606.53962
B8: B1 | C8: BRANCA | D8: RESIDENCIAL | E8: RESIDENCIAL | F8: INT | G8: 0 | H8: 354.6655 | J8: 0 | K8: 363.92381
B9: B1 | C9: BRANCA | D9: RESIDENCIAL | E9: RESIDENCIAL | F9: FP | G9: 0 | H9: 118.2218 | J9: 0 | K9: 121.3079
B10: B1 | C10: PRÉ-PAGAMENTO | D10: RESIDENCIAL | E10: RESIDENCIAL | F10: NA | G10: 0 | H10: 203.83072 | J10: 0 | K10: 209.15159
B11: B1 | C11: CONVENCIONAL | D11: RESIDENCIAL | E11: RESIDENCIAL | F11: NA | G11: 0 | H11: 203.83072 | J11: 0 | K11: 209.15159
B12: B1 | C12: PRÉ-PAGAMENTO | D12: RESIDENCIAL | E12: BAIXA RENDA | F12: NA | G12: 0 | H12: 203.83072 | J12: 0 | K12: 209.15159
B13: B1 | C13: CONVENCIONAL | D13: RESIDENCIAL | E13: BAIXA RENDA | F13: NA | G13: 0 | H13: 203.83072 | J13: 0 | K13: 209.15159
B14: B1 | C14: PRÉ-PAGAMENTO | D14: RESIDENCIAL | E14: RESIDENCIAL DESCONTO SOCIAL | F14: NA | G14: 0 | H14: 203.83072 | J14: 0 | K14: 209.15159
B15: B1 | C15: CONVENCIONAL | D15: RESIDENCIAL | E15: RESIDENCIAL DESCONTO SOCIAL | F15: NA | G15: 0 | H15: 203.83072 | J15: 0 | K15: 209.15159
B16: B2 | C16: BRANCA | D16: RURAL | E16: NÃO SE APLICA | F16: P | G16: 0 | H16: 693.02445 | J16: 0 | K16: 711.11541
B17: B2 | C17: BRANCA | D17: RURAL | E17: NÃO SE APLICA | F17: INT | G17: 0 | H17: 415.81471 | J17: 0 | K17: 426.66929
B18: B2 | C18: BRANCA | D18: RURAL | E18: NÃO SE APLICA | F18: FP | G18: 0 | H18: 138.60487 | J18: 0 | K18: 142.22306
... B39: B | C39: GERAÇÃO | D39: TIPO 02 | E39: NA | F39: NA | G39: 0 | H39: 11.690957 | J39: 0 | K39: 11.996142

Sheet TABELA DE TARIFAS ANTIGAS
A1: TABELA 1 – TARIFAS DE APLICAÇÃO E BASE ECONÔMICA PARA O GRUPO A.
A2: SUBGRUPO | B2: MODALIDADE | C2: UC | D2: POSTO | E2: TARIFAS DE APLICAÇÃO | J2: BASE ECONÔMICA | N2: Reajuste | O2: Dia | P2: Mês | Q2: Ano
E3: TUSD | G3: TE | J3: TUSD | L3: TE | N3: De | O3: 07 | P3: 08 | Q3: 2025
E4: R$/kW | F4: R$/MWh | G4: BVD – R$/MWh | H4: BAM – R$/MWh | I4: BVM – R$/MWh | J4: R$/kW | K4: R$/MWh | L4: R$/MWh | N4: Até | O4: 06 | P4: 08 | Q4: 2026
B5: AZUL | C5: NA | D5: P
A6: A1 (230 kV ou mais) | D6: FP
B7: AZUL APE | C7: NA | D7: P
D8: FP
A9: A2 (88 a 138kV) | B9: AZUL | C9: NA | D9: P
D10: FP
B11: AZUL APE | C11: NA | D11: P
D12: FP
B13: DISTRIBUIÇÃO | C13: ELFSM | D13: P
D14: FP
D15: NA
B16: GERAÇÃO | C16: UTE LASA | D16: NA
C17: UTE ALCON | D17: NA
C18: UTE SOL | D18: NA
C19: UHE MASCARENHAS - ENERGEST | D19: NA
C20: UHE SUICA | D20: NA
C21: PCH SAO JOAQUIM | D21: NA
C22: PCH SAO SIMAO | D22: NA
C23: PCH FRANCISCO GROSS | D23: NA
C24: PCH SAO PEDRO | D24: NA
C25: UTE LINHARES | D25: NA
C26: UTE ARCEL | D26: NA
C27: NOVO GERADOR | D27: NA
A28: A3 (69kV) | B28: AZUL | C28: NA | D28: P
D29: FP
B30: AZUL APE | C30: NA | D30: P
D31: FP
B32: DISTRIBUIÇÃO | D32: P
D33: FP
D34: NA
B35: GERAÇÃO | C35: NA | D35: NA
A36: A3a (30 a 44kV) | B36: AZUL | C36: NA | D36: P
D37: FP
B38: AZUL APE | C38: NA | D38: P
D39: FP
B40: VERDE | C40: NA | D40: NA
D41: P
D42: FP
B43: VERDE APE | C43: NA | D43: NA
D44: P
D45: FP
B46: CONVENCIONAL | C46: NA | D46: NA
B47: GERAÇÃO | C47: NA | D47: NA
A48: A4 (2,3 a 25kV) | B48: AZUL | C48: NA | D48: P
D49: FP
B50: AZUL APE | C50: NA | D50: P
D51: FP
B52: VERDE | C52: NA | D52: NA
D53: P
D54: FP
B55: VERDE APE | C55: NA | D55: NA
D56: P
D57: FP
B58: CONVENCIONAL | C58: NA | D58: NA
B59: DISTRIBUIÇÃO | C59: COELBA | D59: P
D60: FP
D61: NA
B62: GERAÇÃO | C62: NA | D62: NA
A64: TABELA 2 – TARIFAS DE APLICAÇÃO E BASE ECONÔMICA PARA O GRUPO B.
A65: SUBGRUPO | B65: MODALIDADE | C65: CLASSE | D65: SUBCLASSE | E65: POSTO | F65: TARIFAS DE APLICAÇÃO | K65: TARIFAS BASE ECONÔMICA
F66: TUSD | H66: TE | K66: TUSD | M66: TE
F67: R$/kW | G67: R$/MWh | H67: BVD – R$/MWh | I67: BAM – R$/MWh | J67: BVM – R$/MWh | K67: R$/kW | L67: R$/MWh | M67: R$/MWh
A68: B1 | B68: BRANCA | C68: RESIDENCIAL | D68: RESIDENCIAL | E68: P | F68: 0 | G68: 937.61 | H68: 484.48 | K68: 0 | L68: 918.51 | M68: 492.47
E69: INT | F69: 0 | G69: 651.29 | H69: 305.79 | K69: 0 | L69: 634.94 | M69: 316.46
E70: FP | F70: 0 | G70: 364.96 | H70: 305.79 | K70: 0 | L70: 351.38 | M70: 316.46
B71: CONVENCIONAL | C71: RESIDENCIAL | D71: RESIDENCIAL | E71: NA | F71: 0 | G71: 468.63 | H71: 320.68 | K71: 0 | L71: 454.05 | M71: 331.12
D72: BAIXA RENDA(1) | E72: NA | F72: 0 | G72: 325.43 | H72: 282.45 | K72: 0
D73: DESCONTO SOCIAL | E73: NA | G73: 340.19 | H73: 296.66
A74: B2 | B74: BRANCA | C74: RURAL | D74: NA | E74: P | F74: 0 | G74: 1061.03 | H74: 484.48 | K74: 0 | L74: 1040.73 | M74: 492.47
E75: INT | F75: 0 | G75: 725.34 | H75: 305.79 | K75: 0 | L75: 708.28 | M75: 316.46
E76: FP | F76: 0 | G76: 389.65 | H76: 305.79 | K76: 0 | L76: 375.82 | M76: 316.46
B77: CONVENCIONAL | C77: RURAL | D77: NA | E77: NA | F77: 0 | G77: 468.63 | H77: 320.68 | K77: 0 | L77: 454.05 | M77: 331.12
B78: BRANCA | C78: RURAL | D78: COOPERATIVA DE ELETRIFICAÇÃO RURAL | E78: P | F78: 0 | G78: 1061.03 | H78: 484.48 | K78: 0 | L78: 1040.73 | M78: 492.47
E79: INT | F79: 0 | G79: 725.34 | H79: 305.79 | K79: 0 | L79: 708.28 | M79: 316.46
E80: FP | F80: 0 | G80: 389.65 | H80: 305.79 | K80: 0 | L80: 375.82 | M80: 316.46
B81: CONVENCIONAL | C81: RURAL | D81: COOPERATIVA DE ELETRIFICAÇÃO RURAL | E81: NA | F81: 0 | G81: 468.63 | H81: 320.68 | K81: 0 | L81: 454.05 | M81: 331.12
B82: BRANCA | C82: RURAL | D82: SERVIÇO PÚBLICO DE IRRIGAÇÃO RURAL | E82: P | F82: 0 | G82: 1061.03 | H82: 484.48 | K82: 0 | L82: 1040.73 | M82: 492.47
E83: INT | F83: 0 | G83: 725.34 | H83: 305.79 | K83: 0 | L83: 708.28 | M83: 316.46
E84: FP | F84: 0 | G84: 389.65 | H84: 305.79 | K84: 0 | L84: 375.82 | M84: 316.46
B85: CONVENCIONAL | C85: RURAL | D85: SERVIÇO PÚBLICO DE IRRIGAÇÃO RURAL | E85: NA | F85: 0 | G85: 468.63 | H85: 320.68 | K85: 0 | L85: 454.05 | M85: 331.12
A86: B3 | B86: BRANCA | C86: NA | D86: NA | E86: P | F86: 0 | G86: 1061.03 | H86: 484.48 | K86: 0 | L86: 1040.73 | M86: 492.47
E87: INT | F87: 0 | G87: 725.34 | H87: 305.79 | K87: 0 | L87: 708.28 | M87: 316.46
E88: FP | F88: 0 | G88: 389.65 | H88: 305.79 | K88: 0 | L88: 375.82 | M88: 316.46
B89: CONVENCIONAL | C89: NA | D89: NA | E89: NA | F89: 0 | G89: 468.63 | H89: 320.68 | K89: 0 | L89: 454.05 | M89: 331.12
A90: B4 | B90: CONVENCIONAL | C90: ILUMINAÇÃO PÚBLICA | D90: B4a – REDE DE DISTRIBUIÇÃO | E90: NA | F90: 0 | G90: 257.75 | H90: 176.38 | K90: 0 | L90: 249.73 | M90: 182.12
D91: B4b – BULBO DE LÂMPADA | E91: NA | F91: 0 | G91: 281.18 | H91: 192.41 | K91: 0 | L91: 272.43 | M91: 198.67

Sheet TABELA DE TARIFAS NOVAS
A1: TABELA 1 – TARIFAS DE APLICAÇÃO E BASE ECONÔMICA PARA O GRUPO A.
A2: SUBGRUPO | B2: MODALIDADE | C2: UC | D2: POSTO | E2: TARIFAS DE APLICAÇÃO | J2: BASE ECONÔMICA | N2: Reajuste | O2: Dia | P2: Mês | Q2: Ano
E3: TUSD | G3: TE | J3: TUSD | L3: TE | N3: De | O3: 07 | P3: 08 | Q3: 2026
E4: R$/kW | F4: R$/MWh | G4: BVD – R$/MWh | H4: BAM – R$/MWh | I4: BVM – R$/MWh | J4: R$/kW | K4: R$/MWh | L4: R$/MWh | N4: Até | O4: 31 | P4: 12 | Q4: 9999
B5: AZUL | C5: NA | D5: P
A6: A1 (230 kV ou mais) | D6: FP
B7: AZUL APE | C7: NA | D7: P
D8: FP
A9: A2 (88 a 138kV) | B9: AZUL | C9: NA | D9: P
D10: FP
B11: AZUL APE | C11: NA | D11: P
D12: FP
B13: DISTRIBUIÇÃO | C13: ELFSM | D13: P
D14: FP
D15: NA
B16: GERAÇÃO | C16: UTE LASA | D16: NA
C17: UTE ALCON | D17: NA
C18: UTE SOL | D18: NA
C19: UHE MASCARENHAS - ENERGEST | D19: NA
C20: UHE SUICA | D20: NA
C21: PCH SAO JOAQUIM | D21: NA
C22: PCH SAO SIMAO | D22: NA
C23: PCH FRANCISCO GROSS | D23: NA
C24: PCH SAO PEDRO | D24: NA
C25: UTE LINHARES | D25: NA
C26: UTE POVOACAO 1 | D26: NA
C27: UTE ARCEL | D27: NA
C28: UTE BIANCOGRES | D28: NA
C29: NOVO GERADOR | D29: NA
A30: A3 (69kV) | B30: AZUL | C30: NA | D30: P
D31: FP
B32: AZUL APE | C32: NA | D32: P
D33: FP
B34: DISTRIBUIÇÃO | D34: P
D35: FP
D36: NA
B37: GERAÇÃO | C37: NA | D37: NA
A38: A3a (30 a 44kV) | B38: AZUL | C38: NA | D38: P
D39: FP
B40: AZUL APE | C40: NA | D40: P
D41: FP
B42: VERDE | C42: NA | D42: NA
D43: P
D44: FP
B45: VERDE APE | C45: NA | D45: NA
D46: P
D47: FP
B48: CONVENCIONAL | C48: NA | D48: NA
B49: GERAÇÃO | C49: NA | D49: NA
A50: A4 (2,3 a 25kV) | B50: AZUL | C50: NA | D50: P
D51: FP
B52: AZUL APE | C52: NA | D52: P
D53: FP
B54: VERDE | C54: NA | D54: NA
D55: P
D56: FP
B57: VERDE APE | C57: NA | D57: NA
D58: P
D59: FP
B60: CONVENCIONAL | C60: NA | D60: NA
B61: DISTRIBUIÇÃO | C61: COELBA | D61: P
D62: FP
D63: NA
B64: GERAÇÃO | C64: NA | D64: NA
A66: TABELA 2 – TARIFAS DE APLICAÇÃO E BASE ECONÔMICA PARA O GRUPO B.
A67: SUBGRUPO | B67: MODALIDADE | C67: CLASSE | D67: SUBCLASSE | E67: POSTO | F67: TARIFAS DE APLICAÇÃO | K67: TARIFAS BASE ECONÔMICA
F68: TUSD | H68: TE | K68: TUSD | M68: TE
F69: R$/kW | G69: R$/MWh | H69: BVD – R$/MWh | I69: BAM – R$/MWh | J69: BVM – R$/MWh | K69: R$/kW | L69: R$/MWh | M69: R$/MWh
A70: B1 | B70: BRANCA | C70: RESIDENCIAL | D70: RESIDENCIAL | E70: P | F70: 0 | G70: 999.02 | H70: 516.91 | K70: 0 | L70: 956.95 | M70: 478.38
E71: INT | F71: 0 | G71: 698.21 | H71: 321.07 | K71: 0 | L71: 662.46 | M71: 299.92
E72: FP | F72: 0 | G72: 397.41 | H72: 321.07 | K72: 0 | L72: 367.97 | M72: 299.92
B73: CONVENCIONAL | C73: RESIDENCIAL | D73: RESIDENCIAL | E73: NA | F73: 0 | G73: 506.32 | H73: 337.39 | K73: 0 | L73: 474.59 | M73: 314.79
D74: BAIXA RENDA(1) | E74: NA | F74: 0 | G74: 348.95 | H74: 325.32 | K74: 0 | L74: 334.57 | M74: 303.57
D75: DESCONTO SOCIAL | E75: NA | F75: 0 | G75: 356.42 | H75: 337.59 | L75: 343.39 | M75: 314.79
A76: B2 | B76: BRANCA | C76: RURAL | D76: NA | E76: P | F76: 0 | G76: 1128.67 | H76: 516.91 | K76: 0 | L76: 1083.88 | M76: 478.38
E77: INT | F77: 0 | G77: 776.01 | H77: 321.07 | K77: 0 | L77: 738.62 | M77: 299.92
E78: FP | F78: 0 | G78: 423.34 | H78: 321.07 | K78: 0 | L78: 393.35 | M78: 299.92
B79: CONVENCIONAL | C79: RURAL | D79: NA | E79: NA | F79: 0 | G79: 506.32 | H79: 337.39 | K79: 0 | L79: 474.59 | M79: 314.79
B80: BRANCA | C80: RURAL | D80: COOPERATIVA DE ELETRIFICAÇÃO RURAL | E80: P | F80: 0 | G80: 1128.67 | H80: 516.91 | K80: 0 | L80: 1083.88 | M80: 478.38
E81: INT | F81: 0 | G81: 776.01 | H81: 321.07 | K81: 0 | L81: 738.62 | M81: 299.92
E82: FP | F82: 0 | G82: 423.34 | H82: 321.07 | K82: 0 | L82: 393.35 | M82: 299.92
B83: CONVENCIONAL | C83: RURAL | D83: COOPERATIVA DE ELETRIFICAÇÃO RURAL | E83: NA | F83: 0 | G83: 506.32 | H83: 337.39 | K83: 0 | L83: 474.59 | M83: 314.79
B84: BRANCA | C84: RURAL | D84: SERVIÇO PÚBLICO DE IRRIGAÇÃO RURAL | E84: P | F84: 0 | G84: 1128.67 | H84: 516.91 | K84: 0 | L84: 1083.88 | M84: 478.38
E85: INT | F85: 0 | G85: 776.01 | H85: 321.07 | K85: 0 | L85: 738.62 | M85: 299.92
E86: FP | F86: 0 | G86: 423.34 | H86: 321.07 | K86: 0 | L86: 393.35 | M86: 299.92
B87: CONVENCIONAL | C87: RURAL | D87: SERVIÇO PÚBLICO DE IRRIGAÇÃO RURAL | E87: NA | F87: 0 | G87: 506.32 | H87: 337.39 | K87: 0 | L87: 474.59 | M87: 314.79
A88: B3 | B88: BRANCA | C88: NA | D88: NA | E88: P | F88: 0 | G88: 1128.67 | H88: 516.91 | K88: 0 | L88: 1083.88 | M88: 478.38
E89: INT | F89: 0 | G89: 776.01 | H89: 321.07 | K89: 0 | L89: 738.62 | M89: 299.92
E90: FP | F90: 0 | G90: 423.34 | H90: 321.07 | K90: 0 | L90: 393.35 | M90: 299.92
B91: CONVENCIONAL | C91: NA | D91: NA | E91: NA | F91: 0 | G91: 506.32 | H91: 337.39 | K91: 0 | L91: 474.59 | M91: 314.79
A92: B4 | B92: CONVENCIONAL | C92: ILUMINAÇÃO PÚBLICA | D92: B4a – REDE DE DISTRIBUIÇÃO | E92: NA | F92: 0 | G92: 278.48 | H92: 185.56 | K92: 0 | L92: 261.03 | M92: 173.13
D93: B4b – BULBO DE LÂMPADA | E93: NA | F93: 0 | G93: 303.79 | H93: 202.43 | K93: 0 | L93: 284.76 | M93: 188.87

Sheet Fatura B1 (GD) OK
B2: B1 Res | E2: Vigência das Tarifas: | F2: 45695 | M2: Bandeira | N2: R$/kWh | O2: ANEEL em 29/06 | Q2: TUSD FIO B
M3: VERDE | N3: 0
B4: TARIFA | C4: TARIFA ANTIGA - REH 3370/2024 | F4: TARIFA NOVA - REH xxxx/2025 | I4: Tarifas Proporcionalizadas | M4: BAM | N4: =[1]BANDEIRA!$D$5 -> 0.01885 | Q4: TARIFA | R4: =C4 -> TARIFA ANTIGA - REH 3370/2024 | U4: =F4 -> TARIFA NOVA - REH xxxx/2025 | X4: Tarifas Proporcionalizadas
C5: Tusd | D5: TE | E5: TUSD + TE | F5: Tusd | G5: TE | H5: TUSD + TE | I5: Tusd | J5: TE | K5: TUSD + TE | M5: BVM1 | N5: =[1]BANDEIRA!$D$6 -> 0.04463 | R5: Tusd (R$/kWh) | U5: Tusd (R$/kWh) | X5: Tusd (R$/kWh)
B6: B1 | C6: ='TABELA DE TARIFAS ANTIGAS'!G71/1000 -> 0.46863 | D6: ='TABELA DE TARIFAS ANTIGAS'!H71/1000 -> 0.32068 | E6: =C6+D6 -> 0.78931 | F6: ='TABELA DE TARIFAS NOVAS'!G73/1000 -> 0.50632 | G6: ='TABELA DE TARIFAS NOVAS'!H73/1000 -> 0.33739 | H6: =F6+G6 -> 0.84371 | I6: =((C6*$C$14)+(F6*$D$14))/($D$14+$C$14) -> 0.48552552 | J6: =((D6*$C$14)+(G6*$D$14))/($D$14+$C$14) -> 0.32817069 | K6: =I6+J6 -> 0.81369621 | M6: BVM2 | N6: =[1]BANDEIRA!$D$7 -> 0.07877 | Q6: =B6 -> B1 | R6: ='[2]FIO B'!H11/1000 -> 0.18823431 | U6: ='[2]FIO B'!K11/1000 -> 0.20383072 | X6: =((R6*$C$14)+(U6*$D$14))/($D$14+$C$14) -> 0.19522581
B7: CDE Escassez Hídrica | C7: 0.00017567286 | D7: 0.0034297355 | E7: 0.0036054084 | F7: =T11 -> 0.00018774721 | G7: =U11 -> -0.0044031307 | H7: =F7+G7 -> -0.0042153835 | I7: =((C7*$C$14)+(F7*$D$14))/($D$14+$C$14) -> 0.0001810855 | J7: =((D7*$C$14)+(G7*$D$14))/($D$14+$C$14) -> -8.1549352e-05 | K7: =I7+J7 -> 9.953615e-05 | M7: Escassez Hídrica | N7: 0.142
B8: TE SCEE | G8: =G6*15% -> 0.0506085 | J8: =((D8*$C$14)+(G8*$D$14))/($D$14+$C$14) -> 0.022686569 | P8: CUSTO | R8: Part. TUSD (%) | S8: Part. TE (%) | T8: Tusd (R$/kWh) | U8: TE (R$/kWh)
P9: CDE CONTAS
H10: Fatura | L10: Vigência das Tarifas (troca Bandeira): | M10: =EOMONTH(B14,0)+1 -> 45689 | P10: CDE COVID | U10: 0
B11: INSTALAÇÃO | C11: 73278 | H11: =E14 -> 45707 | K11: Altere a bandeira na célula abaixo | P11: CDE ESCASSEZ HÍDRICA | T11: =0.187747214948319/1000 -> 0.00018774721 | U11: =-4.40313074144798/1000 -> -0.0044031307
K12: BVM1 | L12: BVM2
B13: Leitura Anterior | C13: Nº de dias tarifa Anterior | D13: Nº de dias tarifa Nova | E13: Leitura Atual | J13: Leitura Anterior | K13: Nº de dias tarifa Anterior | L13: Nº de dias tarifa Nova | M13: Leitura Atual
B14: 45678 | C14: =IF((F2-B14-1)<0,0,(F2-B14-1)) -> 16 | D14: =E14-F2+1 -> 13 | E14: 45707 | J14: =B14 -> 45678 | K14: =IF((M10-J14-1)<0,0,(M10-J14-1)) -> 10 | L14: =M14-M10+1 -> 19 | M14: =E14 -> 45707
B17: Perc. de Redução da Energia Injetada | E17: TUSD | F17: 1 | G17: TE | H17: 1 | M17: Documento Impressão | O17: 30006757412
B19: Descrição | C19: Unidade | D19: Quantidade | E19: Preço Unit (R$) com tributos | F19: Valor Total (R$) | G19: PIS/COFINS (R$) | H19: Base de Cálculo ICMS (R$) | I19: Alíquota ICMS (%) | J19: ICMS (R$) | K19: Preço Unit (R$) | L19: Tributos | M19: Base de Cálc (R$) | N19: Alíquota (%) | O19: Valor (R$)
R20: TUSD Fio B | S20: Receita Fio B
B21: TUSD - Consumo | C21: kWh | D21: 506 | E21: =(ROUND(D21*K21,2)+ROUND(G21,2)+ROUND(J21,2))/ROUND(D21,4) -> 0.60488142 | F21: =ROUND(D21*E21,2) -> 306.07 | G21: =((D21*K21)/(1-$N$21-$N$23))*($N$21+$N$23) -> 8.357706 | H21: =((D21*K21)/(1-$N$21-$N$23)/(1-$I$21)) -> 306.0646 | I21: 0.17 | J21: =(H21*$I$21) -> 52.030982 | K21: =IF(AND($B$14<$F$2,$E$14<$F$2),C6,IF($B$14<$F$2,I6,F6)) -> 0.48552552 | L21: PIS | M21: =D71 -> 460.78999 | N21: 0.0059 | O21: =ROUND(M21*N21,2) -> 2.72 | R21: =IF(AND($B$14<$F$2,$E$14<$F$2),R6,IF($B$14<$F$2,X6,U6)) -> 0.19522581 | S21: =D21*R21 -> 98.784258
B22: TE - Consumo | C22: kWh | D22: =D21 -> 506 | E22: =(ROUND(D22*K22,2)+ROUND(G22,2)+ROUND(J22,2))/ROUND(D22,4) -> 0.40883399 | F22: =ROUND(D22*E22,2) -> 206.87 | G22: =((D22*K22)/(1-$N$21-$N$23))*($N$21+$N$23) -> 5.6490422 | H22: =ROUND((D22*K22)/(1-$N$21-$N$23)/(1-$I$21),8) -> 206.87158 | J22: =ROUND(H22*$I$21,2) -> 35.17 | K22: =IF(AND($B$14<$F$2,$E$14<$F$2),D6,IF($B$14<$F$2,J6,G6)) -> 0.32817069 | L22: PIS Inj | M22: =D72 -> -326.02626 | N22: =N21 -> 0.0059 | O22: =ROUND(M22*N22,2) -> -1.92
B23: Adicional BAM | C23: kWh | D23: =IF($K$12=M4,($D$21*($K$14)/($L$14+$K$14)),0)+IF($L$12=M4,($D$21*($L$14)/($L$14+$K$14)),0) -> 0 | E23: =IFERROR((ROUND(D23*K23,2)+ROUND(G23,2)+ROUND(J23,2))/ROUND(D23,4), 0) -> 0 | F23: =ROUND(D23*E23,2) -> 0 | G23: =((D23*K23)/(1-$N$21-$N$23))*($N$21+$N$23) -> 0 | H23: =ROUND((D23*K23)/(1-$N$21-$N$23)/(1-$I$21),8) -> 0 | J23: =ROUND(H23*$I$21,2) -> 0 | K23: =N4 -> 0.01885 | L23: COFINS | M23: =M21 -> 460.78999 | N23: 0.027 | O23: =ROUND(M23*N23,2) -> 12.44
B24: Adicional BVM1 | C24: kWh | D24: =IF($K$12=M5,($D$21*($K$14)/($L$14+$K$14)),0)+IF($L$12=M5,($D$21*($L$14)/($L$14+$K$14)),0) -> 174.48276 | E24: =IFERROR((ROUND(D24*K24,2)+ROUND(G24,2)+ROUND(J24,2))/ROUND(D24,4), 0) -> 0.055592872 | F24: =ROUND(D24*E24,2) -> 9.7 | G24: =((D24*K24)/(1-$N$21-$N$23))*($N$21+$N$23) -> 0.2649134 | H24: =ROUND((D24*K24)/(1-$N$21-$N$23)/(1-$I$21),8) -> 9.7012999 | J24: =ROUND(H24*$I$21,2) -> 1.65 | K24: =N5 -> 0.04463 | L24: COFINS Inj | M24: =M22 -> -326.02626 | N24: =N23 -> 0.027 | O24: =ROUND(M24*N24,2) -> -8.8
B25: Adicional BVM2 | C25: kWh | D25: =IF($K$12=M6,($D$21*($K$14)/($L$14+$K$14)),0)+IF($L$12=M6,($D$21*($L$14)/($L$14+$K$14)),0) -> 331.51724 | E25: =IFERROR((ROUND(D25*K25,2)+ROUND(G25,2)+ROUND(J25,2))/ROUND(D25,4), 0) -> 0.098124622 | F25: =ROUND(D25*E25,2) -> 32.53 | G25: =((D25*K25)/(1-$N$21-$N$23))*($N$21+$N$23) -> 0.88836508 | H25: =ROUND((D25*K25)/(1-$N$21-$N$23)/(1-$I$21),8) -> 32.532504 | J25: =ROUND(H25*$I$21,2) -> 5.53 | K25: =N6 -> 0.07877
B26: Adicional EH | C26: kWh | D26: =IF($K$12=M7,($D$21*($K$14)/($L$14+$K$14)),0)+IF($L$12=M7,($D$21*($L$14)/($L$14+$K$14)),0) -> 0 | E26: =IFERROR((ROUND(D26*K26,2)+ROUND(G26,2)+ROUND(J26,2))/ROUND(D26,4), 0) -> 0 | F26: =ROUND(D26*E26,2) -> 0 | G26: =((D26*K26)/(1-$N$21-$N$23))*($N$21+$N$23) -> 0 | H26: =ROUND((D26*K26)/(1-$N$21-$N$23)/(1-$I$21),8) -> 0 | J26: =ROUND(H26*$I$21,2) -> 0 | K26: =N7 -> 0.142
B28: TUSD - Consumo inj | C28: kWh | D28: -358 | E28: =IFERROR((ROUND(D28*K28,2)+ROUND(G28,2)+ROUND(J28,2))/ROUND(D28,4),0) -> 0.50203911 | F28: =ROUND(D28*E28,2) -> -179.73 | G28: =((D28*K28)/(1-$N$22-$N$24))*($N$22+$N$24) -> -5.9131596 | H28: 0 | I28: 0 | J28: =H28*$I$21 -> 0 | K28: =K21 -> 0.48552552
B29: TE - Consumo inj | C29: kWh | D29: =D28 -> -358 | E29: =IFERROR((ROUND(D29*K29,2)+ROUND(G29,2)+ROUND(J29,2))/ROUND(D29,4),0) -> 0.40885475 | F29: =ROUND(D29*E29,2) -> -146.37 | G29: =((D29*K29)/(1-$N$22-$N$24))*($N$22+$N$24) -> -3.9967532 | H29: =ROUND((D29*K29)/(1-$N$22-$N$24)/(1-$I$21),8) -> -146.36369 | I29: =I21 -> 0.17 | J29: =H29*$I$21 -> -24.881827 | K29: =K22 -> 0.32817069
B30: Adicional BAM inj | C30: kWh | D30: =IF($K$12=M4,($D$28*($K$14)/($K$14+$L$14)),0)+IF($L$12=M4,($D$28*($L$14)/($K$14+$L$14)),0) -> 0 | E30: =IFERROR((ROUND(D30*K30,2)+ROUND(G30,2)+ROUND(J30,2))/ROUND(D30,4),0) -> 0 | F30: =ROUND(D30*E30,2) -> 0 | G30: =((D30*K30)/(1-$N$22-$N$24))*($N$22+$N$24) -> 0 | H30: =(D30*K30)/(1-$N$22-$N$24)/(1-$I$21) -> 0 | J30: =H30*$I$21 -> 0 | K30: =N4 -> 0.01885
B31: Adicional BVM1 inj | C31: kWh | D31: =IF($K$12=M5,($D$28*($K$14)/($K$14+$L$14)),0)+IF($L$12=M5,($D$28*($L$14)/($K$14+$L$14)),0) -> -123.44828 | E31: =IFERROR((ROUND(D31*K31,2)+ROUND(G31,2)+ROUND(J31,2))/ROUND(D31,4),0) -> 0.055650827 | F31: =ROUND(D31*E31,2) -> -6.87 | G31: =((D31*K31)/(1-$N$22-$N$24))*($N$22+$N$24) -> -0.18742885 | H31: =(D31*K31)/(1-$N$22-$N$24)/(1-$I$21) -> -6.8637655 | J31: =H31*$I$21 -> -1.1668401 | K31: =N5 -> 0.04463
B32: Adicional BVM2 inj | C32: kWh | D32: =IF($K$12=M6,($D$28*($K$14)/($K$14+$L$14)),0)+IF($L$12=M6,($D$28*($L$14)/($K$14+$L$14)),0) -> -234.55172 | E32: =IFERROR((ROUND(D32*K32,2)+ROUND(G32,2)+ROUND(J32,2))/ROUND(D32,4),0) -> 0.098144673 | F32: =ROUND(D32*E32,2) -> -23.02 | G32: =((D32*K32)/(1-$N$22-$N$24))*($N$22+$N$24) -> -0.62852707 | H32: =(D32*K32)/(1-$N$22-$N$24)/(1-$I$21) -> -23.017068 | J32: =H32*$I$21 -> -3.9129015 | K32: =N6 -> 0.07877
B33: Adicional EH inj | C33: kWh | D33: =IF($K$12=M7,($D$28*($K$14)/($K$14+$L$14)),0)+IF($L$12=M7,($D$28*($L$14)/($K$14+$L$14)),0) -> 0 | E33: =IFERROR((ROUND(D33*K33,2)+ROUND(G33,2)+ROUND(J33,2))/ROUND(D33,4),0) -> 0 | F33: =ROUND(D33*E33,2) -> 0 | G33: =((D33*K33)/(1-$N$22-$N$24))*($N$22+$N$24) -> 0 | H33: =(D33*K33)/(1-$N$22-$N$24)/(1-$I$21) -> 0 | J33: =H33*$I$21 -> 0 | K33: =N7 -> 0.142
B35: Multas
B36: Juros | F36: 3.08
B37: Bônus/Descontos
B38: Doações
B39: CIP | F39: 44.5
B42: TOTAL | F42: =SUM(F21:F41) -> 246.76 | G42: =SUM(G21:G41) -> 4.434158 | H42: =SUM(H21:H41) -> 378.92546 | J42: =SUM(J21:J41) -> 64.419413
B44: Informativo Escassez | C44: =(D21+D28) -> 148 | D44: =IF(AND($B$14<$F$2,$E$14<$F$2),C7,IF($B$14<$F$2,I7,F7)) -> 0.0001810855 | E44: =IF(AND($B$14<$F$2,$E$14<$F$2),D7,IF($B$14<$F$2,J7,G7)) -> -8.1549352e-05 | F44: =C44*(D44+E44) -> 0.01473135
B46: Fatura B1 Residencial
D47: Qtde | E47: TUSD | F47: TE | G47: TUSD + TE | H47: R$
B48: Fornecimento de Energia Elétrica | H48: =SUM(H50:H66)+SUM(H71:H76) -> 199.1798
B50: Energia Fornecida | D50: =D21 -> 506 | E50: =IF(AND($B$14<$F$2,$E$14<$F$2),C6,IF($B$14<$F$2,I6,F6)) -> 0.48552552 | F50: =IF(AND($B$14<$F$2,$E$14<$F$2),D6,IF($B$14<$F$2,J6,G6)) -> 0.32817069 | G50: =E50+F50 -> 0.81369621 | H50: =ROUND((D50*E50),2)+ROUND((D50*F50),2) -> 411.73
B52: Adicional BAM | D52: =IF($K$12=M4,(D50*(K14)/(K14+L14)),0)+IF($L$12=M4,(D50*(L14)/(K14+L14)),0) -> 0 | F52: =N4 -> 0.01885 | H52: =ROUND(D52*(E52+F52),2) -> 0
B53: Adicional BVM 1 | D53: =IF($K$12=M5,(D50*(K14)/(K14+L14)),0)+IF($L$12=M5,(D50*(L14)/(K14+L14)),0) -> 174.48276 | F53: =N5 -> 0.04463 | H53: =ROUND(D53*(E53+F53),2) -> 7.79
B54: Adicional BVM 2 | D54: =IF($K$12=M6,(D50*(K14)/(K14+L14)),0)+IF($L$12=M6,(D50*(L14)/(K14+L14)),0) -> 331.51724 | F54: =N6 -> 0.07877 | H54: =ROUND(D54*(E54+F54),2) -> 26.11
B55: Adicional Escassez Hídrica | D55: =IF($K$12=M8,(D50*(K14)/(K14+L14)),0)+IF($L$12=M8,(D50*(L14)/(K14+L14)),0) -> 0 | F55: =N8 -> 0 | H55: =ROUND(D55*(E55+F55),2) -> 0
B57: Energia Injetada | D57: =D28 -> -358 | E57: =E50*F17 -> 0.48552552 | F57: =F50 -> 0.32817069 | G57: =E57+F57 -> 0.81369621 | H57: =ROUND((D57*E57),2)+ROUND((D57*F57),2) -> -291.31
B59: Adicional BAM | D59: =IF($K$12=M4,(D57*(K14)/(K14+L14)),0)+IF($L$12=M4,(D57*(L14)/(K14+L14)),0) -> 0 | F59: =F52 -> 0.01885 | H59: =ROUND(D59*(E59+F59),2) -> 0
B60: Adicional BVM 1 | D60: =IF($K$12=M5,(D57*(K14)/(K14+L14)),0)+IF($L$12=M5,(D57*(L14)/(K14+L14)),0) -> -123.44828 | F60: =F53 -> 0.04463 | H60: =ROUND(D60*(E60+F60),2) -> -5.51
B61: Adicional BVM 2 | D61: =IF($K$12=M6,(D57*(K14)/(K14+L14)),0)+IF($L$12=M6,(D57*(L14)/(K14+L14)),0) -> -234.55172 | F61: =F54 -> 0.07877 | H61: =ROUND(D61*(E61+F61),2) -> -18.48
B62: Adicional Escassez Hídrica | D62: =IF($K$12=M8,(D57*(K14)/(K14+L14)),0)+IF($L$12=M8,(D57*(L14)/(K14+L14)),0) -> 0 | F62: =F55 -> 0 | H62: =ROUND(D62*(E62+F62),2) -> 0
H68: =SUM(H50:H67) -> 130.33
D70: Base de Cálculo
B71: PIS | D71: =(H50+H52+H53+H54+H55)/(1-E71-E73) -> 460.78999 | E71: =N21 -> 0.0059 | H71: =D71*E71 -> 2.7186609
B72: PIS Eneg Inj | D72: =(H57+H59+H60+H61+H62+H64+H66)/(1-E71-E73) -> -326.02626 | E72: =E71 -> 0.0059 | H72: =D72*E72 -> -1.923555
B73: COFINS | D73: =D71 -> 460.78999 | E73: =N23 -> 0.027 | H73: =D73*E73 -> 12.44133
B74: COFINS Eneg Inj | D74: =D72 -> -326.02626 | E74: =E73 -> 0.027 | H74: =D74*E74 -> -8.8027091
B75: ICMS | D75: =D71/(1-E75) -> 555.16866 | E75: 0.17 | H75: =D75*E75 -> 94.378673
B76: ICMS Eneg Inj | D76: =((D57*F57)+(H59+H60+H61+H62)+(D64*F64)+(D66*F66))/(1-E72-E74)/(1-E76) -> -176.25058 | E76: =E75 -> 0.17 | H76: =D76*E76 -> -29.962599
B78: Informativo Escassez Hídrica | D78: =D50+D57 -> 148 | E78: =IF(AND($B$14<$F$2,$E$14<$F$2),C7,IF($B$14<$F$2,I7,F7)) -> 0.0001810855 | F78: =IF(AND($B$14<$F$2,$E$14<$F$2),D7,IF($B$14<$F$2,J7,G7)) -> -8.1549352e-05 | H78: =D78*(E78+F78) -> 0.01473135

Sheet Fatura B1 BRe (GD)
B2: B1 Baixa renda | E2: Vigência das Tarifas: | F2: ='[3]Fatura B1 (GD)'!F2 -> 45511 | M2: Bandeira | N2: R$/kWh | O2: ANEEL em 29/06 | Q2: TUSD FIO B
M3: VERDE | N3: 0
B4: TARIFA R$ kWh | C4: TARIFA ANTIGA - REH 3091/2022 | F4: ='[3]Fatura B1 (GD)'!F4 -> TARIFA NOVA - REH xxxx/2024 | I4: Tarifas Proporcionalizadas | M4: BAM | N4: 0.01885 | Q4: TARIFA | R4: =C4 -> TARIFA ANTIGA - REH 3091/2022 | U4: =F4 -> TARIFA NOVA - REH xxxx/2024 | X4: Tarifas Proporcionalizadas
C5: Tusd | D5: TE | E5: TUSD + TE | F5: Tusd | G5: TE | H5: TUSD + TE | I5: Tusd | J5: TE | K5: TUSD + TE | M5: BVM1 | N5: 0.04463 | R5: Tusd (R$/kWh) | U5: Tusd (R$/kWh) | X5: Tusd (R$/kWh)
B6: Baixa renda | C6: 0.28337 | D6: 0.2988 | E6: 0.58217 | F6: 0.28935 | G6: 0.29334 | H6: 0.58269 | I6: =((C6*$C$14)+(F6*$D$14))/($D$14+$C$14) -> 0.28935 | J6: =((D6*$C$14)+(G6*$D$14))/($D$14+$C$14) -> 0.29334 | K6: =I6+J6 -> 0.58269 | M6: BVM2 | N6: 0.07877 | Q6: =B6 -> Baixa renda | R6: 0.17652 | U6: 0.061783268 | X6: 0.061783268
B7: CDE Escassez Hídrica | C7: =0.207830737658616/1000 -> 0.00020783074 | D7: =4.01792/1000 -> 0.00401792 | E7: =C7+D7 -> 0.0042257507 | F7: =T11 -> 0.00020783074 | G7: =U11 -> 0.00402 | H7: =F7+G7 -> 0.0042278307 | I7: =((C7*$C$14)+(F7*$D$14))/($D$14+$C$14) -> 0.00020783074 | J7: =((D7*$C$14)+(G7*$D$14))/($D$14+$C$14) -> 0.00402 | K7: =I7+J7 -> 0.0042278307
B8: TE SCEE | G8: =G6*15% -> 0.044001 | J8: =((D8*$C$14)+(G8*$D$14))/($D$14+$C$14) -> 0.044001 | M8: Escassez Hídrica | N8: 0.142 | P8: CUSTO | R8: Part. TUSD (%) | S8: Part. TE (%) | T8: Tusd (R$/kWh) | U8: TE (R$/kWh)
P9: CDE CONTAS
H10: Fatura | L10: Vigência das Tarifas (troca Bandeira): | M10: =EOMONTH(B14,0)+1 -> 45689 | P10: CDE COVID | U10: =5.61/1000 -> 0.00561
B11: INSTALAÇÃO | C11: 1041172 | H11: =E14 -> 45707 | K11: Altere a bandeira na célula abaixo | P11: CDE ESCASSEZ HÍDRICA | T11: =0.207830737658616/1000 -> 0.00020783074 | U11: =4.02/1000 -> 0.00402 | W11: prop
K12: ='Fatura B1 (GD) OK'!K12 -> BVM1 | L12: ='Fatura B1 (GD) OK'!L12 -> BVM2 | P12: 0 - 30 | Q12: 0.65 | U12: =$U$11*(1-Q12) -> 0.001407 | W12: =((T12*$C$14)+(U12*$D$14))/($D$14+$C$14) -> 0.001407
B13: Leitura Anterior | C13: Nº de dias tarifa Anterior | D13: Nº de dias tarifa Nova | E13: Leitura Atual | J13: Leitura Anterior | K13: Nº de dias tarifa Anterior | L13: Nº de dias tarifa Nova | M13: Leitura Atual | P13: 31- 100 | Q13: 0.4 | U13: =$U$11*(1-Q13) -> 0.002412 | W13: =((T13*$C$14)+(U13*$D$14))/($D$14+$C$14) -> 0.002412
B14: ='Fatura B1 (GD) OK'!B14 -> 45678 | C14: =IF((F2-B14-1)<0,0,(F2-B14-1)) -> 0 | D14: =E14-F2+1 -> 197 | E14: ='Fatura B1 (GD) OK'!E14 -> 45707 | J14: =B14 -> 45678 | K14: =IF((M10-J14-1)<0,0,(M10-J14-1)) -> 10 | L14: =M14-M10+1 -> 19 | M14: =E14 -> 45707 | P14: 101 - 220 | Q14: 0.1 | U14: =$U$11*(1-Q14) -> 0.003618 | W14: =((T14*$C$14)+(U14*$D$14))/($D$14+$C$14) -> 0.003618
P15: >220 | Q15: 0 | U15: =$U$11*(1-Q15) -> 0.00402 | W15: =((T15*$C$14)+(U15*$D$14))/($D$14+$C$14) -> 0.00402
B16: CONSUMO | D16: 537
B17: INJEÇÃO | D17: 221
B18: DIFERENÇA | D18: 316
B19: COMPENSAÇÃO | D19: =D16-D18 -> 221 | M19: Documento impressão: | O19: 241002228329
B21: Descrição | C21: Unidade | D21: Quantidade | E21: Preço Unit (R$) com tributos | F21: Valor Total (R$) | G21: PIS/COFINS (R$) | H21: Base de Cálculo ICMS (R$) | I21: Alíquota ICMS (%) | J21: ICMS (R$) | K21: Preço Unit (R$) | L21: Tributos | M21: Base de Cálc (R$) | N21: Alíquota (%) | O21: Valor (R$)
B23: Desconto Bx renda | D23: =-K168 -> -50.066645 | E23: 1 | F23: =D23*E23 -> -50.066645 | G23: 0 | H23: 0 | I23: 0 | K23: 1
B24: Valor Bx Renda | D24: =D23 -> -50.066645 | E24: =K24/(1-$N$25-$N$26)/(1-$I$24) -> 1.2458063 | F24: =-1*(F23-J24) -> 60.669545 | G24: 0 | H24: =ROUND((K168*K24)/(1-$N$25-$N$26)/(1-$I$24),2) -> 62.37 | I24: 0.17 | J24: =H24*$I$24 -> 10.6029 | K24: 1
A25: 0.65 | B25: TUSD - EAF 0 a 30 | C25: kWh | D25: =IF(D19>0,30,0) -> 30 | E25: =K25/(1-$N$25-$N$26)/(1-$I$24) -> 0.12616592 | F25: =ROUND(D25*E25,2) -> 3.78 | G25: =ROUND(((D25*K25)/(1-$N$25-$N$26))*($N$25+$N$26),2) -> 0.1 | H25: =ROUND((D25*K25)/(1-$N$25-$N$26)/(1-$I$24),2) -> 3.78 | J25: =H25*$I$24 -> 0.6426 | K25: =K28*(1-A25) -> 0.1012725 | L25: PIS | M25: =D138 -> 280.79826 | N25: ='Fatura B1 (GD) OK'!N21 -> 0.0059 | O25: =ROUND(M25*N25,2) -> 1.66
A26: 0.4 | B26: TUSD - EAF 31 a 100 | C26: kWh | D26: =IF(D19>30,IF(D19>100,70,D19-30),0) -> 70 | E26: =K26/(1-$N$25-$N$26)/(1-$I$24) -> 0.21628443 | F26: =ROUND(D26*E26,2) -> 15.14 | G26: =ROUND(((D26*K26)/(1-$N$25-$N$26))*($N$25+$N$26),2) -> 0.41 | H26: =ROUND((D26*K26)/(1-$N$25-$N$26)/(1-$I$24),2) -> 15.14 | J26: =H26*$I$24 -> 2.5738 | K26: =K28*(1-A26) -> 0.17361 | L26: COFINS | M26: =M25 -> 280.79826 | N26: ='Fatura B1 (GD) OK'!N23 -> 0.027 | O26: =ROUND(M26*N26,2) -> 7.58
A27: 0.1 | B27: TUSD - EAF 101 a 220 | C27: kWh | D27: =IF(D19>100,IF(D19>220,220-100,D19-100),0) -> 120 | E27: =K27/(1-$N$25-$N$26)/(1-$I$24) -> 0.32442665 | F27: =ROUND(D27*E27,2) -> 38.93 | G27: =ROUND(((D27*K27)/(1-$N$25-$N$26))*($N$25+$N$26),2) -> 1.06 | H27: =ROUND((D27*K27)/(1-$N$25-$N$26)/(1-$I$24),2) -> 38.93 | J27: =H27*$I$24 -> 6.6181 | K27: =K28*(1-A27) -> 0.260415
A28: 0 | B28: TUSD - EAF > 220 | C28: kWh | D28: =IF(D19>220,D19-220,0) -> 1 | E28: =K28/(1-$N$25-$N$26)/(1-$I$24) -> 0.36047405 | F28: =ROUND(D28*E28,2) -> 0.36 | G28: =ROUND(((D28*K28)/(1-$N$25-$N$26))*($N$25+$N$26),2) -> 0.01 | H28: =ROUND((D28*K28)/(1-$N$25-$N$26)/(1-$I$24),2) -> 0.36 | J28: =H28*$I$24 -> 0.0612 | K28: =IF(AND($B$13<$F$2,$E$13<$F$2),C6,IF($B$13<$F$2,I6,F6)) -> 0.28935
A29: 0.65 | B29: TUSD - EAFdc 0 a 30 | C29: kWh | D29: =IF(D18>0,30,0) -> 30 | E29: =K29/(1-$N$25-$N$26)/(1-$I$24) -> 0.12616592 | F29: =ROUND(D29*E29,2) -> 3.78 | G29: =ROUND(((D29*K29)/(1-$N$25-$N$26))*($N$25+$N$26),2) -> 0.1 | H29: =ROUND((D29*K29)/(1-$N$25-$N$26)/(1-$I$24),2) -> 3.78 | J29: =H29*$I$24 -> 0.6426 | K29: =K32*(1-A29) -> 0.1012725
A30: 0.4 | B30: TUSD - EAFdc 31 a 100 | C30: kWh | D30: =IF(D18>30,IF(D18>100,70,D18-30),0) -> 70 | E30: =K30/(1-$N$25-$N$26)/(1-$I$24) -> 0.21628443 | F30: =ROUND(D30*E30,2) -> 15.14 | G30: =ROUND(((D30*K30)/(1-$N$25-$N$26))*($N$25+$N$26),2) -> 0.41 | H30: =ROUND((D30*K30)/(1-$N$25-$N$26)/(1-$I$24),2) -> 15.14 | J30: =H30*$I$24 -> 2.5738 | K30: =K32*(1-A30) -> 0.17361
A31: 0.1 | B31: TUSD - EAFdc 101 a 220 | C31: kWh | D31: =IF(D18>100,IF(D18>220,220-100,D18-100),0) -> 120 | E31: =K31/(1-$N$25-$N$26)/(1-$I$24) -> 0.32442665 | F31: =ROUND(D31*E31,2) -> 38.93 | G31: =ROUND(((D31*K31)/(1-$N$25-$N$26))*($N$25+$N$26),2) -> 1.06 | H31: =ROUND((D31*K31)/(1-$N$25-$N$26)/(1-$I$24),2) -> 38.93 | J31: =H31*$I$24 -> 6.6181 | K31: =K32*(1-A31) -> 0.260415
A32: 0 | B32: TUSD - EAFdc > 220 | C32: kWh | D32: =IF(D18>220,D18-220,0) -> 96 | E32: =K32/(1-$N$25-$N$26)/(1-$I$24) -> 0.36047405 | F32: =ROUND(D32*E32,2) -> 34.61 | G32: =ROUND(((D32*K32)/(1-$N$25-$N$26))*($N$25+$N$26),2) -> 0.94 | H32: =ROUND((D32*K32)/(1-$N$25-$N$26)/(1-$I$24),2) -> 34.61 | J32: =H32*$I$24 -> 5.8837 | K32: =IF(AND($B$14<$F$2,$E$14<$F$2),C6,IF($B$14<$F$2,I6,F6)) -> 0.28935
B34: TE - EAF 0 a 30 | C34: kWh | D34: =D25 -> 30 | E34: =K34/(1-$N$25-$N$26)/(1-$I$24) -> 0.12790569 | F34: =ROUND(D34*E34,2) -> 3.84 | G34: =ROUND(((D34*K34)/(1-$N$25-$N$26))*($N$25+$N$26),2) -> 0.1 | H34: =ROUND((D34*K34)/(1-$N$25-$N$26)/(1-$I$24),2) -> 3.84 | J34: =H34*$I$24 -> 0.6528 | K34: =K37*(1-A25) -> 0.102669
B35: TE - EAF 31 a 100 | C35: kWh | D35: =D26 -> 70 | E35: =K35/(1-$N$25-$N$26)/(1-$I$24) -> 0.21926689 | F35: =ROUND(D35*E35,2) -> 15.35 | G35: =ROUND(((D35*K35)/(1-$N$25-$N$26))*($N$25+$N$26),2) -> 0.42 | H35: =ROUND((D35*K35)/(1-$N$25-$N$26)/(1-$I$24),2) -> 15.35 | J35: =H35*$I$24 -> 2.6095 | K35: =K37*(1-A26) -> 0.176004
B36: TE - EAF 101 a 220 | C36: kWh | D36: =D27 -> 120 | E36: =K36/(1-$N$25-$N$26)/(1-$I$24) -> 0.32890034 | F36: =ROUND(D36*E36,2) -> 39.47 | G36: =ROUND(((D36*K36)/(1-$N$25-$N$26))*($N$25+$N$26),2) -> 1.08 | H36: =ROUND((D36*K36)/(1-$N$25-$N$26)/(1-$I$24),2) -> 39.47 | J36: =H36*$I$24 -> 6.7099 | K36: =K37*(1-A27) -> 0.264006
B37: TE - EAF > 220 | C37: kWh | D37: =D28 -> 1 | E37: =K37/(1-$N$25-$N$26)/(1-$I$24) -> 0.36544482 | F37: =ROUND(D37*E37,2) -> 0.37 | G37: =ROUND(((D37*K37)/(1-$N$25-$N$26))*($N$25+$N$26),2) -> 0.01 | H37: =ROUND((D37*K37)/(1-$N$25-$N$26)/(1-$I$24),2) -> 0.37 | J37: =H37*$I$24 -> 0.0629 | K37: =IF(AND($B$14<$F$2,$E$14<$F$2),D6,IF($B$14<$F$2,J6,G6)) -> 0.29334
B38: TE - EAFdc 0 a 30 | C38: kWh | D38: =D29 -> 30 | E38: =K38/(1-$N$25-$N$26)/(1-$I$24) -> 0.12790569 | F38: =ROUND(D38*E38,2) -> 3.84 | G38: =ROUND(((D38*K38)/(1-$N$25-$N$26))*($N$25+$N$26),2) -> 0.1 | H38: =ROUND((D38*K38)/(1-$N$25-$N$26)/(1-$I$24),2) -> 3.84 | J38: =H38*$I$24 -> 0.6528 | K38: =K41*(1-A29) -> 0.102669
B39: TE - EAFdc 31 a 100 | C39: kWh | D39: =D30 -> 70 | E39: =K39/(1-$N$25-$N$26)/(1-$I$24) -> 0.21926689 | F39: =ROUND(D39*E39,2) -> 15.35 | G39: =ROUND(((D39*K39)/(1-$N$25-$N$26))*($N$25+$N$26),2) -> 0.42 | H39: =ROUND((D39*K39)/(1-$N$25-$N$26)/(1-$I$24),2) -> 15.35 | J39: =H39*$I$24 -> 2.6095 | K39: =K41*(1-A30) -> 0.176004
B40: TE - EAFdc 101 a 220 | C40: kWh | D40: =D31 -> 120 | E40: =K40/(1-$N$25-$N$26)/(1-$I$24) -> 0.32890034 | F40: =ROUND(D40*E40,2) -> 39.47 | G40: =ROUND(((D40*K40)/(1-$N$25-$N$26))*($N$25+$N$26),2) -> 1.08 | H40: =ROUND((D40*K40)/(1-$N$25-$N$26)/(1-$I$24),2) -> 39.47 | J40: =H40*$I$24 -> 6.7099 | K40: =K41*(1-A31) -> 0.264006
B41: TE - EAFdc > 220 | C41: kWh | D41: =D32 -> 96 | E41: =K41/(1-$N$25-$N$26)/(1-$I$24) -> 0.36544482 | F41: =ROUND(D41*E41,2) -> 35.08 | G41: =ROUND(((D41*K41)/(1-$N$25-$N$26))*($N$25+$N$26),2) -> 0.96 | H41: =ROUND((D41*K41)/(1-$N$25-$N$26)/(1-$I$24),2) -> 35.08 | J41: =H41*$I$24 -> 5.9636 | K41: =IF(AND($B$14<$F$2,$E$14<$F$2),D6,IF($B$14<$F$2,J6,G6)) -> 0.29334
B43: Adicional BAM | D43: =C175+C212 -> 0 | F43: =(O175+O212)/(1-$N$25-$N$26)/(1-$I$24) -> 0 | G43: =ROUND(((D43*K43)/(1-$N$25-$N$26))*($N$25+$N$26),2) -> 0 | H43: =F43 -> 0 | J43: =H43*$I$24 -> 0 | K43: =K175 -> 0.0065975
B44: Adicional BAM | D44: =C176+C213 -> 0 | F44: =(O176+O213)/(1-$N$25-$N$26)/(1-$I$24) -> 0 | G44: =ROUND(((D44*K44)/(1-$N$25-$N$26))*($N$25+$N$26),2) -> 0 | H44: =F44 -> 0 | J44: =H44*$I$24 -> 0 | K44: =K176 -> 0.01131
B45: Adicional BAM | D45: =C177+C214 -> 0 | F45: =(O177+O214)/(1-$N$25-$N$26)/(1-$I$24) -> 0 | G45: =ROUND(((D45*K45)/(1-$N$25-$N$26))*($N$25+$N$26),2) -> 0 | H45: =F45 -> 0 | J45: =H45*$I$24 -> 0 | K45: =K177 -> 0.016965
B46: Adicional BAM | D46: =C178+C215 -> 0 | F46: =(O178+O215)/(1-$N$25-$N$26)/(1-$I$24) -> 0 | G46: =ROUND(((D46*K46)/(1-$N$25-$N$26))*($N$25+$N$26),2) -> 0 | H46: =F46 -> 0 | J46: =H46*$I$24 -> 0 | K46: =K178 -> 0.01885
B47: Adicional BVM1 | D47: =C184+C221 -> 20.689655 | F47: =(O184+O221)/(1-$N$25-$N$26)/(1-$I$24) -> 0.39865802 | G47: =ROUND(((D47*K47)/(1-$N$25-$N$26))*($N$25+$N$26),2) -> 0.01 | H47: =F47 -> 0.39865802 | J47: =H47*$I$24 -> 0.067771863 | K47: =K184 -> 0.0156205
B48: Adicional BVM1 | D48: =C185+C222 -> 48.275862 | F48: =(O185+O222)/(1-$N$25-$N$26)/(1-$I$24) -> 1.6195482 | G48: =ROUND(((D48*K48)/(1-$N$25-$N$26))*($N$25+$N$26),2) -> 0.04 | H48: =F48 -> 1.6195482 | J48: =H48*$I$24 -> 0.27532319 | K48: =K185 -> 0.026778
B49: Adicional BVM1 | D49: =C186+C223 -> 82.758621 | F49: =(O186+O223)/(1-$N$25-$N$26)/(1-$I$24) -> 4.1360769 | G49: =ROUND(((D49*K49)/(1-$N$25-$N$26))*($N$25+$N$26),2) -> 0.11 | H49: =F49 -> 4.1360769 | J49: =H49*$I$24 -> 0.70313308 | K49: =K186 -> 0.040167
B50: Adicional BVM1 | D50: =C187+C224 -> 33.448276 | F50: =(O187+O224)/(1-$N$25-$N$26)/(1-$I$24) -> 1.8687095 | G50: =ROUND(((D50*K50)/(1-$N$25-$N$26))*($N$25+$N$26),2) -> 0.05 | H50: =F50 -> 1.8687095 | J50: =H50*$I$24 -> 0.31768061 | K50: =K187 -> 0.04463
B51: Adicional BVM2 | D51: =C193+C230 -> 39.310345 | F51: =(O193+O230)/(1-$N$25-$N$26)/(1-$I$24) -> 1.3454708 | G51: =ROUND(((D51*K51)/(1-$N$25-$N$26))*($N$25+$N$26),2) -> 0.04 | H51: =F51 -> 1.3454708 | J51: =H51*$I$24 -> 0.22873004 | K51: =K193 -> 0.0275695
B52: Adicional BVM2 | D52: =C194+C231 -> 91.724138 | F52: =(O194+O231)/(1-$N$25-$N$26)/(1-$I$24) -> 5.4067994 | G52: =ROUND(((D52*K52)/(1-$N$25-$N$26))*($N$25+$N$26),2) -> 0.15 | H52: =F52 -> 5.4067994 | J52: =H52*$I$24 -> 0.91915589 | K52: =K194 -> 0.047262
B53: Adicional BVM2 | D53: =C195+C232 -> 157.24138 | F53: =(O195+O232)/(1-$N$25-$N$26)/(1-$I$24) -> 13.878282 | G53: =ROUND(((D53*K53)/(1-$N$25-$N$26))*($N$25+$N$26),2) -> 0.38 | H53: =F53 -> 13.878282 | J53: =H53*$I$24 -> 2.359308 | K53: =K195 -> 0.070893
B54: Adicional BVM2 | D54: =C196+C233 -> 63.551724 | F54: =(O196+O233)/(1-$N$25-$N$26)/(1-$I$24) -> 6.2290315 | G54: =ROUND(((D54*K54)/(1-$N$25-$N$26))*($N$25+$N$26),2) -> 0.17 | H54: =F54 -> 6.2290315 | J54: =H54*$I$24 -> 1.0589354 | K54: =K196 -> 0.07877
B55: Adicional EH | D55: =C202+C239 -> 0 | F55: =(O202+O239)/(1-$N$25-$N$26)/(1-$I$24) -> 0 | G55: =ROUND(((D55*K55)/(1-$N$25-$N$26))*($N$25+$N$26),2) -> 0 | H55: =F55 -> 0 | J55: =H55*$I$24 -> 0 | K55: =K202 -> 0.0497
B56: Adicional EH | D56: =C203+C240 -> 0 | F56: =(O203+O240)/(1-$N$25-$N$26)/(1-$I$24) -> 0 | G56: =ROUND(((D56*K56)/(1-$N$25-$N$26))*($N$25+$N$26),2) -> 0 | H56: =F56 -> 0 | J56: =H56*$I$24 -> 0 | K56: =K203 -> 0.0852
B57: Adicional EH | D57: =C204+C241 -> 0 | F57: =(O204+O241)/(1-$N$25-$N$26)/(1-$I$24) -> 0 | G57: =ROUND(((D57*K57)/(1-$N$25-$N$26))*($N$25+$N$26),2) -> 0 | H57: =F57 -> 0 | J57: =H57*$I$24 -> 0 | K57: =K204 -> 0.1278
B58: Adicional EH | D58: =C205+C242 -> 0 | F58: =(O205+O242)/(1-$N$25-$N$26)/(1-$I$24) -> 0 | G58: =ROUND(((D58*K58)/(1-$N$25-$N$26))*($N$25+$N$26),2) -> 0 | H58: =F58 -> 0 | J58: =H58*$I$24 -> 0 | K58: =K205 -> 0.142
A60: 0.65 | B60: TUSD - EAF Inj | C60: kWh | D60: =-(IF(D17>0,30,0)) -> -30 | E60: =K60/(1-$N$25-$N$26)/(1-$I$60) -> 0.10471771 | F60: =ROUND(D60*E60,2) -> -3.14 | G60: =ROUND(((D60*K60)/(1-$N$25-$N$26))*($N$25+$N$26),2) -> -0.1 | H60: =ROUND((D60*K60)/(1-$N$25-$N$26)/(1-$I$24),2) -> -3.78 | J60: =H60*$I$24 -> -0.6426 | K60: =K63*(1-A60) -> 0.1012725 | L60: PIS Inj | M60: =D139 -> -108.4893 | N60: =N25 -> 0.0059 | O60: =ROUND(M60*N60,2) -> -0.64
A61: 0.4 | B61: TUSD - EAF Inj | C61: kWh | D61: =-(IF(D17>30,IF(D17>100,70,D17-30),0)) -> -70 | E61: =K61/(1-$N$25-$N$26)/(1-$I$60) -> 0.17951608 | F61: =ROUND(D61*E61,2) -> -12.57 | G61: =ROUND(((D61*K61)/(1-$N$25-$N$26))*($N$25+$N$26),2) -> -0.41 | H61: =ROUND((D61*K61)/(1-$N$25-$N$26)/(1-$I$24),2) -> -15.14 | J61: =H61*$I$24 -> -2.5738 | K61: =K63*(1-A61) -> 0.17361 | L61: COFINS Inj | M61: =M60 -> -108.4893 | N61: =N26 -> 0.027 | O61: =ROUND(M61*N61,2) -> -2.93
A62: 0.1 | B62: TUSD - EAF Inj | C62: kWh | D62: =-(IF(D17>100,IF(D17>220,220-100,D17-100),0)) -> -120 | E62: =K62/(1-$N$25-$N$26)/(1-$I$60) -> 0.26927412 | F62: =ROUND(D62*E62,2) -> -32.31 | G62: =ROUND(((D62*K62)/(1-$N$25-$N$26))*($N$25+$N$26),2) -> -1.06 | H62: =ROUND((D62*K62)/(1-$N$25-$N$26)/(1-$I$24),2) -> -38.93 | J62: =H62*$I$24 -> -6.6181 | K62: =K63*(1-A62) -> 0.260415
A63: 0 | B63: TUSD - EAF Inj | C63: kWh | D63: =-(IF(D17>220,D17-220,0)) -> -1 | E63: =K63/(1-$N$25-$N$26)/(1-$I$60) -> 0.29919346 | F63: =ROUND(D63*E63,2) -> -0.3 | G63: =ROUND(((D63*K63)/(1-$N$25-$N$26))*($N$25+$N$26),2) -> -0.01 | H63: =ROUND((D63*K63)/(1-$N$25-$N$26)/(1-$I$24),2) -> -0.36 | J63: =H63*$I$24 -> -0.0612 | K63: =IF(AND($B$14<$F$2,$E$14<$F$2),C6,IF($B$14<$F$2,I6,F6)) -> 0.28935
B65: TE - EAF Inj | C65: kWh | D65: =D60 -> -30 | E65: =K65/(1-$N$25-$N$26)/(1-$I$24) -> 0.12790569 | F65: =ROUND(D65*E65,2) -> -3.84 | G65: =ROUND(((D65*K65)/(1-$N$25-$N$26))*($N$25+$N$26),2) -> -0.1 | H65: =ROUND((D65*K65)/(1-$N$25-$N$26)/(1-$I$24),2) -> -3.84 | J65: =H65*$I$24 -> -0.6528 | K65: =$K$68*(1-A60) -> 0.102669
B66: TE - EAF Inj | C66: kWh | D66: =D61 -> -70 | E66: =K66/(1-$N$25-$N$26)/(1-$I$24) -> 0.21926689 | F66: =ROUND(D66*E66,2) -> -15.35 | G66: =ROUND(((D66*K66)/(1-$N$25-$N$26))*($N$25+$N$26),2) -> -0.42 | H66: =ROUND((D66*K66)/(1-$N$25-$N$26)/(1-$I$24),2) -> -15.35 | J66: =H66*$I$24 -> -2.6095 | K66: =$K$68*(1-A61) -> 0.176004
B67: TE - EAF Inj | C67: kWh | D67: =D62 -> -120 | E67: =K67/(1-$N$25-$N$26)/(1-$I$24) -> 0.32890034 | F67: =ROUND(D67*E67,2) -> -39.47 | G67: =ROUND(((D67*K67)/(1-$N$25-$N$26))*($N$25+$N$26),2) -> -1.08 | H67: =ROUND((D67*K67)/(1-$N$25-$N$26)/(1-$I$24),2) -> -39.47 | J67: =H67*$I$24 -> -6.7099 | K67: =$K$68*(1-A62) -> 0.264006
B68: TE - EAF Inj | C68: kWh | D68: =D63 -> -1 | E68: =K68/(1-$N$25-$N$26)/(1-$I$24) -> 0.36544482 | F68: =ROUND(D68*E68,2) -> -0.37 | G68: =ROUND(((D68*K68)/(1-$N$25-$N$26))*($N$25+$N$26),2) -> -0.01 | H68: =ROUND((D68*K68)/(1-$N$25-$N$26)/(1-$I$24),2) -> -0.37 | J68: =H68*$I$24 -> -0.0629 | K68: =IF(AND($B$14<$F$2,$E$14<$F$2),D6,IF($B$14<$F$2,J6,G6)) -> 0.29334
B70: Adicional BAM Inj | D70: =C251 -> 0 | F70: =O251/(1-$N$25-$N$26)/(1-$I$24) -> 0 | G70: =ROUND(((D70*K70)/(1-$N$25-$N$26))*($N$25+$N$26),2) -> 0 | H70: =F70 -> 0 | J70: =H70*$I$24 -> 0 | K70: =K43 -> 0.0065975
B71: Adicional BAM Inj | D71: =C252 -> 0 | F71: =O252/(1-$N$25-$N$26)/(1-$I$24) -> 0 | G71: =ROUND(((D71*K71)/(1-$N$25-$N$26))*($N$25+$N$26),2) -> 0 | H71: =F71 -> 0 | J71: =H71*$I$24 -> 0 | K71: =K44 -> 0.01131
B72: Adicional BAM Inj | D72: =C253 -> 0 | F72: =O253/(1-$N$25-$N$26)/(1-$I$24) -> 0 | G72: =ROUND(((D72*K72)/(1-$N$25-$N$26))*($N$25+$N$26),2) -> 0 | H72: =F72 -> 0 | J72: =H72*$I$24 -> 0 | K72: =K45 -> 0.016965
B73: Adicional BAM Inj | D73: =C254 -> 0 | F73: =O254/(1-$N$25-$N$26)/(1-$I$24) -> 0 | G73: =ROUND(((D73*K73)/(1-$N$25-$N$26))*($N$25+$N$26),2) -> 0 | H73: =F73 -> 0 | J73: =H73*$I$24 -> 0 | K73: =K46 -> 0.01885
B74: Adicional BVM1 Inj | D74: =C260 -> -10.344828 | F74: =O260/(1-$N$25-$N$26)/(1-$I$24) -> -0.19932901 | G74: =ROUND(((D74*K74)/(1-$N$25-$N$26))*($N$25+$N$26),2) -> -0.01 | H74: =F74 -> -0.19932901 | J74: =H74*$I$24 -> -0.033885931 | K74: =K47 -> 0.0156205
B75: Adicional BVM1 Inj | D75: =C261 -> -24.137931 | F75: =O261/(1-$N$25-$N$26)/(1-$I$24) -> -0.8097741 | G75: =ROUND(((D75*K75)/(1-$N$25-$N$26))*($N$25+$N$26),2) -> -0.02 | H75: =F75 -> -0.8097741 | J75: =H75*$I$24 -> -0.1376616 | K75: =K48 -> 0.026778
B76: Adicional BVM1 Inj | D76: =C262 -> -41.37931 | F76: =O262/(1-$N$25-$N$26)/(1-$I$24) -> -2.0680385 | G76: =ROUND(((D76*K76)/(1-$N$25-$N$26))*($N$25+$N$26),2) -> -0.06 | H76: =F76 -> -2.0680385 | J76: =H76*$I$24 -> -0.35156654 | K76: =K49 -> 0.040167
B77: Adicional BVM1 Inj | D77: =C263 -> -0.34482759 | F77: =O263/(1-$N$25-$N$26)/(1-$I$24) -> -0.024916126 | G77: =ROUND(((D77*K77)/(1-$N$25-$N$26))*($N$25+$N$26),2) -> 0 | H77: =F77 -> -0.024916126 | J77: =H77*$I$24 -> -0.0042357414 | K77: =K50 -> 0.04463
B78: Adicional BVM2 Inj | D78: =C269 -> -19.655172 | F78: =O269/(1-$N$25-$N$26)/(1-$I$24) -> -0.6727354 | G78: =ROUND(((D78*K78)/(1-$N$25-$N$26))*($N$25+$N$26),2) -> -0.02 | H78: =F78 -> -0.6727354 | J78: =H78*$I$24 -> -0.11436502 | K78: =K51 -> 0.0275695
B79: Adicional BVM2 Inj | D79: =C270 -> -45.862069 | F79: =O270/(1-$N$25-$N$26)/(1-$I$24) -> -2.7033997 | G79: =ROUND(((D79*K79)/(1-$N$25-$N$26))*($N$25+$N$26),2) -> -0.07 | H79: =F79 -> -2.7033997 | J79: =H79*$I$24 -> -0.45957795 | K79: =K52 -> 0.047262
B80: Adicional BVM2 Inj | D80: =C271 -> -78.62069 | F80: =O271/(1-$N$25-$N$26)/(1-$I$24) -> -6.9391411 | G80: =ROUND(((D80*K80)/(1-$N$25-$N$26))*($N$25+$N$26),2) -> -0.19 | H80: =F80 -> -6.9391411 | J80: =H80*$I$24 -> -1.179654 | K80: =K53 -> 0.070893
B81: Adicional BVM2 Inj | D81: =C272 -> -0.65517241 | F81: =O272/(1-$N$25-$N$26)/(1-$I$24) -> -0.062290315 | G81: =ROUND(((D81*K81)/(1-$N$25-$N$26))*($N$25+$N$26),2) -> 0 | H81: =F81 -> -0.062290315 | J81: =H81*$I$24 -> -0.010589354 | K81: =K54 -> 0.07877
B82: Adicional EH Inj | D82: =C278 -> 0 | F82: =O278/(1-$N$25-$N$26)/(1-$I$24) -> 0 | G82: =ROUND(((D82*K82)/(1-$N$25-$N$26))*($N$25+$N$26),2) -> 0 | H82: =F82 -> 0 | J82: =H82*$I$24 -> 0 | K82: =K55 -> 0.0497
B83: Adicional EH Inj | D83: =C279 -> 0 | F83: =O279/(1-$N$25-$N$26)/(1-$I$24) -> 0 | G83: =ROUND(((D83*K83)/(1-$N$25-$N$26))*($N$25+$N$26),2) -> 0 | H83: =F83 -> 0 | J83: =H83*$I$24 -> 0 | K83: =K56 -> 0.0852
B84: Adicional EH Inj | D84: =C280 -> 0 | F84: =O280/(1-$N$25-$N$26)/(1-$I$24) -> 0 | G84: =ROUND(((D84*K84)/(1-$N$25-$N$26))*($N$25+$N$26),2) -> 0 | H84: =F84 -> 0 | J84: =H84*$I$24 -> 0 | K84: =K57 -> 0.1278
B85: Adicional EH Inj | D85: =C281 -> 0 | F85: =O281/(1-$N$25-$N$26)/(1-$I$24) -> 0 | G85: =ROUND(((D85*K85)/(1-$N$25-$N$26))*($N$25+$N$26),2) -> 0 | H85: =F85 -> 0 | J85: =H85*$I$24 -> 0 | K85: =K58 -> 0.142
B87: Juros | F87: 0.46
B88: Multas | F88: 4.55
B89: CIP
B93: TOTAL | F93: =SUM(F23:F92) -> 233.10585 | G93: =SUM(G25:G92) -> 5.65 | H93: =SUM(H23:H92) -> 269.97295 | J93: =SUM(J23:J92) -> 45.895402
B95: Informativo Escassez | F95: =(D25*AK12)+(D26*AK13)+(D27*AK14)+(D28*AK15) -> 0
B97: Consumo = | G97: =D16 -> 537 | H97: kWh
B98: Energia Injetada = | G98: =D17 -> 221 | H98: kWh | J98: Doc Impr | K98: =O19 -> 241002228329
G99: =G98 -> 221 | H99: =G97-G99 -> 316
B100: Perc. de Redução da Energia Injetada | E100: TUSD | F100: 1 | G100: TE | H100: 1
B102: Fatura B1 Baixa Renda
D103: Qtde | E103: TUSD | F103: TE | G103: TUSD + TE | H103: R$
B104: Fornecimento de Energia Elétrica | H104: =SUM(H106:H135)+SUM(H138:H143) -> 207.60116
J105: Bx Ren
A106: 0.65 | B106: Consumo 0 - 30 | D106: =D25 -> 30 | E106: =$E$119*(1-A106) -> 0.1012725 | F106: =$F$119*(1-A106) -> 0.102669 | G106: =E106+F106 -> 0.2039415 | H106: =ROUND((D106*E106),2)+ROUND((D106*F106),2) -> 6.12 | J106: =IF(D16>0,30,0) -> 30
A107: 0.4 | B107: Consumo 31 - 100 | D107: =D26 -> 70 | E107: =$E$119*(1-A107) -> 0.17361 | F107: =$F$119*(1-A107) -> 0.176004 | G107: =E107+F107 -> 0.349614 | H107: =ROUND((D107*E107),2)+ROUND((D107*F107),2) -> 24.47 | J107: =IF(D16>30,IF(D16>100,70,D16-30),0) -> 70
A108: 0.1 | B108: Consumo 101 - 220 | D108: =D27 -> 120 | E108: =$E$119*(1-A108) -> 0.260415 | F108: =$F$119*(1-A108) -> 0.264006 | G108: =E108+F108 -> 0.524421 | H108: =ROUND((D108*E108),2)+ROUND((D108*F108),2) -> 62.93 | J108: =IF(D16>100,IF(D16>220,220-100,D16-100),0) -> 120
A109: 0 | B109: Consumo > 220 | D109: =D28 -> 1 | E109: =$E$119*(1-A109) -> 0.28935 | F109: =$F$119*(1-A109) -> 0.29334 | G109: =E109+F109 -> 0.58269 | H109: =ROUND((D109*E109),2)+ROUND((D109*F109),2) -> 0.58 | J109: =IF(D16>220,D16-220,0) -> 317
B111: Adicional BAM | H111: =O179 -> 0
B112: Adicional BVM 1 | H112: =O188 -> 2.49
B113: Adicional BVM 2 | H113: =O197 -> 8.33
B114: Adicional Escassez Hídrica | H114: =O206 -> 0
A116: 0.65 | B116: Energia Fornecida 0 - 30 | D116: =D29 -> 30 | E116: =$E$119*(1-A116) -> 0.1012725 | F116: =$F$119*(1-A116) -> 0.102669 | G116: =E116+F116 -> 0.2039415 | H116: =ROUND((D116*E116),2)+ROUND((D116*F116),2) -> 6.12
A117: 0.4 | B117: Energia Fornecida 31 - 100 | D117: =D30 -> 70 | E117: =$E$119*(1-A117) -> 0.17361 | F117: =$F$119*(1-A117) -> 0.176004 | G117: =E117+F117 -> 0.349614 | H117: =ROUND((D117*E117),2)+ROUND((D117*F117),2) -> 24.47
...

Sheet B1 Res (GD) Branca OK
B2: B1 Res TB | E2: Vigência das Tarifas: | F2: 46241 | H2: TARIFA BRANCA | M2: Bandeira | N2: R$/kWh | Q2: TUSD FIO B
M3: VERDE | N3: 0
B4: TARIFA | C4: ='Fatura B1 (GD) OK'!C4:E4 -> TARIFA ANTIGA - REH 3370/2024 | F4: ='Fatura B1 (GD) OK'!F4 -> TARIFA NOVA - REH xxxx/2025 | I4: Tarifas Proporcionalizadas | M4: BAM | N4: =[1]BANDEIRA!$D$5 -> 0.01885 | Q4: TARIFA | R4: =C4 -> TARIFA ANTIGA - REH 3370/2024 | U4: =F4 -> TARIFA NOVA - REH xxxx/2025 | X4: Tarifas Proporcionalizadas
C5: Tusd | D5: TE | E5: TUSD + TE | F5: Tusd | G5: TE | H5: TUSD + TE | I5: Tusd | J5: TE | K5: TUSD + TE | M5: BVM1 | N5: =[1]BANDEIRA!$D$6 -> 0.04463 | R5: Tusd (R$/kWh) | U5: Tusd (R$/kWh) | X5: Tusd (R$/kWh)
B6: B1 Ponta | C6: ='TABELA DE TARIFAS ANTIGAS'!G68/1000 -> 0.93761 | D6: ='TABELA DE TARIFAS ANTIGAS'!H68/1000 -> 0.48448 | E6: =C6+D6 -> 1.42209 | F6: ='TABELA DE TARIFAS NOVAS'!G70/1000 -> 0.99902 | G6: ='TABELA DE TARIFAS NOVAS'!H70/1000 -> 0.51691 | H6: =F6+G6 -> 1.51593 | I6: =((C6*$C$15)+(F6*$D$15))/($D$15+$C$15) -> 0.966268 | J6: =((D6*$C$15)+(G6*$D$15))/($D$15+$C$15) -> 0.499614 | K6: =I6+J6 -> 1.465882 | M6: BVM2 | N6: =[1]BANDEIRA!$D$7 -> 0.07877 | Q6: =B6 -> B1 Ponta | R6: ='FIO B'!H7/1000 -> 0.59110909 | U6: ='FIO B'!K7/1000 -> 0.60653962 | X6: =((R6*$C$15)+(U6*$D$15))/($D$15+$C$15) -> 0.59831
B7: B1 Fora Ponta | C7: ='TABELA DE TARIFAS ANTIGAS'!G70/1000 -> 0.36496 | D7: ='TABELA DE TARIFAS ANTIGAS'!H70/1000 -> 0.30579 | E7: =C7+D7 -> 0.67075 | F7: ='TABELA DE TARIFAS NOVAS'!G72/1000 -> 0.39741 | G7: ='TABELA DE TARIFAS NOVAS'!H72/1000 -> 0.32107 | H7: =F7+G7 -> 0.71848 | I7: =((C7*$C$15)+(F7*$D$15))/($D$15+$C$15) -> 0.38010333 | J7: =((D7*$C$15)+(G7*$D$15))/($D$15+$C$15) -> 0.31292067 | K7: =I7+J7 -> 0.693024 | M7: Escassez Hídrica | N7: 0.142 | Q7: =B7 -> B1 Fora Ponta | R7: ='FIO B'!H8/1000 -> 0.3546655 | U7: ='FIO B'!K8/1000 -> 0.36392381 | X7: =((R7*$C$15)+(U7*$D$15))/($D$15+$C$15) -> 0.35898604
B8: B1 Interm. | C8: ='TABELA DE TARIFAS ANTIGAS'!G69/1000 -> 0.65129 | D8: ='TABELA DE TARIFAS ANTIGAS'!H69/1000 -> 0.30579 | E8: =C8+D8 -> 0.95708 | F8: ='TABELA DE TARIFAS NOVAS'!G71/1000 -> 0.69821 | G8: ='TABELA DE TARIFAS NOVAS'!H71/1000 -> 0.32107 | H8: =F8+G8 -> 1.01928 | I8: =((C8*$C$15)+(F8*$D$15))/($D$15+$C$15) -> 0.673186 | J8: =((D8*$C$15)+(G8*$D$15))/($D$15+$C$15) -> 0.31292067 | K8: =I8+J8 -> 0.98610667 | Q8: =B8 -> B1 Interm. | R8: ='FIO B'!H9/1000 -> 0.1182218 | U8: ='FIO B'!K9/1000 -> 0.1213079 | X8: =((R8*$C$15)+(U8*$D$15))/($D$15+$C$15) -> 0.11966198
B9: CDE Escassez Hídrica | C9: 0.00018774721 | D9: -0.0044031307 | E9: 0.0036054084 | F9: =T13 -> 0.00018418923 | G9: =U13 -> -0.00053182975 | H9: =F9+G9 -> -0.00034764052 | I9: =((C9*$C$15)+(F9*$D$15))/($D$15+$C$15) -> 0.00018608682 | J9: =((D9*$C$15)+(G9*$D$15))/($D$15+$C$15) -> -0.0025965236 | K9: =I9+J9 -> -0.0024104368
P10: CUSTO | R10: Part. TUSD (%) | S10: Part. TE (%) | T10: Tusd (R$/kWh) | U10: TE (R$/kWh)
H11: Fatura | L11: Vigência das Tarifas (troca Bandeira): | M11: =EOMONTH(B15,0)+1 -> 46235 | P11: CDE CONTAS
B12: INSTALAÇÃO | C12: 160295767 | H12: =E15 -> 46254 | K12: Altere a bandeira na célula abaixo | P12: CDE COVID | U12: 0
K13: BAM | L13: BAM | P13: CDE ESCASSEZ HÍDRICA | T13: =0.184189231569235/1000 -> 0.00018418923 | U13: =-0.531829748712515/1000 -> -0.00053182975
B14: Leitura Anterior | C14: Nº de dias tarifa Anterior | D14: Nº de dias tarifa Nova | E14: Leitura Atual | J14: Leitura Anterior | K14: Nº de dias tarifa Anterior | L14: Nº de dias tarifa Nova | M14: Leitura Atual
B15: 46224 | C15: =IF((F2-B15-1)<0,0,(F2-B15-1)) -> 16 | D15: =E15-F2+1 -> 14 | E15: 46254 | J15: =B15 -> 46224 | K15: =IF((M11-J15-1)<0,0,(M11-J15-1)) -> 10 | L15: =M15-M11+1 -> 20 | M15: =E15 -> 46254 | P15: Documento impressão: | R15: 1025310400
B17: Descrição | C17: Unidade | D17: Quantidade | E17: Preço Unit (R$) com tributos | F17: Valor Total (R$) | G17: PIS/COFINS (R$) | H17: Base de Cálculo ICMS (R$) | I17: Alíquota ICMS (%) | J17: ICMS (R$) | K17: Preço Unit (R$) | L17: Tributos | M17: Base de Cálc (R$) | N17: Alíquota (%) | O17: Valor (R$)
B19: TUSD - Ponta | C19: kWh | D19: 139 | E19: =IFERROR((ROUND(D19*K19,2)+ROUND(G19,2)+ROUND(J19,2))/ROUND(D19,4), 0) -> 1.2407194 | F19: =ROUND(D19*E19,2) -> 172.46 | G19: =((D19*K19)/(1-$N$19-$N$21))*($N$19+$N$21) -> 8.8319346 | H19: =((D19*K19)/(1-$N$19-$N$21)/(1-$I$19)) -> 172.46167 | I19: 0.17 | J19: =(H19*$I$19) -> 29.318484 | K19: =E58 -> 0.966268 | L19: PIS | M19: =D78 -> 742.14004 | N19: 0.011 | O19: =ROUND(M19*N19,2) -> 8.16 | Q19: TUSD Fio B | R19: Receita Fio B
B20: TUSD - Intermediário | C20: kWh | D20: 293 | E20: =IFERROR((ROUND(D20*K20,2)+ROUND(G20,2)+ROUND(J20,2))/ROUND(D20,4), 0) -> 0.86440273 | F20: =ROUND(D20*E20,2) -> 253.27 | G20: =((D20*K20)/(1-$N$19-$N$21))*($N$19+$N$21) -> 12.970184 | H20: =((D20*K20)/(1-$N$19-$N$21)/(1-$I$19)) -> 253.2695 | I20: =I19 -> 0.17 | J20: =(H20*$I$19) -> 43.055814 | K20: =E60 -> 0.673186 | L20: PIS Inj | M20: =D79 -> -277.71502 | N20: =N19 -> 0.011 | O20: =ROUND(M20*N20,2) -> -3.05 | Q20: =IF(AND($B$15<$F$2,$E$15<$F$2),R6,IF($B$15<$F$2,X6,U6)) -> 0.59831 | R20: =D19*Q20 -> 83.165091
B21: TUSD - Fora Ponta | C21: kWh | D21: 280 | E21: =IFERROR((ROUND(D21*K21,2)+ROUND(G21,2)+ROUND(J21,2))/ROUND(D21,4), 0) -> 0.48807143 | F21: =ROUND(D21*E21,2) -> 136.66 | G21: =((D21*K21)/(1-$N$19-$N$21))*($N$19+$N$21) -> 6.9984708 | H21: =((D21*K21)/(1-$N$19-$N$21)/(1-$I$19)) -> 136.65952 | I21: =I19 -> 0.17 | J21: =(H21*$I$19) -> 23.232119 | K21: =E59 -> 0.38010333 | L21: COFINS | M21: =M19 -> 742.14004 | N21: 0.0507 | O21: =ROUND(M21*N21,2) -> 37.63 | Q21: =IF(AND($B$15<$F$2,$E$15<$F$2),R7,IF($B$15<$F$2,X7,U7)) -> 0.35898604 | R21: =D20*Q21 -> 105.18291
B22: TE - Ponta | C22: kWh | D22: =D19 -> 139 | E22: =IFERROR((ROUND(D22*K22,2)+ROUND(G22,2)+ROUND(J22,2))/ROUND(D22,4), 0) -> 0.64158273 | F22: =ROUND(D22*E22,2) -> 89.18 | G22: =((D22*K22)/(1-$N$19-$N$21))*($N$19+$N$21) -> 4.5665987 | H22: =ROUND((D22*K22)/(1-$N$19-$N$21)/(1-$I$19),8) -> 89.172223 | J22: =ROUND(H22*$I$19,2) -> 15.16 | K22: =F58 -> 0.499614 | L22: COFINS Inj | M22: =M20 -> -277.71502 | N22: =N21 -> 0.0507 | O22: =ROUND(M22*N22,2) -> -14.08 | Q22: =IF(AND($B$15<$F$2,$E$15<$F$2),R8,IF($B$15<$F$2,X8,U8)) -> 0.11966198 | R22: =D21*Q22 -> 33.505355
B23: TE - Intermediário | C23: kWh | D23: =D20 -> 293 | E23: =IFERROR((ROUND(D23*K23,2)+ROUND(G23,2)+ROUND(J23,2))/ROUND(D23,4), 0) -> 0.40180887 | F23: =ROUND(D23*E23,2) -> 117.73 | G23: =((D23*K23)/(1-$N$19-$N$21))*($N$19+$N$21) -> 6.0290004 | H23: =ROUND((D23*K23)/(1-$N$19-$N$21)/(1-$I$19),8) -> 117.72862 | J23: =ROUND(H23*$I$19,2) -> 20.01 | K23: =F60 -> 0.31292067 | R23: =SUM(R20:R22) -> 221.85336
B24: TE - Fora Ponta | C24: kWh | D24: =D21 -> 280 | E24: =IFERROR((ROUND(D24*K24,2)+ROUND(G24,2)+ROUND(J24,2))/ROUND(D24,4), 0) -> 0.40182143 | F24: =ROUND(D24*E24,2) -> 112.51 | G24: =((D24*K24)/(1-$N$19-$N$21))*($N$19+$N$21) -> 5.7615021 | H24: =ROUND((D24*K24)/(1-$N$19-$N$21)/(1-$I$19),8) -> 112.50517 | J24: =ROUND(H24*$I$19,2) -> 19.13 | K24: =F59 -> 0.31292067
B25: Adicional BAM | C25: kWh | D25: =IF($K$13=M4,(($D$19+$D$20+$D$21)*($K$15)/($K$15+$L$15)),0)+IF($L$13=M4,(($D$19+$D$20+$D$21)*($L$15)/($K$15+$L$15)),0) -> 712 | E25: =IFERROR((ROUND(D25*K25,2)+ROUND(G25,2)+ROUND(J25,2))/ROUND(D25,4), 0) -> 0.024199438 | F25: =ROUND(D25*E25,2) -> 17.23 | G25: =((D25*K25)/(1-$N$19-$N$21))*($N$19+$N$21) -> 0.88254081 | H25: =ROUND((D25*K25)/(1-$N$19-$N$21)/(1-$I$19),8) -> 17.233423 | J25: =ROUND(H25*$I$19,2) -> 2.93 | K25: =N4 -> 0.01885
B26: Adicional BVM1 | C26: kWh | D26: =IF($K$13=M5,(($D$19+$D$20+$D$21)*($K$15)/($K$15+$L$15)),0)+IF($L$13=M5,(($D$19+$D$20+$D$21)*($L$15)/($K$15+$L$15)),0) -> 0 | E26: =IFERROR((ROUND(D26*K26,2)+ROUND(G26,2)+ROUND(J26,2))/ROUND(D26,4), 0) -> 0 | F26: =ROUND(D26*E26,2) -> 0 | G26: =((D26*K26)/(1-$N$19-$N$21))*($N$19+$N$21) -> 0 | H26: =ROUND((D26*K26)/(1-$N$19-$N$21)/(1-$I$19),8) -> 0 | J26: =ROUND(H26*$I$19,2) -> 0 | K26: =N5 -> 0.04463
B27: Adicional BVM2 | C27: kWh | D27: =IF($K$13=M6,(($D$19+$D$20+$D$21)*($K$15)/($K$15+$L$15)),0)+IF($L$13=M6,(($D$19+$D$20+$D$21)*($L$15)/($K$15+$L$15)),0) -> 0 | E27: =IFERROR((ROUND(D27*K27,2)+ROUND(G27,2)+ROUND(J27,2))/ROUND(D27,4), 0) -> 0 | F27: =ROUND(D27*E27,2) -> 0 | G27: =((D27*K27)/(1-$N$19-$N$21))*($N$19+$N$21) -> 0 | H27: =ROUND((D27*K27)/(1-$N$19-$N$21)/(1-$I$19),8) -> 0 | J27: =ROUND(H27*$I$19,2) -> 0 | K27: =N6 -> 0.07877
B28: Adicional EH | C28: kWh | D28: =IF($K$13=M7,(($D$19+$D$20+$D$21)*($K$15)/($K$15+$L$15)),0)+IF($L$13=M7,(($D$19+$D$20+$D$21)*($L$15)/($K$15+$L$15)),0) -> 0 | E28: =IFERROR((ROUND(D28*K28,2)+ROUND(G28,2)+ROUND(J28,2))/ROUND(D28,4), 0) -> 0 | F28: =ROUND(D28*E28,2) -> 0 | G28: =((D28*K28)/(1-$N$19-$N$21))*($N$19+$N$21) -> 0 | H28: =ROUND((D28*K28)/(1-$N$19-$N$21)/(1-$I$19),8) -> 0 | J28: =ROUND(H28*$I$19,2) -> 0 | K28: =N7 -> 0.142 | R28: 56.925816
R29: 24.55085
B30: TUSD - Ponta inj | C30: kWh | D30: 0 | E30: =IFERROR((ROUND(D30*K30,2)+ROUND(G30,2)+ROUND(J30,2))/ROUND(D30,4),0) -> 0 | F30: =ROUND(D30*E30,2) -> 0 | G30: =((D30*K30)/(1-$N$19-$N$21))*($N$19+$N$21) -> 0 | H30: 0 | I30: 0 | J30: =H30*$I$25 -> 0 | K30: =K19 -> 0.966268 | R30: =SUM(R28:R29) -> 81.476667
B31: TUSD - Inermediário inj | C31: kWh | D31: -215 | E31: =IFERROR((ROUND(D31*K31,2)+ROUND(G31,2)+ROUND(J31,2))/ROUND(D31,4),0) -> 0.71744186 | F31: =ROUND(D31*E31,2) -> -154.25 | G31: =((D31*K31)/(1-$N$19-$N$21))*($N$19+$N$21) -> -9.5173707 | H31: 0 | I31: 0 | J31: =H31*$I$25 -> 0 | K31: =K20 -> 0.673186
B32: TUSD - Fora Ponta inj | C32: kWh | D32: -107 | E32: =IFERROR((ROUND(D32*K32,2)+ROUND(G32,2)+ROUND(J32,2))/ROUND(D32,4),0) -> 0.40504673 | F32: =ROUND(D32*E32,2) -> -43.34 | G32: =((D32*K32)/(1-$N$19-$N$21))*($N$19+$N$21) -> -2.6744156 | H32: 0 | I32: 0 | J32: =H32*$I$25 -> 0 | K32: =K21 -> 0.38010333
B33: TE - Ponta inj | C33: kWh | D33: =D30 -> 0 | E33: =IFERROR((ROUND(D33*K33,2)+ROUND(G33,2)+ROUND(J33,2))/ROUND(D33,4),0) -> 0 | F33: =ROUND(D33*E33,2) -> 0 | G33: =((D33*K33)/(1-$N$19-$N$21))*($N$19+$N$21) -> 0 | H33: =ROUND((D33*K33)/(1-$N$19-$N$21)/(1-$I$33),8) -> 0 | I33: =$I$19 -> 0.17 | J33: =H33*$I$33 -> 0 | K33: =K22 -> 0.499614
B34: TE - Intermediário inj | C34: kWh | D34: =D31 -> -215 | E34: =IFERROR((ROUND(D34*K34,2)+ROUND(G34,2)+ROUND(J34,2))/ROUND(D34,4),0) -> 0.40181395 | F34: =ROUND(D34*E34,2) -> -86.39 | G34: =((D34*K34)/(1-$N$19-$N$21))*($N$19+$N$21) -> -4.4240106 | H34: =ROUND((D34*K34)/(1-$N$19-$N$21)/(1-$I$33),8) -> -86.387896 | I34: =$I$19 -> 0.17 | J34: =H34*$I$33 -> -14.685942 | K34: =K23 -> 0.31292067
B35: TE - Fora Ponta inj | C35: kWh | D35: =D32 -> -107 | E35: =IFERROR((ROUND(D35*K35,2)+ROUND(G35,2)+ROUND(J35,2))/ROUND(D35,4),0) -> 0.4017757 | F35: =ROUND(D35*E35,2) -> -42.99 | G35: =((D35*K35)/(1-$N$19-$N$21))*($N$19+$N$21) -> -2.2017169 | H35: =ROUND((D35*K35)/(1-$N$19-$N$21)/(1-$I$33),8) -> -42.993046 | I35: =$I$19 -> 0.17 | J35: =H35*$I$33 -> -7.3088178 | K35: =K24 -> 0.31292067
B36: Adicional BAM inj | C36: kWh | D36: =IF($K$13=M4,(($D$30+$D$31+$D$32)*($K$15)/($K$15+$L$15)),0)+IF($L$13=M4,(($D$30+$D$31+$D$32)*($L$15)/($K$15+$L$15)),0) -> -322 | E36: =IFERROR((ROUND(D36*K36,2)+ROUND(G36,2)+ROUND(J36,2))/ROUND(D36,4),0) -> 0.024192547 | F36: =ROUND(D36*E36,2) -> -7.79 | G36: =((D36*K36)/(1-$N$19-$N$21))*($N$19+$N$21) -> -0.3991266 | H36: =(D36*K36)/(1-$N$19-$N$21)/(1-$I$33) -> -7.793767 | J36: =H36*$I$33 -> -1.3249404 | K36: =N4 -> 0.01885
B37: Adicional BVM1 inj | C37: kWh | D37: =IF($K$13=M5,(($D$30+$D$31+$D$32)*($K$15)/($K$15+$L$15)),0)+IF($L$13=M5,(($D$30+$D$31+$D$32)*($L$15)/($K$15+$L$15)),0) -> 0 | E37: =IFERROR((ROUND(D37*K37,2)+ROUND(G37,2)+ROUND(J37,2))/ROUND(D37,4),0) -> 0 | F37: =ROUND(D37*E37,2) -> 0 | G37: =((D37*K37)/(1-$N$19-$N$21))*($N$19+$N$21) -> 0 | H37: =(D37*K37)/(1-$N$19-$N$21)/(1-$I$33) -> 0 | J37: =H37*$I$33 -> 0 | K37: =N5 -> 0.04463
B38: Adicional BVM2 inj | C38: kWh | D38: =IF($K$13=M6,(($D$30+$D$31+$D$32)*($K$15)/($K$15+$L$15)),0)+IF($L$13=M6,(($D$30+$D$31+$D$32)*($L$15)/($K$15+$L$15)),0) -> 0 | E38: =IFERROR((ROUND(D38*K38,2)+ROUND(G38,2)+ROUND(J38,2))/ROUND(D38,4),0) -> 0 | F38: =ROUND(D38*E38,2) -> 0 | G38: =((D38*K38)/(1-$N$19-$N$21))*($N$19+$N$21) -> 0 | H38: =(D38*K38)/(1-$N$19-$N$21)/(1-$I$33) -> 0 | J38: =H38*$I$33 -> 0 | K38: =N6 -> 0.07877
B39: Adicional EH inj | C39: kWh | D39: =IF($K$13=M7,(($D$30+$D$31+$D$32)*($K$15)/($K$15+$L$15)),0)+IF($L$13=M7,(($D$30+$D$31+$D$32)*($L$15)/($K$15+$L$15)),0) -> 0 | E39: =IFERROR((ROUND(D39*K39,2)+ROUND(G39,2)+ROUND(J39,2))/ROUND(D39,4),0) -> 0 | F39: =ROUND(D39*E39,2) -> 0 | G39: =((D39*K39)/(1-$N$19-$N$21))*($N$19+$N$21) -> 0 | H39: =(D39*K39)/(1-$N$19-$N$21)/(1-$I$33) -> 0 | J39: =H39*$I$33 -> 0 | K39: =N7 -> 0.142
B41: Multas
B42: Juros
B43: Doações | F43: -12.85
B44: CIP
B47: TOTAL | F47: =SUM(F19:F46) -> 551.43 | G47: =SUM(G19:G46) -> 26.823591 | H47: =SUM(H19:H46) -> 761.85541 | J47: =SUM(J19:J46) -> 129.51672
B49: Informativo Escassez | C49: =D84 -> 390 | D49: =E84 -> 0.00018608682 | E49: =F84 -> -0.0025965236 | F49: =C49*(D49+E49) -> -0.94007035
B52: Perc. de Redução da Energia Injetada | E52: TUSD | F52: 1 | G52: TE | H52: 1
B54: Fatura B1 Residencial TB
D55: Qtde | E55: TUSD | F55: TE | G55: TUSD + TE | H55: R$
B56: Fornecimento de Energia Elétrica | H56: =SUM(H58:H65)+SUM(H78:H82) -> 877.00961
B58: Consumo Ponta | D58: =D19 -> 139 | E58: =IF(AND($B$15<$F$2,$E$15<$F$2),C6,IF($B$15<$F$2,I6,F6)) -> 0.966268 | F58: =IF(AND($B$15<$F$2,$E$15<$F$2),D6,IF($B$15<$F$2,J6,G6)) -> 0.499614 | G58: =E58+F58 -> 1.465882 | H58: =ROUND((D58*E58),2)+ROUND((D58*F58),2) -> 203.76
B59: Consumo Fora Ponta | D59: =D20 -> 293 | E59: =IF(AND($B$15<$F$2,$E$15<$F$2),C7,IF($B$15<$F$2,I7,F7)) -> 0.38010333 | F59: =IF(AND($B$15<$F$2,$E$15<$F$2),D7,IF($B$15<$F$2,J7,G7)) -> 0.31292067 | G59: =E59+F59 -> 0.693024 | H59: =ROUND((D59*E59),2)+ROUND((D59*F59),2) -> 203.06
B60: Consumo Intemediário | D60: =D21 -> 280 | E60: =IF(AND($B$15<$F$2,$E$15<$F$2),C8,IF($B$15<$F$2,I8,F8)) -> 0.673186 | F60: =IF(AND($B$15<$F$2,$E$15<$F$2),D8,IF($B$15<$F$2,J8,G8)) -> 0.31292067 | G60: =E60+F60 -> 0.98610667 | H60: =ROUND((D60*E60),2)+ROUND((D60*F60),2) -> 276.11
B62: Adicional BAM | D62: =IF($K$13=M4,((D58+D59+D60)*(K15)/(K15+L15)),0)+IF($L$13=M4,((D58+D59+D60)*(L15)/(K15+L15)),0) -> 712 | F62: =N4 -> 0.01885 | H62: =ROUND(D62*(E62+F62),2) -> 13.42
B63: Adicional BVM 1 | D63: =IF($K$13=M5,((D58+D59+D60)*(K15)/(K15+L15)),0)+IF($L$13=M5,((D58+D59+D60)*(L15)/(K15+L15)),0) -> 0 | F63: =N5 -> 0.04463 | H63: =ROUND(D63*(E63+F63),2) -> 0
B64: Adicional BVM 2 | D64: =IF($K$13=M6,((D58+D59+D60)*(K15)/(K15+L15)),0)+IF($L$13=M6,((D58+D59+D60)*(L15)/(K15+L15)),0) -> 0 | F64: =N6 -> 0.07877 | H64: =ROUND(D64*(E64+F64),2) -> 0
B65: Adicional Escassez Hídrica | D65: =IF($K$13=M7,((D58+D59+D60)*(K15)/(K15+L15)),0)+IF($L$13=M7,((D58+D59+D60)*(L15)/(K15+L15)),0) -> 0 | F65: =N7 -> 0.142 | H65: =ROUND(D65*(E65+F65),2) -> 0
B67: Energ Injetada P | D67: =D30 -> 0 | E67: =E58*F52 -> 0.966268 | F67: =F58 -> 0.499614 | G67: =E67+F67 -> 1.465882 | H67: =ROUND((D67*E67),2)+ROUND((D67*F67),2) -> 0
B68: Energ Injetada FP | D68: =D31 -> -215 | E68: =E59*F52 -> 0.38010333 | F68: =F59 -> 0.31292067 | G68: =E68+F68 -> 0.693024 | H68: =ROUND((D68*E68),2)+ROUND((D68*F68),2) -> -149
B69: Energ Injetada Intem | D69: =D32 -> -107 | E69: =E60*F52 -> 0.673186 | F69: =F60 -> 0.31292067 | G69: =E69+F69 -> 0.98610667 | H69: =ROUND((D69*E69),2)+ROUND((D69*F69),2) -> -105.51
B71: Adicional BAM Inj | D71: =IF($K$13=M4,((D67+D68+D69)*(K15)/(K15+L15)),0)+IF($L$13=M4,((D67+D68+D69)*(L15)/(K15+L15)),0) -> -322 | F71: =N4 -> 0.01885 | H71: =ROUND(D71*(E71+F71),2) -> -6.07
B72: Adicional BVM 1 Inj | D72: =IF($K$13=M5,((D68+D69+D70)*(K15)/(K15+L15)),0)+IF($L$13=M5,((D68+D69+D70)*(L15)/(K15+L15)),0) -> 0 | F72: =N14 -> 0 | H72: =ROUND(D72*(E72+F72),2) -> 0
B73: Adicional BVM 2 Inj | D73: =IF($K$13=M6,((D69+D70+D71)*(K15)/(K15+L15)),0)+IF($L$13=M6,((D69+D70+D71)*(L15)/(K15+L15)),0) -> 0 | F73: =N15 -> 0 | H73: =ROUND(D73*(E73+F73),2) -> 0
B74: Adicional Escassez Hídrica Inj | D74: =IF($K$13=M7,((D70+D71+D72)*(K15)/(K15+L15)),0)+IF($L$13=M7,((D70+D71+D72)*(L15)/(K15+L15)),0) -> 0 | F74: =N16 -> 0 | H74: =ROUND(D74*(E74+F74),2) -> 0
H76: 46.51
D77: Base de Cálculo | H77: 62.53
B78: PIS | D78: =(SUM(H58:H65)/(1-E78-E80)) -> 742.14004 | E78: =N19 -> 0.011 | H78: =D78*E78 -> 8.1635404
B79: PIS INJ | D79: =(SUM(H67:H74)/(1-E79-E81)) -> -277.71502 | E79: =E78 -> 0.011 | H79: =D79*E79 -> -3.0548652
B80: COFINS | D80: =D78 -> 742.14004 | E80: =N21 -> 0.0507 | H80: =D80*E80 -> 37.6265
B81: COFINS INJ | D81: =D79 -> -277.71502 | E81: =E80 -> 0.0507 | H81: =D81*E81 -> -14.080151
B82: ICMS | D82: =D78/(1-E82) -> 894.14463 | E82: 0.17 | H82: =D82*E82 -> 152.00459
B83: ICMS INJ | D83: =((D67*F67)+(D68*F68)+(D69*F69)+H71+H72+H73+H74)/(1-E79-E81)/(1-E83) -> -137.17509 | E83: 0.17 | H83: =D83*E83 -> -23.319766 | J83: =IF($K$13=M4,((D67+D68+D69)*(K15)/(K15+L15)),0)+IF($L$13=M4,((D67+D68+D69)*(L15)/(K15+L15)),0) -> -322
B84: Informativo Escassez Hídrica | D84: =SUM(D58:D60)+SUM(D67:D69) -> 390 | E84: =IF(AND($B$15<$F$2,$E$15<$F$2),C9,IF($B$15<$F$2,I9,F9)) -> 0.00018608682 | F84: =IF(AND($B$15<$F$2,$E$15<$F$2),D9,IF($B$15<$F$2,J9,G9)) -> -0.0025965236 | H84: =D84*(E84+F84) -> -0.94007035
B86: Participação
C87: R$
B88: Energia | C88: =(SUM(H58:H65)*IF($B$15<$F$2,D126,D98)) -> 301.33565
B89: Distribuição | C89: =(SUM(H58:H65)*IF($B$15<$F$2,F126,F98)) -> 180.91323
B90: Transmissão | C90: =(SUM(H58:H65)*IF($B$15<$F$2,E126,E98)) -> 56.701011
B91: Encargos Setoriais | C91: =(SUM(H58:H65)*IF($B$15<$F$2,G126,G98)) -> 157.40011
B92: Impostos / Tributos | C92: =H78+H80+H82 -> 197.79463
B93: Total | C93: =SUM(C88:C92) -> 894.14463
B95: 2023 | D95: Energia | E95: Transmissão | F95: Distribuição | G95: Setoriais
B96: Grupo B | D96: % | E96: % | F96: % | G96: %
B98: B1 - Residencial | D98: 0.43273591 | E98: 0.081426023 | F98: 0.25980216 | G98: 0.22603591
B99: B1 - Residencial Baixa Renda | D99: 0.52914975 | E99: 0.099567792 | F99: 0.31768624 | G99: 0.053596219
B100: B2 - Rural | D100: 0.43273591 | E100: 0.081426023 | F100: 0.25980216 | G100: 0.22603591
B101: B2 - Cooperativa Eletrificação Rural | D101: 0.43273591 | E101: 0.081426023 | F101: 0.25980216 | G101: 0.22603591
B102: B2 - Serviço de Irrigação | D102: 0.43273591 | E102: 0.081426023 | F102: 0.25980216 | G102: 0.22603591
B103: B3 - Demais Classes | D103: 0.43273591 | E103: 0.081426023 | F103: 0.25980216 | G103: 0.22603591
B104: B4 - Iluminação Pública | D104: 0.43273591 | E104: 0.081426023 | F104: 0.25980216 | G104: 0.22603591
B105: B4a - Rede de Distribuição | D105: 0.43273591 | E105: 0.081426023 | F105: 0.25980216 | G105: 0.22603591
B106: B4b - Bulbo de Lâmpada | D106: 0.43273591 | E106: 0.081426023 | F106: 0.25980216 | G106: 0.22603591
B109: 2022 | D109: Energia | E109: Transmissão | F109: Distribuição | G109: Setoriais
B110: Grupo B | D110: % | E110: % | F110: % | G110: %
B112: B1 - Residencial | D112: 0.43273591 | E112: 0.081426023 | F112: 0.25980216 | G112: 0.22603591
B113: B1 - Residencial Baixa Renda | D113: 0.52914975 | E113: 0.099567792 | F113: 0.31768624 | G113: 0.053596219
B114: B2 - Rural | D114: 0.43273591 | E114: 0.081426023 | F114: 0.25980216 | G114: 0.22603591
B115: B2 - Cooperativa Eletrificação Rural | D115: 0.43273591 | E115: 0.081426023 | F115: 0.25980216 | G115: 0.22603591
B116: B2 - Serviço de Irrigação | D116: 0.43273591 | E116: 0.081426023 | F116: 0.25980216 | G116: 0.22603591
B117: B3 - Demais Classes | D117: 0.43273591 | E117: 0.081426023 | F117: 0.25980216 | G117: 0.22603591
B118: B4 - Iluminação Pública | D118: 0.43273591 | E118: 0.081426023 | F118: 0.25980216 | G118: 0.22603591
B119: B4a - Rede de Distribuição | D119: 0.43273591 | E119: 0.081426023 | F119: 0.25980216 | G119: 0.22603591
B120: B4b - Bulbo de Lâmpada | D120: 0.43273591 | E120: 0.081426023 | F120: 0.25980216 | G120: 0.22603591
B122: proporcional
...

Sheet B3 GD Branca OK
B2: B3 TB | E2: Vigência das Tarifas: | F2: ='B1 Res (GD) Branca OK'!F2 -> 46241 | H2: TARIFA BRANCA | M2: Bandeira | N2: R$/kWh | Q2: TUSD FIO B
M3: VERDE | N3: ='[4]B1 (Res) Branca OK'!N3 -> 0
B4: TARIFA | C4: ='Fatura B1 (GD) OK'!C4:E4 -> TARIFA ANTIGA - REH 3370/2024 | F4: ='Fatura B1 (GD) OK'!F4 -> TARIFA NOVA - REH xxxx/2025 | I4: Tarifas Proporcionalizadas | M4: BAM | N4: ='[4]B1 (Res) Branca OK'!N4 -> 0.01885 | Q4: TARIFA | R4: =C4 -> TARIFA ANTIGA - REH 3370/2024 | U4: =F4 -> TARIFA NOVA - REH xxxx/2025 | X4: Tarifas Proporcionalizadas
C5: Tusd | D5: TE | E5: TUSD + TE | F5: Tusd | G5: TE | H5: TUSD + TE | I5: Tusd | J5: TE | K5: TUSD + TE | M5: BVM1 | N5: ='[4]B1 (Res) Branca OK'!N5 -> 0.04463 | R5: Tusd (R$/kWh) | U5: Tusd (R$/kWh) | X5: Tusd (R$/kWh)
B6: B3 Ponta | C6: ='TABELA DE TARIFAS ANTIGAS'!G86/1000 -> 1.06103 | D6: ='TABELA DE TARIFAS ANTIGAS'!H86/1000 -> 0.48448 | E6: =C6+D6 -> 1.54551 | F6: ='TABELA DE TARIFAS NOVAS'!G88/1000 -> 1.12867 | G6: ='TABELA DE TARIFAS NOVAS'!H88/1000 -> 0.51691 | H6: =F6+G6 -> 1.64558 | I6: =((C6*$C$15)+(F6*$D$15))/($D$15+$C$15) -> 1.0925953 | J6: =((D6*$C$15)+(G6*$D$15))/($D$15+$C$15) -> 0.499614 | K6: =I6+J6 -> 1.5922093 | M6: BVM2 | N6: ='[4]B1 (Res) Branca OK'!N6 -> 0.07877 | Q6: =B6 -> B3 Ponta | R6: ='FIO B'!H31/1000 -> 0.69302445 | U6: ='FIO B'!K31/1000 -> 0.71111541 | X6: =((R6*$C$15)+(U6*$D$15))/($D$15+$C$15) -> 0.7014669
B7: B3 Fora Ponta | C7: ='TABELA DE TARIFAS ANTIGAS'!G88/1000 -> 0.38965 | D7: ='TABELA DE TARIFAS ANTIGAS'!H88/1000 -> 0.30579 | E7: =C7+D7 -> 0.69544 | F7: ='TABELA DE TARIFAS NOVAS'!G90/1000 -> 0.42334 | G7: ='TABELA DE TARIFAS NOVAS'!H90/1000 -> 0.32107 | H7: =F7+G7 -> 0.74441 | I7: =((C7*$C$15)+(F7*$D$15))/($D$15+$C$15) -> 0.405372 | J7: =((D7*$C$15)+(G7*$D$15))/($D$15+$C$15) -> 0.31292067 | K7: =I7+J7 -> 0.71829267 | M7: Escassez Hídrica | N7: 0.142 | Q7: =B7 -> B3 Fora Ponta | R7: ='FIO B'!H32/1000 -> 0.41581471 | U7: ='FIO B'!K32/1000 -> 0.42666929 | X7: =((R7*$C$15)+(U7*$D$15))/($D$15+$C$15) -> 0.42088018
B8: B3 Interm. | C8: ='TABELA DE TARIFAS ANTIGAS'!G87/1000 -> 0.72534 | D8: ='TABELA DE TARIFAS ANTIGAS'!H87/1000 -> 0.30579 | E8: =C8+D8 -> 1.03113 | F8: ='TABELA DE TARIFAS NOVAS'!G89/1000 -> 0.77601 | G8: ='TABELA DE TARIFAS NOVAS'!H89/1000 -> 0.32107 | H8: =F8+G8 -> 1.09708 | I8: =((C8*$C$15)+(F8*$D$15))/($D$15+$C$15) -> 0.748986 | J8: =((D8*$C$15)+(G8*$D$15))/($D$15+$C$15) -> 0.31292067 | K8: =I8+J8 -> 1.0619067 | Q8: =B8 -> B3 Interm. | R8: ='FIO B'!H33/1000 -> 0.13860487 | U8: ='FIO B'!K33/1000 -> 0.14222306 | X8: =((R8*$C$15)+(U8*$D$15))/($D$15+$C$15) -> 0.14029336
B9: CDE Escassez Hídrica | C9: 0.00018774721 | D9: -0.0044031307 | E9: =SUM(C9+D9) -> -0.0042153835 | F9: =T13 -> 0.00018418923 | G9: =U13 -> -0.00053182975 | H9: =F9+G9 -> -0.00034764052 | I9: =((C9*$C$15)+(F9*$D$15))/($D$15+$C$15) -> 0.00018608682 | J9: =((D9*$C$15)+(G9*$D$15))/($D$15+$C$15) -> -0.0025965236 | K9: =I9+J9 -> -0.0024104368
P10: CUSTO | R10: Part. TUSD (%) | S10: Part. TE (%) | T10: Tusd (R$/kWh) | U10: TE (R$/kWh)
H11: Fatura | L11: Vigência das Tarifas (troca Bandeira): | M11: =EOMONTH(B15,0)+1 -> 46235 | P11: CDE CONTAS
B12: INSTALAÇÃO | C12: 588890 | H12: =E15 -> 46254 | K12: Altere a bandeira na célula abaixo | P12: CDE COVID | U12: 0
K13: BAM | L13: BAM | P13: CDE ESCASSEZ HÍDRICA | T13: ='B1 Res (GD) Branca OK'!T13 -> 0.00018418923 | U13: ='B1 Res (GD) Branca OK'!U13 -> -0.00053182975
B14: Leitura Anterior | C14: Nº de dias tarifa Anterior | D14: Nº de dias tarifa Nova | E14: Leitura Atual | J14: Leitura Anterior | K14: Nº de dias tarifa Anterior | L14: Nº de dias tarifa Nova | M14: Leitura Atual
B15: 46224 | C15: =IF((F2-B15-1)<0,0,(F2-B15-1)) -> 16 | D15: =E15-F2+1 -> 14 | E15: 46254 | J15: =B15 -> 46224 | K15: =IF((M11-J15-1)<0,0,(M11-J15-1)) -> 10 | L15: =M15-M11+1 -> 20 | M15: =E15 -> 46254
B18: Perc. de Redução da Energia Injetada | E18: TUSD | F18: 1 | G18: TE | H18: 1 | M18: Documento impressão: | O18: 1025310403
B20: Descrição | C20: Unidade | D20: Quantidade | E20: Preço Unit (R$) com tributos | F20: Valor Total (R$) | G20: PIS/COFINS (R$) | H20: Base de Cálculo ICMS (R$) | I20: Alíquota ICMS (%) | J20: ICMS (R$) | K20: Preço Unit (R$) | L20: Tributos | M20: Base de Cálc (R$) | N20: Alíquota (%) | O20: Valor (R$)
B22: TUSD - Ponta | C22: kWh | D22: 64 | E22: =IFERROR((ROUND(D22*K22,2)+ROUND(G22,2)+ROUND(J22,2))/ROUND(D22,4), 0) -> 1.4029688 | F22: =ROUND(D22*E22,2) -> 89.79 | G22: =((D22*K22)/(1-$N$22-$N$24))*($N$22+$N$24) -> 4.5981461 | H22: =((D22*K22)/(1-$N$22-$N$24)/(1-$I$22)) -> 89.78825 | I22: 0.17 | J22: =(H22*$I$22) -> 15.264002 | K22: =E60 -> 1.0925953 | L22: PIS | M22: =D80 -> 378.26921 | N22: ='B1 Res (GD) Branca OK'!N19 -> 0.011 | O22: =ROUND(M22*N22,2) -> 4.16 | Q22: TUSD Fio B | R22: Receita Fio B
B23: TUSD - Intermediário | C23: kWh | D23: 0 | E23: =IFERROR((ROUND(D23*K23,2)+ROUND(G23,2)+ROUND(J23,2))/ROUND(D23,4), 0) -> 0 | F23: =ROUND(D23*E23,2) -> 0 | G23: =((D23*K23)/(1-$N$22-$N$24))*($N$22+$N$24) -> 0 | H23: =((D23*K23)/(1-$N$22-$N$24)/(1-$I$22)) -> 0 | I23: =I22 -> 0.17 | J23: =(H23*$I$22) -> 0 | K23: =E62 -> 0.748986 | L23: PIS Inj | M23: =D83 -> -256.84749 | N23: =N22 -> 0.011 | O23: =ROUND(M23*N23,2) -> -2.83 | Q23: =IF(AND($B$15<$F$2,$E$15<$F$2),R6,IF($B$15<$F$2,X6,U6)) -> 0.7014669 | R23: =D60*Q23 -> 44.893882
B24: TUSD - Fora Ponta | C24: kWh | D24: 233 | E24: =IFERROR((ROUND(D24*K24,2)+ROUND(G24,2)+ROUND(J24,2))/ROUND(D24,4), 0) -> 0.52051502 | F24: =ROUND(D24*E24,2) -> 121.28 | G24: =((D24*K24)/(1-$N$22-$N$24))*($N$22+$N$24) -> 6.2108797 | H24: =((D24*K24)/(1-$N$22-$N$24)/(1-$I$22)) -> 121.28019 | I24: =I22 -> 0.17 | J24: =(H24*$I$22) -> 20.617632 | K24: =E61 -> 0.405372 | L24: COFINS | M24: =M22 -> 378.26921 | N24: ='B1 Res (GD) Branca OK'!N21 -> 0.0507 | O24: =ROUND(M24*N24,2) -> 19.18 | Q24: =IF(AND($B$15<$F$2,$E$15<$F$2),R7,IF($B$15<$F$2,X7,U7)) -> 0.42088018 | R24: =D61*Q24 -> 0
B25: TE - Ponta | C25: kWh | D25: =D22 -> 64 | E25: =IFERROR((ROUND(D25*K25,2)+ROUND(G25,2)+ROUND(J25,2))/ROUND(D25,4), 0) -> 0.6415625 | F25: =ROUND(D25*E25,2) -> 41.06 | G25: =((D25*K25)/(1-$N$22-$N$24))*($N$22+$N$24) -> 2.1026066 | H25: =ROUND((D25*K25)/(1-$N$23-$N$24)/(1-$I$22),8) -> 41.057714 | J25: =ROUND(H25*$I$22,2) -> 6.98 | K25: =F60 -> 0.499614 | L25: COFINS Inj | M25: =M23 -> -256.84749 | N25: =N24 -> 0.0507 | O25: =ROUND(M25*N25,2) -> -13.02 | Q25: =IF(AND($B$15<$F$2,$E$15<$F$2),R8,IF($B$15<$F$2,X8,U8)) -> 0.14029336 | R25: =D62*Q25 -> 32.688353
B26: TE - Intermediário | C26: kWh | D26: =D23 -> 0 | E26: =IFERROR((ROUND(D26*K26,2)+ROUND(G26,2)+ROUND(J26,2))/ROUND(D26,4), 0) -> 0 | F26: =ROUND(D26*E26,2) -> 0 | G26: =((D26*K26)/(1-$N$22-$N$24))*($N$22+$N$24) -> 0 | H26: =ROUND((D26*K26)/(1-$N$23-$N$24)/(1-$I$22),8) -> 0 | J26: =ROUND(H26*$I$22,2) -> 0 | K26: =F62 -> 0.31292067 | R26: =SUM(R23:R25) -> 77.582235
B27: TE - Fora Ponta | C27: kWh | D27: =D24 -> 233 | E27: =IFERROR((ROUND(D27*K27,2)+ROUND(G27,2)+ROUND(J27,2))/ROUND(D27,4), 0) -> 0.40180258 | F27: =ROUND(D27*E27,2) -> 93.62 | G27: =((D27*K27)/(1-$N$22-$N$24))*($N$22+$N$24) -> 4.7943928 | H27: =ROUND((D27*K27)/(1-$N$23-$N$24)/(1-$I$22),8) -> 93.620371 | J27: =ROUND(H27*$I$22,2) -> 15.92 | K27: =F61 -> 0.31292067
B28: Adicional BAM | C28: kWh | D28: =IF($K$13=M4,(($D$22+$D$23+$D$24)*($K$15)/($K$15+$L$15)),0)+IF($L$13=M4,(($D$22+$D$23+$D$24)*($L$15)/($K$15+$L$15)),0) -> 297 | E28: =IFERROR((ROUND(D28*K28,2)+ROUND(G28,2)+ROUND(J28,2))/ROUND(D28,4), 0) -> 0.024208754 | F28: =ROUND(D28*E28,2) -> 7.19 | G28: =((D28*K28)/(1-$N$22-$N$24))*($N$22+$N$24) -> 0.36813851 | H28: =ROUND((D28*K28)/(1-$N$22-$N$24)/(1-$I$22),8) -> 7.1886609 | J28: =ROUND(H28*$I$22,2) -> 1.22 | K28: =N4 -> 0.01885
B29: Adicional BVM1 | C29: kWh | D29: =IF($K$13=M5,(($D$22+$D$23+$D$24)*($K$15)/($K$15+$L$15)),0)+IF($L$13=M5,(($D$22+$D$23+$D$24)*($L$15)/($K$15+$L$15)),0) -> 0 | E29: =IFERROR((ROUND(D29*K29,2)+ROUND(G29,2)+ROUND(J29,2))/ROUND(D29,4), 0) -> 0 | F29: =ROUND(D29*E29,2) -> 0 | G29: =((D29*K29)/(1-$N$22-$N$24))*($N$22+$N$24) -> 0 | H29: =ROUND((D29*K29)/(1-$N$22-$N$24)/(1-$I$22),8) -> 0 | J29: =ROUND(H29*$I$22,2) -> 0 | K29: =N5 -> 0.04463
B30: Adicional BVM2 | C30: kWh | D30: =IF($K$13=M6,(($D$22+$D$23+$D$24)*($K$15)/($K$15+$L$15)),0)+IF($L$13=M6,(($D$22+$D$23+$D$24)*($L$15)/($K$15+$L$15)),0) -> 0 | E30: =IFERROR((ROUND(D30*K30,2)+ROUND(G30,2)+ROUND(J30,2))/ROUND(D30,4), 0) -> 0 | F30: =ROUND(D30*E30,2) -> 0 | G30: =((D30*K30)/(1-$N$22-$N$24))*($N$22+$N$24) -> 0 | H30: =ROUND((D30*K30)/(1-$N$22-$N$24)/(1-$I$22),8) -> 0 | J30: =ROUND(H30*$I$22,2) -> 0 | K30: =N6 -> 0.07877
B31: Adicional EH | C31: kWh | D31: =IF($K$13=M7,(($D$22+$D$23+$D$24)*($K$15)/($K$15+$L$15)),0)+IF($L$13=M7,(($D$22+$D$23+$D$24)*($L$15)/($K$15+$L$15)),0) -> 0 | E31: =IFERROR((ROUND(D31*K31,2)+ROUND(G31,2)+ROUND(J31,2))/ROUND(D31,4), 0) -> 0 | F31: =ROUND(D31*E31,2) -> 0 | G31: =((D31*K31)/(1-$N$22-$N$24))*($N$22+$N$24) -> 0 | H31: =ROUND((D31*K31)/(1-$N$22-$N$24)/(1-$I$22),8) -> 0 | J31: =ROUND(H31*$I$22,2) -> 0 | K31: =N7 -> 0.142
B33: TUSD - Ponta inj | C33: kWh | D33: -52.9735 | E33: =IFERROR((ROUND(D33*K33,2)+ROUND(G33,2)+ROUND(J33,2))/ROUND(D33,4),0) -> 1.1645445 | F33: =ROUND(D33*E33,2) -> -61.69 | G33: =((D33*K33)/(1-$N$23-$N$25))*($N$23+$N$25) -> -3.8059358 | H33: 0 | I33: 0 | J33: =H33*$I$33 -> 0 | K33: =K22 -> 1.0925953
B34: TUSD - Intermediário inj | C34: kWh | D34: 0 | E34: =IFERROR((ROUND(D34*K34,2)+ROUND(G34,2)+ROUND(J34,2))/ROUND(D34,4),0) -> 0 | F34: =ROUND(D34*E34,2) -> 0 | G34: =((D34*K34)/(1-$N$23-$N$25))*($N$23+$N$25) -> 0 | H34: 0 | I34: 0 | J34: =H34*$I$33 -> 0 | K34: =K23 -> 0.748986
B35: TUSD - Fora Ponta inj | C35: kWh | D35: -144.0207 | E35: =IFERROR((ROUND(D35*K35,2)+ROUND(G35,2)+ROUND(J35,2))/ROUND(D35,4),0) -> 0.43202123 | F35: =ROUND(D35*E35,2) -> -62.22 | G35: =((D35*K35)/(1-$N$23-$N$25))*($N$23+$N$25) -> -3.8390354 | H35: 0 | I35: 0 | J35: =H35*$I$33 -> 0 | K35: =K24 -> 0.405372
B36: TE - Ponta inj | C36: kWh | D36: =D33 -> -52.9735 | E36: =IFERROR((ROUND(D36*K36,2)+ROUND(G36,2)+ROUND(J36,2))/ROUND(D36,4),0) -> 0.64164158 | F36: =ROUND(D36*E36,2) -> -33.99 | G36: =((D36*K36)/(1-$N$23-$N$25))*($N$23+$N$25) -> -1.7403505 | H36: =ROUND((D36*K36)/(1-$N$23-$N$25)/(1-$I$36),8) -> -33.983919 | I36: 0.17 | J36: =H36*$I$36 -> -5.7772662 | K36: =K25 -> 0.499614
B37: TE - Intermediário inj | C37: kWh | D37: =D34 -> 0 | E37: =IFERROR((ROUND(D37*K37,2)+ROUND(G37,2)+ROUND(J37,2))/ROUND(D37,4),0) -> 0 | F37: =ROUND(D37*E37,2) -> 0 | G37: =((D37*K37)/(1-$N$23-$N$25))*($N$23+$N$25) -> 0 | H37: =ROUND((D37*K37)/(1-$N$23-$N$25)/(1-$I$36),8) -> 0 | I37: =I36 -> 0.17 | J37: =H37*$I$36 -> 0 | K37: =K26 -> 0.31292067
B38: TE - Fora Ponta inj | C38: kWh | D38: =D35 -> -144.0207 | E38: =IFERROR((ROUND(D38*K38,2)+ROUND(G38,2)+ROUND(J38,2))/ROUND(D38,4),0) -> 0.40181724 | F38: =ROUND(D38*E38,2) -> -57.87 | G38: =((D38*K38)/(1-$N$23-$N$25))*($N$23+$N$25) -> -2.9634842 | H38: =ROUND((D38*K38)/(1-$N$23-$N$25)/(1-$I$36),8) -> -57.868118 | I38: =I36 -> 0.17 | J38: =H38*$I$36 -> -9.83758 | K38: =K27 -> 0.31292067
B39: Adicional BAM inj | C39: kWh | D39: =IF($K$13=M4,(($D$33+$D$34+$D$35)*($K$15)/($K$15+$L$15)),0)+IF($L$13=M4,(($D$33+$D$34+$D$35)*($L$15)/($K$15+$L$15)),0) -> -196.9942 | E39: =IFERROR((ROUND(D39*K39,2)+ROUND(G39,2)+ROUND(J39,2))/ROUND(D39,4),0) -> 0.024163148 | F39: =ROUND(D39*E39,2) -> -4.76 | G39: =((D39*K39)/(1-$N$23-$N$25))*($N$23+$N$25) -> -0.24417896 | H39: =(D39*K39)/(1-$N$23-$N$25)/(1-$I$36) -> -4.7680959 | J39: =H39*$I$36 -> -0.81057631 | K39: =N4 -> 0.01885
B40: Adicional BVM1 inj | C40: kWh | D40: =IF($K$13=M5,(($D$33+$D$34+$D$35)*($K$15)/($K$15+$L$15)),0)+IF($L$13=M5,(($D$33+$D$34+$D$35)*($L$15)/($K$15+$L$15)),0) -> 0 | E40: =IFERROR((ROUND(D40*K40,2)+ROUND(G40,2)+ROUND(J40,2))/ROUND(D40,4),0) -> 0 | F40: =ROUND(D40*E40,2) -> 0 | G40: =((D40*K40)/(1-$N$23-$N$25))*($N$23+$N$25) -> 0 | H40: =(D40*K40)/(1-$N$23-$N$25)/(1-$I$36) -> 0 | J40: =H40*$I$36 -> 0 | K40: =N5 -> 0.04463
B41: Adicional BVM2 inj | C41: kWh | D41: =IF($K$13=M6,(($D$33+$D$34+$D$35)*($K$15)/($K$15+$L$15)),0)+IF($L$13=M6,(($D$33+$D$34+$D$35)*($L$15)/($K$15+$L$15)),0) -> 0 | E41: =IFERROR((ROUND(D41*K41,2)+ROUND(G41,2)+ROUND(J41,2))/ROUND(D41,4),0) -> 0 | F41: =ROUND(D41*E41,2) -> 0 | G41: =((D41*K41)/(1-$N$23-$N$25))*($N$23+$N$25) -> 0 | H41: =(D41*K41)/(1-$N$23-$N$25)/(1-$I$36) -> 0 | J41: =H41*$I$36 -> 0 | K41: =N6 -> 0.07877
B42: Adicional EH inj | C42: kWh | E42: =IFERROR((ROUND(D42*K42,2)+ROUND(G42,2)+ROUND(J42,2))/ROUND(D42,4),0) -> 0 | F42: =ROUND(D42*E42,2) -> 0 | G42: =((D42*K42)/(1-$N$23-$N$25))*($N$23+$N$25) -> 0 | H42: =(D42*K42)/(1-$N$23-$N$25)/(1-$I$36) -> 0 | J42: =H42*$I$36 -> 0 | K42: =N7 -> 0.142
B44: Multas
B45: Juros
B46: Bônus/Descontos
B47: Doações
B48: CIP | F48: 44.32
B51: TOTAL | F51: =SUM(F22:F50) -> 176.73 | G51: =SUM(G22:G50) -> 5.4811789 | H51: =SUM(H22:H50) -> 256.31505 | J51: =SUM(J22:J50) -> 43.576212
B53: Informativo Escassez | C53: =D86 -> 100.0058 | D53: =E86 -> 0.00018608682 | E53: =F86 -> -0.0025965236 | F53: =C53*(D53+E53) -> -0.24105766
B56: Fatura B1 Residencial TB
D57: Qtde | E57: TUSD | F57: TE | G57: TUSD + TE | H57: R$
B58: Fornecimento de Energia Elétrica | H58: =SUM(H60:H67)+SUM(H80:H84) -> 439.89855
B60: Consumo Ponta | D60: =D22 -> 64 | E60: =IF(AND($B$15<$F$2,$E$15<$F$2),C6,IF($B$15<$F$2,I6,F6)) -> 1.0925953 | F60: =IF(AND($B$15<$F$2,$E$15<$F$2),D6,IF($B$15<$F$2,J6,G6)) -> 0.499614 | G60: =E60+F60 -> 1.5922093 | H60: =ROUND((D60*E60),2)+ROUND((D60*F60),2) -> 101.91
B61: Consumo Fora Ponta | D61: =D23 -> 0 | E61: =IF(AND($B$15<$F$2,$E$15<$F$2),C7,IF($B$15<$F$2,I7,F7)) -> 0.405372 | F61: =IF(AND($B$15<$F$2,$E$15<$F$2),D7,IF($B$15<$F$2,J7,G7)) -> 0.31292067 | G61: =E61+F61 -> 0.71829267 | H61: =ROUND((D61*E61),2)+ROUND((D61*F61),2) -> 0
B62: Consumo Intemediário | D62: =D24 -> 233 | E62: =IF(AND($B$15<$F$2,$E$15<$F$2),C8,IF($B$15<$F$2,I8,F8)) -> 0.748986 | F62: =IF(AND($B$15<$F$2,$E$15<$F$2),D8,IF($B$15<$F$2,J8,G8)) -> 0.31292067 | G62: =E62+F62 -> 1.0619067 | H62: =ROUND((D62*E62),2)+ROUND((D62*F62),2) -> 247.42
B64: Adicional BAM | D64: =IF($K$13=M4,((D60+D61+D62)*(K15)/(K15+L15)),0)+IF($L$13=M4,((D60+D61+D62)*(L15)/(K15+L15)),0) -> 297 | F64: =N4 -> 0.01885 | H64: =ROUND(D64*(E64+F64),2) -> 5.6
B65: Adicional BVM 1 | D65: =IF($K$13=M5,((D60+D61+D62)*(K15)/(K15+L15)),0)+IF($L$13=M5,((D60+D61+D62)*(L15)/(K15+L15)),0) -> 0 | F65: =N5 -> 0.04463 | H65: =ROUND(D65*(E65+F65),2) -> 0
B66: Adicional BVM 2 | D66: =IF($K$13=M6,((D60+D61+D62)*(K15)/(K15+L15)),0)+IF($L$13=M6,((D60+D61+D62)*(L15)/(K15+L15)),0) -> 0 | F66: =N6 -> 0.07877 | H66: =ROUND(D66*(E66+F66),2) -> 0
B67: Adicional Escassez Hídrica | D67: =IF($K$13=M7,((D60+D61+D62)*(K15)/(K15+L15)),0)+IF($L$13=M7,((D60+D61+D62)*(L15)/(K15+L15)),0) -> 0 | F67: =N7 -> 0.142 | H67: =ROUND(D67*(E67+F67),2) -> 0 | K67: 58.22 | L67: 82.53
K68: 6.63 | L68: 9.4
B69: Energ Injetada P | D69: =D33 -> -52.9735 | E69: =E60*F18 -> 1.0925953 | F69: =F60 -> 0.499614 | G69: =E69+F69 -> 1.5922093 | H69: =ROUND((D69*E69),2)+ROUND((D69*F69),2) -> -84.35 | K69: =SUM(K67:K68) -> 64.85 | L69: =SUM(L67:L68) -> 91.93
B70: Energ Injetada FP | D70: =D34 -> 0 | E70: =E61*F18 -> 0.405372 | F70: =F61 -> 0.31292067 | G70: =E70+F70 -> 0.71829267 | H70: =ROUND((D70*E70),2)+ROUND((D70*F70),2) -> 0
B71: Energ Injetada Intem | D71: =D35 -> -144.0207 | E71: =E62*F18 -> 0.748986 | F71: =F62 -> 0.31292067 | G71: =E71+F71 -> 1.0619067 | H71: =ROUND((D71*E71),2)+ROUND((D71*F71),2) -> -152.94
B73: Adicional BAM Inj | D73: =IF($K$13=M4,(($D$69+$D$70+$D$71)*($K$15)/($K$15+$L$15)),0)+IF($L$13=M4,(($D$69+$D$70+$D$71)*($L$15)/($K$15+$L$15)),0) -> -196.9942 | F73: =N4 -> 0.01885 | H73: =ROUND(D73*(E73+F73),2) -> -3.71
B74: Adicional BVM 1 Inj | D74: =IF($K$13=M5,(($D$69+$D$70+$D$71)*($K$15)/($K$15+$L$15)),0)+IF($L$13=M5,(($D$69+$D$70+$D$71)*($L$15)/($K$15+$L$15)),0) -> 0 | F74: =N14 -> 0 | H74: =ROUND(D74*(E74+F74),2) -> 0
B75: Adicional BVM 2 Inj | D75: =IF($K$13=M6,(($D$69+$D$70+$D$71)*($K$15)/($K$15+$L$15)),0)+IF($L$13=M6,(($D$69+$D$70+$D$71)*($L$15)/($K$15+$L$15)),0) -> 0 | F75: =N15 -> 0 | H75: =ROUND(D75*(E75+F75),2) -> 0
B76: Adicional Escassez Hídrica Inj | D76: =IF($K$13=M7,(($D$69+$D$70+$D$71)*($K$15)/($K$15+$L$15)),0)+IF($L$13=M7,(($D$69+$D$70+$D$71)*($L$15)/($K$15+$L$15)),0) -> 0 | F76: =N16 -> 0 | H76: =ROUND(D76*(E76+F76),2) -> 0
H78: 77.59
D79: Base de Cálculo
B80: PIS | D80: =(SUM(H60:H67)/(1-E80-E82)) -> 378.26921 | E80: =N22 -> 0.011 | H80: =D80*E80 -> 4.1609613
B81: PIS INJ | D81: =(SUM(H69:H76)/(1-E81-E83)) -> -256.84749 | E81: =E80 -> 0.011 | H81: =D81*E81 -> -2.8253224
B82: COFINS | D82: =D80 -> 378.26921 | E82: =N24 -> 0.0507 | H82: =D82*E82 -> 19.178249
B83: COFINS INJ | D83: =D81 -> -256.84749 | E83: =E82 -> 0.0507 | H83: =D83*E83 -> -13.022168
B84: ICMS | D84: =D80/(1-E84) -> 455.74604 | E84: 0.17 | H84: =D84*E84 -> 77.476826
B85: ICMS INJ | D85: =((D69*F69)+(D70*F70)+(D71*F71)+H73+H74+H75+H76)/(1-E81-E83)/(1-E85) -> -96.615843 | E85: 0.17 | H85: =D85*E85 -> -16.424693
B86: Informativo Escassez Hídrica | D86: =SUM(D60:D62)+SUM(D69:D71) -> 100.0058 | E86: =IF(AND($B$15<$F$2,$E$15<$F$2),C9,IF($B$15<$F$2,I9,F9)) -> 0.00018608682 | F86: =IF(AND($B$15<$F$2,$E$15<$F$2),D9,IF($B$15<$F$2,J9,G9)) -> -0.0025965236 | H86: =D86*(E86+F86) -> -0.24105766
B88: Participação
C89: R$
B90: Energia | C90: =(SUM(H60:H67)*IF($B$15<$F$2,D128,D100)) -> 153.59096
B91: Distribuição | C91: =(SUM(H60:H67)*IF($B$15<$F$2,F128,F100)) -> 92.211579
B92: Transmissão | C92: =(SUM(H60:H67)*IF($B$15<$F$2,E128,E100)) -> 28.900538
B93: Encargos Setoriais | C93: =(SUM(H60:H67)*IF($B$15<$F$2,G128,G100)) -> 80.226925
B94: Impostos / Tributos | C94: =H80+H82+H84 -> 100.81604
B95: Total | C95: =SUM(C90:C94) -> 455.74604
B97: 2023 | D97: Energia | E97: Transmissão | F97: Distribuição | G97: Setoriais
B98: Grupo B | D98: % | E98: % | F98: % | G98: %
B100: B1 - Residencial | D100: 0.43273591 | E100: 0.081426023 | F100: 0.25980216 | G100: 0.22603591
B101: B1 - Residencial Baixa Renda | D101: 0.52914975 | E101: 0.099567792 | F101: 0.31768624 | G101: 0.053596219
B102: B2 - Rural | D102: 0.43273591 | E102: 0.081426023 | F102: 0.25980216 | G102: 0.22603591
B103: B2 - Cooperativa Eletrificação Rural | D103: 0.43273591 | E103: 0.081426023 | F103: 0.25980216 | G103: 0.22603591
B104: B2 - Serviço de Irrigação | D104: 0.43273591 | E104: 0.081426023 | F104: 0.25980216 | G104: 0.22603591
B105: B3 - Demais Classes | D105: 0.43273591 | E105: 0.081426023 | F105: 0.25980216 | G105: 0.22603591
B106: B4 - Iluminação Pública | D106: 0.43273591 | E106: 0.081426023 | F106: 0.25980216 | G106: 0.22603591
B107: B4a - Rede de Distribuição | D107: 0.43273591 | E107: 0.081426023 | F107: 0.25980216 | G107: 0.22603591
B108: B4b - Bulbo de Lâmpada | D108: 0.43273591 | E108: 0.081426023 | F108: 0.25980216 | G108: 0.22603591
B111: 2022 | D111: Energia | E111: Transmissão | F111: Distribuição | G111: Setoriais
B112: Grupo B | D112: % | E112: % | F112: % | G112: %
B114: B1 - Residencial | D114: 0.43273591 | E114: 0.081426023 | F114: 0.25980216 | G114: 0.22603591
B115: B1 - Residencial Baixa Renda | D115: 0.52914975 | E115: 0.099567792 | F115: 0.31768624 | G115: 0.053596219
B116: B2 - Rural | D116: 0.43273591 | E116: 0.081426023 | F116: 0.25980216 | G116: 0.22603591
B117: B2 - Cooperativa Eletrificação Rural | D117: 0.43273591 | E117: 0.081426023 | F117: 0.25980216 | G117: 0.22603591
B118: B2 - Serviço de Irrigação | D118: 0.43273591 | E118: 0.081426023 | F118: 0.25980216 | G118: 0.22603591
B119: B3 - Demais Classes | D119: 0.43273591 | E119: 0.081426023 | F119: 0.25980216 | G119: 0.22603591
B120: B4 - Iluminação Pública | D120: 0.43273591 | E120: 0.081426023 | F120: 0.25980216 | G120: 0.22603591
B121: B4a - Rede de Distribuição | D121: 0.43273591 | E121: 0.081426023 | F121: 0.25980216 | G121: 0.22603591
B122: B4b - Bulbo de Lâmpada | D122: 0.43273591 | E122: 0.081426023 | F122: 0.25980216 | G122: 0.22603591
...

Sheet B2 GD Branca OK
B2: B2 TB | E2: Vigência das Tarifas: | F2: ='B1 Res (GD) Branca OK'!F2 -> 46241 | H2: TARIFA BRANCA | M2: Bandeira | N2: R$/kWh | Q2: TUSD FIO B
M3: VERDE | N3: ='[4]B1 (Res) Branca OK'!N3 -> 0
B4: TARIFA | C4: ='Fatura B1 (GD) OK'!C4:E4 -> TARIFA ANTIGA - REH 3370/2024 | F4: ='Fatura B1 (GD) OK'!F4 -> TARIFA NOVA - REH xxxx/2025 | I4: Tarifas Proporcionalizadas | M4: BAM | N4: ='[4]B1 (Res) Branca OK'!N4 -> 0.01885 | Q4: TARIFA | R4: =C4 -> TARIFA ANTIGA - REH 3370/2024 | U4: =F4 -> TARIFA NOVA - REH xxxx/2025 | X4: Tarifas Proporcionalizadas
C5: Tusd | D5: TE | E5: TUSD + TE | F5: Tusd | G5: TE | H5: TUSD + TE | I5: Tusd | J5: TE | K5: TUSD + TE | M5: BVM1 | N5: ='[4]B1 (Res) Branca OK'!N5 -> 0.04463 | R5: Tusd (R$/kWh) | U5: Tusd (R$/kWh) | X5: Tusd (R$/kWh)
B6: B2 Ponta | C6: ='TABELA DE TARIFAS ANTIGAS'!G74/1000 -> 1.06103 | D6: ='TABELA DE TARIFAS ANTIGAS'!H74/1000 -> 0.48448 | E6: =C6+D6 -> 1.54551 | F6: ='TABELA DE TARIFAS NOVAS'!G76/1000 -> 1.12867 | G6: ='TABELA DE TARIFAS NOVAS'!H76/1000 -> 0.51691 | H6: =F6+G6 -> 1.64558 | I6: =((C6*$C$15)+(F6*$D$15))/($D$15+$C$15) -> 1.0715987 | J6: =((D6*$C$15)+(G6*$D$15))/($D$15+$C$15) -> 0.48954719 | K6: =I6+J6 -> 1.5611459 | M6: BVM2 | N6: ='[4]B1 (Res) Branca OK'!N6 -> 0.07877 | Q6: =B6 -> B2 Ponta | R6: ='FIO B'!H16/1000 -> 0.69302445 | U6: ='FIO B'!K16/1000 -> 0.71111541 | X6: =((R6*$C$15)+(U6*$D$15))/($D$15+$C$15) -> 0.69585117
B7: B2 Fora Ponta | C7: ='TABELA DE TARIFAS ANTIGAS'!G76/1000 -> 0.38965 | D7: ='TABELA DE TARIFAS ANTIGAS'!H76/1000 -> 0.30579 | E7: =C7+D7 -> 0.69544 | F7: ='TABELA DE TARIFAS NOVAS'!G78/1000 -> 0.42334 | G7: ='TABELA DE TARIFAS NOVAS'!H78/1000 -> 0.32107 | H7: =F7+G7 -> 0.74441 | I7: =((C7*$C$15)+(F7*$D$15))/($D$15+$C$15) -> 0.39491406 | J7: =((D7*$C$15)+(G7*$D$15))/($D$15+$C$15) -> 0.3081775 | K7: =I7+J7 -> 0.70309156 | M7: Escassez Hídrica | N7: 0.142 | Q7: =B7 -> B2 Fora Ponta | R7: ='FIO B'!H17/1000 -> 0.41581471 | U7: ='FIO B'!K17/1000 -> 0.42666929 | X7: =((R7*$C$15)+(U7*$D$15))/($D$15+$C$15) -> 0.41751074
B8: B2 Interm. | C8: ='TABELA DE TARIFAS ANTIGAS'!G75/1000 -> 0.72534 | D8: ='TABELA DE TARIFAS ANTIGAS'!H75/1000 -> 0.30579 | E8: =C8+D8 -> 1.03113 | F8: ='TABELA DE TARIFAS NOVAS'!G77/1000 -> 0.77601 | G8: ='TABELA DE TARIFAS NOVAS'!H77/1000 -> 0.32107 | H8: =F8+G8 -> 1.09708 | I8: =((C8*$C$15)+(F8*$D$15))/($D$15+$C$15) -> 0.73325719 | J8: =((D8*$C$15)+(G8*$D$15))/($D$15+$C$15) -> 0.3081775 | K8: =I8+J8 -> 1.0414347 | Q8: =B8 -> B2 Interm. | R8: ='FIO B'!H18/1000 -> 0.13860487 | U8: ='FIO B'!K18/1000 -> 0.14222306 | X8: =((R8*$C$15)+(U8*$D$15))/($D$15+$C$15) -> 0.13917021
B9: CDE Escassez Hídrica | C9: 0.00018774721 | D9: -0.0044031307 | E9: =SUM(C9+D9) -> -0.0042153835 | F9: =T13 -> 0.00018418923 | G9: =U13 -> -0.00053182975 | H9: =F9+G9 -> -0.00034764052 | I9: =((C9*$C$15)+(F9*$D$15))/($D$15+$C$15) -> 0.00018719128 | J9: =((D9*$C$15)+(G9*$D$15))/($D$15+$C$15) -> -0.00379824 | K9: =I9+J9 -> -0.0036110487
P10: CUSTO | R10: Part. TUSD (%) | S10: Part. TE (%) | T10: Tusd (R$/kWh) | U10: TE (R$/kWh)
H11: Fatura | L11: Vigência das Tarifas (troca Bandeira): | M11: =EOMONTH(B15,0)+1 -> 46235 | P11: CDE CONTAS
B12: INSTALAÇÃO | C12: 584185 | H12: =E15 -> 46245 | K12: Altere a bandeira na célula abaixo | P12: CDE COVID | U12: 0
K13: BAM | L13: BAM | P13: CDE ESCASSEZ HÍDRICA | T13: ='B1 Res (GD) Branca OK'!T13 -> 0.00018418923 | U13: ='B1 Res (GD) Branca OK'!U13 -> -0.00053182975
B14: Leitura Anterior | C14: Nº de dias tarifa Anterior | D14: Nº de dias tarifa Nova | E14: Leitura Atual | J14: Leitura Anterior | K14: Nº de dias tarifa Anterior | L14: Nº de dias tarifa Nova | M14: Leitura Atual
B15: 46213 | C15: =IF((F2-B15-1)<0,0,(F2-B15-1)) -> 27 | D15: =E15-F2+1 -> 5 | E15: 46245 | J15: =B15 -> 46213 | K15: =IF((M11-J15-1)<0,0,(M11-J15-1)) -> 21 | L15: =M15-M11+1 -> 11 | M15: =E15 -> 46245
Q16: instalações
Q17: 584185
B18: Perc. de Redução da Energia Injetada | E18: TUSD | F18: 1 | G18: TE | H18: 1 | M18: Documento impressão: | O18: 1025310408 | Q18: 160671516
Q19: 645437
B20: Descrição | C20: Unidade | D20: Quantidade | E20: Preço Unit (R$) com tributos | F20: Valor Total (R$) | G20: PIS/COFINS (R$) | H20: Base de Cálculo ICMS (R$) | I20: Alíquota ICMS (%) | J20: ICMS (R$) | K20: Preço Unit (R$) | L20: Tributos | M20: Base de Cálc (R$) | N20: Alíquota (%) | O20: Valor (R$)
B22: TUSD - Ponta | C22: kWh | D22: 204 | E22: =IFERROR((ROUND(D22*K22,2)+ROUND(G22,2)+ROUND(J22,2))/ROUND(D22,4), 0) -> 1.1896569 | F22: =ROUND(D22*E22,2) -> 242.69 | G22: =((D22*K22)/(1-$N$22-$N$24))*($N$22+$N$24) -> 14.374932 | H22: =(IF($I$22=12%,(D22*K22)/(1-$N$22-$N$24)/(1-$C$93)/$F$93*$C$93,(D22*K22)/(1-$N$22-$N$24)/(1-$I$22))) -> 80.896207 | I22: 0.12 | J22: =(H22*$I$22) -> 9.7075449 | K22: =E60 -> 1.0715987 | L22: PIS | M22: =D80 -> 805.69114 | N22: ='B1 Res (GD) Branca OK'!N19 -> 0.011 | O22: =ROUND(M22*N22,2) -> 8.86 | R22: 60.906708
B23: TUSD - Intermediário | C23: kWh | D23: 0 | E23: =IFERROR((ROUND(D23*K23,2)+ROUND(G23,2)+ROUND(J23,2))/ROUND(D23,4), 0) -> 0 | F23: =ROUND(D23*E23,2) -> 0 | G23: =((D23*K23)/(1-$N$22-$N$24))*($N$22+$N$24) -> 0 | H23: =(IF($I$22=12%,(D23*K23)/(1-$N$22-$N$24)/(1-$C$93)/$F$93*$C$93,(D23*K23)/(1-$N$22-$N$24)/(1-$I$22))) -> 0 | I23: =I22 -> 0.12 | J23: =(H23*$I$22) -> 0 | K23: =E62 -> 0.73325719 | L23: PIS Inj | M23: =D81 -> -691.49526 | N23: =N22 -> 0.011 | O23: =ROUND(M23*N23,2) -> -7.61 | R23: 23.773292
B24: TUSD - Fora Ponta | C24: kWh | D24: 409 | E24: =IFERROR((ROUND(D24*K24,2)+ROUND(G24,2)+ROUND(J24,2))/ROUND(D24,4), 0) -> 0.43841076 | F24: =ROUND(D24*E24,2) -> 179.31 | G24: =((D24*K24)/(1-$N$22-$N$24))*($N$22+$N$24) -> 10.621096 | H24: =(IF($I$22=12%,(D24*K24)/(1-$N$22-$N$24)/(1-$C$93)/$F$93*$C$93,(D24*K24)/(1-$N$22-$N$24)/(1-$I$22))) -> 59.771163 | I24: =I22 -> 0.12 | J24: =(H24*$I$22) -> 7.1725395 | K24: =E61 -> 0.39491406 | L24: COFINS | M24: =D82 -> 805.69114 | N24: ='B1 Res (GD) Branca OK'!N21 -> 0.0507 | O24: =ROUND(M24*N24,2) -> 40.85
B25: TE - Ponta | C25: kWh | D25: =D22 -> 204 | E25: =IFERROR((ROUND(D25*K25,2)+ROUND(G25,2)+ROUND(J25,2))/ROUND(D25,4), 0) -> 0.54348039 | F25: =ROUND(D25*E25,2) -> 110.87 | G25: =((D25*K25)/(1-$N$22-$N$24))*($N$22+$N$24) -> 6.5670175 | H25: =(IF($I$22=12%,(D25*K25)/(1-$N$22-$N$24)/(1-$C$93)/$F$93*$C$93,(D25*K25)/(1-$N$22-$N$24)/(1-$I$22))) -> 36.956474 | J25: =(H25*$I$22) -> 4.4347768 | K25: =F60 -> 0.48954719 | L25: COFINS Inj | M25: =D83 -> -691.49526 | N25: =N24 -> 0.0507 | O25: =ROUND(M25*N25,2) -> -35.06
B26: TE - Intermediário | C26: kWh | D26: =D23 -> 0 | E26: =IFERROR((ROUND(D26*K26,2)+ROUND(G26,2)+ROUND(J26,2))/ROUND(D26,4), 0) -> 0 | F26: =ROUND(D26*E26,2) -> 0 | G26: =((D26*K26)/(1-$N$22-$N$24))*($N$22+$N$24) -> 0 | H26: =(IF($I$22=12%,(D26*K26)/(1-$N$22-$N$24)/(1-$C$93)/$F$93*$C$93,(D26*K26)/(1-$N$22-$N$24)/(1-$I$22))) -> 0 | J26: =(H26*$I$22) -> 0 | K26: =F62 -> 0.3081775
B27: TE - Fora Ponta | C27: kWh | D27: =D24 -> 409 | E27: =IFERROR((ROUND(D27*K27,2)+ROUND(G27,2)+ROUND(J27,2))/ROUND(D27,4), 0) -> 0.34212714 | F27: =ROUND(D27*E27,2) -> 139.93 | G27: =((D27*K27)/(1-$N$22-$N$24))*($N$22+$N$24) -> 8.2883424 | H27: =(IF($I$22=12%,(D27*K27)/(1-$N$22-$N$24)/(1-$C$93)/$F$93*$C$93,(D27*K27)/(1-$N$22-$N$24)/(1-$I$22))) -> 46.643382 | J27: =(H27*$I$22) -> 5.5972058 | K27: =F61 -> 0.3081775
B28: Adicional BAM | C28: kWh | D28: =IF($K$13=M4,(($D$22+$D$23+$D$24)*($K$15)/($K$15+$L$15)),0)+IF($L$13=M4,(($D$22+$D$23+$D$24)*($L$15)/($K$15+$L$15)),0) -> 613 | E28: =IFERROR((ROUND(D28*K28,2)+ROUND(G28,2)+ROUND(J28,2))/ROUND(D28,4), 0) -> 0.020929853 | F28: =ROUND(D28*E28,2) -> 12.83 | G28: =((D28*K28)/(1-$N$22-$N$24))*($N$22+$N$24) -> 0.75982797 | H28: =(IF($I$22=12%,(D28*K28)/(1-$N$22-$N$24)/(1-$C$93)/$F$93*$C$93,(D28*K28)/(1-$N$22-$N$24)/(1-$I$22))) -> 4.2759993 | J28: =ROUND(H28*$I$22,2) -> 0.51 | K28: =N4 -> 0.01885
B29: Adicional BVM1 | C29: kWh | D29: =IF($K$13=M5,(($D$22+$D$23+$D$24)*($K$15)/($K$15+$L$15)),0)+IF($L$13=M5,(($D$22+$D$23+$D$24)*($L$15)/($K$15+$L$15)),0) -> 0 | E29: =IFERROR((ROUND(D29*K29,2)+ROUND(G29,2)+ROUND(J29,2))/ROUND(D29,4), 0) -> 0 | F29: =ROUND(D29*E29,2) -> 0 | G29: =((D29*K29)/(1-$N$22-$N$24))*($N$22+$N$24) -> 0 | H29: =(IF($I$22=12%,(D29*K29)/(1-$N$22-$N$24)/(1-$C$93)/$F$93*$C$93,(D29*K29)/(1-$N$22-$N$24)/(1-$I$22))) -> 0 | J29: =ROUND(H29*$I$22,2) -> 0 | K29: =N5 -> 0.04463
B30: Adicional BVM2 | C30: kWh | D30: =IF($K$13=M6,(($D$22+$D$23+$D$24)*($K$15)/($K$15+$L$15)),0)+IF($L$13=M6,(($D$22+$D$23+$D$24)*($L$15)/($K$15+$L$15)),0) -> 0 | E30: =IFERROR((ROUND(D30*K30,2)+ROUND(G30,2)+ROUND(J30,2))/ROUND(D30,4), 0) -> 0 | F30: =ROUND(D30*E30,2) -> 0 | G30: =((D30*K30)/(1-$N$22-$N$24))*($N$22+$N$24) -> 0 | H30: =(IF($I$22=12%,(D30*K30)/(1-$N$22-$N$24)/(1-$C$93)/$F$93*$C$93,(D30*K30)/(1-$N$22-$N$24)/(1-$I$22))) -> 0 | J30: =ROUND(H30*$I$22,2) -> 0 | K30: =N6 -> 0.07877 | R30: TUSD Fio B | S30: Receita Fio B
B31: Adicional EH | C31: kWh | D31: =IF($K$13=M7,(($D$22+$D$23+$D$24)*($K$15)/($K$15+$L$15)),0)+IF($L$13=M7,(($D$22+$D$23+$D$24)*($L$15)/($K$15+$L$15)),0) -> 0 | E31: =IFERROR((ROUND(D31*K31,2)+ROUND(G31,2)+ROUND(J31,2))/ROUND(D31,4), 0) -> 0 | F31: =ROUND(D31*E31,2) -> 0 | G31: =((D31*K31)/(1-$N$22-$N$24))*($N$22+$N$24) -> 0 | H31: =(IF($I$22=12%,(D31*K31)/(1-$N$22-$N$24)/(1-$C$93)/$F$93*$C$93,(D31*K31)/(1-$N$22-$N$24)/(1-$I$22))) -> 0 | J31: =ROUND(H31*$I$22,2) -> 0 | K31: =N7 -> 0.142 | R31: =IF(AND($B$15<$F$2,$E$15<$F$2),R6,IF($B$15<$F$2,X6,U6)) -> 0.69585117 | S31: =D60*R31 -> 141.95364
R32: =IF(AND($B$15<$F$2,$E$15<$F$2),R7,IF($B$15<$F$2,X7,U7)) -> 0.41751074 | S32: =D61*R32 -> 0
B33: TUSD - Ponta inj | C33: kWh | D33: -186.9945 | E33: =IFERROR((ROUND(D33*K33,2)+ROUND(G33,2)+ROUND(J33,2))/ROUND(D33,4),0) -> 1.1420657 | F33: =ROUND(D33*E33,2) -> -213.56 | G33: =((D33*K33)/(1-$N$23-$N$25))*($N$23+$N$25) -> -13.176634 | H33: 0 | I33: 0 | J33: =H33*$I$25 -> 0 | K33: =K22 -> 1.0715987 | R33: =IF(AND($B$15<$F$2,$E$15<$F$2),R8,IF($B$15<$F$2,X8,U8)) -> 0.13917021 | S33: =D62*R33 -> 56.920617
B34: TUSD - Inermediário inj | C34: kWh | D34: 0 | E34: =IFERROR((ROUND(D34*K34,2)+ROUND(G34,2)+ROUND(J34,2))/ROUND(D34,4),0) -> 0 | F34: =ROUND(D34*E34,2) -> 0 | G34: =((D34*K34)/(1-$N$23-$N$25))*($N$23+$N$25) -> 0 | H34: 0 | I34: 0 | J34: =H34*$I$25 -> 0 | K34: =K23 -> 0.73325719 | S34: =SUM(S31:S33) -> 198.87426
B35: TUSD - Fora Ponta inj | C35: kWh | D35: -333.2916 | E35: =IFERROR((ROUND(D35*K35,2)+ROUND(G35,2)+ROUND(J35,2))/ROUND(D35,4),0) -> 0.4208927 | F35: =ROUND(D35*E35,2) -> -140.28 | G35: =((D35*K35)/(1-$N$23-$N$25))*($N$23+$N$25) -> -8.6550666 | H35: 0 | I35: 0 | J35: =H35*$I$25 -> 0 | K35: =K24 -> 0.39491406
B36: TE - Ponta inj | C36: kWh | D36: =D33 -> -186.9945 | E36: =IFERROR((ROUND(D36*K36,2)+ROUND(G36,2)+ROUND(J36,2))/ROUND(D36,4),0) -> 0.54349192 | F36: =ROUND(D36*E36,2) -> -101.63 | G36: =((D36*K36)/(1-$N$23-$N$25))*($N$23+$N$25) -> -6.019589 | H36: =(IF($I$36=12%,(D36*K36)/(1-$N$22-$N$24)/(1-$C$104)/$F$104*$C$104,(D36*K36)/(1-$N$22-$N$24)/(1-$I$36))) -> -33.875771 | I36: =$I$22 -> 0.12 | J36: =H36*$I$36 -> -4.0650925 | K36: =K25 -> 0.48954719
B37: TE - Intermediário inj | C37: kWh | D37: =D34 -> 0 | E37: =IFERROR((ROUND(D37*K37,2)+ROUND(G37,2)+ROUND(J37,2))/ROUND(D37,4),0) -> 0 | F37: =ROUND(D37*E37,2) -> 0 | G37: =((D37*K37)/(1-$N$23-$N$25))*($N$23+$N$25) -> 0 | H37: =(IF($I$36=12%,(D37*K37)/(1-$N$22-$N$24)/(1-$C$104)/$F$104*$C$104,(D37*K37)/(1-$N$22-$N$24)/(1-$I$36))) -> 0 | I37: =$I$22 -> 0.12 | J37: =H37*$I$36 -> 0 | K37: =K26 -> 0.3081775
B38: TE - Fora Ponta inj | C38: kWh | D38: =D35 -> -333.2916 | E38: =IFERROR((ROUND(D38*K38,2)+ROUND(G38,2)+ROUND(J38,2))/ROUND(D38,4),0) -> 0.34210283 | F38: =ROUND(D38*E38,2) -> -114.02 | G38: =((D38*K38)/(1-$N$23-$N$25))*($N$23+$N$25) -> -6.7541196 | H38: =(IF($I$36=12%,(D38*K38)/(1-$N$22-$N$24)/(1-$C$104)/$F$104*$C$104,(D38*K38)/(1-$N$22-$N$24)/(1-$I$36))) -> -38.009407 | I38: =$I$22 -> 0.12 | J38: =H38*$I$36 -> -4.5611288 | K38: =K27 -> 0.3081775
B39: Adicional BAM inj | C39: kWh | D39: =IF($K$13=M4,(($D$33+$D$34+$D$35)*($K$15)/($K$15+$L$15)),0)+IF($L$13=M4,(($D$33+$D$34+$D$35)*($L$15)/($K$15+$L$15)),0) -> -520.2861 | E39: =IFERROR((ROUND(D39*K39,2)+ROUND(G39,2)+ROUND(J39,2))/ROUND(D39,4),0) -> 0.020930792 | F39: =ROUND(D39*E39,2) -> -10.89 | G39: =((D39*K39)/(1-$N$23-$N$25))*($N$23+$N$25) -> -0.6449069 | H39: =(IF($I$36=12%,(D39*K39)/(1-$N$22-$N$24)/(1-$C$104)/$F$104*$C$104,(D39*K39)/(1-$N$22-$N$24)/(1-$I$36))) -> -3.6292708 | J39: =H39*$I$36 -> -0.4355125 | K39: =N4 -> 0.01885
B40: Adicional BVM1 inj | C40: kWh | D40: =IF($K$13=M5,(($D$33+$D$34+$D$35)*($K$15)/($K$15+$L$15)),0)+IF($L$13=M5,(($D$33+$D$34+$D$35)*($L$15)/($K$15+$L$15)),0) -> 0 | E40: =IFERROR((ROUND(D40*K40,2)+ROUND(G40,2)+ROUND(J40,2))/ROUND(D40,4),0) -> 0 | F40: =ROUND(D40*E40,2) -> 0 | G40: =((D40*K40)/(1-$N$23-$N$25))*($N$23+$N$25) -> 0 | H40: =(IF($I$36=12%,(D40*K40)/(1-$N$22-$N$24)/(1-$C$104)/$F$104*$C$104,(D40*K40)/(1-$N$22-$N$24)/(1-$I$36))) -> 0 | J40: =H40*$I$36 -> 0 | K40: =N5 -> 0.04463
B41: Adicional BVM2 inj | C41: kWh | D41: =IF($K$13=M6,(($D$33+$D$34+$D$35)*($K$15)/($K$15+$L$15)),0)+IF($L$13=M6,(($D$33+$D$34+$D$35)*($L$15)/($K$15+$L$15)),0) -> 0 | E41: =IFERROR((ROUND(D41*K41,2)+ROUND(G41,2)+ROUND(J41,2))/ROUND(D41,4),0) -> 0 | F41: =ROUND(D41*E41,2) -> 0 | G41: =((D41*K41)/(1-$N$23-$N$25))*($N$23+$N$25) -> 0 | H41: =(IF($I$36=12%,(D41*K41)/(1-$N$22-$N$24)/(1-$C$104)/$F$104*$C$104,(D41*K41)/(1-$N$22-$N$24)/(1-$I$36))) -> 0 | J41: =H41*$I$36 -> 0 | K41: =N6 -> 0.07877
B42: Adicional EH inj | C42: kWh | D42: =IF($K$13=M7,(($D$33+$D$34+$D$35)*($K$15)/($K$15+$L$15)),0)+IF($L$13=M7,(($D$33+$D$34+$D$35)*($L$15)/($K$15+$L$15)),0) -> 0 | E42: =IFERROR((ROUND(D42*K42,2)+ROUND(G42,2)+ROUND(J42,2))/ROUND(D42,4),0) -> 0 | F42: =ROUND(D42*E42,2) -> 0 | G42: =((D42*K42)/(1-$N$23-$N$25))*($N$23+$N$25) -> 0 | H42: =(IF($I$36=12%,(D42*K42)/(1-$N$22-$N$24)/(1-$C$104)/$F$104*$C$104,(D42*K42)/(1-$N$22-$N$24)/(1-$I$36))) -> 0 | J42: =H42*$I$36 -> 0 | K42: =N7 -> 0.142
B44: Multas
B45: Juros
B46: Doações | F46: -8.35
B47: CIP
B50: TOTAL | F50: =SUM(F22:F49) -> 96.9 | G50: =SUM(G22:G49) -> 5.3609009 | H50: =SUM(H22:H49) -> 153.02878 | J50: =SUM(J22:J49) -> 18.360333
B52: Informativo Escassez | C52: =D86 -> 92.7139 | D52: =E86 -> 0.00018719128 | E52: =F86 -> -0.00379824 | F52: =C52*(D52+E52) -> -0.33479441
B56: Fatura B1 Residencial TB
D57: Qtde | E57: TUSD | F57: TE | G57: TUSD + TE | H57: R$
B58: Fornecimento de Energia Elétrica | H58: =SUM(H60:H67)+SUM(H80:H84) -> 796.59635
B60: Consumo Ponta | D60: =D22 -> 204 | E60: =IF(AND($B$15<$F$2,$E$15<$F$2),C6,IF($B$15<$F$2,I6,F6)) -> 1.0715987 | F60: =IF(AND($B$15<$F$2,$E$15<$F$2),D6,IF($B$15<$F$2,J6,G6)) -> 0.48954719 | G60: =E60+F60 -> 1.5611459 | H60: =ROUND((D60*E60),2)+ROUND((D60*F60),2) -> 318.48
B61: Consumo Fora Ponta | D61: =D23 -> 0 | E61: =IF(AND($B$15<$F$2,$E$15<$F$2),C7,IF($B$15<$F$2,I7,F7)) -> 0.39491406 | F61: =IF(AND($B$15<$F$2,$E$15<$F$2),D7,IF($B$15<$F$2,J7,G7)) -> 0.3081775 | G61: =E61+F61 -> 0.70309156 | H61: =ROUND((D61*E61),2)+ROUND((D61*F61),2) -> 0
B62: Consumo Intemediário | D62: =D24 -> 409 | E62: =IF(AND($B$15<$F$2,$E$15<$F$2),C8,IF($B$15<$F$2,I8,F8)) -> 0.73325719 | F62: =IF(AND($B$15<$F$2,$E$15<$F$2),D8,IF($B$15<$F$2,J8,G8)) -> 0.3081775 | G62: =E62+F62 -> 1.0414347 | H62: =ROUND((D62*E62),2)+ROUND((D62*F62),2) -> 425.94
B64: Adicional BAM | D64: =IF($K$13=M4,((D60+D61+D62)*(K15)/(K15+L15)),0)+IF($L$13=M4,((D60+D61+D62)*(L15)/(K15+L15)),0) -> 613 | F64: =N4 -> 0.01885 | H64: =ROUND(D64*(E64+F64),2) -> 11.56
B65: Adicional BVM 1 | D65: =IF($K$13=M5,((D60+D61+D62)*(K15)/(K15+L15)),0)+IF($L$13=M5,((D60+D61+D62)*(L15)/(K15+L15)),0) -> 0 | F65: =N5 -> 0.04463 | H65: =ROUND(D65*(E65+F65),2) -> 0
B66: Adicional BVM 2 | D66: =IF($K$13=M6,((D60+D61+D62)*(K15)/(K15+L15)),0)+IF($L$13=M6,((D60+D61+D62)*(L15)/(K15+L15)),0) -> 0 | F66: =N6 -> 0.07877 | H66: =ROUND(D66*(E66+F66),2) -> 0
B67: Adicional Escassez Hídrica | D67: =IF($K$13=M7,((D60+D61+D62)*(K15)/(K15+L15)),0)+IF($L$13=M7,((D60+D61+D62)*(L15)/(K15+L15)),0) -> 0 | F67: =N7 -> 0.142 | H67: =ROUND(D67*(E67+F67),2) -> 0
B69: Energ Injetada P | D69: =D33 -> -186.9945 | E69: =E60*F18 -> 1.0715987 | F69: =F60 -> 0.48954719 | G69: =E69+F69 -> 1.5611459 | H69: =ROUND((D69*E69),2)+ROUND((D69*F69),2) -> -291.92
B70: Energ Injetada FP | D70: =D34 -> 0 | E70: =E61*F18 -> 0.39491406 | F70: =F61 -> 0.3081775 | G70: =E70+F70 -> 0.70309156 | H70: =ROUND((D70*E70),2)+ROUND((D70*F70),2) -> 0
B71: Energ Injetada Intem | D71: =D35 -> -333.2916 | E71: =E62*F18 -> 0.73325719 | F71: =F62 -> 0.3081775 | G71: =E71+F71 -> 1.0414347 | H71: =ROUND((D71*E71),2)+ROUND((D71*F71),2) -> -347.1
B73: Adicional BAM Inj | D73: =IF($K$13=M4,((D69+D70+D71)*(K15)/(K15+L15)),0)+IF($L$13=M4,((D69+D70+D71)*(L15)/(K15+L15)),0) -> -520.2861 | F73: =N4 -> 0.01885 | H73: =ROUND(D73*(E73+F73),2) -> -9.81
B74: Adicional BVM 1 Inj | D74: =IF($K$13=M5,((D70+D71+D72)*(K15)/(K15+L15)),0)+IF($L$13=M5,((D70+D71+D72)*(L15)/(K15+L15)),0) -> 0 | F74: =N14 -> 0 | H74: =ROUND(D74*(E74+F74),2) -> 0
B75: Adicional BVM 2 Inj | D75: =IF($K$13=M6,((D71+D72+D73)*(K15)/(K15+L15)),0)+IF($L$13=M6,((D71+D72+D73)*(L15)/(K15+L15)),0) -> 0 | F75: =N15 -> 0 | H75: =ROUND(D75*(E75+F75),2) -> 0
B76: Adicional Escassez Hídrica Inj | D76: =IF($K$13=M7,((D72+D73+D74)*(K15)/(K15+L15)),0)+IF($L$13=M7,((D72+D73+D74)*(L15)/(K15+L15)),0) -> 0 | F76: =N16 -> 0 | H76: =ROUND(D76*(E76+F76),2) -> 0
D79: Base de Cálculo
B80: PIS | D80: =(SUM(H60:H67)/(1-E80-E82)) -> 805.69114 | E80: =N22 -> 0.011 | H80: =D80*E80 -> 8.8626026
B81: PIS INJ | D81: =(SUM(H69:H76)/(1-E81-E83)) -> -691.49526 | E81: =E80 -> 0.011 | H81: =D81*E81 -> -7.6064478
B82: COFINS | D82: =D80 -> 805.69114 | E82: =N24 -> 0.0507 | H82: =D82*E82 -> 40.848541
B83: COFINS INJ | D83: =D81 -> -691.49526 | E83: =E82 -> 0.0507 | H83: =D83*E83 -> -35.05881
B84: ICMS | D84: =IF((E84=17%),(D80/(1-(E84))),D93) -> 279.75387 | E84: 0.12 | H84: =D84*E84 -> 33.570464
B85: ICMS INJ | D85: =D104 -> -75.515413 | E85: 0.12 | H85: =D85*E85 -> -9.0618496
B86: Informativo Escassez Hídrica | D86: =SUM(D60:D62)+SUM(D69:D71) -> 92.7139 | E86: =IF(AND($B$15<$F$2,$E$15<$F$2),C9,IF($B$15<$F$2,I9,F9)) -> 0.00018719128 | F86: =IF(AND($B$15<$F$2,$E$15<$F$2),D9,IF($B$15<$F$2,J9,G9)) -> -0.00379824 | H86: =D86*(E86+F86) -> -0.33479441
B88: Se for base reduzida: (célula E33 = 12%)
A89: FORNECIDA
D90: Com tributos
B91: PIS | C91: =E80 -> 0.011 | D91: =(SUM(H60:H67)/(1-E80-E82)) -> 805.69114 | E91: x | F91: =C91 -> 0.011 | G91: =D91*F91 -> 8.8626026
B92: COFINS | C92: =E82 -> 0.0507 | D92: =D91 -> 805.69114 | E92: x | F92: =C92 -> 0.0507 | G92: =D92*F92 -> 40.848541
A93: Rural c/ incrição | B93: ICMS | C93: 0.04 | D93: =H93/F93*C93 -> 279.75387 | E93: x | F93: 0.12 | G93: =D93*F93 -> 33.570464 | H93: =((SUM(H60:H67))/(1-F91-F92)/(1-(C93))) -> 839.26161 | I93: =H93*C93 -> 33.570464
E94: =(O82)/(1-C91-C92-C93) -> 0
D96: Base de cálculo reduzida = | E96: Importe | G96: = | H96: =H93/F93*C93 -> 279.75387
E97: 12% x 4%
A99: INJETADA
B100: Se for base reduzida: (célula E33 = 12%)
D101: Com tributos
B102: PIS | C102: =E81 -> 0.011 | D102: =SUM(H69:H76)/(1-C102-C103) -> -691.49526 | E102: x | F102: =C102 -> 0.011 | G102: =D102*F102 -> -7.6064478
B103: COFINS | C103: =E83 -> 0.0507 | D103: =D102 -> -691.49526 | E103: x | F103: =C103 -> 0.0507 | G103: =D103*F103 -> -35.05881
A104: Rural c/ incrição | B104: ICMS | C104: 0.04 | D104: =H104/F104*C104 -> -75.515413 | E104: x | F104: 0.12 | G104: =D104*F104 -> -9.0618496 | H104: =((D69*F69)+(D70*F70)+(D71*F71)+H73+H74+H75+H76)/(1-E81-E83)/(1-C104) -> -226.54624 | I104: =H104*C104 -> -9.0618496
E105: =(O93)/(1-C102-C103-C104) -> 0
D107: Base de cálculo reduzida = | E107: Importe | G107: = | H107: =H104/F104*C104 -> -75.515413
E108: 12% x 4%
B130: Participação
C131: R$
B132: Energia | C132: =(SUM(H60:H67)*IF($B$15<$F$2,D170,D142)) -> 327.13969
B133: Distribuição | C133: =(SUM(H60:H67)*IF($B$15<$F$2,F170,F142)) -> 196.40523
B134: Transmissão | C134: =(SUM(H60:H67)*IF($B$15<$F$2,E172,E144)) -> 61.556445
B135: Encargos Setoriais | C135: =(SUM(H60:H67)*IF($B$15<$F$2,G170,G142)) -> 170.87863
B136: Impostos / Tributos | C136: =H80+H82+H84 -> 83.281608
B137: Total | C137: =SUM(C132:C136) -> 839.26161
B139: 2023 | D139: Energia | F139: Distribuição | G139: Setoriais
B140: Grupo B | D140: % | F140: % | G140: %
E141: Transmissão
...

Sheet B2 IRR GD Branca SEM MASSA
B2: B2 TB | E2: Vigência das Tarifas: | F2: ='B1 Res (GD) Branca OK'!F2 -> 46241 | H2: TARIFA BRANCA | M2: Bandeira | N2: R$/kWh | Q2: TUSD FIO B
M3: VERDE | N3: ='[4]B1 (Res) Branca OK'!N3 -> 0
B4: TARIFA | C4: ='Fatura B1 (GD) OK'!C4:E4 -> TARIFA ANTIGA - REH 3370/2024 | F4: ='Fatura B1 (GD) OK'!F4 -> TARIFA NOVA - REH xxxx/2025 | I4: Tarifas Proporcionalizadas | M4: BAM | N4: ='[4]B1 (Res) Branca OK'!N4 -> 0.01885 | Q4: TARIFA | R4: =C4 -> TARIFA ANTIGA - REH 3370/2024 | U4: =F4 -> TARIFA NOVA - REH xxxx/2025 | X4: Tarifas Proporcionalizadas
C5: Tusd | D5: TE | E5: TUSD + TE | F5: Tusd | G5: TE | H5: TUSD + TE | I5: Tusd | J5: TE | K5: TUSD + TE | M5: BVM1 | N5: ='[4]B1 (Res) Branca OK'!N5 -> 0.04463 | R5: Tusd (R$/kWh) | U5: Tusd (R$/kWh) | X5: Tusd (R$/kWh)
B6: B2 Ponta | C6: ='TABELA DE TARIFAS ANTIGAS'!G74/1000 -> 1.06103 | D6: ='TABELA DE TARIFAS ANTIGAS'!H74/1000 -> 0.48448 | E6: =C6+D6 -> 1.54551 | F6: ='TABELA DE TARIFAS NOVAS'!G76/1000 -> 1.12867 | G6: ='TABELA DE TARIFAS NOVAS'!H76/1000 -> 0.51691 | H6: =F6+G6 -> 1.64558 | I6: =((C6*$C$15)+(F6*$D$15))/($D$15+$C$15) -> 1.0086635 | J6: =((D6*$C$15)+(G6*$D$15))/($D$15+$C$15) -> 0.4593729 | K6: =I6+J6 -> 1.4680365 | M6: BVM2 | N6: ='[4]B1 (Res) Branca OK'!N6 -> 0.07877 | Q6: =B6 -> B2 Ponta | R6: ='FIO B'!H16/1000 -> 0.69302445 | U6: ='FIO B'!K16/1000 -> 0.71111541 | X6: =((R6*$C$15)+(U6*$D$15))/($D$15+$C$15) -> 0.67901855
B7: B2 Fora Ponta | C7: ='TABELA DE TARIFAS ANTIGAS'!G76/1000 -> 0.38965 | D7: ='TABELA DE TARIFAS ANTIGAS'!H76/1000 -> 0.30579 | E7: =C7+D7 -> 0.69544 | F7: ='TABELA DE TARIFAS NOVAS'!G78/1000 -> 0.42334 | G7: ='TABELA DE TARIFAS NOVAS'!H78/1000 -> 0.32107 | H7: =F7+G7 -> 0.74441 | I7: =((C7*$C$15)+(F7*$D$15))/($D$15+$C$15) -> 0.36356742 | J7: =((D7*$C$15)+(G7*$D$15))/($D$15+$C$15) -> 0.29396032 | K7: =I7+J7 -> 0.65752774 | M7: Escassez Hídrica | N7: 0.142 | Q7: =B7 -> B2 Fora Ponta | R7: ='FIO B'!H17/1000 -> 0.41581471 | U7: ='FIO B'!K17/1000 -> 0.42666929 | X7: =((R7*$C$15)+(U7*$D$15))/($D$15+$C$15) -> 0.40741117
B8: B2 Interm. | C8: ='TABELA DE TARIFAS ANTIGAS'!G75/1000 -> 0.72534 | D8: ='TABELA DE TARIFAS ANTIGAS'!H75/1000 -> 0.30579 | E8: =C8+D8 -> 1.03113 | F8: ='TABELA DE TARIFAS NOVAS'!G77/1000 -> 0.77601 | G8: ='TABELA DE TARIFAS NOVAS'!H77/1000 -> 0.32107 | H8: =F8+G8 -> 1.09708 | I8: =((C8*$C$15)+(F8*$D$15))/($D$15+$C$15) -> 0.68611161 | J8: =((D8*$C$15)+(G8*$D$15))/($D$15+$C$15) -> 0.29396032 | K8: =I8+J8 -> 0.98007194 | Q8: =B8 -> B2 Interm. | R8: ='FIO B'!H18/1000 -> 0.13860487 | U8: ='FIO B'!K18/1000 -> 0.14222306 | X8: =((R8*$C$15)+(U8*$D$15))/($D$15+$C$15) -> 0.13580369
B9: CDE Escassez Hídrica | C9: 0.00018774721 | D9: -0.0044031307 | E9: =SUM(C9+D9) -> -0.0042153835 | F9: =T13 -> 0.00018418923 | G9: =U13 -> -0.00053182975 | H9: =F9+G9 -> -0.00034764052 | I9: =((C9*$C$15)+(F9*$D$15))/($D$15+$C$15) -> 0.00019050178 | J9: =((D9*$C$15)+(G9*$D$15))/($D$15+$C$15) -> -0.007400267 | K9: =I9+J9 -> -0.0072097652
P10: CUSTO | R10: Part. TUSD (%) | S10: Part. TE (%) | T10: Tusd (R$/kWh) | U10: TE (R$/kWh)
H11: Fatura | L11: Vigência das Tarifas (troca Bandeira): | M11: =EOMONTH(B15,0)+1 -> 46204 | P11: CDE CONTAS
B12: INSTALAÇÃO | C12: 160787403 | H12: =E15 -> 46216 | K12: Altere a bandeira na célula abaixo | P12: CDE COVID | U12: 0
K13: BAM | L13: BAM | P13: CDE ESCASSEZ HÍDRICA | T13: ='B1 Res (GD) Branca OK'!T13 -> 0.00018418923 | U13: ='B1 Res (GD) Branca OK'!U13 -> -0.00053182975
B14: Leitura Anterior | C14: Nº de dias tarifa Anterior | D14: Nº de dias tarifa Nova | E14: Leitura Atual | J14: Leitura Anterior | K14: Nº de dias tarifa Anterior | L14: Nº de dias tarifa Nova | M14: Leitura Atual
B15: 46185 | C15: =IF((F2-B15-1)<0,0,(F2-B15-1)) -> 55 | D15: =E15-F2+1 -> -24 | E15: 46216 | J15: =B15 -> 46185 | K15: =IF((M11-J15-1)<0,0,(M11-J15-1)) -> 18 | L15: =M15-M11+1 -> 13 | M15: =E15 -> 46216
B18: Perc. de Redução da Energia Injetada | E18: TUSD | F18: 1 | G18: TE | H18: 1 | M18: Documento impressão:
B20: Descrição | C20: Unidade | D20: Quantidade | E20: Preço Unit (R$) com tributos | F20: Valor Total (R$) | G20: PIS/COFINS (R$) | H20: Base de Cálculo ICMS (R$) | I20: Alíquota ICMS (%) | J20: ICMS (R$) | K20: Preço Unit (R$) | L20: Tributos | M20: Base de Cálc (R$) | N20: Alíquota (%) | O20: Valor (R$)
B22: TUSD - Ponta | C22: kWh | D22: 1 | E22: =IFERROR((ROUND(D22*K22,2)+ROUND(G22,2)+ROUND(J22,2))/ROUND(D22,4), 0) -> 1.18 | F22: =ROUND(D22*E22,2) -> 1.18 | G22: =((D22*K22)/(1-$N$22-$N$24))*($N$22+$N$24) -> 0.069770384 | H22: =(IF($I$22=12%,(D22*K22)/(1-$N$22-$N$24)/(1-$C$112)/$F$112*$C$112,(D22*K22)/(1-$N$22-$N$24)/(1-$I$22))) -> 0.39263902 | I22: 0.12 | J22: =(H22*$I$22) -> 0.047116683 | K22: =E64 -> 1.06103 | L22: PIS | M22: =D99 -> 1449.1698 | N22: ='B1 Res (GD) Branca OK'!N19 -> 0.011 | O22: =ROUND(M22*N22,2) -> 15.94
B23: TUSD - Intermediário | C23: kWh | D23: 105 | E23: =IFERROR((ROUND(D23*K23,2)+ROUND(G23,2)+ROUND(J23,2))/ROUND(D23,4), 0) -> 0.8052381 | F23: =ROUND(D23*E23,2) -> 84.55 | G23: =((D23*K23)/(1-$N$22-$N$24))*($N$22+$N$24) -> 5.0081159 | H23: =(IF($I$22=12%,(D23*K23)/(1-$N$22-$N$24)/(1-$C$112)/$F$112*$C$112,(D23*K23)/(1-$N$22-$N$24)/(1-$I$22))) -> 28.183617 | I23: =I22 -> 0.12 | J23: =(H23*$I$22) -> 3.382034 | K23: =E66 -> 0.72534 | L23: PIS Inj | M23: =D100 -> 1474.0168 | N23: =N22 -> 0.011 | O23: =ROUND(M23*N23,2) -> 16.21
B24: TUSD - Fora Ponta | C24: kWh | D24: 888 | E24: =IFERROR((ROUND(D24*K24,2)+ROUND(G24,2)+ROUND(J24,2))/ROUND(D24,4), 0) -> 0.43257883 | F24: =ROUND(D24*E24,2) -> 384.13 | G24: =((D24*K24)/(1-$N$22-$N$24))*($N$22+$N$24) -> 22.752603 | H24: =(IF($I$22=12%,(D24*K24)/(1-$N$22-$N$24)/(1-$C$112)/$F$112*$C$112,(D24*K24)/(1-$N$22-$N$24)/(1-$I$22))) -> 128.04229 | I24: =I22 -> 0.12 | J24: =(H24*$I$22) -> 15.365075 | K24: =E65 -> 0.38965 | L24: COFINS | M24: =D101 -> 1449.1698 | N24: ='B1 Res (GD) Branca OK'!N21 -> 0.0507 | O24: =ROUND(M24*N24,2) -> 73.47
B25: TUSD - Consumo Reservado | C25: kWh | D25: 2206 | E25: =IFERROR((ROUND(D25*K25,2)+ROUND(G25,2)+ROUND(J25,2))/ROUND(D25,4), 0) -> 0.17303264 | F25: =ROUND(D25*E25,2) -> 381.71 | G25: =((D25*K25)/(1-$N$22-$N$24))*($N$22+$N$24) -> 22.609118 | H25: =(IF($I$22=12%,(D25*K25)/(1-$N$22-$N$24)/(1-$C$112)/$F$112*$C$112,(D25*K25)/(1-$N$22-$N$24)/(1-$I$22))) -> 127.23482 | I25: =I23 -> 0.12 | J25: =(H25*$I$22) -> 15.268178 | K25: =J65 -> 0.15586 | L25: COFINS Inj | M25: =D102 -> 1474.0168 | N25: =N24 -> 0.0507 | O25: =ROUND(M25*N25,2) -> 74.73
B26: TE - Ponta | C26: kWh | D26: =D22 -> 1 | E26: =IFERROR((ROUND(D26*K26,2)+ROUND(G26,2)+ROUND(J26,2))/ROUND(D26,4), 0) -> 0.53 | F26: =ROUND(D26*E26,2) -> 0.53 | G26: =((D26*K26)/(1-$N$22-$N$24))*($N$22+$N$24) -> 0.031858058 | H26: =(IF($I$22=12%,(D26*K26)/(1-$N$22-$N$24)/(1-$C$112)/$F$112*$C$112,(D26*K26)/(1-$N$22-$N$24)/(1-$I$22))) -> 0.17928405 | J26: =(H26*$I$22) -> 0.021514086 | K26: =F64 -> 0.48448
B27: TE - Intermediário | C27: kWh | D27: =D23 -> 105 | E27: =IFERROR((ROUND(D27*K27,2)+ROUND(G27,2)+ROUND(J27,2))/ROUND(D27,4), 0) -> 0.33952381 | F27: =ROUND(D27*E27,2) -> 35.65 | G27: =((D27*K27)/(1-$N$22-$N$24))*($N$22+$N$24) -> 2.1113295 | H27: =(IF($I$22=12%,(D27*K27)/(1-$N$22-$N$24)/(1-$C$112)/$F$112*$C$112,(D27*K27)/(1-$N$22-$N$24)/(1-$I$22))) -> 11.881694 | J27: =(H27*$I$22) -> 1.4258033 | K27: =F66 -> 0.30579
B28: TE - Fora Ponta | C28: kWh | D28: =D24 -> 888 | E28: =IFERROR((ROUND(D28*K28,2)+ROUND(G28,2)+ROUND(J28,2))/ROUND(D28,4), 0) -> 0.33948198 | F28: =ROUND(D28*E28,2) -> 301.46 | G28: =((D28*K28)/(1-$N$22-$N$24))*($N$22+$N$24) -> 17.855816 | H28: =(IF($I$22=12%,(D28*K28)/(1-$N$22-$N$24)/(1-$C$112)/$F$112*$C$112,(D28*K28)/(1-$N$22-$N$24)/(1-$I$22))) -> 100.48519 | J28: =(H28*$I$22) -> 12.058222 | K28: =F65 -> 0.30579
B29: TE - Consumo Reservado | D29: =D25 -> 2206 | E29: =IFERROR((ROUND(D29*K29,2)+ROUND(G29,2)+ROUND(J29,2))/ROUND(D29,4), 0) -> 0.13578876 | F29: =ROUND(D29*E29,2) -> 299.55 | G29: =((D29*K29)/(1-$N$22-$N$24))*($N$22+$N$24) -> 17.743211 | H29: =(IF($I$22=12%,(D29*K29)/(1-$N$22-$N$24)/(1-$C$112)/$F$112*$C$112,(D29*K29)/(1-$N$22-$N$24)/(1-$I$22))) -> 99.851496 | J29: =(H29*$I$22) -> 11.982179 | K29: =K65 -> 0.122316
B30: Adicional BAM | C30: kWh | D30: =IF($K$13=M4,(($D$22+$D$23+$D$24+$D$25)*($K$15)/($K$15+$L$15)),0)+IF($L$13=M4,(($D$22+$D$23+$D$24+$D$25)*($L$15)/($K$15+$L$15)),0) -> 3200 | E30: =IFERROR((ROUND(D30*K30,2)+ROUND(G30,2)+ROUND(J30,2))/ROUND(D30,4), 0) -> 0.012271875 | F30: =ROUND(D30*E30,2) -> 39.27 | G30: =((D30*K30)/(1-$N$22-$N$24))*($N$22+$N$24) -> 2.3258421 | H30: =(IF($I$22=12%,(D30*K30)/(1-$N$22-$N$24)/(1-$C$112)/$F$112*$C$112,(D30*K30)/(1-$N$22-$N$24)/(1-$I$22))) -> 13.088883 | J30: =ROUND(H30*$I$22,2) -> 1.57 | K30: =J71 -> 0.011053169
B31: Adicional BVM1 | C31: kWh | D31: =IF($K$13=M5,(($D$22+$D$23+$D$24)*($K$15)/($K$15+$L$15)),0)+IF($L$13=M5,(($D$22+$D$23+$D$24)*($L$15)/($K$15+$L$15)),0) -> 0 | E31: =IFERROR((ROUND(D31*K31,2)+ROUND(G31,2)+ROUND(J31,2))/ROUND(D31,4), 0) -> 0 | F31: =ROUND(D31*E31,2) -> 0 | G31: =((D31*K31)/(1-$N$22-$N$24))*($N$22+$N$24) -> 0 | H31: =(IF($I$22=12%,(D31*K31)/(1-$N$22-$N$24)/(1-$C$112)/$F$112*$C$112,(D31*K31)/(1-$N$22-$N$24)/(1-$I$22))) -> 0 | J31: =ROUND(H31*$I$22,2) -> 0 | K31: =J72 -> 0
B32: Adicional BVM2 | C32: kWh | D32: =IF($K$13=M6,(($D$22+$D$23+$D$24)*($K$15)/($K$15+$L$15)),0)+IF($L$13=M6,(($D$22+$D$23+$D$24)*($L$15)/($K$15+$L$15)),0) -> 0 | E32: =IFERROR((ROUND(D32*K32,2)+ROUND(G32,2)+ROUND(J32,2))/ROUND(D32,4), 0) -> 0 | F32: =ROUND(D32*E32,2) -> 0 | G32: =((D32*K32)/(1-$N$22-$N$24))*($N$22+$N$24) -> 0 | H32: =(IF($I$22=12%,(D32*K32)/(1-$N$22-$N$24)/(1-$C$112)/$F$112*$C$112,(D32*K32)/(1-$N$22-$N$24)/(1-$I$22))) -> 0 | J32: =ROUND(H32*$I$22,2) -> 0 | K32: =J73 -> 0 | R32: TUSD Fio B | S32: Receita Fio B
B33: Adicional EH | C33: kWh | D33: =IF($K$13=M7,(($D$22+$D$23+$D$24)*($K$15)/($K$15+$L$15)),0)+IF($L$13=M7,(($D$22+$D$23+$D$24)*($L$15)/($K$15+$L$15)),0) -> 0 | E33: =IFERROR((ROUND(D33*K33,2)+ROUND(G33,2)+ROUND(J33,2))/ROUND(D33,4), 0) -> 0 | F33: =ROUND(D33*E33,2) -> 0 | G33: =((D33*K33)/(1-$N$22-$N$24))*($N$22+$N$24) -> 0 | H33: =(IF($I$22=12%,(D33*K33)/(1-$N$22-$N$24)/(1-$C$112)/$F$112*$C$112,(D33*K33)/(1-$N$22-$N$24)/(1-$I$22))) -> 0 | J33: =ROUND(H33*$I$22,2) -> 0 | K33: =J74 -> 0 | R33: =IF(AND($B$15<$F$2,$E$15<$F$2),R6,IF($B$15<$F$2,X6,U6)) -> 0.69302445 | S33: =D64*R33 -> 0.69302445
R34: =IF(AND($B$15<$F$2,$E$15<$F$2),R7,IF($B$15<$F$2,X7,U7)) -> 0.41581471 | S34: =D65*R34 -> 369.24347
B35: TUSD - Ponta inj | C35: kWh | D35: 0 | E35: =IFERROR((ROUND(D35*K35,2)+ROUND(G35,2)+ROUND(J35,2))/ROUND(D35,4),0) -> 0 | F35: =ROUND(D35*E35,2) -> 0 | G35: =((D35*K35)/(1-$N$23-$N$25))*($N$23+$N$25) -> 0 | H35: 0 | I35: 0 | J35: =H35*$I$26 -> 0 | K35: =K22 -> 1.06103 | R35: =IF(AND($B$15<$F$2,$E$15<$F$2),R8,IF($B$15<$F$2,X8,U8)) -> 0.13860487 | S35: =D66*R35 -> 14.553511
B36: TUSD - Inermediário inj | C36: kWh | D36: 0 | E36: =IFERROR((ROUND(D36*K36,2)+ROUND(G36,2)+ROUND(J36,2))/ROUND(D36,4),0) -> 0 | F36: =ROUND(D36*E36,2) -> 0 | G36: =((D36*K36)/(1-$N$23-$N$25))*($N$23+$N$25) -> 0 | H36: 0 | I36: 0 | J36: =H36*$I$26 -> 0 | K36: =K23 -> 0.72534 | S36: =SUM(S33:S35) -> 384.49
B37: TUSD - Fora Ponta inj | C37: kWh | D37: 1317.2328 | E37: =IFERROR((ROUND(D37*K37,2)+ROUND(G37,2)+ROUND(J37,2))/ROUND(D37,4),0) -> 0.41527208 | F37: =ROUND(D37*E37,2) -> 547.01 | G37: =((D37*K37)/(1-$N$23-$N$25))*($N$23+$N$25) -> 33.750534 | H37: 0 | I37: 0 | J37: =H37*$I$26 -> 0 | K37: =K24 -> 0.38965
B38: TUSD - Consumo inj Reservado
B39: TE - Ponta inj | C39: kWh | D39: =D35 -> 0 | E39: =IFERROR((ROUND(D39*K39,2)+ROUND(G39,2)+ROUND(J39,2))/ROUND(D39,4),0) -> 0 | F39: =ROUND(D39*E39,2) -> 0 | G39: =((D39*K39)/(1-$N$23-$N$25))*($N$23+$N$25) -> 0 | H39: =(IF($I$39=12%,(D39*K39)/(1-$N$22-$N$24)/(1-$C$123)/$F$123*$C$123,(D39*K39)/(1-$N$22-$N$24)/(1-$I$39))) -> 0 | I39: =$I$22 -> 0.12 | J39: =H39*$I$39 -> 0 | K39: =K26 -> 0.48448 | M39: 658.6164
B40: TE - Intermediário inj | C40: kWh | D40: =D36 -> 0 | E40: =IFERROR((ROUND(D40*K40,2)+ROUND(G40,2)+ROUND(J40,2))/ROUND(D40,4),0) -> 0 | F40: =ROUND(D40*E40,2) -> 0 | G40: =((D40*K40)/(1-$N$23-$N$25))*($N$23+$N$25) -> 0 | H40: =(IF($I$39=12%,(D40*K40)/(1-$N$22-$N$24)/(1-$C$123)/$F$123*$C$123,(D40*K40)/(1-$N$22-$N$24)/(1-$I$39))) -> 0 | I40: =$I$22 -> 0.12 | J40: =H40*$I$39 -> 0 | K40: =K27 -> 0.30579 | M40: 786.6036
B41: TE - Fora Ponta inj | C41: kWh | D41: =D37 -> 1317.2328 | E41: =IFERROR((ROUND(D41*K41,2)+ROUND(G41,2)+ROUND(J41,2))/ROUND(D41,4),0) -> 0.33948441 | F41: =ROUND(D41*E41,2) -> 447.18 | G41: =((D41*K41)/(1-$N$23-$N$25))*($N$23+$N$25) -> 26.486785 | H41: =(IF($I$39=12%,(D41*K41)/(1-$N$22-$N$24)/(1-$C$123)/$F$123*$C$123,(D41*K41)/(1-$N$22-$N$24)/(1-$I$39))) -> 149.05673 | I41: =$I$22 -> 0.12 | J41: =H41*$I$39 -> 17.886808 | K41: =K28 -> 0.30579 | M41: =SUM(M39:M40) -> 1445.22
B42: TE - Consumo inj Reservado
B43: Adicional BAM inj | C43: kWh | D43: =IF($K$13=M4,(($D$35+$D$36+$D$37)*($K$15)/($K$15+$L$15)),0)+IF($L$13=M4,(($D$35+$D$36+$D$37)*($L$15)/($K$15+$L$15)),0) -> 1317.2328 | E43: =IFERROR((ROUND(D43*K43,2)+ROUND(G43,2)+ROUND(J43,2))/ROUND(D43,4),0) -> 0.020922649 | F43: =ROUND(D43*E43,2) -> 27.56 | G43: =((D43*K43)/(1-$N$23-$N$25))*($N$23+$N$25) -> 1.6327411 | H43: =(IF($I$39=12%,(D43*K43)/(1-$N$22-$N$24)/(1-$C$123)/$F$123*$C$123,(D43*K43)/(1-$N$22-$N$24)/(1-$I$39))) -> 9.1883953 | J43: =H43*$I$39 -> 1.1026074 | K43: =J87 -> 0.01885
B44: Adicional BVM1 inj | C44: kWh | D44: =IF($K$13=M5,(($D$35+$D$36+$D$37)*($K$15)/($K$15+$L$15)),0)+IF($L$13=M5,(($D$35+$D$36+$D$37)*($L$15)/($K$15+$L$15)),0) -> 0 | E44: =IFERROR((ROUND(D44*K44,2)+ROUND(G44,2)+ROUND(J44,2))/ROUND(D44,4),0) -> 0 | F44: =ROUND(D44*E44,2) -> 0 | G44: =((D44*K44)/(1-$N$23-$N$25))*($N$23+$N$25) -> 0 | H44: =(IF($I$39=12%,(D44*K44)/(1-$N$22-$N$24)/(1-$C$123)/$F$123*$C$123,(D44*K44)/(1-$N$22-$N$24)/(1-$I$39))) -> 0 | J44: =H44*$I$39 -> 0 | K44: =N5 -> 0.04463
B45: Adicional BVM2 inj | C45: kWh | D45: =IF($K$13=M6,(($D$35+$D$36+$D$37)*($K$15)/($K$15+$L$15)),0)+IF($L$13=M6,(($D$35+$D$36+$D$37)*($L$15)/($K$15+$L$15)),0) -> 0 | E45: =IFERROR((ROUND(D45*K45,2)+ROUND(G45,2)+ROUND(J45,2))/ROUND(D45,4),0) -> 0 | F45: =ROUND(D45*E45,2) -> 0 | G45: =((D45*K45)/(1-$N$23-$N$25))*($N$23+$N$25) -> 0 | H45: =(IF($I$39=12%,(D45*K45)/(1-$N$22-$N$24)/(1-$C$123)/$F$123*$C$123,(D45*K45)/(1-$N$22-$N$24)/(1-$I$39))) -> 0 | J45: =H45*$I$39 -> 0 | K45: =N6 -> 0.07877
B46: Adicional EH inj | C46: kWh | D46: =IF($K$13=M7,(($D$35+$D$36+$D$37)*($K$15)/($K$15+$L$15)),0)+IF($L$13=M7,(($D$35+$D$36+$D$37)*($L$15)/($K$15+$L$15)),0) -> 0 | E46: =IFERROR((ROUND(D46*K46,2)+ROUND(G46,2)+ROUND(J46,2))/ROUND(D46,4),0) -> 0 | F46: =ROUND(D46*E46,2) -> 0 | G46: =((D46*K46)/(1-$N$23-$N$25))*($N$23+$N$25) -> 0 | H46: =(IF($I$39=12%,(D46*K46)/(1-$N$22-$N$24)/(1-$C$123)/$F$123*$C$123,(D46*K46)/(1-$N$22-$N$24)/(1-$I$39))) -> 0 | J46: =H46*$I$39 -> 0 | K46: =N7 -> 0.142
B48: Multas | F48: 332.74
B49: Juros | F49: 0.54
B50: Doações | F50: 16.3
B51: CIP
B54: TOTAL | F54: =SUM(F22:F53) -> 2899.36 | G54: =SUM(G22:G53) -> 152.37773 | H54: =SUM(H22:H53) -> 667.58504 | J54: =SUM(J22:J53) -> 80.109539
B56: Informativo Escassez | C56: =D105 -> 2311.2328 | D56: =E105 -> 0.00018774721 | E56: =F105 -> -0.0044031307 | F56: =C56*(D56+E56) -> -9.7427325
G59: desconto: | H59: 0.6
B60: Fatura B1 Residencial TB
D61: Qtde | E61: TUSD | F61: TE | G61: TUSD + TE | H61: R$
B62: Fornecimento de Energia Elétrica | H62: =SUM(H64:H73)+SUM(H99:H103) -> 1600.4987
B64: Consumo Ponta | D64: =D22 -> 1 | E64: =IF(AND($B$15<$F$2,$E$15<$F$2),C6,IF($B$15<$F$2,I6,F6)) -> 1.06103 | F64: =IF(AND($B$15<$F$2,$E$15<$F$2),D6,IF($B$15<$F$2,J6,G6)) -> 0.48448 | G64: =E64+F64 -> 1.54551 | H64: =ROUND((D64*E64),2)+ROUND((D64*F64),2) -> 1.54 | J64: Tarifa reservada com desconto
B65: Consumo Fora Ponta | D65: =D24 -> 888 | E65: =IF(AND($B$15<$F$2,$E$15<$F$2),C7,IF($B$15<$F$2,I7,F7)) -> 0.38965 | F65: =IF(AND($B$15<$F$2,$E$15<$F$2),D7,IF($B$15<$F$2,J7,G7)) -> 0.30579 | G65: =E65+F65 -> 0.69544 | H65: =ROUND((D65*E65),2)+ROUND((D65*F65),2) -> 617.55 | J65: =(($D$67*E67)-($D$67*E67*$H$59))/$D$67 -> 0.15586 | K65: =(($D$67*F67)-($D$67*F67*$H$59))/$D$67 -> 0.122316
B66: Consumo Intemediário | D66: =D23 -> 105 | E66: =IF(AND($B$15<$F$2,$E$15<$F$2),C8,IF($B$15<$F$2,I8,F8)) -> 0.72534 | F66: =IF(AND($B$15<$F$2,$E$15<$F$2),D8,IF($B$15<$F$2,J8,G8)) -> 0.30579 | G66: =E66+F66 -> 1.03113 | H66: =ROUND((D66*E66),2)+ROUND((D66*F66),2) -> 108.27
B67: Energia Fornecida reservado | D67: =D25 -> 2206 | E67: =IF(AND($B$15<$F$2,$E$15<$F$2),C7,IF($B$15<$F$2,I7,F7)) -> 0.38965 | F67: =IF(AND($B$15<$F$2,$E$15<$F$2),D7,IF($B$15<$F$2,J7,G7)) -> 0.30579 | G67: =E67+F67 -> 0.69544 | H67: =ROUND((D67*E67),2)+ROUND((D67*F67),2) -> 1534.14
B68: Desconto reservado | H68: =-H67*$H$59 -> -920.484
B70: Adicional BAM | D70: =IF($K$13=M4,((D64+D65+D66)*(K15)/(K15+L15)),0)+IF($L$13=M4,((D64+D65+D66)*(L15)/(K15+L15)),0) -> 994 | F70: =N4 -> 0.01885 | H70: =ROUND(D70*(E70+F70),2) -> 18.74 | J70: Tarifa reservada bandeira com desconto
B71: Adicional BVM 1 | D71: =IF($K$13=M5,((D64+D65+D66)*(K15)/(K15+L15)),0)+IF($L$13=M5,((D64+D65+D66)*(L15)/(K15+L15)),0) -> 0 | F71: =N5 -> 0.04463 | H71: =ROUND(D71*(E71+F71),2) -> 0 | J71: =IFERROR(((($D$70*$F$70)+($D$75*$F$75))-($D$75*$F$75*$H$59))/($D$70+$D$75), 0) -> 0.011053169
B72: Adicional BVM 2 | D72: =IF($K$13=M6,((D64+D65+D66)*(K15)/(K15+L15)),0)+IF($L$13=M6,((D64+D65+D66)*(L15)/(K15+L15)),0) -> 0 | F72: =N6 -> 0.07877 | H72: =ROUND(D72*(E72+F72),2) -> 0 | J72: =IFERROR((((D71*F71)+(D76*F76))-(D76*F76*$H$59))/(D71+D76), 0) -> 0
B73: Adicional Escassez Hídrica | D73: =IF($K$13=M7,((D64+D65+D66)*(K15)/(K15+L15)),0)+IF($L$13=M7,((D64+D65+D66)*(L15)/(K15+L15)),0) -> 0 | F73: =N7 -> 0.142 | H73: =ROUND(D73*(E73+F73),2) -> 0 | J73: =IFERROR((((D72*F72)+(D77*F77))-(D77*F77*$H$59))/(D72+D77), 0) -> 0
J74: =IFERROR((((D73*F73)+(D78*F78))-(D78*F78*$H$59))/(D73+D78), 0) -> 0
B75: Adicional BAM PT Reservado | D75: =IF($K$13=M4,((D67)*(K15)/(K15+L15)),0)+IF($L$13=M4,((D67)*(L15)/(K15+L15)),0) -> 2206 | F75: =F70 -> 0.01885 | H75: =ROUND(D75*(E75+F75),2) -> 41.58
B76: Adicional BVM 1 PT Reservado | D76: =IF($K$13=M5,((D68)*(K16)/(K16+L16)),0)+IF($L$13=M5,((D68)*(L16)/(K16+L16)),0) -> 0 | F76: =F71 -> 0.04463 | H76: =ROUND(D76*(E76+F76),2) -> 0
B77: Adicional BVM 2 PT Reservado | D77: =IF($K$13=M6,((D69)*(K17)/(K17+L17)),0)+IF($L$13=M6,((D69)*(L17)/(K17+L17)),0) -> 0 | F77: =F72 -> 0.07877 | H77: =ROUND(D77*(E77+F77),2) -> 0
B78: Adicional Esc. Hídrica Reserv | D78: =IF($K$13=M7,((D70)*(K18)/(K18+L18)),0)+IF($L$13=M7,((D70)*(L18)/(K18+L18)),0) -> 0 | F78: =F73 -> 0.142 | H78: =ROUND(D78*(E78+F78),2) -> 0
B80: Energ Injetada P | D80: =D35 -> 0 | E80: =E64*F18 -> 1.06103 | F80: =F64 -> 0.48448 | G80: =E80+F80 -> 1.54551 | H80: =ROUND((D80*E80),2)+ROUND((D80*F80),2) -> 0 | J80: Tarifa reservada inj com desconto
B81: Energ Injetada FP | D81: =D36 -> 0 | E81: =E65*F18 -> 0.38965 | F81: =F65 -> 0.30579 | G81: =E81+F81 -> 0.69544 | H81: =ROUND((D81*E81),2)+ROUND((D81*F81),2) -> 0 | J81: =IFERROR((($D$83*E83)-($D$83*E83*$H$59))/$D$83,0) -> 0 | K81: =IFERROR((($D$83*F83)-($D$83*F83*$H$59))/$D$83,0) -> 0
B82: Energ Injetada Intem | D82: =D37 -> 1317.2328 | E82: =E66*F18 -> 0.72534 | F82: =F66 -> 0.30579 | G82: =E82+F82 -> 1.03113 | H82: =ROUND((D82*E82),2)+ROUND((D82*F82),2) -> 1358.24
B83: Energia Injetada reservado | D83: =D38 -> 0 | E83: =E81 -> 0.38965 | F83: =F81 -> 0.30579 | G83: =E83+F83 -> 0.69544 | H83: =ROUND((D83*E83),2)+ROUND((D83*F83),2) -> 0
B84: Desconto Injetado reservado | H84: =-H83*$H$59 -> 0
B86: Adicional BAM Inj | D86: =IF($K$13=M4,((D80+D81+D82)*(K15)/(K15+L15)),0)+IF($L$13=M4,((D80+D81+D82)*(L15)/(K15+L15)),0) -> 1317.2328 | F86: =N4 -> 0.01885 | H86: =ROUND(D86*(E86+F86),2) -> 24.83 | J86: Tarifa reservada bandeira com desconto
B87: Adicional BVM 1 Inj | D87: =IF($K$13=M5,((D81+D82+D85)*(K15)/(K15+L15)),0)+IF($L$13=M5,((D81+D82+D85)*(L15)/(K15+L15)),0) -> 0 | F87: =N14 -> 0 | H87: =ROUND(D87*(E87+F87),2) -> 0 | J87: =IFERROR(((($D$86*$F$86)+($D$91*$F$91))-($D$91*$F$91*$H$59))/($D$86+$D$91), 0) -> 0.01885
B88: Adicional BVM 2 Inj | D88: =IF($K$13=M6,((D82+D85+D86)*(K15)/(K15+L15)),0)+IF($L$13=M6,((D82+D85+D86)*(L15)/(K15+L15)),0) -> 0 | F88: =N15 -> 0 | H88: =ROUND(D88*(E88+F88),2) -> 0
B89: Adicional Escassez Hídrica Inj | D89: =IF($K$13=M7,((D85+D86+D87)*(K15)/(K15+L15)),0)+IF($L$13=M7,((D85+D86+D87)*(L15)/(K15+L15)),0) -> 0 | F89: =N16 -> 0 | H89: =ROUND(D89*(E89+F89),2) -> 0
B91: Adicional BAM PT Reservado | D91: =IF($K$13=M18,((D83)*(K29)/(K29+L29)),0)+IF($L$13=M18,((D83)*(L29)/(K29+L29)),0) -> 0 | F91: =F86 -> 0.01885 | H91: =ROUND(D91*(E91+F91),2) -> 0
B92: Adicional BVM 1 PT Reservado | D92: =IF($K$13=M19,((D83)*(K30)/(K30+L30)),0)+IF($L$13=M19,((D83)*(L30)/(K30+L30)),0) -> 0 | F92: =F87 -> 0 | H92: =ROUND(D92*(E92+F92),2) -> 0
B93: Adicional BVM 2 PT Reservado | D93: =IF($K$13=M20,((D83)*(K31)/(K31+L31)),0)+IF($L$13=M20,((D83)*(L31)/(K31+L31)),0) -> 0 | F93: =F88 -> 0 | H93: =ROUND(D93*(E93+F93),2) -> 0
B94: Adicional Esc. Hídrica Reserv | D94: =IF($K$13=M21,((D83)*(K32)/(K32+L32)),0)+IF($L$13=M21,((D83)*(L32)/(K32+L32)),0) -> 0 | F94: =F89 -> 0 | H94: =ROUND(D94*(E94+F94),2) -> 0
D98: Base de Cálculo
B99: PIS | D99: =(SUM(H64:H73)/(1-E99-E101)) -> 1449.1698 | E99: =N22 -> 0.011 | H99: =D99*E99 -> 15.940868
B100: PIS INJ | D100: =(SUM(H80:H89)/(1-E100-E102)) -> 1474.0168 | E100: =E99 -> 0.011 | H100: =D100*E100 -> 16.214185
B101: COFINS | D101: =D99 -> 1449.1698 | E101: =N24 -> 0.0507 | H101: =D101*E101 -> 73.472908
B102: COFINS INJ | D102: =D100 -> 1474.0168 | E102: =E101 -> 0.0507 | H102: =D102*E102 -> 74.732654
B103: ICMS | D103: =IF((E103=17%),(D99/(1-(E103))),D112) -> 503.18395 | E103: 0.12 | H103: =D103*E103 -> 60.382074
B104: ICMS INJ | D104: =D123 -> 158.24519 | E104: 0.12 | H104: =D104*E104 -> 18.989423
B105: Informativo Escassez Hídrica | D105: =SUM(D64:D66)+SUM(D80:D82) -> 2311.2328 | E105: =IF(AND($B$15<$F$2,$E$15<$F$2),C9,IF($B$15<$F$2,I9,F9)) -> 0.00018774721 | F105: =IF(AND($B$15<$F$2,$E$15<$F$2),D9,IF($B$15<$F$2,J9,G9)) -> -0.0044031307 | H105: =D105*(E105+F105) -> -9.7427325
B107: Se for base reduzida: (célula E33 = 12%)
A108: FORNECIDA
D109: Com tributos
B110: PIS | C110: =E99 -> 0.011 | D110: =(SUM(H64:H73)/(1-E99-E101)) -> 1449.1698 | E110: x | F110: =C110 -> 0.011 | G110: =D110*F110 -> 15.940868
B111: COFINS | C111: =E101 -> 0.0507 | D111: =D110 -> 1449.1698 | E111: x | F111: =C111 -> 0.0507 | G111: =D111*F111 -> 73.472908
A112: Rural c/ incrição | B112: ICMS | C112: 0.04 | D112: =H112/F112*C112 -> 503.18395 | E112: x | F112: 0.12 | G112: =D112*F112 -> 60.382074 | H112: =((SUM(H64:H73))/(1-F110-F111)/(1-(C112))) -> 1509.5518 | I112: =H112*C112 -> 60.382074
E113: =(O101)/(1-C110-C111-C112) -> 0
D115: Base de cálculo reduzida = | E115: Importe | G115: = | H115: =H112/F112*C112 -> 503.18395
E116: 12% x 4%
A118: INJETADA
B119: Se for base reduzida: (célula E33 = 12%)
D120: Com tributos
B121: PIS | C121: =E100 -> 0.011 | D121: =SUM(H80:H89)/(1-C121-C122) -> 1474.0168 | E121: x | F121: =C121 -> 0.011 | G121: =D121*F121 -> 16.214185
B122: COFINS | C122: =E102 -> 0.0507 | D122: =D121 -> 1474.0168 | E122: x | F122: =C122 -> 0.0507 | G122: =D122*F122 -> 74.732654
...

Sheet V4 MMGD GDII
B2: A4 Verde | C2: MMGD | E2: Vigência das Tarifas: | F2: ='[5]A2 Azul'!F2 -> 45145 | I2: OK | M2: Bandeira | N2: R$/kWh | Q2: TUSD FIO B
M3: VERDE | N3: =[5]BANDEIRA!$D$4 -> 0
B4: TARIFA | C4: ='[5]A2 Azul'!C4:E4 -> TARIFA ANTIGA - REH 3091/2022 | F4: ='[5]A2 Azul'!F4:H4 -> TARIFA NOVA - REH 3241/2023 | I4: Tarifas Proporcionalizadas | M4: BAM | N4: =[5]BANDEIRA!$D$5 -> 0.02989 | Q4: TARIFA | R4: =C4 -> TARIFA ANTIGA - REH 3091/2022 | U4: =F4 -> TARIFA NOVA - REH 3241/2023 | X4: Tarifas Proporcionalizadas
C5: Tusd (R$/kW) | D5: Tusd (R$/kWh) | E5: TE (R$/kWh) | F5: Tusd (R$/kW) | G5: Tusd (R$/kWh) | H5: TE (R$/kWh) | I5: Tusd (R$/kW) | J5: Tusd (R$/kWh) | K5: TE (R$/kWh) | M5: BVM1 | N5: =[5]BANDEIRA!$D$6 -> 0.065 | R5: Tusd (R$/kW) | S5: Tusd (R$/kW) | U5: Tusd (R$/kW) | V5: Tusd (R$/kW) | X5: Tusd (R$/kW) | Y5: Tusd (R$/kW)
B6: A4 Verde P | C6: ='[5]TABELA DE TARIFAS ANTIGAS'!E52 -> 30.44 | D6: ='[5]TABELA DE TARIFAS ANTIGAS'!F53/1000 -> 1.24002 | E6: ='[5]TABELA DE TARIFAS ANTIGAS'!G53/1000 -> 0.4226 | F6: ='[5]TABELA DE TARIFAS NOVAS'!E52 -> 31.53 | G6: ='[5]TABELA DE TARIFAS NOVAS'!F53/1000 -> 1.26783 | H6: ='[5]TABELA DE TARIFAS NOVAS'!G53/1000 -> 0.45803 | I6: =((C6*$C$17)+(F6*$D$17))/($D$17+$C$17) -> 31.319032 | J6: =((D6*$C$17)+(G6*$D$17))/($D$17+$C$17) -> 1.2624474 | K6: =((E6*$C$17)+(H6*$D$17))/($D$17+$C$17) -> 0.45117258 | M6: BVM2 | N6: =[5]BANDEIRA!$D$7 -> 0.09795 | Q6: =B6 -> A4 Verde P | R6: ='[5]Grupo A_FIO B'!F49 -> 26.16 | S6: ='[5]Grupo A_FIO B'!G50/1000 -> 0.93588 | U6: ='[5]Grupo A_FIO B'!I49 -> 24.04 | V6: ='[5]Grupo A_FIO B'!J50/1000 -> 0.86024 | X6: =((R6*$C$17)+(U6*$D$17))/($D$17+$C$17) -> 24.450323 | Y6: =((S6*$C$17)+(V6*$D$17))/($D$17+$C$17) -> 0.87488
B7: A4 Verde FP | D7: ='[5]TABELA DE TARIFAS ANTIGAS'!F54/1000 -> 0.13433 | E7: ='[5]TABELA DE TARIFAS ANTIGAS'!G54/1000 -> 0.2638 | G7: ='[5]TABELA DE TARIFAS NOVAS'!F54/1000 -> 0.12117 | H7: ='[5]TABELA DE TARIFAS NOVAS'!G54/1000 -> 0.29041 | J7: =((D7*$C$17)+(G7*$D$17))/($D$17+$C$17) -> 0.1237171 | K7: =((E7*$C$17)+(H7*$D$17))/($D$17+$C$17) -> 0.28525968 | M7: Escassez Hídrica | N7: =[5]BANDEIRA!$D$8 -> 0.142 | Q7: =B7 -> A4 Verde FP
B8: B1 | D8: ='[5]TABELA DE TARIFAS ANTIGAS'!G71/1000 -> 0.39681 | E8: ='[5]TABELA DE TARIFAS ANTIGAS'!H71/1000 -> 0.27703 | G8: ='[5]TABELA DE TARIFAS NOVAS'!G71/1000 -> 0.39253 | H8: ='[5]TABELA DE TARIFAS NOVAS'!H71/1000 -> 0.3056 | J8: =((D8*$C$17)+(G8*$D$17))/($D$17+$C$17) -> 0.39335839 | K8: =((E8*$C$17)+(H8*$D$17))/($D$17+$C$17) -> 0.30007032
B9: TE SCEE P | H9: =H6*15% -> 0.0687045 | K9: =((D9*$C$17)+(H9*$D$17))/($D$17+$C$17) -> 0.055406855
B10: TE SCEE FP | H10: =H7*15% -> 0.0435615 | K10: =((D10*$C$17)+(H10*$D$17))/($D$17+$C$17) -> 0.035130242
B12: MMGD
H13: Fatura | L13: Vigência das Tarifas (troca Bandeira): | M13: =EOMONTH(B17,0)+1 -> 45139
B14: INSTALAÇÃO | C14: 1175387 | H14: =E17 -> 45169 | K14: Altere a bandeira na célula abaixo
K15: VERDE | L15: VERDE
B16: Leitura Anterior | C16: Nº de dias tarifa Anterior | D16: Nº de dias tarifa Nova | E16: Leitura Atual | J16: Leitura Anterior | K16: Nº de dias tarifa Anterior | L16: Nº de dias tarifa Nova | M16: Leitura Atual
B17: 45138 | C17: =IF((F2-B17-1)<0,0,(F2-B17-1)) -> 6 | D17: =E17-F2+1 -> 25 | E17: 45169 | J17: =B17 -> 45138 | K17: =IF((M13-J17-1)<0,0,(M13-J17-1)) -> 0 | L17: =M17-M13+1 -> 31 | M17: =E17 -> 45169
B19: Perc. de Redução da Energia Injetada | E19: TUSD P | F19: 0.8868 | G19: TE P | H19: 1
E20: TUSD FP | F20: 1 | G20: TE FP | H20: 1
B22: Fatura A4 Verde - MMGD | J22: Documento impressão:
D23: Qtde | E23: TUSD | F23: TE | G23: TUSD + TE | H23: R$
J24: TUSD Fio B | K24: Receita Fio B
B25: Consumo Ponta | D25: 1290.8358 | E25: =IF(AND($B$17<$F$2,$E$17<$F$2),D6,IF($B$17<$F$2,J6,G6)) -> 1.2624474 | F25: =IF(AND($B$17<$F$2,$E$17<$F$2),E6,IF($B$17<$F$2,K6,H6)) -> 0.45117258 | G25: =E25+F25 -> 1.71362 | H25: =ROUND((D25*E25),2)+ROUND((D25*F25),2) -> 2212 | J25: =IF(AND($B$17<$F$2,$E$17<$F$2),S6,IF($B$17<$F$2,Y6,V6)) -> 0.87488 | K25: =D25*J25 -> 1129.3264
B26: Consumo Fora Ponta | D26: 12358.327 | E26: =IF(AND($B$17<$F$2,$E$17<$F$2),D7,IF($B$17<$F$2,J7,G7)) -> 0.1237171 | F26: =IF(AND($B$17<$F$2,$E$17<$F$2),E7,IF($B$17<$F$2,K7,H7)) -> 0.28525968 | G26: =E26+F26 -> 0.40897677 | H26: =ROUND((D26*E26),2)+ROUND((D26*F26),2) -> 5054.27
B28: Adicional BAM | D28: =IF($K$15=$M$4,((D25+D26)*(K17)/(K17+L17)),0)+IF($L$15=$M$4,((D25+D26)*(L17)/(K17+L17)),0) -> 0 | F28: =N4 -> 0.02989 | H28: =ROUND(D28*(E28+F28),2) -> 0
B29: Adicional BVM 1 | D29: =IF($K$15=$M$5,((D25+D26)*(K17)/(K17+L17)),0)+IF($L$15=$M$5,((D25+D26)*(L17)/(K17+L17)),0) -> 0 | F29: =N5 -> 0.065 | H29: =ROUND(D29*(E29+F29),2) -> 0
B30: Adicional BVM 2 | D30: =IF($K$15=$M$6,((D25+D26)*(K17)/(K17+L17)),0)+IF($L$15=$M$6,((D25+D26)*(L17)/(K17+L17)),0) -> 0 | F30: =N6 -> 0.09795 | H30: =ROUND(D30*(E30+F30),2) -> 0
B31: Adic. Escassez Hídrica | D31: =IF($K$15=$M$7,((D25+D26)*(K17)/(K17+L17)),0)+IF($L$15=$M$7,((D25+D26)*(L17)/(K17+L17)),0) -> 0 | F31: =N7 -> 0.142 | H31: =ROUND(D31*(E31+F31),2) -> 0
B33: Energ Injetada Ponta | D33: 0 | E33: =-E25 -> -1.2624474 | F33: =-F25 -> -0.45117258 | H33: =ROUND(D33*(E33+F33),2) -> 0
B34: Energ Injetada Fora Ponta | D34: -1422.72 | E34: =-E26 -> -0.1237171 | F34: =-F26 -> -0.28525968 | H34: =ROUND(D34*(E34+F34),2) -> 581.86
B36: Adicional BAM | D36: =IF($K$15=$M$4,((D33+D34)*(K17)/(K17+L17)),0)+IF($L$15=$M$4,((D33+D34)*(L17)/(K17+L17)),0) -> 0 | F36: =-F28 -> -0.02989 | H36: =ROUND(D36*(E36+F36),2) -> 0
B37: Adicional BVM 1 | D37: =IF($K$15=$M$5,((D33+D34)*(K17)/(K17+L17)),0)+IF($L$15=$M$5,((D33+D34)*(L17)/(K17+L17)),0) -> 0 | F37: =-F29 -> -0.065 | H37: =ROUND(D37*(E37+F37),2) -> 0
B38: Adicional BVM 2 | D38: =IF($K$15=$M$6,((D33+D34)*(K17)/(K17+L17)),0)+IF($L$15=$M$6,((D33+D34)*(L17)/(K17+L17)),0) -> 0 | F38: =-F30 -> -0.09795 | H38: =ROUND(D38*(E38+F38),2) -> 0
B39: Adic. Escassez Hídrica | D39: =IF($K$15=$M$7,((D33+D34)*(K17)/(K17+L17)),0)+IF($L$15=$M$7,((D33+D34)*(L17)/(K17+L17)),0) -> 0 | F39: =-F31 -> -0.142 | H39: =ROUND(D39*(E39+F39),2) -> 0
J40: TUSD Fio B | K40: Receita Fio B | L40: EUSD B
B41: Demanda | D41: 100.86 | E41: =IF(AND($B$17<$F$2,$E$17<$F$2),C6,IF($B$17<$F$2,I6,F6)) -> 31.319032 | H41: =ROUND(D41*(E41+F41),2) -> 3158.84 | J41: =IF(AND($B$17<$F$2,$E$17<$F$2),R6,IF($B$17<$F$2,X6,U6)) -> 24.450323 | K41: =D41*J41 -> 2466.0595 | L41: =K41+K44+K47 -> 2567.2839
B44: Demanda não utilizada | D44: 4.14 | E44: =E41 -> 31.319032 | H44: =ROUND(D44*(E44+F44),2) -> 129.66 | J44: =J41 -> 24.450323 | K44: =D44*J44 -> 101.22434
B47: Ultrap Demanda | D47: 0 | E47: =E41*2 -> 62.638065 | H47: =ROUND(D47*(E47+F47),2) -> 0
B49: Energia Comp. P SCEE | D49: =-D33 -> 0 | E49: =E25 -> 1.2624474 | F49: =IF(AND($B$17<$F$2,$E$17<$F$2),D9,IF($B$17<$F$2,K9,H9)) -> 0.055406855 | G49: =E49+F49 -> 1.3178543 | H49: =ROUND(D49*(E49+F49),2) -> 0
B50: Energia Comp. FP SCEE | D50: =-D34 -> 1422.72 | E50: =E26 -> 0.1237171 | F50: =IF(AND($B$17<$F$2,$E$17<$F$2),D10,IF($B$17<$F$2,K10,H10)) -> 0.035130242 | G50: =E50+F50 -> 0.15884734 | H50: =ROUND(D50*(E50+F50),2) -> 226
B52: Des Energ. Comp. P SCEE | D52: =-D49 -> 0 | E52: =E49*F19 -> 1.1195384 | F52: =F49*H19 -> 0.055406855 | G52: =E52+F52 -> 1.1749452 | H52: =ROUND(D52*(E52+F52),2) -> 0
B53: Des Energ. Comp. FP SCEE | D53: =-D50 -> -1422.72 | E53: =E50*F20 -> 0.1237171 | F53: =F50*H20 -> 0.035130242 | G53: =E53+F53 -> 0.15884734 | H53: =ROUND(D53*(E53+F53),2) -> -226
B55: ERE | D55: 27.675 | F55: =IF(AND($B$17<$F$2,$E$17<$F$2),E8,IF($B$17<$F$2,K8,H8)) -> 0.30007032 | H55: =ROUND(D55*(E55+F55),2) -> 8.3
B56: DRE | D56: 0 | E56: =E42 -> 0 | H56: =ROUND(D56*(E56+F56),2) -> 0
D58: Base de Cálculo
B59: PIS | D59: =(SUM(H25:H31)+H41+H47+H55+H56)/(1-E59-E62) -> 10922.749 | E59: 0.008 | H59: =D59*E59 -> 87.381993
B60: PIS Injetado | D60: =(SUM(H33:H39,H49:H53))/(1-E59-E62) -> 609.14992 | E60: =E59 -> 0.008 | H60: =D60*E60 -> 4.8731993
B61: PIS não utilizada | D61: =(H44)/(1-E61-E64) -> 135.74121 | E61: =E59 -> 0.008 | H61: =D61*E61 -> 1.0859296
B62: COFINS | D62: =D59 -> 10922.749 | E62: 0.0368 | H62: =D62*E62 -> 401.95717
B63: COFINS Injetado | D63: =D60 -> 609.14992 | E63: =E62 -> 0.0368 | H63: =D63*E63 -> 22.416717
B64: COFINS não utilizada | D64: =D61 -> 135.74121 | E64: =E62 -> 0.0368 | H64: =D64*E64 -> 4.9952764
B65: ICMS | D65: =D59/(1-E65) -> 13159.939 | E65: 0.17 | H65: =D65*E65 -> 2237.1896
B66: ICMS Injetado TE | D66: =((D33*F33)+(D34*F34)+SUM(H36:H39)+(D49*F49)+(D50*F50)+(D52*F52)+(D53*F53))/(1-E60-E63)/(1-E66) -> 511.9027 | E66: =E65 -> 0.17 | H66: =D66*E66 -> 87.023458

Sheet A4 MMGD GDII
B2: A4 AZUL | C2: MMGD | E2: Vigência das Tarifas: | F2: ='[5]A2 Azul'!F2 -> 45145 | I2: OK | M2: Bandeira | N2: R$/kWh | Q2: TUSD FIO B
M3: VERDE | N3: =[5]BANDEIRA!$D$4 -> 0
B4: TARIFA | C4: ='[5]A2 Azul'!C4:E4 -> TARIFA ANTIGA - REH 3091/2022 | F4: ='[5]A2 Azul'!F4:H4 -> TARIFA NOVA - REH 3241/2023 | I4: Tarifas Proporcionalizadas | M4: BAM | N4: =[5]BANDEIRA!$D$5 -> 0.02989 | Q4: TARIFA | R4: =C4 -> TARIFA ANTIGA - REH 3091/2022 | U4: =F4 -> TARIFA NOVA - REH 3241/2023 | X4: Tarifas Proporcionalizadas
C5: Tusd (R$/kW) | D5: Tusd (R$/kWh) | E5: TE (R$/kWh) | F5: Tusd (R$/kW) | G5: Tusd (R$/kWh) | H5: TE (R$/kWh) | I5: Tusd (R$/kW) | J5: Tusd (R$/kWh) | K5: TE (R$/kWh) | M5: BVM1 | N5: =[5]BANDEIRA!$D$6 -> 0.065 | R5: Tusd (R$/kW) | S5: Tusd (R$/kW) | U5: Tusd (R$/kW) | V5: Tusd (R$/kW) | X5: Tusd (R$/kW) | Y5: Tusd (R$/kW)
B6: A4 Azul P | C6: ='[5]A4 Azul'!C6 -> 45.59 | D6: ='[5]A4 Azul'!D6 -> 0.13433 | E6: ='[5]A4 Azul'!E6 -> 0.4226 | F6: ='[5]A4 Azul'!F6 -> 47.23 | G6: ='[5]A4 Azul'!G6 -> 0.12117 | H6: ='[5]A4 Azul'!H6 -> 0.45803 | I6: =((C6*$C$17)+(F6*$D$17))/($D$17+$C$17) -> 46.912581 | J6: =((D6*$C$17)+(G6*$D$17))/($D$17+$C$17) -> 0.1237171 | K6: =((E6*$C$17)+(H6*$D$17))/($D$17+$C$17) -> 0.45117258 | M6: BVM2 | N6: =[5]BANDEIRA!$D$7 -> 0.09795 | Q6: =B6 -> A4 Azul P | R6: ='[5]Grupo A_FIO B'!F49 -> 26.16 | S6: ='[5]Grupo A_FIO B'!G50/1000 -> 0.93588 | U6: ='[5]Grupo A_FIO B'!I49 -> 24.04 | V6: ='[5]Grupo A_FIO B'!J50/1000 -> 0.86024 | X6: =((R6*$C$17)+(U6*$D$17))/($D$17+$C$17) -> 24.450323 | Y6: =((S6*$C$17)+(V6*$D$17))/($D$17+$C$17) -> 0.87488
B7: A4 Azul FP | C7: ='[5]A4 Azul'!C7 -> 30.44 | D7: ='[5]A4 Azul'!D7 -> 0.13433 | E7: ='[5]A4 Azul'!E7 -> 0.2638 | F7: ='[5]A4 Azul'!F7 -> 31.53 | G7: ='[5]A4 Azul'!G7 -> 0.12117 | H7: ='[5]A4 Azul'!H7 -> 0.29041 | I7: =((C7*$C$17)+(F7*$D$17))/($D$17+$C$17) -> 31.319032 | J7: =((D7*$C$17)+(G7*$D$17))/($D$17+$C$17) -> 0.1237171 | K7: =((E7*$C$17)+(H7*$D$17))/($D$17+$C$17) -> 0.28525968 | M7: Escassez Hídrica | N7: =[5]BANDEIRA!$D$8 -> 0.142 | Q7: =B7 -> A4 Azul FP
B8: B1 | D8: ='[5]TABELA DE TARIFAS ANTIGAS'!G71/1000 -> 0.39681 | E8: ='[5]TABELA DE TARIFAS ANTIGAS'!H71/1000 -> 0.27703 | G8: ='[5]TABELA DE TARIFAS NOVAS'!G71/1000 -> 0.39253 | H8: ='[5]TABELA DE TARIFAS NOVAS'!H71/1000 -> 0.3056 | J8: =((D8*$C$17)+(G8*$D$17))/($D$17+$C$17) -> 0.39335839 | K8: =((E8*$C$17)+(H8*$D$17))/($D$17+$C$17) -> 0.30007032
B9: TE SCEE P | H9: =H6*15% -> 0.0687045 | K9: =((D9*$C$17)+(H9*$D$17))/($D$17+$C$17) -> 0.055406855
B10: TE SCEE FP | H10: =H7*15% -> 0.0435615 | K10: =((D10*$C$17)+(H10*$D$17))/($D$17+$C$17) -> 0.035130242
B12: MMGD
H13: Fatura | L13: Vigência das Tarifas (troca Bandeira): | M13: =EOMONTH(B17,0)+1 -> 45139
B14: INSTALAÇÃO | H14: =E17 -> 45169 | K14: Altere a bandeira na célula abaixo
K15: VERDE | L15: VERDE
B16: Leitura Anterior | C16: Nº de dias tarifa Anterior | D16: Nº de dias tarifa Nova | E16: Leitura Atual | J16: Leitura Anterior | K16: Nº de dias tarifa Anterior | L16: Nº de dias tarifa Nova | M16: Leitura Atual
B17: 45138 | C17: =IF((F2-B17-1)<0,0,(F2-B17-1)) -> 6 | D17: =E17-F2+1 -> 25 | E17: 45169 | J17: =B17 -> 45138 | K17: =IF((M13-J17-1)<0,0,(M13-J17-1)) -> 0 | L17: =M17-M13+1 -> 31 | M17: =E17 -> 45169
B19: Perc. de Redução da Energia Injetada | E19: TUSD P | F19: 1 | G19: TE P | H19: 1
E20: TUSD FP | F20: 1 | G20: TE FP | H20: 1
B22: Fatura A4 Azul - MMGD | J22: Documento impressão:
D23: Qtde | E23: TUSD | F23: TE | G23: TUSD + TE | H23: R$
J24: TUSD Fio B | K24: Receita Fio B
B25: Consumo Ponta | D25: 1290.8358 | E25: =IF(AND($B$17<$F$2,$E$17<$F$2),D6,IF($B$17<$F$2,J6,G6)) -> 0.1237171 | F25: =IF(AND($B$17<$F$2,$E$17<$F$2),E6,IF($B$17<$F$2,K6,H6)) -> 0.45117258 | G25: =E25+F25 -> 0.57488968 | H25: =ROUND((D25*E25),2)+ROUND((D25*F25),2) -> 742.09 | J25: =IF(AND($B$17<$F$2,$E$17<$F$2),S6,IF($B$17<$F$2,Y6,V6)) -> 0.87488 | K25: =D25*J25 -> 1129.3264
B26: Consumo Fora Ponta | D26: 12358.327 | E26: =IF(AND($B$17<$F$2,$E$17<$F$2),D7,IF($B$17<$F$2,J7,G7)) -> 0.1237171 | F26: =IF(AND($B$17<$F$2,$E$17<$F$2),E7,IF($B$17<$F$2,K7,H7)) -> 0.28525968 | G26: =E26+F26 -> 0.40897677 | H26: =ROUND((D26*E26),2)+ROUND((D26*F26),2) -> 5054.27
B28: Adicional BAM | D28: =IF($K$15=$M$4,((D25+D26)*(K17)/(K17+L17)),0)+IF($L$15=$M$4,((D25+D26)*(L17)/(K17+L17)),0) -> 0 | F28: =N4 -> 0.02989 | H28: =ROUND(D28*(E28+F28),2) -> 0
B29: Adicional BVM 1 | D29: =IF($K$15=$M$5,((D25+D26)*(K17)/(K17+L17)),0)+IF($L$15=$M$5,((D25+D26)*(L17)/(K17+L17)),0) -> 0 | F29: =N5 -> 0.065 | H29: =ROUND(D29*(E29+F29),2) -> 0
B30: Adicional BVM 2 | D30: =IF($K$15=$M$6,((D25+D26)*(K17)/(K17+L17)),0)+IF($L$15=$M$6,((D25+D26)*(L17)/(K17+L17)),0) -> 0 | F30: =N6 -> 0.09795 | H30: =ROUND(D30*(E30+F30),2) -> 0
B31: Adic. Escassez Hídrica | D31: =IF($K$15=$M$7,((D25+D26)*(K17)/(K17+L17)),0)+IF($L$15=$M$7,((D25+D26)*(L17)/(K17+L17)),0) -> 0 | F31: =N7 -> 0.142 | H31: =ROUND(D31*(E31+F31),2) -> 0
B33: Energ Injetada Ponta | D33: 0 | E33: =-E25 -> -0.1237171 | F33: =-F25 -> -0.45117258 | H33: =ROUND(D33*(E33+F33),2) -> 0
B34: Energ Injetada Fora Ponta | D34: 1422.72 | E34: =-E26 -> -0.1237171 | F34: =-F26 -> -0.28525968 | H34: =ROUND(D34*(E34+F34),2) -> -581.86
B36: Adicional BAM | D36: =IF($K$15=$M$4,((D33+D34)*(K17)/(K17+L17)),0)+IF($L$15=$M$4,((D33+D34)*(L17)/(K17+L17)),0) -> 0 | F36: =-F28 -> -0.02989 | H36: =ROUND(D36*(E36+F36),2) -> 0
B37: Adicional BVM 1 | D37: =IF($K$15=$M$5,((D33+D34)*(K17)/(K17+L17)),0)+IF($L$15=$M$5,((D33+D34)*(L17)/(K17+L17)),0) -> 0 | F37: =-F29 -> -0.065 | H37: =ROUND(D37*(E37+F37),2) -> 0
B38: Adicional BVM 2 | D38: =IF($K$15=$M$6,((D33+D34)*(K17)/(K17+L17)),0)+IF($L$15=$M$6,((D33+D34)*(L17)/(K17+L17)),0) -> 0 | F38: =-F30 -> -0.09795 | H38: =ROUND(D38*(E38+F38),2) -> 0
B39: Adic. Escassez Hídrica | D39: =IF($K$15=$M$7,((D33+D34)*(K17)/(K17+L17)),0)+IF($L$15=$M$7,((D33+D34)*(L17)/(K17+L17)),0) -> 0 | F39: =-F31 -> -0.142 | H39: =ROUND(D39*(E39+F39),2) -> 0
J40: TUSD Fio B | K40: Receita Fio B | L40: EUSD B
B41: Demanda Ponta | D41: 100.86 | E41: =IF(AND($B$17<$F$2,$E$17<$F$2),C6,IF($B$17<$F$2,I6,F6)) -> 46.912581 | H41: =ROUND(D41*(E41+F41),2) -> 4731.6 | J41: =IF(AND($B$17<$F$2,$E$17<$F$2),R6,IF($B$17<$F$2,X6,U6)) -> 24.450323 | K41: =D41*J41 -> 2466.0595 | L41: =K41+K44+K47 -> 2567.2839
B42: Demanda Fora Ponta | D42: 100.86 | E42: =IF(AND($B$17<$F$2,$E$17<$F$2),C7,IF($B$17<$F$2,I7,F7)) -> 31.319032 | H42: =ROUND(D42*(E42+F42),2) -> 3158.84
B44: Demanda não utilizada P | D44: 4.14 | E44: =E41 -> 46.912581 | H44: =ROUND(D44*(E44+F44),2) -> 194.22 | J44: =J41 -> 24.450323 | K44: =D44*J44 -> 101.22434
B45: Demanda não utilizada FP | D45: 4.14 | E45: =E42 -> 31.319032 | H45: =ROUND(D45*(E45+F45),2) -> 129.66
B47: Ultrap Demanda P | D47: 0 | E47: =E41*2 -> 93.825161 | H47: =ROUND(D47*(E47+F47),2) -> 0
B48: Ultrap Demanda FP | D48: 0 | E48: =E42*2 -> 62.638065 | H48: =ROUND(D48*(E48+F48),2) -> 0
B50: Energia Comp. P SCEE | D50: =-D33 -> 0 | E50: =E25 -> 0.1237171 | F50: =IF(AND($B$17<$F$2,$E$17<$F$2),D9,IF($B$17<$F$2,K9,H9)) -> 0.055406855 | G50: =E50+F50 -> 0.17912395 | H50: =ROUND(D50*(E50+F50),2) -> 0
B51: Energia Comp. FP SCEE | D51: =-D34 -> -1422.72 | E51: =E26 -> 0.1237171 | F51: =IF(AND($B$17<$F$2,$E$17<$F$2),D10,IF($B$17<$F$2,K10,H10)) -> 0.035130242 | G51: =E51+F51 -> 0.15884734 | H51: =ROUND(D51*(E51+F51),2) -> -226
B53: Des Energ. Comp. P SCEE | D53: =-D50 -> 0 | E53: =E50*F19 -> 0.1237171 | F53: =F50*H19 -> 0.055406855 | G53: =E53+F53 -> 0.17912395 | H53: =ROUND(D53*(E53+F53),2) -> 0
B54: Des Energ. Comp. FP SCEE | D54: =-D51 -> 1422.72 | E54: =E51*F20 -> 0.1237171 | F54: =F51*H20 -> 0.035130242 | G54: =E54+F54 -> 0.15884734 | H54: =ROUND(D54*(E54+F54),2) -> 226
B56: ERE | D56: 27.675 | F56: =IF(AND($B$17<$F$2,$E$17<$F$2),E8,IF($B$17<$F$2,K8,H8)) -> 0.30007032 | H56: =ROUND(D56*(E56+F56),2) -> 8.3
B57: DRE | D57: 0 | E57: =E42 -> 31.319032 | H57: =ROUND(D57*(E57+F57),2) -> 0
D59: Base de Cálculo
B60: PIS | D60: =(SUM(H25:H31)+H41+H42+H47+H48+H56+H57)/(1-E60-E63) -> 14337.416 | E60: 0.008 | H60: =D60*E60 -> 114.69933
B61: PIS Injetado | D61: =(SUM(H33:H39))/(1-E60-E63) -> -609.14992 | E61: =E60 -> 0.008 | H61: =D61*E61 -> -4.8731993
B62: PIS não utilizada | D62: =(H44+H45)/(1-E62-E65) -> 339.07035 | E62: =E60 -> 0.008 | H62: =D62*E62 -> 2.7125628
B63: COFINS | D63: =D60 -> 14337.416 | E63: 0.0368 | H63: =D63*E63 -> 527.61692
B64: COFINS Injetado | D64: =D61 -> -609.14992 | E64: =E63 -> 0.0368 | H64: =D64*E64 -> -22.416717
B65: COFINS não utilizada | D65: =D62 -> 339.07035 | E65: =E63 -> 0.0368 | H65: =D65*E65 -> 12.477789
B66: ICMS | D66: =D60/(1-E66) -> 17273.995 | E66: 0.17 | H66: =D66*E66 -> 2936.5792
B67: ICMS Injetado TE | D67: =((D33*F33)+(D34*F34)+SUM(H36:H39)+(D50*F50)+(D51*F51)+(D53*F53)+(D54*F54))/(1-E61-E64)/(1-E67) -> -511.9027 | E67: =E66 -> 0.17 | H67: =D67*E67 -> -87.023458

Sheet Fatura B1 (GD II) (Baixa Re (2)
B2: B1 Baixa renda | E2: Vigência das Tarifas: | F2: 45145 | I2: GDII | M2: Bandeira | N2: R$/kWh | O2: ANEEL em 29/06 | Q2: TUSD FIO B
M3: VERDE | N3: 0
B4: TARIFA R$ kWh | C4: TARIFA ANTIGA - REH 3091/2022 | F4: TARIFA NOVA - REH XXXX/2023 | I4: Tarifas Proporcionalizadas | M4: BAM | N4: 0.02989 | Q4: TARIFA | R4: =C4 -> TARIFA ANTIGA - REH 3091/2022 | U4: =F4 -> TARIFA NOVA - REH XXXX/2023 | X4: Tarifas Proporcionalizadas
C5: Tusd | D5: TE | E5: TUSD + TE | F5: Tusd | G5: TE | H5: TUSD + TE | I5: Tusd | J5: TE | K5: TUSD + TE | M5: BVM1 | N5: 0.065 | R5: Tusd (R$/kWh) | U5: Tusd (R$/kWh) | X5: Tusd (R$/kWh)
B6: Baixa renda | C6: 0.27266 | D6: 0.27703 | E6: =C6+D6 -> 0.54969 | F6: 0.27266 | G6: 0.27703 | H6: =F6+G6 -> 0.54969 | I6: =((C6*$C$13)+(F6*$D$13))/($D$13+$C$13) -> 0.27266 | J6: =((D6*$C$13)+(G6*$D$13))/($D$13+$C$13) -> 0.27703 | K6: =I6+J6 -> 0.54969 | M6: BVM2 | N6: 0.09795 | Q6: =B6 -> Baixa renda | R6: ='[6]FIO B'!H11/1000 -> 0.19205 | U6: ='[6]FIO B'!K11/1000 -> 0.17652 | X6: =((R6*$C$13)+(U6*$D$13))/($D$13+$C$13) -> 0.18503645
B7: TE SCEE | G7: =G6*15% -> 0.0415545 | J7: =((D7*$C$13)+(G7*$D$13))/($D$13+$C$13) -> 0.018766548 | M7: Escassez Hídrica | N7: 0.142
H9: Fatura | L9: Vigência das Tarifas (troca Bandeira): | M9: =EOMONTH(B13,0)+1 -> 45139
B10: INSTALAÇÃO | C10: 1182321 | H10: =E13 -> 45158 | K10: Altere a bandeira na célula abaixo
K11: VERDE | L11: VERDE
B12: Leitura Anterior | C12: Nº de dias tarifa Anterior | D12: Nº de dias tarifa Nova | E12: Leitura Atual | J12: Leitura Anterior | K12: Nº de dias tarifa Anterior | L12: Nº de dias tarifa Nova | M12: Leitura Atual
B13: 45127 | C13: =IF((F2-B13-1)<0,0,(F2-B13-1)) -> 17 | D13: =E13-F2+1 -> 14 | E13: 45158 | J13: =B13 -> 45127 | K13: =IF((M9-J13-1)<0,0,(M9-J13-1)) -> 11 | L13: =M13-M9+1 -> 20 | M13: =E13 -> 45158
B15: Regra do custo de disponibilidade
A16: monofásico | B16: Cliente | D16: trifásico | G16: =IF(D16="monofásico",30,IF(D16="bifásico",50,100)) -> 100 | H16: kWh
A17: bifásico | B17: TUSD = | G17: =I6 -> 0.27266 | H17: R$/kWh
A18: trifásico | B18: TE = | G18: =J6 -> 0.27703 | H18: R$/kWh | J18: bandeira proporcional
B19: Adicional de Bandeira Amarela | G19: =(IF($K$11=M4,(G16*(K13)/(K13+L13)),0)+IF($L$11=M4,(G16*(L13)/(K13+L13)),0))*N4 -> 0 | H19: R$ | I19: =IF(OR($K$11=M4,$L$11=M4),N4,0) -> 0 | J19: =(IF($K$11=M4,(N4*(K13)/(K13+L13)),0)+IF($L$11=M4,(N4*(L13)/(K13+L13)),0)) -> 0
B20: Adicional de bandeira Vermelha 1 | G20: =(IF($K$11=M5,(G16*(K13)/(K13+L13)),0)+IF($L$11=M5,(G16*(L13)/(K13+L13)),0))*N5 -> 0 | H20: R$ | I20: =IF(OR($K$11=M5,$L$11=M5),N5,0) -> 0 | J20: =(IF($K$11=M5,(N5*(K13)/(K13+L13)),0)+IF($L$11=M5,(N5*(L13)/(K13+L13)),0)) -> 0
B21: Adicional de bandeira Vermelha 2 | G21: =(IF($K$11=M6,(G16*(K13)/(K13+L13)),0)+IF($L$11=M6,(G16*(L13)/(K13+L13)),0))*N6 -> 0 | H21: R$ | I21: =IF(OR($K$11=M6,$L$11=M6),N6,0) -> 0 | J21: =(IF($K$11=M6,(N6*(K13)/(K13+L13)),0)+IF($L$11=M6,(N6*(L13)/(K13+L13)),0)) -> 0
B22: Custo de disponibilidade | G22: =G16*(G17+G18)+G19+G20+G21 -> 54.969 | H22: R$
B24: Consumo = | G24: 1000 | H24: kWh
B25: Energia Injetada = | G25: 600 | H25: kWh | I25: =G25+D53 -> 570
G26: =-IF(G24<G16,0,IF(G25<(((G24*(E46+F46))+H48+H49+H50+H51)-((G16*(G17+G18)+G19+G20+G21)))/(E71+F56+J19+J20+J21),-G25,-(((G24*(E46+F46))+H48+H49+H50+H51)-((G16*(G17+G18)+G19+G20+G21)))/(E71+F56+J19+J20+J21))) -> 600 | H26: =G24-G26 -> 400
B27: Perc. de Redução da Energia Injetada | E27: TUSD | F27: 1 | G27: TE | H27: 1 | K27: =M101+M107 -> 72.880698
B29: Fatura B1 Baixa Renda
D30: Qtde | E30: TUSD | F30: TE | G30: TUSD + TE | H30: R$
B31: Fornecimento de Energia Elétrica | H31: =SUM(H33:H71)+SUM(H76:H81) -> 25.154358
A33: 0.65 | B33: Consumo 0 - 30 | D33: =IF(H26>0,30,0) -> 30 | E33: =$E$46*(1-A33) -> 0.095431 | F33: =$F$46*(1-A33) -> 0.0969605 | G33: =E33+F33 -> 0.1923915 | H33: =ROUND((D33*E33),2)+ROUND((D33*F33),2) -> 5.77
A34: 0.4 | B34: Consumo 31 - 100 | D34: 20 | E34: =$E$46*(1-A34) -> 0.163596 | F34: =$F$46*(1-A34) -> 0.166218 | G34: =E34+F34 -> 0.329814 | H34: =ROUND((D34*E34),2)+ROUND((D34*F34),2) -> 6.59
A35: 0.1 | B35: Consumo 101 - 220 | E35: =$E$46*(1-A35) -> 0.245394 | F35: =$F$46*(1-A35) -> 0.249327 | G35: =E35+F35 -> 0.494721 | H35: =ROUND((D35*E35),2)+ROUND((D35*F35),2) -> 0
A36: 0 | B36: Consumo > 220 | E36: =$E$46*(1-A36) -> 0.27266 | F36: =$F$46*(1-A36) -> 0.27703 | G36: =E36+F36 -> 0.54969 | H36: =ROUND((D36*E36),2)+ROUND((D36*F36),2) -> 0
B38: Adicional BAM | H38: =O124 -> 0
B39: Adicional BVM 1 | H39: =O133 -> 0
B40: Adicional BVM 2 | H40: =O142 -> 0
B41: Adicional Escassez Hídrica | H41: =O151 -> 0
A43: 0.65 | B43: Energia Fornecida 0 - 30 | D43: 30 | E43: =$E$46*(1-A43) -> 0.095431 | F43: =$F$46*(1-A43) -> 0.0969605 | G43: =E43+F43 -> 0.1923915 | H43: =ROUND((D43*E43),2)+ROUND((D43*F43),2) -> 5.77
A44: 0.4 | B44: Energia Fornecida 31 - 100 | D44: 70 | E44: =$E$46*(1-A44) -> 0.163596 | F44: =$F$46*(1-A44) -> 0.166218 | G44: =E44+F44 -> 0.329814 | H44: =ROUND((D44*E44),2)+ROUND((D44*F44),2) -> 23.09
A45: 0.1 | B45: Energia Fornecida 101 - 220 | D45: 120 | E45: =$E$46*(1-A45) -> 0.245394 | F45: =$F$46*(1-A45) -> 0.249327 | G45: =E45+F45 -> 0.494721 | H45: =ROUND((D45*E45),2)+ROUND((D45*F45),2) -> 59.37
A46: 0 | B46: Energia Fornecida > 220 | D46: 9 | E46: =IF(AND($B$13<$F$2,$E$13<$F$2),C6,IF($B$13<$F$2,I6,F6)) -> 0.27266 | F46: =IF(AND($B$13<$F$2,$E$13<$F$2),D6,IF($B$13<$F$2,J6,G6)) -> 0.27703 | G46: =E46+F46 -> 0.54969 | H46: =ROUND((D46*E46),2)+ROUND((D46*F46),2) -> 4.94
B48: Adicional BAM | H48: =O161 -> 0
B49: Adicional BVM 1 | H49: =O170 -> 0
B50: Adicional BVM 2 | H50: =O179 -> 0
B51: Adicional Escassez Hídrica | H51: =O188 -> 0
A53: 0.65 | B53: Energia Inejtada 0 - 30 | D53: -30 | E53: =E43 -> 0.095431 | F53: =F43 -> 0.0969605 | G53: =E53+F53 -> 0.1923915 | H53: =ROUND((D53*E53),2)+ROUND((D53*F53),2) -> -5.77
A54: 0.4 | B54: Energia Injetada 31 - 100 | D54: -70 | E54: =E44 -> 0.163596 | F54: =F44 -> 0.166218 | G54: =E54+F54 -> 0.329814 | H54: =ROUND((D54*E54),2)+ROUND((D54*F54),2) -> -23.09
A55: 0.1 | B55: Energia Injetada 101 - 220 | D55: -120 | E55: =E45 -> 0.245394 | F55: =F45 -> 0.249327 | G55: =E55+F55 -> 0.494721 | H55: =ROUND((D55*E55),2)+ROUND((D55*F55),2) -> -59.37
A56: 0 | B56: Energia Injetada > 220 | D56: -9 | E56: =E46 -> 0.27266 | F56: =F46 -> 0.27703 | G56: =E56+F56 -> 0.54969 | H56: =ROUND((D56*E56),2)+ROUND((D56*F56),2) -> -4.94
B58: Adicional BAM | H58: =O200 -> 0
B59: Adicional BVM 1 | H59: =O209 -> 0
B60: Adicional BVM 2 | H60: =O218 -> 0
B61: Adicional Escassez Hídrica | H61: =O227 -> 0
A63: 0.65 | B63: Energia Compensada SCEE 0 - 30 | D63: =-D53 -> 30 | E63: =$E$66*(1-A63) -> 0.095431 | F63: =$F$66*(1-A63) -> 0.0065682919 | G63: =E63+F63 -> 0.10199929 | H63: =ROUND(D63*(E63+F63),2) -> 3.06
A64: 0.4 | B64: Energia Compensada SCEE 31 - 100 | D64: =-D54 -> 70 | E64: =$E$66*(1-A64) -> 0.163596 | F64: =$F$66*(1-A64) -> 0.011259929 | G64: =E64+F64 -> 0.17485593 | H64: =ROUND(D64*(E64+F64),2) -> 12.24
A65: 0.1 | B65: Energia Compensada SCEE 101 - 220 | D65: =-D55 -> 120 | E65: =$E$66*(1-A65) -> 0.245394 | F65: =$F$66*(1-A65) -> 0.016889894 | G65: =E65+F65 -> 0.26228389 | H65: =ROUND(D65*(E65+F65),2) -> 31.47
A66: 0 | B66: Energia Compensada SCEE > 220 | D66: =-D56 -> 9 | E66: =E46 -> 0.27266 | F66: =IF(AND($B$13<$F$2,$E$13<$F$2),D7,IF($B$13<$F$2,J7,G7)) -> 0.018766548 | G66: =E66+F66 -> 0.29142655 | H66: =ROUND(D66*(E66+F66),2) -> 2.62
B68: Des Energ. Comp. SCEE 0 - 30 | D68: =-D63 -> -30 | E68: =E63*$F$27 -> 0.095431 | F68: =F63*$H$27 -> 0.0065682919 | G68: =E68+F68 -> 0.10199929 | H68: =ROUND(D68*(E68+F68),2) -> -3.06
B69: Des Energ. Comp. SCEE 31 - 100 | D69: =-D64 -> -70 | E69: =E64*$F$27 -> 0.163596 | F69: =F64*$H$27 -> 0.011259929 | G69: =E69+F69 -> 0.17485593 | H69: =ROUND(D69*(E69+F69),2) -> -12.24
B70: Des Energ. Comp. SCEE 101 - 220 | D70: =-D65 -> -120 | E70: =E65*$F$27 -> 0.245394 | F70: =F65*$H$27 -> 0.016889894 | G70: =E70+F70 -> 0.26228389 | H70: =ROUND(D70*(E70+F70),2) -> -31.47
B71: Des Energ. Comp. SCEE > 220 | D71: =-D66 -> -9 | E71: =E66*$F$27 -> 0.27266 | F71: =F66*$H$27 -> 0.018766548 | G71: =E71+F71 -> 0.29142655 | H71: =ROUND(D71*(E71+F71),2) -> -2.62 | I71: =SUM(H63:H71) -> -9.7699626e-15
H73: =SUM(H33:H72) -> 12.36 | J73: =231.75-'Fatura B1 (GD II) (Baixa Re (2)'!H73 -> 219.39
D75: Base de Cálculo
B76: PIS | D76: =SUM(H33:H51)/(1-E76-E78) -> 108.98482 | E76: 0.0056 | H76: =D76*E76 -> 0.61031499
B77: PIS Eneg Inj | D77: =SUM(H53:H71)/(1-E76-E78) -> -96.22018 | E77: =E76 -> 0.0056 | H77: =D77*E77 -> -0.53883301
B78: COFINS | D78: =D76 -> 108.98482 | E78: 0.0261 | H78: =D78*E78 -> 2.8445038
B79: COFINS Eneg Inj | D79: =D77 -> -96.22018 | E79: =E78 -> 0.0261 | H79: =D79*E79 -> -2.5113467
B80: ICMS | D80: =D76/(1-E80) -> 131.30701 | E80: 0.17 | H80: =D80*E80 -> 22.322192
B81: ICMS Eneg Inj | D81: =((D53*F53)+(D54*F54)+(D55*F55)+(D56*F56)+(D64*F64)+(D65*F65)+(D66*F66)+(D69*F69)+(D70*F70)+(D71*F71)+(H58+H59+H60+H61)+(D63*F63)+(D68*F68))/(1-E77-E79)/(1-E81) -> -58.426313 | E81: =E80 -> 0.17 | H81: =D81*E81 -> -9.9324732
B82: ICMS Desc Tarifa Social | D82: =K114 -> 39.007906 | E82: =E81 -> 0.17 | H82: =D82*E82 -> 6.631344
B85: Benefício Tarifa Social | H85: =K113 -> 15.1245 | I85: (mensagem na fatura)
F87: Memória benefício Tarifa Social
I88: TUSD X | J88: TE | M88: Com tributos e bandeiras (base ICMS)
F89: Consumo | G89: B1 Baixa Renda | H89: =SUM(D33:D36,D43:D46) -> 279 | I89: =E36 -> 0.27266 | J89: =F36 -> 0.27703 | K89: =H89*(I89+J89) -> 153.36351 | M89: =SUM(K89:K93)/(1-E76-E78)/(1-E80) -> 190.82445
G90: BAM | H90: =IF($K$11=$B$154,(H89*($K$13)/($K$13+$L$13)),0)+IF($L$11=$B$154,(H89*($L$13)/($K$13+$L$13)),0) -> 0 | J90: =N4 -> 0.02989 | K90: =H90*(I90+J90) -> 0
G91: BVM1 | H91: =IF($K$11=$B$163,(H90*($K$13)/($K$13+$L$13)),0)+IF($L$11=$B$163,(H90*($L$13)/($K$13+$L$13)),0) -> 0 | J91: =N5 -> 0.065 | K91: =H91*(I91+J91) -> 0
G92: BVM2 | H92: =IF($K$11=$B$172,(H91*($K$13)/($K$13+$L$13)),0)+IF($L$11=$B$172,(H91*($L$13)/($K$13+$L$13)),0) -> 0 | J92: =N6 -> 0.09795 | K92: =H92*(I92+J92) -> 0
G93: Escassez Hídrica | H93: =IF($K$11=$B$181,(H92*($K$13)/($K$13+$L$13)),0)+IF($L$11=$B$181,(H92*($L$13)/($K$13+$L$13)),0) -> 0 | J93: =N7 -> 0.142 | K93: =H93*(I93+J93) -> 0
F95: Injetada | G95: B1 Baixa Renda | H95: =SUM(D53:D56) -> -229 | I95: =E71 -> 0.27266 | J95: =J89 -> 0.27703 | K95: =H95*(I95+J95) -> -125.87901 | M95: =((H95*J95)+(K96+K97+K98+K99))/(1-E77-E79)/(1-E81) -> -78.935845
G96: BAM | H96: =IF($K$11=$B$154,(H95*($K$13)/($K$13+$L$13)),0)+IF($L$11=$B$154,(H95*($L$13)/($K$13+$L$13)),0) -> 0 | J96: =J90 -> 0.02989 | K96: =H96*(I96+J96) -> 0
G97: BVM1 | H97: =IF($K$11=$B$163,(H96*($K$13)/($K$13+$L$13)),0)+IF($L$11=$B$163,(H96*($L$13)/($K$13+$L$13)),0) -> 0 | J97: =J91 -> 0.065 | K97: =H97*(I97+J97) -> 0
G98: BVM2 | H98: =IF($K$11=$B$172,(H97*($K$13)/($K$13+$L$13)),0)+IF($L$11=$B$172,(H97*($L$13)/($K$13+$L$13)),0) -> 0 | J98: =J92 -> 0.09795 | K98: =H98*(I98+J98) -> 0
G99: Escassez Hídrica | H99: =IF($K$11=$B$181,(H98*($K$13)/($K$13+$L$13)),0)+IF($L$11=$B$181,(H98*($L$13)/($K$13+$L$13)),0) -> 0 | J99: =J93 -> 0.142 | K99: =H99*(I99+J99) -> 0
F101: Bx Renda Consumo | G101: Baixa Renda | K101: =SUM(H33:H36,H43:H46) -> 105.53 | M101: =SUM(K101:K105)/(1-E76-E78)/(1-E80) -> 131.30701
G102: BAM | K102: =H38+H48 -> 0
G103: BVM1 | K103: =H39+H49 -> 0
G104: BVM2 | K104: =H40+H50 -> 0
G105: Escassez Hídrica | K105: =H41+H51 -> 0
F107: Bx Renda Injetada | G107: Baixa Renda | K107: =SUM(H53:H56,H63:H66,H68:H71) -> -93.17 | M107: =D81 -> -58.426313
G108: BAM | K108: =H58 -> 0
G109: BVM1 | K109: =H59 -> 0
G110: BVM2 | K110: =H60 -> 0
G111: Escassez Hídrica | K111: =H61 -> 0
J113: Benefício Tarifa Social | K113: =(K89+K95)-(K101+K107) -> 15.1245 | L113: sem considerar as bandeiras
J114: Com tributos | K114: =(M89+M95)-(M101+M107) -> 39.007906 | L114: considerando as bandeiras no cálculo dos tributos
B116: Consumo - Adicional de Bandeira
B117: BAM | K117: =N4 -> 0.02989
C118: Consumo | J118: Tarifas | M118: Receita | O118: Receita Total
C119: KWh | K119: TE | M119: Tusd | N119: TE | O119: Tusd+TE
C120: =IF($K$11=$B$117,(D33*($K$13)/($K$13+$L$13)),0)+IF($L$11=$B$117,(D33*($L$13)/($K$13+$L$13)),0) -> 0 | K120: =$K$154*(1-Q120) -> 0.0104615 | N120: =ROUND((C120*K120),2) -> 0 | O120: =M120+N120 -> 0 | Q120: 0.65
C121: =IF($K$11=$B$117,(D34*($K$13)/($K$13+$L$13)),0)+IF($L$11=$B$117,(D34*($L$13)/($K$13+$L$13)),0) -> 0 | K121: =$K$154*(1-Q121) -> 0.017934 | N121: =ROUND((C121*K121),2) -> 0 | O121: =M121+N121 -> 0 | Q121: 0.4
C122: =IF($K$11=$B$117,(D35*($K$13)/($K$13+$L$13)),0)+IF($L$11=$B$117,(D35*($L$13)/($K$13+$L$13)),0) -> 0 | K122: =$K$154*(1-Q122) -> 0.026901 | N122: =ROUND((C122*K122),2) -> 0 | O122: =M122+N122 -> 0 | Q122: 0.1
C123: =IF($K$11=$B$117,(D36*($K$13)/($K$13+$L$13)),0)+IF($L$11=$B$117,(D36*($L$13)/($K$13+$L$13)),0) -> 0 | K123: =$K$154*(1-Q123) -> 0.02989 | N123: =ROUND((C123*K123),2) -> 0 | O123: =M123+N123 -> 0 | Q123: 0
...
