Workbook

Sheet FIO B
B2: TUSD FIO B
B4: SUBGRUPO | C4: MODALIDADE | D4: CLASSE | E4: SUBCLASSE | F4: POSTO | G4: TARIFAS DE APLICAÇÃO
G5: TUSD FIO B (RTP 2025) | J5: TUSD FIO B (RTA 2026)
G6: R$/kW | H6: R$/MWh | J6: R$/kW | K6: R$/MWh
B7: B1 | C7: BRANCA | D7: RESIDENCIAL | E7: RESIDENCIAL | F7: P | G7: 0 | H7: 591.10909 | J7: 0 | K7: 606.53962
B8: B1 | C8: BRANCA | D8: RESIDENCIAL | E8: RESIDENCIAL | F8: INT | G8: 0 | H8: 354.6655 | J8: 0 | K8: 363.92381
B9: B1 | C9: BRANCA | D9: RESIDENCIAL | E9: RESIDENCIAL | F9: FP | G9: 0 | H9: 118.2218 | J9: 0 | K9: 121.3079
B10: B1 | C10: PRÉ-PAGAMENTO | D10: RESIDENCIAL | E10: RESIDENCIAL | F10: NA | G10: 0 | H10: 203.83072 | J10: 0 | K10: 209.15159
B11: B1 | C11: CONVENCIONAL | D11: RESIDENCIAL | E11: RESIDENCIAL | F11: NA | G11: 0 | H11: 203.83072 | J11: 0 | K11: 209.15159
B12: B1 | C12: PRÉ-PAGAMENTO | D12: RESIDENCIAL | E12: BAIXA RENDA | F12: NA | G12: 0 | H12: 203.83072 | J12: 0 | K12: 209.15159
B13: B1 | C13: CONVENCIONAL | D13: RESIDENCIAL | E13: BAIXA RENDA | F13: NA | G13: 0 | H13: 203.83072 | J13: 0 | K13: 209.15159
B14: B1 | C14: PRÉ-PAGAMENTO | D14: RESIDENCIAL | E14: RESIDENCIAL DESCONTO SOCIAL | F14: NA | G14: 0 | H14: 203.83072 | J14: 0 | K14: 209.15159
B15: B1 | C15: CONVENCIONAL | D15: RESIDENCIAL | E15: RESIDENCIAL DESCONTO SOCIAL | F15: NA | G15: 0 | H15: 203.83072 | J15: 0 | K15: 209.15159
B16: B2 | C16: BRANCA | D16: RURAL | E16: NÃO SE APLICA | F16: P | G16: 0 | H16: 693.02445 | J16: 0 | K16: 711.11541
B17: B2 | C17: BRANCA | D17: RURAL | E17: NÃO SE APLICA | F17: INT | G17: 0 | H17: 415.81471 | J17: 0 | K17: 426.66929
B18: B2 | C18: BRANCA | D18: RURAL | E18: NÃO SE APLICA | F18: FP | G18: 0 | H18: 138.60487 | J18: 0 | K18: 142.22306
... B39: B | C39: GERAÇÃO | D39: TIPO 02 | E39: NA | F39: NA | G39: 0 | H39: 11.690957 | J39: 0 | K39: 11.996142

Sheet TABELA DE TARIFAS ANTIGAS
A1: TABELA 1 – TARIFAS DE APLICAÇÃO E BASE ECONÔMICA PARA O GRUPO A.
A2: SUBGRUPO | B2: MODALIDADE | C2: UC | D2: POSTO | E2: TARIFAS DE APLICAÇÃO | J2: BASE ECONÔMICA | N2: Reajuste | O2: Dia | P2: Mês | Q2: Ano
E3: TUSD | G3: TE | J3: TUSD | L3: TE | N3: De | O3: 07 | P3: 08 | Q3: 2025
E4: R$/kW | F4: R$/MWh | G4: BVD – R$/MWh | H4: BAM – R$/MWh | I4: BVM – R$/MWh | J4: R$/kW | K4: R$/MWh | L4: R$/MWh | N4: Até | O4: 06 | P4: 08 | Q4: 2026
B5: AZUL | C5: NA | D5: P
A6: A1 (230 kV ou mais) | D6: FP
B7: AZUL APE | C7: NA | D7: P
D8: FP
A9: A2 (88 a 138kV) | B9: AZUL | C9: NA | D9: P
D10: FP
B11: AZUL APE | C11: NA | D11: P
D12: FP
B13: DISTRIBUIÇÃO | C13: ELFSM | D13: P
D14: FP
D15: NA
B16: GERAÇÃO | C16: UTE LASA | D16: NA
C17: UTE ALCON | D17: NA
C18: UTE SOL | D18: NA
C19: UHE MASCARENHAS - ENERGEST | D19: NA
C20: UHE SUICA | D20: NA
C21: PCH SAO JOAQUIM | D21: NA
C22: PCH SAO SIMAO | D22: NA
C23: PCH FRANCISCO GROSS | D23: NA
C24: PCH SAO PEDRO | D24: NA
C25: UTE LINHARES | D25: NA
C26: UTE ARCEL | D26: NA
C27: NOVO GERADOR | D27: NA
A28: A3 (69kV) | B28: AZUL | C28: NA | D28: P
D29: FP
B30: AZUL APE | C30: NA | D30: P
D31: FP
B32: DISTRIBUIÇÃO | D32: P
D33: FP
D34: NA
B35: GERAÇÃO | C35: NA | D35: NA
A36: A3a (30 a 44kV) | B36: AZUL | C36: NA | D36: P
D37: FP
B38: AZUL APE | C38: NA | D38: P
D39: FP
B40: VERDE | C40: NA | D40: NA
D41: P
D42: FP
B43: VERDE APE | C43: NA | D43: NA
D44: P
D45: FP
B46: CONVENCIONAL | C46: NA | D46: NA
B47: GERAÇÃO | C47: NA | D47: NA
A48: A4 (2,3 a 25kV) | B48: AZUL | C48: NA | D48: P
D49: FP
B50: AZUL APE | C50: NA | D50: P
D51: FP
B52: VERDE | C52: NA | D52: NA
D53: P
D54: FP
B55: VERDE APE | C55: NA | D55: NA
D56: P
D57: FP
B58: CONVENCIONAL | C58: NA | D58: NA
B59: DISTRIBUIÇÃO | C59: COELBA | D59: P
D60: FP
D61: NA
B62: GERAÇÃO | C62: NA | D62: NA
A64: TABELA 2 – TARIFAS DE APLICAÇÃO E BASE ECONÔMICA PARA O GRUPO B.
A65: SUBGRUPO | B65: MODALIDADE | C65: CLASSE | D65: SUBCLASSE | E65: POSTO | F65: TARIFAS DE APLICAÇÃO | K65: TARIFAS BASE ECONÔMICA
F66: TUSD | H66: TE | K66: TUSD | M66: TE
F67: R$/kW | G67: R$/MWh | H67: BVD – R$/MWh | I67: BAM – R$/MWh | J67: BVM – R$/MWh | K67: R$/kW | L67: R$/MWh | M67: R$/MWh
A68: B1 | B68: BRANCA | C68: RESIDENCIAL | D68: RESIDENCIAL | E68: P | F68: 0 | G68: 937.61 | H68: 484.48 | K68: 0 | L68: 918.51 | M68: 492.47
E69: INT | F69: 0 | G69: 651.29 | H69: 305.79 | K69: 0 | L69: 634.94 | M69: 316.46
E70: FP | F70: 0 | G70: 364.96 | H70: 305.79 | K70: 0 | L70: 351.38 | M70: 316.46
B71: CONVENCIONAL | C71: RESIDENCIAL | D71: RESIDENCIAL | E71: NA | F71: 0 | G71: 468.63 | H71: 320.68 | K71: 0 | L71: 454.05 | M71: 331.12
D72: BAIXA RENDA(1) | E72: NA | F72: 0 | G72: 325.43 | H72: 282.45 | K72: 0
D73: DESCONTO SOCIAL | E73: NA | G73: 340.19 | H73: 296.66
A74: B2 | B74: BRANCA | C74: RURAL | D74: NA | E74: P | F74: 0 | G74: 1061.03 | H74: 484.48 | K74: 0 | L74: 1040.73 | M74: 492.47
E75: INT | F75: 0 | G75: 725.34 | H75: 305.79 | K75: 0 | L75: 708.28 | M75: 316.46
E76: FP | F76: 0 | G76: 389.65 | H76: 305.79 | K76: 0 | L76: 375.82 | M76: 316.46
B77: CONVENCIONAL | C77: RURAL | D77: NA | E77: NA | F77: 0 | G77: 468.63 | H77: 320.68 | K77: 0 | L77: 454.05 | M77: 331.12
B78: BRANCA | C78: RURAL | D78: COOPERATIVA DE ELETRIFICAÇÃO RURAL | E78: P | F78: 0 | G78: 1061.03 | H78: 484.48 | K78: 0 | L78: 1040.73 | M78: 492.47
E79: INT | F79: 0 | G79: 725.34 | H79: 305.79 | K79: 0 | L79: 708.28 | M79: 316.46
E80: FP | F80: 0 | G80: 389.65 | H80: 305.79 | K80: 0 | L80: 375.82 | M80: 316.46
B81: CONVENCIONAL | C81: RURAL | D81: COOPERATIVA DE ELETRIFICAÇÃO RURAL | E81: NA | F81: 0 | G81: 468.63 | H81: 320.68 | K81: 0 | L81: 454.05 | M81: 331.12
B82: BRANCA | C82: RURAL | D82: SERVIÇO PÚBLICO DE IRRIGAÇÃO RURAL | E82: P | F82: 0 | G82: 1061.03 | H82: 484.48 | K82: 0 | L82: 1040.73 | M82: 492.47
E83: INT | F83: 0 | G83: 725.34 | H83: 305.79 | K83: 0 | L83: 708.28 | M83: 316.46
E84: FP | F84: 0 | G84: 389.65 | H84: 305.79 | K84: 0 | L84: 375.82 | M84: 316.46
B85: CONVENCIONAL | C85: RURAL | D85: SERVIÇO PÚBLICO DE IRRIGAÇÃO RURAL | E85: NA | F85: 0 | G85: 468.63 | H85: 320.68 | K85: 0 | L85: 454.05 | M85: 331.12
A86: B3 | B86: BRANCA | C86: NA | D86: NA | E86: P | F86: 0 | G86: 1061.03 | H86: 484.48 | K86: 0 | L86: 1040.73 | M86: 492.47
E87: INT | F87: 0 | G87: 725.34 | H87: 305.79 | K87: 0 | L87: 708.28 | M87: 316.46
E88: FP | F88: 0 | G88: 389.65 | H88: 305.79 | K88: 0 | L88: 375.82 | M88: 316.46
B89: CONVENCIONAL | C89: NA | D89: NA | E89: NA | F89: 0 | G89: 468.63 | H89: 320.68 | K89: 0 | L89: 454.05 | M89: 331.12
A90: B4 | B90: CONVENCIONAL | C90: ILUMINAÇÃO PÚBLICA | D90: B4a – REDE DE DISTRIBUIÇÃO | E90: NA | F90: 0 | G90: 257.75 | H90: 176.38 | K90: 0 | L90: 249.73 | M90: 182.12
D91: B4b – BULBO DE LÂMPADA | E91: NA | F91: 0 | G91: 281.18 | H91: 192.41 | K91: 0 | L91: 272.43 | M91: 198.67

Sheet TABELA DE TARIFAS NOVAS
A1: TABELA 1 – TARIFAS DE APLICAÇÃO E BASE ECONÔMICA PARA O GRUPO A.
A2: SUBGRUPO | B2: MODALIDADE | C2: UC | D2: POSTO | E2: TARIFAS DE APLICAÇÃO | J2: BASE ECONÔMICA | N2: Reajuste | O2: Dia | P2: Mês | Q2: Ano
E3: TUSD | G3: TE | J3: TUSD | L3: TE | N3: De | O3: 07 | P3: 08 | Q3: 2026
E4: R$/kW | F4: R$/MWh | G4: BVD – R$/MWh | H4: BAM – R$/MWh | I4: BVM – R$/MWh | J4: R$/kW | K4: R$/MWh | L4: R$/MWh | N4: Até | O4: 31 | P4: 12 | Q4: 9999
B5: AZUL | C5: NA | D5: P
A6: A1 (230 kV ou mais) | D6: FP
B7: AZUL APE | C7: NA | D7: P
D8: FP
A9: A2 (88 a 138kV) | B9: AZUL | C9: NA | D9: P
D10: FP
B11: AZUL APE | C11: NA | D11: P
D12: FP
B13: DISTRIBUIÇÃO | C13: ELFSM | D13: P
D14: FP
D15: NA
B16: GERAÇÃO | C16: UTE LASA | D16: NA
C17: UTE ALCON | D17: NA
C18: UTE SOL | D18: NA
C19: UHE MASCARENHAS - ENERGEST | D19: NA
C20: UHE SUICA | D20: NA
C21: PCH SAO JOAQUIM | D21: NA
C22: PCH SAO SIMAO | D22: NA
C23: PCH FRANCISCO GROSS | D23: NA
C24: PCH SAO PEDRO | D24: NA
C25: UTE LINHARES | D25: NA
C26: UTE POVOACAO 1 | D26: NA
C27: UTE ARCEL | D27: NA
C28: UTE BIANCOGRES | D28: NA
C29: NOVO GERADOR | D29: NA
A30: A3 (69kV) | B30: AZUL | C30: NA | D30: P
D31: FP
B32: AZUL APE | C32: NA | D32: P
D33: FP
B34: DISTRIBUIÇÃO | D34: P
D35: FP
D36: NA
B37: GERAÇÃO | C37: NA | D37: NA
A38: A3a (30 a 44kV) | B38: AZUL | C38: NA | D38: P
D39: FP
B40: AZUL APE | C40: NA | D40: P
D41: FP
B42: VERDE | C42: NA | D42: NA
D43: P
D44: FP
B45: VERDE APE | C45: NA | D45: NA
D46: P
D47: FP
B48: CONVENCIONAL | C48: NA | D48: NA
B49: GERAÇÃO | C49: NA | D49: NA
A50: A4 (2,3 a 25kV) | B50: AZUL | C50: NA | D50: P
D51: FP
B52: AZUL APE | C52: NA | D52: P
D53: FP
B54: VERDE | C54: NA | D54: NA
D55: P
D56: FP
B57: VERDE APE | C57: NA | D57: NA
D58: P
D59: FP
B60: CONVENCIONAL | C60: NA | D60: NA
B61: DISTRIBUIÇÃO | C61: COELBA | D61: P
D62: FP
D63: NA
B64: GERAÇÃO | C64: NA | D64: NA
A66: TABELA 2 – TARIFAS DE APLICAÇÃO E BASE ECONÔMICA PARA O GRUPO B.
A67: SUBGRUPO | B67: MODALIDADE | C67: CLASSE | D67: SUBCLASSE | E67: POSTO | F67: TARIFAS DE APLICAÇÃO | K67: TARIFAS BASE ECONÔMICA
F68: TUSD | H68: TE | K68: TUSD | M68: TE
F69: R$/kW | G69: R$/MWh | H69: BVD – R$/MWh | I69: BAM – R$/MWh | J69: BVM – R$/MWh | K69: R$/kW | L69: R$/MWh | M69: R$/MWh
A70: B1 | B70: BRANCA | C70: RESIDENCIAL | D70: RESIDENCIAL | E70: P | F70: 0 | G70: 999.02 | H70: 516.91 | K70: 0 | L70: 956.95 | M70: 478.38
E71: INT | F71: 0 | G71: 698.21 | H71: 321.07 | K71: 0 | L71: 662.46 | M71: 299.92
E72: FP | F72: 0 | G72: 397.41 | H72: 321.07 | K72: 0 | L72: 367.97 | M72: 299.92
B73: CONVENCIONAL | C73: RESIDENCIAL | D73: RESIDENCIAL | E73: NA | F73: 0 | G73: 506.32 | H73: 337.39 | K73: 0 | L73: 474.59 | M73: 314.79
D74: BAIXA RENDA(1) | E74: NA | F74: 0 | G74: 348.95 | H74: 325.32 | K74: 0 | L74: 334.57 | M74: 303.57
D75: DESCONTO SOCIAL | E75: NA | F75: 0 | G75: 356.42 | H75: 337.59 | L75: 343.39 | M75: 314.79
A76: B2 | B76: BRANCA | C76: RURAL | D76: NA | E76: P | F76: 0 | G76: 1128.67 | H76: 516.91 | K76: 0 | L76: 1083.88 | M76: 478.38
E77: INT | F77: 0 | G77: 776.01 | H77: 321.07 | K77: 0 | L77: 738.62 | M77: 299.92
E78: FP | F78: 0 | G78: 423.34 | H78: 321.07 | K78: 0 | L78: 393.35 | M78: 299.92
B79: CONVENCIONAL | C79: RURAL | D79: NA | E79: NA | F79: 0 | G79: 506.32 | H79: 337.39 | K79: 0 | L79: 474.59 | M79: 314.79
B80: BRANCA | C80: RURAL | D80: COOPERATIVA DE ELETRIFICAÇÃO RURAL | E80: P | F80: 0 | G80: 1128.67 | H80: 516.91 | K80: 0 | L80: 1083.88 | M80: 478.38
E81: INT | F81: 0 | G81: 776.01 | H81: 321.07 | K81: 0 | L81: 738.62 | M81: 299.92
E82: FP | F82: 0 | G82: 423.34 | H82: 321.07 | K82: 0 | L82: 393.35 | M82: 299.92
B83: CONVENCIONAL | C83: RURAL | D83: COOPERATIVA DE ELETRIFICAÇÃO RURAL | E83: NA | F83: 0 | G83: 506.32 | H83: 337.39 | K83: 0 | L83: 474.59 | M83: 314.79
B84: BRANCA | C84: RURAL | D84: SERVIÇO PÚBLICO DE IRRIGAÇÃO RURAL | E84: P | F84: 0 | G84: 1128.67 | H84: 516.91 | K84: 0 | L84: 1083.88 | M84: 478.38
E85: INT | F85: 0 | G85: 776.01 | H85: 321.07 | K85: 0 | L85: 738.62 | M85: 299.92
E86: FP | F86: 0 | G86: 423.34 | H86: 321.07 | K86: 0 | L86: 393.35 | M86: 299.92
B87: CONVENCIONAL | C87: RURAL | D87: SERVIÇO PÚBLICO DE IRRIGAÇÃO RURAL | E87: NA | F87: 0 | G87: 506.32 | H87: 337.39 | K87: 0 | L87: 474.59 | M87: 314.79
A88: B3 | B88: BRANCA | C88: NA | D88: NA | E88: P | F88: 0 | G88: 1128.67 | H88: 516.91 | K88: 0 | L88: 1083.88 | M88: 478.38
E89: INT | F89: 0 | G89: 776.01 | H89: 321.07 | K89: 0 | L89: 738.62 | M89: 299.92
E90: FP | F90: 0 | G90: 423.34 | H90: 321.07 | K90: 0 | L90: 393.35 | M90: 299.92
B91: CONVENCIONAL | C91: NA | D91: NA | E91: NA | F91: 0 | G91: 506.32 | H91: 337.39 | K91: 0 | L91: 474.59 | M91: 314.79
A92: B4 | B92: CONVENCIONAL | C92: ILUMINAÇÃO PÚBLICA | D92: B4a – REDE DE DISTRIBUIÇÃO | E92: NA | F92: 0 | G92: 278.48 | H92: 185.56 | K92: 0 | L92: 261.03 | M92: 173.13
D93: B4b – BULBO DE LÂMPADA | E93: NA | F93: 0 | G93: 303.79 | H93: 202.43 | K93: 0 | L93: 284.76 | M93: 188.87

Sheet Fatura B1 (GD) OK
B2: B1 Res | E2: Vigência das Tarifas: | F2: 46241 | M2: Bandeira | N2: R$/kWh | O2: ANEEL em 29/06 | Q2: TUSD FIO B
M3: VERDE | N3: 0
B4: TARIFA | C4: TARIFA NOVA - REH 3241/2023 | F4: TARIFA NOVA - REH xxxx/2024 | I4: Tarifas Proporcionalizadas | M4: BAM | N4: =[1]BANDEIRA!$D$5 -> 0.01885 | Q4: TARIFA | R4: =C4 -> TARIFA NOVA - REH 3241/2023 | U4: =F4 -> TARIFA NOVA - REH xxxx/2024 | X4: Tarifas Proporcionalizadas
C5: Tusd | D5: TE | E5: TUSD + TE | F5: Tusd | G5: TE | H5: TUSD + TE | I5: Tusd | J5: TE | K5: TUSD + TE | M5: BVM1 | N5: =[1]BANDEIRA!$D$6 -> 0.04463 | R5: Tusd (R$/kWh) | U5: Tusd (R$/kWh) | X5: Tusd (R$/kWh)
B6: B1 | C6: ='TABELA DE TARIFAS ANTIGAS'!G71/1000 -> 0.46863 | D6: ='TABELA DE TARIFAS ANTIGAS'!H71/1000 -> 0.32068 | E6: =C6+D6 -> 0.78931 | F6: ='TABELA DE TARIFAS NOVAS'!G73/1000 -> 0.50632 | G6: ='TABELA DE TARIFAS NOVAS'!H73/1000 -> 0.33739 | H6: =F6+G6 -> 0.84371 | I6: =((C6*$C$14)+(F6*$D$14))/($D$14+$C$14) -> 0.48621867 | J6: =((D6*$C$14)+(G6*$D$14))/($D$14+$C$14) -> 0.328478 | K6: =I6+J6 -> 0.81469667 | M6: BVM2 | N6: =[1]BANDEIRA!$D$7 -> 0.07877 | Q6: =B6 -> B1 | R6: ='FIO B'!H11/1000 -> 0.20383072 | U6: ='FIO B'!K11/1000 -> 0.20915159 | X6: =((R6*$C$14)+(U6*$D$14))/($D$14+$C$14) -> 0.20631379
B7: CDE Escassez Hídrica | C7: 0.00018774721 | D7: -0.0044031307 | E7: 0.0036054084 | F7: =T11 -> 0.00018418923 | G7: =U11 -> -0.00053182975 | H7: =F7+G7 -> -0.00034764052 | I7: =((C7*$C$14)+(F7*$D$14))/($D$14+$C$14) -> 0.00018608682 | J7: =((D7*$C$14)+(G7*$D$14))/($D$14+$C$14) -> -0.0025965236 | K7: =I7+J7 -> -0.0024104368 | M7: Escassez Hídrica | N7: 0.142
B8: TE SCEE | G8: =G6*15% -> 0.0506085 | J8: =((D8*$C$14)+(G8*$D$14))/($D$14+$C$14) -> 0.0236173 | P8: CUSTO | R8: Part. TUSD (%) | S8: Part. TE (%) | T8: Tusd (R$/kWh) | U8: TE (R$/kWh)
P9: CDE CONTAS
H10: Fatura | L10: Vigência das Tarifas (troca Bandeira): | M10: =EOMONTH(B14,0)+1 -> 46235 | P10: CDE COVID | U10: 0
B11: INSTALAÇÃO | C11: 7735 | H11: =E14 -> 46254 | K11: Altere a bandeira na célula abaixo | P11: CDE ESCASSEZ HÍDRICA | T11: =0.184189231569235/1000 -> 0.00018418923 | U11: =-0.531829748712515/1000 -> -0.00053182975
K12: BAM | L12: BAM
B13: Leitura Anterior | C13: Nº de dias tarifa Anterior | D13: Nº de dias tarifa Nova | E13: Leitura Atual | J13: Leitura Anterior | K13: Nº de dias tarifa Anterior | L13: Nº de dias tarifa Nova | M13: Leitura Atual
B14: 46224 | C14: =IF((F2-B14-1)<0,0,(F2-B14-1)) -> 16 | D14: =E14-F2+1 -> 14 | E14: 46254 | J14: =B14 -> 46224 | K14: =IF((M10-J14-1)<0,0,(M10-J14-1)) -> 10 | L14: =M14-M10+1 -> 20 | M14: =E14 -> 46254 | P14: 160881579
P15: 160890575 | Q15: falta mês11
P16: 160890581 | Q16: falta mês11
B17: Perc. de Redução da Energia Injetada | E17: TUSD | F17: 1 | G17: TE | H17: 1 | M17: Documento Impressão | O17: 1025310622 | P17: 161102501 | Q17: falta mês11
P18: 161104228 | Q18: falta mês11
B19: Descrição | C19: Unidade | D19: Quantidade | E19: Preço Unit (R$) com tributos | F19: Valor Total (R$) | G19: PIS/COFINS (R$) | H19: Base de Cálculo ICMS (R$) | I19: Alíquota ICMS (%) | J19: ICMS (R$) | K19: Preço Unit (R$) | L19: Tributos | M19: Base de Cálc (R$) | N19: Alíquota (%) | O19: Valor (R$)
R20: TUSD Fio B | S20: Receita Fio B
B21: TUSD - Consumo | C21: kWh | D21: 263 | E21: =(ROUND(D21*K21,2)+ROUND(G21,2)+ROUND(J21,2))/ROUND(D21,4) -> 0.6243346 | F21: =ROUND(D21*E21,2) -> 164.2 | G21: =((D21*K21)/(1-$N$21-$N$23))*($N$21+$N$23) -> 8.4087381 | H21: =((D21*K21)/(1-$N$21-$N$23)/(1-$I$21)) -> 164.19789 | I21: 0.17 | J21: =(H21*$I$21) -> 27.913641 | K21: =IF(AND($B$14<$F$2,$E$14<$F$2),C6,IF($B$14<$F$2,I6,F6)) -> 0.48621867 | L21: PIS | M21: =D70 -> 233.64596 | N21: 0.011 | O21: =ROUND(M21*N21,2) -> 2.57 | R21: =IF(AND($B14<$F$2,$E$14<$F$2),R6,IF($B$14<$F$2,X6,U6)) -> 0.20631379 | S21: =D21*R21 -> 54.260528 | T21: não está considerando a energia injetada
B22: TE - Consumo | C22: kWh | D22: =D21 -> 263 | E22: =(ROUND(D22*K22,2)+ROUND(G22,2)+ROUND(J22,2))/ROUND(D22,4) -> 0.42178707 | F22: =ROUND(D22*E22,2) -> 110.93 | G22: =((D22*K22)/(1-$N$21-$N$23))*($N$21+$N$23) -> 5.6807475 | H22: =ROUND((D22*K22)/(1-$N$21-$N$23)/(1-$I$21),8) -> 110.92827 | J22: =ROUND(H22*$I$21,2) -> 18.86 | K22: =IF(AND($B$14<$F$2,$E$14<$F$2),D6,IF($B$14<$F$2,J6,G6)) -> 0.328478 | L22: PIS Inj | M22: =D71*0 -> 0 | N22: =N21 -> 0.011 | O22: =ROUND(M22*N22,2) -> 0
B23: Adicional BAM | C23: kWh | D23: =IF($K$12=M4,($D$21*($K$14)/($L$14+$K$14)),0)+IF($L$12=M4,($D$21*($L$14)/($L$14+$K$14)),0) -> 263 | E23: =IFERROR((ROUND(D23*K23,2)+ROUND(G23,2)+ROUND(J23,2))/ROUND(D23,4), 0) -> 0.024220532 | F23: =ROUND(D23*E23,2) -> 6.37 | G23: =((D23*K23)/(1-$N$21-$N$23))*($N$21+$N$23) -> 0.32599471 | H23: =ROUND((D23*K23)/(1-$N$21-$N$23)/(1-$I$21),8) -> 6.3657165 | J23: =ROUND(H23*$I$21,2) -> 1.08 | K23: =N4 -> 0.01885 | L23: COFINS | M23: =M21 -> 233.64596 | N23: 0.0507 | O23: =ROUND(M23*N23,2) -> 11.85
B24: Adicional BVM1 | C24: kWh | D24: =IF($K$12=M5,($D$21*($K$14)/($L$14+$K$14)),0)+IF($L$12=M5,($D$21*($L$14)/($L$14+$K$14)),0) -> 0 | E24: =IFERROR((ROUND(D24*K24,2)+ROUND(G24,2)+ROUND(J24,2))/ROUND(D24,4), 0) -> 0 | F24: =ROUND(D24*E24,2) -> 0 | G24: =((D24*K24)/(1-$N$21-$N$23))*($N$21+$N$23) -> 0 | H24: =ROUND((D24*K24)/(1-$N$21-$N$23)/(1-$I$21),8) -> 0 | J24: =ROUND(H24*$I$21,2) -> 0 | K24: =N5 -> 0.04463 | L24: COFINS Inj | M24: =M22 -> 0 | N24: =N23 -> 0.0507 | O24: =ROUND(M24*N24,2) -> 0
B25: Adicional BVM2 | C25: kWh | D25: =IF($K$12=M6,($D$21*($K$14)/($L$14+$K$14)),0)+IF($L$12=M6,($D$21*($L$14)/($L$14+$K$14)),0) -> 0 | E25: =IFERROR((ROUND(D25*K25,2)+ROUND(G25,2)+ROUND(J25,2))/ROUND(D25,4), 0) -> 0 | F25: =ROUND(D25*E25,2) -> 0 | G25: =((D25*K25)/(1-$N$21-$N$23))*($N$21+$N$23) -> 0 | H25: =ROUND((D25*K25)/(1-$N$21-$N$23)/(1-$I$21),8) -> 0 | J25: =ROUND(H25*$I$21,2) -> 0 | K25: =N6 -> 0.07877
B26: Adicional EH | C26: kWh | D26: =IF($K$12=M7,($D$21*($K$14)/($L$14+$K$14)),0)+IF($L$12=M7,($D$21*($L$14)/($L$14+$K$14)),0) -> 0 | E26: =IFERROR((ROUND(D26*K26,2)+ROUND(G26,2)+ROUND(J26,2))/ROUND(D26,4), 0) -> 0 | F26: =ROUND(D26*E26,2) -> 0 | G26: =((D26*K26)/(1-$N$21-$N$23))*($N$21+$N$23) -> 0 | H26: =ROUND((D26*K26)/(1-$N$21-$N$23)/(1-$I$21),8) -> 0 | J26: =ROUND(H26*$I$21,2) -> 0 | K26: =N7 -> 0.142
B28: TUSD - Consumo inj | C28: kWh | D28: -233.0001 | E28: =IFERROR((ROUND(D28*K28,2)+ROUND(G28,2)+ROUND(J28,2))/ROUND(D28,4),0) -> 0.59236026 | F28: =ROUND(D28*E28,2) -> -138.02 | G28: 0 | H28: =ROUND((D28*K28)/(1-$N$21-$N$23)/(1-$I$21),8) -> -145.46815 | I28: 0.17 | J28: =H28*$I$21 -> -24.729586 | K28: =K21 -> 0.48621867
B29: TE - Consumo inj | C29: kWh | D29: =D28 -> -233.0001 | E29: =IFERROR((ROUND(D29*K29,2)+ROUND(G29,2)+ROUND(J29,2))/ROUND(D29,4),0) -> 0.40021442 | F29: =ROUND(D29*E29,2) -> -93.25 | G29: 0 | H29: =ROUND((D29*K29)/(1-$N$22-$N$24)/(1-$I$21),8) -> -98.274895 | I29: =I21 -> 0.17 | J29: =H29*$I$21 -> -16.706732 | K29: =K22 -> 0.328478
B30: Adicional BAM inj | C30: kWh | D30: =IF($K$12=M4,($D$28*($K$14)/($K$14+$L$14)),0)+IF($L$12=M4,($D$28*($L$14)/($K$14+$L$14)),0) -> -233.0001 | E30: =IFERROR((ROUND(D30*K30,2)+ROUND(G30,2)+ROUND(J30,2))/ROUND(D30,4),0) -> 0.022961364 | F30: =ROUND(D30*E30,2) -> -5.35 | G30: 0 | H30: =(D30*K30)/(1-$N$22-$N$24)/(1-$I$21) -> -5.6395916 | J30: =H30*$I$21 -> -0.95873057 | K30: =N4 -> 0.01885
B31: Adicional BVM1 inj | C31: kWh | D31: =IF($K$12=M5,($D$28*($K$14)/($K$14+$L$14)),0)+IF($L$12=M5,($D$28*($L$14)/($K$14+$L$14)),0) -> 0 | E31: =IFERROR((ROUND(D31*K31,2)+ROUND(G31,2)+ROUND(J31,2))/ROUND(D31,4),0) -> 0 | F31: =ROUND(D31*E31,2) -> 0 | G31: 0 | H31: =(D31*K31)/(1-$N$22-$N$24)/(1-$I$21) -> 0 | J31: =H31*$I$21 -> 0 | K31: =N5 -> 0.04463
B32: Adicional BVM2 inj | C32: kWh | D32: =IF($K$12=M6,($D$28*($K$14)/($K$14+$L$14)),0)+IF($L$12=M6,($D$28*($L$14)/($K$14+$L$14)),0) -> 0 | E32: =IFERROR((ROUND(D32*K32,2)+ROUND(G32,2)+ROUND(J32,2))/ROUND(D32,4),0) -> 0 | F32: =ROUND(D32*E32,2) -> 0 | G32: 0 | H32: =(D32*K32)/(1-$N$22-$N$24)/(1-$I$21) -> 0 | J32: =H32*$I$21 -> 0 | K32: =N6 -> 0.07877
B33: Adicional EH inj | C33: kWh | D33: =IF($K$12=M7,($D$28*($K$14)/($K$14+$L$14)),0)+IF($L$12=M7,($D$28*($L$14)/($K$14+$L$14)),0) -> 0 | E33: =IFERROR((ROUND(D33*K33,2)+ROUND(G33,2)+ROUND(J33,2))/ROUND(D33,4),0) -> 0 | F33: =ROUND(D33*E33,2) -> 0 | G33: 0 | H33: =(D33*K33)/(1-$N$22-$N$24)/(1-$I$21) -> 0 | J33: =H33*$I$21 -> 0 | K33: =N7 -> 0.142
B35: Multas
B36: Juros | F36: -2.47
B37: Doações
B38: CIP | F38: 27.91
B41: TOTAL | F41: =SUM(F21:F40) -> 70.32 | G41: =SUM(G21:G40) -> 14.41548 | H41: =SUM(H21:H40) -> 32.109232 | J41: =SUM(J21:J40) -> 5.4585923
B43: Informativo Escassez | C43: =(D21+D28) -> 29.9999 | D43: =IF(AND($B$14<$F$2,$E$14<$F$2),C7,IF($B$14<$F$2,I7,F7)) -> 0.00018608682 | E43: =IF(AND($B$14<$F$2,$E$14<$F$2),D7,IF($B$14<$F$2,J7,G7)) -> -0.0025965236 | F43: =C43*(D43+E43) -> -0.072312863
B45: Fatura B1 Residencial
D46: Qtde | E46: TUSD | F46: TE | G46: TUSD + TE | H46: R$
B47: Fornecimento de Energia Elétrica | H47: =SUM(H49:H65)+SUM(H70:H75) -> 56.844769
B49: Energia Fornecida | D49: =D21 -> 263 | E49: =IF(AND($B$14<$F$2,$E$14<$F$2),C6,IF($B$14<$F$2,I6,F6)) -> 0.48621867 | F49: =IF(AND($B$14<$F$2,$E$14<$F$2),D6,IF($B$14<$F$2,J6,G6)) -> 0.328478 | G49: =E49+F49 -> 0.81469667 | H49: =ROUND((D49*E49),2)+ROUND((D49*F49),2) -> 214.27
B51: Adicional BAM | D51: =IF($K$12=M4,(D49*(K14)/(K14+L14)),0)+IF($L$12=M4,(D49*(L14)/(K14+L14)),0) -> 263 | F51: =N4 -> 0.01885 | H51: =ROUND(D51*(E51+F51),2) -> 4.96
B52: Adicional BVM 1 | D52: =IF($K$12=M5,(D49*(K14)/(K14+L14)),0)+IF($L$12=M5,(D49*(L14)/(K14+L14)),0) -> 0 | F52: =N5 -> 0.04463 | H52: =ROUND(D52*(E52+F52),2) -> 0
B53: Adicional BVM 2 | D53: =IF($K$12=M6,(D49*(K14)/(K14+L14)),0)+IF($L$12=M6,(D49*(L14)/(K14+L14)),0) -> 0 | F53: =N6 -> 0.07877 | H53: =ROUND(D53*(E53+F53),2) -> 0
B54: Adicional Escassez Hídrica | D54: =IF($K$12=M8,(D49*(K14)/(K14+L14)),0)+IF($L$12=M8,(D49*(L14)/(K14+L14)),0) -> 0 | F54: =N8 -> 0 | H54: =ROUND(D54*(E54+F54),2) -> 0
B56: Energia Injetada | D56: =D28 -> -233.0001 | E56: =E49*F17 -> 0.48621867 | F56: =F49 -> 0.328478 | G56: =E56+F56 -> 0.81469667 | H56: =ROUND((D56*E56),2)+ROUND((D56*F56),2) -> -189.83
B58: Adicional BAM | D58: =IF($K$12=M4,(D56*(K14)/(K14+L14)),0)+IF($L$12=M4,(D56*(L14)/(K14+L14)),0) -> -233.0001 | F58: =F51 -> 0.01885 | H58: =ROUND(D58*(E58+F58),2) -> -4.39
B59: Adicional BVM 1 | D59: =IF($K$12=M5,(D56*(K14)/(K14+L14)),0)+IF($L$12=M5,(D56*(L14)/(K14+L14)),0) -> 0 | F59: =F52 -> 0.04463 | H59: =ROUND(D59*(E59+F59),2) -> 0
B60: Adicional BVM 2 | D60: =IF($K$12=M6,(D56*(K14)/(K14+L14)),0)+IF($L$12=M6,(D56*(L14)/(K14+L14)),0) -> 0 | F60: =F53 -> 0.07877 | H60: =ROUND(D60*(E60+F60),2) -> 0
B61: Adicional Escassez Hídrica | D61: =IF($K$12=M8,(D56*(K14)/(K14+L14)),0)+IF($L$12=M8,(D56*(L14)/(K14+L14)),0) -> 0 | F61: =F54 -> 0 | H61: =ROUND(D61*(E61+F61),2) -> 0
H67: =SUM(H49:H66) -> 25.01
D69: Base de Cálculo
B70: PIS | D70: =(H49+H51+H52+H53+H54)/(1-E70-E72) -> 233.64596 | E70: =N21 -> 0.011 | H70: =D70*E70 -> 2.5701055
B71: PIS Eneg Inj | D71: =(H56+H58+H59+H60+H61+H63+H65)/(1-E70-E72) -> -206.99137 | E71: =E70 -> 0.011 | H71: =D71*E71 -> -2.276905
B72: COFINS | D72: =D70 -> 233.64596 | E72: =N23 -> 0.0507 | H72: =D72*E72 -> 11.84585
B73: COFINS Eneg Inj | D73: =D71 -> -206.99137 | E73: =E72 -> 0.0507 | H73: =D73*E73 -> -10.494462
B74: ICMS | D74: =D70/(1-E74) -> 281.50115 | E74: 0.17 | H74: =D74*E74 -> 47.855196
B75: ICMS Eneg Inj | D75: =((D56*F56)+(H58+H59+H60+H61)+(D63*F63)+(D65*F65))/(1-E71-E73)/(1-E75) -> -103.91185 | E75: =E74 -> 0.17 | H75: =D75*E75 -> -17.665015
B77: Informativo Escassez Hídrica | D77: =D49+D56 -> 29.9999 | E77: =IF(AND($B$14<$F$2,$E$14<$F$2),C7,IF($B$14<$F$2,I7,F7)) -> 0.00018608682 | F77: =IF(AND($B$14<$F$2,$E$14<$F$2),D7,IF($B$14<$F$2,J7,G7)) -> -0.0025965236 | H77: =D77*(E77+F77) -> -0.072312863

Sheet Fatura B3 (GD) OK
B2: B3 | E2: Vigência das Tarifas: | F2: ='Fatura B1 (GD) OK'!F2 -> 46241 | M2: Bandeira | N2: R$/kWh | O2: ANEEL em 29/06 | Q2: TUSD FIO B
M3: VERDE | N3: 0
B4: TARIFA | C4: TARIFA ANTIGA - REH 3091/2022 | F4: ='Fatura B1 (GD) OK'!F4 -> TARIFA NOVA - REH xxxx/2024 | I4: Tarifas Proporcionalizadas | M4: BAM | N4: =[1]BANDEIRA!$D$5 -> 0.01885 | Q4: TARIFA | R4: =C4 -> TARIFA ANTIGA - REH 3091/2022 | U4: =F4 -> TARIFA NOVA - REH xxxx/2024 | X4: Tarifas Proporcionalizadas
C5: Tusd | D5: TE | E5: TUSD + TE | F5: Tusd | G5: TE | H5: TUSD + TE | I5: Tusd | J5: TE | K5: TUSD + TE | M5: BVM1 | N5: =[1]BANDEIRA!$D$6 -> 0.04463 | R5: Tusd (R$/kWh) | U5: Tusd (R$/kWh) | X5: Tusd (R$/kWh)
B6: B3 | C6: ='TABELA DE TARIFAS ANTIGAS'!G89/1000 -> 0.46863 | D6: ='TABELA DE TARIFAS ANTIGAS'!H89/1000 -> 0.32068 | E6: =C6+D6 -> 0.78931 | F6: ='TABELA DE TARIFAS NOVAS'!G91/1000 -> 0.50632 | G6: ='TABELA DE TARIFAS NOVAS'!H91/1000 -> 0.33739 | H6: =F6+G6 -> 0.84371 | I6: =((C6*$C$14)+(F6*$D$14))/($D$14+$C$14) -> 0.48983062 | J6: =((D6*$C$14)+(G6*$D$14))/($D$14+$C$14) -> 0.33007938 | K6: =I6+J6 -> 0.81991 | M6: BVM2 | N6: =[1]BANDEIRA!$D$7 -> 0.07877 | Q6: =B6 -> B3 | R6: ='FIO B'!H35/1000 -> 0.20383072 | U6: ='FIO B'!K35/1000 -> 0.20915159 | X6: =((R6*$C$14)+(U6*$D$14))/($D$14+$C$14) -> 0.20682371
B7: CDE Escassez Hídrica | C7: 0.00018774721 | D7: -0.0044031307 | E7: 0.0036054084 | F7: =T11 -> 0.00018418923 | G7: =U11 -> -0.00053182975 | H7: =F7+G7 -> -0.00034764052 | I7: =((C7*$C$14)+(F7*$D$14))/($D$14+$C$14) -> 0.00018574585 | J7: =((D7*$C$14)+(G7*$D$14))/($D$14+$C$14) -> -0.0022255239 | K7: =I7+J7 -> -0.0020397781 | M7: Escassez Hídrica | N7: 0.142
B8: TE SCEE | G8: =G6*15% -> 0.0506085 | J8: =((D8*$C$14)+(G8*$D$14))/($D$14+$C$14) -> 0.028467281 | P8: CUSTO | R8: Part. TUSD (%) | S8: Part. TE (%) | T8: Tusd (R$/kWh) | U8: TE (R$/kWh)
P9: CDE CONTAS
H10: Fatura | L10: Vigência das Tarifas (troca Bandeira): | M10: =EOMONTH(B14,0)+1 -> 46235 | P10: CDE COVID | U10: 0
B11: INSTALAÇÃO | C11: 1185290 | H11: =E14 -> 46258 | K11: Altere a bandeira na célula abaixo | P11: CDE ESCASSEZ HÍDRICA | T11: ='Fatura B1 (GD) OK'!T11 -> 0.00018418923 | U11: ='Fatura B1 (GD) OK'!U11 -> -0.00053182975
K12: BAM | L12: BAM
B13: Leitura Anterior | C13: Nº de dias tarifa Anterior | D13: Nº de dias tarifa Nova | E13: Leitura Atual | J13: Leitura Anterior | K13: Nº de dias tarifa Anterior | L13: Nº de dias tarifa Nova | M13: Leitura Atual
B14: 46226 | C14: =IF((F2-B14-1)<0,0,(F2-B14-1)) -> 14 | D14: =E14-F2+1 -> 18 | E14: 46258 | J14: =B14 -> 46226 | K14: =IF((M10-J14-1)<0,0,(M10-J14-1)) -> 8 | L14: =M14-M10+1 -> 24 | M14: =E14 -> 46258
B17: Perc. de Redução da Energia Injetada | E17: TUSD | F17: 1 | G17: TE | H17: 1 | M17: Documento Impressão | O17: 1025310624
B19: Descrição | C19: Unidade | D19: Quantidade | E19: Preço Unit (R$) com tributos | F19: Valor Total (R$) | G19: PIS/COFINS (R$) | H19: Base de Cálculo ICMS (R$) | I19: Alíquota ICMS (%) | J19: ICMS (R$) | K19: Preço Unit (R$) | L19: Tributos | M19: Base de Cálc (R$) | N19: Alíquota (%) | O19: Valor (R$)
R20: TUSD Fio B | S20: Receita Fio B
B21: TUSD - Consumo | C21: kWh | D21: 987 | E21: =(ROUND(D21*K21,2)+ROUND(G21,2)+ROUND(J21,2))/ROUND(D21,4) -> 0.62895643 | F21: =ROUND(D21*E21,2) -> 620.78 | G21: =((D21*K21)/(1-$N$21-$N$23))*($N$21+$N$23) -> 31.791172 | H21: =((D21*K21)/(1-$N$21-$N$23)/(1-$I$21)) -> 620.78795 | I21: 0.17 | J21: =(H21*$I$21) -> 105.53395 | K21: =IF(AND($B$14<$F$2,$E$14<$F$2),C6,IF($B$14<$F$2,I6,F6)) -> 0.48983062 | L21: PIS | M21: =D70 -> 882.28711 | N21: 0.011 | O21: =ROUND(M21*N21,2) -> 9.71 | R21: =IF(AND($B$14<$F$2,$E$14<$F$2),R6,IF($B$14<$F$2,X6,U6)) -> 0.20682371 | S21: =D21*R21 -> 204.135 | T21: não está considerando a energia injetada
B22: TE - Consumo | C22: kWh | D22: =D21 -> 987 | E22: =(ROUND(D22*K22,2)+ROUND(G22,2)+ROUND(J22,2))/ROUND(D22,4) -> 0.42383992 | F22: =ROUND(D22*E22,2) -> 418.33 | G22: =((D22*K22)/(1-$N$21-$N$23))*($N$21+$N$23) -> 21.422936 | H22: =ROUND((D22*K22)/(1-$N$21-$N$23)/(1-$I$21),8) -> 418.32684 | J22: =ROUND(H22*$I$21,2) -> 71.12 | K22: =IF(AND($B$14<$F$2,$E$14<$F$2),D6,IF($B$14<$F$2,J6,G6)) -> 0.33007938 | L22: PIS Inj | M22: =D71*0 -> 0 | N22: =N21 -> 0.011 | O22: =ROUND(M22*N22,2) -> 0
B23: Adicional BAM | C23: kWh | D23: =IF($K$12=M4,($D$21*($K$14)/($K$14+$L$14)),0)+IF($L$12=M4,($D$21*($L$14)/($K$14+$L$14)),0) -> 987 | E23: =IFERROR((ROUND(D23*K23,2)+ROUND(G23,2)+ROUND(J23,2))/ROUND(D23,4), 0) -> 0.024194529 | F23: =ROUND(D23*E23,2) -> 23.88 | G23: =((D23*K23)/(1-$N$21-$N$23))*($N$21+$N$23) -> 1.2234098 | H23: =ROUND((D23*K23)/(1-$N$21-$N$23)/(1-$I$21),8) -> 23.88959 | J23: =ROUND(H23*$I$21,2) -> 4.06 | K23: =N4 -> 0.01885 | L23: COFINS | M23: =M21 -> 882.28711 | N23: 0.0507 | O23: =ROUND(M23*N23,2) -> 44.73
B24: Adicional BVM1 | C24: kWh | D24: =IF($K$12=M5,($D$21*($K$14)/($K$14+$L$14)),0)+IF($L$12=M5,($D$21*($L$14)/($K$14+$L$14)),0) -> 0 | E24: =IFERROR((ROUND(D24*K24,2)+ROUND(G24,2)+ROUND(J24,2))/ROUND(D24,4), 0) -> 0 | F24: =ROUND(D24*E24,2) -> 0 | G24: =((D24*K24)/(1-$N$21-$N$23))*($N$21+$N$23) -> 0 | H24: =ROUND((D24*K24)/(1-$N$21-$N$23)/(1-$I$21),8) -> 0 | J24: =ROUND(H24*$I$21,2) -> 0 | K24: =N5 -> 0.04463 | L24: COFINS Inj | M24: =M22 -> 0 | N24: =N23 -> 0.0507 | O24: =ROUND(M24*N24,2) -> 0
B25: Adicional BVM2 | C25: kWh | D25: =IF($K$12=M6,($D$21*($K$14)/($K$14+$L$14)),0)+IF($L$12=M6,($D$21*($L$14)/($K$14+$L$14)),0) -> 0 | E25: =IFERROR((ROUND(D25*K25,2)+ROUND(G25,2)+ROUND(J25,2))/ROUND(D25,4), 0) -> 0 | F25: =ROUND(D25*E25,2) -> 0 | G25: =((D25*K25)/(1-$N$21-$N$23))*($N$21+$N$23) -> 0 | H25: =ROUND((D25*K25)/(1-$N$21-$N$23)/(1-$I$21),8) -> 0 | J25: =ROUND(H25*$I$21,2) -> 0 | K25: =N6 -> 0.07877
B26: Adicional EH | C26: kWh | D26: =IF($K$12=M7,($D$21*($K$14)/($K$14+$L$14)),0)+IF($L$12=M7,($D$21*($L$14)/($K$14+$L$14)),0) -> 0 | E26: =IFERROR((ROUND(D26*K26,2)+ROUND(G26,2)+ROUND(J26,2))/ROUND(D26,4), 0) -> 0 | F26: =ROUND(D26*E26,2) -> 0 | G26: =((D26*K26)/(1-$N$21-$N$23))*($N$21+$N$23) -> 0 | H26: =ROUND((D26*K26)/(1-$N$21-$N$23)/(1-$I$21),8) -> 0 | J26: =ROUND(H26*$I$21,2) -> 0 | K26: =N7 -> 0.142 | S26: 1827762
Q27: 342.9911 | S27: 160147060
B28: TUSD - Consumo inj | C28: kWh | D28: -887 | E28: =IFERROR((ROUND(D28*K28,2)+ROUND(G28,2)+ROUND(J28,2))/ROUND(D28,4),0) -> 0.5967531 | F28: =ROUND(D28*E28,2) -> -529.32 | G28: 0 | H28: =ROUND((D28*K28)/(1-$N$22-$N$24)/(1-$I$21),8) -> -557.8915 | I28: 0 | J28: =H28*$I$21 -> -94.841555 | K28: =K21 -> 0.48983062 | Q28: 316.1171 | S28: 1494523
B29: TE - Consumo inj | C29: kWh | D29: =D28 -> -887 | E29: =IFERROR((ROUND(D29*K29,2)+ROUND(G29,2)+ROUND(J29,2))/ROUND(D29,4),0) -> 0.40213078 | F29: =ROUND(D29*E29,2) -> -356.69 | G29: 0 | H29: =ROUND((D29*K29)/(1-$N$22-$N$24)/(1-$I$21),8) -> -375.94317 | I29: =I21 -> 0.17 | J29: =H29*$I$21 -> -63.910339 | K29: =K22 -> 0.33007938 | Q29: 227.8918 | S29: 160832701
B30: Adicional BAM inj | C30: kWh | D30: =IF($K$12=M4,($D$28*($K$14)/($K$14+$L$14)),0)+IF($L$12=M4,($D$28*($L$14)/($K$14+$L$14)),0) -> -887 | E30: =IFERROR((ROUND(D30*K30,2)+ROUND(G30,2)+ROUND(J30,2))/ROUND(D30,4),0) -> 0.022965051 | F30: =ROUND(D30*E30,2) -> -20.37 | G30: 0 | H30: =(D30*K30)/(1-$N$22-$N$24)/(1-$I$21) -> -21.469166 | J30: =H30*$I$21 -> -3.6497582 | K30: =N4 -> 0.01885 | Q30: =SUM(Q27:Q29) -> 887
B31: Adicional BVM1 inj | C31: kWh | D31: =IF($K$12=M5,($D$28*($K$14)/($K$14+$L$14)),0)+IF($L$12=M5,($D$28*($L$14)/($K$14+$L$14)),0) -> 0 | E31: =IFERROR((ROUND(D31*K31,2)+ROUND(G31,2)+ROUND(J31,2))/ROUND(D31,4),0) -> 0 | F31: =ROUND(D31*E31,2) -> 0 | G31: 0 | H31: =(D31*K31)/(1-$N$22-$N$24)/(1-$I$21) -> 0 | J31: =H31*$I$21 -> 0 | K31: =N5 -> 0.04463
B32: Adicional BVM2 inj | C32: kWh | D32: =IF($K$12=M6,($D$28*($K$14)/($K$14+$L$14)),0)+IF($L$12=M6,($D$28*($L$14)/($K$14+$L$14)),0) -> 0 | E32: =IFERROR((ROUND(D32*K32,2)+ROUND(G32,2)+ROUND(J32,2))/ROUND(D32,4),0) -> 0 | F32: =ROUND(D32*E32,2) -> 0 | G32: 0 | H32: =(D32*K32)/(1-$N$22-$N$24)/(1-$I$21) -> 0 | J32: =H32*$I$21 -> 0 | K32: =N6 -> 0.07877
B33: Adicional EH inj | C33: kWh | D33: =IF($K$12=M7,($D$28*($K$14)/($K$14+$L$14)),0)+IF($L$12=M7,($D$28*($L$14)/($K$14+$L$14)),0) -> 0 | E33: =IFERROR((ROUND(D33*K33,2)+ROUND(G33,2)+ROUND(J33,2))/ROUND(D33,4),0) -> 0 | F33: =ROUND(D33*E33,2) -> 0 | G33: 0 | H33: =(D33*K33)/(1-$N$22-$N$24)/(1-$I$21) -> 0 | J33: =H33*$I$21 -> 0 | K33: =N7 -> 0.142
B35: Multas | W35: 1827762
B36: Juros | W36: 160147060
B37: Doações | W37: 1494523
B38: CIP | F38: 92.81 | W38: 160832701
B41: TOTAL | F41: =SUM(F21:F40) -> 249.42 | G41: =SUM(G21:G40) -> 54.437517 | H41: =SUM(H21:H40) -> 107.70055 | J41: =SUM(J21:J40) -> 18.312299
B45: Fatura B1 Residencial
D46: Qtde | E46: TUSD | F46: TE | G46: TUSD + TE | H46: R$
B47: Fornecimento de Energia Elétrica | H47: =SUM(H49:H65)+SUM(H70:H75) -> 202.53436
B49: Energia Fornecida | D49: =D21 -> 987 | E49: =IF(AND($B$14<$F$2,$E$14<$F$2),C6,IF($B$14<$F$2,I6,F6)) -> 0.48983062 | F49: =IF(AND($B$14<$F$2,$E$14<$F$2),D6,IF($B$14<$F$2,J6,G6)) -> 0.33007938 | G49: =E49+F49 -> 0.81991 | H49: =ROUND((D49*E49),2)+ROUND((D49*F49),2) -> 809.25
B51: Adicional BAM | D51: =IF($K$12=M4,(D49*(K14)/(K14+L14)),0)+IF($L$12=M4,(D49*(L14)/(K14+L14)),0) -> 987 | F51: =N4 -> 0.01885 | H51: =ROUND(D51*(E51+F51),2) -> 18.6
B52: Adicional BVM 1 | D52: =IF($K$12=M5,(D49*(K14)/(K14+L14)),0)+IF($L$12=M5,(D49*(L14)/(K14+L14)),0) -> 0 | F52: =N5 -> 0.04463 | H52: =ROUND(D52*(E52+F52),2) -> 0
B53: Adicional BVM 2 | D53: =IF($K$12=M6,(D49*(K14)/(K14+L14)),0)+IF($L$12=M6,(D49*(L14)/(K14+L14)),0) -> 0 | F53: =N6 -> 0.07877 | H53: =ROUND(D53*(E53+F53),2) -> 0
B54: Adicional Escassez Hídrica | D54: =IF($K$12=M8,(D49*(K14)/(K14+L14)),0)+IF($L$12=M8,(D49*(L14)/(K14+L14)),0) -> 0 | F54: =N8 -> 0 | H54: =ROUND(D54*(E54+F54),2) -> 0
B56: Energia Injetada | D56: =D28 -> -887 | E56: =E49*F17 -> 0.48983062 | F56: =F49 -> 0.33007938 | G56: =E56+F56 -> 0.81991 | H56: =ROUND((D56*E56),2)+ROUND((D56*F56),2) -> -727.26
B58: Adicional BAM | D58: =IF($K$12=M4,(D56*(K14)/(K14+L14)),0)+IF($L$12=M4,(D56*(L14)/(K14+L14)),0) -> -887 | F58: =F51 -> 0.01885 | H58: =ROUND(D58*(E58+F58),2) -> -16.72
B59: Adicional BVM 1 | D59: =IF($K$12=M5,(D56*(K14)/(K14+L14)),0)+IF($L$12=M5,(D56*(L14)/(K14+L14)),0) -> 0 | F59: =F52 -> 0.04463 | H59: =ROUND(D59*(E59+F59),2) -> 0
B60: Adicional BVM 2 | D60: =IF($K$12=M6,(D56*(K14)/(K14+L14)),0)+IF($L$12=M6,(D56*(L14)/(K14+L14)),0) -> 0 | F60: =F53 -> 0.07877 | H60: =ROUND(D60*(E60+F60),2) -> 0
B61: Adicional Escassez Hídrica | D61: =IF($K$12=M8,(D56*(K14)/(K14+L14)),0)+IF($L$12=M8,(D56*(L14)/(K14+L14)),0) -> 0 | F61: =F54 -> 0 | H61: =ROUND(D61*(E61+F61),2) -> 0
H67: =SUM(H49:H66) -> 83.87
D69: Base de Cálculo
B70: PIS | D70: =(H49+H51+H52+H53+H54)/(1-E70-E72) -> 882.28711 | E70: =N21 -> 0.011 | H70: =D70*E70 -> 9.7051583
B71: PIS Eneg Inj | D71: =(H56+H58+H59+H60+H61+H63+H65)/(1-E70-E72) -> -792.90206 | E71: =E70 -> 0.011 | H71: =D71*E71 -> -8.7219226
B72: COFINS | D72: =D70 -> 882.28711 | E72: =N23 -> 0.0507 | H72: =D72*E72 -> 44.731957
B73: COFINS Eneg Inj | D73: =D71 -> -792.90206 | E73: =E72 -> 0.0507 | H73: =D73*E73 -> -40.200134
B74: ICMS | D74: =D70/(1-E74) -> 1062.9965 | E74: 0.17 | H74: =D74*E74 -> 180.70941
B75: ICMS Eneg Inj | D75: =((D56*F56)+(H58+H59+H60+H61)+(D63*F63)+(D65*F65))/(1-E71-E73)/(1-E75) -> -397.4124 | E75: =E74 -> 0.17 | H75: =D75*E75 -> -67.560108
B77: Informativo Escassez Hídrica | D77: =D49+D56 -> 100 | E77: =IF(AND($B$14<$F$2,$E$14<$F$2),C7,IF($B$14<$F$2,I7,F7)) -> 0.00018574585 | F77: =IF(AND($B$14<$F$2,$E$14<$F$2),D7,IF($B$14<$F$2,J7,G7)) -> -0.0022255239 | H77: =D77*(E77+F77) -> -0.20397781

Sheet Fatura B2 (GD) Massa OK
B2: B2 | E2: Vigência das Tarifas: | F2: ='Fatura B1 (GD) OK'!F2 -> 46241 | M2: Bandeira | N2: R$/kWh | O2: ANEEL em 29/06 | Q2: TUSD FIO B
M3: VERDE | N3: 0
B4: TARIFA | C4: TARIFA ANTIGA - REH 3091/2022 | F4: ='[2]Fatura B1 (GD)'!F4 -> TARIFA NOVA - REH xxxx/2024 | I4: Tarifas Proporcionalizadas | M4: BAM | N4: ='[3]Fatura B1 (Res) OK'!$N$4 -> 0.01885 | Q4: TARIFA | R4: =C4 -> TARIFA ANTIGA - REH 3091/2022 | U4: =F4 -> TARIFA NOVA - REH xxxx/2024 | X4: Tarifas Proporcionalizadas
C5: Tusd | D5: TE | E5: TUSD + TE | F5: Tusd | G5: TE | H5: TUSD + TE | I5: Tusd | J5: TE | K5: TUSD + TE | M5: BVM1 | N5: ='[3]Fatura B1 (Res) OK'!$N$5 -> 0.04463 | R5: Tusd (R$/kWh) | U5: Tusd (R$/kWh) | X5: Tusd (R$/kWh)
B6: B2 | C6: ='TABELA DE TARIFAS ANTIGAS'!G77/1000 -> 0.46863 | D6: ='TABELA DE TARIFAS ANTIGAS'!H77/1000 -> 0.32068 | E6: =C6+D6 -> 0.78931 | F6: ='TABELA DE TARIFAS NOVAS'!G79/1000 -> 0.50632 | G6: ='TABELA DE TARIFAS NOVAS'!H79/1000 -> 0.33739 | H6: =F6+G6 -> 0.84371 | I6: =((C6*$C$14)+(F6*$D$14))/($D$14+$C$14) -> 0.47742433 | J6: =((D6*$C$14)+(G6*$D$14))/($D$14+$C$14) -> 0.324579 | K6: =I6+J6 -> 0.80200333 | M6: BVM2 | N6: ='[3]Fatura B1 (Res) OK'!$N$6 -> 0.07877 | Q6: =B6 -> B2 | R6: ='FIO B'!H25/1000 -> 0.20383072 | U6: ='FIO B'!K25/1000 -> 0.20915159 | X6: =((R6*$C$14)+(U6*$D$14))/($D$14+$C$14) -> 0.20507226
B7: CDE Escassez Hídrica | C7: 0.00018774721 | D7: -0.0044031307 | E7: 0.0036054084 | F7: =T11 -> 0.00018418923 | G7: =U11 -> -0.00053182975 | H7: =F7+G7 -> -0.00034764052 | I7: =((C7*$C$14)+(F7*$D$14))/($D$14+$C$14) -> 0.00018691702 | J7: =((D7*$C$14)+(G7*$D$14))/($D$14+$C$14) -> -0.0034998272 | K7: =I7+J7 -> -0.0033129102 | M7: Escassez Hídrica | N7: 0.142
B8: TE SCEE | G8: =G6*15% -> 0.0506085 | J8: =((D8*$C$14)+(G8*$D$14))/($D$14+$C$14) -> 0.01180865 | P8: CUSTO | R8: Part. TUSD (%) | S8: Part. TE (%) | T8: Tusd (R$/kWh) | U8: TE (R$/kWh)
P9: CDE CONTAS
H10: Fatura | L10: Vigência das Tarifas (troca Bandeira): | M10: =EOMONTH(B14,0)+1 -> 46235 | P10: CDE COVID | U10: 0
B11: INSTALAÇÃO | H11: =E14 -> 46247 | K11: Altere a bandeira na célula abaixo | P11: CDE ESCASSEZ HÍDRICA | T11: ='Fatura B1 (GD) OK'!T11 -> 0.00018418923 | U11: ='Fatura B1 (GD) OK'!U11 -> -0.00053182975
C12: 1494523 | K12: ='Fatura B1 (GD) OK'!K12 -> BAM | L12: ='Fatura B1 (GD) OK'!L12 -> BAM
B13: Leitura Anterior | C13: Nº de dias tarifa Anterior | D13: Nº de dias tarifa Nova | E13: Leitura Atual | J13: Leitura Anterior | K13: Nº de dias tarifa Anterior | L13: Nº de dias tarifa Nova | M13: Leitura Atual
B14: 46217 | C14: =IF((F2-B14-1)<0,0,(F2-B14-1)) -> 23 | D14: =E14-F2+1 -> 7 | E14: 46247 | J14: =B14 -> 46217 | K14: =IF((M10-J14-1)<0,0,(M10-J14-1)) -> 17 | L14: =M14-M10+1 -> 13 | M14: =E14 -> 46247
B17: Perc. de Redução da Energia Injetada | E17: TUSD | F17: 1 | G17: TE | H17: 1 | M17: Documento Impressão | O17: 1025310636
B19: Descrição | C19: Unidade | D19: Quantidade | E19: Preço Unit (R$) com tributos | F19: Valor Total (R$) | G19: PIS/COFINS (R$) | H19: Base de Cálculo ICMS (R$) | I19: Alíquota ICMS (%) | J19: ICMS (R$) | K19: Preço Unit (R$) | L19: Tributos | M19: Base de Cálc (R$) | N19: Alíquota (%) | O19: Valor (R$)
R20: TUSD Fio B | S20: Receita Fio B
B21: TUSD - Consumo | C21: kWh | D21: 1409 | E21: =(ROUND(D21*K21,2)+ROUND(G21,2)+ROUND(J21,2))/ROUND(D21,4) -> 0.61303052 | F21: =ROUND(D21*E21,2) -> 863.76 | G21: =((D21*K21)/(1-$N$21-$N$23))*($N$21+$N$23) -> 44.234283 | H21: =(IF($I$21=12%,(D21*K21)/(1-$N$21-$N$23)/(1-$C$50)/$F$50*$C$50,(D21*K21)/(1-$N$21-$N$23)/(1-$I$21))) -> 863.76526 | I21: 0.17 | J21: =(H21*$I$21) -> 146.84009 | K21: =IF(AND($B$14<$F$2,$E$14<$F$2),C6,IF($B$14<$F$2,I6,F6)) -> 0.47742433 | L21: PIS | M21: =D81 -> 1232.6335 | N21: ='Fatura B1 (GD) OK'!N21 -> 0.011 | O21: =ROUND(M21*N21,2) -> 13.56 | R21: =IF(AND($B14<$F$2,$E$14<$F$2),R6,IF($B$14<$F$2,X6,U6)) -> 0.20507226 | S21: =D21*R21 -> 288.94681 | T21: não está considerando a energia injetada
B22: TE - Consumo | C22: kWh | D22: =D21 -> 1409 | E22: =(ROUND(D22*K22,2)+ROUND(G22,2)+ROUND(J22,2))/ROUND(D22,4) -> 0.41677076 | F22: =ROUND(D22*E22,2) -> 587.23 | G22: =((D22*K22)/(1-$N$21-$N$23))*($N$21+$N$23) -> 30.072869 | H22: =(IF($I$21=12%,(D22*K22)/(1-$N$21-$N$23)/(1-$C$50)/$F$50*$C$50,(D22*K22)/(1-$N$21-$N$23)/(1-$I$21))) -> 587.23455 | J22: =ROUND(H22*$I$21,2) -> 99.83 | K22: =IF(AND($B$14<$F$2,$E$14<$F$2),D6,IF($B$14<$F$2,J6,G6)) -> 0.324579 | L22: PIS Inj | M22: =D82*0 -> 0 | N22: =N21 -> 0.011 | O22: =ROUND(M22*N22,2) -> 0
B23: Adicional BAM | C23: kWh | D23: =IF($K$12=M4,($D$21*($K$14)/($K$14+$L$14)),0)+IF($L$12=M4,($D$21*($L$14)/($K$14+$L$14)),0) -> 1409 | E23: =IFERROR((ROUND(D23*K23,2)+ROUND(G23,2)+ROUND(J23,2))/ROUND(D23,4), 0) -> 0.024208659 | F23: =ROUND(D23*E23,2) -> 34.11 | G23: =((D23*K23)/(1-$N$21-$N$23))*($N$21+$N$23) -> 1.7464888 | H23: =(IF($I$21=12%,(D23*K23)/(1-$N$21-$N$23)/(1-$C$50)/$F$50*$C$50,(D23*K23)/(1-$N$21-$N$23)/(1-$I$21))) -> 34.103782 | J23: =ROUND(H23*$I$21,2) -> 5.8 | K23: =N4 -> 0.01885 | L23: COFINS | M23: =M21 -> 1232.6335 | N23: ='Fatura B1 (GD) OK'!N23 -> 0.0507 | O23: =ROUND(M23*N23,2) -> 62.49
B24: Adicional BAM | C24: kWh | D24: =IF($K$12=M5,($D$21*($K$14)/($K$14+$L$14)),0)+IF($L$12=M5,($D$21*($L$14)/($K$14+$L$14)),0) -> 0 | E24: =IFERROR((ROUND(D24*K24,2)+ROUND(G24,2)+ROUND(J24,2))/ROUND(D24,4), 0) -> 0 | F24: =ROUND(D24*E24,2) -> 0 | G24: =((D24*K24)/(1-$N$21-$N$23))*($N$21+$N$23) -> 0 | H24: =(IF($I$21=12%,(D24*K24)/(1-$N$21-$N$23)/(1-$C$50)/$F$50*$C$50,(D24*K24)/(1-$N$21-$N$23)/(1-$I$21))) -> 0 | J24: =ROUND(H24*$I$21,2) -> 0 | K24: =N5 -> 0.04463 | L24: COFINS Inj | M24: =M22 -> 0 | N24: =N23 -> 0.0507 | O24: =ROUND(M24*N24,2) -> 0
B25: Adicional BAM | C25: kWh | D25: =IF($K$12=M6,($D$21*($K$14)/($K$14+$L$14)),0)+IF($L$12=M6,($D$21*($L$14)/($K$14+$L$14)),0) -> 0 | E25: =IFERROR((ROUND(D25*K25,2)+ROUND(G25,2)+ROUND(J25,2))/ROUND(D25,4), 0) -> 0 | F25: =ROUND(D25*E25,2) -> 0 | G25: =((D25*K25)/(1-$N$21-$N$23))*($N$21+$N$23) -> 0 | H25: =(IF($I$21=12%,(D25*K25)/(1-$N$21-$N$23)/(1-$C$50)/$F$50*$C$50,(D25*K25)/(1-$N$21-$N$23)/(1-$I$21))) -> 0 | J25: =ROUND(H25*$I$21,2) -> 0 | K25: =N6 -> 0.07877
B26: Adicional BAM | C26: kWh | D26: =IF($K$12=M7,($D$21*($K$14)/($K$14+$L$14)),0)+IF($L$12=M7,($D$21*($L$14)/($K$14+$L$14)),0) -> 0 | E26: =IFERROR((ROUND(D26*K26,2)+ROUND(G26,2)+ROUND(J26,2))/ROUND(D26,4), 0) -> 0 | F26: =ROUND(D26*E26,2) -> 0 | G26: =((D26*K26)/(1-$N$21-$N$23))*($N$21+$N$23) -> 0 | H26: =(IF($I$21=12%,(D26*K26)/(1-$N$21-$N$23)/(1-$C$50)/$F$50*$C$50,(D26*K26)/(1-$N$21-$N$23)/(1-$I$21))) -> 0 | J26: =ROUND(H26*$I$21,2) -> 0 | K26: =N7 -> 0.142
B28: TUSD - Consumo inj | C28: kWh | D28: -1379 | E28: =IFERROR((ROUND(D28*K28,2)+ROUND(G28,2)+ROUND(J28,2))/ROUND(D28,4), 0) -> 0.58163887 | F28: =ROUND(D28*E28,2) -> -802.08 | G28: 0 | H28: =(IF($I$29=12%,(D28*K28)/(1-$N$22-$N$24)/(1-$C$50)/$F$50*$C$50,(D28*K28)/(1-$N$22-$N$24)/(1-$I$29))) -> -845.37424 | I28: =I21 -> 0.17 | J28: =H28*$I$21 -> -143.71362 | K28: =E67 -> 0.47742433 | Q28: 571.6518
B29: TE - Consumo inj | C29: kWh | D29: =D28 -> -1379 | E29: =IFERROR((ROUND(D29*K29,2)+ROUND(G29,2)+ROUND(J29,2))/ROUND(D29,4), 0) -> 0.39542422 | F29: =ROUND(D29*E29,2) -> -545.29 | G29: 0 | H29: =(IF($I$29=12%,(D29*K29)/(1-$N$22-$N$24)/(1-$C$50)/$F$50*$C$50,(D29*K29)/(1-$N$22-$N$24)/(1-$I$29))) -> -574.73133 | I29: =I21 -> 0.17 | J29: =H29*$I$21 -> -97.704327 | K29: =K22 -> 0.324579 | Q29: 526.8619
B30: Adicional BAM inj | C30: kWh | D30: =IF($K$12=M4,($D$28*($K$14)/($K$14+$L$14)),0)+IF($L$12=M4,($D$28*($L$14)/($K$14+$L$14)),0) -> -1379 | E30: =IFERROR((ROUND(D30*K30,2)+ROUND(G30,2)+ROUND(J30,2))/ROUND(D30,4), 0) -> 0.022958666 | F30: =ROUND(D30*E30,2) -> -31.66 | G30: 0 | H30: =(IF($I$29=12%,(D30*K30)/(1-$N$22-$N$24)/(1-$C$50)/$F$50*$C$50,(D30*K30)/(1-$N$22-$N$24)/(1-$I$29))) -> -33.377654 | J30: =H30*$I$21 -> -5.6742012 | K30: =N4 -> 0.01885 | Q30: 280.4863
B31: Adicional BAM inj | C31: kWh | D31: =IF($K$12=M5,($D$28*($K$14)/($K$14+$L$14)),0)+IF($L$12=M5,($D$28*($L$14)/($K$14+$L$14)),0) -> 0 | E31: =IFERROR((ROUND(D31*K31,2)+ROUND(G31,2)+ROUND(J31,2))/ROUND(D31,4), 0) -> 0 | F31: =ROUND(D31*E31,2) -> 0 | G31: 0 | H31: =(IF($I$29=12%,(D31*K31)/(1-$N$22-$N$24)/(1-$C$50)/$F$50*$C$50,(D31*K31)/(1-$N$22-$N$24)/(1-$I$29))) -> 0 | J31: =H31*$I$21 -> 0 | K31: =N5 -> 0.04463
B32: Adicional BAM inj | C32: kWh | D32: =IF($K$12=M6,($D$28*($K$14)/($K$14+$L$14)),0)+IF($L$12=M6,($D$28*($L$14)/($K$14+$L$14)),0) -> 0 | E32: =IFERROR((ROUND(D32*K32,2)+ROUND(G32,2)+ROUND(J32,2))/ROUND(D32,4), 0) -> 0 | F32: =ROUND(D32*E32,2) -> 0 | G32: 0 | H32: =(IF($I$29=12%,(D32*K32)/(1-$N$22-$N$24)/(1-$C$50)/$F$50*$C$50,(D32*K32)/(1-$N$22-$N$24)/(1-$I$29))) -> 0 | J32: =H32*$I$21 -> 0 | K32: =N6 -> 0.07877
B33: Adicional BAM inj | C33: kWh | D33: =IF($K$12=M7,($D$28*($K$14)/($K$14+$L$14)),0)+IF($L$12=M7,($D$28*($L$14)/($K$14+$L$14)),0) -> 0 | E33: =IFERROR((ROUND(D33*K33,2)+ROUND(G33,2)+ROUND(J33,2))/ROUND(D33,4), 0) -> 0 | F33: =ROUND(D33*E33,2) -> 0 | G33: 0 | H33: =(IF($I$29=12%,(D33*K33)/(1-$N$22-$N$24)/(1-$C$50)/$F$50*$C$50,(D33*K33)/(1-$N$22-$N$24)/(1-$I$29))) -> 0 | J33: =H33*$I$21 -> 0 | K33: =N7 -> 0.142 | Q33: =SUM(Q28:Q32) -> 1379
B35: Juros
B36: Multas | F36: -355.76
B37: Doações | F37: -3.28
B38: CIP
B42: TOTAL | F42: =SUM(F21:F41) -> -252.97 | G42: =SUM(G21:G41) -> 76.05364 | H42: =SUM(H21:H41) -> 31.620375 | J42: =SUM(J21:J41) -> 5.3779467
B44: Informativo Escassez | C44: =D21+D28 -> 30 | D44: =IF(AND($B$14<$F$2,$E$14<$F$2),C7,IF($B$14<$F$2,I7,F7)) -> 0.00018691702 | E44: =IF(AND($B$14<$F$2,$E$14<$F$2),D7,IF($B$14<$F$2,J7,G7)) -> -0.0034998272 | F44: =C44*(D44+E44) -> -0.099387305
B46: Se for base reduzida: (célula I18 = 12%)
D47: Com tributos
B48: PIS | C48: =N21 -> 0.011 | D48: =((D21*K21)+(D22*K22)+(D23*K23)+(D24*K24)+(D25*K25)+(D26*K26))/(1-$N$21-$N$23) -> 1232.636 | E48: x | F48: =C48 -> 0.011 | G48: =D48*F48 -> 13.558996
B49: COFINS | C49: =N23 -> 0.0507 | D49: =D48 -> 1232.636 | E49: x | F49: =C49 -> 0.0507 | G49: =D49*F49 -> 62.494645
A50: Rural c/ incrição | B50: ICMS | C50: 0.04 | D50: =H50/F50*C50 -> 427.99861 | E50: x | F50: 0.12 | G50: =D50*F50 -> 51.359833 | H50: =((D21*K21)+(D22*K22)+(D23*K23)+(D24*K24)+(D25*K25)+(D26*K26))/(1-F48-F49)/(1-(C50)) -> 1283.9958
E51: =(O40)/(1-C48-C49-C50) -> 0
C52: Base de cálculo reduzida = | D52: Importe
D53: 12% x 4%
B56: Fatura B2
D57: Qtde | E57: TUSD | F57: TE | G57: TUSD + TE | H57: R$
B58: Fornecimento de Energia Elétrica | H58: =SUM(H60:H76)+SUM(H81:H86) -> 175.33908
B60: Energia Fornecida | D60: =D21 -> 1409 | E60: =IF(AND($B$14<$F$2,$E$14<$F$2),C6,IF($B$14<$F$2,I6,F6)) -> 0.47742433 | F60: =IF(AND($B$14<$F$2,$E$14<$F$2),D6,IF($B$14<$F$2,J6,G6)) -> 0.324579 | G60: =E60+F60 -> 0.80200333 | H60: =ROUND((D60*E60),2)+ROUND((D60*F60),2) -> 1130.02
B62: Adicional BAM | D62: =IF($K$12=M4,(D60*(K14)/(K14+L14)),0)+IF($L$12=M4,(D60*(L14)/(K14+L14)),0) -> 1409 | F62: =N4 -> 0.01885 | H62: =ROUND(D62*(E62+F62),2) -> 26.56
B63: Adicional BVM 1 | D63: =IF($K$12=M5,(D60*(K14)/(K14+L14)),0)+IF($L$12=M5,(D60*(L14)/(K14+L14)),0) -> 0 | F63: =N5 -> 0.04463 | H63: =ROUND(D63*(E63+F63),2) -> 0
B64: Adicional BVM 2 | D64: =IF($K$12=M6,(D60*(K14)/(K14+L14)),0)+IF($L$12=M6,(D60*(L14)/(K14+L14)),0) -> 0 | F64: =N6 -> 0.07877 | H64: =ROUND(D64*(E64+F64),2) -> 0
B65: Adicional Escassez Hídrica | D65: =IF($K$12=M7,(D60*(K14)/(K14+L14)),0)+IF($L$12=M7,(D60*(L14)/(K14+L14)),0) -> 0 | F65: =N7 -> 0.142 | H65: =ROUND(D65*(E65+F65),2) -> 0
B67: Energia Injetada | D67: =D28 -> -1379 | E67: =E60*F17 -> 0.47742433 | F67: =F60 -> 0.324579 | G67: =E67+F67 -> 0.80200333 | H67: =ROUND((D67*E67),2)+ROUND((D67*F67),2) -> -1105.96
B69: Adicional BAM | D69: =IF($K$12=M4,(D67*(K14)/(K14+L14)),0)+IF($L$12=M4,(D67*(L14)/(K14+L14)),0) -> -1379 | F69: =F62 -> 0.01885 | H69: =ROUND(D69*(E69+F69),2) -> -25.99
B70: Adicional BVM 1 | D70: =IF($K$12=M5,(D67*(K14)/(K14+L14)),0)+IF($L$12=M5,(D67*(L14)/(K14+L14)),0) -> 0 | F70: =F63 -> 0.04463 | H70: =ROUND(D70*(E70+F70),2) -> 0
B71: Adicional BVM 2 | D71: =IF($K$12=M6,(D67*(K14)/(K14+L14)),0)+IF($L$12=M6,(D67*(L14)/(K14+L14)),0) -> 0 | F71: =F64 -> 0.07877 | H71: =ROUND(D71*(E71+F71),2) -> 0
B72: Adicional Escassez Hídrica | D72: =IF($K$12=M7,(D67*(K14)/(K14+L14)),0)+IF($L$12=M7,(D67*(L14)/(K14+L14)),0) -> 0 | F72: =F65 -> 0.142 | H72: =ROUND(D72*(E72+F72),2) -> 0
H78: =SUM(H60:H77) -> 24.63
D80: Base de Cálculo
B81: PIS | D81: =(H60+H62+H63+H64+H65)/(1-E81-E83) -> 1232.6335 | E81: =N21 -> 0.011 | H81: =D81*E81 -> 13.558968
B82: PIS Eneg Inj | D82: =(H67+H69+H70+H71+H72+H74+H76)/(1-E81-E83) -> -1206.3839 | E82: =E81 -> 0.011 | H82: =D82*E82 -> -13.270223
B83: COFINS | D83: =D81 -> 1232.6335 | E83: =N23 -> 0.0507 | H83: =D83*E83 -> 62.494518
B84: COFINS Eneg Inj | D84: =D82 -> -1206.3839 | E84: =E83 -> 0.0507 | H84: =D84*E84 -> -61.163663
B85: ICMS | D85: =D81/(1-E85) -> 1485.1006 | E85: 0.17 | H85: =D85*E85 -> 252.4671
B86: ICMS Eneg Inj | D86: =((D67*F67)+(H69+H70+H71+H72)+(D74*F74)+(D76*F76))/(1-E82-E84)/(1-E86) -> -608.10366 | E86: =E85 -> 0.17 | H86: =D86*E86 -> -103.37762
B88: Informativo Escassez Hídrica | D88: =D60+D67 -> 30 | E88: =IF(AND($B$14<$F$2,$E$14<$F$2),C7,IF($B$14<$F$2,I7,F7)) -> 0.00018691702 | F88: =IF(AND($B$14<$F$2,$E$14<$F$2),D7,IF($B$14<$F$2,J7,G7)) -> -0.0034998272 | H88: =D88*(E88+F88) -> -0.099387305

Sheet Fatura B2 (GD II) OK
B2: B2 | E2: Vigência das Tarifas: | F2: ='Fatura B1 (GD) OK'!F2 -> 46241 | M2: Bandeira | N2: R$/kWh | O2: ANEEL em 29/06 | Q2: TUSD FIO B
M3: VERDE | N3: 0
B4: TARIFA | C4: TARIFA ANTIGA - REH 3091/2022 | F4: ='[2]Fatura B1 (GD)'!F4 -> TARIFA NOVA - REH xxxx/2024 | I4: Tarifas Proporcionalizadas | M4: BAM | N4: ='[3]Fatura B1 (Res) OK'!$N$4 -> 0.01885 | Q4: TARIFA | R4: =C4 -> TARIFA ANTIGA - REH 3091/2022 | U4: =F4 -> TARIFA NOVA - REH xxxx/2024 | X4: Tarifas Proporcionalizadas
C5: Tusd | D5: TE | E5: TUSD + TE | F5: Tusd | G5: TE | H5: TUSD + TE | I5: Tusd | J5: TE | K5: TUSD + TE | M5: BVM1 | N5: ='[3]Fatura B1 (Res) OK'!$N$5 -> 0.04463 | R5: Tusd (R$/kWh) | U5: Tusd (R$/kWh) | X5: Tusd (R$/kWh)
B6: B2 | C6: ='[4]TABELA DE TARIFAS ANTIGAS'!G77/1000 -> 0.46863 | D6: ='[4]TABELA DE TARIFAS ANTIGAS'!H77/1000 -> 0.32068 | E6: =C6+D6 -> 0.78931 | F6: ='[4]TABELA DE TARIFAS NOVAS'!G79/1000 -> 0.50632 | G6: ='[4]TABELA DE TARIFAS NOVAS'!H79/1000 -> 0.33739 | H6: =F6+G6 -> 0.84371 | I6: =((C6*$C$14)+(F6*$D$14))/($D$14+$C$14) -> 0.47742433 | J6: =((D6*$C$14)+(G6*$D$14))/($D$14+$C$14) -> 0.324579 | K6: =I6+J6 -> 0.80200333 | M6: BVM2 | N6: ='[3]Fatura B1 (Res) OK'!$N$6 -> 0.07877 | Q6: =B6 -> B2 | R6: ='[4]FIO B'!H25/1000 -> 0.20383072 | U6: ='[4]FIO B'!K25/1000 -> 0.20915159 | X6: =((R6*$C$14)+(U6*$D$14))/($D$14+$C$14) -> 0.20507226
B7: CDE Escassez Hídrica | C7: 0.00018774721 | D7: -0.0044031307 | E7: 0.0036054084 | F7: =T11 -> 0.00018418923 | G7: =U11 -> -0.00053182975 | H7: =F7+G7 -> -0.00034764052 | I7: =((C7*$C$14)+(F7*$D$14))/($D$14+$C$14) -> 0.00018691702 | J7: =((D7*$C$14)+(G7*$D$14))/($D$14+$C$14) -> -0.0034998272 | K7: =I7+J7 -> -0.0033129102 | M7: Escassez Hídrica | N7: 0.142
B8: TE SCEE | G8: =G6*15% -> 0.0506085 | J8: =((D8*$C$14)+(G8*$D$14))/($D$14+$C$14) -> 0.01180865 | P8: CUSTO | R8: Part. TUSD (%) | S8: Part. TE (%) | T8: Tusd (R$/kWh) | U8: TE (R$/kWh)
P9: CDE CONTAS
H10: Fatura | L10: Vigência das Tarifas (troca Bandeira): | M10: =EOMONTH(B14,0)+1 -> 46235 | P10: CDE COVID | U10: 0
B11: INSTALAÇÃO | H11: =E14 -> 46247 | K11: Altere a bandeira na célula abaixo | P11: CDE ESCASSEZ HÍDRICA | T11: =#REF! -> 0.00018418923 | U11: =#REF! -> -0.00053182975
C12: 1827762 | K12: BAM | L12: BAM
B13: Leitura Anterior | C13: Nº de dias tarifa Anterior | D13: Nº de dias tarifa Nova | E13: Leitura Atual | J13: Leitura Anterior | K13: Nº de dias tarifa Anterior | L13: Nº de dias tarifa Nova | M13: Leitura Atual
B14: 46217 | C14: =IF((F2-B14-1)<0,0,(F2-B14-1)) -> 23 | D14: =E14-F2+1 -> 7 | E14: 46247 | J14: =B14 -> 46217 | K14: =IF((M10-J14-1)<0,0,(M10-J14-1)) -> 17 | L14: =M14-M10+1 -> 13 | M14: =E14 -> 46247
B17: Perc. de Redução da Energia Injetada | E17: TUSD | F17: 1 | G17: TE | H17: 1 | M17: Documento Impressão | O17: 1025310625
B19: Descrição | C19: Unidade | D19: Quantidade | E19: Preço Unit (R$) com tributos | F19: Valor Total (R$) | G19: PIS/COFINS (R$) | H19: Base de Cálculo ICMS (R$) | I19: Alíquota ICMS (%) | J19: ICMS (R$) | K19: Preço Unit (R$) | L19: Tributos | M19: Base de Cálc (R$) | N19: Alíquota (%) | O19: Valor (R$)
R20: TUSD Fio B | S20: Receita Fio B
B21: TUSD - Consumo | C21: kWh | D21: 369 | E21: =(ROUND(D21*K21,2)+ROUND(G21,2)+ROUND(J21,2))/ROUND(D21,4) -> 0.61303523 | F21: =ROUND(D21*E21,2) -> 226.21 | G21: =((D21*K21)/(1-$N$21-$N$23))*($N$21+$N$23) -> 11.584422 | H21: =(IF($I$21=12%,(D21*K21)/(1-$N$21-$N$23)/(1-$C$50)/$F$50*$C$50,(D21*K21)/(1-$N$21-$N$23)/(1-$I$21))) -> 226.20964 | I21: 0.17 | J21: =(H21*$I$21) -> 38.455639 | K21: =IF(AND($B$14<$F$2,$E$14<$F$2),C6,IF($B$14<$F$2,I6,F6)) -> 0.47742433 | L21: PIS | M21: =D84 -> 322.81786 | N21: 0.011 | O21: =ROUND(M21*N21,2) -> 3.55 | R21: =IF(AND($B14<$F$2,$E$14<$F$2),R6,IF($B$14<$F$2,X6,U6)) -> 0.20507226 | S21: =D21*R21 -> 75.671663 | T21: não está considerando a energia injetada
B22: TE - Consumo | C22: kWh | D22: =D21 -> 369 | E22: =(ROUND(D22*K22,2)+ROUND(G22,2)+ROUND(J22,2))/ROUND(D22,4) -> 0.41677507 | F22: =ROUND(D22*E22,2) -> 153.79 | G22: =((D22*K22)/(1-$N$21-$N$23))*($N$21+$N$23) -> 7.8757194 | H22: =(IF($I$21=12%,(D22*K22)/(1-$N$21-$N$23)/(1-$C$50)/$F$50*$C$50,(D22*K22)/(1-$N$21-$N$23)/(1-$I$21))) -> 153.7896 | J22: =ROUND(H22*$I$21,2) -> 26.14 | K22: =IF(AND($B$14<$F$2,$E$14<$F$2),D6,IF($B$14<$F$2,J6,G6)) -> 0.324579 | L22: PIS Inj | M22: 0 | N22: =N21 -> 0.011 | O22: =ROUND(M22*N22,2) -> 0
B23: Adicional BAM | C23: kWh | D23: =IF($K$12=M4,($D$21*($K$14)/($K$14+$L$14)),0)+IF($L$12=M4,($D$21*($L$14)/($K$14+$L$14)),0) -> 369 | E23: =IFERROR((ROUND(D23*K23,2)+ROUND(G23,2)+ROUND(J23,2))/ROUND(D23,4), 0) -> 0.024227642 | F23: =ROUND(D23*E23,2) -> 8.94 | G23: =((D23*K23)/(1-$N$21-$N$23))*($N$21+$N$23) -> 0.45738421 | H23: =(IF($I$21=12%,(D23*K23)/(1-$N$21-$N$23)/(1-$C$50)/$F$50*$C$50,(D23*K23)/(1-$N$21-$N$23)/(1-$I$21))) -> 8.9313665 | J23: =ROUND(H23*$I$21,2) -> 1.52 | K23: =N4 -> 0.01885 | L23: COFINS | M23: =M21 -> 322.81786 | N23: 0.0507 | O23: =ROUND(M23*N23,2) -> 16.37
B24: Adicional BAM | C24: kWh | D24: =IF($K$12=M5,($D$21*($K$14)/($K$14+$L$14)),0)+IF($L$12=M5,($D$21*($L$14)/($K$14+$L$14)),0) -> 0 | E24: =IFERROR((ROUND(D24*K24,2)+ROUND(G24,2)+ROUND(J24,2))/ROUND(D24,4), 0) -> 0 | F24: =ROUND(D24*E24,2) -> 0 | G24: =((D24*K24)/(1-$N$21-$N$23))*($N$21+$N$23) -> 0 | H24: =(IF($I$21=12%,(D24*K24)/(1-$N$21-$N$23)/(1-$C$50)/$F$50*$C$50,(D24*K24)/(1-$N$21-$N$23)/(1-$I$21))) -> 0 | J24: =ROUND(H24*$I$21,2) -> 0 | K24: =N5 -> 0.04463 | L24: COFINS Inj | M24: =M22 -> 0 | N24: =N23 -> 0.0507 | O24: =ROUND(M24*N24,2) -> 0 | P24: Massa
B25: Adicional BAM | C25: kWh | D25: =IF($K$12=M6,($D$21*($K$14)/($K$14+$L$14)),0)+IF($L$12=M6,($D$21*($L$14)/($K$14+$L$14)),0) -> 0 | E25: =IFERROR((ROUND(D25*K25,2)+ROUND(G25,2)+ROUND(J25,2))/ROUND(D25,4), 0) -> 0 | F25: =ROUND(D25*E25,2) -> 0 | G25: =((D25*K25)/(1-$N$21-$N$23))*($N$21+$N$23) -> 0 | H25: =(IF($I$21=12%,(D25*K25)/(1-$N$21-$N$23)/(1-$C$50)/$F$50*$C$50,(D25*K25)/(1-$N$21-$N$23)/(1-$I$21))) -> 0 | J25: =ROUND(H25*$I$21,2) -> 0 | K25: =N6 -> 0.07877 | P25: 1827762
B26: Adicional BAM | C26: kWh | D26: =IF($K$12=M7,($D$21*($K$14)/($K$14+$L$14)),0)+IF($L$12=M7,($D$21*($L$14)/($K$14+$L$14)),0) -> 0 | E26: =IFERROR((ROUND(D26*K26,2)+ROUND(G26,2)+ROUND(J26,2))/ROUND(D26,4), 0) -> 0 | F26: =ROUND(D26*E26,2) -> 0 | G26: =((D26*K26)/(1-$N$21-$N$23))*($N$21+$N$23) -> 0 | H26: =(IF($I$21=12%,(D26*K26)/(1-$N$21-$N$23)/(1-$C$50)/$F$50*$C$50,(D26*K26)/(1-$N$21-$N$23)/(1-$I$21))) -> 0 | J26: =ROUND(H26*$I$21,2) -> 0 | K26: =N7 -> 0.142 | P26: 160147060
P27: 1494523
B28: TUSD - Consumo inj | C28: kWh | D28: -339 | E28: =IFERROR((ROUND(D28*K28,2)+ROUND(G28,2)+ROUND(J28,2))/ROUND(D28,4), 0) -> 0.43162242 | F28: =ROUND(D28*E28,2) -> -146.32 | G28: 0 | H28: =(IF($I$29=12%,(D28*K28)/(1-$N$22-$N$24)/(1-$C$50)/$F$50*$C$50,(D28*K28)/(1-$N$22-$N$24)/(1-$I$29))) -> -154.21804 | I28: =I21 -> 0.17 | J28: =H28*$I$21 -> -26.217066 | K28: =E70 -> 0.35428705 | P28: 160832701
B29: TE - Consumo inj | C29: kWh | D29: =D28 -> -339 | E29: =IFERROR((ROUND(D29*K29,2)+ROUND(G29,2)+ROUND(J29,2))/ROUND(D29,4), 0) -> 0.39542773 | F29: =ROUND(D29*E29,2) -> -134.05 | G29: 0 | H29: =(IF($I$29=12%,(D29*K29)/(1-$N$22-$N$24)/(1-$C$50)/$F$50*$C$50,(D29*K29)/(1-$N$22-$N$24)/(1-$I$29))) -> -141.28638 | I29: =I21 -> 0.17 | J29: =H29*$I$21 -> -24.018685 | K29: =K22 -> 0.324579
B30: Adicional BAM inj | C30: kWh | D30: =IF($K$12=M4,($D$28*($K$14)/($K$14+$L$14)),0)+IF($L$12=M4,($D$28*($L$14)/($K$14+$L$14)),0) -> -339 | E30: =IFERROR((ROUND(D30*K30,2)+ROUND(G30,2)+ROUND(J30,2))/ROUND(D30,4), 0) -> 0.022949853 | F30: =ROUND(D30*E30,2) -> -7.78 | G30: 0 | H30: =(IF($I$29=12%,(D30*K30)/(1-$N$22-$N$24)/(1-$C$50)/$F$50*$C$50,(D30*K30)/(1-$N$22-$N$24)/(1-$I$29))) -> -8.2052392 | J30: =H30*$I$21 -> -1.3948907 | K30: =N4 -> 0.01885
B31: Adicional BAM inj | C31: kWh | D31: =IF($K$12=M5,($D$28*($K$14)/($K$14+$L$14)),0)+IF($L$12=M5,($D$28*($L$14)/($K$14+$L$14)),0) -> 0 | E31: =IFERROR((ROUND(D31*K31,2)+ROUND(G31,2)+ROUND(J31,2))/ROUND(D31,4), 0) -> 0 | F31: =ROUND(D31*E31,2) -> 0 | G31: 0 | H31: =(IF($I$29=12%,(D31*K31)/(1-$N$22-$N$24)/(1-$C$50)/$F$50*$C$50,(D31*K31)/(1-$N$22-$N$24)/(1-$I$29))) -> 0 | J31: =H31*$I$21 -> 0 | K31: =N5 -> 0.04463
B32: Adicional BAM inj | C32: kWh | D32: =IF($K$12=M6,($D$28*($K$14)/($K$14+$L$14)),0)+IF($L$12=M6,($D$28*($L$14)/($K$14+$L$14)),0) -> 0 | E32: =IFERROR((ROUND(D32*K32,2)+ROUND(G32,2)+ROUND(J32,2))/ROUND(D32,4), 0) -> 0 | F32: =ROUND(D32*E32,2) -> 0 | G32: 0 | H32: =(IF($I$29=12%,(D32*K32)/(1-$N$22-$N$24)/(1-$C$50)/$F$50*$C$50,(D32*K32)/(1-$N$22-$N$24)/(1-$I$29))) -> 0 | J32: =H32*$I$21 -> 0 | K32: =N6 -> 0.07877
B33: Adicional BAM inj | C33: kWh | D33: =IF($K$12=M7,($D$28*($K$14)/($K$14+$L$14)),0)+IF($L$12=M7,($D$28*($L$14)/($K$14+$L$14)),0) -> 0 | E33: =IFERROR((ROUND(D33*K33,2)+ROUND(G33,2)+ROUND(J33,2))/ROUND(D33,4), 0) -> 0 | F33: =ROUND(D33*E33,2) -> 0 | G33: 0 | H33: =(IF($I$29=12%,(D33*K33)/(1-$N$22-$N$24)/(1-$C$50)/$F$50*$C$50,(D33*K33)/(1-$N$22-$N$24)/(1-$I$29))) -> 0 | J33: =H33*$I$21 -> 0 | K33: =N7 -> 0.142
B35: Juros | F35: 1.92
B36: Multas | F36: 0.06
B37: Doações
B38: CIP
B42: TOTAL | F42: =SUM(F21:F41) -> 102.77 | G42: =SUM(G21:G41) -> 19.917525 | H42: =SUM(H21:H41) -> 85.220951 | J42: =SUM(J21:J41) -> 14.484997
B44: Informativo Escassez | C44: =D21+D28 -> 30 | D44: =IF(AND($B$14<$F$2,$E$14<$F$2),C7,IF($B$14<$F$2,I7,F7)) -> 0.00018691702 | E44: =IF(AND($B$14<$F$2,$E$14<$F$2),D7,IF($B$14<$F$2,J7,G7)) -> -0.0034998272 | F44: =C44*(D44+E44) -> -0.099387305
B46: Se for base reduzida: (célula I18 = 12%)
D47: Com tributos
B48: PIS | C48: =N21 -> 0.011 | D48: =((D21*K21)+(D22*K22)+(D23*K23)+(D24*K24)+(D25*K25)+(D26*K26))/(1-$N$21-$N$23) -> 322.81241 | E48: x | F48: =C48 -> 0.011 | G48: =D48*F48 -> 3.5509365
B49: COFINS | C49: =N23 -> 0.0507 | D49: =D48 -> 322.81241 | E49: x | F49: =C49 -> 0.0507 | G49: =D49*F49 -> 16.366589
A50: Rural c/ incrição | B50: ICMS | C50: 0.04 | D50: =H50/F50*C50 -> 112.08764 | E50: x | F50: 0.12 | G50: =D50*F50 -> 13.450517 | H50: =((D21*K21)+(D22*K22)+(D23*K23)+(D24*K24)+(D25*K25)+(D26*K26))/(1-F48-F49)/(1-(C50)) -> 336.26292
E51: =(O40)/(1-C48-C49-C50) -> 0
C52: Base de cálculo reduzida = | D52: Importe
D53: 12% x 4%
B55: Perc. de Redução da Energia Injetada | E55: TUSD | F55: 0.739 | G55: TE | H55: 1 | I55: =#REF! -> #REF!
E56: TUSD | F56: 0.7522 | G56: TE | H56: 1 | I56: =#REF! -> #REF!
B59: Fatura B2
D60: Qtde | E60: TUSD | F60: TE | G60: TUSD + TE | H60: R$
B61: Fornecimento de Energia Elétrica | H61: =SUM(H63:H79)+SUM(H84:H89) -> 111.45074
B63: Energia Fornecida | D63: =D21 -> 369 | E63: =IF(AND($B$14<$F$2,$E$14<$F$2),C6,IF($B$14<$F$2,I6,F6)) -> 0.47742433 | F63: =IF(AND($B$14<$F$2,$E$14<$F$2),D6,IF($B$14<$F$2,J6,G6)) -> 0.324579 | G63: =E63+F63 -> 0.80200333 | H63: =ROUND((D63*E63),2)+ROUND((D63*F63),2) -> 295.94
B65: Adicional BAM | D65: =IF($K$12=M4,(D63*(K14)/(K14+L14)),0)+IF($L$12=M4,(D63*(L14)/(K14+L14)),0) -> 369 | F65: =N4 -> 0.01885 | H65: =ROUND(D65*(E65+F65),2) -> 6.96
B66: Adicional BVM 1 | D66: =IF($K$12=M5,(D63*(K14)/(K14+L14)),0)+IF($L$12=M5,(D63*(L14)/(K14+L14)),0) -> 0 | F66: =N5 -> 0.04463 | H66: =ROUND(D66*(E66+F66),2) -> 0
B67: Adicional BVM 2 | D67: =IF($K$12=M6,(D63*(K14)/(K14+L14)),0)+IF($L$12=M6,(D63*(L14)/(K14+L14)),0) -> 0 | F67: =N6 -> 0.07877 | H67: =ROUND(D67*(E67+F67),2) -> 0
B68: Adicional Escassez Hídrica | D68: =IF($K$12=M7,(D63*(K14)/(K14+L14)),0)+IF($L$12=M7,(D63*(L14)/(K14+L14)),0) -> 0 | F68: =N7 -> 0.142 | H68: =ROUND(D68*(E68+F68),2) -> 0
B70: Energia Injetada | D70: =D28 -> -339 | E70: =IF(AND($B$14<$F$2,$E$14<$F$2),C6*$F$55,IF($B$14<$F$2,(((I6*F55)*C14)+((I6*F56)*D14))/(C14+D14),I6*$F$56)) -> 0.35428705 | F70: =F63 -> 0.324579 | G70: =E70+F70 -> 0.67886605 | H70: =ROUND((D70*E70),2)+ROUND((D70*F70),2) -> -230.13
B72: Adicional BAM | D72: =IF($K$12=M4,(D70*(K14)/(K14+L14)),0)+IF($L$12=M4,(D70*(L14)/(K14+L14)),0) -> -339 | F72: =F65 -> 0.01885 | H72: =ROUND(D72*(E72+F72),2) -> -6.39
B73: Adicional BVM 1 | D73: =IF($K$12=M5,(D70*(K14)/(K14+L14)),0)+IF($L$12=M5,(D70*(L14)/(K14+L14)),0) -> 0 | F73: =F66 -> 0.04463 | H73: =ROUND(D73*(E73+F73),2) -> 0
B74: Adicional BVM 2 | D74: =IF($K$12=M6,(D70*(K14)/(K14+L14)),0)+IF($L$12=M6,(D70*(L14)/(K14+L14)),0) -> 0 | F74: =F67 -> 0.07877 | H74: =ROUND(D74*(E74+F74),2) -> 0
B75: Adicional Escassez Hídrica | D75: =IF($K$12=M7,(D70*(K14)/(K14+L14)),0)+IF($L$12=M7,(D70*(L14)/(K14+L14)),0) -> 0 | F75: =F68 -> 0.142 | H75: =ROUND(D75*(E75+F75),2) -> 0
H81: =SUM(H63:H80) -> 66.38
D83: Base de Cálculo
B84: PIS | D84: =(H63+H65+H66+H67+H68)/(1-E84-E86) -> 322.81786 | E84: =N21 -> 0.011 | H84: =D84*E84 -> 3.5509965
B85: PIS Eneg Inj | D85: =(H70+H72+H73+H74+H75+H77+H79)/(1-E84-E86) -> -252.0729 | E85: =E84 -> 0.011 | H85: =D85*E85 -> -2.7728019
B86: COFINS | D86: =D84 -> 322.81786 | E86: =N23 -> 0.0507 | H86: =D86*E86 -> 16.366866
B87: COFINS Eneg Inj | D87: =D85 -> -252.0729 | E87: =E86 -> 0.0507 | H87: =D87*E87 -> -12.780096
B88: ICMS | D88: =D84/(1-E88) -> 388.93718 | E88: 0.17 | H88: =D88*E88 -> 66.119321
B89: ICMS Eneg Inj | D89: =((D70*F70)+(H72+H73+H74+H75)+(D77*F77)+(D79*F79))/(1-E85-E87)/(1-E89) -> -149.49143 | E89: =E88 -> 0.17 | H89: =D89*E89 -> -25.413543
B91: Informativo Escassez Hídrica | D91: =D63+D70 -> 30 | E91: =IF(AND($B$14<$F$2,$E$14<$F$2),C7,IF($B$14<$F$2,I7,F7)) -> 0.00018691702 | F91: =IF(AND($B$14<$F$2,$E$14<$F$2),D7,IF($B$14<$F$2,J7,G7)) -> -0.0034998272 | H91: =D91*(E91+F91) -> -0.099387305
