Workbook

Sheet Fatura B1 (GD I)
B2: B1 Res | E2: Vigência das Tarifas: | F2: 45145 | I2: GDI | M2: Bandeira | N2: R$/kWh | O2: ANEEL em 29/06 | Q2: TUSD FIO B
M3: VERDE | N3: 0
B4: TARIFA | C4: TARIFA ANTIGA - REH 3091/2022 | F4: TARIFA NOVA - REH XXXX/2023 | I4: Tarifas Proporcionalizadas | M4: BAM | N4: 0.02989 | Q4: TARIFA | R4: =C4 -> TARIFA ANTIGA - REH 3091/2022 | U4: =F4 -> TARIFA NOVA - REH XXXX/2023 | X4: Tarifas Proporcionalizadas
C5: Tusd | D5: TE | E5: TUSD + TE | F5: Tusd | G5: TE | H5: TUSD + TE | I5: Tusd | J5: TE | K5: TUSD + TE | M5: BVM1 | N5: 0.065 | R5: Tusd (R$/kWh) | U5: Tusd (R$/kWh) | X5: Tusd (R$/kWh)
B6: B1 | C6: 0.39681 | D6: 0.27703 | E6: =C6+D6 -> 0.67384 | F6: 0.39681 | G6: 0.27703 | H6: =F6+G6 -> 0.67384 | I6: =((C6*$C$14)+(F6*$D$14))/($D$14+$C$14) -> 0.39681 | J6: =((D6*$C$14)+(G6*$D$14))/($D$14+$C$14) -> 0.27703 | K6: =I6+J6 -> 0.67384 | M6: BVM2 | N6: 0.09795 | Q6: =B6 -> B1 | R6: ='[2]FIO B'!H11/1000 -> 0.19205 | U6: ='[2]FIO B'!K11/1000 -> 0.17652 | X6: =((R6*$C$14)+(U6*$D$14))/($D$14+$C$14) -> 0.18503645
B7: CDE Escassez Hídrica | F7: =T11 -> 0.00020011 | G7: =U11 -> 0.00402681 | H7: =F7+G7 -> 0.00422692 | I7: =((C7*$C$14)+(F7*$D$14))/($D$14+$C$14) -> 9.0372258e-05 | J7: =((D7*$C$14)+(G7*$D$14))/($D$14+$C$14) -> 0.0018185594 | K7: =I7+J7 -> 0.0019089316
B8: TE SCEE | G8: =G6*15% -> 0.0415545 | J8: =((D8*$C$14)+(G8*$D$14))/($D$14+$C$14) -> 0.018766548 | M8: Escassez Hídrica | N8: 0.142 | P8: CUSTO | T8: Tusd (R$/kWh) | U8: TE (R$/kWh)
P9: CDE CONTAS
H10: Fatura | L10: Vigência das Tarifas (troca Bandeira): | M10: =EOMONTH(B14,0)+1 -> 45139 | P10: CDE COVID
B11: INSTALAÇÃO | C11: 1182321 | H11: =E14 -> 45158 | K11: Altere a bandeira na célula abaixo | P11: CDE ESCASSEZ HÍDRICA | T11: 0.00020011 | U11: 0.00402681
K12: BAM | L12: BVM2
B13: Leitura Anterior | C13: Nº de dias tarifa Anterior | D13: Nº de dias tarifa Nova | E13: Leitura Atual | J13: Leitura Anterior | K13: Nº de dias tarifa Anterior | L13: Nº de dias tarifa Nova | M13: Leitura Atual
B14: 45127 | C14: =IF((F2-B14-1)<0,0,(F2-B14-1)) -> 17 | D14: =E14-F2+1 -> 14 | E14: 45158 | J14: =B14 -> 45127 | K14: =IF((M10-J14-1)<0,0,(M10-J14-1)) -> 11 | L14: =M14-M10+1 -> 20 | M14: =E14 -> 45158
B17: Perc. de Redução da Energia Injetada | E17: TUSD | F17: 1 | G17: TE | H17: 1
B19: Fatura B1 Residencial
D20: Qtde | E20: TUSD | F20: TE | G20: TUSD + TE | H20: R$
B21: Fornecimento de Energia Elétrica | H21: =SUM(H23:H39)+SUM(H44:H49) -> 254.92055
B23: Energia Fornecida | D23: 2000 | E23: =IF(AND($B$14<$F$2,$E$14<$F$2),C6,IF($B$14<$F$2,I6,F6)) -> 0.39681 | F23: =IF(AND($B$14<$F$2,$E$14<$F$2),D6,IF($B$14<$F$2,J6,G6)) -> 0.27703 | G23: =E23+F23 -> 0.67384 | H23: =ROUND((D23*E23),2)+ROUND((D23*F23),2) -> 1347.68
B25: Adicional BAM | D25: =IF($K$12=M4,(D23*(K14)/(K14+L14)),0)+IF($L$12=M4,(D23*(L14)/(K14+L14)),0) -> 709.67742 | F25: =N4 -> 0.02989 | H25: =ROUND(D25*(E25+F25),2) -> 21.21
B26: Adicional BVM 1 | D26: =IF($K$12=M5,(D23*(K14)/(K14+L14)),0)+IF($L$12=M5,(D23*(L14)/(K14+L14)),0) -> 0 | F26: =N5 -> 0.065 | H26: =ROUND(D26*(E26+F26),2) -> 0
B27: Adicional BVM 2 | D27: =IF($K$12=M6,(D23*(K14)/(K14+L14)),0)+IF($L$12=M6,(D23*(L14)/(K14+L14)),0) -> 1290.3226 | F27: =N6 -> 0.09795 | H27: =ROUND(D27*(E27+F27),2) -> 126.39
B28: Adicional Escassez Hídrica | D28: =IF($K$12=M8,(D23*(K14)/(K14+L14)),0)+IF($L$12=M8,(D23*(L14)/(K14+L14)),0) -> 0 | F28: =N8 -> 0.142 | H28: =ROUND(D28*(E28+F28),2) -> 0
B30: Energia Injetada | D30: -1900.0009 | E30: =E23*F17 -> 0.39681 | F30: =F23 -> 0.27703 | G30: =E30+F30 -> 0.67384 | H30: =ROUND((D30*E30),2)+ROUND((D30*F30),2) -> -1280.3
B32: Adicional BAM | D32: =IF($K$12=M4,(D30*(K14)/(K14+L14)),0)+IF($L$12=M4,(D30*(L14)/(K14+L14)),0) -> -674.19385 | F32: =F25 -> 0.02989 | H32: =ROUND(D32*(E32+F32),2) -> -20.15
B33: Adicional BVM 1 | D33: =IF($K$12=M5,(D30*(K14)/(K14+L14)),0)+IF($L$12=M5,(D30*(L14)/(K14+L14)),0) -> 0 | F33: =F26 -> 0.065 | H33: =ROUND(D33*(E33+F33),2) -> 0
B34: Adicional BVM 2 | D34: =IF($K$12=M6,(D30*(K14)/(K14+L14)),0)+IF($L$12=M6,(D30*(L14)/(K14+L14)),0) -> -1225.807 | F34: =F27 -> 0.09795 | H34: =ROUND(D34*(E34+F34),2) -> -120.07
B35: Adicional Escassez Hídrica | D35: =IF($K$12=M8,(D30*(K14)/(K14+L14)),0)+IF($L$12=M8,(D30*(L14)/(K14+L14)),0) -> 0 | F35: =F28 -> 0.142 | H35: =ROUND(D35*(E35+F35),2) -> 0
H41: =SUM(H23:H40) -> 74.76
D43: Base de Cálculo
B44: PIS | D44: =(H23+H25+H26+H27+H28)/(1-E44-E46) -> 1559.0449 | E44: 0.0073 | H44: =D44*E44 -> 11.381028
B45: PIS Eneg Inj | D45: =(H30+H32+H33+H34+H35+H37+H39)/(1-E44-E46) -> -1481.0969 | E45: =E44 -> 0.0073 | H45: =D45*E45 -> -10.812007
B46: COFINS | D46: =D44 -> 1559.0449 | E46: 0.0336 | H46: =D46*E46 -> 52.38391
B47: COFINS Eneg Inj | D47: =D45 -> -1481.0969 | E47: =E46 -> 0.0336 | H47: =D47*E47 -> -49.764855
B48: ICMS | D48: =D44/(1-E48) -> 1878.3674 | E48: 0.17 | H48: =D48*E48 -> 319.32246
B49: ICMS Eneg Inj | D49: =((D30*F30)+(H32+H33+H34+H35)+(D37*F37)+(D39*F39))/(1-E45-E47)/(1-E49) -> -837.35284 | E49: =E48 -> 0.17 | H49: =D49*E49 -> -142.34998
B51: Informativo Escassez Hídrica | D51: =D23+D30 -> 99.999137 | E51: =IF(AND($B$13<$F$2,$E$13<$F$2),C7,IF($B$13<$F$2,I7,F7)) -> 0.00020011 | F51: =IF(AND($B$13<$F$2,$E$13<$F$2),D7,IF($B$13<$F$2,J7,G7)) -> 0.00402681 | H51: =D51*(E51+F51) -> 0.42268835

Sheet FIO B
B2: TUSD FIO B
B4: SUBGRUPO | C4: MODALIDADE | D4: CLASSE | E4: SUBCLASSE | F4: POSTO | G4: TARIFAS DE APLICAÇÃO
G5: TUSD FIO B (RTP 2025) | J5: TUSD FIO B (RTA 2026)
G6: R$/kW | H6: R$/MWh | J6: R$/kW | K6: R$/MWh
B7: B1 | C7: BRANCA | D7: RESIDENCIAL | E7: RESIDENCIAL | F7: P | G7: 0 | H7: 591.10909 | J7: 0 | K7: 606.53962
B8: B1 | C8: BRANCA | D8: RESIDENCIAL | E8: RESIDENCIAL | F8: INT | G8: 0 | H8: 354.6655 | J8: 0 | K8: 363.92381
B9: B1 | C9: BRANCA | D9: RESIDENCIAL | E9: RESIDENCIAL | F9: FP | G9: 0 | H9: 118.2218 | J9: 0 | K9: 121.3079
B10: B1 | C10: PRÉ-PAGAMENTO | D10: RESIDENCIAL | E10: RESIDENCIAL | F10: NA | G10: 0 | H10: 203.83072 | J10: 0 | K10: 209.15159
B11: B1 | C11: CONVENCIONAL | D11: RESIDENCIAL | E11: RESIDENCIAL | F11: NA | G11: 0 | H11: 203.83072 | J11: 0 | K11: 209.15159
B12: B1 | C12: PRÉ-PAGAMENTO | D12: RESIDENCIAL | E12: BAIXA RENDA | F12: NA | G12: 0 | H12: 203.83072 | J12: 0 | K12: 209.15159
B13: B1 | C13: CONVENCIONAL | D13: RESIDENCIAL | E13: BAIXA RENDA | F13: NA | G13: 0 | H13: 203.83072 | J13: 0 | K13: 209.15159
B14: B1 | C14: PRÉ-PAGAMENTO | D14: RESIDENCIAL | E14: RESIDENCIAL DESCONTO SOCIAL | F14: NA | G14: 0 | H14: 203.83072 | J14: 0 | K14: 209.15159
B15: B1 | C15: CONVENCIONAL | D15: RESIDENCIAL | E15: RESIDENCIAL DESCONTO SOCIAL | F15: NA | G15: 0 | H15: 203.83072 | J15: 0 | K15: 209.15159
B16: B2 | C16: BRANCA | D16: RURAL | E16: NÃO SE APLICA | F16: P | G16: 0 | H16: 693.02445 | J16: 0 | K16: 711.11541
B17: B2 | C17: BRANCA | D17: RURAL | E17: NÃO SE APLICA | F17: INT | G17: 0 | H17: 415.81471 | J17: 0 | K17: 426.66929
B18: B2 | C18: BRANCA | D18: RURAL | E18: NÃO SE APLICA | F18: FP | G18: 0 | H18: 138.60487 | J18: 0 | K18: 142.22306
... B39: B | C39: GERAÇÃO | D39: TIPO 02 | E39: NA | F39: NA | G39: 0 | H39: 11.690957 | J39: 0 | K39: 11.996142

Sheet TABELA DE TARIFAS ANTIGAS
A1: TABELA 1 – TARIFAS DE APLICAÇÃO E BASE ECONÔMICA PARA O GRUPO A.
A2: SUBGRUPO | B2: MODALIDADE | C2: UC | D2: POSTO | E2: TARIFAS DE APLICAÇÃO | J2: BASE ECONÔMICA | N2: Reajuste | O2: Dia | P2: Mês | Q2: Ano
E3: TUSD | G3: TE | J3: TUSD | L3: TE | N3: De | O3: 07 | P3: 08 | Q3: 2025
E4: R$/kW | F4: R$/MWh | G4: BVD – R$/MWh | H4: BAM – R$/MWh | I4: BVM – R$/MWh | J4: R$/kW | K4: R$/MWh | L4: R$/MWh | N4: Até | O4: 06 | P4: 08 | Q4: 2026
B5: AZUL | C5: NA | D5: P
A6: A1 (230 kV ou mais) | D6: FP
B7: AZUL APE | C7: NA | D7: P
D8: FP
A9: A2 (88 a 138kV) | B9: AZUL | C9: NA | D9: P
D10: FP
B11: AZUL APE | C11: NA | D11: P
D12: FP
B13: DISTRIBUIÇÃO | C13: ELFSM | D13: P
D14: FP
D15: NA
B16: GERAÇÃO | C16: UTE LASA | D16: NA
C17: UTE ALCON | D17: NA
C18: UTE SOL | D18: NA
C19: UHE MASCARENHAS - ENERGEST | D19: NA
C20: UHE SUICA | D20: NA
C21: PCH SAO JOAQUIM | D21: NA
C22: PCH SAO SIMAO | D22: NA
C23: PCH FRANCISCO GROSS | D23: NA
C24: PCH SAO PEDRO | D24: NA
C25: UTE LINHARES | D25: NA
C26: UTE ARCEL | D26: NA
C27: NOVO GERADOR | D27: NA
A28: A3 (69kV) | B28: AZUL | C28: NA | D28: P
D29: FP
B30: AZUL APE | C30: NA | D30: P
D31: FP
B32: DISTRIBUIÇÃO | D32: P
D33: FP
D34: NA
B35: GERAÇÃO | C35: NA | D35: NA
A36: A3a (30 a 44kV) | B36: AZUL | C36: NA | D36: P
D37: FP
B38: AZUL APE | C38: NA | D38: P
D39: FP
B40: VERDE | C40: NA | D40: NA
D41: P
D42: FP
B43: VERDE APE | C43: NA | D43: NA
D44: P
D45: FP
B46: CONVENCIONAL | C46: NA | D46: NA
B47: GERAÇÃO | C47: NA | D47: NA
A48: A4 (2,3 a 25kV) | B48: AZUL | C48: NA | D48: P
D49: FP
B50: AZUL APE | C50: NA | D50: P
D51: FP
B52: VERDE | C52: NA | D52: NA
D53: P
D54: FP
B55: VERDE APE | C55: NA | D55: NA
D56: P
D57: FP
B58: CONVENCIONAL | C58: NA | D58: NA
B59: DISTRIBUIÇÃO | C59: COELBA | D59: P
D60: FP
D61: NA
B62: GERAÇÃO | C62: NA | D62: NA
A64: TABELA 2 – TARIFAS DE APLICAÇÃO E BASE ECONÔMICA PARA O GRUPO B.
A65: SUBGRUPO | B65: MODALIDADE | C65: CLASSE | D65: SUBCLASSE | E65: POSTO | F65: TARIFAS DE APLICAÇÃO | K65: TARIFAS BASE ECONÔMICA
F66: TUSD | H66: TE | K66: TUSD | M66: TE
F67: R$/kW | G67: R$/MWh | H67: BVD – R$/MWh | I67: BAM – R$/MWh | J67: BVM – R$/MWh | K67: R$/kW | L67: R$/MWh | M67: R$/MWh
A68: B1 | B68: BRANCA | C68: RESIDENCIAL | D68: RESIDENCIAL | E68: P | F68: 0 | G68: 937.61 | H68: 484.48 | K68: 0 | L68: 918.51 | M68: 492.47
E69: INT | F69: 0 | G69: 651.29 | H69: 305.79 | K69: 0 | L69: 634.94 | M69: 316.46
E70: FP | F70: 0 | G70: 364.96 | H70: 305.79 | K70: 0 | L70: 351.38 | M70: 316.46
B71: CONVENCIONAL | C71: RESIDENCIAL | D71: RESIDENCIAL | E71: NA | F71: 0 | G71: 468.63 | H71: 320.68 | K71: 0 | L71: 454.05 | M71: 331.12
D72: BAIXA RENDA(1) | E72: NA | F72: 0 | G72: 325.43 | H72: 282.45 | K72: 0
D73: DESCONTO SOCIAL | E73: NA | G73: 340.19 | H73: 296.66
A74: B2 | B74: BRANCA | C74: RURAL | D74: NA | E74: P | F74: 0 | G74: 1061.03 | H74: 484.48 | K74: 0 | L74: 1040.73 | M74: 492.47
E75: INT | F75: 0 | G75: 725.34 | H75: 305.79 | K75: 0 | L75: 708.28 | M75: 316.46
E76: FP | F76: 0 | G76: 389.65 | H76: 305.79 | K76: 0 | L76: 375.82 | M76: 316.46
B77: CONVENCIONAL | C77: RURAL | D77: NA | E77: NA | F77: 0 | G77: 468.63 | H77: 320.68 | K77: 0 | L77: 454.05 | M77: 331.12
B78: BRANCA | C78: RURAL | D78: COOPERATIVA DE ELETRIFICAÇÃO RURAL | E78: P | F78: 0 | G78: 1061.03 | H78: 484.48 | K78: 0 | L78: 1040.73 | M78: 492.47
E79: INT | F79: 0 | G79: 725.34 | H79: 305.79 | K79: 0 | L79: 708.28 | M79: 316.46
E80: FP | F80: 0 | G80: 389.65 | H80: 305.79 | K80: 0 | L80: 375.82 | M80: 316.46
B81: CONVENCIONAL | C81: RURAL | D81: COOPERATIVA DE ELETRIFICAÇÃO RURAL | E81: NA | F81: 0 | G81: 468.63 | H81: 320.68 | K81: 0 | L81: 454.05 | M81: 331.12
B82: BRANCA | C82: RURAL | D82: SERVIÇO PÚBLICO DE IRRIGAÇÃO RURAL | E82: P | F82: 0 | G82: 1061.03 | H82: 484.48 | K82: 0 | L82: 1040.73 | M82: 492.47
E83: INT | F83: 0 | G83: 725.34 | H83: 305.79 | K83: 0 | L83: 708.28 | M83: 316.46
E84: FP | F84: 0 | G84: 389.65 | H84: 305.79 | K84: 0 | L84: 375.82 | M84: 316.46
B85: CONVENCIONAL | C85: RURAL | D85: SERVIÇO PÚBLICO DE IRRIGAÇÃO RURAL | E85: NA | F85: 0 | G85: 468.63 | H85: 320.68 | K85: 0 | L85: 454.05 | M85: 331.12
A86: B3 | B86: BRANCA | C86: NA | D86: NA | E86: P | F86: 0 | G86: 1061.03 | H86: 484.48 | K86: 0 | L86: 1040.73 | M86: 492.47
E87: INT | F87: 0 | G87: 725.34 | H87: 305.79 | K87: 0 | L87: 708.28 | M87: 316.46
E88: FP | F88: 0 | G88: 389.65 | H88: 305.79 | K88: 0 | L88: 375.82 | M88: 316.46
B89: CONVENCIONAL | C89: NA | D89: NA | E89: NA | F89: 0 | G89: 468.63 | H89: 320.68 | K89: 0 | L89: 454.05 | M89: 331.12
A90: B4 | B90: CONVENCIONAL | C90: ILUMINAÇÃO PÚBLICA | D90: B4a – REDE DE DISTRIBUIÇÃO | E90: NA | F90: 0 | G90: 257.75 | H90: 176.38 | K90: 0 | L90: 249.73 | M90: 182.12
D91: B4b – BULBO DE LÂMPADA | E91: NA | F91: 0 | G91: 281.18 | H91: 192.41 | K91: 0 | L91: 272.43 | M91: 198.67

Sheet TABELA DE TARIFAS NOVAS
A1: TABELA 1 – TARIFAS DE APLICAÇÃO E BASE ECONÔMICA PARA O GRUPO A.
A2: SUBGRUPO | B2: MODALIDADE | C2: UC | D2: POSTO | E2: TARIFAS DE APLICAÇÃO | J2: BASE ECONÔMICA | N2: Reajuste | O2: Dia | P2: Mês | Q2: Ano
E3: TUSD | G3: TE | J3: TUSD | L3: TE | N3: De | O3: 07 | P3: 08 | Q3: 2026
E4: R$/kW | F4: R$/MWh | G4: BVD – R$/MWh | H4: BAM – R$/MWh | I4: BVM – R$/MWh | J4: R$/kW | K4: R$/MWh | L4: R$/MWh | N4: Até | O4: 31 | P4: 12 | Q4: 9999
B5: AZUL | C5: NA | D5: P
A6: A1 (230 kV ou mais) | D6: FP
B7: AZUL APE | C7: NA | D7: P
D8: FP
A9: A2 (88 a 138kV) | B9: AZUL | C9: NA | D9: P
D10: FP
B11: AZUL APE | C11: NA | D11: P
D12: FP
B13: DISTRIBUIÇÃO | C13: ELFSM | D13: P
D14: FP
D15: NA
B16: GERAÇÃO | C16: UTE LASA | D16: NA
C17: UTE ALCON | D17: NA
C18: UTE SOL | D18: NA
C19: UHE MASCARENHAS - ENERGEST | D19: NA
C20: UHE SUICA | D20: NA
C21: PCH SAO JOAQUIM | D21: NA
C22: PCH SAO SIMAO | D22: NA
C23: PCH FRANCISCO GROSS | D23: NA
C24: PCH SAO PEDRO | D24: NA
C25: UTE LINHARES | D25: NA
C26: UTE POVOACAO 1 | D26: NA
C27: UTE ARCEL | D27: NA
C28: UTE BIANCOGRES | D28: NA
C29: NOVO GERADOR | D29: NA
A30: A3 (69kV) | B30: AZUL | C30: NA | D30: P
D31: FP
B32: AZUL APE | C32: NA | D32: P
D33: FP
B34: DISTRIBUIÇÃO | D34: P
D35: FP
D36: NA
B37: GERAÇÃO | C37: NA | D37: NA
A38: A3a (30 a 44kV) | B38: AZUL | C38: NA | D38: P
D39: FP
B40: AZUL APE | C40: NA | D40: P
D41: FP
B42: VERDE | C42: NA | D42: NA
D43: P
D44: FP
B45: VERDE APE | C45: NA | D45: NA
D46: P
D47: FP
B48: CONVENCIONAL | C48: NA | D48: NA
B49: GERAÇÃO | C49: NA | D49: NA
A50: A4 (2,3 a 25kV) | B50: AZUL | C50: NA | D50: P
D51: FP
B52: AZUL APE | C52: NA | D52: P
D53: FP
B54: VERDE | C54: NA | D54: NA
D55: P
D56: FP
B57: VERDE APE | C57: NA | D57: NA
D58: P
D59: FP
B60: CONVENCIONAL | C60: NA | D60: NA
B61: DISTRIBUIÇÃO | C61: COELBA | D61: P
D62: FP
D63: NA
B64: GERAÇÃO | C64: NA | D64: NA
A66: TABELA 2 – TARIFAS DE APLICAÇÃO E BASE ECONÔMICA PARA O GRUPO B.
A67: SUBGRUPO | B67: MODALIDADE | C67: CLASSE | D67: SUBCLASSE | E67: POSTO | F67: TARIFAS DE APLICAÇÃO | K67: TARIFAS BASE ECONÔMICA
F68: TUSD | H68: TE | K68: TUSD | M68: TE
F69: R$/kW | G69: R$/MWh | H69: BVD – R$/MWh | I69: BAM – R$/MWh | J69: BVM – R$/MWh | K69: R$/kW | L69: R$/MWh | M69: R$/MWh
A70: B1 | B70: BRANCA | C70: RESIDENCIAL | D70: RESIDENCIAL | E70: P | F70: 0 | G70: 999.02 | H70: 516.91 | K70: 0 | L70: 956.95 | M70: 478.38
E71: INT | F71: 0 | G71: 698.21 | H71: 321.07 | K71: 0 | L71: 662.46 | M71: 299.92
E72: FP | F72: 0 | G72: 397.41 | H72: 321.07 | K72: 0 | L72: 367.97 | M72: 299.92
B73: CONVENCIONAL | C73: RESIDENCIAL | D73: RESIDENCIAL | E73: NA | F73: 0 | G73: 506.32 | H73: 337.39 | K73: 0 | L73: 474.59 | M73: 314.79
D74: BAIXA RENDA(1) | E74: NA | F74: 0 | G74: 348.95 | H74: 325.32 | K74: 0 | L74: 334.57 | M74: 303.57
D75: DESCONTO SOCIAL | E75: NA | F75: 0 | G75: 356.42 | H75: 337.59 | L75: 343.39 | M75: 314.79
A76: B2 | B76: BRANCA | C76: RURAL | D76: NA | E76: P | F76: 0 | G76: 1128.67 | H76: 516.91 | K76: 0 | L76: 1083.88 | M76: 478.38
E77: INT | F77: 0 | G77: 776.01 | H77: 321.07 | K77: 0 | L77: 738.62 | M77: 299.92
E78: FP | F78: 0 | G78: 423.34 | H78: 321.07 | K78: 0 | L78: 393.35 | M78: 299.92
B79: CONVENCIONAL | C79: RURAL | D79: NA | E79: NA | F79: 0 | G79: 506.32 | H79: 337.39 | K79: 0 | L79: 474.59 | M79: 314.79
B80: BRANCA | C80: RURAL | D80: COOPERATIVA DE ELETRIFICAÇÃO RURAL | E80: P | F80: 0 | G80: 1128.67 | H80: 516.91 | K80: 0 | L80: 1083.88 | M80: 478.38
E81: INT | F81: 0 | G81: 776.01 | H81: 321.07 | K81: 0 | L81: 738.62 | M81: 299.92
E82: FP | F82: 0 | G82: 423.34 | H82: 321.07 | K82: 0 | L82: 393.35 | M82: 299.92
B83: CONVENCIONAL | C83: RURAL | D83: COOPERATIVA DE ELETRIFICAÇÃO RURAL | E83: NA | F83: 0 | G83: 506.32 | H83: 337.39 | K83: 0 | L83: 474.59 | M83: 314.79
B84: BRANCA | C84: RURAL | D84: SERVIÇO PÚBLICO DE IRRIGAÇÃO RURAL | E84: P | F84: 0 | G84: 1128.67 | H84: 516.91 | K84: 0 | L84: 1083.88 | M84: 478.38
E85: INT | F85: 0 | G85: 776.01 | H85: 321.07 | K85: 0 | L85: 738.62 | M85: 299.92
E86: FP | F86: 0 | G86: 423.34 | H86: 321.07 | K86: 0 | L86: 393.35 | M86: 299.92
B87: CONVENCIONAL | C87: RURAL | D87: SERVIÇO PÚBLICO DE IRRIGAÇÃO RURAL | E87: NA | F87: 0 | G87: 506.32 | H87: 337.39 | K87: 0 | L87: 474.59 | M87: 314.79
A88: B3 | B88: BRANCA | C88: NA | D88: NA | E88: P | F88: 0 | G88: 1128.67 | H88: 516.91 | K88: 0 | L88: 1083.88 | M88: 478.38
E89: INT | F89: 0 | G89: 776.01 | H89: 321.07 | K89: 0 | L89: 738.62 | M89: 299.92
E90: FP | F90: 0 | G90: 423.34 | H90: 321.07 | K90: 0 | L90: 393.35 | M90: 299.92
B91: CONVENCIONAL | C91: NA | D91: NA | E91: NA | F91: 0 | G91: 506.32 | H91: 337.39 | K91: 0 | L91: 474.59 | M91: 314.79
A92: B4 | B92: CONVENCIONAL | C92: ILUMINAÇÃO PÚBLICA | D92: B4a – REDE DE DISTRIBUIÇÃO | E92: NA | F92: 0 | G92: 278.48 | H92: 185.56 | K92: 0 | L92: 261.03 | M92: 173.13
D93: B4b – BULBO DE LÂMPADA | E93: NA | F93: 0 | G93: 303.79 | H93: 202.43 | K93: 0 | L93: 284.76 | M93: 188.87

Sheet Fatura B1 (GD II) OK
B2: B1 Res | E2: Vigência das Tarifas: | F2: 46241 | G2: 2025: | H2: 45658 | M2: Bandeira | N2: R$/kWh | O2: ANEEL em 29/06 | Q2: TUSD FIO B
M3: VERDE | N3: 0
B4: TARIFA | C4: TARIFA ANTIGA - REH 3370/2024 | F4: TARIFA NOVA - REH xxxx/2025 | I4: Tarifas Proporcionalizadas | M4: BAM | N4: =[3]BANDEIRA!$D$5 -> 0.01885 | Q4: TARIFA | R4: =C4 -> TARIFA ANTIGA - REH 3370/2024 | U4: =F4 -> TARIFA NOVA - REH xxxx/2025 | X4: Tarifas Proporcionalizadas
C5: Tusd | D5: TE | E5: TUSD + TE | F5: Tusd | G5: TE | H5: TUSD + TE | I5: Tusd | J5: TE | K5: TUSD + TE | M5: BVM1 | N5: =[3]BANDEIRA!$D$6 -> 0.04463 | R5: Tusd (R$/kWh) | U5: Tusd (R$/kWh) | X5: Tusd (R$/kWh)
B6: B1 | C6: ='TABELA DE TARIFAS ANTIGAS'!G71/1000 -> 0.46863 | D6: ='TABELA DE TARIFAS ANTIGAS'!H71/1000 -> 0.32068 | E6: =C6+D6 -> 0.78931 | F6: ='TABELA DE TARIFAS NOVAS'!G73/1000 -> 0.50632 | G6: ='TABELA DE TARIFAS NOVAS'!H73/1000 -> 0.33739 | H6: =F6+G6 -> 0.84371 | I6: =((C6*$C$14)+(F6*$D$14))/($D$14+$C$14) -> 0.49100844 | J6: =((D6*$C$14)+(G6*$D$14))/($D$14+$C$14) -> 0.33060156 | K6: =I6+J6 -> 0.82161 | M6: BVM2 | N6: =[3]BANDEIRA!$D$7 -> 0.07877 | Q6: =B6 -> B1 | R6: ='FIO B'!H11/1000 -> 0.20383072 | U6: ='FIO B'!K11/1000 -> 0.20915159 | X6: =((R6*$C$14)+(U6*$D$14))/($D$14+$C$14) -> 0.20698999
B7: CDE Escassez Hídrica | C7: 0.00018774721 | D7: -0.0044031307 | E7: 0.0036054084 | F7: =T11 -> 0.00018418923 | G7: =U11 -> -0.00053182975 | H7: =F7+G7 -> -0.00034764052 | I7: =((C7*$C$14)+(F7*$D$14))/($D$14+$C$14) -> 0.00018563466 | J7: =((D7*$C$14)+(G7*$D$14))/($D$14+$C$14) -> -0.0021045458 | K7: =I7+J7 -> -0.0019189111
B8: TE SCEE | G8: =G6*15% -> 0.0506085 | J8: =((D8*$C$14)+(G8*$D$14))/($D$14+$C$14) -> 0.030048797 | M8: Escassez Hídrica | N8: 0.142 | P8: CUSTO | R8: Part. TUSD (%) | S8: Part. TE (%) | T8: Tusd (R$/kWh) | U8: TE (R$/kWh)
P9: CDE CONTAS
H10: Fatura | L10: Vigência das Tarifas (troca Bandeira): | M10: =EOMONTH(B14,0)+1 -> 46235 | P10: CDE COVID | U10: 0
B11: INSTALAÇÃO | C11: 1280804 | H11: =E14 -> 46259 | K11: Altere a bandeira na célula abaixo | P11: CDE ESCASSEZ HÍDRICA | T11: =0.184189231569235/1000 -> 0.00018418923 | U11: =-0.531829748712515/1000 -> -0.00053182975
K12: BAM | L12: BAM
B13: Leitura Anterior | C13: Nº de dias tarifa Anterior | D13: Nº de dias tarifa Nova | E13: Leitura Atual | J13: Leitura Anterior | K13: Nº de dias tarifa Anterior | L13: Nº de dias tarifa Nova | M13: Leitura Atual
B14: 46227 | C14: =IF((F2-B14-1)<0,0,(F2-B14-1)) -> 13 | D14: =E14-F2+1 -> 19 | E14: 46259 | J14: =B14 -> 46227 | K14: =IF((M10-J14-1)<0,0,(M10-J14-1)) -> 7 | L14: =M14-M10+1 -> 25 | M14: =E14 -> 46259 | O14: Documento Impressão | Q14: 1025310412
B16: Descrição | C16: Unidade | D16: Quantidade | E16: Preço Unit (R$) com tributos | F16: Valor Total (R$) | G16: PIS/COFINS (R$) | H16: Base de Cálculo ICMS (R$) | I16: Alíquota ICMS (%) | J16: ICMS (R$) | K16: Preço Unit (R$) | L16: Tributos | M16: Base de Cálc (R$) | N16: Alíquota (%) | O16: Valor (R$) | P16: não está contabilizando injetada
R17: TUSD Fio B | S17: Receita Fio B
B18: TUSD - Consumo | C18: kWh | D18: 149 | E18: =(ROUND(D18*K18,2)+ROUND(G18,2)+ROUND(J18,2))/ROUND(D18,4) -> 0.6304698 | F18: =ROUND(D18*E18,2) -> 93.94 | G18: =((D18*K18)/(1-$N$18-$N$20))*($N$18+$N$20) -> 4.8108152 | H18: =((D18*K18)/(1-$N$18-$N$20)/(1-$I$18)) -> 93.941051 | I18: 0.17 | J18: =(H18*$I$18) -> 15.969979 | K18: =IF(AND($B$14<$F$2,$E$14<$F$2),C6,IF($B$14<$F$2,I6,F6)) -> 0.49100844 | L18: PIS | M18: =D71 -> 133.46478 | N18: 0.011 | O18: =ROUND(M18*N18,2) -> 1.47 | R18: =IF(AND($B$14<$F$2,$E$14<$F$2),R6,IF($B$14<$F$2,X6,U6)) -> 0.20698999 | S18: =D18*R18 -> 30.841508
B19: TE - Consumo | C19: kWh | D19: =D18 -> 149 | E19: =(ROUND(D19*K19,2)+ROUND(G19,2)+ROUND(J19,2))/ROUND(D19,4) -> 0.42449664 | F19: =ROUND(D19*E19,2) -> 63.25 | G19: =((D19*K19)/(1-$N$18-$N$20))*($N$18+$N$20) -> 3.2391765 | H19: =ROUND((D19*K19)/(1-$N$18-$N$20)/(1-$I$18),8) -> 63.251578 | J19: =(H19*$I$18) -> 10.752768 | K19: =IF(AND($B$14<$F$2,$E$14<$F$2),D6,IF($B$14<$F$2,J6,G6)) -> 0.33060156 | L19: PIS Inj | M19: =D72 -> -43.887882 | N19: =N18 -> 0.011 | O19: =ROUND(M19*N19,2) -> -0.48
B20: Adicional BAM | C20: kWh | D20: =IF($K$12=M4,($D$18*($K$14)/($L$14+$K$14)),0)+IF($L$12=M4,($D$18*($L$14)/($L$14+$K$14)),0) -> 149 | E20: =IFERROR((ROUND(D20*K20,2)+ROUND(G20,2)+ROUND(J20,2))/ROUND(D20,4), 0) -> 0.024161074 | F20: =ROUND(D20*E20,2) -> 3.6 | G20: =((D20*K20)/(1-$N$18-$N$20))*($N$18+$N$20) -> 0.18468902 | H20: =ROUND((D20*K20)/(1-$N$18-$N$20)/(1-$I$18),8) -> 3.6064326 | J20: =(H20*$I$18) -> 0.61309353 | K20: =N4 -> 0.01885 | L20: COFINS | M20: =M18 -> 133.46478 | N20: 0.0507 | O20: =ROUND(M20*N20,2) -> 6.77
B21: Adicional BVM1 | C21: kWh | D21: =IF($K$12=M5,($D$18*($K$14)/($L$14+$K$14)),0)+IF($L$12=M5,($D$18*($L$14)/($L$14+$K$14)),0) -> 0 | E21: =IFERROR((ROUND(D21*K21,2)+ROUND(G21,2)+ROUND(J21,2))/ROUND(D21,4), 0) -> 0 | F21: =ROUND(D21*E21,2) -> 0 | G21: =((D21*K21)/(1-$N$18-$N$20))*($N$18+$N$20) -> 0 | H21: =ROUND((D21*K21)/(1-$N$18-$N$20)/(1-$I$18),8) -> 0 | J21: =(H21*$I$18) -> 0 | K21: =N5 -> 0.04463 | L21: COFINS Inj | M21: =M19 -> -43.887882 | N21: =N20 -> 0.0507 | O21: =ROUND(M21*N21,2) -> -2.23
B22: Adicional BVM2 | C22: kWh | D22: =IF($K$12=M6,($D$18*($K$14)/($L$14+$K$14)),0)+IF($L$12=M6,($D$18*($L$14)/($L$14+$K$14)),0) -> 0 | E22: =IFERROR((ROUND(D22*K22,2)+ROUND(G22,2)+ROUND(J22,2))/ROUND(D22,4), 0) -> 0 | F22: =ROUND(D22*E22,2) -> 0 | G22: =((D22*K22)/(1-$N$18-$N$20))*($N$18+$N$20) -> 0 | H22: =ROUND((D22*K22)/(1-$N$18-$N$20)/(1-$I$18),8) -> 0 | J22: =(H22*$I$18) -> 0 | K22: =N6 -> 0.07877
B23: Adicional EH | C23: kWh | D23: =IF($K$12=M8,($D$18*($K$14)/($L$14+$K$14)),0)+IF($L$12=M8,($D$18*($L$14)/($L$14+$K$14)),0) -> 0 | E23: =IFERROR((ROUND(D23*K23,2)+ROUND(G23,2)+ROUND(J23,2))/ROUND(D23,4), 0) -> 0 | F23: =ROUND(D23*E23,2) -> 0 | G23: =((D23*K23)/(1-$N$18-$N$20))*($N$18+$N$20) -> 0 | H23: =ROUND((D23*K23)/(1-$N$18-$N$20)/(1-$I$18),8) -> 0 | J23: =(H23*$I$18) -> 0 | K23: =N8 -> 0.142
B25: TUSD - Consumo inj | C25: kWh | D25: -57.503 | E25: =IFERROR((ROUND(D25*K25,2)+ROUND(G25,2)+ROUND(J25,2))/ROUND(D25,4),0) -> 0.39093613 | F25: =ROUND(D25*E25,2) -> -22.48 | G25: =((D25*K25)/(1-$N$19-$N$21))*($N$19+$N$21) -> -1.3865931 | H25: 0 | I25: 0 | J25: =H25*$I$25 -> 0 | K25: =E57 -> 0.36670351
B26: TE - Consumo inj | C26: kWh | D26: =D25 -> -57.503 | E26: =IFERROR((ROUND(D26*K26,2)+ROUND(G26,2)+ROUND(J26,2))/ROUND(D26,4),0) -> 0.42449959 | F26: =ROUND(D26*E26,2) -> -24.41 | G26: =((D26*K26)/(1-$N$19-$N$21))*($N$19+$N$21) -> -1.250083 | H26: =ROUND((D26*K26)/(1-$N$19-$N$21)/(1-$I$26),8) -> -24.410439 | I26: =I18 -> 0.17 | J26: =H26*$I$26 -> -4.1497747 | K26: =F57 -> 0.33060156
B27: Adicional BAM inj | C27: kWh | D27: =IF($K$12=M4,($D$25*($K$14)/($K$14+$L$14)),0)+IF($L$12=M4,($D$25*($L$14)/($K$14+$L$14)),0) -> -57.503 | E27: =IFERROR((ROUND(D27*K27,2)+ROUND(G27,2)+ROUND(J27,2))/ROUND(D27,4),0) -> 0.024172652 | F27: =ROUND(D27*E27,2) -> -1.39 | G27: =((D27*K27)/(1-$N$19-$N$21))*($N$19+$N$21) -> -0.071276326 | H27: =ROUND((D27*K27)/(1-$N$19-$N$21)/(1-$I$26),8) -> -1.3918167 | J27: =H27*$I$26 -> -0.23660884 | K27: =N4 -> 0.01885
B28: Adicional BVM1 inj | C28: kWh | D28: =IF($K$12=M5,($D$25*($K$14)/($K$14+$L$14)),0)+IF($L$12=M5,($D$25*($L$14)/($K$14+$L$14)),0) -> 0 | E28: =IFERROR((ROUND(D28*K28,2)+ROUND(G28,2)+ROUND(J28,2))/ROUND(D28,4),0) -> 0 | F28: =ROUND(D28*E28,2) -> 0 | G28: =((D28*K28)/(1-$N$19-$N$21))*($N$19+$N$21) -> 0 | H28: =ROUND((D28*K28)/(1-$N$19-$N$21)/(1-$I$26),8) -> 0 | J28: =H28*$I$26 -> 0 | K28: =N5 -> 0.04463
B29: Adicional BVM2 inj | C29: kWh | D29: =IF($K$12=M6,($D$25*($K$14)/($K$14+$L$14)),0)+IF($L$12=M6,($D$25*($L$14)/($K$14+$L$14)),0) -> 0 | E29: =IFERROR((ROUND(D29*K29,2)+ROUND(G29,2)+ROUND(J29,2))/ROUND(D29,4),0) -> 0 | F29: =ROUND(D29*E29,2) -> 0 | G29: =((D29*K29)/(1-$N$19-$N$21))*($N$19+$N$21) -> 0 | H29: =ROUND((D29*K29)/(1-$N$19-$N$21)/(1-$I$26),8) -> 0 | J29: =H29*$I$26 -> 0 | K29: =N6 -> 0.07877
B30: Adicional EH inj | C30: kWh | D30: =IF($K$12=M7,($D$25*($K$14)/($K$14+$L$14)),0)+IF($L$12=M7,($D$25*($L$14)/($K$14+$L$14)),0) -> 0 | E30: =IFERROR((ROUND(D30*K30,2)+ROUND(G30,2)+ROUND(J30,2))/ROUND(D30,4),0) -> 0 | F30: =ROUND(D30*E30,2) -> 0 | G30: =((D30*K30)/(1-$N$19-$N$21))*($N$19+$N$21) -> 0 | H30: =ROUND((D30*K30)/(1-$N$19-$N$21)/(1-$I$26),8) -> 0 | J30: =H30*$I$26 -> 0 | K30: =N8 -> 0.142
B32: Multas
B33: Juros
B34: Doações
B35: Bônus/Descontos | F35: -7.07
B36: CIP | F36: 40.37
B38: TOTAL | F38: =SUM(F18:F37) -> 145.81 | G38: =SUM(G18:G37) -> 5.5267283 | H38: =SUM(H18:H37) -> 134.99681 | J38: =SUM(J18:J37) -> 22.949457
B40: Informativo Escassez Hídrica | D40: =D18 -> 149 | E40: =IF(AND($B$14<$F$2,$E$14<$F$2),C7,IF($B$14<$F$2,I7,F7)) -> 0.00018563466 | F40: =IF(AND($B$14<$F$2,$E$14<$F$2),D7,IF($B$14<$F$2,J7,G7)) -> -0.0021045458 | G40: =D40*(E40+F40) -> -0.28591776
D41: =D25 -> -57.503 | E41: =IF(AND($B$14<$F$2,$E$14<$F$2),C7*$F$44,IF($B$14<$F$2,(((I7*F44)*C14)+((I7*F45)*D14))/(C14+D14),I7*$F$45)) -> 0.00013863893 | F41: =IF(AND($B$14<$F$2,$E$14<$F$2),D7,IF($B$14<$F$2,J7,G7)) -> -0.0021045458 | G41: =D41*(E41+F41) -> 0.11304554
G42: =SUM(G40:G41) -> -0.17287221
B44: Perc. de Redução da Energia Injetada | E44: TUSD | F44: 0.739 | G44: TE | H44: 1 | I44: A partir de 01/01/2026
E45: TUSD | F45: 0.7522 | G45: TE | H45: 1 | I45: A partir de 07/08/2026
B46: Fatura B1 Residencial
D47: Qtde | E47: TUSD | F47: TE | G47: TUSD + TE | H47: R$
B48: Fornecimento de Energia Elétrica | H48: =SUM(H50:H66)+SUM(H71:H76) -> 112.52753
B50: Energia Fornecida | D50: =D18 -> 149 | E50: =IF(AND($B$14<$F$2,$E$14<$F$2),C6,IF($B$14<$F$2,I6,F6)) -> 0.49100844 | F50: =IF(AND($B$14<$F$2,$E$14<$F$2),D6,IF($B$14<$F$2,J6,G6)) -> 0.33060156 | G50: =E50+F50 -> 0.82161 | H50: =ROUND((D50*E50),2)+ROUND((D50*F50),2) -> 122.42
B52: Adicional BAM | D52: =IF($K$12=M4,(D50*(K14)/(K14+L14)),0)+IF($L$12=M4,(D50*(L14)/(K14+L14)),0) -> 149 | F52: =N4 -> 0.01885 | H52: =ROUND(D52*(E52+F52),2) -> 2.81
B53: Adicional BVM 1 | D53: =IF($K$12=M5,(D50*(K14)/(K14+L14)),0)+IF($L$12=M5,(D50*(L14)/(K14+L14)),0) -> 0 | F53: =N5 -> 0.04463 | H53: =ROUND(D53*(E53+F53),2) -> 0
B54: Adicional BVM 2 | D54: =IF($K$12=M6,(D50*(K14)/(K14+L14)),0)+IF($L$12=M6,(D50*(L14)/(K14+L14)),0) -> 0 | F54: =N6 -> 0.07877 | H54: =ROUND(D54*(E54+F54),2) -> 0
B55: Adicional Escassez Hídrica | D55: =IF($K$12=M8,(D50*(K14)/(K14+L14)),0)+IF($L$12=M8,(D50*(L14)/(K14+L14)),0) -> 0 | F55: =N4 -> 0.01885 | H55: =ROUND(D55*(E55+F55),2) -> 0
L56: Valor da fatura
B57: Energia Injetada | D57: =D26 -> -57.503 | E57: =IF(AND($B$14<$F$2,$E$14<$F$2),C6*$F$44,IF($B$14<$F$2,(((I6*F44)*C14)+((I6*F45)*D14))/(C14+D14),I6*$F$45)) -> 0.36670351 | F57: =F50 -> 0.33060156 | G57: =E57+F57 -> 0.69730508 | H57: =ROUND((D57*E57),2)+ROUND((D57*F57),2) -> -40.1 | I57: =C6*F44 -> 0.34631757 | J57: =(I57/31)*C14 -> 0.14522995 | L57: 0.39491809
I58: =F6*F45 -> 0.3808539 | J58: =(I58/31)*D14 -> 0.23342659
B59: Adicional BAM | D59: =IF($K$12=M4,($D$57*($K$14)/($K$14+$L$14)),0)+IF($L$12=M4,($D$57*($L$14)/($K$14+$L$14)),0) -> -57.503 | F59: =F52 -> 0.01885 | H59: =ROUND(D59*(E59+F59),2) -> -1.08
B60: Adicional BVM 1 | D60: =IF($K$12=M5,($D$57*($K$14)/($K$14+$L$14)),0)+IF($L$12=M5,($D$57*($L$14)/($K$14+$L$14)),0) -> 0 | F60: =F53 -> 0.04463 | H60: =ROUND(D60*(E60+F60),2) -> 0
B61: Adicional BVM 2 | D61: =IF($K$12=M6,($D$57*($K$14)/($K$14+$L$14)),0)+IF($L$12=M6,($D$57*($L$14)/($K$14+$L$14)),0) -> 0 | F61: =F54 -> 0.07877 | H61: =ROUND(D61*(E61+F61),2) -> 0
B62: Adicional Escassez Hídrica | D62: =IF($K$12=M8,($D$57*($K$14)/($K$14+$L$14)),0)+IF($L$12=M8,($D$57*($L$14)/($K$14+$L$14)),0) -> 0 | F62: =F55 -> 0.01885 | H62: =ROUND(D62*(E62+F62),2) -> 0
H68: =SUM(H50:H67) -> 84.05
H69: 26.35
D70: Base de Cálculo
B71: PIS | D71: =(H50+H52+H53+H54+H55)/(1-E71-E73) -> 133.46478 | E71: =N18 -> 0.011 | H71: =D71*E71 -> 1.4681125
B72: PIS Eneg Inj | D72: =(H57+H59+H60+H61+H62)/(1-E71-E73) -> -43.887882 | E72: =E71 -> 0.011 | H72: =D72*E72 -> -0.48276671
B73: COFINS | D73: =D71 -> 133.46478 | E73: =N20 -> 0.0507 | H73: =D73*E73 -> 6.7666642
B74: COFINS Eneg Inj | D74: =D72 -> -43.887882 | E74: =E73 -> 0.0507 | H74: =D74*E74 -> -2.2251156
B75: ICMS | D75: =D71/(1-E75) -> 160.80094 | E75: 0.17 | H75: =D75*E75 -> 27.336159
B76: ICMS Eneg Inj | D76: =((D57*F57)+(H59+H60+H61+H62)+(D64*F64)+(D66*F66))/(1-E72-E74)/(1-E76) -> -25.797208 | E76: =E75 -> 0.17 | H76: =D76*E76 -> -4.3855253
B78: Informativo Escassez Hídrica | D78: =D50+D57 -> 91.497 | E78: =IF(AND($B$14<$F$2,$E$14<$F$2),C7,IF($B$14<$F$2,I7,F7)) -> 0.00018563466 | F78: =IF(AND($B$14<$F$2,$E$14<$F$2),D7,IF($B$14<$F$2,J7,G7)) -> -0.0021045458 | H78: =D78*(E78+F78) -> -0.17557461

Sheet Fatura B2 (GD II) OK
B2: B2 | E2: Vigência das Tarifas: | F2: ='Fatura B1 (GD II) OK'!F2 -> 46241 | G2: 2025: | H2: 45658 | M2: Bandeira | N2: R$/kWh | O2: ANEEL em 29/06 | Q2: TUSD FIO B
M3: VERDE | N3: 0
B4: TARIFA | C4: ='Fatura B1 (GD II) OK'!C4:E4 -> TARIFA ANTIGA - REH 3370/2024 | F4: ='Fatura B1 (GD II) OK'!F4:H4 -> TARIFA NOVA - REH xxxx/2025 | I4: Tarifas Proporcionalizadas | M4: BAM | N4: ='[1]Fatura B1 (Res) OK'!$N$4 -> 0.01885 | Q4: TARIFA | R4: =C4 -> TARIFA ANTIGA - REH 3370/2024 | U4: =F4 -> TARIFA NOVA - REH xxxx/2025 | X4: Tarifas Proporcionalizadas
C5: Tusd | D5: TE | E5: TUSD + TE | F5: Tusd | G5: TE | H5: TUSD + TE | I5: Tusd | J5: TE | K5: TUSD + TE | M5: BVM1 | N5: ='[1]Fatura B1 (Res) OK'!$N$5 -> 0.04463 | R5: Tusd (R$/kWh) | U5: Tusd (R$/kWh) | X5: Tusd (R$/kWh)
B6: B2 | C6: ='TABELA DE TARIFAS ANTIGAS'!G77/1000 -> 0.46863 | D6: ='TABELA DE TARIFAS ANTIGAS'!H77/1000 -> 0.32068 | E6: =C6+D6 -> 0.78931 | F6: ='TABELA DE TARIFAS NOVAS'!G79/1000 -> 0.50632 | G6: ='TABELA DE TARIFAS NOVAS'!H79/1000 -> 0.33739 | H6: =F6+G6 -> 0.84371 | I6: =((C6*$C$14)+(F6*$D$14))/($D$14+$C$14) -> 0.48621867 | J6: =((D6*$C$14)+(G6*$D$14))/($D$14+$C$14) -> 0.328478 | K6: =I6+J6 -> 0.81469667 | M6: BVM2 | N6: ='[1]Fatura B1 (Res) OK'!$N$6 -> 0.07877 | Q6: =B6 -> B2 | R6: ='FIO B'!H20/1000 -> 0.20383072 | U6: ='FIO B'!K20/1000 -> 0.20915159 | X6: =((R6*$C$14)+(U6*$D$14))/($D$14+$C$14) -> 0.20631379
B7: B1 | C7: ='TABELA DE TARIFAS ANTIGAS'!G71/1000 -> 0.46863 | D7: ='TABELA DE TARIFAS ANTIGAS'!H71/1000 -> 0.32068 | E7: =C7+D7 -> 0.78931 | F7: ='TABELA DE TARIFAS NOVAS'!G73/1000 -> 0.50632 | G7: ='TABELA DE TARIFAS NOVAS'!H73/1000 -> 0.33739 | H7: =F7+G7 -> 0.84371 | I7: =((C7*$C$14)+(F7*$D$14))/($D$14+$C$14) -> 0.48621867 | J7: =((D7*$C$14)+(G7*$D$14))/($D$14+$C$14) -> 0.328478 | K7: =I7+J7 -> 0.81469667
B8: CDE Escassez Hídrica | C8: 0.00018774721 | D8: -0.0044031307 | E8: 0.0036054084 | F8: =T11 -> 0.00018418923 | G8: =U11 -> -0.00053182975 | H8: =F8+G8 -> -0.00034764052 | I8: =((C8*$C$14)+(F8*$D$14))/($D$14+$C$14) -> 0.00018608682 | J8: =((D8*$C$14)+(G8*$D$14))/($D$14+$C$14) -> -0.0025965236 | K8: =I8+J8 -> -0.0024104368 | M8: Escassez Hídrica | N8: 0.142 | P8: CUSTO | R8: Part. TUSD (%) | S8: Part. TE (%) | T8: Tusd (R$/kWh) | U8: TE (R$/kWh)
P9: CDE CONTAS
H10: Fatura | L10: Vigência das Tarifas (troca Bandeira): | M10: =EOMONTH(B14,0)+1 -> 46235 | P10: CDE COVID | U10: 0
B11: INSTALAÇÃO | C11: 1687996 | H11: =E14 -> 46254 | K11: Altere a bandeira na célula abaixo | P11: CDE ESCASSEZ HÍDRICA | T11: ='Fatura B1 (GD II) OK'!T11 -> 0.00018418923 | U11: ='Fatura B1 (GD II) OK'!U11 -> -0.00053182975
K12: ='Fatura B1 (GD II) OK'!K12 -> BAM | L12: ='Fatura B1 (GD II) OK'!L12 -> BAM
B13: Leitura Anterior | C13: Nº de dias tarifa Anterior | D13: Nº de dias tarifa Nova | E13: Leitura Atual | J13: Leitura Anterior | K13: Nº de dias tarifa Anterior | L13: Nº de dias tarifa Nova | M13: Leitura Atual
B14: 46224 | C14: =IF((F2-B14-1)<0,0,(F2-B14-1)) -> 16 | D14: =E14-F2+1 -> 14 | E14: 46254 | J14: =B14 -> 46224 | K14: =IF((M10-J14-1)<0,0,(M10-J14-1)) -> 10 | L14: =M14-M10+1 -> 20 | M14: =E14 -> 46254 | O14: Documento Impressão | Q14: 1025310490
B16: Descrição | C16: Unidade | D16: Quantidade | E16: Preço Unit (R$) com tributos | F16: Valor Total (R$) | G16: PIS/COFINS (R$) | H16: Base de Cálculo ICMS (R$) | I16: Alíquota ICMS (%) | J16: ICMS (R$) | K16: Preço Unit (R$) | L16: Tributos | M16: Base de Cálc (R$) | N16: Alíquota (%) | O16: Valor (R$) | P16: não está contabilizando injetada
R17: TUSD Fio B | S17: Receita Fio B
B18: TUSD - Consumo | C18: kWh | D18: 297 | E18: =(ROUND(D18*K18,2)+ROUND(G18,2)+ROUND(J18,2))/ROUND(D18,4) -> 0.62434343 | F18: =ROUND(D18*E18,2) -> 185.43 | G18: =((D18*K18)/(1-$N$18-$N$20))*($N$18+$N$20) -> 9.4957993 | H18: =(IF($I$18=12%,(D18*K18)/(1-$N$18-$N$20)/(1-$C$48)/$F$48*$C$48,(D18*K18)/(1-$N$18-$N$20)/(1-$I$18))) -> 185.42499 | I18: 0.17 | J18: =(H18*$I$18) -> 31.522249 | K18: =IF(AND($B$14<$F$2,$E$14<$F$2),C6,IF($B$14<$F$2,I6,F6)) -> 0.48621867 | L18: PIS | M18: =D82 -> 263.84952 | N18: ='Fatura B1 (GD II) OK'!N18 -> 0.011 | O18: =ROUND(M18*N18,2) -> 2.9 | R18: =IF(AND($B$14<$F$2,$E$14<$F$2),R6,IF($B$14<$F$2,X6,U6)) -> 0.20631379 | S18: =D18*R18 -> 61.275197
B19: TE - Consumo | C19: kWh | D19: =D18 -> 297 | E19: =(ROUND(D19*K19,2)+ROUND(G19,2)+ROUND(J19,2))/ROUND(D19,4) -> 0.42181818 | F19: =ROUND(D19*E19,2) -> 125.28 | G19: =((D19*K19)/(1-$N$18-$N$20))*($N$18+$N$20) -> 6.4151407 | H19: =(IF($I$18=12%,(D19*K19)/(1-$N$18-$N$20)/(1-$C$48)/$F$48*$C$48,(D19*K19)/(1-$N$18-$N$20)/(1-$I$18))) -> 125.2688 | J19: =(H19*$I$18) -> 21.295697 | K19: =IF(AND($B$14<$F$2,$E$14<$F$2),D6,IF($B$14<$F$2,J6,G6)) -> 0.328478 | L19: PIS Inj | M19: =D83 -> -218.66141 | N19: =N18 -> 0.011 | O19: =ROUND(M19*N19,2) -> -2.41
B20: Adicional BAM | C20: kWh | D20: =IF($K$12=M4,($D$18*($K$14)/($K$14+$L$14)),0)+IF($L$12=M4,($D$18*($L$14)/($K$14+$L$14)),0) -> 297 | E20: =IFERROR((ROUND(D20*K20,2)+ROUND(G20,2)+ROUND(J20,2))/ROUND(D20,4), 0) -> 0.024208754 | F20: =ROUND(D20*E20,2) -> 7.19 | G20: =((D20*K20)/(1-$N$18-$N$20))*($N$18+$N$20) -> 0.36813851 | H20: =(IF($I$18=12%,(D20*K20)/(1-$N$18-$N$20)/(1-$C$48)/$F$48*$C$48,(D20*K20)/(1-$N$18-$N$20)/(1-$I$18))) -> 7.1886609 | J20: =(H20*$I$18) -> 1.2220723 | K20: =N4 -> 0.01885 | L20: COFINS | M20: =M18 -> 263.84952 | N20: ='Fatura B1 (GD II) OK'!N20 -> 0.0507 | O20: =ROUND(M20*N20,2) -> 13.38
B21: Adicional BVM1 | C21: kWh | D21: =IF($K$12=M5,($D$18*($K$14)/($K$14+$L$14)),0)+IF($L$12=M5,($D$18*($L$14)/($K$14+$L$14)),0) -> 0 | E21: =IFERROR((ROUND(D21*K21,2)+ROUND(G21,2)+ROUND(J21,2))/ROUND(D21,4), 0) -> 0 | F21: =ROUND(D21*E21,2) -> 0 | G21: =((D21*K21)/(1-$N$18-$N$20))*($N$18+$N$20) -> 0 | H21: =(IF($I$18=12%,(D21*K21)/(1-$N$18-$N$20)/(1-$C$48)/$F$48*$C$48,(D21*K21)/(1-$N$18-$N$20)/(1-$I$18))) -> 0 | J21: =(H21*$I$18) -> 0 | K21: =N5 -> 0.04463 | L21: COFINS Inj | M21: =M19 -> -218.66141 | N21: =N20 -> 0.0507 | O21: =ROUND(M21*N21,2) -> -11.09
B22: Adicional BVM2 | C22: kWh | D22: =IF($K$12=M6,($D$18*($K$14)/($K$14+$L$14)),0)+IF($L$12=M6,($D$18*($L$14)/($K$14+$L$14)),0) -> 0 | E22: =IFERROR((ROUND(D22*K22,2)+ROUND(G22,2)+ROUND(J22,2))/ROUND(D22,4), 0) -> 0 | F22: =ROUND(D22*E22,2) -> 0 | G22: =((D22*K22)/(1-$N$18-$N$20))*($N$18+$N$20) -> 0 | H22: =(IF($I$18=12%,(D22*K22)/(1-$N$18-$N$20)/(1-$C$48)/$F$48*$C$48,(D22*K22)/(1-$N$18-$N$20)/(1-$I$18))) -> 0 | J22: =(H22*$I$18) -> 0 | K22: =N6 -> 0.07877
B23: Adicional EH | C23: kWh | D23: =IF($K$12=M8,($D$18*($K$14)/($K$14+$L$14)),0)+IF($L$12=M8,($D$18*($L$14)/($K$14+$L$14)),0) -> 0 | E23: =IFERROR((ROUND(D23*K23,2)+ROUND(G23,2)+ROUND(J23,2))/ROUND(D23,4), 0) -> 0 | F23: =ROUND(D23*E23,2) -> 0 | G23: =((D23*K23)/(1-$N$18-$N$20))*($N$18+$N$20) -> 0 | H23: =(IF($I$18=12%,(D23*K23)/(1-$N$18-$N$20)/(1-$C$48)/$F$48*$C$48,(D23*K23)/(1-$N$18-$N$20)/(1-$I$18))) -> 0 | J23: =(H23*$I$18) -> 0 | K23: =N8 -> 0.142
B25: TUSD - Consumo inj | C25: kWh | D25: -297 | E25: =IFERROR((ROUND(D25*K25,2)+ROUND(G25,2)+ROUND(J25,2))/ROUND(D25,4), 0) -> 0.38616162 | F25: =ROUND(D25*E25,2) -> -114.69 | G25: =((D25*K25)/(1-$N$19-$N$21))*($N$19+$N$21) -> -7.0758898 | H25: 0 | I25: 0 | J25: =H25*$I$21 -> 0 | K25: =E68 -> 0.3623107
B26: TE - Consumo inj | C26: kWh | D26: =D25 -> -297 | E26: =IFERROR((ROUND(D26*K26,2)+ROUND(G26,2)+ROUND(J26,2))/ROUND(D26,4), 0) -> 0.42181818 | F26: =ROUND(D26*E26,2) -> -125.28 | G26: =((D26*K26)/(1-$N$19-$N$21))*($N$19+$N$21) -> -6.4151407 | H26: =(IF($I$26=12%,(D26*K26)/(1-$N$19-$N$21)/(1-$C$48)/$F$48*$C$48,(D26*K26)/(1-$N$19-$N$21)/(1-$I$26))) -> -125.2688 | I26: =I18 -> 0.17 | J26: =H26*$I$26 -> -21.295697 | K26: =F68 -> 0.328478
B27: Adicional BAM inj | C27: kWh | D27: =IF($K$12=M4,($D$25*($K$14)/($K$14+$L$14)),0)+IF($L$12=M4,($D$25*($L$14)/($K$14+$L$14)),0) -> -297 | E27: =IFERROR((ROUND(D27*K27,2)+ROUND(G27,2)+ROUND(J27,2))/ROUND(D27,4), 0) -> 0.024208754 | F27: =ROUND(D27*E27,2) -> -7.19 | G27: =((D27*K27)/(1-$N$19-$N$21))*($N$19+$N$21) -> -0.36813851 | H27: =(IF($I$26=12%,(D27*K27)/(1-$N$19-$N$21)/(1-$C$48)/$F$48*$C$48,(D27*K27)/(1-$N$19-$N$21)/(1-$I$26))) -> -7.1886609 | J27: =H27*$I$26 -> -1.2220723 | K27: =K20 -> 0.01885
B28: Adicional BVM1 inj | C28: kWh | D28: =IF($K$12=M5,($D$25*($K$14)/($K$14+$L$14)),0)+IF($L$12=M5,($D$25*($L$14)/($K$14+$L$14)),0) -> 0 | E28: =IFERROR((ROUND(D28*K28,2)+ROUND(G28,2)+ROUND(J28,2))/ROUND(D28,4), 0) -> 0 | F28: =ROUND(D28*E28,2) -> 0 | G28: =((D28*K28)/(1-$N$19-$N$21))*($N$19+$N$21) -> 0 | H28: =(IF($I$26=12%,(D28*K28)/(1-$N$19-$N$21)/(1-$C$48)/$F$48*$C$48,(D28*K28)/(1-$N$19-$N$21)/(1-$I$26))) -> 0 | J28: =H28*$I$26 -> 0 | K28: =K21 -> 0.04463
B29: Adicional BVM2 inj | C29: kWh | D29: =IF($K$12=M6,($D$25*($K$14)/($K$14+$L$14)),0)+IF($L$12=M6,($D$25*($L$14)/($K$14+$L$14)),0) -> 0 | E29: =IFERROR((ROUND(D29*K29,2)+ROUND(G29,2)+ROUND(J29,2))/ROUND(D29,4), 0) -> 0 | F29: =ROUND(D29*E29,2) -> 0 | G29: =((D29*K29)/(1-$N$19-$N$21))*($N$19+$N$21) -> 0 | H29: =(IF($I$26=12%,(D29*K29)/(1-$N$19-$N$21)/(1-$C$48)/$F$48*$C$48,(D29*K29)/(1-$N$19-$N$21)/(1-$I$26))) -> 0 | J29: =H29*$I$26 -> 0 | K29: =K22 -> 0.07877
B30: Adicional EH inj | C30: kWh | D30: =IF($K$12=M8,($D$25*($K$14)/($K$14+$L$14)),0)+IF($L$12=M8,($D$25*($L$14)/($K$14+$L$14)),0) -> 0 | E30: =IFERROR((ROUND(D30*K30,2)+ROUND(G30,2)+ROUND(J30,2))/ROUND(D30,4), 0) -> 0 | F30: =ROUND(D30*E30,2) -> 0 | G30: =((D30*K30)/(1-$N$19-$N$21))*($N$19+$N$21) -> 0 | H30: =(IF($I$26=12%,(D30*K30)/(1-$N$19-$N$21)/(1-$C$48)/$F$48*$C$48,(D30*K30)/(1-$N$19-$N$21)/(1-$I$26))) -> 0 | J30: =H30*$I$26 -> 0 | K30: =K23 -> 0.142
B32: Multas
B33: Juros
B34: Doações | F34: -0.67
B35: Bônus/Descontos
B36: CIP
B38: TOTAL | F38: =SUM(F18:F37) -> 70.07 | G38: =SUM(G18:G37) -> 2.4199095 | H38: =SUM(H18:H37) -> 185.42499 | J38: =SUM(J18:J37) -> 31.522249
B40: Informativo Escassez | C40: =D18 -> 297 | D40: =IF(AND($B$14<$F$2,$E$14<$F$2),C8,IF($B$14<$F$2,I8,F8)) -> 0.00018608682 | E40: =IF(AND($B$14<$F$2,$E$14<$F$2),D8,IF($B$14<$F$2,J8,G8)) -> -0.0025965236 | F40: =C40*(D40+E40) -> -0.71589973
C41: =D25 -> -297 | D41: =IF(AND($B$14<$F$2,$E$14<$F$2),C8*$F$55,IF($B$14<$F$2,(((I8*F55)*C14)+((I8*F56)*D14))/(C14+D14),I8*$F$56)) -> 0.00013866446 | E41: =IF(AND($B$14<$F$2,$E$14<$F$2),D8,IF($B$14<$F$2,J8,G8)) -> -0.0025965236 | F41: =C41*(D41+E41) -> 0.72998417
F42: =SUM(F40:F41) -> 0.014084443
B44: Se for base reduzida: (célula I18 = 12%)
D45: Com tributos
B46: PIS | C46: =N18 -> 0.011 | D46: =((D18*K18)+(D19*K19)+(D20*K20)+(D21*K21)+(D22*K22)+(D23*K23))/(1-$N$21-$N$23) -> 260.78517 | E46: x | F46: =C46 -> 0.011 | G46: =D46*F46 -> 2.8686368
B47: COFINS | C47: =N20 -> 0.0507 | D47: =D46 -> 260.78517 | E47: x | F47: =C47 -> 0.0507 | G47: =D47*F47 -> 13.221808
A48: Rural c/ incrição | B48: ICMS | C48: 0.04 | D48: =H48/F48*C48 -> 91.611958 | E48: x | F48: 0.12 | G48: =D48*F48 -> 10.993435 | H48: =((D18*K18)+(D19*K19)+(D20*K20)+(D21*K21)+(D22*K22)+(D23*K23))/(1-F46-F47)/(1-(C48)) -> 274.83587
E49: =(O36)/(1-C46-C47-C48) -> 0
C50: Base de cálculo reduzida = | D50: Importe
D51: 12% x 4%
B55: Perc. de Redução da Energia Injetada | E55: TUSD | F55: 0.739 | G55: TE | H55: 1 | I55: ='Fatura B1 (GD II) OK'!I44 -> A partir de 01/01/2026
E56: TUSD | F56: 0.7522 | G56: TE | H56: 1 | I56: ='Fatura B1 (GD II) OK'!I45 -> A partir de 07/08/2026
B57: Fatura B2
D58: Qtde | E58: TUSD | F58: TE | G58: TUSD + TE | H58: R$
B59: Fornecimento de Energia Elétrica | H59: =SUM(H61:H66)+SUM(#REF!) -> #REF!
B61: Energia Fornecida | D61: =D18 -> 297 | E61: =IF(AND($B$14<$F$2,$E$14<$F$2),C6,IF($B$14<$F$2,I6,F6)) -> 0.48621867 | F61: =IF(AND($B$14<$F$2,$E$14<$F$2),D6,IF($B$14<$F$2,J6,G6)) -> 0.328478 | G61: =E61+F61 -> 0.81469667 | H61: =ROUND((D61*E61),2)+ROUND((D61*F61),2) -> 241.97
J62: 17.01 | K62: 10.9
B63: Adicional BAM | D63: =IF($K$12=M4,(D61*(K14)/(K14+L14)),0)+IF($L$12=M4,(D61*(L14)/(K14+L14)),0) -> 297 | F63: =N4 -> 0.01885 | H63: =ROUND(D63*(E63+F63),2) -> 5.6 | J63: 205 | K63: 131.26
B64: Adicional BVM 1 | D64: =IF($K$12=M5,(D61*(K14)/(K14+L14)),0)+IF($L$12=M5,(D61*(L14)/(K14+L14)),0) -> 0 | F64: =N5 -> 0.04463 | H64: =ROUND(D64*(E64+F64),2) -> 0 | J64: =SUM(J62:J63) -> 222.01 | K64: =SUM(K62:K63) -> 142.16
B65: Adicional BVM 2 | D65: =IF($K$12=M6,(D61*(K14)/(K14+L14)),0)+IF($L$12=M6,(D61*(L14)/(K14+L14)),0) -> 0 | F65: =N6 -> 0.07877 | H65: =ROUND(D65*(E65+F65),2) -> 0
B66: Adicional Escassez Hídrica | D66: =IF($K$12=M8,(D61*(K14)/(K14+L14)),0)+IF($L$12=M8,(D61*(L14)/(K14+L14)),0) -> 0 | F66: =N8 -> 0.142 | H66: =ROUND(D66*(E66+F66),2) -> 0
B68: Energia Injetada | D68: =D25 -> -297 | E68: =IF(AND($B$14<$F$2,$E$14<$F$2),C6*$F$55,IF($B$14<$F$2,(((I6*F55)*C14)+((I6*F56)*D14))/(C14+D14),I6*$F$56)) -> 0.3623107 | F68: =F61 -> 0.328478 | G68: =E68+F68 -> 0.6907887 | H68: =ROUND((D68*E68),2)+ROUND((D68*F68),2) -> -205.17
B70: Adicional BAM | D70: =IF($K$12=M14,(#REF!*(K24)/(K24+L24)),0)+IF($L$12=M14,(#REF!*(L24)/(K24+L24)),0) -> 0 | F70: =F63 -> 0.01885 | H70: =ROUND(D70*(E70+F70),2) -> 0
B71: Adicional BVM 1 | D71: =IF($K$12=M15,(#REF!*(K24)/(K24+L24)),0)+IF($L$12=M15,(#REF!*(L24)/(K24+L24)),0) -> 0 | F71: =F64 -> 0.04463 | H71: =ROUND(D71*(E71+F71),2) -> 0
B72: Adicional BVM 2 | D72: =IF($K$12=M16,(#REF!*(K24)/(K24+L24)),0)+IF($L$12=M16,(#REF!*(L24)/(K24+L24)),0) -> 0 | F72: =F65 -> 0.07877 | H72: =ROUND(D72*(E72+F72),2) -> 0
B73: Adicional Escassez Hídrica | D73: =IF($K$12=M8,(D68*(K14)/(K14+L14)),0)+IF($L$12=M8,(D68*(L14)/(K14+L14)),0) -> 0 | F73: =F66 -> 0.142 | H73: =ROUND(D73*(E73+F73),2) -> 0
H79: =SUM(H61:H78) -> 42.4
H80: 26.35
D81: Base de Cálculo
B82: PIS | D82: =(H61+H63+H64+H65+H66)/(1-E82-E84) -> 263.84952 | E82: =N18 -> 0.011 | H82: =D82*E82 -> 2.9023447
B83: PIS Eneg Inj | D83: =(H68+H70+H71+H72+H73)/(1-E82-E84) -> -218.66141 | E83: =E82 -> 0.011 | H83: =D83*E83 -> -2.4052755
B84: COFINS | D84: =D82 -> 263.84952 | E84: =N20 -> 0.0507 | H84: =D84*E84 -> 13.37717
B85: COFINS Eneg Inj | D85: =D83 -> -218.66141 | E85: =E84 -> 0.0507 | H85: =D85*E85 -> -11.086133
B86: ICMS | D86: =D82/(1-E86) -> 317.89098 | E86: 0.17 | H86: =D86*E86 -> 54.041467
B87: ICMS Eneg Inj | D87: =((D68*F68)+(H70+H71+H72+H73))/(1-E83-E85)/(1-E87) -> -125.2688 | E87: =E86 -> 0.17 | H87: =D87*E87 -> -21.295697
B89: Informativo Escassez Hídrica | D89: =D61+D68 -> 0 | E89: =IF(AND($B$14<$F$2,$E$14<$F$2),C8,IF($B$14<$F$2,I8,F8)) -> 0.00018608682 | F89: =IF(AND($B$14<$F$2,$E$14<$F$2),E8,IF($B$14<$F$2,K8,H8)) -> -0.0024104368 | H89: =D89*(E89+F89) -> 0

Sheet Fatura B3 (GD II) OK
B2: B3 | E2: Vigência das Tarifas: | F2: ='Fatura B1 (GD II) OK'!F2 -> 46241 | G2: 2025: | H2: 45658 | M2: Bandeira | N2: R$/kWh | O2: ANEEL em 29/06 | Q2: TUSD FIO B
M3: VERDE | N3: 0
B4: TARIFA R$ kWh | C4: ='Fatura B1 (GD II) OK'!C4:E4 -> TARIFA ANTIGA - REH 3370/2024 | F4: ='Fatura B1 (GD II) OK'!F4:H4 -> TARIFA NOVA - REH xxxx/2025 | I4: Tarifas Proporcionalizadas | M4: BAM | N4: =[3]BANDEIRA!$D$5 -> 0.01885 | Q4: TARIFA | R4: =C4 -> TARIFA ANTIGA - REH 3370/2024 | U4: =F4 -> TARIFA NOVA - REH xxxx/2025 | X4: Tarifas Proporcionalizadas
C5: Tusd | D5: TE | E5: TUSD + TE | F5: Tusd | G5: TE | H5: TUSD + TE | I5: Tusd | J5: TE | K5: TUSD + TE | M5: BVM1 | N5: =[3]BANDEIRA!$D$6 -> 0.04463 | R5: Tusd (R$/kWh) | U5: Tusd (R$/kWh) | X5: Tusd (R$/kWh)
B6: B3 | C6: ='TABELA DE TARIFAS ANTIGAS'!G89/1000 -> 0.46863 | D6: ='TABELA DE TARIFAS ANTIGAS'!H89/1000 -> 0.32068 | E6: =C6+D6 -> 0.78931 | F6: ='TABELA DE TARIFAS NOVAS'!G91/1000 -> 0.50632 | G6: ='TABELA DE TARIFAS NOVAS'!H91/1000 -> 0.33739 | H6: =F6+G6 -> 0.84371 | I6: =((C6*$C$14)+(F6*$D$14))/($D$14+$C$14) -> 0.47742433 | J6: =((D6*$C$14)+(G6*$D$14))/($D$14+$C$14) -> 0.324579 | K6: =I6+J6 -> 0.80200333 | M6: BVM2 | N6: =[3]BANDEIRA!$D$7 -> 0.07877 | Q6: =B6 -> B3 | R6: ='FIO B'!H35/1000 -> 0.20383072 | U6: ='FIO B'!K35/1000 -> 0.20915159 | X6: =((R6*$C$14)+(U6*$D$14))/($D$14+$C$14) -> 0.20507226
B7: CDE Escassez Hídrica | C7: 0.00018774721 | D7: -0.0044031307 | E7: 0.0036054084 | F7: =T11 -> 0.00018418923 | G7: =U11 -> -0.00053182975 | H7: =F7+G7 -> -0.00034764052 | I7: =((C7*$C$14)+(F7*$D$14))/($D$14+$C$14) -> 0.00018691702 | J7: =((D7*$C$14)+(G7*$D$14))/($D$14+$C$14) -> -0.0034998272 | K7: =I7+J7 -> -0.0033129102
B8: TE SCEE | G8: =G6*15% -> 0.0506085 | J8: =((D8*$C$14)+(G8*$D$14))/($D$14+$C$14) -> 0.01180865 | M8: Escassez Hídrica | N8: 0.142 | P8: CUSTO | R8: Part. TUSD (%) | S8: Part. TE (%) | T8: Tusd (R$/kWh) | U8: TE (R$/kWh)
P9: CDE CONTAS
H10: Fatura | L10: Vigência das Tarifas (troca Bandeira): | M10: =EOMONTH(B14,0)+1 -> 46235 | P10: CDE COVID | U10: 0
B11: INSTALAÇÃO | C11: 160392975 | H11: =E14 -> 46247 | K11: Altere a bandeira na célula abaixo | P11: CDE ESCASSEZ HÍDRICA | T11: ='Fatura B1 (GD II) OK'!T11 -> 0.00018418923 | U11: ='Fatura B1 (GD II) OK'!U11 -> -0.00053182975
K12: ='Fatura B1 (GD II) OK'!K12 -> BAM | L12: ='Fatura B1 (GD II) OK'!L12 -> BAM
B13: Leitura Anterior | C13: Nº de dias tarifa Anterior | D13: Nº de dias tarifa Nova | E13: Leitura Atual | J13: Leitura Anterior | K13: Nº de dias tarifa Anterior | L13: Nº de dias tarifa Nova | M13: Leitura Atual
B14: 46217 | C14: =IF((F2-B14-1)<0,0,(F2-B14-1)) -> 23 | D14: =E14-F2+1 -> 7 | E14: 46247 | J14: =B14 -> 46217 | K14: =IF((M10-J14-1)<0,0,(M10-J14-1)) -> 17 | L14: =M14-M10+1 -> 13 | M14: =E14 -> 46247 | O14: Documento Impressão | Q14: 1025310638
B16: Descrição | C16: Unidade | D16: Quantidade | E16: Preço Unit (R$) com tributos | F16: Valor Total (R$) | G16: PIS/COFINS (R$) | H16: Base de Cálculo ICMS (R$) | I16: Alíquota ICMS (%) | J16: ICMS (R$) | K16: Preço Unit (R$) | L16: Tributos | M16: Base de Cálc (R$) | N16: Alíquota (%) | O16: Valor (R$) | P16: não está contabilizando injetada
R17: TUSD Fio B | S17: Receita Fio B
B18: TUSD - Consumo | C18: kWh | D18: 1078 | E18: =(ROUND(D18*K18,2)+ROUND(G18,2)+ROUND(J18,2))/ROUND(D18,4) -> 0.61302412 | F18: =ROUND(D18*E18,2) -> 660.84 | G18: =((D18*K18)/(1-$N$18-$N$20))*($N$18+$N$20) -> 33.842837 | H18: =((D18*K18)/(1-$N$18-$N$20)/(1-$I$18)) -> 660.85093 | I18: 0.17 | J18: =(H18*$I$18) -> 112.34466 | K18: =IF(AND($B$14<$F$2,$E$14<$F$2),C6,IF($B$14<$F$2,I6,F6)) -> 0.47742433 | L18: PIS | M18: =D76 -> 943.06725 | N18: ='Fatura B1 (GD II) OK'!N18 -> 0.011 | O18: =ROUND(M18*N18,2) -> 10.37 | R18: =IF(AND($B$14<$F$2,$E$14<$F$2),R6,IF($B$14<$F$2,X6,U6)) -> 0.20507226 | S18: =D18*R18 -> 221.06789
B19: TE - Consumo | C19: kWh | D19: =D18 -> 1078 | E19: =(ROUND(D19*K19,2)+ROUND(G19,2)+ROUND(J19,2))/ROUND(D19,4) -> 0.41678108 | F19: =ROUND(D19*E19,2) -> 449.29 | G19: =((D19*K19)/(1-$N$18-$N$20))*($N$18+$N$20) -> 23.008199 | H19: =((D19*K19)/(1-$N$18-$N$20)/(1-$I$18)) -> 449.28236 | J19: =(H19*$I$18) -> 76.378002 | K19: =IF(AND($B$14<$F$2,$E$14<$F$2),D6,IF($B$14<$F$2,J6,G6)) -> 0.324579 | L19: PIS Inj | M19: =D77 -> -2297.7726 | N19: =N18 -> 0.011 | O19: =ROUND(M19*N19,2) -> -25.28
B20: Adicional BAM | C20: kWh | D20: =IF($K$12=M4,($D$18*($K$14)/($K$14+$L$14)),0)+IF($L$12=M4,($D$18*($L$14)/($K$14+$L$14)),0) -> 1078 | E20: =IFERROR((ROUND(D20*K20,2)+ROUND(G20,2)+ROUND(J20,2))/ROUND(D20,4), 0) -> 0.024211503 | F20: =ROUND(D20*E20,2) -> 26.1 | G20: =((D20*K20)/(1-$N$18-$N$20))*($N$18+$N$20) -> 1.3362064 | H20: =((D20*K20)/(1-$N$18-$N$20)/(1-$I$18)) -> 26.092176 | J20: =(H20*$I$18) -> 4.43567 | K20: =N4 -> 0.01885 | L20: COFINS | M20: =M18 -> 943.06725 | N20: ='Fatura B1 (GD II) OK'!N20 -> 0.0507 | O20: =ROUND(M20*N20,2) -> 47.81
B21: Adicional BVM1 | C21: kWh | D21: =IF($K$12=M5,($D$18*($K$14)/($K$14+$L$14)),0)+IF($L$12=M5,($D$18*($L$14)/($K$14+$L$14)),0) -> 0 | E21: =IFERROR((ROUND(D21*K21,2)+ROUND(G21,2)+ROUND(J21,2))/ROUND(D21,4), 0) -> 0 | F21: =ROUND(D21*E21,2) -> 0 | G21: =((D21*K21)/(1-$N$18-$N$20))*($N$18+$N$20) -> 0 | H21: =((D21*K21)/(1-$N$18-$N$20)/(1-$I$18)) -> 0 | J21: =(H21*$I$18) -> 0 | K21: =N5 -> 0.04463 | L21: COFINS Inj | M21: =M19 -> -2297.7726 | N21: =N20 -> 0.0507 | O21: =ROUND(M21*N21,2) -> -116.5
B22: Adicional BVM2 | C22: kWh | D22: =IF($K$12=M6,($D$18*($K$14)/($K$14+$L$14)),0)+IF($L$12=M6,($D$18*($L$14)/($K$14+$L$14)),0) -> 0 | E22: =IFERROR((ROUND(D22*K22,2)+ROUND(G22,2)+ROUND(J22,2))/ROUND(D22,4), 0) -> 0 | F22: =ROUND(D22*E22,2) -> 0 | G22: =((D22*K22)/(1-$N$18-$N$20))*($N$18+$N$20) -> 0 | H22: =((D22*K22)/(1-$N$18-$N$20)/(1-$I$18)) -> 0 | J22: =(H22*$I$18) -> 0 | K22: =N6 -> 0.07877
B23: Adicional EH | C23: kWh | D23: =IF($K$12=M7,($D$18*($K$14)/($K$14+$L$14)),0)+IF($L$12=M7,($D$18*($L$14)/($K$14+$L$14)),0) -> 0 | E23: =IFERROR((ROUND(D23*K23,2)+ROUND(G23,2)+ROUND(J23,2))/ROUND(D23,4), 0) -> 0 | F23: =ROUND(D23*E23,2) -> 0 | G23: =((D23*K23)/(1-$N$18-$N$20))*($N$18+$N$20) -> 0 | H23: =((D23*K23)/(1-$N$18-$N$20)/(1-$I$18)) -> 0 | J23: =(H23*$I$18) -> 0 | K23: =N8 -> 0.142
B25: TUSD - Consumo inj | C25: kWh | D25: -1078 | E25: =IFERROR((ROUND(D25*K25,2)+ROUND(G25,2)+ROUND(J25,2))/ROUND(D25,4),0) -> 0.37757885 | F25: =ROUND(D25*E25,2) -> -407.03 | G25: =((D25*K25)/(1-$N$19-$N$21))*($N$19+$N$21) -> -25.114092 | H25: 0 | I25: 0 | J25: =H25*$I$21 -> 0 | K25: =E62 -> 0.35428705
B26: TE - Consumo inj | C26: kWh | D26: =D25 -> -1078 | E26: =IFERROR((ROUND(D26*K26,2)+ROUND(G26,2)+ROUND(J26,2))/ROUND(D26,4),0) -> 0.41678108 | F26: =ROUND(D26*E26,2) -> -449.29 | G26: =((D26*K26)/(1-$N$19-$N$21))*($N$19+$N$21) -> -23.008199 | H26: =ROUND((D26*K26)/(1-$N$19-$N$21)/(1-$I$26),8) -> -449.28236 | I26: =I18 -> 0.17 | J26: =H26*$I$26 -> -76.378002 | K26: =F62 -> 0.324579
B27: Adicional BAM inj | C27: kWh | D27: =IF($K$12=M4,($D$25*($K$14)/($K$14+$L$14)),0)+IF($L$12=M4,($D$25*($L$14)/($K$14+$L$14)),0) -> -1078 | E27: =IFERROR((ROUND(D27*K27,2)+ROUND(G27,2)+ROUND(J27,2))/ROUND(D27,4),0) -> 0.024211503 | F27: =ROUND(D27*E27,2) -> -26.1 | G27: =((D27*K27)/(1-$N$19-$N$21))*($N$19+$N$21) -> -1.3362064 | H27: =ROUND((D27*K27)/(1-$N$19-$N$21)/(1-$I$26),8) -> -26.092176 | J27: =H27*$I$26 -> -4.43567 | K27: =K20 -> 0.01885
B28: Adicional BVM1 inj | C28: kWh | D28: =IF($K$12=M5,($D$25*($K$14)/($K$14+$L$14)),0)+IF($L$12=M5,($D$25*($L$14)/($K$14+$L$14)),0) -> 0 | E28: =IFERROR((ROUND(D28*K28,2)+ROUND(G28,2)+ROUND(J28,2))/ROUND(D28,4),0) -> 0 | F28: =ROUND(D28*E28,2) -> 0 | G28: =((D28*K28)/(1-$N$19-$N$21))*($N$19+$N$21) -> 0 | H28: =ROUND((D28*K28)/(1-$N$19-$N$21)/(1-$I$26),8) -> 0 | J28: =H28*$I$26 -> 0 | K28: =K21 -> 0.04463
B29: Adicional BVM2 inj | C29: kWh | D29: =IF($K$12=M6,($D$25*($K$14)/($K$14+$L$14)),0)+IF($L$12=M6,($D$25*($L$14)/($K$14+$L$14)),0) -> 0 | E29: =IFERROR((ROUND(D29*K29,2)+ROUND(G29,2)+ROUND(J29,2))/ROUND(D29,4),0) -> 0 | F29: =ROUND(D29*E29,2) -> 0 | G29: =((D29*K29)/(1-$N$19-$N$21))*($N$19+$N$21) -> 0 | H29: =ROUND((D29*K29)/(1-$N$19-$N$21)/(1-$I$26),8) -> 0 | J29: =H29*$I$26 -> 0 | K29: =K22 -> 0.07877
B30: Adicional EH inj | C30: kWh | D30: =IF($K$12=M8,($D$25*($K$14)/($K$14+$L$14)),0)+IF($L$12=M8,($D$25*($L$14)/($K$14+$L$14)),0) -> 0 | E30: =IFERROR((ROUND(D30*K30,2)+ROUND(G30,2)+ROUND(J30,2))/ROUND(D30,4),0) -> 0 | F30: =ROUND(D30*E30,2) -> 0 | G30: =((D30*K30)/(1-$N$19-$N$21))*($N$19+$N$21) -> 0 | H30: =ROUND((D30*K30)/(1-$N$19-$N$21)/(1-$I$26),8) -> 0 | J30: =H30*$I$26 -> 0 | K30: =K23 -> 0.142
B32: Multas | F32: 0.43
B33: Juros
B34: Doações | F34: 2.94
B35: Bônus/Descontos
B36: CIP | F36: 77.47
B38: TOTAL | F38: =SUM(F18:F37) -> 334.65 | G38: =SUM(G18:G37) -> 8.7287445 | H38: =SUM(H18:H37) -> 660.85093 | J38: =SUM(J18:J37) -> 112.34466
B40: Informativo Escassez Hídrica | D40: =D18 -> 1078 | E40: =IF(AND($B$14<$F$2,$E$14<$F$2),C7,IF($B$14<$F$2,I7,F7)) -> 0.00018691702 | F40: =IF(AND($B$14<$F$2,$E$14<$F$2),D7,IF($B$14<$F$2,J7,G7)) -> -0.0034998272 | G40: =D40*(E40+F40) -> -3.5713171
D41: =D25 -> -1078 | E41: =IF(AND($B$14<$F$2,$E$14<$F$2),C7*$F$49,IF($B$14<$F$2,(((I7*F49)*C14)+((I7*F50)*D14))/(C14+D14),I7*$F$50)) -> 0.00013870738 | F41: =IF(AND($B$14<$F$2,$E$14<$F$2),D7,IF($B$14<$F$2,J7,G7)) -> -0.0034998272 | G41: =D41*(E41+F41) -> 3.6232871
G42: =SUM(G40:G41) -> 0.051969989
B49: Perc. de Redução da Energia Injetada | E49: TUSD | F49: 0.739 | G49: TE | H49: 1 | I49: ='Fatura B1 (GD II) OK'!I44 -> A partir de 01/01/2026 | K49: =C6*F49 -> 0.34631757 | L49: =(K49*C14)/(C14+D14) -> 0.26551014
E50: TUSD | F50: 0.7522 | G50: TE | H50: 1 | I50: ='Fatura B1 (GD II) OK'!I45 -> A partir de 07/08/2026 | K50: =F6*F50 -> 0.3808539 | L50: =(K50*D14)/(C14+D14) -> 0.088865911
B51: Fatura B1 Residencial
D52: Qtde | E52: TUSD | F52: TE | G52: TUSD + TE | H52: R$
B53: Fornecimento de Energia Elétrica | H53: =SUM(H55:H71)+SUM(H76:H81) -> 161.49943
B55: Energia Fornecida | D55: =D18 -> 1078 | E55: =IF(AND($B$14<$F$2,$E$14<$F$2),C6,IF($B$14<$F$2,I6,F6)) -> 0.47742433 | F55: =IF(AND($B$14<$F$2,$E$14<$F$2),D6,IF($B$14<$F$2,J6,G6)) -> 0.324579 | G55: =E55+F55 -> 0.80200333 | H55: =ROUND((D55*E55),2)+ROUND((D55*F55),2) -> 864.56
B57: Adicional BAM | D57: =IF($K$12=M4,(D55*(K14)/(K14+L14)),0)+IF($L$12=M4,(D55*(L14)/(K14+L14)),0) -> 1078 | F57: =N4 -> 0.01885 | H57: =ROUND(D57*(E57+F57),2) -> 20.32
B58: Adicional BVM 1 | D58: =IF($K$12=M5,(D55*(K14)/(K14+L14)),0)+IF($L$12=M5,(D55*(L14)/(K14+L14)),0) -> 0 | F58: =N5 -> 0.04463 | H58: =ROUND(D58*(E58+F58),2) -> 0
B59: Adicional BVM 2 | D59: =IF($K$12=M6,(D55*(K14)/(K14+L14)),0)+IF($L$12=M6,(D55*(L14)/(K14+L14)),0) -> 0 | F59: =N6 -> 0.07877 | H59: =ROUND(D59*(E59+F59),2) -> 0
B60: Adicional Escassez Hídrica | D60: =IF($K$12=M8,(D55*(K14)/(K14+L14)),0)+IF($L$12=M8,(D55*(L14)/(K14+L14)),0) -> 0 | F60: =N8 -> 0.142 | H60: =ROUND(D60*(E60+F60),2) -> 0
B62: Energia Injetada | D62: =D25 -> -1078 | E62: =IF(AND($B$14<$F$2,$E$14<$F$2),C6*$F$49,IF($B$14<$F$2,(((I6*F49)*C14)+((I6*F50)*D14))/(C14+D14),I6*$F$50)) -> 0.35428705 | F62: =F55 -> 0.324579 | G62: =E62+F62 -> 0.67886605 | H62: =ROUND((D62*E62),2)+ROUND((D62*F62),2) -> -731.82
B64: Adicional BAM | D64: =IF($K$12=M4,($D$62*($K$14)/($K$14+$L$14)),0)+IF($L$12=M4,($D$62*($L$14)/($K$14+$L$14)),0) -> -1078 | F64: =F57 -> 0.01885 | H64: =ROUND(D64*(E64+F64),2) -> -20.32
B65: Adicional BVM 1 | D65: =IF($K$12=M5,($D$62*($K$14)/($K$14+$L$14)),0)+IF($L$12=M5,($D$62*($L$14)/($K$14+$L$14)),0) -> 0 | F65: =F58 -> 0.04463 | H65: =ROUND(D65*(E65+F65),2) -> 0
B66: Adicional BVM 2 | D66: =IF($K$12=M6,($D$62*($K$14)/($K$14+$L$14)),0)+IF($L$12=M6,($D$62*($L$14)/($K$14+$L$14)),0) -> 0 | F66: =F59 -> 0.07877 | H66: =ROUND(D66*(E66+F66),2) -> 0
B67: Adicional Escassez Hídrica | D67: =IF($K$12=M8,($D$62*($K$14)/($K$14+$L$14)),0)+IF($L$12=M8,($D$62*($L$14)/($K$14+$L$14)),0) -> 0 | F67: =F60 -> 0.142 | H67: =ROUND(D67*(E67+F67),2) -> 0
H73: =SUM(H55:H72) -> 132.74
D75: Base de Cálculo
B76: PIS | D76: =(H55+H57+H58+H59+H60)/(1-E76-E78) -> 943.06725 | E76: =N18 -> 0.011 | H76: =D76*E76 -> 10.37374
B77: PIS Eneg Inj | D77: =(D62+D64+D65+D66+D67)/(1-E76-E78) -> -2297.7726 | E77: =E76 -> 0.011 | H77: =D77*E77 -> -25.275498
B78: COFINS | D78: =D76 -> 943.06725 | E78: =N20 -> 0.0507 | H78: =D78*E78 -> 47.81351
B79: COFINS Eneg Inj | D79: =D77 -> -2297.7726 | E79: =E78 -> 0.0507 | H79: =D79*E79 -> -116.49707
B80: ICMS | D80: =D76/(1-E80) -> 1136.2256 | E80: 0.17 | H80: =D80*E80 -> 193.15835
B81: ICMS Eneg Inj | D81: =((D62*F62)+(H64+H65+H66+H67))/(1-E77-E79)/(1-E81) -> -475.37415 | E81: =E80 -> 0.17 | H81: =D81*E81 -> -80.813606
B83: Informativo Escassez Hídrica | D83: =D55+D62 -> 0 | E83: =IF(AND($B$14<$F$2,$E$14<$F$2),C7,IF($B$14<$F$2,I7,F7)) -> 0.00018691702 | F83: =IF(AND($B$14<$F$2,$E$14<$F$2),D7,IF($B$14<$F$2,J7,G7)) -> -0.0034998272 | H83: =D83*(E83+F83) -> 0

Sheet Fatura B2 IRRIG (GD II) OK
B2: B2 | E2: Vigência das Tarifas: | F2: ='Fatura B1 (GD II) OK'!F2 -> 46241 | G2: 2025: | H2: 45658 | M2: Bandeira | N2: R$/kWh | O2: ANEEL em 29/06 | Q2: TUSD FIO B
M3: VERDE | N3: 0
B4: TARIFA | C4: ='Fatura B1 (GD II) OK'!C4:E4 -> TARIFA ANTIGA - REH 3370/2024 | F4: ='Fatura B1 (GD II) OK'!F4:H4 -> TARIFA NOVA - REH xxxx/2025 | I4: Tarifas Proporcionalizadas | M4: BAM | N4: ='[1]Fatura B1 (Res) OK'!$N$4 -> 0.01885 | Q4: TARIFA | R4: =C4 -> TARIFA ANTIGA - REH 3370/2024 | U4: =F4 -> TARIFA NOVA - REH xxxx/2025 | X4: Tarifas Proporcionalizadas
C5: Tusd | D5: TE | E5: TUSD + TE | F5: Tusd | G5: TE | H5: TUSD + TE | I5: Tusd | J5: TE | K5: TUSD + TE | M5: BVM1 | N5: ='[1]Fatura B1 (Res) OK'!$N$5 -> 0.04463 | R5: Tusd (R$/kWh) | U5: Tusd (R$/kWh) | X5: Tusd (R$/kWh)
B6: B2 | C6: ='TABELA DE TARIFAS ANTIGAS'!G77/1000 -> 0.46863 | D6: ='TABELA DE TARIFAS ANTIGAS'!H77/1000 -> 0.32068 | E6: =C6+D6 -> 0.78931 | F6: ='TABELA DE TARIFAS NOVAS'!G79/1000 -> 0.50632 | G6: ='TABELA DE TARIFAS NOVAS'!H79/1000 -> 0.33739 | H6: =F6+G6 -> 0.84371 | I6: =((C6*$C$14)+(F6*$D$14))/($D$14+$C$14) -> 0.48621867 | J6: =((D6*$C$14)+(G6*$D$14))/($D$14+$C$14) -> 0.328478 | K6: =I6+J6 -> 0.81469667 | M6: BVM2 | N6: ='[1]Fatura B1 (Res) OK'!$N$6 -> 0.07877 | Q6: =B6 -> B2 | R6: ='FIO B'!H20/1000 -> 0.20383072 | U6: ='FIO B'!K20/1000 -> 0.20915159 | X6: =((R6*$C$14)+(U6*$D$14))/($D$14+$C$14) -> 0.20631379
B7: CDE Escassez Hídrica | C7: 0.00018774721 | D7: -0.0044031307 | E7: 0.0036054084 | F7: =T11 -> 0.00018418923 | G7: =U11 -> -0.00053182975 | H7: =F7+G7 -> -0.00034764052 | I7: =((C7*$C$14)+(F7*$D$14))/($D$14+$C$14) -> 0.00018608682 | J7: =((D7*$C$14)+(G7*$D$14))/($D$14+$C$14) -> -0.0025965236 | K7: =I7+J7 -> -0.0024104368
B8: TE SCEE | G8: =G6*15% -> 0.0506085 | J8: =((D8*$C$14)+(G8*$D$14))/($D$14+$C$14) -> 0.0236173 | M8: Escassez Hídrica | N8: 0.142 | P8: CUSTO | R8: Part. TUSD (%) | S8: Part. TE (%) | T8: Tusd (R$/kWh) | U8: TE (R$/kWh)
P9: CDE CONTAS
H10: Fatura | L10: Vigência das Tarifas (troca Bandeira): | M10: =EOMONTH(B14,0)+1 -> 46235 | P10: CDE COVID | U10: 0
B11: INSTALAÇÃO | C11: 160846277 | H11: =E14 -> 46254 | K11: Altere a bandeira na célula abaixo | P11: CDE ESCASSEZ HÍDRICA | T11: ='Fatura B1 (GD II) OK'!T11 -> 0.00018418923 | U11: ='Fatura B1 (GD II) OK'!U11 -> -0.00053182975
K12: ='Fatura B1 (GD II) OK'!K12 -> BAM | L12: ='Fatura B1 (GD II) OK'!L12 -> BAM
B13: Leitura Anterior | C13: Nº de dias tarifa Anterior | D13: Nº de dias tarifa Nova | E13: Leitura Atual | J13: Leitura Anterior | K13: Nº de dias tarifa Anterior | L13: Nº de dias tarifa Nova | M13: Leitura Atual
B14: 46224 | C14: =IF((F2-B14-1)<0,0,(F2-B14-1)) -> 16 | D14: =E14-F2+1 -> 14 | E14: 46254 | J14: =B14 -> 46224 | K14: =IF((M10-J14-1)<0,0,(M10-J14-1)) -> 10 | L14: =M14-M10+1 -> 20 | M14: =E14 -> 46254 | O14: Documento Impressão | Q14: 1025310493
N15: desconto: | O15: 0.6
B16: Descrição | C16: Unidade | D16: Quantidade | E16: Preço Unit (R$) com tributos | F16: Valor Total (R$) | G16: PIS/COFINS (R$) | H16: Base de Cálculo ICMS (R$) | I16: Alíquota ICMS (%) | J16: ICMS (R$) | K16: Preço Unit (R$) | L16: Tributos | M16: Base de Cálc (R$) | N16: Alíquota (%) | O16: Valor (R$) | P16: não está contabilizando injetada
R17: TUSD Fio B | S17: Receita Fio B
B18: TUSD - Ativo | C18: kWh | D18: 6812 | E18: =IFERROR((ROUND(D18*K18,2)+ROUND(G18,2)+ROUND(J18,2))/ROUND(D18,4), 0) -> 0.53978274 | F18: =ROUND(D18*E18,2) -> 3677 | G18: =((D18*K18)/(1-$N$18-$N$20))*($N$18+$N$20) -> 217.79591 | H18: =(IF($I$18=12%,(D18*K18)/(1-$N$18-$N$20)/(1-$C$124)/$F$124*$C$124,(D18*K18)/(1-$N$18-$N$20)/(1-$I$18))) -> 1225.6658 | I18: 0.12 | J18: =(H18*$I$18) -> 147.07989 | K18: =IF(AND($B$14<$F$2,$E$14<$F$2),C6,IF($B$14<$F$2,I6,F6)) -> 0.48621867 | L18: PIS | M18: =D112 -> 6219.222 | N18: ='Fatura B1 (GD II) OK'!N18 -> 0.011 | O18: =ROUND(M18*N18,2) -> 68.41 | R18: =IF(AND($B$14<$F$2,$E$14<$F$2),R6,IF($B$14<$F$2,X6,U6)) -> 0.20631379 | S18: =D18*R18 -> 1405.4096
B19: TUSD - Consumo Reservado | C19: kWh | D19: 472 | E19: =IFERROR((ROUND(D19*K19,2)+ROUND(G19,2)+ROUND(J19,2))/ROUND(D19,4), 0) -> 0.2159322 | F19: =ROUND(D19*E19,2) -> 101.92 | G19: =((D19*K19)/(1-$N$18-$N$20))*($N$18+$N$20) -> 6.0363869 | H19: =(IF($I$18=12%,(D19*K19)/(1-$N$18-$N$20)/(1-$C$124)/$F$124*$C$124,(D19*K19)/(1-$N$18-$N$20)/(1-$I$18))) -> 33.970302 | I19: =I18 -> 0.12 | J19: =(H19*$I$18) -> 4.0764363 | K19: =(K18+(K18*(-$H$57))) -> 0.19448747 | L19: PIS Inj | M19: =D113 -> -0.75668763 | N19: =N18 -> 0.011 | O19: =ROUND(M19*N19,2) -> -0.01 | R19: =IF(AND($B$14<$F$2,$E$14<$F$2),R6,IF($B$14<$F$2,X6,U6)) -> 0.20631379 | S19: =D19*R19 -> 97.380111
B20: TE - Consumo | C20: kWh | D20: =D18 -> 6812 | E20: =IFERROR((ROUND(D20*K20,2)+ROUND(G20,2)+ROUND(J20,2))/ROUND(D20,4), 0) -> 0.36466383 | F20: =ROUND(D20*E20,2) -> 2484.09 | G20: =((D20*K20)/(1-$N$18-$N$20))*($N$18+$N$20) -> 147.13784 | H20: =(IF($I$18=12%,(D20*K20)/(1-$N$18-$N$20)/(1-$C$124)/$F$124*$C$124,(D20*K20)/(1-$N$18-$N$20)/(1-$I$18))) -> 828.03124 | J20: =(H20*$I$18) -> 99.363749 | K20: =IF(AND($B$14<$F$2,$E$14<$F$2),D6,IF($B$14<$F$2,J6,G6)) -> 0.328478 | L20: COFINS | M20: =M18 -> 6219.222 | N20: ='Fatura B1 (GD II) OK'!N20 -> 0.0507 | O20: =ROUND(M20*N20,2) -> 315.31 | S20: =-S19*60% -> -58.428067
B21: TE - Consumo Reservado | C21: kWh | D21: =D19 -> 472 | E21: =IFERROR((ROUND(D21*K21,2)+ROUND(G21,2)+ROUND(J21,2))/ROUND(D21,4), 0) -> 0.14586864 | F21: =ROUND(D21*E21,2) -> 68.85 | G21: =((D21*K21)/(1-$N$18-$N$20))*($N$18+$N$20) -> 4.0780423 | H21: =(IF($I$18=12%,(D21*K21)/(1-$N$18-$N$20)/(1-$C$124)/$F$124*$C$124,(D21*K21)/(1-$N$18-$N$20)/(1-$I$18))) -> 22.949545 | J21: =(H21*$I$18) -> 2.7539454 | K21: =ROUND(K20+(K20*(-$H$57)),8) -> 0.1313912 | L21: COFINS Inj | M21: =M19 -> -0.75668763 | N21: =N20 -> 0.0507 | O21: =ROUND(M21*N21,2) -> -0.04 | S21: =SUM(S18:S20) -> 1444.3616
B22: Adicional BAM | C22: kWh | D22: =IF($K$12=M4,(($D$18+$D$19)*($K$14)/($K$14+$L$14)),0)+IF($L$12=M4,(($D$18+$D$19)*($L$14)/($K$14+$L$14)),0) -> 7284 | E22: =IFERROR((ROUND(D22*K22,2)+ROUND(G22,2)+ROUND(J22,2))/ROUND(D22,4), 0) -> 0.020113948 | F22: =ROUND(D22*E22,2) -> 146.51 | G22: =((D22*K22)/(1-$N$18-$N$20))*($N$18+$N$20) -> 8.6776569 | H22: =(IF($I$18=12%,(D22*K22)/(1-$N$18-$N$20)/(1-$C$124)/$F$124*$C$124,(D22*K22)/(1-$N$18-$N$20)/(1-$I$18))) -> 48.834284 | J22: =(H22*$I$18) -> 5.860114 | K22: =J63 -> 0.018117117 | Q22: 838840 | R22: massa
B23: Adicional BVM1 | C23: kWh | D23: =IF($K$12=M5,(($D$18+$D$19)*($K$14)/($K$14+$L$14)),0)+IF($L$12=M5,(($D$18+$D$19)*($L$14)/($K$14+$L$14)),0) -> 0 | E23: =IFERROR((ROUND(D23*K23,2)+ROUND(G23,2)+ROUND(J23,2))/ROUND(D23,4), 0) -> 0 | F23: =ROUND(D23*E23,2) -> 0 | G23: =((D23*K23)/(1-$N$18-$N$20))*($N$18+$N$20) -> 0 | H23: =(IF($I$18=12%,(D23*K23)/(1-$N$18-$N$20)/(1-$C$124)/$F$124*$C$124,(D23*K23)/(1-$N$18-$N$20)/(1-$I$18))) -> 0 | J23: =(H23*$I$18) -> 0 | K23: =J64 -> 0
B24: Adicional BVM2 | C24: kWh | D24: =IF($K$12=M6,(($D$18+$D$19)*($K$14)/($K$14+$L$14)),0)+IF($L$12=M6,(($D$18+$D$19)*($L$14)/($K$14+$L$14)),0) -> 0 | E24: =IFERROR((ROUND(D24*K24,2)+ROUND(G24,2)+ROUND(J24,2))/ROUND(D24,4), 0) -> 0 | F24: =ROUND(D24*E24,2) -> 0 | G24: =((D24*K24)/(1-$N$18-$N$20))*($N$18+$N$20) -> 0 | H24: =(IF($I$18=12%,(D24*K24)/(1-$N$18-$N$20)/(1-$C$124)/$F$124*$C$124,(D24*K24)/(1-$N$18-$N$20)/(1-$I$18))) -> 0 | J24: =(H24*$I$18) -> 0 | K24: =J65 -> 0
B25: Adicional EH | C25: kWh | D25: =IF($K$12=M7,(($D$18+$D$19)*($K$14)/($K$14+$L$14)),0)+IF($L$12=M7,(($D$18+$D$19)*($L$14)/($K$14+$L$14)),0) -> 0 | E25: =IFERROR((ROUND(D25*K25,2)+ROUND(G25,2)+ROUND(J25,2))/ROUND(D25,4), 0) -> 0 | F25: =ROUND(D25*E25,2) -> 0 | G25: =((D25*K25)/(1-$N$18-$N$20))*($N$18+$N$20) -> 0 | H25: =(IF($I$18=12%,(D25*K25)/(1-$N$18-$N$20)/(1-$C$124)/$F$124*$C$124,(D25*K25)/(1-$N$18-$N$20)/(1-$I$18))) -> 0 | J25: =(H25*$I$18) -> 0 | K25: =J66 -> 0
B27: TUSD - Consumo inj Reservado | C27: kWh | D27: 0 | E27: =IFERROR((ROUND(D27*K27,2)+ROUND(G27,2)+ROUND(J27,2))/ROUND(D27,4), 0) -> 0 | F27: =ROUND(D27*E27,2) -> 0 | G27: =((D27*K27)/(1-$N$19-$N$21))*($N$19+$N$21) -> 0 | H27: 0 | I27: 0 | J27: =H27*$I$21 -> 0 | K27: =(K28+(K28*(-$H$57))) -> 0.14492428
B28: TUSD - Consumo inj | C28: kWh | D28: -1 | E28: =IFERROR((ROUND(D28*K28,2)+ROUND(G28,2)+ROUND(J28,2))/ROUND(D28,4), 0) -> 0.38 | F28: =ROUND(D28*E28,2) -> -0.38 | G28: =((D28*K28)/(1-$N$19-$N$21))*($N$19+$N$21) -> -0.023824545 | H28: 0 | I28: 0 | J28: =H28*$I$21 -> 0 | K28: =E81 -> 0.3623107
B29: TE - Consumo inj Reservado | C29: kWh | D29: =D27 -> 0 | E29: =IFERROR((ROUND(D29*K29,2)+ROUND(G29,2)+ROUND(J29,2))/ROUND(D29,4), 0) -> 0 | F29: =ROUND(D29*E29,2) -> 0 | G29: =((D29*K29)/(1-$N$19-$N$21))*($N$19+$N$21) -> 0 | H29: =(IF($I$29=12%,(D29*K29)/(1-$N$19-$N$21)/(1-$C$130)/$F$130*$C$130,(D29*K29)/(1-$N$19-$N$21)/(1-$I$29))) -> 0 | I29: =I18 -> 0.12 | J29: =H29*$I$29 -> 0 | K29: =K30+(K30*(-$H$57)) -> 0.1313912
B30: TE - Consumo inj | C30: kWh | D30: =D28 -> -1 | E30: =IFERROR((ROUND(D30*K30,2)+ROUND(G30,2)+ROUND(J30,2))/ROUND(D30,4), 0) -> 0.36 | F30: =ROUND(D30*E30,2) -> -0.36 | G30: =((D30*K30)/(1-$N$19-$N$21))*($N$19+$N$21) -> -0.0215998 | H30: =(IF($I$29=12%,(D30*K30)/(1-$N$19-$N$21)/(1-$C$130)/$F$130*$C$130,(D30*K30)/(1-$N$19-$N$21)/(1-$I$29))) -> -0.12155479 | I30: =I19 -> 0.12 | J30: =H30*$I$29 -> -0.014586575 | K30: =K20 -> 0.328478
B31: Adicional BAM inj | C31: kWh | D31: =IF($K$12=M4,(($D$27+$D$28)*($K$14)/($K$14+$L$14)),0)+IF($L$12=M4,(($D$27+$D$28)*($L$14)/($K$14+$L$14)),0) -> -1 | E31: =IFERROR((ROUND(D31*K31,2)+ROUND(G31,2)+ROUND(J31,2))/ROUND(D31,4), 0) -> 0.02 | F31: =ROUND(D31*E31,2) -> -0.02 | G31: =((D31*K31)/(1-$N$19-$N$21))*($N$19+$N$21) -> -0.0012395236 | H31: =(IF($I$29=12%,(D31*K31)/(1-$N$19-$N$21)/(1-$C$130)/$F$130*$C$130,(D31*K31)/(1-$N$19-$N$21)/(1-$I$29))) -> -0.006975529 | J31: =H31*$I$29 -> -0.00083706348 | K31: =J84 -> 0.01885
B32: Adicional BVM1 inj | C32: kWh | D32: =IF($K$12=M5,(($D$27+$D$28)*($K$14)/($K$14+$L$14)),0)+IF($L$12=M5,(($D$27+$D$28)*($L$14)/($K$14+$L$14)),0) -> 0 | E32: =IFERROR((ROUND(D32*K32,2)+ROUND(G32,2)+ROUND(J32,2))/ROUND(D32,4), 0) -> 0 | F32: =ROUND(D32*E32,2) -> 0 | G32: =((D32*K32)/(1-$N$19-$N$21))*($N$19+$N$21) -> 0 | H32: =(IF($I$29=12%,(D32*K32)/(1-$N$19-$N$21)/(1-$C$130)/$F$130*$C$130,(D32*K32)/(1-$N$19-$N$21)/(1-$I$29))) -> 0 | J32: =H32*$I$29 -> 0 | K32: =J85 -> 0
B33: Adicional BVM2 inj | C33: kWh | D33: =IF($K$12=M6,(($D$27+$D$28)*($K$14)/($K$14+$L$14)),0)+IF($L$12=M6,(($D$27+$D$28)*($L$14)/($K$14+$L$14)),0) -> 0 | E33: =IFERROR((ROUND(D33*K33,2)+ROUND(G33,2)+ROUND(J33,2))/ROUND(D33,4), 0) -> 0 | F33: =ROUND(D33*E33,2) -> 0 | G33: =((D33*K33)/(1-$N$19-$N$21))*($N$19+$N$21) -> 0 | H33: =(IF($I$29=12%,(D33*K33)/(1-$N$19-$N$21)/(1-$C$130)/$F$130*$C$130,(D33*K33)/(1-$N$19-$N$21)/(1-$I$29))) -> 0 | J33: =H33*$I$29 -> 0 | K33: =J86 -> 0
B34: Adicional EH inj | C34: kWh | D34: =IF($K$12=M7,(($D$27+$D$28)*($K$14)/($K$14+$L$14)),0)+IF($L$12=M7,(($D$27+$D$28)*($L$14)/($K$14+$L$14)),0) -> 0 | E34: =IFERROR((ROUND(D34*K34,2)+ROUND(G34,2)+ROUND(J34,2))/ROUND(D34,4), 0) -> 0 | F34: =ROUND(D34*E34,2) -> 0 | G34: =((D34*K34)/(1-$N$19-$N$21))*($N$19+$N$21) -> 0 | H34: =(IF($I$29=12%,(D34*K34)/(1-$N$19-$N$21)/(1-$C$130)/$F$130*$C$130,(D34*K34)/(1-$N$19-$N$21)/(1-$I$29))) -> 0 | J34: =H34*$I$29 -> 0 | K34: =J87 -> 0
B36: Multas
B37: Juros | F37: -0.33
B38: Doações
B39: Bônus/Descontos
B40: CIP
B42: TOTAL | F42: =SUM(F18:F41) -> 6477.28 | G42: =SUM(G18:G41) -> 383.67917 | H42: =SUM(H18:H41) -> 2159.3226 | J42: =SUM(J18:J41) -> 259.11872
B44: Informativo Escassez | C44: =D18 -> 6812 | D44: =IF(AND($B$14<$F$2,$E$14<$F$2),C7,IF($B$14<$F$2,I7,F7)) -> 0.00018608682 | E44: =IF(AND($B$14<$F$2,$E$14<$F$2),D7,IF($B$14<$F$2,J7,G7)) -> -0.0025965236 | F44: =C44*(D44+E44) -> -16.419895 | G44: Incorreto no SAP
C45: =D19 -> 472 | D45: =IF(AND($B$14<$F$2,$E$14<$F$2),C7,IF($B$14<$F$2,I7,F7)) -> 0.00018608682 | E45: =IF(AND($B$14<$F$2,$E$14<$F$2),D7,IF($B$14<$F$2,J7,G7)) -> -0.0025965236 | F45: =C45*(D45+E45) -> -1.1377262
F46: =-F45*H57 -> 0.6826357
C47: =D28 -> -1 | D47: =IF(AND($B$14<$F$2,$E$14<$F$2),C7*$F$55,IF($B$14<$F$2,(((I7*F55)*C14)+((I7*F56)*D14))/(C14+D14),I7*$F$56)) -> 0.00013866446 | E47: =IF(AND($B$14<$F$2,$E$14<$F$2),D7,IF($B$14<$F$2,J7,G7)) -> -0.0025965236 | F47: =C47*(D47+E47) -> 0.0024578592
C48: =D27 -> 0 | D48: =IF(AND($B$14<$F$2,$E$14<$F$2),C7*$F$55,IF($B$14<$F$2,(((I7*F55)*C14)+((I7*F56)*D14))/(C14+D14),I7*$F$56)) -> 0.00013866446 | E48: =IF(AND($B$14<$F$2,$E$14<$F$2),D7,IF($B$14<$F$2,J7,G7)) -> -0.0025965236 | F48: =C48*(D48+E48) -> 0
F49: =-F48*H57 -> 0
F50: =SUM(F44:F49) -> -16.872528
B52: Desconto Rural Irrigante | F52: =SUM(H76+H64+H77+H78+H79+H84+H96+H97+H98+H99) -> -236.064 | G52: Incorreto no SAP
B55: Perc. de Redução da Energia Injetada | E55: TUSD | F55: 0.739 | G55: TE | H55: 1 | I55: ='Fatura B1 (GD II) OK'!I44 -> A partir de 01/01/2026
E56: TUSD | F56: 0.7522 | G56: TE | H56: 1 | I56: ='Fatura B1 (GD II) OK'!I45 -> A partir de 07/08/2026
G57: desconto: | H57: =O15 -> 0.6
B58: Fatura B2 Irrig
D59: Qtde | E59: TUSD | F59: TE | G59: TUSD + TE | H59: R$
B60: Fornecimento de Energia Elétrica | H60: =SUM(H62:H107)+SUM(H112:H117) -> 7066.4904
B62: Energia Fornecida | D62: =D18 -> 6812 | E62: =IF(AND($B$14<$F$2,$E$14<$F$2),C6,IF($B$14<$F$2,I6,F6)) -> 0.48621867 | F62: =IF(AND($B$14<$F$2,$E$14<$F$2),D6,IF($B$14<$F$2,J6,G6)) -> 0.328478 | G62: =E62+F62 -> 0.81469667 | H62: =ROUND((D62*E62),2)+ROUND((D62*F62),2) -> 5549.71 | J62: Tarifa reservada bandeira com desconto
B63: Energia Fornecida reservado | D63: =D19 -> 472 | E63: =E62 -> 0.48621867 | F63: =F62 -> 0.328478 | G63: =G62 -> 0.81469667 | H63: =ROUND((D63*E63),2)+ROUND((D63*F63),2) -> 384.54 | J63: =IFERROR((((D66*F66)+(D71*F71))-(D71*F71*$H$57))/(D66+D71), 0) -> 0.018117117
B64: Desconto reservado | H64: =-H63*$H$57 -> -230.724 | J64: =IFERROR((((D67*F67)+(D72*F72))-(D72*F72*$H$57))/(D67+D72), 0) -> 0
J65: =IFERROR((((D68*F68)+(D73*F73))-(D73*F73*$H$57))/(D68+D73), 0) -> 0
B66: Adicional BAM | D66: =IF($K$12=M4,(D62*(K14)/(K14+L14)),0)+IF($L$12=M4,(D62*(L14)/(K14+L14)),0) -> 6812 | F66: =N4 -> 0.01885 | H66: =ROUND(D66*(E66+F66),2) -> 128.41 | J66: =IFERROR((((D69*F69)+(D74*F74))-(D74*F74*$H$57))/(D69+D74), 0) -> 0
B67: Adicional BVM 1 | D67: =IF($K$12=M5,(D62*(K14)/(K14+L14)),0)+IF($L$12=M5,(D62*(L14)/(K14+L14)),0) -> 0 | F67: =N5 -> 0.04463 | H67: =ROUND(D67*(E67+F67),2) -> 0
B68: Adicional BVM 2 | D68: =IF($K$12=M6,(D62*(K14)/(K14+L14)),0)+IF($L$12=M6,(D62*(L14)/(K14+L14)),0) -> 0 | F68: =N6 -> 0.07877 | H68: =ROUND(D68*(E68+F68),2) -> 0
B69: Adicional Escassez Hídrica | D69: =IF($K$12=M8,(D62*(K14)/(K14+L14)),0)+IF($L$12=M8,(D62*(L14)/(K14+L14)),0) -> 0 | F69: =N8 -> 0.142 | H69: =ROUND(D69*(E69+F69),2) -> 0
B71: Adicional BAM PT Reservado | D71: =IF($K$12=M4,((D63)*(K14)/(K14+L14)),0)+IF($L$12=M4,((D63)*(L14)/(K14+L14)),0) -> 472 | F71: =F66 -> 0.01885 | H71: =ROUND(D71*(E71+F71),2) -> 8.9
B72: Adicional BVM 1 PT Reservado | D72: =IF($K$12=M5,((D63)*(K14)/(K14+L14)),0)+IF($L$12=M5,((D63)*(L14)/(K14+L14)),0) -> 0 | F72: =F67 -> 0.04463 | H72: =ROUND(D72*(E72+F72),2) -> 0
B73: Adicional BVM 2 PT Reservado | D73: =IF($K$12=M6,((D63)*(K14)/(K14+L14)),0)+IF($L$12=M6,((D63)*(L14)/(K14+L14)),0) -> 0 | F73: =F68 -> 0.07877 | H73: =ROUND(D73*(E73+F73),2) -> 0
B74: Adicional Esc. Hídrica Reserv | D74: =IF($K$12=M8,((D63)*(K14)/(K14+L14)),0)+IF($L$12=M8,((D63)*(L14)/(K14+L14)),0) -> 0 | F74: =F69 -> 0.142 | H74: =ROUND(D74*(E74+F74),2) -> 0
B76: Desc Adicional BAM | H76: =-H71*$H$57 -> -5.34
B77: Desc Adicional BVM 1 | H77: =-H72*$H$57 -> 0
B78: Desc Adicional BVM 2 | H78: =-H73*$H$57 -> 0
B79: Desc Adicional Escassez Hídrica | H79: =-H74*$H$57 -> 0
B81: Energia Injetada | D81: =D28 -> -1 | E81: =IF(AND($B$14<$F$2,$E$14<$F$2),C6*$F$55,IF($B$14<$F$2,(((I6*F55)*C14)+((I6*F56)*D14))/(C14+D14),I6*$F$56)) -> 0.3623107 | F81: =F62 -> 0.328478 | G81: =E81+F81 -> 0.6907887 | H81: =ROUND((D81*E81),2)+ROUND((D81*F81),2) -> -0.69
B83: Energia Injetada reservado | D83: =D27 -> 0 | E83: =IF(AND($B$14<$F$2,$E$14<$F$2),C6*$F$55,IF($B$14<$F$2,(((C6*F55)*C14)+((F6*F56)*D14))/(C14+D14),F6*$F$56)) -> 0.36243453 | F83: =F81 -> 0.328478 | G83: =G81 -> 0.6907887 | H83: =ROUND((D83*E83),2)+ROUND((D83*F83),2) -> 0 | J83: Tarifa reservada bandeira com desconto
B84: Desconto Injetado reservado | H84: =-H83*$H$57 -> 0 | J84: =IFERROR((((D86*F86)+(D91*F91))-(D91*F91*$H$57))/(D86+D91), 0) -> 0.01885
J85: =IFERROR((((D87*F87)+(D92*F92))-(D92*F92*$H$57))/(D87+D92), 0) -> 0
B86: Adicional BAM Injet | D86: =IF($K$12=M4,(D81*(K14)/(K14+L14)),0)+IF($L$12=M4,(D81*(L14)/(K14+L14)),0) -> -1 | F86: =F66 -> 0.01885 | H86: =ROUND(D86*(E86+F86),2) -> -0.02 | J86: =IFERROR((((D88*F88)+(D93*F93))-(D93*F93*$H$57))/(D88+D93), 0) -> 0
B87: Adicional BVM 1 Injet | D87: =IF($K$12=M5,(D81*(K14)/(K14+L14)),0)+IF($L$12=M5,(D81*(L14)/(K14+L14)),0) -> 0 | F87: =F67 -> 0.04463 | H87: =ROUND(D87*(E87+F87),2) -> 0 | J87: =IFERROR((((D89*F89)+(D94*F94))-(D94*F94*$H$57))/(D89+D94), 0) -> 0
B88: Adicional BVM 2 Injet | D88: =IF($K$12=M6,(D81*(K14)/(K14+L14)),0)+IF($L$12=M6,(D81*(L14)/(K14+L14)),0) -> 0 | F88: =F68 -> 0.07877 | H88: =ROUND(D88*(E88+F88),2) -> 0
B89: Adicional Escassez Hídrica | D89: =IF($K$12=M8,(D81*(K14)/(K14+L14)),0)+IF($L$12=M8,(D81*(L14)/(K14+L14)),0) -> 0 | F89: =F69 -> 0.142 | H89: =ROUND(D89*(E89+F89),2) -> 0
B91: Adicional BAM PT Reservado Injet | D91: =IF($K$12=M4,((D83)*(K14)/(K14+L14)),0)+IF($L$12=M4,((D83)*(L14)/(K14+L14)),0) -> 0 | F91: =F86 -> 0.01885 | H91: =ROUND(D91*(E91+F91),2) -> 0
B92: Adicional BVM 1 PT Reservado Injet | D92: =IF($K$12=M5,((D83)*(K14)/(K14+L14)),0)+IF($L$12=M5,((D83)*(L14)/(K14+L14)),0) -> 0 | F92: =F87 -> 0.04463 | H92: =ROUND(D92*(E92+F92),2) -> 0
B93: Adicional BVM 2 PT Reservado Injet | D93: =IF($K$12=M6,((D83)*(K14)/(K14+L14)),0)+IF($L$12=M6,((D83)*(L14)/(K14+L14)),0) -> 0 | F93: =F88 -> 0.07877 | H93: =ROUND(D93*(E93+F93),2) -> 0
B94: Adicional Esc. Hídrica Reserv | D94: =IF($K$12=M8,((D83)*(K14)/(K14+L14)),0)+IF($L$12=M8,((D83)*(L14)/(K14+L14)),0) -> 0 | F94: =F89 -> 0.142 | H94: =ROUND(D94*(E94+F94),2) -> 0
B96: Desc Adicional BAM Injet | H96: =-H91*$H$57 -> 0
B97: Desc Adicional BVM 1 Injet | H97: =-H92*$H$57 -> 0
B98: Desc Adicional BVM 2 Injet | H98: =-H93*$H$57 -> 0
B99: Desc Adicional Escassez Hídrica | H99: =-H94*$H$57 -> 0
I105: =H101+H105 -> 0
H109: =SUM(H62:H108) -> 5834.786
D111: Base de Cálculo
B112: PIS | D112: =SUM(H62:H64,H66:H69,H71:H74,H76:H79)/(1-E112-E114) -> 6219.222 | E112: =N18 -> 0.011 | H112: =D112*E112 -> 68.411442
B113: PIS Eneg Inj | D113: =SUM(H81:H84,H86:H89,H91:H94,H96:H99,H101:H103,H105:H107)/(1-E112-E114) -> -0.75668763 | E113: =E112 -> 0.011 | H113: =D113*E113 -> -0.0083235639
B114: COFINS | D114: =D112 -> 6219.222 | E114: =N20 -> 0.0507 | H114: =D114*E114 -> 315.31456
B115: COFINS Eneg Inj | D115: =D113 -> -0.75668763 | E115: =E114 -> 0.0507 | H115: =D115*E115 -> -0.038364063
B116: ICMS | D116: =D112/(1-E116) -> 7067.2977 | E116: =I18 -> 0.12 | H116: =D116*E116 -> 848.07573
B117: ICMS Eneg Inj | D117: =((D81*F81)+(H86+H87+H88+H89)+(D83*F83)+(D83*F83*-H57)+(H91+H92+H93+H94+H96+H97+H98+H99)+(D101*F101)+(D102*F102)+(D102*F102*-H57)+(D106*F106)+(D106*F106*-H57)+(D105*F105))/(1-E113-E115)/(1-E117) -> -0.42203744 | E117: =E116 -> 0.12 | H117: =D117*E117 -> -0.050644492
B120: Se for base reduzida: (célula E43 = 12%)
B121: Fornecida | D121: Com tributos
B122: PIS | C122: =E112 -> 0.011 | D122: =SUM(H62:H79)/(1-C122-C123) -> 6219.222 | E122: x | F122: =C122 -> 0.011 | G122: =D122*F122 -> 68.411442
B123: COFINS | C123: =E114 -> 0.0507 | D123: =D122 -> 6219.222 | E123: x | F123: =C123 -> 0.0507 | G123: =D123*F123 -> 315.31456
A124: Rural c/ incrição | B124: ICMS | C124: 0.04 | D124: =H124/F124*C124 -> 2159.4521 | E124: x | F124: 0.12 | G124: =D124*F124 -> 259.13425 | H124: =((SUM(H62:H79))/(1-F122-F123)/(1-(C124))) -> 6478.3562 | I124: =H124*C124 -> 259.13425
E125: =(O114)/(1-C122-C123-C124) -> 0
B127: Injetada | D127: Com tributos
...

Sheet Fatura B2 IRRIG (GD II) OK (2)
B2: B2 | E2: Vigência das Tarifas: | F2: ='Fatura B1 (GD II) OK'!F2 -> 46241 | G2: 2025: | H2: 45658 | M2: Bandeira | N2: R$/kWh | O2: ANEEL em 29/06 | Q2: TUSD FIO B
M3: VERDE | N3: 0
B4: TARIFA | C4: ='Fatura B1 (GD II) OK'!C4:E4 -> TARIFA ANTIGA - REH 3370/2024 | F4: ='Fatura B1 (GD II) OK'!F4:H4 -> TARIFA NOVA - REH xxxx/2025 | I4: Tarifas Proporcionalizadas | M4: BAM | N4: ='[1]Fatura B1 (Res) OK'!$N$4 -> 0.01885 | Q4: TARIFA | R4: =C4 -> TARIFA ANTIGA - REH 3370/2024 | U4: =F4 -> TARIFA NOVA - REH xxxx/2025 | X4: Tarifas Proporcionalizadas
C5: Tusd | D5: TE | E5: TUSD + TE | F5: Tusd | G5: TE | H5: TUSD + TE | I5: Tusd | J5: TE | K5: TUSD + TE | M5: BVM1 | N5: ='[1]Fatura B1 (Res) OK'!$N$5 -> 0.04463 | R5: Tusd (R$/kWh) | U5: Tusd (R$/kWh) | X5: Tusd (R$/kWh)
B6: B2 | C6: ='TABELA DE TARIFAS ANTIGAS'!G77/1000 -> 0.46863 | D6: ='TABELA DE TARIFAS ANTIGAS'!H77/1000 -> 0.32068 | E6: =C6+D6 -> 0.78931 | F6: ='TABELA DE TARIFAS NOVAS'!G79/1000 -> 0.50632 | G6: ='TABELA DE TARIFAS NOVAS'!H79/1000 -> 0.33739 | H6: =F6+G6 -> 0.84371 | I6: =((C6*$C$14)+(F6*$D$14))/($D$14+$C$14) -> 0.47451906 | J6: =((D6*$C$14)+(G6*$D$14))/($D$14+$C$14) -> 0.32329094 | K6: =I6+J6 -> 0.79781 | M6: BVM2 | N6: ='[1]Fatura B1 (Res) OK'!$N$6 -> 0.07877 | Q6: =B6 -> B2 | R6: ='FIO B'!H20/1000 -> 0.20383072 | U6: ='FIO B'!K20/1000 -> 0.20915159 | X6: =((R6*$C$14)+(U6*$D$14))/($D$14+$C$14) -> 0.20466211
B7: CDE Escassez Hídrica | C7: 0.00018774721 | D7: -0.0044031307 | E7: 0.0036054084 | F7: =T11 -> 0.00018418923 | G7: =U11 -> -0.00053182975 | H7: =F7+G7 -> -0.00034764052 | I7: =((C7*$C$14)+(F7*$D$14))/($D$14+$C$14) -> 0.00018719128 | J7: =((D7*$C$14)+(G7*$D$14))/($D$14+$C$14) -> -0.00379824 | K7: =I7+J7 -> -0.0036110487
B8: TE SCEE | G8: =G6*15% -> 0.0506085 | J8: =((D8*$C$14)+(G8*$D$14))/($D$14+$C$14) -> 0.0079075781 | M8: Escassez Hídrica | N8: 0.142 | P8: CUSTO | R8: Part. TUSD (%) | S8: Part. TE (%) | T8: Tusd (R$/kWh) | U8: TE (R$/kWh)
P9: CDE CONTAS
H10: Fatura | L10: Vigência das Tarifas (troca Bandeira): | M10: =EOMONTH(B14,0)+1 -> 46235 | P10: CDE COVID | U10: 0
B11: INSTALAÇÃO | C11: 838840 | H11: =E14 -> 46245 | K11: Altere a bandeira na célula abaixo | P11: CDE ESCASSEZ HÍDRICA | T11: ='Fatura B1 (GD II) OK'!T11 -> 0.00018418923 | U11: ='Fatura B1 (GD II) OK'!U11 -> -0.00053182975
K12: ='Fatura B1 (GD II) OK'!K12 -> BAM | L12: ='Fatura B1 (GD II) OK'!L12 -> BAM
B13: Leitura Anterior | C13: Nº de dias tarifa Anterior | D13: Nº de dias tarifa Nova | E13: Leitura Atual | J13: Leitura Anterior | K13: Nº de dias tarifa Anterior | L13: Nº de dias tarifa Nova | M13: Leitura Atual
B14: 46213 | C14: =IF((F2-B14-1)<0,0,(F2-B14-1)) -> 27 | D14: =E14-F2+1 -> 5 | E14: 46245 | J14: =B14 -> 46213 | K14: =IF((M10-J14-1)<0,0,(M10-J14-1)) -> 21 | L14: =M14-M10+1 -> 11 | M14: =E14 -> 46245 | O14: Documento Impressão | Q14: 1025310494
N15: desconto: | O15: 0.6
B16: Descrição | C16: Unidade | D16: Quantidade | E16: Preço Unit (R$) com tributos | F16: Valor Total (R$) | G16: PIS/COFINS (R$) | H16: Base de Cálculo ICMS (R$) | I16: Alíquota ICMS (%) | J16: ICMS (R$) | K16: Preço Unit (R$) | L16: Tributos | M16: Base de Cálc (R$) | N16: Alíquota (%) | O16: Valor (R$) | P16: não está contabilizando injetada
R17: TUSD Fio B | S17: Receita Fio B
B18: TUSD - Ativo | C18: kWh | D18: 4480 | E18: =IFERROR((ROUND(D18*K18,2)+ROUND(G18,2)+ROUND(J18,2))/ROUND(D18,4), 0) -> 0.6093058 | F18: =ROUND(D18*E18,2) -> 2729.69 | G18: =((D18*K18)/(1-$N$18-$N$20))*($N$18+$N$20) -> 139.78968 | H18: =(IF($I$18=12%,(D18*K18)/(1-$N$18-$N$20)/(1-$C$124)/$F$124*$C$124,(D18*K18)/(1-$N$18-$N$20)/(1-$I$18))) -> 2729.6808 | I18: 0.17 | J18: =(H18*$I$18) -> 464.04574 | K18: =IF(AND($B$14<$F$2,$E$14<$F$2),C6,IF($B$14<$F$2,I6,F6)) -> 0.47451906 | L18: PIS | M18: =D112 -> 4957.5786 | N18: ='Fatura B1 (GD II) OK'!N18 -> 0.011 | O18: =ROUND(M18*N18,2) -> 54.53 | R18: =IF(AND($B$14<$F$2,$E$14<$F$2),R6,IF($B$14<$F$2,X6,U6)) -> 0.20466211 | S18: =D18*R18 -> 916.88624
B19: TUSD - Consumo Reservado | C19: kWh | D19: 3040 | E19: =IFERROR((ROUND(D19*K19,2)+ROUND(G19,2)+ROUND(J19,2))/ROUND(D19,4), 0) -> 0.24372368 | F19: =ROUND(D19*E19,2) -> 740.92 | G19: =((D19*K19)/(1-$N$18-$N$20))*($N$18+$N$20) -> 37.942914 | H19: =(IF($I$18=12%,(D19*K19)/(1-$N$18-$N$20)/(1-$C$124)/$F$124*$C$124,(D19*K19)/(1-$N$18-$N$20)/(1-$I$18))) -> 740.91337 | I19: =I18 -> 0.17 | J19: =(H19*$I$18) -> 125.95527 | K19: =(K18+(K18*(-$H$57))) -> 0.18980762 | L19: PIS Inj | M19: =D113 -> -3135.0954 | N19: =N18 -> 0.011 | O19: =ROUND(M19*N19,2) -> -34.49 | R19: =IF(AND($B$14<$F$2,$E$14<$F$2),R6,IF($B$14<$F$2,X6,U6)) -> 0.20466211 | S19: =D19*R19 -> 622.17281
B20: TE - Consumo | C20: kWh | D20: =D18 -> 4480 | E20: =IFERROR((ROUND(D20*K20,2)+ROUND(G20,2)+ROUND(J20,2))/ROUND(D20,4), 0) -> 0.41512054 | F20: =ROUND(D20*E20,2) -> 1859.74 | G20: =((D20*K20)/(1-$N$18-$N$20))*($N$18+$N$20) -> 95.239036 | H20: =(IF($I$18=12%,(D20*K20)/(1-$N$18-$N$20)/(1-$C$124)/$F$124*$C$124,(D20*K20)/(1-$N$18-$N$20)/(1-$I$18))) -> 1859.7379 | J20: =(H20*$I$18) -> 316.15544 | K20: =IF(AND($B$14<$F$2,$E$14<$F$2),D6,IF($B$14<$F$2,J6,G6)) -> 0.32329094 | L20: COFINS | M20: =M18 -> 4957.5786 | N20: ='Fatura B1 (GD II) OK'!N20 -> 0.0507 | O20: =ROUND(M20*N20,2) -> 251.35 | S20: =-S19*60% -> -373.30368
B21: TE - Consumo Reservado | C21: kWh | D21: =D19 -> 3040 | E21: =IFERROR((ROUND(D21*K21,2)+ROUND(G21,2)+ROUND(J21,2))/ROUND(D21,4), 0) -> 0.16604605 | F21: =ROUND(D21*E21,2) -> 504.78 | G21: =((D21*K21)/(1-$N$18-$N$20))*($N$18+$N$20) -> 25.850597 | H21: =(IF($I$18=12%,(D21*K21)/(1-$N$18-$N$20)/(1-$C$124)/$F$124*$C$124,(D21*K21)/(1-$N$18-$N$20)/(1-$I$18))) -> 504.78601 | J21: =(H21*$I$18) -> 85.813622 | K21: =ROUND(K20+(K20*(-$H$57)),8) -> 0.12931638 | L21: COFINS Inj | M21: =M19 -> -3135.0954 | N21: =N20 -> 0.0507 | O21: =ROUND(M21*N21,2) -> -158.95 | S21: =SUM(S18:S20) -> 1165.7554
B22: Adicional BAM | C22: kWh | D22: =IF($K$12=M4,(($D$18+$D$19)*($K$14)/($K$14+$L$14)),0)+IF($L$12=M4,(($D$18+$D$19)*($L$14)/($K$14+$L$14)),0) -> 7520 | E22: =IFERROR((ROUND(D22*K22,2)+ROUND(G22,2)+ROUND(J22,2))/ROUND(D22,4), 0) -> 0.018333777 | F22: =ROUND(D22*E22,2) -> 137.87 | G22: =((D22*K22)/(1-$N$18-$N$20))*($N$18+$N$20) -> 7.0603265 | H22: =(IF($I$18=12%,(D22*K22)/(1-$N$18-$N$20)/(1-$C$124)/$F$124*$C$124,(D22*K22)/(1-$N$18-$N$20)/(1-$I$18))) -> 137.86738 | J22: =(H22*$I$18) -> 23.437455 | K22: =J63 -> 0.014277872 | Q22: 838840 | R22: massa
B23: Adicional BVM1 | C23: kWh | D23: =IF($K$12=M5,(($D$18+$D$19)*($K$14)/($K$14+$L$14)),0)+IF($L$12=M5,(($D$18+$D$19)*($L$14)/($K$14+$L$14)),0) -> 0 | E23: =IFERROR((ROUND(D23*K23,2)+ROUND(G23,2)+ROUND(J23,2))/ROUND(D23,4), 0) -> 0 | F23: =ROUND(D23*E23,2) -> 0 | G23: =((D23*K23)/(1-$N$18-$N$20))*($N$18+$N$20) -> 0 | H23: =(IF($I$18=12%,(D23*K23)/(1-$N$18-$N$20)/(1-$C$124)/$F$124*$C$124,(D23*K23)/(1-$N$18-$N$20)/(1-$I$18))) -> 0 | J23: =(H23*$I$18) -> 0 | K23: =J64 -> 0
B24: Adicional BVM2 | C24: kWh | D24: =IF($K$12=M6,(($D$18+$D$19)*($K$14)/($K$14+$L$14)),0)+IF($L$12=M6,(($D$18+$D$19)*($L$14)/($K$14+$L$14)),0) -> 0 | E24: =IFERROR((ROUND(D24*K24,2)+ROUND(G24,2)+ROUND(J24,2))/ROUND(D24,4), 0) -> 0 | F24: =ROUND(D24*E24,2) -> 0 | G24: =((D24*K24)/(1-$N$18-$N$20))*($N$18+$N$20) -> 0 | H24: =(IF($I$18=12%,(D24*K24)/(1-$N$18-$N$20)/(1-$C$124)/$F$124*$C$124,(D24*K24)/(1-$N$18-$N$20)/(1-$I$18))) -> 0 | J24: =(H24*$I$18) -> 0 | K24: =J65 -> 0
B25: Adicional EH | C25: kWh | D25: =IF($K$12=M7,(($D$18+$D$19)*($K$14)/($K$14+$L$14)),0)+IF($L$12=M7,(($D$18+$D$19)*($L$14)/($K$14+$L$14)),0) -> 0 | E25: =IFERROR((ROUND(D25*K25,2)+ROUND(G25,2)+ROUND(J25,2))/ROUND(D25,4), 0) -> 0 | F25: =ROUND(D25*E25,2) -> 0 | G25: =((D25*K25)/(1-$N$18-$N$20))*($N$18+$N$20) -> 0 | H25: =(IF($I$18=12%,(D25*K25)/(1-$N$18-$N$20)/(1-$C$124)/$F$124*$C$124,(D25*K25)/(1-$N$18-$N$20)/(1-$I$18))) -> 0 | J25: =(H25*$I$18) -> 0 | K25: =J66 -> 0
B27: TUSD - Consumo inj Reservado | C27: kWh | D27: 0 | E27: =IFERROR((ROUND(D27*K27,2)+ROUND(G27,2)+ROUND(J27,2))/ROUND(D27,4), 0) -> 0 | F27: =ROUND(D27*E27,2) -> 0 | G27: =((D27*K27)/(1-$N$19-$N$21))*($N$19+$N$21) -> 0 | H27: 0 | I27: 0 | J27: =H27*$I$21 -> 0 | K27: =(K28+(K28*(-$H$57))) -> 0.14065931
B28: TUSD - Consumo inj | C28: kWh | D28: -4240 | E28: =IFERROR((ROUND(D28*K28,2)+ROUND(G28,2)+ROUND(J28,2))/ROUND(D28,4), 0) -> 0.37477123 | F28: =ROUND(D28*E28,2) -> -1589.03 | G28: =((D28*K28)/(1-$N$19-$N$21))*($N$19+$N$21) -> -98.043274 | H28: 0 | I28: 0 | J28: =H28*$I$21 -> 0 | K28: =E81 -> 0.35164828
B29: TE - Consumo inj Reservado | C29: kWh | D29: =D27 -> 0 | E29: =IFERROR((ROUND(D29*K29,2)+ROUND(G29,2)+ROUND(J29,2))/ROUND(D29,4), 0) -> 0 | F29: =ROUND(D29*E29,2) -> 0 | G29: =((D29*K29)/(1-$N$19-$N$21))*($N$19+$N$21) -> 0 | H29: =(IF($I$29=12%,(D29*K29)/(1-$N$19-$N$21)/(1-$C$130)/$F$130*$C$130,(D29*K29)/(1-$N$19-$N$21)/(1-$I$29))) -> 0 | I29: =I18 -> 0.17 | J29: =H29*$I$29 -> 0 | K29: =K30+(K30*(-$H$57)) -> 0.12931638
B30: TE - Consumo inj | C30: kWh | D30: =D28 -> -4240 | E30: =IFERROR((ROUND(D30*K30,2)+ROUND(G30,2)+ROUND(J30,2))/ROUND(D30,4), 0) -> 0.41512028 | F30: =ROUND(D30*E30,2) -> -1760.11 | G30: =((D30*K30)/(1-$N$19-$N$21))*($N$19+$N$21) -> -90.136945 | H30: =(IF($I$29=12%,(D30*K30)/(1-$N$19-$N$21)/(1-$C$130)/$F$130*$C$130,(D30*K30)/(1-$N$19-$N$21)/(1-$I$29))) -> -1760.1091 | I30: =I19 -> 0.17 | J30: =H30*$I$29 -> -299.21854 | K30: =K20 -> 0.32329094
B31: Adicional BAM inj | C31: kWh | D31: =IF($K$12=M4,(($D$27+$D$28)*($K$14)/($K$14+$L$14)),0)+IF($L$12=M4,(($D$27+$D$28)*($L$14)/($K$14+$L$14)),0) -> -4240 | E31: =IFERROR((ROUND(D31*K31,2)+ROUND(G31,2)+ROUND(J31,2))/ROUND(D31,4), 0) -> 0.024205189 | F31: =ROUND(D31*E31,2) -> -102.63 | G31: =((D31*K31)/(1-$N$19-$N$21))*($N$19+$N$21) -> -5.2555801 | H31: =(IF($I$29=12%,(D31*K31)/(1-$N$19-$N$21)/(1-$C$130)/$F$130*$C$130,(D31*K31)/(1-$N$19-$N$21)/(1-$I$29))) -> -102.626 | J31: =H31*$I$29 -> -17.44642 | K31: =J84 -> 0.01885
B32: Adicional BVM1 inj | C32: kWh | D32: =IF($K$12=M5,(($D$27+$D$28)*($K$14)/($K$14+$L$14)),0)+IF($L$12=M5,(($D$27+$D$28)*($L$14)/($K$14+$L$14)),0) -> 0 | E32: =IFERROR((ROUND(D32*K32,2)+ROUND(G32,2)+ROUND(J32,2))/ROUND(D32,4), 0) -> 0 | F32: =ROUND(D32*E32,2) -> 0 | G32: =((D32*K32)/(1-$N$19-$N$21))*($N$19+$N$21) -> 0 | H32: =(IF($I$29=12%,(D32*K32)/(1-$N$19-$N$21)/(1-$C$130)/$F$130*$C$130,(D32*K32)/(1-$N$19-$N$21)/(1-$I$29))) -> 0 | J32: =H32*$I$29 -> 0 | K32: =J85 -> 0
B33: Adicional BVM2 inj | C33: kWh | D33: =IF($K$12=M6,(($D$27+$D$28)*($K$14)/($K$14+$L$14)),0)+IF($L$12=M6,(($D$27+$D$28)*($L$14)/($K$14+$L$14)),0) -> 0 | E33: =IFERROR((ROUND(D33*K33,2)+ROUND(G33,2)+ROUND(J33,2))/ROUND(D33,4), 0) -> 0 | F33: =ROUND(D33*E33,2) -> 0 | G33: =((D33*K33)/(1-$N$19-$N$21))*($N$19+$N$21) -> 0 | H33: =(IF($I$29=12%,(D33*K33)/(1-$N$19-$N$21)/(1-$C$130)/$F$130*$C$130,(D33*K33)/(1-$N$19-$N$21)/(1-$I$29))) -> 0 | J33: =H33*$I$29 -> 0 | K33: =J86 -> 0
B34: Adicional EH inj | C34: kWh | D34: =IF($K$12=M7,(($D$27+$D$28)*($K$14)/($K$14+$L$14)),0)+IF($L$12=M7,(($D$27+$D$28)*($L$14)/($K$14+$L$14)),0) -> 0 | E34: =IFERROR((ROUND(D34*K34,2)+ROUND(G34,2)+ROUND(J34,2))/ROUND(D34,4), 0) -> 0 | F34: =ROUND(D34*E34,2) -> 0 | G34: =((D34*K34)/(1-$N$19-$N$21))*($N$19+$N$21) -> 0 | H34: =(IF($I$29=12%,(D34*K34)/(1-$N$19-$N$21)/(1-$C$130)/$F$130*$C$130,(D34*K34)/(1-$N$19-$N$21)/(1-$I$29))) -> 0 | J34: =H34*$I$29 -> 0 | K34: =J87 -> 0
B36: Multas | F36: 27.77
B37: Juros | F37: 0.93
B38: Doações
B39: Bônus/Descontos
B40: CIP
B42: TOTAL | F42: =SUM(F18:F41) -> 2549.93 | G42: =SUM(G18:G41) -> 112.44676 | H42: =SUM(H18:H41) -> 4110.2504 | J42: =SUM(J18:J41) -> 698.74257
B44: Informativo Escassez | C44: =D18 -> 4480 | D44: =IF(AND($B$14<$F$2,$E$14<$F$2),C7,IF($B$14<$F$2,I7,F7)) -> 0.00018719128 | E44: =IF(AND($B$14<$F$2,$E$14<$F$2),D7,IF($B$14<$F$2,J7,G7)) -> -0.00379824 | F44: =C44*(D44+E44) -> -16.177498 | G44: Incorreto no SAP
C45: =D19 -> 3040 | D45: =IF(AND($B$14<$F$2,$E$14<$F$2),C7,IF($B$14<$F$2,I7,F7)) -> 0.00018719128 | E45: =IF(AND($B$14<$F$2,$E$14<$F$2),D7,IF($B$14<$F$2,J7,G7)) -> -0.00379824 | F45: =C45*(D45+E45) -> -10.977588
F46: =-F45*H57 -> 6.5865528
C47: =D28 -> -4240 | D47: =IF(AND($B$14<$F$2,$E$14<$F$2),C7*$F$55,IF($B$14<$F$2,(((I7*F55)*C14)+((I7*F56)*D14))/(C14+D14),I7*$F$56)) -> 0.00013872044 | E47: =IF(AND($B$14<$F$2,$E$14<$F$2),D7,IF($B$14<$F$2,J7,G7)) -> -0.00379824 | F47: =C47*(D47+E47) -> 15.516363
C48: =D27 -> 0 | D48: =IF(AND($B$14<$F$2,$E$14<$F$2),C7*$F$55,IF($B$14<$F$2,(((I7*F55)*C14)+((I7*F56)*D14))/(C14+D14),I7*$F$56)) -> 0.00013872044 | E48: =IF(AND($B$14<$F$2,$E$14<$F$2),D7,IF($B$14<$F$2,J7,G7)) -> -0.00379824 | F48: =C48*(D48+E48) -> 0
F49: =-F48*H57 -> 0
F50: =SUM(F44:F49) -> -5.0521705
B52: Desconto Rural Irrigante | F52: =SUM(H76+H64+H77+H78+H79+H84+H96+H97+H98+H99) -> -1489.584 | G52: Incorreto no SAP
B55: Perc. de Redução da Energia Injetada | E55: TUSD | F55: 0.739 | G55: TE | H55: 1 | I55: ='Fatura B1 (GD II) OK'!I44 -> A partir de 01/01/2026
E56: TUSD | F56: 0.7522 | G56: TE | H56: 1 | I56: ='Fatura B1 (GD II) OK'!I45 -> A partir de 07/08/2026
G57: desconto: | H57: =O15 -> 0.6
B58: Fatura B2 Irrig
D59: Qtde | E59: TUSD | F59: TE | G59: TUSD + TE | H59: R$
B60: Fornecimento de Energia Elétrica | H60: =SUM(H62:H107)+SUM(H112:H117) -> 2521.2268
B62: Energia Fornecida | D62: =D18 -> 4480 | E62: =IF(AND($B$14<$F$2,$E$14<$F$2),C6,IF($B$14<$F$2,I6,F6)) -> 0.47451906 | F62: =IF(AND($B$14<$F$2,$E$14<$F$2),D6,IF($B$14<$F$2,J6,G6)) -> 0.32329094 | G62: =E62+F62 -> 0.79781 | H62: =ROUND((D62*E62),2)+ROUND((D62*F62),2) -> 3574.19 | J62: Tarifa reservada bandeira com desconto
B63: Energia Fornecida reservado | D63: =D19 -> 3040 | E63: =E62 -> 0.47451906 | F63: =F62 -> 0.32329094 | G63: =G62 -> 0.79781 | H63: =ROUND((D63*E63),2)+ROUND((D63*F63),2) -> 2425.34 | J63: =IFERROR((((D66*F66)+(D71*F71))-(D71*F71*$H$57))/(D66+D71), 0) -> 0.014277872
B64: Desconto reservado | H64: =-H63*$H$57 -> -1455.204 | J64: =IFERROR((((D67*F67)+(D72*F72))-(D72*F72*$H$57))/(D67+D72), 0) -> 0
J65: =IFERROR((((D68*F68)+(D73*F73))-(D73*F73*$H$57))/(D68+D73), 0) -> 0
B66: Adicional BAM | D66: =IF($K$12=M4,(D62*(K14)/(K14+L14)),0)+IF($L$12=M4,(D62*(L14)/(K14+L14)),0) -> 4480 | F66: =N4 -> 0.01885 | H66: =ROUND(D66*(E66+F66),2) -> 84.45 | J66: =IFERROR((((D69*F69)+(D74*F74))-(D74*F74*$H$57))/(D69+D74), 0) -> 0
B67: Adicional BVM 1 | D67: =IF($K$12=M5,(D62*(K14)/(K14+L14)),0)+IF($L$12=M5,(D62*(L14)/(K14+L14)),0) -> 0 | F67: =N5 -> 0.04463 | H67: =ROUND(D67*(E67+F67),2) -> 0
B68: Adicional BVM 2 | D68: =IF($K$12=M6,(D62*(K14)/(K14+L14)),0)+IF($L$12=M6,(D62*(L14)/(K14+L14)),0) -> 0 | F68: =N6 -> 0.07877 | H68: =ROUND(D68*(E68+F68),2) -> 0
B69: Adicional Escassez Hídrica | D69: =IF($K$12=M8,(D62*(K14)/(K14+L14)),0)+IF($L$12=M8,(D62*(L14)/(K14+L14)),0) -> 0 | F69: =N8 -> 0.142 | H69: =ROUND(D69*(E69+F69),2) -> 0
B71: Adicional BAM PT Reservado | D71: =IF($K$12=M4,((D63)*(K14)/(K14+L14)),0)+IF($L$12=M4,((D63)*(L14)/(K14+L14)),0) -> 3040 | F71: =F66 -> 0.01885 | H71: =ROUND(D71*(E71+F71),2) -> 57.3
B72: Adicional BVM 1 PT Reservado | D72: =IF($K$12=M5,((D63)*(K14)/(K14+L14)),0)+IF($L$12=M5,((D63)*(L14)/(K14+L14)),0) -> 0 | F72: =F67 -> 0.04463 | H72: =ROUND(D72*(E72+F72),2) -> 0
B73: Adicional BVM 2 PT Reservado | D73: =IF($K$12=M6,((D63)*(K14)/(K14+L14)),0)+IF($L$12=M6,((D63)*(L14)/(K14+L14)),0) -> 0 | F73: =F68 -> 0.07877 | H73: =ROUND(D73*(E73+F73),2) -> 0
B74: Adicional Esc. Hídrica Reserv | D74: =IF($K$12=M8,((D63)*(K14)/(K14+L14)),0)+IF($L$12=M8,((D63)*(L14)/(K14+L14)),0) -> 0 | F74: =F69 -> 0.142 | H74: =ROUND(D74*(E74+F74),2) -> 0
B76: Desc Adicional BAM | H76: =-H71*$H$57 -> -34.38
B77: Desc Adicional BVM 1 | H77: =-H72*$H$57 -> 0
B78: Desc Adicional BVM 2 | H78: =-H73*$H$57 -> 0
B79: Desc Adicional Escassez Hídrica | H79: =-H74*$H$57 -> 0
B81: Energia Injetada | D81: =D28 -> -4240 | E81: =IF(AND($B$14<$F$2,$E$14<$F$2),C6*$F$55,IF($B$14<$F$2,(((I6*F55)*C14)+((I6*F56)*D14))/(C14+D14),I6*$F$56)) -> 0.35164828 | F81: =F62 -> 0.32329094 | G81: =E81+F81 -> 0.67493922 | H81: =ROUND((D81*E81),2)+ROUND((D81*F81),2) -> -2861.74 | L81: 0.35166608
B83: Energia Injetada reservado | D83: =D27 -> 0 | E83: =IF(AND($B$14<$F$2,$E$14<$F$2),C6*$F$55,IF($B$14<$F$2,(((C6*F55)*C14)+((F6*F56)*D14))/(C14+D14),F6*$F$56)) -> 0.35171387 | F83: =F81 -> 0.32329094 | G83: =G81 -> 0.67493922 | H83: =ROUND((D83*E83),2)+ROUND((D83*F83),2) -> 0 | J83: Tarifa reservada bandeira com desconto
B84: Desconto Injetado reservado | H84: =-H83*$H$57 -> 0 | J84: =IFERROR((((D86*F86)+(D91*F91))-(D91*F91*$H$57))/(D86+D91), 0) -> 0.01885
J85: =IFERROR((((D87*F87)+(D92*F92))-(D92*F92*$H$57))/(D87+D92), 0) -> 0
B86: Adicional BAM Injet | D86: =IF($K$12=M4,(D81*(K14)/(K14+L14)),0)+IF($L$12=M4,(D81*(L14)/(K14+L14)),0) -> -4240 | F86: =F66 -> 0.01885 | H86: =ROUND(D86*(E86+F86),2) -> -79.92 | J86: =IFERROR((((D88*F88)+(D93*F93))-(D93*F93*$H$57))/(D88+D93), 0) -> 0
B87: Adicional BVM 1 Injet | D87: =IF($K$12=M5,(D81*(K14)/(K14+L14)),0)+IF($L$12=M5,(D81*(L14)/(K14+L14)),0) -> 0 | F87: =F67 -> 0.04463 | H87: =ROUND(D87*(E87+F87),2) -> 0 | J87: =IFERROR((((D89*F89)+(D94*F94))-(D94*F94*$H$57))/(D89+D94), 0) -> 0
B88: Adicional BVM 2 Injet | D88: =IF($K$12=M6,(D81*(K14)/(K14+L14)),0)+IF($L$12=M6,(D81*(L14)/(K14+L14)),0) -> 0 | F88: =F68 -> 0.07877 | H88: =ROUND(D88*(E88+F88),2) -> 0
B89: Adicional Escassez Hídrica | D89: =IF($K$12=M8,(D81*(K14)/(K14+L14)),0)+IF($L$12=M8,(D81*(L14)/(K14+L14)),0) -> 0 | F89: =F69 -> 0.142 | H89: =ROUND(D89*(E89+F89),2) -> 0
B91: Adicional BAM PT Reservado Injet | D91: =IF($K$12=M4,((D83)*(K14)/(K14+L14)),0)+IF($L$12=M4,((D83)*(L14)/(K14+L14)),0) -> 0 | F91: =F86 -> 0.01885 | H91: =ROUND(D91*(E91+F91),2) -> 0
B92: Adicional BVM 1 PT Reservado Injet | D92: =IF($K$12=M5,((D83)*(K14)/(K14+L14)),0)+IF($L$12=M5,((D83)*(L14)/(K14+L14)),0) -> 0 | F92: =F87 -> 0.04463 | H92: =ROUND(D92*(E92+F92),2) -> 0
B93: Adicional BVM 2 PT Reservado Injet | D93: =IF($K$12=M6,((D83)*(K14)/(K14+L14)),0)+IF($L$12=M6,((D83)*(L14)/(K14+L14)),0) -> 0 | F93: =F88 -> 0.07877 | H93: =ROUND(D93*(E93+F93),2) -> 0
B94: Adicional Esc. Hídrica Reserv | D94: =IF($K$12=M8,((D83)*(K14)/(K14+L14)),0)+IF($L$12=M8,((D83)*(L14)/(K14+L14)),0) -> 0 | F94: =F89 -> 0.142 | H94: =ROUND(D94*(E94+F94),2) -> 0
B96: Desc Adicional BAM Injet | H96: =-H91*$H$57 -> 0
B97: Desc Adicional BVM 1 Injet | H97: =-H92*$H$57 -> 0
B98: Desc Adicional BVM 2 Injet | H98: =-H93*$H$57 -> 0
B99: Desc Adicional Escassez Hídrica | H99: =-H94*$H$57 -> 0
I105: =H101+H105 -> 0
H109: =SUM(H62:H108) -> 1710.036
D111: Base de Cálculo
B112: PIS | D112: =SUM(H62:H64,H66:H69,H71:H74,H76:H79)/(1-E112-E114) -> 4957.5786 | E112: =N18 -> 0.011 | H112: =D112*E112 -> 54.533365
B113: PIS Eneg Inj | D113: =SUM(H81:H84,H86:H89,H91:H94,H96:H99,H101:H103,H105:H107)/(1-E112-E114) -> -3135.0954 | E113: =E112 -> 0.011 | H113: =D113*E113 -> -34.486049
B114: COFINS | D114: =D112 -> 4957.5786 | E114: =N20 -> 0.0507 | H114: =D114*E114 -> 251.34923
B115: COFINS Eneg Inj | D115: =D113 -> -3135.0954 | E115: =E114 -> 0.0507 | H115: =D115*E115 -> -158.94934
B116: ICMS | D116: =D112/(1-E116) -> 5972.9863 | E116: =I18 -> 0.17 | H116: =D116*E116 -> 1015.4077
B117: ICMS Eneg Inj | D117: =((D81*F81)+(H86+H87+H88+H89)+(D83*F83)+(D83*F83*-H57)+(H91+H92+H93+H94+H96+H97+H98+H99)+(D101*F101)+(D102*F102)+(D102*F102*-H57)+(D106*F106)+(D106*F106*-H57)+(D105*F105))/(1-E113-E115)/(1-E117) -> -1862.7299 | E117: =E116 -> 0.17 | H117: =D117*E117 -> -316.66409
B120: Se for base reduzida: (célula E43 = 12%)
B121: Fornecida | D121: Com tributos
B122: PIS | C122: =E112 -> 0.011 | D122: =SUM(H62:H79)/(1-C122-C123) -> 4957.5786 | E122: x | F122: =C122 -> 0.011 | G122: =D122*F122 -> 54.533365
B123: COFINS | C123: =E114 -> 0.0507 | D123: =D122 -> 4957.5786 | E123: x | F123: =C123 -> 0.0507 | G123: =D123*F123 -> 251.34923
A124: Rural c/ incrição | B124: ICMS | C124: 0.04 | D124: =H124/F124*C124 -> 1721.3815 | E124: x | F124: 0.12 | G124: =D124*F124 -> 206.56577 | H124: =((SUM(H62:H79))/(1-F122-F123)/(1-(C124))) -> 5164.1444 | I124: =H124*C124 -> 206.56577
E125: =(O114)/(1-C122-C123-C124) -> 0
B127: Injetada | D127: Com tributos
...

Sheet Fatura B1 (GD) (Baixa Renda) X
B2: B1 Baixa renda | E2: Vigência das Tarifas: | F2: ='Fatura B1 (GD II) OK'!F2 -> 46241 | M2: Bandeira | N2: R$/kWh | O2: ANEEL em 29/06 | Q2: TUSD FIO B
M3: VERDE | N3: 0
B4: TARIFA R$ kWh | C4: TARIFA ANTIGA - REH 3091/2022 | F4: ='Fatura B1 (GD II) OK'!F4 -> TARIFA NOVA - REH xxxx/2025 | I4: Tarifas Proporcionalizadas | M4: BAM | N4: ='[1]Fatura B1 (Res) OK'!$N$4 -> 0.01885 | Q4: TARIFA | R4: =C4 -> TARIFA ANTIGA - REH 3091/2022 | U4: =F4 -> TARIFA NOVA - REH xxxx/2025 | X4: Tarifas Proporcionalizadas
C5: Tusd | D5: TE | E5: TUSD + TE | F5: Tusd | G5: TE | H5: TUSD + TE | I5: Tusd | J5: TE | K5: TUSD + TE | M5: BVM1 | N5: ='[1]Fatura B1 (Res) OK'!$N$5 -> 0.04463 | R5: Tusd (R$/kWh) | U5: Tusd (R$/kWh) | X5: Tusd (R$/kWh)
B6: Baixa renda | C6: ='[1]TABELA DE TARIFAS ANTIGAS'!G72/1000 -> 0.28337 | D6: ='[1]TABELA DE TARIFAS ANTIGAS'!H72/1000 -> 0.2988 | E6: =C6+D6 -> 0.58217 | F6: ='[1]TABELA DE TARIFAS NOVAS'!G74/1000 -> 0.28935 | G6: ='[1]TABELA DE TARIFAS NOVAS'!H74/1000 -> 0.29334 | H6: =F6+G6 -> 0.58269 | I6: =((C6*$C$14)+(F6*$D$14))/($D$14+$C$14) -> 0.09799 | J6: =((D6*$C$14)+(G6*$D$14))/($D$14+$C$14) -> 0.46806 | K6: =I6+J6 -> 0.56605 | M6: BVM2 | N6: ='[1]Fatura B1 (Res) OK'!$N$6 -> 0.07877 | Q6: =B6 -> Baixa renda | R6: ='[1]FIO B'!H12/1000 -> 0.17652 | U6: ='[1]FIO B'!K12/1000 -> 0.061783268 | X6: =((R6*$C$14)+(U6*$D$14))/($D$14+$C$14) -> 3.7333587
B7: CDE Escassez Hídrica | C7: =0.207830737658616/1000 -> 0.00020783074 | D7: =4.01792/1000 -> 0.00401792 | E7: =C7+D7 -> 0.0042257507 | F7: =T11 -> 0.00020783074 | G7: =U11 -> 0.00402 | H7: =F7+G7 -> 0.0042278307 | I7: =((C7*$C$14)+(F7*$D$14))/($D$14+$C$14) -> 0.00020783074 | J7: =((D7*$C$14)+(G7*$D$14))/($D$14+$C$14) -> 0.00395344 | K7: =I7+J7 -> 0.0041612707
B8: TE SCEE | G8: =G6*15% -> 0.044001 | J8: =((D8*$C$14)+(G8*$D$14))/($D$14+$C$14) -> -1.364031 | M8: Escassez Hídrica | N8: 0.142 | P8: CUSTO | R8: Part. TUSD (%) | S8: Part. TE (%) | T8: Tusd (R$/kWh) | U8: TE (R$/kWh)
P9: CDE CONTAS
H10: Fatura | L10: Vigência das Tarifas (troca Bandeira): | M10: =EOMONTH(B14,0)+1 -> 45352 | P10: CDE COVID | U10: =5.61/1000 -> 0.00561
B11: INSTALAÇÃO | C11: 554681 | H11: =E14 -> 45372 | K11: Altere a bandeira na célula abaixo | P11: CDE ESCASSEZ HÍDRICA | T11: =0.207830737658616/1000 -> 0.00020783074 | U11: =4.02/1000 -> 0.00402 | W11: prop
K12: BAM | L12: VERDE | P12: 0 - 30 | Q12: 0.65 | U12: =$U$11*(1-Q12) -> 0.001407 | W12: =((T12*$C$14)+(U12*$D$14))/($D$14+$C$14) -> -0.043617
B13: Leitura Anterior | C13: Nº de dias tarifa Anterior | D13: Nº de dias tarifa Nova | E13: Leitura Atual | J13: Leitura Anterior | K13: Nº de dias tarifa Anterior | L13: Nº de dias tarifa Nova | M13: Leitura Atual | P13: 31- 100 | Q13: 0.4 | U13: =$U$11*(1-Q13) -> 0.002412 | W13: =((T13*$C$14)+(U13*$D$14))/($D$14+$C$14) -> -0.074772
B14: 45344 | C14: =IF((F2-B14-1)<0,0,(F2-B14-1)) -> 896 | D14: =E14-F2+1 -> -868 | E14: 45372 | J14: =B14 -> 45344 | K14: =IF((M10-J14-1)<0,0,(M10-J14-1)) -> 7 | L14: =M14-M10+1 -> 21 | M14: =E14 -> 45372 | P14: 101 - 220 | Q14: 0.1 | U14: =$U$11*(1-Q14) -> 0.003618 | W14: =((T14*$C$14)+(U14*$D$14))/($D$14+$C$14) -> -0.112158
P15: >220 | Q15: 0 | U15: =$U$11*(1-Q15) -> 0.00402 | W15: =((T15*$C$14)+(U15*$D$14))/($D$14+$C$14) -> -0.12462
B16: Consumo = | G16: 300 | H16: kWh
B17: Energia Injetada = | G17: 500 | H17: kWh
F18: alterar o % caso GD II | G18: =G17 -> 500 | H18: =G16-G18 -> -200 | K18: Doc impr | L18: 30005966432
B19: Perc. de Redução da Energia Injetada | E19: TUSD | F19: 0.8131 | G19: TE | H19: 1 | I19: Até 06/08/2023
E20: TUSD | F20: 0.8048 | G20: TE | H20: 1 | I20: A partir de 07/08/2024
B21: Fatura B1 Baixa Renda
D22: Qtde | E22: TUSD | F22: TE | G22: TUSD + TE | H22: R$
B23: Fornecimento de Energia Elétrica | H23: =SUM(H25:H63)+SUM(H68:H73) -> 51.360562
A25: 0.65 | B25: Consumo 0 - 30 | D25: =IF(H18>0,30,0) -> 0 | E25: =$E$38*(1-A25) -> 0.0991795 | F25: =$F$38*(1-A25) -> 0.10458 | G25: =E25+F25 -> 0.2037595 | H25: =ROUND((D25*E25),2)+ROUND((D25*F25),2) -> 0
A26: 0.4 | B26: Consumo 31 - 100 | D26: =IF(H18>30,IF(H18>100,70,H18-30),0) -> 0 | E26: =$E$38*(1-A26) -> 0.170022 | F26: =$F$38*(1-A26) -> 0.17928 | G26: =E26+F26 -> 0.349302 | H26: =ROUND((D26*E26),2)+ROUND((D26*F26),2) -> 0
A27: 0.1 | B27: Consumo 101 - 220 | D27: =IF(H18>100,IF(H18>220,220-100,H18-100),0) -> 0 | E27: =$E$38*(1-A27) -> 0.255033 | F27: =$F$38*(1-A27) -> 0.26892 | G27: =E27+F27 -> 0.523953 | H27: =ROUND((D27*E27),2)+ROUND((D27*F27),2) -> 0
A28: 0 | B28: Consumo > 220 | D28: =IF(H18>220,H18-220,0) -> 0 | E28: =$E$38*(1-A28) -> 0.28337 | F28: =$F$38*(1-A28) -> 0.2988 | G28: =E28+F28 -> 0.58217 | H28: =ROUND((D28*E28),2)+ROUND((D28*F28),2) -> 0
B30: Adicional BAM | H30: =O116 -> 0
B31: Adicional BVM 1 | H31: =O125 -> 0
B32: Adicional BVM 2 | H32: =O134 -> 0
B33: Adicional Escassez Hídrica | H33: =O143 -> 0
A35: 0.65 | B35: Energia Fornecida 0 - 30 | D35: =IF(G18>0,30,0) -> 30 | E35: =$E$38*(1-A35) -> 0.0991795 | F35: =$F$38*(1-A35) -> 0.10458 | G35: =E35+F35 -> 0.2037595 | H35: =ROUND((D35*E35),2)+ROUND((D35*F35),2) -> 6.12
A36: 0.4 | B36: Energia Fornecida 31 - 100 | D36: =IF(G18>30,IF(G18>100,70,G18-30),0) -> 70 | E36: =$E$38*(1-A36) -> 0.170022 | F36: =$F$38*(1-A36) -> 0.17928 | G36: =E36+F36 -> 0.349302 | H36: =ROUND((D36*E36),2)+ROUND((D36*F36),2) -> 24.45
A37: 0.1 | B37: Energia Fornecida 101 - 220 | D37: =IF(G18>100,IF(G18>220,220-100,G18-100),0) -> 120 | E37: =$E$38*(1-A37) -> 0.255033 | F37: =$F$38*(1-A37) -> 0.26892 | G37: =E37+F37 -> 0.523953 | H37: =ROUND((D37*E37),2)+ROUND((D37*F37),2) -> 62.87
A38: 0 | B38: Energia Fornecida > 220 | D38: =IF(G18>220,G18-220,0) -> 280 | E38: =IF(AND($B$14<$F$2,$E$14<$F$2),C6,IF($B$14<$F$2,I6,F6)) -> 0.28337 | F38: =IF(AND($B$14<$F$2,$E$14<$F$2),D6,IF($B$14<$F$2,J6,G6)) -> 0.2988 | G38: =E38+F38 -> 0.58217 | H38: =ROUND((D38*E38),2)+ROUND((D38*F38),2) -> 163
B40: Adicional BAM | H40: =O153 -> 2.08
B41: Adicional BVM 1 | H41: =O162 -> 0
B42: Adicional BVM 2 | H42: =O171 -> 0
B43: Adicional Escassez Hídrica | H43: =O180 -> 0
A45: 0.65 | B45: Energia Inejtada 0 - 30 | D45: =-IF(G18>0,30,0) -> -30 | E45: =$E$48*(1-A45) -> 0.080642851 | F45: =F35 -> 0.10458 | G45: =E45+F45 -> 0.18522285 | H45: =ROUND((D45*E45),2)+ROUND((D45*F45),2) -> -5.56
A46: 0.4 | B46: Energia Injetada 31 - 100 | D46: =-IF(G18>30,IF(G18>100,70,G18-30),0) -> -70 | E46: =$E$48*(1-A46) -> 0.13824489 | F46: =F36 -> 0.17928 | G46: =E46+F46 -> 0.31752489 | H46: =ROUND((D46*E46),2)+ROUND((D46*F46),2) -> -22.23
A47: 0.1 | B47: Energia Injetada 101 - 220 | D47: =-IF(G18>100,IF(G18>220,220-100,G18-100),0) -> -120 | E47: =$E$48*(1-A47) -> 0.20736733 | F47: =F37 -> 0.26892 | G47: =E47+F47 -> 0.47628733 | H47: =ROUND((D47*E47),2)+ROUND((D47*F47),2) -> -57.15
A48: 0 | B48: Energia Injetada > 220 | D48: =-IF(G18>220,G18-220,0) -> -280 | E48: =IF(AND($B$14<$F$2,$E$14<$F$2),C6*$F$19,IF($B$14<$F$2,(((C6*F19)*C14)+((F6*F20)*D14))/(C14+D14),F6*$F$20)) -> 0.23040815 | F48: =F38 -> 0.2988 | G48: =E48+F48 -> 0.52920815 | H48: =ROUND((D48*E48),2)+ROUND((D48*F48),2) -> -148.17 | K48: =IF(AND($B$14<$F$2,$E$14<$F$2),C6*$F$19,IF($B$14<$F$2,(((C6*F19)*C14)+((F6*F20)*D14))/(C14+D14),F6*$F$20)) -> 0.23040815
B50: Adicional BAM | H50: =O192 -> -2.08
B51: Adicional BVM 1 | H51: =O201 -> 0
B52: Adicional BVM 2 | H52: =O210 -> 0
B53: Adicional Escassez Hídrica | H53: =O219 -> 0
A55: 0.65
A56: 0.4
A57: 0.1
A58: 0
I63: =SUM(H55:H63) -> 0
H65: =SUM(H25:H64) -> 23.33
D67: Base de Cálculo
B68: PIS | D68: =SUM(H25:H43)/(1-E68-E70) -> 271.55462 | E68: 0.0085 | H68: =D68*E68 -> 2.3082143
B69: PIS Eneg Inj | D69: =SUM(H45:H63)/(1-E68-E70) -> -247.04832 | E69: =E68 -> 0.0085 | H69: =D69*E69 -> -2.0999107
B70: COFINS | D70: =D68 -> 271.55462 | E70: 0.0395 | H70: =D70*E70 -> 10.726408
B71: COFINS Eneg Inj | D71: =D69 -> -247.04832 | E71: =E70 -> 0.0395 | H71: =D71*E71 -> -9.7584086
B72: ICMS | D72: =D68/(1-E72) -> 327.17424 | E72: 0.17 | H72: =D72*E72 -> 55.619621
B73: ICMS Eneg Inj | D73: =((D45*F45)+(D46*F46)+(D47*F47)+(D48*F48)+(D56*F56)+(D57*F57)+(D58*F58)+(D61*F61)+(D62*F62)+(D63*F63)+(H50+H51+H52+H53)+(D55*F55)+(D60*F60))/(1-E69-E71)/(1-E73) -> -169.20801 | E73: =E72 -> 0.17 | H73: =D73*E73 -> -28.765361
B74: ICMS Desc Tarifa Social | D74: =K106 -> 21.34555 | E74: =E73 -> 0.17 | H74: =D74*E74 -> 3.6287435
B75: Informativo Escassez Hídrica | H75: =IF(AND($B$14<$F$2,$E$14<$F$2),(D25*U12)+(D26*U13)+(D27*U14)+(D28*U15)+(D35*U12)+(D36*U13)+(D37*U14)+(D38*U15)+(D45*U12)+(D46*U13)+(D47*U14)+(D48*U15),(D25*W12)+(D26*W13)+(D27*W14)+(D28*W15)+(D35*W12)+(D36*W13)+(D37*W14)+(D38*W15)+(D45*W12)+(D46*W13)+(D47*W14)+(D48*W15)) -> 0
B77: Benefício Tarifa Social | H77: =K105 -> 3.1509265 | I77: (mensagem na fatura)
F79: Memória benefício Tarifa Social
I80: TUSD X | J80: TE | M80: Com tributos e bandeiras (base ICMS)
F81: Consumo | G81: B1 Baixa Renda | H81: =SUM(D25:D28,D35:D38) -> 500 | I81: =E28 -> 0.28337 | J81: =F28 -> 0.2988 | K81: =H81*(I81+J81) -> 291.085 | M81: =SUM(K81:K85)/(1-E68-E70)/(1-E72) -> 371.36941
G82: BAM | H82: =IF($K$12=$B$146,(H81*($K$14)/($K$14+$L$14)),0)+IF($L$12=$B$146,(H81*($L$14)/($K$14+$L$14)),0) -> 125 | J82: =N4 -> 0.01885 | K82: =H82*(I82+J82) -> 2.35625
G83: BVM1 | H83: =IF($K$12=$B$155,(H82*($K$14)/($K$14+$L$14)),0)+IF($L$12=$B$155,(H82*($L$14)/($K$14+$L$14)),0) -> 0 | J83: =N5 -> 0.04463 | K83: =H83*(I83+J83) -> 0
G84: BVM2 | H84: =IF($K$12=$B$164,(H83*($K$14)/($K$14+$L$14)),0)+IF($L$12=$B$164,(H83*($L$14)/($K$14+$L$14)),0) -> 0 | J84: =N6 -> 0.07877 | K84: =H84*(I84+J84) -> 0
G85: Escassez Hídrica | H85: =IF($K$12=$B$173,(H84*($K$14)/($K$14+$L$14)),0)+IF($L$12=$B$173,(H84*($L$14)/($K$14+$L$14)),0) -> 0 | J85: =N8 -> 0.142 | K85: =H85*(I85+J85) -> 0
F87: Injetada | G87: B1 Baixa Renda | H87: =SUM(D45:D48) -> -500 | I87: =E48 -> 0.23040815 | J87: =J81 -> 0.2988 | K87: =H87*(I87+J87) -> -264.60407 | M87: =((H87*J87)+(K88+K89+K90+K91))/(1-E69-E71)/(1-E73) -> -192.05762
G88: BAM | H88: =IF($K$12=$B$146,(H87*($K$14)/($K$14+$L$14)),0)+IF($L$12=$B$146,(H87*($L$14)/($K$14+$L$14)),0) -> -125 | J88: =J82 -> 0.01885 | K88: =H88*(I88+J88) -> -2.35625
G89: BVM1 | H89: =IF($K$12=$B$155,(H88*($K$14)/($K$14+$L$14)),0)+IF($L$12=$B$155,(H88*($L$14)/($K$14+$L$14)),0) -> 0 | J89: =J83 -> 0.04463 | K89: =H89*(I89+J89) -> 0
G90: BVM2 | H90: =IF($K$12=$B$164,(H89*($K$14)/($K$14+$L$14)),0)+IF($L$12=$B$164,(H89*($L$14)/($K$14+$L$14)),0) -> 0 | J90: =J84 -> 0.07877 | K90: =H90*(I90+J90) -> 0
G91: Escassez Hídrica | H91: =IF($K$12=$B$173,(H90*($K$14)/($K$14+$L$14)),0)+IF($L$12=$B$173,(H90*($L$14)/($K$14+$L$14)),0) -> 0 | J91: =J85 -> 0.142 | K91: =H91*(I91+J91) -> 0
F93: Bx Renda Consumo | G93: Baixa Renda | K93: =SUM(H25:H28,H35:H38) -> 256.44 | M93: =SUM(K93:K97)/(1-E68-E70)/(1-E72) -> 327.17424
G94: BAM | K94: =H30+H40 -> 2.08
G95: BVM1 | K95: =H31+H41 -> 0
G96: BVM2 | K96: =H32+H42 -> 0
G97: Escassez Hídrica | K97: =H33+H43 -> 0
F99: Bx Renda Injetada | G99: Baixa Renda | K99: =SUM(H45:H48,H55:H58,H60:H63) -> -233.11 | M99: =D73 -> -169.20801
G100: BAM | K100: =H50 -> -2.08
G101: BVM1 | K101: =H51 -> 0
G102: BVM2 | K102: =H52 -> 0
G103: Escassez Hídrica | K103: =H53 -> 0
J105: Benefício Tarifa Social | K105: =(K81+K87)-(K93+K99) -> 3.1509265 | L105: sem considerar as bandeiras
J106: Com tributos | K106: =(M81+M87)-(M93+M99) -> 21.34555 | L106: considerando as bandeiras no cálculo dos tributos
B108: Consumo - Adicional de Bandeira
B109: BAM | K109: =N4 -> 0.01885
C110: Consumo | J110: Tarifas | M110: Receita | O110: Receita Total
C111: KWh | K111: TE | M111: Tusd | N111: TE | O111: Tusd+TE
C112: =IF($K$12=$B$109,(D25*($K$14)/($K$14+$L$14)),0)+IF($L$12=$B$109,(D25*($L$14)/($K$14+$L$14)),0) -> 0 | K112: =$K$146*(1-Q112) -> 0.0065975 | N112: =ROUND((C112*K112),2) -> 0 | O112: =M112+N112 -> 0 | Q112: 0.65
C113: =IF($K$12=$B$109,(D26*($K$14)/($K$14+$L$14)),0)+IF($L$12=$B$109,(D26*($L$14)/($K$14+$L$14)),0) -> 0 | K113: =$K$146*(1-Q113) -> 0.01131 | N113: =ROUND((C113*K113),2) -> 0 | O113: =M113+N113 -> 0 | Q113: 0.4
C114: =IF($K$12=$B$109,(D27*($K$14)/($K$14+$L$14)),0)+IF($L$12=$B$109,(D27*($L$14)/($K$14+$L$14)),0) -> 0 | K114: =$K$146*(1-Q114) -> 0.016965 | N114: =ROUND((C114*K114),2) -> 0 | O114: =M114+N114 -> 0 | Q114: 0.1
C115: =IF($K$12=$B$109,(D28*($K$14)/($K$14+$L$14)),0)+IF($L$12=$B$109,(D28*($L$14)/($K$14+$L$14)),0) -> 0 | K115: =$K$146*(1-Q115) -> 0.01885 | N115: =ROUND((C115*K115),2) -> 0 | O115: =M115+N115 -> 0 | Q115: 0
C116: TOTAL | O116: =SUM(O112:O115) -> 0
B118: BVM1 | K118: =N5 -> 0.04463
C119: Consumo | J119: Tarifas Proporcionalizadas | M119: Receita | O119: Receita Total
C120: KWh | G120: Tusd | H120: TE | J120: Tusd | K120: TE | M120: Tusd | N120: TE | O120: Tusd+TE
C121: =IF($K$12=$B$118,(D25*($K$14)/($K$14+$L$14)),0)+IF($L$12=$B$118,(D25*($L$14)/($K$14+$L$14)),0) -> 0 | K121: =$K$155*(1-Q121) -> 0.0156205 | N121: =ROUND((C121*K121),2) -> 0 | O121: =M121+N121 -> 0 | Q121: 0.65
C122: =IF($K$12=$B$118,(D26*($K$14)/($K$14+$L$14)),0)+IF($L$12=$B$118,(D26*($L$14)/($K$14+$L$14)),0) -> 0 | K122: =$K$155*(1-Q122) -> 0.026778 | N122: =ROUND((C122*K122),2) -> 0 | O122: =M122+N122 -> 0 | Q122: 0.4
...

Sheet B1 (Res) GD Branca GDII
B2: B1 Res | E2: Vigência das Tarifas: | F2: 45358 | H2: TARIFA BRANCA | M2: Bandeira | N2: R$/kWh | Q2: TUSD FIO B
M3: VERDE | N3: 0
B4: TARIFA | C4: TARIFA ANTIGA - REH 3091/2022 | F4: ='Fatura B1 (GD II) OK'!F4 -> TARIFA NOVA - REH xxxx/2025 | I4: Tarifas Proporcionalizadas | M4: BAM | N4: =[3]BANDEIRA!$D$5 -> 0.01885 | Q4: TARIFA | R4: =C4 -> TARIFA ANTIGA - REH 3091/2022 | U4: =F4 -> TARIFA NOVA - REH xxxx/2025 | X4: Tarifas Proporcionalizadas
C5: Tusd | D5: TE | E5: TUSD + TE | F5: Tusd | G5: TE | H5: TUSD + TE | I5: Tusd | J5: TE | K5: TUSD + TE | M5: BVM1 | N5: =[3]BANDEIRA!$D$6 -> 0.04463 | R5: Tusd (R$/kWh) | U5: Tusd (R$/kWh) | X5: Tusd (R$/kWh)
B6: B1 Ponta | C6: ='[4]TABELA DE TARIFAS ANTIGAS'!G68/1000 -> 0.81172 | D6: ='[4]TABELA DE TARIFAS ANTIGAS'!H68/1000 -> 0.45925 | E6: =C6+D6 -> 1.27097 | F6: ='[4]TABELA DE TARIFAS NOVAS'!G70/1000 -> 0.80935 | G6: ='[4]TABELA DE TARIFAS NOVAS'!H70/1000 -> 0.45611 | H6: =F6+G6 -> 1.26546 | I6: =((C6*$C$15)+(F6*$D$15))/($D$15+$C$15) -> 0.82693387 | J6: =((D6*$C$15)+(G6*$D$15))/($D$15+$C$15) -> 0.47940677 | K6: =I6+J6 -> 1.3063406 | M6: BVM2 | N6: =[3]BANDEIRA!$D$7 -> 0.07877 | Q6: =B6 -> B1 Ponta | R6: ='[4]FIO B'!H7/1000 -> 0.54733 | U6: ='[4]FIO B'!K7/1000 -> 0.50309239 | X6: =((R6*$C$15)+(U6*$D$15))/($D$15+$C$15) -> 0.83130691
B7: B1 Fora Ponta | C7: ='[4]TABELA DE TARIFAS ANTIGAS'!G70/1000 -> 0.2951 | D7: ='[4]TABELA DE TARIFAS ANTIGAS'!H70/1000 -> 0.29163 | E7: =C7+D7 -> 0.58673 | F7: ='[4]TABELA DE TARIFAS NOVAS'!G72/1000 -> 0.28453 | G7: ='[4]TABELA DE TARIFAS NOVAS'!H72/1000 -> 0.28686 | H7: =F7+G7 -> 0.57139 | I7: =((C7*$C$15)+(F7*$D$15))/($D$15+$C$15) -> 0.36295258 | J7: =((D7*$C$15)+(G7*$D$15))/($D$15+$C$15) -> 0.32225032 | K7: =I7+J7 -> 0.6852029 | M7: Escassez Hídrica | N7: 0.142 | Q7: =B7 -> B1 Fora Ponta | R7: ='[4]FIO B'!H9/1000 -> 0.10947 | U7: ='[4]FIO B'!K9/1000 -> 0.10061852 | X7: =((R7*$C$15)+(U7*$D$15))/($D$15+$C$15) -> 0.16629081
B8: B1 Interm. | C8: ='[4]TABELA DE TARIFAS ANTIGAS'!G69/1000 -> 0.55341 | D8: ='[4]TABELA DE TARIFAS ANTIGAS'!H69/1000 -> 0.29163 | E8: =C8+D8 -> 0.84504 | F8: ='[4]TABELA DE TARIFAS NOVAS'!G71/1000 -> 0.54694 | G8: ='[4]TABELA DE TARIFAS NOVAS'!H71/1000 -> 0.28686 | H8: =F8+G8 -> 0.8338 | I8: =((C8*$C$15)+(F8*$D$15))/($D$15+$C$15) -> 0.59494323 | J8: =((D8*$C$15)+(G8*$D$15))/($D$15+$C$15) -> 0.32225032 | K8: =I8+J8 -> 0.91719355 | Q8: =B8 -> B1 Interm. | R8: ='[4]FIO B'!H8/1000 -> 0.3284 | U8: ='[4]FIO B'!K8/1000 -> 0.30185545 | X8: =((R8*$C$15)+(U8*$D$15))/($D$15+$C$15) -> 0.49879886
B9: CDE Escassez Hídrica | C9: 0.00020783074 | D9: 0.00401792 | E9: 0.0042278307 | F9: =T13 -> 0.00017567286 | G9: =U13 -> 0.0034297355 | H9: =F9+G9 -> 0.0036054084 | I9: =((C9*$C$15)+(F9*$D$15))/($D$15+$C$15) -> 0.00041426357 | J9: =((D9*$C$15)+(G9*$D$15))/($D$15+$C$15) -> 0.0077936848 | K9: =I9+J9 -> 0.0082079484
P10: CUSTO | R10: Part. TUSD (%) | S10: Part. TE (%) | T10: Tusd (R$/kWh) | U10: TE (R$/kWh)
H11: Fatura | L11: Vigência das Tarifas (troca Bandeira): | M11: =EOMONTH(B15,0)+1 -> 45139 | P11: CDE CONTAS
B12: INSTALAÇÃO | H12: =E15 -> 45158 | K12: Altere a bandeira na célula abaixo | P12: CDE COVID | U12: =5.61/1000 -> 0.00561
K13: VERDE | L13: VERDE | P13: CDE ESCASSEZ HÍDRICA | T13: =0.175672859965349/1000 -> 0.00017567286 | U13: =3.42973552660492/1000 -> 0.0034297355
B14: Leitura Anterior | C14: Nº de dias tarifa Anterior | D14: Nº de dias tarifa Nova | E14: Leitura Atual | J14: Leitura Anterior | K14: Nº de dias tarifa Anterior | L14: Nº de dias tarifa Nova | M14: Leitura Atual
B15: 45127 | C15: =IF((F2-B15-1)<0,0,(F2-B15-1)) -> 230 | D15: =E15-F2+1 -> -199 | E15: 45158 | J15: =B15 -> 45127 | K15: =IF((M11-J15-1)<0,0,(M11-J15-1)) -> 11 | L15: =M15-M11+1 -> 20 | M15: =E15 -> 45158
F17: alterar o % caso GD II
B18: Perc. de Redução da Energia Injetada | E18: TUSD P | F18: 0.8141 | G18: TE | H18: 1 | I18: Até 06/08/2023
E19: TUSD FP | F19: 0.8977 | G19: TE | H19: 1 | I19: Até 06/08/2023
E20: TUSD Intem | F20: 0.8364 | G20: TE | H20: 1 | I20: Até 06/08/2023
E21: TUSD P | F21: 0.8011 | G21: TE | H21: 1 | I21: A partir de 07/08/2024
E22: TUSD FP | F22: 0.8869 | G22: TE | H22: 1 | I22: A partir de 07/08/2024
E23: TUSD Intem | F23: 0.8234 | G23: TE | H23: 1 | I23: A partir de 07/08/2024
B25: Fatura B1 Residencial TB
D26: Qtde | E26: TUSD | F26: TE | G26: TUSD + TE | H26: R$ | J26: Documento impressão:
B27: Fornecimento de Energia Elétrica | H27: =SUM(H29:H36)+SUM(H49:H51) -> 752.19866
R28: TUSD Fio B | S28: Receita Fio B
B29: Consumo Ponta | D29: 103 | E29: =IF(AND($B$15<$F$2,$E$15<$F$2),C6,IF($B$15<$F$2,I6,F6)) -> 0.81172 | F29: =IF(AND($B$15<$F$2,$E$15<$F$2),D6,IF($B$15<$F$2,J6,G6)) -> 0.45925 | G29: =E29+F29 -> 1.27097 | H29: =ROUND((D29*E29),2)+ROUND((D29*F29),2) -> 130.91 | R29: =IF(AND($B$15<$F$2,$E$15<$F$2),R6,IF($B$15<$F$2,X6,U6)) -> 0.54733 | S29: =D29*R29 -> 56.37499 | U29: =D29*E29 -> 83.60716
B30: Consumo Fora Ponta | D30: 724 | E30: =IF(AND($B$15<$F$2,$E$15<$F$2),C7,IF($B$15<$F$2,I7,F7)) -> 0.2951 | F30: =IF(AND($B$15<$F$2,$E$15<$F$2),D7,IF($B$15<$F$2,J7,G7)) -> 0.29163 | G30: =E30+F30 -> 0.58673 | H30: =ROUND((D30*E30),2)+ROUND((D30*F30),2) -> 424.79 | R30: =IF(AND($B$15<$F$2,$E$15<$F$2),R7,IF($B$15<$F$2,X7,U7)) -> 0.10947 | S30: =D30*R30 -> 79.25628 | U30: =D30*E30 -> 213.6524
B31: Consumo Intemediário | D31: 51 | E31: =IF(AND($B$15<$F$2,$E$15<$F$2),C8,IF($B$15<$F$2,I8,F8)) -> 0.55341 | F31: =IF(AND($B$15<$F$2,$E$15<$F$2),D8,IF($B$15<$F$2,J8,G8)) -> 0.29163 | G31: =E31+F31 -> 0.84504 | H31: =ROUND((D31*E31),2)+ROUND((D31*F31),2) -> 43.09 | R31: =IF(AND($B$15<$F$2,$E$15<$F$2),R8,IF($B$15<$F$2,X8,U8)) -> 0.3284 | S31: =D31*R31 -> 16.7484 | U31: =D31*E31 -> 28.22391
S32: =SUM(S29:S31) -> 152.37967 | U32: =SUM(U29:U31) -> 325.48347
B33: Adicional BAM | D33: =IF($K$13=M4,((D29+D30+D31)*(K15)/(K15+L15)),0)+IF($L$13=M4,((D29+D30+D31)*(L15)/(K15+L15)),0) -> 0 | F33: =N4 -> 0.01885 | H33: =ROUND(D33*(E33+F33),2) -> 0
B34: Adicional BVM 1 | D34: =IF($K$13=M5,((D29+D30+D31)*(K15)/(K15+L15)),0)+IF($L$13=M5,((D29+D30+D31)*(L15)/(K15+L15)),0) -> 0 | F34: =N5 -> 0.04463 | H34: =ROUND(D34*(E34+F34),2) -> 0
B35: Adicional BVM 2 | D35: =IF($K$13=M6,((D29+D30+D31)*(K15)/(K15+L15)),0)+IF($L$13=M6,((D29+D30+D31)*(L15)/(K15+L15)),0) -> 0 | F35: =N6 -> 0.07877 | H35: =ROUND(D35*(E35+F35),2) -> 0
B36: Adicional Escassez Hídrica | D36: =IF($K$13=M7,((D29+D30+D31)*(K15)/(K15+L15)),0)+IF($L$13=M7,((D29+D30+D31)*(L15)/(K15+L15)),0) -> 0 | F36: =N7 -> 0.142 | H36: =ROUND(D36*(E36+F36),2) -> 0
B38: Energ Injetada P | D38: -10 | E38: =IF(AND($B$15<$F$2,$E$15<$F$2),C6*$F$18,IF($B$15<$F$2,(((C6*F18)*C15)+((F6*F21)*D15))/(C15+D15),F6*$F$21)) -> 0.66082125 | F38: =F29 -> 0.45925 | G38: =E38+F38 -> 1.1200713 | H38: =ROUND((D38*E38),2)+ROUND((D38*F38),2) -> -11.2
B39: Energ Injetada FP | D39: -100 | E39: =IF(AND($B$15<$F$2,$E$15<$F$2),C7*$F$19,IF($B$15<$F$2,(((C7*F19)*C15)+((F7*F22)*D15))/(C15+D15),F7*$F$22)) -> 0.26491127 | F39: =F30 -> 0.29163 | G39: =E39+F39 -> 0.55654127 | H39: =ROUND((D39*E39),2)+ROUND((D39*F39),2) -> -55.65
B40: Energ Injetada Intem | D40: -10 | E40: =IF(AND($B$15<$F$2,$E$15<$F$2),C8*$F$20,IF($B$15<$F$2,(((C8*F20)*C15)+((F8*F23)*D15))/(C15+D15),F8*$F$23)) -> 0.46287212 | F40: =F31 -> 0.29163 | G40: =E40+F40 -> 0.75450212 | H40: =ROUND((D40*E40),2)+ROUND((D40*F40),2) -> -7.55
B42: Adicional BAM Inj | D42: =IF($K$13=M4,((D38+D39+D40)*(K15)/(K15+L15)),0)+IF($L$13=M4,((D38+D39+D40)*(L15)/(K15+L15)),0) -> 0 | F42: =N13 -> 0 | H42: =ROUND(D42*(E42+F42),2) -> 0
B43: Adicional BVM 1 Inj | D43: =IF($K$13=M5,((D39+D40+D41)*(K15)/(K15+L15)),0)+IF($L$13=M5,((D39+D40+D41)*(L15)/(K15+L15)),0) -> 0 | F43: =N14 -> 0 | H43: =ROUND(D43*(E43+F43),2) -> 0
B44: Adicional BVM 2 Inj | D44: =IF($K$13=M6,((D40+D41+D42)*(K15)/(K15+L15)),0)+IF($L$13=M6,((D40+D41+D42)*(L15)/(K15+L15)),0) -> 0 | F44: =N15 -> 0 | H44: =ROUND(D44*(E44+F44),2) -> 0
B45: Adicional Escassez Hídrica Inj | D45: =IF($K$13=M7,((D41+D42+D43)*(K15)/(K15+L15)),0)+IF($L$13=M7,((D41+D42+D43)*(L15)/(K15+L15)),0) -> 0 | F45: =N16 -> 0 | H45: =ROUND(D45*(E45+F45),2) -> 0
D48: Base de Cálculo
B49: PIS | D49: =(SUM(H29:H36)/(1-E49-E50)) -> 624.32489 | E49: 0.0073 | H49: =D49*E49 -> 4.5575717
B50: COFINS | D50: =D49 -> 624.32489 | E50: 0.0336 | H50: =D50*E50 -> 20.977316
B51: ICMS | D51: =D49/(1-E51) -> 752.19866 | E51: 0.17 | H51: =D51*E51 -> 127.87377
B53: Informativo Escassez Hídrica | D53: =SUM(D29:D31)+SUM(D38:D40) -> 758 | E53: =IF(AND($B$15<$F$2,$E$15<$F$2),C9,IF($B$15<$F$2,I9,F9)) -> 0.00020783074 | F53: =IF(AND($B$15<$F$2,$E$15<$F$2),D9,IF($B$15<$F$2,J9,G9)) -> 0.00401792 | H53: =D53*(E53+F53) -> 3.2031191
B55: Participação
C56: R$
B57: Energia | C57: =(SUM(H29:H36)*IF($B$15<$F$2,D95,D67)) -> 259.11794
B58: Distribuição | C58: =(SUM(H29:H36)*IF($B$15<$F$2,F95,F67)) -> 155.56693
B59: Transmissão | C59: =(SUM(H29:H36)*IF($B$15<$F$2,E95,E67)) -> 48.757088
B60: Encargos Setoriais | C60: =(SUM(H29:H36)*IF($B$15<$F$2,G95,G67)) -> 135.34804
B61: Impostos / Tributos | C61: =H49+H50+H51 -> 153.40866
B62: Total | C62: =SUM(C57:C61) -> 752.19866
B64: 2023 | D64: Energia | E64: Transmissão | F64: Distribuição | G64: Setoriais
B65: Grupo B | D65: % | E65: % | F65: % | G65: %
B67: B1 - Residencial | D67: 0.43273591 | E67: 0.081426023 | F67: 0.25980216 | G67: 0.22603591
B68: B1 - Residencial Baixa Renda | D68: 0.52914975 | E68: 0.099567792 | F68: 0.31768624 | G68: 0.053596219
B69: B2 - Rural | D69: 0.43273591 | E69: 0.081426023 | F69: 0.25980216 | G69: 0.22603591
B70: B2 - Cooperativa Eletrificação Rural | D70: 0.43273591 | E70: 0.081426023 | F70: 0.25980216 | G70: 0.22603591
B71: B2 - Serviço de Irrigação | D71: 0.43273591 | E71: 0.081426023 | F71: 0.25980216 | G71: 0.22603591
B72: B3 - Demais Classes | D72: 0.43273591 | E72: 0.081426023 | F72: 0.25980216 | G72: 0.22603591
B73: B4 - Iluminação Pública | D73: 0.43273591 | E73: 0.081426023 | F73: 0.25980216 | G73: 0.22603591
B74: B4a - Rede de Distribuição | D74: 0.43273591 | E74: 0.081426023 | F74: 0.25980216 | G74: 0.22603591
B75: B4b - Bulbo de Lâmpada | D75: 0.43273591 | E75: 0.081426023 | F75: 0.25980216 | G75: 0.22603591
B78: 2022 | D78: Energia | E78: Transmissão | F78: Distribuição | G78: Setoriais
B79: Grupo B | D79: % | E79: % | F79: % | G79: %
B81: B1 - Residencial | D81: 0.43273591 | E81: 0.081426023 | F81: 0.25980216 | G81: 0.22603591
B82: B1 - Residencial Baixa Renda | D82: 0.52914975 | E82: 0.099567792 | F82: 0.31768624 | G82: 0.053596219
B83: B2 - Rural | D83: 0.43273591 | E83: 0.081426023 | F83: 0.25980216 | G83: 0.22603591
B84: B2 - Cooperativa Eletrificação Rural | D84: 0.43273591 | E84: 0.081426023 | F84: 0.25980216 | G84: 0.22603591
B85: B2 - Serviço de Irrigação | D85: 0.43273591 | E85: 0.081426023 | F85: 0.25980216 | G85: 0.22603591
B86: B3 - Demais Classes | D86: 0.43273591 | E86: 0.081426023 | F86: 0.25980216 | G86: 0.22603591
B87: B4 - Iluminação Pública | D87: 0.43273591 | E87: 0.081426023 | F87: 0.25980216 | G87: 0.22603591
B88: B4a - Rede de Distribuição | D88: 0.43273591 | E88: 0.081426023 | F88: 0.25980216 | G88: 0.22603591
B89: B4b - Bulbo de Lâmpada | D89: 0.43273591 | E89: 0.081426023 | F89: 0.25980216 | G89: 0.22603591
B91: proporcional
D92: Energia | E92: Transmissão | F92: Distribuição | G92: Setoriais
B93: Grupo B | D93: % | E93: % | F93: % | G93: %
B95: B1 - Residencial | D95: =((D81*$C$15)+(D67*$D$15))/($C$15+$D$15) -> 0.43273591 | E95: =((E81*$C$15)+(E67*$D$15))/($C$15+$D$15) -> 0.081426023 | F95: =((F81*$C$15)+(F67*$D$15))/($C$15+$D$15) -> 0.25980216 | G95: =((G81*$C$15)+(G67*$D$15))/($C$15+$D$15) -> 0.22603591
B96: B1 - Residencial Baixa Renda | D96: =((D82*$C$15)+(D68*$D$15))/($C$15+$D$15) -> 0.52914975 | E96: =((E82*$C$15)+(E68*$D$15))/($C$15+$D$15) -> 0.099567792 | F96: =((F82*$C$15)+(F68*$D$15))/($C$15+$D$15) -> 0.31768624 | G96: =((G82*$C$15)+(G68*$D$15))/($C$15+$D$15) -> 0.053596219
B97: B2 - Rural | D97: =((D83*$C$15)+(D69*$D$15))/($C$15+$D$15) -> 0.43273591 | E97: =((E83*$C$15)+(E69*$D$15))/($C$15+$D$15) -> 0.081426023 | F97: =((F83*$C$15)+(F69*$D$15))/($C$15+$D$15) -> 0.25980216 | G97: =((G83*$C$15)+(G69*$D$15))/($C$15+$D$15) -> 0.22603591
B98: B2 - Cooperativa Eletrificação Rural | D98: =((D84*$C$15)+(D70*$D$15))/($C$15+$D$15) -> 0.43273591 | E98: =((E84*$C$15)+(E70*$D$15))/($C$15+$D$15) -> 0.081426023 | F98: =((F84*$C$15)+(F70*$D$15))/($C$15+$D$15) -> 0.25980216 | G98: =((G84*$C$15)+(G70*$D$15))/($C$15+$D$15) -> 0.22603591
B99: B2 - Serviço de Irrigação | D99: =((D85*$C$15)+(D71*$D$15))/($C$15+$D$15) -> 0.43273591 | E99: =((E85*$C$15)+(E71*$D$15))/($C$15+$D$15) -> 0.081426023 | F99: =((F85*$C$15)+(F71*$D$15))/($C$15+$D$15) -> 0.25980216 | G99: =((G85*$C$15)+(G71*$D$15))/($C$15+$D$15) -> 0.22603591
B100: B3 - Demais Classes | D100: =((D86*$C$15)+(D72*$D$15))/($C$15+$D$15) -> 0.43273591 | E100: =((E86*$C$15)+(E72*$D$15))/($C$15+$D$15) -> 0.081426023 | F100: =((F86*$C$15)+(F72*$D$15))/($C$15+$D$15) -> 0.25980216 | G100: =((G86*$C$15)+(G72*$D$15))/($C$15+$D$15) -> 0.22603591
B101: B4 - Iluminação Pública | D101: =((D87*$C$15)+(D73*$D$15))/($C$15+$D$15) -> 0.43273591 | E101: =((E87*$C$15)+(E73*$D$15))/($C$15+$D$15) -> 0.081426023 | F101: =((F87*$C$15)+(F73*$D$15))/($C$15+$D$15) -> 0.25980216 | G101: =((G87*$C$15)+(G73*$D$15))/($C$15+$D$15) -> 0.22603591
B102: B4a - Rede de Distribuição | D102: =((D88*$C$15)+(D74*$D$15))/($C$15+$D$15) -> 0.43273591 | E102: =((E88*$C$15)+(E74*$D$15))/($C$15+$D$15) -> 0.081426023 | F102: =((F88*$C$15)+(F74*$D$15))/($C$15+$D$15) -> 0.25980216 | G102: =((G88*$C$15)+(G74*$D$15))/($C$15+$D$15) -> 0.22603591
B103: B4b - Bulbo de Lâmpada | D103: =((D89*$C$15)+(D75*$D$15))/($C$15+$D$15) -> 0.43273591 | E103: =((E89*$C$15)+(E75*$D$15))/($C$15+$D$15) -> 0.081426023 | F103: =((F89*$C$15)+(F75*$D$15))/($C$15+$D$15) -> 0.25980216 | G103: =((G89*$C$15)+(G75*$D$15))/($C$15+$D$15) -> 0.22603591

Sheet B2 GD Branca GDII
B2: B2 | E2: Vigência das Tarifas: | F2: 45358 | H2: TARIFA BRANCA | M2: Bandeira | N2: R$/kWh | Q2: TUSD FIO B
M3: VERDE | N3: ='[4]B1 (Res) Branca OK'!N3 -> 0
B4: TARIFA | C4: TARIFA ANTIGA - REH 3091/2022 | F4: ='Fatura B1 (GD II) OK'!F4 -> TARIFA NOVA - REH xxxx/2025 | I4: Tarifas Proporcionalizadas | M4: BAM | N4: ='[4]B1 (Res) Branca OK'!N4 -> 0.01885 | Q4: TARIFA | R4: =C4 -> TARIFA ANTIGA - REH 3091/2022 | U4: =F4 -> TARIFA NOVA - REH xxxx/2025 | X4: Tarifas Proporcionalizadas
C5: Tusd | D5: TE | E5: TUSD + TE | F5: Tusd | G5: TE | H5: TUSD + TE | I5: Tusd | J5: TE | K5: TUSD + TE | M5: BVM1 | N5: ='[4]B1 (Res) Branca OK'!N5 -> 0.04463 | R5: Tusd (R$/kWh) | U5: Tusd (R$/kWh) | X5: Tusd (R$/kWh)
B6: B1 Ponta | C6: ='[4]TABELA DE TARIFAS ANTIGAS'!G73/1000 -> 0.85704 | D6: ='[4]TABELA DE TARIFAS ANTIGAS'!H73/1000 -> 0.45925 | E6: =C6+D6 -> 1.31629 | F6: ='[4]TABELA DE TARIFAS NOVAS'!G75/1000 -> 0.85539 | G6: ='[4]TABELA DE TARIFAS NOVAS'!H75/1000 -> 0.45611 | H6: =F6+G6 -> 1.3115 | I6: =((C6*$C$15)+(F6*$D$15))/($D$15+$C$15) -> 0.86763194 | J6: =((D6*$C$15)+(G6*$D$15))/($D$15+$C$15) -> 0.47940677 | K6: =I6+J6 -> 1.3470387 | M6: BVM2 | N6: ='[4]B1 (Res) Branca OK'!N6 -> 0.07877 | Q6: =B6 -> B1 Ponta | R6: ='[4]FIO B'!H14/1000 -> 0.5506 | U6: ='[4]FIO B'!K14/1000 -> 0.53839715 | X6: =((R6*$C$15)+(U6*$D$15))/($D$15+$C$15) -> 0.6289344
B7: B1 Fora Ponta | C7: ='[4]TABELA DE TARIFAS ANTIGAS'!G75/1000 -> 0.30417 | D7: ='[4]TABELA DE TARIFAS ANTIGAS'!H75/1000 -> 0.29163 | E7: =C7+D7 -> 0.5958 | F7: ='[4]TABELA DE TARIFAS NOVAS'!G77/1000 -> 0.29373 | G7: ='[4]TABELA DE TARIFAS NOVAS'!H77/1000 -> 0.28686 | H7: =F7+G7 -> 0.58059 | I7: =((C7*$C$15)+(F7*$D$15))/($D$15+$C$15) -> 0.37118806 | J7: =((D7*$C$15)+(G7*$D$15))/($D$15+$C$15) -> 0.32225032 | K7: =I7+J7 -> 0.69343839 | M7: Escassez Hídrica | N7: 0.142 | Q7: =B7 -> B1 Fora Ponta | R7: ='[4]FIO B'!H16/1000 -> 0.11012 | U7: ='[4]FIO B'!K16/1000 -> 0.10767945 | X7: =((R7*$C$15)+(U7*$D$15))/($D$15+$C$15) -> 0.12578675
B8: B1 Interm. | C8: ='[4]TABELA DE TARIFAS ANTIGAS'!G74/1000 -> 0.5806 | D8: ='[4]TABELA DE TARIFAS ANTIGAS'!H74/1000 -> 0.29163 | E8: =C8+D8 -> 0.87223 | F8: ='[4]TABELA DE TARIFAS NOVAS'!G76/1000 -> 0.57456 | G8: ='[4]TABELA DE TARIFAS NOVAS'!H76/1000 -> 0.28686 | H8: =F8+G8 -> 0.86142 | I8: =((C8*$C$15)+(F8*$D$15))/($D$15+$C$15) -> 0.6193729 | J8: =((D8*$C$15)+(G8*$D$15))/($D$15+$C$15) -> 0.32225032 | K8: =I8+J8 -> 0.94162323 | Q8: =B8 -> B1 Interm. | R8: ='[4]FIO B'!H15/1000 -> 0.33036 | U8: ='[4]FIO B'!K15/1000 -> 0.32303825 | X8: =((R8*$C$15)+(U8*$D$15))/($D$15+$C$15) -> 0.37736089
B9: CDE Escassez Hídrica | C9: ='[4]B1 (Res) Branca OK'!C9 -> 0.00020783074 | D9: ='[4]B1 (Res) Branca OK'!D9 -> 0.00401792 | E9: =SUM(C9+D9) -> 0.0042257507 | F9: =T13 -> 0.00017567286 | G9: =U13 -> 0.0034297355 | H9: =F9+G9 -> 0.0036054084 | I9: =((C9*$C$15)+(F9*$D$15))/($D$15+$C$15) -> 0.00041426357 | J9: =((D9*$C$15)+(G9*$D$15))/($D$15+$C$15) -> 0.0077936848 | K9: =I9+J9 -> 0.0082079484
P10: CUSTO | R10: Part. TUSD (%) | S10: Part. TE (%) | T10: Tusd (R$/kWh) | U10: TE (R$/kWh)
H11: Fatura | L11: Vigência das Tarifas (troca Bandeira): | M11: =EOMONTH(B15,0)+1 -> 45139 | P11: CDE CONTAS
B12: INSTALAÇÃO | H12: =E15 -> 45158 | K12: Altere a bandeira na célula abaixo | P12: CDE COVID | U12: =5.61/1000 -> 0.00561
K13: VERDE | L13: VERDE | P13: CDE ESCASSEZ HÍDRICA | T13: =0.175672859965349/1000 -> 0.00017567286 | U13: =3.42973552660492/1000 -> 0.0034297355
B14: Leitura Anterior | C14: Nº de dias tarifa Anterior | D14: Nº de dias tarifa Nova | E14: Leitura Atual | J14: Leitura Anterior | K14: Nº de dias tarifa Anterior | L14: Nº de dias tarifa Nova | M14: Leitura Atual
B15: 45127 | C15: =IF((F2-B15-1)<0,0,(F2-B15-1)) -> 230 | D15: =E15-F2+1 -> -199 | E15: 45158 | J15: =B15 -> 45127 | K15: =IF((M11-J15-1)<0,0,(M11-J15-1)) -> 11 | L15: =M15-M11+1 -> 20 | M15: =E15 -> 45158
F17: alterar o % caso GD II
B18: Perc. de Redução da Energia Injetada | E18: TUSD P | F18: 0.8115 | G18: TE | H18: 1 | I18: Até 06/08/2023
E19: TUSD FP | F19: 0.8938 | G19: TE | H19: 1 | I19: Até 06/08/2023
E20: TUSD Intem | F20: 0.8331 | G20: TE | H20: 1 | I20: Até 06/08/2023
E21: TUSD P | F21: 0.7986 | G21: TE | H21: 1 | I21: A partir de 07/08/2024
E22: TUSD FP | F22: 0.8827 | G22: TE | H22: 1 | I22: A partir de 07/08/2024
E23: TUSD Intem | F23: 0.8201 | G23: TE | H23: 1 | I23: A partir de 07/08/2024
B25: Fatura B1 Residencial TB
D26: Qtde | E26: TUSD | F26: TE | G26: TUSD + TE | H26: R$ | J26: Documento impressão:
B27: Fornecimento de Energia Elétrica | H27: =SUM(H29:H36)+SUM(H49:H51) -> 768.06444
R28: TUSD Fio B | S28: Receita Fio B
B29: Consumo Ponta | D29: 103 | E29: =IF(AND($B$15<$F$2,$E$15<$F$2),C6,IF($B$15<$F$2,I6,F6)) -> 0.85704 | F29: =IF(AND($B$15<$F$2,$E$15<$F$2),D6,IF($B$15<$F$2,J6,G6)) -> 0.45925 | G29: =E29+F29 -> 1.31629 | H29: =ROUND((D29*E29),2)+ROUND((D29*F29),2) -> 135.58 | R29: =IF(AND($B$15<$F$2,$E$15<$F$2),R6,IF($B$15<$F$2,X6,U6)) -> 0.5506 | S29: =D29*R29 -> 56.7118 | U29: =D29*E29 -> 88.27512
B30: Consumo Fora Ponta | D30: 724 | E30: =IF(AND($B$15<$F$2,$E$15<$F$2),C7,IF($B$15<$F$2,I7,F7)) -> 0.30417 | F30: =IF(AND($B$15<$F$2,$E$15<$F$2),D7,IF($B$15<$F$2,J7,G7)) -> 0.29163 | G30: =E30+F30 -> 0.5958 | H30: =ROUND((D30*E30),2)+ROUND((D30*F30),2) -> 431.36 | R30: =IF(AND($B$15<$F$2,$E$15<$F$2),R7,IF($B$15<$F$2,X7,U7)) -> 0.11012 | S30: =D30*R30 -> 79.72688 | U30: =D30*E30 -> 220.21908
B31: Consumo Intemediário | D31: 51 | E31: =IF(AND($B$15<$F$2,$E$15<$F$2),C8,IF($B$15<$F$2,I8,F8)) -> 0.5806 | F31: =IF(AND($B$15<$F$2,$E$15<$F$2),D8,IF($B$15<$F$2,J8,G8)) -> 0.29163 | G31: =E31+F31 -> 0.87223 | H31: =ROUND((D31*E31),2)+ROUND((D31*F31),2) -> 44.48 | R31: =IF(AND($B$15<$F$2,$E$15<$F$2),R8,IF($B$15<$F$2,X8,U8)) -> 0.33036 | S31: =D31*R31 -> 16.84836 | U31: =D31*E31 -> 29.6106
S32: =SUM(S29:S31) -> 153.28704 | U32: =SUM(U29:U31) -> 338.1048
B33: Adicional BAM | D33: =IF($K$13=M4,((D29+D30+D31)*(K15)/(K15+L15)),0)+IF($L$13=M4,((D29+D30+D31)*(L15)/(K15+L15)),0) -> 0 | F33: =N4 -> 0.01885 | H33: =ROUND(D33*(E33+F33),2) -> 0
B34: Adicional BVM 1 | D34: =IF($K$13=M5,((D29+D30+D31)*(K15)/(K15+L15)),0)+IF($L$13=M5,((D29+D30+D31)*(L15)/(K15+L15)),0) -> 0 | F34: =N5 -> 0.04463 | H34: =ROUND(D34*(E34+F34),2) -> 0
B35: Adicional BVM 2 | D35: =IF($K$13=M6,((D29+D30+D31)*(K15)/(K15+L15)),0)+IF($L$13=M6,((D29+D30+D31)*(L15)/(K15+L15)),0) -> 0 | F35: =N6 -> 0.07877 | H35: =ROUND(D35*(E35+F35),2) -> 0
B36: Adicional Escassez Hídrica | D36: =IF($K$13=M7,((D29+D30+D31)*(K15)/(K15+L15)),0)+IF($L$13=M7,((D29+D30+D31)*(L15)/(K15+L15)),0) -> 0 | F36: =N7 -> 0.142 | H36: =ROUND(D36*(E36+F36),2) -> 0
B38: Energ Injetada P | D38: -10 | E38: =IF(AND($B$15<$F$2,$E$15<$F$2),C6*$F$18,IF($B$15<$F$2,(((C6*F18)*C15)+((F6*F21)*D15))/(C15+D15),F6*$F$21)) -> 0.69548796 | F38: =F29 -> 0.45925 | G38: =E38+F38 -> 1.154738 | H38: =ROUND((D38*E38),2)+ROUND((D38*F38),2) -> -11.54
B39: Energ Injetada FP | D39: -100 | E39: =IF(AND($B$15<$F$2,$E$15<$F$2),C7*$F$19,IF($B$15<$F$2,(((C7*F19)*C15)+((F7*F22)*D15))/(C15+D15),F7*$F$22)) -> 0.27186715 | F39: =F30 -> 0.29163 | G39: =E39+F39 -> 0.56349715 | H39: =ROUND((D39*E39),2)+ROUND((D39*F39),2) -> -56.35
B40: Energ Injetada Intem | D40: -10 | E40: =IF(AND($B$15<$F$2,$E$15<$F$2),C8*$F$20,IF($B$15<$F$2,(((C8*F20)*C15)+((F8*F23)*D15))/(C15+D15),F8*$F$23)) -> 0.48369786 | F40: =F31 -> 0.29163 | G40: =E40+F40 -> 0.77532786 | H40: =ROUND((D40*E40),2)+ROUND((D40*F40),2) -> -7.76
B42: Adicional BAM Inj | D42: =IF($K$13=M4,((D38+D39+D40)*(K15)/(K15+L15)),0)+IF($L$13=M4,((D38+D39+D40)*(L15)/(K15+L15)),0) -> 0 | F42: =N13 -> 0 | H42: =ROUND(D42*(E42+F42),2) -> 0
B43: Adicional BVM 1 Inj | D43: =IF($K$13=M5,((D39+D40+D41)*(K15)/(K15+L15)),0)+IF($L$13=M5,((D39+D40+D41)*(L15)/(K15+L15)),0) -> 0 | F43: =N14 -> 0 | H43: =ROUND(D43*(E43+F43),2) -> 0
B44: Adicional BVM 2 Inj | D44: =IF($K$13=M6,((D40+D41+D42)*(K15)/(K15+L15)),0)+IF($L$13=M6,((D40+D41+D42)*(L15)/(K15+L15)),0) -> 0 | F44: =N15 -> 0 | H44: =ROUND(D44*(E44+F44),2) -> 0
B45: Adicional Escassez Hídrica Inj | D45: =IF($K$13=M7,((D41+D42+D43)*(K15)/(K15+L15)),0)+IF($L$13=M7,((D41+D42+D43)*(L15)/(K15+L15)),0) -> 0 | F45: =N16 -> 0 | H45: =ROUND(D45*(E45+F45),2) -> 0
D48: Base de Cálculo
B49: PIS | D49: =(SUM(H29:H36)/(1-E49-E50)) -> 637.49348 | E49: 0.0073 | H49: =D49*E49 -> 4.6537024
B50: COFINS | D50: =D49 -> 637.49348 | E50: 0.0336 | H50: =D50*E50 -> 21.419781
B51: ICMS | D51: =D49/(1-E51) -> 768.06444 | E51: 0.17 | H51: =D51*E51 -> 130.57095
B53: Informativo Escassez Hídrica | D53: =SUM(D29:D31)+SUM(D38:D40) -> 758 | E53: =IF(AND($B$15<$F$2,$E$15<$F$2),C9,IF($B$15<$F$2,I9,F9)) -> 0.00020783074 | F53: =IF(AND($B$15<$F$2,$E$15<$F$2),D9,IF($B$15<$F$2,J9,G9)) -> 0.00401792 | H53: =D53*(E53+F53) -> 3.2031191
B55: Participação
C56: R$
B57: Energia | C57: =(SUM(H29:H36)*IF($B$15<$F$2,D95,D67)) -> 264.58339
B58: Distribuição | C58: =(SUM(H29:H36)*IF($B$15<$F$2,F95,F67)) -> 158.84823
B59: Transmissão | C59: =(SUM(H29:H36)*IF($B$15<$F$2,E95,E67)) -> 49.785499
B60: Encargos Setoriais | C60: =(SUM(H29:H36)*IF($B$15<$F$2,G95,G67)) -> 138.20288
B61: Impostos / Tributos | C61: =H49+H50+H51 -> 156.64444
B62: Total | C62: =SUM(C57:C61) -> 768.06444
B64: 2023 | D64: Energia | E64: Transmissão | F64: Distribuição | G64: Setoriais
B65: Grupo B | D65: % | E65: % | F65: % | G65: %
B67: B1 - Residencial | D67: 0.43273591 | E67: 0.081426023 | F67: 0.25980216 | G67: 0.22603591
B68: B1 - Residencial Baixa Renda | D68: 0.52914975 | E68: 0.099567792 | F68: 0.31768624 | G68: 0.053596219
B69: B2 - Rural | D69: 0.43273591 | E69: 0.081426023 | F69: 0.25980216 | G69: 0.22603591
B70: B2 - Cooperativa Eletrificação Rural | D70: 0.43273591 | E70: 0.081426023 | F70: 0.25980216 | G70: 0.22603591
B71: B2 - Serviço de Irrigação | D71: 0.43273591 | E71: 0.081426023 | F71: 0.25980216 | G71: 0.22603591
B72: B3 - Demais Classes | D72: 0.43273591 | E72: 0.081426023 | F72: 0.25980216 | G72: 0.22603591
B73: B4 - Iluminação Pública | D73: 0.43273591 | E73: 0.081426023 | F73: 0.25980216 | G73: 0.22603591
B74: B4a - Rede de Distribuição | D74: 0.43273591 | E74: 0.081426023 | F74: 0.25980216 | G74: 0.22603591
B75: B4b - Bulbo de Lâmpada | D75: 0.43273591 | E75: 0.081426023 | F75: 0.25980216 | G75: 0.22603591
B78: 2022 | D78: Energia | E78: Transmissão | F78: Distribuição | G78: Setoriais
B79: Grupo B | D79: % | E79: % | F79: % | G79: %
B81: B1 - Residencial | D81: 0.43273591 | E81: 0.081426023 | F81: 0.25980216 | G81: 0.22603591
B82: B1 - Residencial Baixa Renda | D82: 0.52914975 | E82: 0.099567792 | F82: 0.31768624 | G82: 0.053596219
B83: B2 - Rural | D83: 0.43273591 | E83: 0.081426023 | F83: 0.25980216 | G83: 0.22603591
B84: B2 - Cooperativa Eletrificação Rural | D84: 0.43273591 | E84: 0.081426023 | F84: 0.25980216 | G84: 0.22603591
B85: B2 - Serviço de Irrigação | D85: 0.43273591 | E85: 0.081426023 | F85: 0.25980216 | G85: 0.22603591
B86: B3 - Demais Classes | D86: 0.43273591 | E86: 0.081426023 | F86: 0.25980216 | G86: 0.22603591
B87: B4 - Iluminação Pública | D87: 0.43273591 | E87: 0.081426023 | F87: 0.25980216 | G87: 0.22603591
B88: B4a - Rede de Distribuição | D88: 0.43273591 | E88: 0.081426023 | F88: 0.25980216 | G88: 0.22603591
B89: B4b - Bulbo de Lâmpada | D89: 0.43273591 | E89: 0.081426023 | F89: 0.25980216 | G89: 0.22603591
B91: proporcional
D92: Energia | E92: Transmissão | F92: Distribuição | G92: Setoriais
B93: Grupo B | D93: % | E93: % | F93: % | G93: %
B95: B1 - Residencial | D95: =((D81*$C$15)+(D67*$D$15))/($C$15+$D$15) -> 0.43273591 | E95: =((E81*$C$15)+(E67*$D$15))/($C$15+$D$15) -> 0.081426023 | F95: =((F81*$C$15)+(F67*$D$15))/($C$15+$D$15) -> 0.25980216 | G95: =((G81*$C$15)+(G67*$D$15))/($C$15+$D$15) -> 0.22603591
B96: B1 - Residencial Baixa Renda | D96: =((D82*$C$15)+(D68*$D$15))/($C$15+$D$15) -> 0.52914975 | E96: =((E82*$C$15)+(E68*$D$15))/($C$15+$D$15) -> 0.099567792 | F96: =((F82*$C$15)+(F68*$D$15))/($C$15+$D$15) -> 0.31768624 | G96: =((G82*$C$15)+(G68*$D$15))/($C$15+$D$15) -> 0.053596219
B97: B2 - Rural | D97: =((D83*$C$15)+(D69*$D$15))/($C$15+$D$15) -> 0.43273591 | E97: =((E83*$C$15)+(E69*$D$15))/($C$15+$D$15) -> 0.081426023 | F97: =((F83*$C$15)+(F69*$D$15))/($C$15+$D$15) -> 0.25980216 | G97: =((G83*$C$15)+(G69*$D$15))/($C$15+$D$15) -> 0.22603591
B98: B2 - Cooperativa Eletrificação Rural | D98: =((D84*$C$15)+(D70*$D$15))/($C$15+$D$15) -> 0.43273591 | E98: =((E84*$C$15)+(E70*$D$15))/($C$15+$D$15) -> 0.081426023 | F98: =((F84*$C$15)+(F70*$D$15))/($C$15+$D$15) -> 0.25980216 | G98: =((G84*$C$15)+(G70*$D$15))/($C$15+$D$15) -> 0.22603591
B99: B2 - Serviço de Irrigação | D99: =((D85*$C$15)+(D71*$D$15))/($C$15+$D$15) -> 0.43273591 | E99: =((E85*$C$15)+(E71*$D$15))/($C$15+$D$15) -> 0.081426023 | F99: =((F85*$C$15)+(F71*$D$15))/($C$15+$D$15) -> 0.25980216 | G99: =((G85*$C$15)+(G71*$D$15))/($C$15+$D$15) -> 0.22603591
B100: B3 - Demais Classes | D100: =((D86*$C$15)+(D72*$D$15))/($C$15+$D$15) -> 0.43273591 | E100: =((E86*$C$15)+(E72*$D$15))/($C$15+$D$15) -> 0.081426023 | F100: =((F86*$C$15)+(F72*$D$15))/($C$15+$D$15) -> 0.25980216 | G100: =((G86*$C$15)+(G72*$D$15))/($C$15+$D$15) -> 0.22603591
B101: B4 - Iluminação Pública | D101: =((D87*$C$15)+(D73*$D$15))/($C$15+$D$15) -> 0.43273591 | E101: =((E87*$C$15)+(E73*$D$15))/($C$15+$D$15) -> 0.081426023 | F101: =((F87*$C$15)+(F73*$D$15))/($C$15+$D$15) -> 0.25980216 | G101: =((G87*$C$15)+(G73*$D$15))/($C$15+$D$15) -> 0.22603591
B102: B4a - Rede de Distribuição | D102: =((D88*$C$15)+(D74*$D$15))/($C$15+$D$15) -> 0.43273591 | E102: =((E88*$C$15)+(E74*$D$15))/($C$15+$D$15) -> 0.081426023 | F102: =((F88*$C$15)+(F74*$D$15))/($C$15+$D$15) -> 0.25980216 | G102: =((G88*$C$15)+(G74*$D$15))/($C$15+$D$15) -> 0.22603591
B103: B4b - Bulbo de Lâmpada | D103: =((D89*$C$15)+(D75*$D$15))/($C$15+$D$15) -> 0.43273591 | E103: =((E89*$C$15)+(E75*$D$15))/($C$15+$D$15) -> 0.081426023 | F103: =((F89*$C$15)+(F75*$D$15))/($C$15+$D$15) -> 0.25980216 | G103: =((G89*$C$15)+(G75*$D$15))/($C$15+$D$15) -> 0.22603591

Sheet B3 GD Branca GDII X
B2: B3 | E2: Vigência das Tarifas: | F2: 45358 | H2: TARIFA BRANCA | M2: Bandeira | N2: R$/kWh | Q2: TUSD FIO B
M3: VERDE | N3: ='[4]B1 (Res) Branca OK'!N3 -> 0
B4: TARIFA | C4: TARIFA ANTIGA - REH 3091/2022 | F4: ='Fatura B1 (GD II) OK'!F4 -> TARIFA NOVA - REH xxxx/2025 | I4: Tarifas Proporcionalizadas | M4: BAM | N4: ='[4]B1 (Res) Branca OK'!N4 -> 0.01885 | Q4: TARIFA | R4: =C4 -> TARIFA ANTIGA - REH 3091/2022 | U4: =F4 -> TARIFA NOVA - REH xxxx/2025 | X4: Tarifas Proporcionalizadas
C5: Tusd | D5: TE | E5: TUSD + TE | F5: Tusd | G5: TE | H5: TUSD + TE | I5: Tusd | J5: TE | K5: TUSD + TE | M5: BVM1 | N5: ='[4]B1 (Res) Branca OK'!N5 -> 0.04463 | R5: Tusd (R$/kWh) | U5: Tusd (R$/kWh) | X5: Tusd (R$/kWh)
B6: B1 Ponta | C6: ='[4]TABELA DE TARIFAS ANTIGAS'!G85/1000 -> 0.95901 | D6: ='[4]TABELA DE TARIFAS ANTIGAS'!H85/1000 -> 0.45925 | E6: =C6+D6 -> 1.41826 | F6: ='[4]TABELA DE TARIFAS NOVAS'!G87/1000 -> 0.95897 | G6: ='[4]TABELA DE TARIFAS NOVAS'!H87/1000 -> 0.45611 | H6: =F6+G6 -> 1.41508 | I6: =((C6*$C$15)+(F6*$D$15))/($D$15+$C$15) -> 0.95899 | J6: =((D6*$C$15)+(G6*$D$15))/($D$15+$C$15) -> 0.45768 | K6: =I6+J6 -> 1.41667 | M6: BVM2 | N6: ='[4]B1 (Res) Branca OK'!N6 -> 0.07877 | Q6: =B6 -> B1 Ponta | R6: ='[4]FIO B'!H29/1000 -> 0.67216 | U6: ='[4]FIO B'!K29/1000 -> 0.61783277 | X6: =((R6*$C$15)+(U6*$D$15))/($D$15+$C$15) -> 0.64499639
B7: B1 Fora Ponta | C7: ='[4]TABELA DE TARIFAS ANTIGAS'!G87/1000 -> 0.32456 | D7: ='[4]TABELA DE TARIFAS ANTIGAS'!H87/1000 -> 0.29163 | E7: =C7+D7 -> 0.61619 | F7: ='[4]TABELA DE TARIFAS NOVAS'!G89/1000 -> 0.31445 | G7: ='[4]TABELA DE TARIFAS NOVAS'!H89/1000 -> 0.28686 | H7: =F7+G7 -> 0.60131 | I7: =((C7*$C$15)+(F7*$D$15))/($D$15+$C$15) -> 0.319505 | J7: =((D7*$C$15)+(G7*$D$15))/($D$15+$C$15) -> 0.289245 | K7: =I7+J7 -> 0.60875 | M7: Escassez Hídrica | N7: 0.142 | Q7: =B7 -> B1 Fora Ponta | R7: ='[4]FIO B'!H31/1000 -> 0.13443 | U7: ='[4]FIO B'!K31/1000 -> 0.12356657 | X7: =((R7*$C$15)+(U7*$D$15))/($D$15+$C$15) -> 0.12899829
B8: B1 Interm. | C8: ='[4]TABELA DE TARIFAS ANTIGAS'!G86/1000 -> 0.64178 | D8: ='[4]TABELA DE TARIFAS ANTIGAS'!H86/1000 -> 0.29163 | E8: =C8+D8 -> 0.93341 | F8: ='[4]TABELA DE TARIFAS NOVAS'!G88/1000 -> 0.63671 | G8: ='[4]TABELA DE TARIFAS NOVAS'!H88/1000 -> 0.28686 | H8: =F8+G8 -> 0.92357 | I8: =((C8*$C$15)+(F8*$D$15))/($D$15+$C$15) -> 0.639245 | J8: =((D8*$C$15)+(G8*$D$15))/($D$15+$C$15) -> 0.289245 | K8: =I8+J8 -> 0.92849 | Q8: =B8 -> B1 Interm. | R8: ='[4]FIO B'!H30/1000 -> 0.4033 | U8: ='[4]FIO B'!K30/1000 -> 0.37069963 | X8: =((R8*$C$15)+(U8*$D$15))/($D$15+$C$15) -> 0.38699981
B9: CDE Escassez Hídrica | C9: ='[4]B1 (Res) Branca OK'!C8 -> 0.55341 | D9: ='[4]B1 (Res) Branca OK'!D8 -> 0.29163 | E9: =SUM(C9+D9) -> 0.84504 | F9: =T12 -> 0 | G9: =U12 -> 0.00561 | H9: =F9+G9 -> 0.00561 | I9: =((C9*$C$15)+(F9*$D$15))/($D$15+$C$15) -> 0.276705 | J9: =((D9*$C$15)+(G9*$D$15))/($D$15+$C$15) -> 0.14862 | K9: =I9+J9 -> 0.425325
P10: CUSTO | R10: Part. TUSD (%) | S10: Part. TE (%) | T10: Tusd (R$/kWh) | U10: TE (R$/kWh)
H11: Fatura | L11: Vigência das Tarifas (troca Bandeira): | M11: =EOMONTH(B15,0)+1 -> 45352 | P11: CDE CONTAS
B12: INSTALAÇÃO | C12: 302116 | H12: =E15 -> 45365 | K12: Altere a bandeira na célula abaixo | P12: CDE COVID | U12: =5.61/1000 -> 0.00561
K13: BAM | L13: VERDE | P13: CDE ESCASSEZ HÍDRICA | T13: =0.175672859965349/1000 -> 0.00017567286 | U13: =3.42973552660492/1000 -> 0.0034297355
B14: Leitura Anterior | C14: Nº de dias tarifa Anterior | D14: Nº de dias tarifa Nova | E14: Leitura Atual | J14: Leitura Anterior | K14: Nº de dias tarifa Anterior | L14: Nº de dias tarifa Nova | M14: Leitura Atual
B15: 45349 | C15: =IF((F2-B15-1)<0,0,(F2-B15-1)) -> 8 | D15: =E15-F2+1 -> 8 | E15: 45365 | J15: =B15 -> 45349 | K15: =IF((M11-J15-1)<0,0,(M11-J15-1)) -> 2 | L15: =M15-M11+1 -> 14 | M15: =E15 -> 45365
B18: Perc. de Redução da Energia Injetada | E18: TUSD P | F18: 0.8067 | G18: TE | H18: 1 | I18: Até 06/08/2023 | K18: Doc impr | L18: 30005966440
E19: TUSD FP | F19: 0.8267 | G19: TE | H19: 1 | I19: Até 06/08/2023
E20: TUSD Intem | F20: 0.8858 | G20: TE | H20: 1 | I20: Até 06/08/2023
E21: TUSD P | F21: 0.7939 | G21: TE | H21: 1 | I21: A partir de 07/08/2024
E22: TUSD FP | F22: 0.8743 | G22: TE | H22: 1 | I22: A partir de 07/08/2024
E23: TUSD Intem | F23: 0.8137 | G23: TE | H23: 1 | I23: A partir de 07/08/2024
B25: Fatura B1 Residencial TB
D26: Qtde | E26: TUSD | F26: TE | G26: TUSD + TE | H26: R$
B27: Fornecimento de Energia Elétrica | H27: =SUM(H29:H36)+SUM(H49:H51) -> 743.92032
R28: TUSD Fio B | S28: Receita Fio B
B29: Consumo Ponta | D29: 200 | E29: =IF(AND($B$15<$F$2,$E$15<$F$2),C6,IF($B$15<$F$2,I6,F6)) -> 0.95899 | F29: =IF(AND($B$15<$F$2,$E$15<$F$2),D6,IF($B$15<$F$2,J6,G6)) -> 0.45768 | G29: =E29+F29 -> 1.41667 | H29: =ROUND((D29*E29),2)+ROUND((D29*F29),2) -> 283.34 | R29: =IF(AND($B$15<$F$2,$E$15<$F$2),R6,IF($B$15<$F$2,X6,U6)) -> 0.64499639 | S29: =D29*R29 -> 128.99928 | U29: =D29*E29 -> 191.798
B30: Consumo Fora Ponta | D30: 200 | E30: =IF(AND($B$15<$F$2,$E$15<$F$2),C7,IF($B$15<$F$2,I7,F7)) -> 0.319505 | F30: =IF(AND($B$15<$F$2,$E$15<$F$2),D7,IF($B$15<$F$2,J7,G7)) -> 0.289245 | G30: =E30+F30 -> 0.60875 | H30: =ROUND((D30*E30),2)+ROUND((D30*F30),2) -> 121.75 | R30: =IF(AND($B$15<$F$2,$E$15<$F$2),R7,IF($B$15<$F$2,X7,U7)) -> 0.12899829 | S30: =D30*R30 -> 25.799657 | U30: =D30*E30 -> 63.901
B31: Consumo Intemediário | D31: 200 | E31: =IF(AND($B$15<$F$2,$E$15<$F$2),C8,IF($B$15<$F$2,I8,F8)) -> 0.639245 | F31: =IF(AND($B$15<$F$2,$E$15<$F$2),D8,IF($B$15<$F$2,J8,G8)) -> 0.289245 | G31: =E31+F31 -> 0.92849 | H31: =ROUND((D31*E31),2)+ROUND((D31*F31),2) -> 185.7 | R31: =IF(AND($B$15<$F$2,$E$15<$F$2),R8,IF($B$15<$F$2,X8,U8)) -> 0.38699981 | S31: =D31*R31 -> 77.399963 | U31: =D31*E31 -> 127.849
S32: =SUM(S29:S31) -> 232.1989 | U32: =SUM(U29:U31) -> 383.548
B33: Adicional BAM | D33: =IF($K$13=M4,((D29+D30+D31)*(K15)/(K15+L15)),0)+IF($L$13=M4,((D29+D30+D31)*(L15)/(K15+L15)),0) -> 75 | F33: =N4 -> 0.01885 | H33: =ROUND(D33*(E33+F33),2) -> 1.41
B34: Adicional BVM 1 | D34: =IF($K$13=M5,((D29+D30+D31)*(K15)/(K15+L15)),0)+IF($L$13=M5,((D29+D30+D31)*(L15)/(K15+L15)),0) -> 0 | F34: =N5 -> 0.04463 | H34: =ROUND(D34*(E34+F34),2) -> 0
B35: Adicional BVM 2 | D35: =IF($K$13=M6,((D29+D30+D31)*(K15)/(K15+L15)),0)+IF($L$13=M6,((D29+D30+D31)*(L15)/(K15+L15)),0) -> 0 | F35: =N6 -> 0.07877 | H35: =ROUND(D35*(E35+F35),2) -> 0
B36: Adicional Escassez Hídrica | D36: =IF($K$13=M7,((D29+D30+D31)*(K15)/(K15+L15)),0)+IF($L$13=M7,((D29+D30+D31)*(L15)/(K15+L15)),0) -> 0 | F36: =N7 -> 0.142 | H36: =ROUND(D36*(E36+F36),2) -> 0
B38: Energ Injetada P | D38: -200 | E38: =IF(AND($B$15<$F$2,$E$15<$F$2),C6*$F$18,IF($B$15<$F$2,(((C6*F18)*C15)+((F6*F21)*D15))/(C15+D15),F6*$F$21)) -> 0.76747983 | F38: =F29 -> 0.45768 | G38: =E38+F38 -> 1.2251598 | H38: =ROUND((D38*E38),2)+ROUND((D38*F38),2) -> -245.04
B39: Energ Injetada FP | D39: -200 | E39: =IF(AND($B$15<$F$2,$E$15<$F$2),C7*$F$19,IF($B$15<$F$2,(((C7*F19)*C15)+((F7*F22)*D15))/(C15+D15),F7*$F$22)) -> 0.27161869 | F39: =F30 -> 0.289245 | G39: =E39+F39 -> 0.56086369 | H39: =ROUND((D39*E39),2)+ROUND((D39*F39),2) -> -112.17
B40: Energ Injetada Intem | D40: -200 | E40: =IF(AND($B$15<$F$2,$E$15<$F$2),C8*$F$20,IF($B$15<$F$2,(((C8*F20)*C15)+((F8*F23)*D15))/(C15+D15),F8*$F$23)) -> 0.54328983 | F40: =F31 -> 0.289245 | G40: =E40+F40 -> 0.83253483 | H40: =ROUND((D40*E40),2)+ROUND((D40*F40),2) -> -166.51
B42: Adicional BAM Inj | D42: =IF($K$13=M4,((D38+D39+D40)*(K15)/(K15+L15)),0)+IF($L$13=M4,((D38+D39+D40)*(L15)/(K15+L15)),0) -> -75 | F42: =N4 -> 0.01885 | H42: =ROUND(D42*(E42+F42),2) -> -1.41
B43: Adicional BVM 1 Inj | D43: =IF($K$13=M5,((D39+D40+D41)*(K15)/(K15+L15)),0)+IF($L$13=M5,((D39+D40+D41)*(L15)/(K15+L15)),0) -> 0 | F43: =N14 -> 0 | H43: =ROUND(D43*(E43+F43),2) -> 0
B44: Adicional BVM 2 Inj | D44: =IF($K$13=M6,((D40+D41+D42)*(K15)/(K15+L15)),0)+IF($L$13=M6,((D40+D41+D42)*(L15)/(K15+L15)),0) -> 0 | F44: =N15 -> 0 | H44: =ROUND(D44*(E44+F44),2) -> 0
B45: Adicional Escassez Hídrica Inj | D45: =IF($K$13=M7,((D41+D42+D43)*(K15)/(K15+L15)),0)+IF($L$13=M7,((D41+D42+D43)*(L15)/(K15+L15)),0) -> 0 | F45: =N16 -> 0 | H45: =ROUND(D45*(E45+F45),2) -> 0
D48: Base de Cálculo
B49: PIS | D49: =(SUM(H29:H36)/(1-E49-E50)) -> 617.45386 | E49: 0.0073 | H49: =D49*E49 -> 4.5074132
B50: COFINS | D50: =D49 -> 617.45386 | E50: 0.0336 | H50: =D50*E50 -> 20.74645
B51: ICMS | D51: =D49/(1-E51) -> 743.92032 | E51: 0.17 | H51: =D51*E51 -> 126.46645
B53: Informativo Escassez Hídrica | D53: =SUM(D29:D31)+SUM(D38:D40) -> 0 | E53: =IF(AND($B$15<$F$2,$E$15<$F$2),C9,IF($B$15<$F$2,I9,F9)) -> 0.276705 | F53: =IF(AND($B$15<$F$2,$E$15<$F$2),D9,IF($B$15<$F$2,J9,G9)) -> 0.14862 | H53: =D53*(E53+F53) -> 0
B55: Participação
C56: R$
B57: Energia | C57: =(SUM(H29:H36)*IF($B$15<$F$2,D95,D67)) -> 256.26621
B58: Distribuição | C58: =(SUM(H29:H36)*IF($B$15<$F$2,F95,F67)) -> 153.85484
B59: Transmissão | C59: =(SUM(H29:H36)*IF($B$15<$F$2,E95,E67)) -> 48.220491
B60: Encargos Setoriais | C60: =(SUM(H29:H36)*IF($B$15<$F$2,G95,G67)) -> 133.85847
B61: Impostos / Tributos | C61: =H49+H50+H51 -> 151.72032
B62: Total | C62: =SUM(C57:C61) -> 743.92032
B64: 2023 | D64: Energia | E64: Transmissão | F64: Distribuição | G64: Setoriais
B65: Grupo B | D65: % | E65: % | F65: % | G65: %
B67: B1 - Residencial | D67: 0.43273591 | E67: 0.081426023 | F67: 0.25980216 | G67: 0.22603591
B68: B1 - Residencial Baixa Renda | D68: 0.52914975 | E68: 0.099567792 | F68: 0.31768624 | G68: 0.053596219
B69: B2 - Rural | D69: 0.43273591 | E69: 0.081426023 | F69: 0.25980216 | G69: 0.22603591
B70: B2 - Cooperativa Eletrificação Rural | D70: 0.43273591 | E70: 0.081426023 | F70: 0.25980216 | G70: 0.22603591
B71: B2 - Serviço de Irrigação | D71: 0.43273591 | E71: 0.081426023 | F71: 0.25980216 | G71: 0.22603591
B72: B3 - Demais Classes | D72: 0.43273591 | E72: 0.081426023 | F72: 0.25980216 | G72: 0.22603591
B73: B4 - Iluminação Pública | D73: 0.43273591 | E73: 0.081426023 | F73: 0.25980216 | G73: 0.22603591
B74: B4a - Rede de Distribuição | D74: 0.43273591 | E74: 0.081426023 | F74: 0.25980216 | G74: 0.22603591
B75: B4b - Bulbo de Lâmpada | D75: 0.43273591 | E75: 0.081426023 | F75: 0.25980216 | G75: 0.22603591
B78: 2022 | D78: Energia | E78: Transmissão | F78: Distribuição | G78: Setoriais
B79: Grupo B | D79: % | E79: % | F79: % | G79: %
B81: B1 - Residencial | D81: 0.43273591 | E81: 0.081426023 | F81: 0.25980216 | G81: 0.22603591
B82: B1 - Residencial Baixa Renda | D82: 0.52914975 | E82: 0.099567792 | F82: 0.31768624 | G82: 0.053596219
B83: B2 - Rural | D83: 0.43273591 | E83: 0.081426023 | F83: 0.25980216 | G83: 0.22603591
B84: B2 - Cooperativa Eletrificação Rural | D84: 0.43273591 | E84: 0.081426023 | F84: 0.25980216 | G84: 0.22603591
B85: B2 - Serviço de Irrigação | D85: 0.43273591 | E85: 0.081426023 | F85: 0.25980216 | G85: 0.22603591
B86: B3 - Demais Classes | D86: 0.43273591 | E86: 0.081426023 | F86: 0.25980216 | G86: 0.22603591
B87: B4 - Iluminação Pública | D87: 0.43273591 | E87: 0.081426023 | F87: 0.25980216 | G87: 0.22603591
B88: B4a - Rede de Distribuição | D88: 0.43273591 | E88: 0.081426023 | F88: 0.25980216 | G88: 0.22603591
B89: B4b - Bulbo de Lâmpada | D89: 0.43273591 | E89: 0.081426023 | F89: 0.25980216 | G89: 0.22603591
B91: proporcional
D92: Energia | E92: Transmissão | F92: Distribuição | G92: Setoriais
B93: Grupo B | D93: % | E93: % | F93: % | G93: %
B95: B1 - Residencial | D95: =((D81*$C$15)+(D67*$D$15))/($C$15+$D$15) -> 0.43273591 | E95: =((E81*$C$15)+(E67*$D$15))/($C$15+$D$15) -> 0.081426023 | F95: =((F81*$C$15)+(F67*$D$15))/($C$15+$D$15) -> 0.25980216 | G95: =((G81*$C$15)+(G67*$D$15))/($C$15+$D$15) -> 0.22603591
B96: B1 - Residencial Baixa Renda | D96: =((D82*$C$15)+(D68*$D$15))/($C$15+$D$15) -> 0.52914975 | E96: =((E82*$C$15)+(E68*$D$15))/($C$15+$D$15) -> 0.099567792 | F96: =((F82*$C$15)+(F68*$D$15))/($C$15+$D$15) -> 0.31768624 | G96: =((G82*$C$15)+(G68*$D$15))/($C$15+$D$15) -> 0.053596219
B97: B2 - Rural | D97: =((D83*$C$15)+(D69*$D$15))/($C$15+$D$15) -> 0.43273591 | E97: =((E83*$C$15)+(E69*$D$15))/($C$15+$D$15) -> 0.081426023 | F97: =((F83*$C$15)+(F69*$D$15))/($C$15+$D$15) -> 0.25980216 | G97: =((G83*$C$15)+(G69*$D$15))/($C$15+$D$15) -> 0.22603591
B98: B2 - Cooperativa Eletrificação Rural | D98: =((D84*$C$15)+(D70*$D$15))/($C$15+$D$15) -> 0.43273591 | E98: =((E84*$C$15)+(E70*$D$15))/($C$15+$D$15) -> 0.081426023 | F98: =((F84*$C$15)+(F70*$D$15))/($C$15+$D$15) -> 0.25980216 | G98: =((G84*$C$15)+(G70*$D$15))/($C$15+$D$15) -> 0.22603591
B99: B2 - Serviço de Irrigação | D99: =((D85*$C$15)+(D71*$D$15))/($C$15+$D$15) -> 0.43273591 | E99: =((E85*$C$15)+(E71*$D$15))/($C$15+$D$15) -> 0.081426023 | F99: =((F85*$C$15)+(F71*$D$15))/($C$15+$D$15) -> 0.25980216 | G99: =((G85*$C$15)+(G71*$D$15))/($C$15+$D$15) -> 0.22603591
B100: B3 - Demais Classes | D100: =((D86*$C$15)+(D72*$D$15))/($C$15+$D$15) -> 0.43273591 | E100: =((E86*$C$15)+(E72*$D$15))/($C$15+$D$15) -> 0.081426023 | F100: =((F86*$C$15)+(F72*$D$15))/($C$15+$D$15) -> 0.25980216 | G100: =((G86*$C$15)+(G72*$D$15))/($C$15+$D$15) -> 0.22603591
B101: B4 - Iluminação Pública | D101: =((D87*$C$15)+(D73*$D$15))/($C$15+$D$15) -> 0.43273591 | E101: =((E87*$C$15)+(E73*$D$15))/($C$15+$D$15) -> 0.081426023 | F101: =((F87*$C$15)+(F73*$D$15))/($C$15+$D$15) -> 0.25980216 | G101: =((G87*$C$15)+(G73*$D$15))/($C$15+$D$15) -> 0.22603591
B102: B4a - Rede de Distribuição | D102: =((D88*$C$15)+(D74*$D$15))/($C$15+$D$15) -> 0.43273591 | E102: =((E88*$C$15)+(E74*$D$15))/($C$15+$D$15) -> 0.081426023 | F102: =((F88*$C$15)+(F74*$D$15))/($C$15+$D$15) -> 0.25980216 | G102: =((G88*$C$15)+(G74*$D$15))/($C$15+$D$15) -> 0.22603591
B103: B4b - Bulbo de Lâmpada | D103: =((D89*$C$15)+(D75*$D$15))/($C$15+$D$15) -> 0.43273591 | E103: =((E89*$C$15)+(E75*$D$15))/($C$15+$D$15) -> 0.081426023 | F103: =((F89*$C$15)+(F75*$D$15))/($C$15+$D$15) -> 0.25980216 | G103: =((G89*$C$15)+(G75*$D$15))/($C$15+$D$15) -> 0.22603591

Sheet V4 MMGD GDII
B2: A4 Verde | C2: MMGD | E2: Vigência das Tarifas: | F2: ='[5]A2 Azul'!F2 -> 45145 | I2: OK | M2: Bandeira | N2: R$/kWh | Q2: TUSD FIO B
M3: VERDE | N3: =[5]BANDEIRA!$D$4 -> 0
B4: TARIFA | C4: ='[5]A2 Azul'!C4:E4 -> TARIFA ANTIGA - REH 3091/2022 | F4: ='[5]A2 Azul'!F4:H4 -> TARIFA NOVA - REH 3241/2023 | I4: Tarifas Proporcionalizadas | M4: BAM | N4: =[5]BANDEIRA!$D$5 -> 0.02989 | Q4: TARIFA | R4: =C4 -> TARIFA ANTIGA - REH 3091/2022 | U4: =F4 -> TARIFA NOVA - REH 3241/2023 | X4: Tarifas Proporcionalizadas
C5: Tusd (R$/kW) | D5: Tusd (R$/kWh) | E5: TE (R$/kWh) | F5: Tusd (R$/kW) | G5: Tusd (R$/kWh) | H5: TE (R$/kWh) | I5: Tusd (R$/kW) | J5: Tusd (R$/kWh) | K5: TE (R$/kWh) | M5: BVM1 | N5: =[5]BANDEIRA!$D$6 -> 0.065 | R5: Tusd (R$/kW) | S5: Tusd (R$/kW) | U5: Tusd (R$/kW) | V5: Tusd (R$/kW) | X5: Tusd (R$/kW) | Y5: Tusd (R$/kW)
B6: A4 Verde P | C6: ='[5]TABELA DE TARIFAS ANTIGAS'!E52 -> 30.44 | D6: ='[5]TABELA DE TARIFAS ANTIGAS'!F53/1000 -> 1.24002 | E6: ='[5]TABELA DE TARIFAS ANTIGAS'!G53/1000 -> 0.4226 | F6: ='[5]TABELA DE TARIFAS NOVAS'!E52 -> 31.53 | G6: ='[5]TABELA DE TARIFAS NOVAS'!F53/1000 -> 1.26783 | H6: ='[5]TABELA DE TARIFAS NOVAS'!G53/1000 -> 0.45803 | I6: =((C6*$C$17)+(F6*$D$17))/($D$17+$C$17) -> 31.319032 | J6: =((D6*$C$17)+(G6*$D$17))/($D$17+$C$17) -> 1.2624474 | K6: =((E6*$C$17)+(H6*$D$17))/($D$17+$C$17) -> 0.45117258 | M6: BVM2 | N6: =[5]BANDEIRA!$D$7 -> 0.09795 | Q6: =B6 -> A4 Verde P | R6: ='[5]Grupo A_FIO B'!F49 -> 26.16 | S6: ='[5]Grupo A_FIO B'!G50/1000 -> 0.93588 | U6: ='[5]Grupo A_FIO B'!I49 -> 24.04 | V6: ='[5]Grupo A_FIO B'!J50/1000 -> 0.86024 | X6: =((R6*$C$17)+(U6*$D$17))/($D$17+$C$17) -> 24.450323 | Y6: =((S6*$C$17)+(V6*$D$17))/($D$17+$C$17) -> 0.87488
B7: A4 Verde FP | D7: ='[5]TABELA DE TARIFAS ANTIGAS'!F54/1000 -> 0.13433 | E7: ='[5]TABELA DE TARIFAS ANTIGAS'!G54/1000 -> 0.2638 | G7: ='[5]TABELA DE TARIFAS NOVAS'!F54/1000 -> 0.12117 | H7: ='[5]TABELA DE TARIFAS NOVAS'!G54/1000 -> 0.29041 | J7: =((D7*$C$17)+(G7*$D$17))/($D$17+$C$17) -> 0.1237171 | K7: =((E7*$C$17)+(H7*$D$17))/($D$17+$C$17) -> 0.28525968 | M7: Escassez Hídrica | N7: =[5]BANDEIRA!$D$8 -> 0.142 | Q7: =B7 -> A4 Verde FP
B8: B1 | D8: ='[5]TABELA DE TARIFAS ANTIGAS'!G71/1000 -> 0.39681 | E8: ='[5]TABELA DE TARIFAS ANTIGAS'!H71/1000 -> 0.27703 | G8: ='[5]TABELA DE TARIFAS NOVAS'!G71/1000 -> 0.39253 | H8: ='[5]TABELA DE TARIFAS NOVAS'!H71/1000 -> 0.3056 | J8: =((D8*$C$17)+(G8*$D$17))/($D$17+$C$17) -> 0.39335839 | K8: =((E8*$C$17)+(H8*$D$17))/($D$17+$C$17) -> 0.30007032
B9: TE SCEE P | H9: =H6*15% -> 0.0687045 | K9: =((D9*$C$17)+(H9*$D$17))/($D$17+$C$17) -> 0.055406855
B10: TE SCEE FP | H10: =H7*15% -> 0.0435615 | K10: =((D10*$C$17)+(H10*$D$17))/($D$17+$C$17) -> 0.035130242
B12: MMGD
H13: Fatura | L13: Vigência das Tarifas (troca Bandeira): | M13: =EOMONTH(B17,0)+1 -> 45139
B14: INSTALAÇÃO | C14: 1175387 | H14: =E17 -> 45169 | K14: Altere a bandeira na célula abaixo
K15: VERDE | L15: VERDE
B16: Leitura Anterior | C16: Nº de dias tarifa Anterior | D16: Nº de dias tarifa Nova | E16: Leitura Atual | J16: Leitura Anterior | K16: Nº de dias tarifa Anterior | L16: Nº de dias tarifa Nova | M16: Leitura Atual
B17: 45138 | C17: =IF((F2-B17-1)<0,0,(F2-B17-1)) -> 6 | D17: =E17-F2+1 -> 25 | E17: 45169 | J17: =B17 -> 45138 | K17: =IF((M13-J17-1)<0,0,(M13-J17-1)) -> 0 | L17: =M17-M13+1 -> 31 | M17: =E17 -> 45169
B19: Perc. de Redução da Energia Injetada | E19: TUSD P | F19: 0.8868 | G19: TE P | H19: 1
E20: TUSD FP | F20: 1 | G20: TE FP | H20: 1
B22: Fatura A4 Verde - MMGD | J22: Documento impressão:
D23: Qtde | E23: TUSD | F23: TE | G23: TUSD + TE | H23: R$
J24: TUSD Fio B | K24: Receita Fio B
B25: Consumo Ponta | D25: 1290.8358 | E25: =IF(AND($B$17<$F$2,$E$17<$F$2),D6,IF($B$17<$F$2,J6,G6)) -> 1.2624474 | F25: =IF(AND($B$17<$F$2,$E$17<$F$2),E6,IF($B$17<$F$2,K6,H6)) -> 0.45117258 | G25: =E25+F25 -> 1.71362 | H25: =ROUND((D25*E25),2)+ROUND((D25*F25),2) -> 2212 | J25: =IF(AND($B$17<$F$2,$E$17<$F$2),S6,IF($B$17<$F$2,Y6,V6)) -> 0.87488 | K25: =D25*J25 -> 1129.3264
B26: Consumo Fora Ponta | D26: 12358.327 | E26: =IF(AND($B$17<$F$2,$E$17<$F$2),D7,IF($B$17<$F$2,J7,G7)) -> 0.1237171 | F26: =IF(AND($B$17<$F$2,$E$17<$F$2),E7,IF($B$17<$F$2,K7,H7)) -> 0.28525968 | G26: =E26+F26 -> 0.40897677 | H26: =ROUND((D26*E26),2)+ROUND((D26*F26),2) -> 5054.27
B28: Adicional BAM | D28: =IF($K$15=$M$4,((D25+D26)*(K17)/(K17+L17)),0)+IF($L$15=$M$4,((D25+D26)*(L17)/(K17+L17)),0) -> 0 | F28: =N4 -> 0.02989 | H28: =ROUND(D28*(E28+F28),2) -> 0
B29: Adicional BVM 1 | D29: =IF($K$15=$M$5,((D25+D26)*(K17)/(K17+L17)),0)+IF($L$15=$M$5,((D25+D26)*(L17)/(K17+L17)),0) -> 0 | F29: =N5 -> 0.065 | H29: =ROUND(D29*(E29+F29),2) -> 0
B30: Adicional BVM 2 | D30: =IF($K$15=$M$6,((D25+D26)*(K17)/(K17+L17)),0)+IF($L$15=$M$6,((D25+D26)*(L17)/(K17+L17)),0) -> 0 | F30: =N6 -> 0.09795 | H30: =ROUND(D30*(E30+F30),2) -> 0
B31: Adic. Escassez Hídrica | D31: =IF($K$15=$M$7,((D25+D26)*(K17)/(K17+L17)),0)+IF($L$15=$M$7,((D25+D26)*(L17)/(K17+L17)),0) -> 0 | F31: =N7 -> 0.142 | H31: =ROUND(D31*(E31+F31),2) -> 0
B33: Energ Injetada Ponta | D33: 0 | E33: =-E25 -> -1.2624474 | F33: =-F25 -> -0.45117258 | H33: =ROUND(D33*(E33+F33),2) -> 0
B34: Energ Injetada Fora Ponta | D34: -1422.72 | E34: =-E26 -> -0.1237171 | F34: =-F26 -> -0.28525968 | H34: =ROUND(D34*(E34+F34),2) -> 581.86
B36: Adicional BAM | D36: =IF($K$15=$M$4,((D33+D34)*(K17)/(K17+L17)),0)+IF($L$15=$M$4,((D33+D34)*(L17)/(K17+L17)),0) -> 0 | F36: =-F28 -> -0.02989 | H36: =ROUND(D36*(E36+F36),2) -> 0
B37: Adicional BVM 1 | D37: =IF($K$15=$M$5,((D33+D34)*(K17)/(K17+L17)),0)+IF($L$15=$M$5,((D33+D34)*(L17)/(K17+L17)),0) -> 0 | F37: =-F29 -> -0.065 | H37: =ROUND(D37*(E37+F37),2) -> 0
B38: Adicional BVM 2 | D38: =IF($K$15=$M$6,((D33+D34)*(K17)/(K17+L17)),0)+IF($L$15=$M$6,((D33+D34)*(L17)/(K17+L17)),0) -> 0 | F38: =-F30 -> -0.09795 | H38: =ROUND(D38*(E38+F38),2) -> 0
B39: Adic. Escassez Hídrica | D39: =IF($K$15=$M$7,((D33+D34)*(K17)/(K17+L17)),0)+IF($L$15=$M$7,((D33+D34)*(L17)/(K17+L17)),0) -> 0 | F39: =-F31 -> -0.142 | H39: =ROUND(D39*(E39+F39),2) -> 0
J40: TUSD Fio B | K40: Receita Fio B | L40: EUSD B
B41: Demanda | D41: 100.86 | E41: =IF(AND($B$17<$F$2,$E$17<$F$2),C6,IF($B$17<$F$2,I6,F6)) -> 31.319032 | H41: =ROUND(D41*(E41+F41),2) -> 3158.84 | J41: =IF(AND($B$17<$F$2,$E$17<$F$2),R6,IF($B$17<$F$2,X6,U6)) -> 24.450323 | K41: =D41*J41 -> 2466.0595 | L41: =K41+K44+K47 -> 2567.2839
B44: Demanda não utilizada | D44: 4.14 | E44: =E41 -> 31.319032 | H44: =ROUND(D44*(E44+F44),2) -> 129.66 | J44: =J41 -> 24.450323 | K44: =D44*J44 -> 101.22434
B47: Ultrap Demanda | D47: 0 | E47: =E41*2 -> 62.638065 | H47: =ROUND(D47*(E47+F47),2) -> 0
B49: Energia Comp. P SCEE | D49: =-D33 -> 0 | E49: =E25 -> 1.2624474 | F49: =IF(AND($B$17<$F$2,$E$17<$F$2),D9,IF($B$17<$F$2,K9,H9)) -> 0.055406855 | G49: =E49+F49 -> 1.3178543 | H49: =ROUND(D49*(E49+F49),2) -> 0
B50: Energia Comp. FP SCEE | D50: =-D34 -> 1422.72 | E50: =E26 -> 0.1237171 | F50: =IF(AND($B$17<$F$2,$E$17<$F$2),D10,IF($B$17<$F$2,K10,H10)) -> 0.035130242 | G50: =E50+F50 -> 0.15884734 | H50: =ROUND(D50*(E50+F50),2) -> 226
B52: Des Energ. Comp. P SCEE | D52: =-D49 -> 0 | E52: =E49*F19 -> 1.1195384 | F52: =F49*H19 -> 0.055406855 | G52: =E52+F52 -> 1.1749452 | H52: =ROUND(D52*(E52+F52),2) -> 0
B53: Des Energ. Comp. FP SCEE | D53: =-D50 -> -1422.72 | E53: =E50*F20 -> 0.1237171 | F53: =F50*H20 -> 0.035130242 | G53: =E53+F53 -> 0.15884734 | H53: =ROUND(D53*(E53+F53),2) -> -226
B55: ERE | D55: 27.675 | F55: =IF(AND($B$17<$F$2,$E$17<$F$2),E8,IF($B$17<$F$2,K8,H8)) -> 0.30007032 | H55: =ROUND(D55*(E55+F55),2) -> 8.3
B56: DRE | D56: 0 | E56: =E42 -> 0 | H56: =ROUND(D56*(E56+F56),2) -> 0
D58: Base de Cálculo
B59: PIS | D59: =(SUM(H25:H31)+H41+H47+H55+H56)/(1-E59-E62) -> 10922.749 | E59: 0.008 | H59: =D59*E59 -> 87.381993
B60: PIS Injetado | D60: =(SUM(H33:H39,H49:H53))/(1-E59-E62) -> 609.14992 | E60: =E59 -> 0.008 | H60: =D60*E60 -> 4.8731993
B61: PIS não utilizada | D61: =(H44)/(1-E61-E64) -> 135.74121 | E61: =E59 -> 0.008 | H61: =D61*E61 -> 1.0859296
B62: COFINS | D62: =D59 -> 10922.749 | E62: 0.0368 | H62: =D62*E62 -> 401.95717
B63: COFINS Injetado | D63: =D60 -> 609.14992 | E63: =E62 -> 0.0368 | H63: =D63*E63 -> 22.416717
B64: COFINS não utilizada | D64: =D61 -> 135.74121 | E64: =E62 -> 0.0368 | H64: =D64*E64 -> 4.9952764
B65: ICMS | D65: =D59/(1-E65) -> 13159.939 | E65: 0.17 | H65: =D65*E65 -> 2237.1896
B66: ICMS Injetado TE | D66: =((D33*F33)+(D34*F34)+SUM(H36:H39)+(D49*F49)+(D50*F50)+(D52*F52)+(D53*F53))/(1-E60-E63)/(1-E66) -> 511.9027 | E66: =E65 -> 0.17 | H66: =D66*E66 -> 87.023458

Sheet A4 MMGD GDII
B2: A4 AZUL | C2: MMGD | E2: Vigência das Tarifas: | F2: ='[5]A2 Azul'!F2 -> 45145 | I2: OK | M2: Bandeira | N2: R$/kWh | Q2: TUSD FIO B
M3: VERDE | N3: =[5]BANDEIRA!$D$4 -> 0
B4: TARIFA | C4: ='[5]A2 Azul'!C4:E4 -> TARIFA ANTIGA - REH 3091/2022 | F4: ='[5]A2 Azul'!F4:H4 -> TARIFA NOVA - REH 3241/2023 | I4: Tarifas Proporcionalizadas | M4: BAM | N4: =[5]BANDEIRA!$D$5 -> 0.02989 | Q4: TARIFA | R4: =C4 -> TARIFA ANTIGA - REH 3091/2022 | U4: =F4 -> TARIFA NOVA - REH 3241/2023 | X4: Tarifas Proporcionalizadas
C5: Tusd (R$/kW) | D5: Tusd (R$/kWh) | E5: TE (R$/kWh) | F5: Tusd (R$/kW) | G5: Tusd (R$/kWh) | H5: TE (R$/kWh) | I5: Tusd (R$/kW) | J5: Tusd (R$/kWh) | K5: TE (R$/kWh) | M5: BVM1 | N5: =[5]BANDEIRA!$D$6 -> 0.065 | R5: Tusd (R$/kW) | S5: Tusd (R$/kW) | U5: Tusd (R$/kW) | V5: Tusd (R$/kW) | X5: Tusd (R$/kW) | Y5: Tusd (R$/kW)
B6: A4 Azul P | C6: ='[5]A4 Azul'!C6 -> 45.59 | D6: ='[5]A4 Azul'!D6 -> 0.13433 | E6: ='[5]A4 Azul'!E6 -> 0.4226 | F6: ='[5]A4 Azul'!F6 -> 47.23 | G6: ='[5]A4 Azul'!G6 -> 0.12117 | H6: ='[5]A4 Azul'!H6 -> 0.45803 | I6: =((C6*$C$17)+(F6*$D$17))/($D$17+$C$17) -> 46.912581 | J6: =((D6*$C$17)+(G6*$D$17))/($D$17+$C$17) -> 0.1237171 | K6: =((E6*$C$17)+(H6*$D$17))/($D$17+$C$17) -> 0.45117258 | M6: BVM2 | N6: =[5]BANDEIRA!$D$7 -> 0.09795 | Q6: =B6 -> A4 Azul P | R6: ='[5]Grupo A_FIO B'!F49 -> 26.16 | S6: ='[5]Grupo A_FIO B'!G50/1000 -> 0.93588 | U6: ='[5]Grupo A_FIO B'!I49 -> 24.04 | V6: ='[5]Grupo A_FIO B'!J50/1000 -> 0.86024 | X6: =((R6*$C$17)+(U6*$D$17))/($D$17+$C$17) -> 24.450323 | Y6: =((S6*$C$17)+(V6*$D$17))/($D$17+$C$17) -> 0.87488
B7: A4 Azul FP | C7: ='[5]A4 Azul'!C7 -> 30.44 | D7: ='[5]A4 Azul'!D7 -> 0.13433 | E7: ='[5]A4 Azul'!E7 -> 0.2638 | F7: ='[5]A4 Azul'!F7 -> 31.53 | G7: ='[5]A4 Azul'!G7 -> 0.12117 | H7: ='[5]A4 Azul'!H7 -> 0.29041 | I7: =((C7*$C$17)+(F7*$D$17))/($D$17+$C$17) -> 31.319032 | J7: =((D7*$C$17)+(G7*$D$17))/($D$17+$C$17) -> 0.1237171 | K7: =((E7*$C$17)+(H7*$D$17))/($D$17+$C$17) -> 0.28525968 | M7: Escassez Hídrica | N7: =[5]BANDEIRA!$D$8 -> 0.142 | Q7: =B7 -> A4 Azul FP
B8: B1 | D8: ='[5]TABELA DE TARIFAS ANTIGAS'!G71/1000 -> 0.39681 | E8: ='[5]TABELA DE TARIFAS ANTIGAS'!H71/1000 -> 0.27703 | G8: ='[5]TABELA DE TARIFAS NOVAS'!G71/1000 -> 0.39253 | H8: ='[5]TABELA DE TARIFAS NOVAS'!H71/1000 -> 0.3056 | J8: =((D8*$C$17)+(G8*$D$17))/($D$17+$C$17) -> 0.39335839 | K8: =((E8*$C$17)+(H8*$D$17))/($D$17+$C$17) -> 0.30007032
B9: TE SCEE P | H9: =H6*15% -> 0.0687045 | K9: =((D9*$C$17)+(H9*$D$17))/($D$17+$C$17) -> 0.055406855
B10: TE SCEE FP | H10: =H7*15% -> 0.0435615 | K10: =((D10*$C$17)+(H10*$D$17))/($D$17+$C$17) -> 0.035130242
B12: MMGD
H13: Fatura | L13: Vigência das Tarifas (troca Bandeira): | M13: =EOMONTH(B17,0)+1 -> 45139
B14: INSTALAÇÃO | H14: =E17 -> 45169 | K14: Altere a bandeira na célula abaixo
K15: VERDE | L15: VERDE
B16: Leitura Anterior | C16: Nº de dias tarifa Anterior | D16: Nº de dias tarifa Nova | E16: Leitura Atual | J16: Leitura Anterior | K16: Nº de dias tarifa Anterior | L16: Nº de dias tarifa Nova | M16: Leitura Atual
B17: 45138 | C17: =IF((F2-B17-1)<0,0,(F2-B17-1)) -> 6 | D17: =E17-F2+1 -> 25 | E17: 45169 | J17: =B17 -> 45138 | K17: =IF((M13-J17-1)<0,0,(M13-J17-1)) -> 0 | L17: =M17-M13+1 -> 31 | M17: =E17 -> 45169
B19: Perc. de Redução da Energia Injetada | E19: TUSD P | F19: 1 | G19: TE P | H19: 1
E20: TUSD FP | F20: 1 | G20: TE FP | H20: 1
B22: Fatura A4 Azul - MMGD | J22: Documento impressão:
D23: Qtde | E23: TUSD | F23: TE | G23: TUSD + TE | H23: R$
J24: TUSD Fio B | K24: Receita Fio B
B25: Consumo Ponta | D25: 1290.8358 | E25: =IF(AND($B$17<$F$2,$E$17<$F$2),D6,IF($B$17<$F$2,J6,G6)) -> 0.1237171 | F25: =IF(AND($B$17<$F$2,$E$17<$F$2),E6,IF($B$17<$F$2,K6,H6)) -> 0.45117258 | G25: =E25+F25 -> 0.57488968 | H25: =ROUND((D25*E25),2)+ROUND((D25*F25),2) -> 742.09 | J25: =IF(AND($B$17<$F$2,$E$17<$F$2),S6,IF($B$17<$F$2,Y6,V6)) -> 0.87488 | K25: =D25*J25 -> 1129.3264
B26: Consumo Fora Ponta | D26: 12358.327 | E26: =IF(AND($B$17<$F$2,$E$17<$F$2),D7,IF($B$17<$F$2,J7,G7)) -> 0.1237171 | F26: =IF(AND($B$17<$F$2,$E$17<$F$2),E7,IF($B$17<$F$2,K7,H7)) -> 0.28525968 | G26: =E26+F26 -> 0.40897677 | H26: =ROUND((D26*E26),2)+ROUND((D26*F26),2) -> 5054.27
B28: Adicional BAM | D28: =IF($K$15=$M$4,((D25+D26)*(K17)/(K17+L17)),0)+IF($L$15=$M$4,((D25+D26)*(L17)/(K17+L17)),0) -> 0 | F28: =N4 -> 0.02989 | H28: =ROUND(D28*(E28+F28),2) -> 0
B29: Adicional BVM 1 | D29: =IF($K$15=$M$5,((D25+D26)*(K17)/(K17+L17)),0)+IF($L$15=$M$5,((D25+D26)*(L17)/(K17+L17)),0) -> 0 | F29: =N5 -> 0.065 | H29: =ROUND(D29*(E29+F29),2) -> 0
B30: Adicional BVM 2 | D30: =IF($K$15=$M$6,((D25+D26)*(K17)/(K17+L17)),0)+IF($L$15=$M$6,((D25+D26)*(L17)/(K17+L17)),0) -> 0 | F30: =N6 -> 0.09795 | H30: =ROUND(D30*(E30+F30),2) -> 0
B31: Adic. Escassez Hídrica | D31: =IF($K$15=$M$7,((D25+D26)*(K17)/(K17+L17)),0)+IF($L$15=$M$7,((D25+D26)*(L17)/(K17+L17)),0) -> 0 | F31: =N7 -> 0.142 | H31: =ROUND(D31*(E31+F31),2) -> 0
B33: Energ Injetada Ponta | D33: 0 | E33: =-E25 -> -0.1237171 | F33: =-F25 -> -0.45117258 | H33: =ROUND(D33*(E33+F33),2) -> 0
B34: Energ Injetada Fora Ponta | D34: 1422.72 | E34: =-E26 -> -0.1237171 | F34: =-F26 -> -0.28525968 | H34: =ROUND(D34*(E34+F34),2) -> -581.86
B36: Adicional BAM | D36: =IF($K$15=$M$4,((D33+D34)*(K17)/(K17+L17)),0)+IF($L$15=$M$4,((D33+D34)*(L17)/(K17+L17)),0) -> 0 | F36: =-F28 -> -0.02989 | H36: =ROUND(D36*(E36+F36),2) -> 0
B37: Adicional BVM 1 | D37: =IF($K$15=$M$5,((D33+D34)*(K17)/(K17+L17)),0)+IF($L$15=$M$5,((D33+D34)*(L17)/(K17+L17)),0) -> 0 | F37: =-F29 -> -0.065 | H37: =ROUND(D37*(E37+F37),2) -> 0
B38: Adicional BVM 2 | D38: =IF($K$15=$M$6,((D33+D34)*(K17)/(K17+L17)),0)+IF($L$15=$M$6,((D33+D34)*(L17)/(K17+L17)),0) -> 0 | F38: =-F30 -> -0.09795 | H38: =ROUND(D38*(E38+F38),2) -> 0
B39: Adic. Escassez Hídrica | D39: =IF($K$15=$M$7,((D33+D34)*(K17)/(K17+L17)),0)+IF($L$15=$M$7,((D33+D34)*(L17)/(K17+L17)),0) -> 0 | F39: =-F31 -> -0.142 | H39: =ROUND(D39*(E39+F39),2) -> 0
J40: TUSD Fio B | K40: Receita Fio B | L40: EUSD B
B41: Demanda Ponta | D41: 100.86 | E41: =IF(AND($B$17<$F$2,$E$17<$F$2),C6,IF($B$17<$F$2,I6,F6)) -> 46.912581 | H41: =ROUND(D41*(E41+F41),2) -> 4731.6 | J41: =IF(AND($B$17<$F$2,$E$17<$F$2),R6,IF($B$17<$F$2,X6,U6)) -> 24.450323 | K41: =D41*J41 -> 2466.0595 | L41: =K41+K44+K47 -> 2567.2839
B42: Demanda Fora Ponta | D42: 100.86 | E42: =IF(AND($B$17<$F$2,$E$17<$F$2),C7,IF($B$17<$F$2,I7,F7)) -> 31.319032 | H42: =ROUND(D42*(E42+F42),2) -> 3158.84
B44: Demanda não utilizada P | D44: 4.14 | E44: =E41 -> 46.912581 | H44: =ROUND(D44*(E44+F44),2) -> 194.22 | J44: =J41 -> 24.450323 | K44: =D44*J44 -> 101.22434
B45: Demanda não utilizada FP | D45: 4.14 | E45: =E42 -> 31.319032 | H45: =ROUND(D45*(E45+F45),2) -> 129.66
B47: Ultrap Demanda P | D47: 0 | E47: =E41*2 -> 93.825161 | H47: =ROUND(D47*(E47+F47),2) -> 0
B48: Ultrap Demanda FP | D48: 0 | E48: =E42*2 -> 62.638065 | H48: =ROUND(D48*(E48+F48),2) -> 0
B50: Energia Comp. P SCEE | D50: =-D33 -> 0 | E50: =E25 -> 0.1237171 | F50: =IF(AND($B$17<$F$2,$E$17<$F$2),D9,IF($B$17<$F$2,K9,H9)) -> 0.055406855 | G50: =E50+F50 -> 0.17912395 | H50: =ROUND(D50*(E50+F50),2) -> 0
B51: Energia Comp. FP SCEE | D51: =-D34 -> -1422.72 | E51: =E26 -> 0.1237171 | F51: =IF(AND($B$17<$F$2,$E$17<$F$2),D10,IF($B$17<$F$2,K10,H10)) -> 0.035130242 | G51: =E51+F51 -> 0.15884734 | H51: =ROUND(D51*(E51+F51),2) -> -226
B53: Des Energ. Comp. P SCEE | D53: =-D50 -> 0 | E53: =E50*F19 -> 0.1237171 | F53: =F50*H19 -> 0.055406855 | G53: =E53+F53 -> 0.17912395 | H53: =ROUND(D53*(E53+F53),2) -> 0
B54: Des Energ. Comp. FP SCEE | D54: =-D51 -> 1422.72 | E54: =E51*F20 -> 0.1237171 | F54: =F51*H20 -> 0.035130242 | G54: =E54+F54 -> 0.15884734 | H54: =ROUND(D54*(E54+F54),2) -> 226
B56: ERE | D56: 27.675 | F56: =IF(AND($B$17<$F$2,$E$17<$F$2),E8,IF($B$17<$F$2,K8,H8)) -> 0.30007032 | H56: =ROUND(D56*(E56+F56),2) -> 8.3
B57: DRE | D57: 0 | E57: =E42 -> 31.319032 | H57: =ROUND(D57*(E57+F57),2) -> 0
D59: Base de Cálculo
B60: PIS | D60: =(SUM(H25:H31)+H41+H42+H47+H48+H56+H57)/(1-E60-E63) -> 14337.416 | E60: 0.008 | H60: =D60*E60 -> 114.69933
B61: PIS Injetado | D61: =(SUM(H33:H39))/(1-E60-E63) -> -609.14992 | E61: =E60 -> 0.008 | H61: =D61*E61 -> -4.8731993
B62: PIS não utilizada | D62: =(H44+H45)/(1-E62-E65) -> 339.07035 | E62: =E60 -> 0.008 | H62: =D62*E62 -> 2.7125628
B63: COFINS | D63: =D60 -> 14337.416 | E63: 0.0368 | H63: =D63*E63 -> 527.61692
B64: COFINS Injetado | D64: =D61 -> -609.14992 | E64: =E63 -> 0.0368 | H64: =D64*E64 -> -22.416717
B65: COFINS não utilizada | D65: =D62 -> 339.07035 | E65: =E63 -> 0.0368 | H65: =D65*E65 -> 12.477789
B66: ICMS | D66: =D60/(1-E66) -> 17273.995 | E66: 0.17 | H66: =D66*E66 -> 2936.5792
B67: ICMS Injetado TE | D67: =((D33*F33)+(D34*F34)+SUM(H36:H39)+(D50*F50)+(D51*F51)+(D53*F53)+(D54*F54))/(1-E61-E64)/(1-E67) -> -511.9027 | E67: =E66 -> 0.17 | H67: =D67*E67 -> -87.023458

Sheet Fatura B1 (GD II) (Baixa Re (2)
B2: B1 Baixa renda | E2: Vigência das Tarifas: | F2: 45145 | I2: GDII | M2: Bandeira | N2: R$/kWh | O2: ANEEL em 29/06 | Q2: TUSD FIO B
M3: VERDE | N3: 0
B4: TARIFA R$ kWh | C4: TARIFA ANTIGA - REH 3091/2022 | F4: TARIFA NOVA - REH XXXX/2023 | I4: Tarifas Proporcionalizadas | M4: BAM | N4: 0.02989 | Q4: TARIFA | R4: =C4 -> TARIFA ANTIGA - REH 3091/2022 | U4: =F4 -> TARIFA NOVA - REH XXXX/2023 | X4: Tarifas Proporcionalizadas
C5: Tusd | D5: TE | E5: TUSD + TE | F5: Tusd | G5: TE | H5: TUSD + TE | I5: Tusd | J5: TE | K5: TUSD + TE | M5: BVM1 | N5: 0.065 | R5: Tusd (R$/kWh) | U5: Tusd (R$/kWh) | X5: Tusd (R$/kWh)
B6: Baixa renda | C6: 0.27266 | D6: 0.27703 | E6: =C6+D6 -> 0.54969 | F6: 0.27266 | G6: 0.27703 | H6: =F6+G6 -> 0.54969 | I6: =((C6*$C$13)+(F6*$D$13))/($D$13+$C$13) -> 0.27266 | J6: =((D6*$C$13)+(G6*$D$13))/($D$13+$C$13) -> 0.27703 | K6: =I6+J6 -> 0.54969 | M6: BVM2 | N6: 0.09795 | Q6: =B6 -> Baixa renda | R6: ='[2]FIO B'!H11/1000 -> 0.19205 | U6: ='[2]FIO B'!K11/1000 -> 0.17652 | X6: =((R6*$C$13)+(U6*$D$13))/($D$13+$C$13) -> 0.18503645
B7: TE SCEE | G7: =G6*15% -> 0.0415545 | J7: =((D7*$C$13)+(G7*$D$13))/($D$13+$C$13) -> 0.018766548 | M7: Escassez Hídrica | N7: 0.142
H9: Fatura | L9: Vigência das Tarifas (troca Bandeira): | M9: =EOMONTH(B13,0)+1 -> 45139
B10: INSTALAÇÃO | C10: 1182321 | H10: =E13 -> 45158 | K10: Altere a bandeira na célula abaixo
K11: VERDE | L11: VERDE
B12: Leitura Anterior | C12: Nº de dias tarifa Anterior | D12: Nº de dias tarifa Nova | E12: Leitura Atual | J12: Leitura Anterior | K12: Nº de dias tarifa Anterior | L12: Nº de dias tarifa Nova | M12: Leitura Atual
B13: 45127 | C13: =IF((F2-B13-1)<0,0,(F2-B13-1)) -> 17 | D13: =E13-F2+1 -> 14 | E13: 45158 | J13: =B13 -> 45127 | K13: =IF((M9-J13-1)<0,0,(M9-J13-1)) -> 11 | L13: =M13-M9+1 -> 20 | M13: =E13 -> 45158
B15: Regra do custo de disponibilidade
A16: monofásico | B16: Cliente | D16: trifásico | G16: =IF(D16="monofásico",30,IF(D16="bifásico",50,100)) -> 100 | H16: kWh
A17: bifásico | B17: TUSD = | G17: =I6 -> 0.27266 | H17: R$/kWh
A18: trifásico | B18: TE = | G18: =J6 -> 0.27703 | H18: R$/kWh | J18: bandeira proporcional
B19: Adicional de Bandeira Amarela | G19: =(IF($K$11=M4,(G16*(K13)/(K13+L13)),0)+IF($L$11=M4,(G16*(L13)/(K13+L13)),0))*N4 -> 0 | H19: R$ | I19: =IF(OR($K$11=M4,$L$11=M4),N4,0) -> 0 | J19: =(IF($K$11=M4,(N4*(K13)/(K13+L13)),0)+IF($L$11=M4,(N4*(L13)/(K13+L13)),0)) -> 0
B20: Adicional de bandeira Vermelha 1 | G20: =(IF($K$11=M5,(G16*(K13)/(K13+L13)),0)+IF($L$11=M5,(G16*(L13)/(K13+L13)),0))*N5 -> 0 | H20: R$ | I20: =IF(OR($K$11=M5,$L$11=M5),N5,0) -> 0 | J20: =(IF($K$11=M5,(N5*(K13)/(K13+L13)),0)+IF($L$11=M5,(N5*(L13)/(K13+L13)),0)) -> 0
B21: Adicional de bandeira Vermelha 2 | G21: =(IF($K$11=M6,(G16*(K13)/(K13+L13)),0)+IF($L$11=M6,(G16*(L13)/(K13+L13)),0))*N6 -> 0 | H21: R$ | I21: =IF(OR($K$11=M6,$L$11=M6),N6,0) -> 0 | J21: =(IF($K$11=M6,(N6*(K13)/(K13+L13)),0)+IF($L$11=M6,(N6*(L13)/(K13+L13)),0)) -> 0
B22: Custo de disponibilidade | G22: =G16*(G17+G18)+G19+G20+G21 -> 54.969 | H22: R$
B24: Consumo = | G24: 1000 | H24: kWh
B25: Energia Injetada = | G25: 600 | H25: kWh | I25: =G25+D53 -> 570
G26: =-IF(G24<G16,0,IF(G25<(((G24*(E46+F46))+H48+H49+H50+H51)-((G16*(G17+G18)+G19+G20+G21)))/(E71+F56+J19+J20+J21),-G25,-(((G24*(E46+F46))+H48+H49+H50+H51)-((G16*(G17+G18)+G19+G20+G21)))/(E71+F56+J19+J20+J21))) -> 600 | H26: =G24-G26 -> 400
B27: Perc. de Redução da Energia Injetada | E27: TUSD | F27: 1 | G27: TE | H27: 1 | K27: =M101+M107 -> 72.880698
B29: Fatura B1 Baixa Renda
D30: Qtde | E30: TUSD | F30: TE | G30: TUSD + TE | H30: R$
B31: Fornecimento de Energia Elétrica | H31: =SUM(H33:H71)+SUM(H76:H81) -> 25.154358
A33: 0.65 | B33: Consumo 0 - 30 | D33: =IF(H26>0,30,0) -> 30 | E33: =$E$46*(1-A33) -> 0.095431 | F33: =$F$46*(1-A33) -> 0.0969605 | G33: =E33+F33 -> 0.1923915 | H33: =ROUND((D33*E33),2)+ROUND((D33*F33),2) -> 5.77
A34: 0.4 | B34: Consumo 31 - 100 | D34: 20 | E34: =$E$46*(1-A34) -> 0.163596 | F34: =$F$46*(1-A34) -> 0.166218 | G34: =E34+F34 -> 0.329814 | H34: =ROUND((D34*E34),2)+ROUND((D34*F34),2) -> 6.59
A35: 0.1 | B35: Consumo 101 - 220 | E35: =$E$46*(1-A35) -> 0.245394 | F35: =$F$46*(1-A35) -> 0.249327 | G35: =E35+F35 -> 0.494721 | H35: =ROUND((D35*E35),2)+ROUND((D35*F35),2) -> 0
A36: 0 | B36: Consumo > 220 | E36: =$E$46*(1-A36) -> 0.27266 | F36: =$F$46*(1-A36) -> 0.27703 | G36: =E36+F36 -> 0.54969 | H36: =ROUND((D36*E36),2)+ROUND((D36*F36),2) -> 0
B38: Adicional BAM | H38: =O124 -> 0
B39: Adicional BVM 1 | H39: =O133 -> 0
B40: Adicional BVM 2 | H40: =O142 -> 0
B41: Adicional Escassez Hídrica | H41: =O151 -> 0
A43: 0.65 | B43: Energia Fornecida 0 - 30 | D43: 30 | E43: =$E$46*(1-A43) -> 0.095431 | F43: =$F$46*(1-A43) -> 0.0969605 | G43: =E43+F43 -> 0.1923915 | H43: =ROUND((D43*E43),2)+ROUND((D43*F43),2) -> 5.77
A44: 0.4 | B44: Energia Fornecida 31 - 100 | D44: 70 | E44: =$E$46*(1-A44) -> 0.163596 | F44: =$F$46*(1-A44) -> 0.166218 | G44: =E44+F44 -> 0.329814 | H44: =ROUND((D44*E44),2)+ROUND((D44*F44),2) -> 23.09
A45: 0.1 | B45: Energia Fornecida 101 - 220 | D45: 120 | E45: =$E$46*(1-A45) -> 0.245394 | F45: =$F$46*(1-A45) -> 0.249327 | G45: =E45+F45 -> 0.494721 | H45: =ROUND((D45*E45),2)+ROUND((D45*F45),2) -> 59.37
A46: 0 | B46: Energia Fornecida > 220 | D46: 9 | E46: =IF(AND($B$13<$F$2,$E$13<$F$2),C6,IF($B$13<$F$2,I6,F6)) -> 0.27266 | F46: =IF(AND($B$13<$F$2,$E$13<$F$2),D6,IF($B$13<$F$2,J6,G6)) -> 0.27703 | G46: =E46+F46 -> 0.54969 | H46: =ROUND((D46*E46),2)+ROUND((D46*F46),2) -> 4.94
B48: Adicional BAM | H48: =O161 -> 0
B49: Adicional BVM 1 | H49: =O170 -> 0
B50: Adicional BVM 2 | H50: =O179 -> 0
B51: Adicional Escassez Hídrica | H51: =O188 -> 0
A53: 0.65 | B53: Energia Inejtada 0 - 30 | D53: -30 | E53: =E43 -> 0.095431 | F53: =F43 -> 0.0969605 | G53: =E53+F53 -> 0.1923915 | H53: =ROUND((D53*E53),2)+ROUND((D53*F53),2) -> -5.77
A54: 0.4 | B54: Energia Injetada 31 - 100 | D54: -70 | E54: =E44 -> 0.163596 | F54: =F44 -> 0.166218 | G54: =E54+F54 -> 0.329814 | H54: =ROUND((D54*E54),2)+ROUND((D54*F54),2) -> -23.09
A55: 0.1 | B55: Energia Injetada 101 - 220 | D55: -120 | E55: =E45 -> 0.245394 | F55: =F45 -> 0.249327 | G55: =E55+F55 -> 0.494721 | H55: =ROUND((D55*E55),2)+ROUND((D55*F55),2) -> -59.37
A56: 0 | B56: Energia Injetada > 220 | D56: -9 | E56: =E46 -> 0.27266 | F56: =F46 -> 0.27703 | G56: =E56+F56 -> 0.54969 | H56: =ROUND((D56*E56),2)+ROUND((D56*F56),2) -> -4.94
B58: Adicional BAM | H58: =O200 -> 0
B59: Adicional BVM 1 | H59: =O209 -> 0
B60: Adicional BVM 2 | H60: =O218 -> 0
B61: Adicional Escassez Hídrica | H61: =O227 -> 0
A63: 0.65 | B63: Energia Compensada SCEE 0 - 30 | D63: =-D53 -> 30 | E63: =$E$66*(1-A63) -> 0.095431 | F63: =$F$66*(1-A63) -> 0.0065682919 | G63: =E63+F63 -> 0.10199929 | H63: =ROUND(D63*(E63+F63),2) -> 3.06
A64: 0.4 | B64: Energia Compensada SCEE 31 - 100 | D64: =-D54 -> 70 | E64: =$E$66*(1-A64) -> 0.163596 | F64: =$F$66*(1-A64) -> 0.011259929 | G64: =E64+F64 -> 0.17485593 | H64: =ROUND(D64*(E64+F64),2) -> 12.24
A65: 0.1 | B65: Energia Compensada SCEE 101 - 220 | D65: =-D55 -> 120 | E65: =$E$66*(1-A65) -> 0.245394 | F65: =$F$66*(1-A65) -> 0.016889894 | G65: =E65+F65 -> 0.26228389 | H65: =ROUND(D65*(E65+F65),2) -> 31.47
A66: 0 | B66: Energia Compensada SCEE > 220 | D66: =-D56 -> 9 | E66: =E46 -> 0.27266 | F66: =IF(AND($B$13<$F$2,$E$13<$F$2),D7,IF($B$13<$F$2,J7,G7)) -> 0.018766548 | G66: =E66+F66 -> 0.29142655 | H66: =ROUND(D66*(E66+F66),2) -> 2.62
B68: Des Energ. Comp. SCEE 0 - 30 | D68: =-D63 -> -30 | E68: =E63*$F$27 -> 0.095431 | F68: =F63*$H$27 -> 0.0065682919 | G68: =E68+F68 -> 0.10199929 | H68: =ROUND(D68*(E68+F68),2) -> -3.06
B69: Des Energ. Comp. SCEE 31 - 100 | D69: =-D64 -> -70 | E69: =E64*$F$27 -> 0.163596 | F69: =F64*$H$27 -> 0.011259929 | G69: =E69+F69 -> 0.17485593 | H69: =ROUND(D69*(E69+F69),2) -> -12.24
B70: Des Energ. Comp. SCEE 101 - 220 | D70: =-D65 -> -120 | E70: =E65*$F$27 -> 0.245394 | F70: =F65*$H$27 -> 0.016889894 | G70: =E70+F70 -> 0.26228389 | H70: =ROUND(D70*(E70+F70),2) -> -31.47
B71: Des Energ. Comp. SCEE > 220 | D71: =-D66 -> -9 | E71: =E66*$F$27 -> 0.27266 | F71: =F66*$H$27 -> 0.018766548 | G71: =E71+F71 -> 0.29142655 | H71: =ROUND(D71*(E71+F71),2) -> -2.62 | I71: =SUM(H63:H71) -> -9.7699626e-15
H73: =SUM(H33:H72) -> 12.36 | J73: =231.75-'Fatura B1 (GD II) (Baixa Re (2)'!H73 -> 219.39
D75: Base de Cálculo
B76: PIS | D76: =SUM(H33:H51)/(1-E76-E78) -> 108.98482 | E76: 0.0056 | H76: =D76*E76 -> 0.61031499
B77: PIS Eneg Inj | D77: =SUM(H53:H71)/(1-E76-E78) -> -96.22018 | E77: =E76 -> 0.0056 | H77: =D77*E77 -> -0.53883301
B78: COFINS | D78: =D76 -> 108.98482 | E78: 0.0261 | H78: =D78*E78 -> 2.8445038
B79: COFINS Eneg Inj | D79: =D77 -> -96.22018 | E79: =E78 -> 0.0261 | H79: =D79*E79 -> -2.5113467
B80: ICMS | D80: =D76/(1-E80) -> 131.30701 | E80: 0.17 | H80: =D80*E80 -> 22.322192
B81: ICMS Eneg Inj | D81: =((D53*F53)+(D54*F54)+(D55*F55)+(D56*F56)+(D64*F64)+(D65*F65)+(D66*F66)+(D69*F69)+(D70*F70)+(D71*F71)+(H58+H59+H60+H61)+(D63*F63)+(D68*F68))/(1-E77-E79)/(1-E81) -> -58.426313 | E81: =E80 -> 0.17 | H81: =D81*E81 -> -9.9324732
B82: ICMS Desc Tarifa Social | D82: =K114 -> 39.007906 | E82: =E81 -> 0.17 | H82: =D82*E82 -> 6.631344
B85: Benefício Tarifa Social | H85: =K113 -> 15.1245 | I85: (mensagem na fatura)
F87: Memória benefício Tarifa Social
I88: TUSD X | J88: TE | M88: Com tributos e bandeiras (base ICMS)
F89: Consumo | G89: B1 Baixa Renda | H89: =SUM(D33:D36,D43:D46) -> 279 | I89: =E36 -> 0.27266 | J89: =F36 -> 0.27703 | K89: =H89*(I89+J89) -> 153.36351 | M89: =SUM(K89:K93)/(1-E76-E78)/(1-E80) -> 190.82445
G90: BAM | H90: =IF($K$11=$B$154,(H89*($K$13)/($K$13+$L$13)),0)+IF($L$11=$B$154,(H89*($L$13)/($K$13+$L$13)),0) -> 0 | J90: =N4 -> 0.02989 | K90: =H90*(I90+J90) -> 0
G91: BVM1 | H91: =IF($K$11=$B$163,(H90*($K$13)/($K$13+$L$13)),0)+IF($L$11=$B$163,(H90*($L$13)/($K$13+$L$13)),0) -> 0 | J91: =N5 -> 0.065 | K91: =H91*(I91+J91) -> 0
G92: BVM2 | H92: =IF($K$11=$B$172,(H91*($K$13)/($K$13+$L$13)),0)+IF($L$11=$B$172,(H91*($L$13)/($K$13+$L$13)),0) -> 0 | J92: =N6 -> 0.09795 | K92: =H92*(I92+J92) -> 0
G93: Escassez Hídrica | H93: =IF($K$11=$B$181,(H92*($K$13)/($K$13+$L$13)),0)+IF($L$11=$B$181,(H92*($L$13)/($K$13+$L$13)),0) -> 0 | J93: =N7 -> 0.142 | K93: =H93*(I93+J93) -> 0
F95: Injetada | G95: B1 Baixa Renda | H95: =SUM(D53:D56) -> -229 | I95: =E71 -> 0.27266 | J95: =J89 -> 0.27703 | K95: =H95*(I95+J95) -> -125.87901 | M95: =((H95*J95)+(K96+K97+K98+K99))/(1-E77-E79)/(1-E81) -> -78.935845
G96: BAM | H96: =IF($K$11=$B$154,(H95*($K$13)/($K$13+$L$13)),0)+IF($L$11=$B$154,(H95*($L$13)/($K$13+$L$13)),0) -> 0 | J96: =J90 -> 0.02989 | K96: =H96*(I96+J96) -> 0
G97: BVM1 | H97: =IF($K$11=$B$163,(H96*($K$13)/($K$13+$L$13)),0)+IF($L$11=$B$163,(H96*($L$13)/($K$13+$L$13)),0) -> 0 | J97: =J91 -> 0.065 | K97: =H97*(I97+J97) -> 0
G98: BVM2 | H98: =IF($K$11=$B$172,(H97*($K$13)/($K$13+$L$13)),0)+IF($L$11=$B$172,(H97*($L$13)/($K$13+$L$13)),0) -> 0 | J98: =J92 -> 0.09795 | K98: =H98*(I98+J98) -> 0
G99: Escassez Hídrica | H99: =IF($K$11=$B$181,(H98*($K$13)/($K$13+$L$13)),0)+IF($L$11=$B$181,(H98*($L$13)/($K$13+$L$13)),0) -> 0 | J99: =J93 -> 0.142 | K99: =H99*(I99+J99) -> 0
F101: Bx Renda Consumo | G101: Baixa Renda | K101: =SUM(H33:H36,H43:H46) -> 105.53 | M101: =SUM(K101:K105)/(1-E76-E78)/(1-E80) -> 131.30701
G102: BAM | K102: =H38+H48 -> 0
G103: BVM1 | K103: =H39+H49 -> 0
G104: BVM2 | K104: =H40+H50 -> 0
G105: Escassez Hídrica | K105: =H41+H51 -> 0
F107: Bx Renda Injetada | G107: Baixa Renda | K107: =SUM(H53:H56,H63:H66,H68:H71) -> -93.17 | M107: =D81 -> -58.426313
G108: BAM | K108: =H58 -> 0
G109: BVM1 | K109: =H59 -> 0
G110: BVM2 | K110: =H60 -> 0
G111: Escassez Hídrica | K111: =H61 -> 0
J113: Benefício Tarifa Social | K113: =(K89+K95)-(K101+K107) -> 15.1245 | L113: sem considerar as bandeiras
J114: Com tributos | K114: =(M89+M95)-(M101+M107) -> 39.007906 | L114: considerando as bandeiras no cálculo dos tributos
B116: Consumo - Adicional de Bandeira
B117: BAM | K117: =N4 -> 0.02989
C118: Consumo | J118: Tarifas | M118: Receita | O118: Receita Total
C119: KWh | K119: TE | M119: Tusd | N119: TE | O119: Tusd+TE
C120: =IF($K$11=$B$117,(D33*($K$13)/($K$13+$L$13)),0)+IF($L$11=$B$117,(D33*($L$13)/($K$13+$L$13)),0) -> 0 | K120: =$K$154*(1-Q120) -> 0.0104615 | N120: =ROUND((C120*K120),2) -> 0 | O120: =M120+N120 -> 0 | Q120: 0.65
C121: =IF($K$11=$B$117,(D34*($K$13)/($K$13+$L$13)),0)+IF($L$11=$B$117,(D34*($L$13)/($K$13+$L$13)),0) -> 0 | K121: =$K$154*(1-Q121) -> 0.017934 | N121: =ROUND((C121*K121),2) -> 0 | O121: =M121+N121 -> 0 | Q121: 0.4
C122: =IF($K$11=$B$117,(D35*($K$13)/($K$13+$L$13)),0)+IF($L$11=$B$117,(D35*($L$13)/($K$13+$L$13)),0) -> 0 | K122: =$K$154*(1-Q122) -> 0.026901 | N122: =ROUND((C122*K122),2) -> 0 | O122: =M122+N122 -> 0 | Q122: 0.1
C123: =IF($K$11=$B$117,(D36*($K$13)/($K$13+$L$13)),0)+IF($L$11=$B$117,(D36*($L$13)/($K$13+$L$13)),0) -> 0 | K123: =$K$154*(1-Q123) -> 0.02989 | N123: =ROUND((C123*K123),2) -> 0 | O123: =M123+N123 -> 0 | Q123: 0
...
